Workbook

Sheet Capex Summary
A1: BSNL - annual capital expenditure, FY2019-20 to FY2023-24
A2: Standalone figures extracted from Bharat Sanchar Nigam Limited's annual reports. All amounts in INR crore (source figures are in INR lakh; 100 lakh = 1 crore).
A3: Green = converted from the 'Source Data (INR lakh)' sheet. Black = calculated. Every figure traces to a printed line item; see 'Notes & Sources'.
A5: INR crore | B5: FY2019-20 | C5: FY2020-21 | D5: FY2021-22 | E5: FY2022-23 | F5: FY2023-24
A6: A. Cash capex (Statement of Cash Flows - investing activities)
A7: Acquisition of property, plant and equipment (and CWIP) | B7: ='Source Data (INR lakh)'!B5/100 -> 7198.88 | C7: ='Source Data (INR lakh)'!C5/100 -> 815.33 | D7: ='Source Data (INR lakh)'!D5/100 -> 3985.52 | E7: ='Source Data (INR lakh)'!E5/100 -> 2197.89 | F7: ='Source Data (INR lakh)'!F5/100 -> 11124.84
A8: Acquisition of intangible assets (spectrum, software) | B8: =N('Source Data (INR lakh)'!B6)/100 -> 0 | C8: =N('Source Data (INR lakh)'!C6)/100 -> 0 | D8: =N('Source Data (INR lakh)'!D6)/100 -> 0 | E8: =N('Source Data (INR lakh)'!E6)/100 -> 19964.11 | F8: =N('Source Data (INR lakh)'!F6)/100 -> 10320.59
A9: Total cash capex | B9: =SUM(B7:B8) -> 7198.88 | C9: =SUM(C7:C8) -> 815.33 | D9: =SUM(D7:D8) -> 3985.52 | E9: =SUM(E7:E8) -> 22162 | F9: =SUM(F7:F8) -> 21445.43
A11: B. Accrual capex (additions to gross block per the asset notes)
A12: Additions to property, plant and equipment | B12: ='Source Data (INR lakh)'!B7/100 -> 5567.87 | C12: ='Source Data (INR lakh)'!C7/100 -> 1991.41 | D12: ='Source Data (INR lakh)'!D7/100 -> 1219.23 | E12: ='Source Data (INR lakh)'!E7/100 -> 1159.79 | F12: ='Source Data (INR lakh)'!F7/100 -> 1817.07
A13: Additions to capital work-in-progress (net of provisions) | B13: ='Source Data (INR lakh)'!B8/100 -> 8275.58 | C13: ='Source Data (INR lakh)'!C8/100 -> 3493.36 | D13: ='Source Data (INR lakh)'!D8/100 -> 2572.37 | E13: ='Source Data (INR lakh)'!E8/100 -> 2088.36 | F13: ='Source Data (INR lakh)'!F8/100 -> 9413.1
A14: Additions to intangible assets | B14: ='Source Data (INR lakh)'!B9/100 -> 25.84 | C14: ='Source Data (INR lakh)'!C9/100 -> 26.1 | D14: ='Source Data (INR lakh)'!D9/100 -> 6 | E14: ='Source Data (INR lakh)'!E9/100 -> 19964.11 | F14: ='Source Data (INR lakh)'!F9/100 -> 10329.71
A15: of which: spectrum capitalised | B15: =N('Source Data (INR lakh)'!B10)/100 -> 0 | C15: =N('Source Data (INR lakh)'!C10)/100 -> 0 | D15: =N('Source Data (INR lakh)'!D10)/100 -> 0 | E15: =N('Source Data (INR lakh)'!E10)/100 -> 19808 | F15: =N('Source Data (INR lakh)'!F10)/100 -> 10253.31
A16: Memo: total additions (PPE + CWIP + intangibles) | B16: =B12+B13+B14 -> 13869.29 | C16: =C12+C13+C14 -> 5510.87 | D16: =D12+D13+D14 -> 3797.6 | E16: =E12+E13+E14 -> 23212.26 | F16: =F12+F13+F14 -> 21559.88
A17: Not a clean total - assets transferred out of CWIP into PPE during the year appear in both the PPE and the CWIP additions columns.
A19: C. Context
A20: Revenue from operations | B20: ='Source Data (INR lakh)'!B11/100 -> 17886.09 | C20: ='Source Data (INR lakh)'!C11/100 -> 17451.8 | D20: ='Source Data (INR lakh)'!D11/100 -> 16809.22 | E20: ='Source Data (INR lakh)'!E11/100 -> 19127.79 | F20: ='Source Data (INR lakh)'!F11/100 -> 19330.71
A21: Total cash capex as % of revenue | B21: =IF(B20=0,"",B9/B20) -> 0.40248484 | C21: =IF(C20=0,"",C9/C20) -> 0.046718963 | D21: =IF(D20=0,"",D9/D20) -> 0.23710321 | E21: =IF(E20=0,"",E9/E20) -> 1.1586284 | F21: =IF(F20=0,"",F9/F20) -> 1.1093969
A24: FY2024-25 (25th Annual Report) - not included above
A25: BSNL's FY2024-25 annual report is not published on bsnl.co.in in a form reachable from this environment and has no Internet Archive capture, so no FY25 figure is extracted here. For reference only, PIB press release PRID 2131702 (27 May 2025) reports FY25 capex of INR 26,022 crore, comprising INR 15,324 crore of equipment/towers and INR 10,698 crore of spectrum. That is a government press figure, not an audited annual-report line item, and is not comparable to the rows above.

Sheet Source Data (INR lakh)
A1: BSNL - capex source figures as printed in the annual reports
A2: Standalone financial statements. All amounts in INR lakh, exactly as printed. Blue = hardcoded from the report; blank = not disclosed as a separate line.
A4: Line item (as printed) | B4: FY2019-20 | C4: FY2020-21 | D4: FY2021-22 | E4: FY2022-23 | F4: FY2023-24 | G4: Where in the report
A5: Cash flow: acquisition of property, plant and equipment (and CWIP) | B5: 719888 | C5: 81533 | D5: 398552 | E5: 219789 | F5: 1112484 | G5: Standalone Statement of Cash Flows, 'B. Cash flows from investing activities'. FY20-FY22 line reads 'Acquisition of property, plant and equipment'; FY23-FY24 line reads 'Acquisition of property, plant and equipment and CWIP'.
A6: Cash flow: acquisition of intangible assets | E6: 1996411 | F6: 1032059 | G6: Standalone Statement of Cash Flows, investing activities. No separate intangibles line was presented in the FY20, FY21 and FY22 cash flow statements.
A7: Note 3(i) PPE: additions to gross block | B7: 556787 | C7: 199141 | D7: 121923 | E7: 115979 | F7: 181707 | G7: Note 3(i) Tangible assets, 'Additions' column of the gross block table (Total row). FY23 figure taken from the comparative column of the 24th AR.
A8: Note 3(ii) CWIP: additions (net of provisions) | B8: 827558 | C8: 349336 | D8: 257237 | E8: 208836 | F8: 941310 | G8: Note 3(ii) Capital work-in-progress, 'Additions' column, Total row (CWIP + CWIP in store, less movements in the related provisions).
A9: Note 4 Intangible assets: additions to gross block | B9: 2584 | C9: 2610 | D9: 600 | E9: 1996411 | F9: 1032971 | G9: Note 4 Intangible assets, 'Additions' column of the gross block table (Total row). FY23/FY24 additions are dominated by spectrum capitalised under 'Entry license fees'.
A10: of which: spectrum capitalised | E10: 1980800 | F10: 1025331 | G10: Note 4 Intangible assets, 'Entry license fees' row and notes (a)-(c) thereunder. FY23: 900/1800 MHz allotment INR 19,80,800 lakh. FY24: 700 MHz INR 8,20,918 lakh + 2100 MHz INR 1,49,182 lakh + spectrum fee INR 55,230 lakh.
A11: Revenue from operations (for capex intensity) | B11: 1788609 | C11: 1745180 | D11: 1680922 | E11: 1912779 | F11: 1933071 | G11: Standalone Statement of Profit and Loss, 'Revenue from operations'. FY23 figure taken from the comparative column of the 24th AR.
A13: Annual report used for each column | B13: 20th AR | C13: 21st AR | D13: 22nd AR | E13: 23rd AR (via 24th AR) | F13: 24th AR

Sheet Notes & Sources
A1: Notes, sources and caveats
A3: Reports used
A4: Financial year | B4: Report | C4: Source URL | D4: Pages
A5: FY2019-20 | B5: 20th Annual Report | C5: https://tender.bsnl.co.in/bsnltenders/pdf/BSNL _Annual Report 2019-20.pdf | D5: 480
A6: FY2020-21 | B6: 21st Annual Report | C6: https://bsnl.co.in/opencms/export/finresult/21ST_ENGLISH_BSNL_ANNUAL_REPORT.pdf | D6: 480
A7: FY2021-22 | B7: 22nd Annual Report | C7: https://bsnl.co.in/opencms/export/sites/default/BSNL/investors/pdf/BSNL_AR_2021-22.pdf | D7: 516
A8: FY2022-23 | B8: 23rd Annual Report | C8: https://bsnl.co.in/opencms/export/sites/default/BSNL/investors/pdf/Annual_Report_2022-23.pdf | D8: 544
A9: FY2023-24 | B9: 24th Annual Report | C9: https://bsnl.co.in/opencms/export/sites/default/BSNL/investors/pdf/Annual_Report_2023_24.pdf | D9: 556
A11: Which number is 'capex'
A12: BSNL does not print a single 'capital expenditure' total in its financial statements. Two defensible measures are given: (A) cash actually paid for fixed assets, from the investing section of the cash flow statement, and (B) accrual additions to the gross block of PPE, CWIP and intangibles from the asset notes. They differ because of creditor timing, non-cash additions and spectrum allotted against equity infusion.
A16: Spectrum dominates FY2022-23 and FY2023-24
A17: The step-up in FY23 and FY24 is spectrum administratively allotted by DoT under the BSNL revival packages and capitalised under 'Entry license fees': INR 19,808 crore in FY23 (900/1800 MHz) and INR 10,253 crore in FY24 (700 MHz INR 8,209 crore, 2100 MHz INR 1,492 crore, regularisation fee INR 552 crore). Excluding spectrum, capex is far smaller and much flatter across all five years.
A21: FY2020-21 cash capex looks anomalously low
A22: The FY21 cash flow statement shows only INR 815 crore of PPE acquisition against INR 1,991 crore of gross-block additions and INR 3,493 crore of CWIP additions. This is a cash-timing effect (capital creditors), not an error in extraction - the FY22 report reprints the same INR 81,533 lakh comparative.
A26: Segment note 'Capital expenditure during the year' is unreliable in the 24th AR
A27: In the 20th to 22nd annual reports this segment row exactly equals additions to the PPE gross block (FY20 5,56,787 lakh; FY21 1,99,141 lakh; FY22 1,21,923 lakh). In the 24th AR the FY23 row (5,65,863 lakh) instead reproduces that year's depreciation and amortisation figures line for line, and the FY24 row totals 2,63,71,771 lakh - larger than the company's entire segment asset base. Both are misprints, so this row is not used and the asset notes are used instead.
A31: FY2022-23 figures were read from the 24th Annual Report
A32: The 23rd Annual Report PDF stores its financial statements with subset fonts that carry no Unicode mapping, so the numbers cannot be reliably read from that file by text extraction. The FY23 column therefore uses the comparative (prior-year) columns printed in the 24th Annual Report, which are the same audited figures.
A36: Standalone, not consolidated
A37: All figures are standalone. The 24th AR's consolidated cash flow shows a marginally different PPE/CWIP acquisition (INR 11,124.84 crore standalone vs the same figure consolidated for FY24; FY23 219,789 lakh standalone vs 222,862 lakh consolidated).
... A42: bsnl.co.in refuses connections from this environment, so the report PDFs were retrieved from Internet Archive captures of the URLs listed above. Page counts were checked against the originals (480/480/516/544/556 pages).
