Workbook
Name \a: #REF!
Name \a: #REF!
Name \a: #REF!
Name \a: #REF!
Name \a: #REF!
Name \a: #REF!
Name \a: #REF!
Name \a: #REF!
Name \a: #REF!
Name \a: #REF!
Name \a: #REF!
Name \a: #REF!
Name \a: #REF!
Name \a: #REF!
Name \a: #REF!
Name \a: #REF!
Name \a: #REF!
Name \a: #REF!
Name \a: #REF!
Name \b: #REF!
Name \b: #REF!
Name \b: #REF!
Name \b: #REF!
Name \b: #REF!
Name \b: #REF!
Name \b: #REF!
Name \b: #REF!
Name \b: #REF!
Name \b: #REF!
Name \b: #REF!
Name \b: #REF!
Name \b: #REF!
Name \b: #REF!
Name \b: #REF!
Name \b: #REF!
Name \b: #REF!
Name \b: #REF!
Name \b: #REF!
Name \c: #REF!
Name \c: #REF!
Name \c: #REF!
Name \c: #REF!
Name \c: #REF!
Name \c: #REF!
Name \c: #REF!
Name \c: #REF!
Name \c: #REF!
Name \c: #REF!
Name \c: #REF!
Name \c: #REF!
Name \c: #REF!
Name \c: #REF!
Name \c: #REF!
Name \c: #REF!
Name \c: #REF!
Name \c: #REF!
Name \c: #REF!
Name \d: #REF!
Name \d: #REF!
Name \d: #REF!

Sheet Equibase
C1: Input | D1: =IF(SUM(B3:B5023)=0,"✓","×") -> ✓ | E1: 7 | H1: 37316 | I1: 37681 | J1: 38047 | K1: 38412 | L1: 38777 | M1: 39142 | N1: 39508 | O1: 39873 | P1: 40238 | Q1: 40603 | R1: 40969 | S1: 41334 | T1: 41699 | U1: 42064 | V1: 42430 | W1: 42795 | X1: 43160 | Y1: 43525 | Z1: 43891 | AA1: 44256 | AB1: 44621 | AC1: 44986 | AD1: 45352 | AE1: 45717 | AF1: 46082 | AG1: 46447 | AH1: 46813 | AI1: 47178 | AJ1: 47543
A2: Item Codes | C2: Calculated | E2: Actual/Estimate | F2: UNITS | H2: =IF(H1<=$G$21,"A","E") -> A | I2: =IF(I1<=$G$21,"A","E") -> A | J2: =IF(J1<=$G$21,"A","E") -> A | K2: =IF(K1<=$G$21,"A","E") -> A | L2: =IF(L1<=$G$21,"A","E") -> A | M2: =IF(M1<=$G$21,"A","E") -> A | N2: =IF(N1<=$G$21,"A","E") -> A | O2: =IF(O1<=$G$21,"A","E") -> A | ... AE2: =IF(AE1<=$G$21,"A","E") -> A | AF2: A | AG2: =IF(AG1<=$G$21,"A","E") -> E | AH2: =IF(AH1<=$G$21,"A","E") -> E | AI2: =IF(AI1<=$G$21,"A","E") -> E | AJ2: =IF(AJ1<=$G$21,"A","E") -> E
C3: Input | E3: Months | H3: 12 | I3: 12 | J3: 12 | K3: 12 | L3: 12 | M3: 12 | N3: 12 | O3: 12 | P3: 12 | Q3: 12 | R3: 12 | S3: 12 | T3: 12 | U3: 12 | V3: 12 | W3: 12 | X3: 12 | Y3: 12 | Z3: 12 | AA3: 12 | AB3: 12 | AC3: 12 | AD3: 12 | AE3: 12 | AF3: 12 | AG3: 12 | AH3: 12 | AI3: 12 | AJ3: 12
C4: Input | E4: Period Type | H4: Annual | I4: Annual | J4: Annual | K4: Annual | L4: Annual | M4: Annual | N4: Annual | O4: Annual | P4: Annual | Q4: Annual | R4: Annual | S4: Annual | T4: Annual | U4: Annual | V4: Annual | W4: Annual | X4: Annual | Y4: Annual | Z4: Annual | AA4: Annual | AB4: Annual | AC4: Annual | AD4: Annual | AE4: Annual | AF4: Annual | AG4: Annual | AH4: Annual | AI4: Annual | AJ4: Annual
C5: Input | E5: Year End | H5: =H1 -> 37316 | I5: =I1 -> 37681 | J5: =J1 -> 38047 | K5: =K1 -> 38412 | L5: =L1 -> 38777 | M5: =M1 -> 39142 | N5: =N1 -> 39508 | O5: =O1 -> 39873 | ... AJ5: =AJ1 -> 47543
C6: Calculated | E6: Year Label | H6: =IF(MONTH(H1)=12,"CY"&TEXT(H1,"YY"),"FY"&TEXT(H1,"YY"))&H2 -> FY02A | I6: =IF(MONTH(I1)=12,"CY"&TEXT(I1,"YY"),"FY"&TEXT(I1,"YY"))&I2 -> FY03A | J6: =IF(MONTH(J1)=12,"CY"&TEXT(J1,"YY"),"FY"&TEXT(J1,"YY"))&J2 -> FY04A | K6: =IF(MONTH(K1)=12,"CY"&TEXT(K1,"YY"),"FY"&TEXT(K1,"YY"))&K2 -> FY05A | L6: =IF(MONTH(L1)=12,"CY"&TEXT(L1,"YY"),"FY"&TEXT(L1,"YY"))&L2 -> FY06A | M6: =IF(MONTH(M1)=12,"CY"&TEXT(M1,"YY"),"FY"&TEXT(M1,"YY"))&M2 -> FY07A | N6: =IF(MONTH(N1)=12,"CY"&TEXT(N1,"YY"),"FY"&TEXT(N1,"YY"))&N2 -> FY08A | O6: =IF(MONTH(O1)=12,"CY"&TEXT(O1,"YY"),"FY"&TEXT(O1,"YY"))&O2 -> FY09A | ... AJ6: =IF(MONTH(AJ1)=12,"CY"&TEXT(AJ1,"YY"),"FY"&TEXT(AJ1,"YY"))&AJ2 -> FY30E
A7: EQ_COMPANY_NAME | C7: Calculated | E7: Full Name Of Company | G7: JSW Infrastructure | H7: <-- Use EQUIDATA
A8: COMPANY_SHORT_NAME | C8: Calculated | E8: Short Name For Company | G8: JSW Infra | H8: <-- Use EQUIDATA
A9: EQ_SECTOR_NAME | C9: Calculated | E9: Sector | G9: Infrastructure | H9: <-- Use EQUIDATA
A10: EQ_INDUSTRY_NAME | C10: Calculated | E10: Industry | H10: <-- Use EQUIDATA
A11: EQ_SUBINDUSTRY_NAME | C11: Calculated | E11: Sub-Industry | H11: <-- Use EQUIDATA
A12: BB | C12: Input | E12: Bloomberg code | G12: JSWINFRA IN EQUITY | H12: <-- Analyst to enter
A13: RATING | C13: Input | E13: Recommendation | G13: ADD | H13: <-- Analyst to enter
A14: PRIOR_RATING | C14: Calculated | E14: Prior Rating | H14: <-- Use EQUIDATA
A15: DATE_RATING_CHG | C15: Input | E15: Date of Recommendation Change | H15: <-- Analyst to enter
A16: FREE_FLOAT | C16: Calculated | E16: Free Float | F16: % | H16: <-- Use EQUIDATA
A17: CMP | C17: Calculated | E17: Share Price (Rs) | G17: 310 | H17: <-- Use EQUIDATA
A18: EQ_PXDT | C18: Calculated | E18: Price Date | G18: 46168 | H18: <-- Use EQUIDATA
A19: PRICE_TARGET | C19: Input | E19: Target Price (Rs) | G19: 290 | H19: <-- Analyst to enter
A20: SHARES_OS_CUR | C20: Input | E20: Current Shares Out (m) | F20: mn | G20: {=_xll.EQUIDATA($G$12,$A20,"private")} -> 2100.002 | H20: <-- Analyst to enter
A21: LAST_REPORT_DATE | C21: Input | E21: Last Reported Result Date | G21: 46021 | H21: <-- Analyst to enter
A22: FISCAL_YEAR_END | C22: Input | E22: Fiscal Year End | H22: <-- Analyst to enter
A23: COMPANY_TYPE | C23: Input | E23: Consolidated/Standalone | H23: <-- Analyst to enter
A24: BSE_SENSEX | C24: Calculated | E24: BSE Sensex | H24: <-- Use EQUIDATA
A25: INR CURNCY | C25: Calculated | E25: Exchange rate (Rs:USD) | H25: <-- Use EQUIDATA
A26: FIFTY_TWO_WEEK_HIGH | C26: Calculated | E26: 52-week High | G26: {=_xll.EQUIDATA($G$12,$A26,"private")} -> 349 | H26: <-- Use EQUIDATA
A27: FIFTY_TWO_WEEK_LOW | C27: Calculated | E27: 52-week Low | G27: {=_xll.EQUIDATA($G$12,$A27,"private")} -> 233.42 | H27: <-- Use EQUIDATA
A28: CURR_MKT_CAP_RS | C28: Calculated | E28: Current Market cap | G28: =NewFinSumm!I76 -> 731745 | H28: <-- Use EQUIDATA
A29: CURR_MKT_CAP_USD | C29: Calculated | E29: Current Market cap USD | G29: {=_xll.EQUIDATA($G$12,$A29,"private")} -> 6982.3877 | H29: <-- Use EQUIDATA
A30: TABLE1_SCALE | C30: Input | E30: Financial Summary (scale) | G30: Rs mn
A31: TABLE2_SCALE | C31: Input | E31: Income Statement (scale) | G31: Rs mn
A32: TABLE3_SCALE | C32: Input | E32: Balance Sheet (scale) | G32: Rs mn
A33: TABLE4_SCALE | C33: Input | E33: Cash Flow (scale) | G33: Rs mn
A34: TABLE5_SCALE | C34: Input | E34: Old vs. New Table (scale) | G34: Rs mn
E37: Profit & Loss statement
A38: IS_GR_SALES | B38: =IF(IF(D38="+",MIN(H38:IU38)>=0,IF(D38="-",MAX(H38:IU38)<=0,TRUE)),"",1) | C38: Input | D38: + | E38: Gross Sales | F38: mn
A39: IS_DUTIES | B39: =IF(IF(D39="+",MIN(H39:IU39)>=0,IF(D39="-",MAX(H39:IU39)<=0,TRUE)),"",1) | C39: Input | D39: + | E39: Less: Duties | F39: mn
A40: IS_NET_SALES | C40: Calculated | D40: ● | E40: Net Sales | F40: mn | X40: =Consol!G16 -> 9980.936 | Y40: =Consol!H16 -> 10802.602 | Z40: =Consol!I16 -> 11431.453 | AA40: =Consol!J16 -> 16035.705 | AB40: =Consol!K16 -> 22730.588 | AC40: =Consol!L16 -> 31947.396 | AD40: =Consol!M16 -> 37628.9 | AE40: =Consol!N16 -> 44761.4 | ... AJ40: =Consol!S16 -> 188550.74
A41: IS_NET_SALES_USD | B41: =IF(IF(D41="+",MIN(H41:IU41)>=0,IF(D41="-",MAX(H41:IU41)<=0,TRUE)),"",1) | C41: Input | D41: + | E41: Net Sales ($) | F41: mn
A42: IS_OOP_INC | B42: =IF(IF(D42="+",MIN(H42:IU42)>=0,IF(D42="-",MAX(H42:IU42)<=0,TRUE)),"",1) | C42: Input | D42: + | E42: Other Operating Income | F42: mn
A43: IS_TTL_REV | C43: Calculated | D43: ● | E43: Total Revenue | F43: mn | Q43: =Q40 -> 0 | R43: =R40 -> 0 | S43: =S40 -> 0 | T43: =T40 -> 0 | U43: =U40 -> 0 | V43: =V40 -> 0 | W43: =W40 -> 0 | X43: =X40 -> 9980.936 | ... AJ43: =AJ40 -> 188550.74
A44: IS_RAW_MATERIALS | B44: =IF(IF(D44="+",MIN(H44:IU44)>=0,IF(D44="-",MAX(H44:IU44)<=0,TRUE)),"",1) | C44: Input | D44: + | E44: Raw material expenses | F44: mn
A45: IS_DIRECT_EXP | B45: =IF(IF(D45="+",MIN(H45:IU45)>=0,IF(D45="-",MAX(H45:IU45)<=0,TRUE)),"",1) | C45: Input | D45: + | E45: Direct /Employee Costs | F45: mn
A46: IS_GROSS_PRFT | C46: Calculated | D46: ● | E46: Gross Profit | F46: mn
A47: IS_EMPL_EXP | B47: =IF(IF(D47="+",MIN(H47:IU47)>=0,IF(D47="-",MAX(H47:IU47)<=0,TRUE)),"",1) | C47: Input | D47: + | E47: Employee Expenses | F47: mn | X47: =Consol!G20 -> 569.579 | Y47: =Consol!H20 -> 596.223 | Z47: =Consol!I20 -> 746.658 | AA47: =Consol!J20 -> 1113.5 | AB47: =Consol!K20 -> 1496.51 | AC47: =Consol!L20 -> 2299.58 | AD47: =Consol!M20 -> 2846.4 | AE47: =Consol!N20 -> 2406.5 | AF47: =Consol!O20 -> 2386.9
A48: IS_PROM_EXP | B48: =IF(IF(D48="+",MIN(H48:IU48)>=0,IF(D48="-",MAX(H48:IU48)<=0,TRUE)),"",1) | C48: Input | D48: + | E48: Promotion Expenses | F48: mn
A49: IS_FND_EXP | B49: =IF(IF(D49="+",MIN(H49:IU49)>=0,IF(D49="-",MAX(H49:IU49)<=0,TRUE)),"",1) | C49: Input | D49: + | E49: Freight & Distribution Expenses | F49: mn
A50: IS_REPAIR_MAIN | B50: =IF(IF(D50="+",MIN(H50:IU50)>=0,IF(D50="-",MAX(H50:IU50)<=0,TRUE)),"",1) | C50: Input | D50: + | E50: Repairs & maintenance | F50: mn
A51: IS_RENT | B51: =IF(IF(D51="+",MIN(H51:IU51)>=0,IF(D51="-",MAX(H51:IU51)<=0,TRUE)),"",1) | C51: Input | D51: + | E51: Rent | F51: mn
A52: IS_POWER_FUEL | B52: =IF(IF(D52="+",MIN(H52:IU52)>=0,IF(D52="-",MAX(H52:IU52)<=0,TRUE)),"",1) | C52: Input | D52: + | E52: Power & fuel | F52: mn
A53: IS_RD_EXPENSE | B53: =IF(IF(D53="+",MIN(H53:IU53)>=0,IF(D53="-",MAX(H53:IU53)<=0,TRUE)),"",1) | C53: Input | D53: + | E53: R&D Expense | F53: mn
A54: IS_PROV | B54: =IF(IF(D54="+",MIN(H54:IU54)>=0,IF(D54="-",MAX(H54:IU54)<=0,TRUE)),"",1) | C54: Input | D54: + | E54: Provisions | F54: mn
A55: IS_FND_EXP | B55: =IF(IF(D55="+",MIN(H55:IU55)>=0,IF(D55="-",MAX(H55:IU55)<=0,TRUE)),"",1) | C55: Input | D55: + | E55: Royalty | F55: mn
A56: IS_OOP_EXP | B56: =IF(IF(D56="+",MIN(H56:IU56)>=0,IF(D56="-",MAX(H56:IU56)<=0,TRUE)),"",1) | C56: Input | D56: + | E56: Other Operating Expenses | F56: mn | X56: =+Consol!G19+Consol!G21 -> 3533.001 | Y56: =+Consol!H19+Consol!H21 -> 4084.972 | Z56: =+Consol!I19+Consol!I21 -> 4492.833 | AA56: =+Consol!J19+Consol!J21 -> 6757.81 | AB56: =+Consol!K19+Consol!K21 -> 10139.77 | AC56: =+Consol!L19+Consol!L21 -> 13445.92 | AD56: =+Consol!M19+Consol!M21 -> 15136.9 | AE56: =+Consol!N19+Consol!N21 -> 19733.1 | AF56: =+Consol!O19+Consol!O21 -> 25190.2
A57: IS_TTL_EXP | C57: Calculated | D57: ● | E57: Total Operating Expenses | F57: mn | Q57: =+SUM(Q47:Q56) -> 0 | R57: =+SUM(R47:R56) -> 0 | S57: =+SUM(S47:S56) -> 0 | T57: =+SUM(T47:T56) -> 0 | U57: =+SUM(U47:U56) -> 0 | V57: =+SUM(V47:V56) -> 0 | W57: =+SUM(W47:W56) -> 0 | X57: =+SUM(X47:X56) -> 4102.58 | ... AF57: =+SUM(AF47:AF56) -> 27577.1
A58: EBITDA | C58: Calculated | D58: ● | E58: EBITDA | F58: mn | Q58: =+Q43-Q57 -> 0 | R58: =+R43-R57 -> 0 | S58: =+S43-S57 -> 0 | T58: =+T43-T57 -> 0 | U58: =+U43-U57 -> 0 | V58: =+V43-V57 -> 0 | W58: =+W43-W57 -> 0 | X58: =+X43-X57 -> 5878.356 | ... AF58: =+AF43-AF57 -> 26037.3 | AG58: =Consol!P23 -> 29530.876 | AH58: =Consol!Q23 -> 47439.421 | AI58: =Consol!R23 -> 57966.428 | AJ58: =Consol!S23 -> 75506.814
A59: IS_DEP | B59: =IF(IF(D59="+",MIN(H59:IU59)>=0,IF(D59="-",MAX(H59:IU59)<=0,TRUE)),"",1) | C59: Input | D59: + | E59: Depreciation | F59: mn | X59: =Consol!G28 -> 1571.402 | Y59: =Consol!H28 -> 2524.951 | Z59: =Consol!I28 -> 2018.573 | AA59: =Consol!J28 -> 2706.55 | AB59: =Consol!K28 -> 3695.05 | AC59: =Consol!L28 -> 3912.23 | AD59: =Consol!M28 -> 4364.8 | AE59: =Consol!N28 -> 5465.5 | ... AJ59: =Consol!S28 -> 24495.596
A60: IS_AMRT | B60: =IF(IF(D60="+",MIN(H60:IU60)>=0,IF(D60="-",MAX(H60:IU60)<=0,TRUE)),"",1) | C60: Input | D60: + | E60: Amortisation | F60: mn
A61: IS_TTL_DNA | C61: Calculated | D61: ● | E61: Total D&A | F61: mn | Q61: =+Q59+Q60 -> 0 | R61: =+R59+R60 -> 0 | S61: =+S59+S60 -> 0 | T61: =+T59+T60 -> 0 | U61: =+U59+U60 -> 0 | V61: =+V59+V60 -> 0 | W61: =+W59+W60 -> 0 | X61: =+X59+X60 -> 1571.402 | ... AJ61: =+AJ59+AJ60 -> 24495.596
A62: IS_EBIT | C62: Calculated | D62: ● | E62: EBIT | F62: mn | Q62: =+Q58-Q61 -> 0 | R62: =+R58-R61 -> 0 | S62: =+S58-S61 -> 0 | T62: =+T58-T61 -> 0 | U62: =+U58-U61 -> 0 | V62: =+V58-V61 -> 0 | W62: =+W58-W61 -> 0 | X62: =+X58-X61 -> 4306.954 | ... AJ62: =+AJ58-AJ61 -> 51011.218
A63: IS_INT_INC | B63: =IF(IF(D63="+",MIN(H63:IU63)>=0,IF(D63="-",MAX(H63:IU63)<=0,TRUE)),"",1) | C63: Input | D63: + | E63: Interest Income | F63: mn
A64: IS_INT_EXP | B64: =IF(IF(D64="+",MIN(H64:IU64)>=0,IF(D64="-",MAX(H64:IU64)<=0,TRUE)),"",1) | C64: Input | D64: + | E64: Interest Expenses | F64: mn | X64: =Consol!G32 -> 1298.942 | Y64: =Consol!H32 -> 1771.365 | Z64: =Consol!I32 -> 2774.583 | AA64: =Consol!J32 -> 2278.57 | AB64: =Consol!K32 -> 4196.22 | AC64: =Consol!L32 -> 5960.8 | AD64: =Consol!M32 -> 3324.6 | AE64: =Consol!N32 -> 2657.4 | ... AJ64: =Consol!S32 -> 15540.225
A65: IS_NET_NET | C65: Calculated | D65: ● | E65: Net Interest | F65: mn | Q65: =+Q63+Q64 -> 0 | R65: =+R63+R64 -> 0 | S65: =+S63+S64 -> 0 | T65: =+T63+T64 -> 0 | U65: =+U63+U64 -> 0 | V65: =+V63+V64 -> 0 | W65: =+W63+W64 -> 0 | X65: =+X63+X64 -> 1298.942 | ... AJ65: =+AJ63+AJ64 -> 15540.225
A66: IS_OTHR_NOP_INC | B66: =IF(IF(D66="+",MIN(H66:IU66)>=0,IF(D66="-",MAX(H66:IU66)<=0,TRUE)),"",1) | C66: Input | D66: + | E66: Other Non Operating Income | F66: mn | X66: =Consol!G27 -> 766.755 | Y66: =Consol!H27 -> 1013.331 | Z66: =Consol!I27 -> 942.207 | AA66: =Consol!J27 -> 746.93 | AB66: =Consol!K27 -> 1056.79 | AC66: =Consol!L27 -> 1781.13 | AD66: =Consol!M27 -> 2694.1 | AE66: =Consol!N27 -> 3529.5 | ... AJ66: =Consol!S27 -> 1594.2853
A67: IS_EXCPT_ITEM | B67: =IF(IF(D67="+",MIN(H67:IU67)>=0,IF(D67="-",MAX(H67:IU67)<=0,TRUE)),"",1) | C67: Input | D67: ± | E67: Exceptional Items | F67: mn
A68: IS_RPBT | C68: Calculated | D68: ● | E68: Reported PBT | F68: mn | Q68: =+Q62-Q65+Q66+Q67 -> 0 | R68: =+R62-R65+R66+R67 -> 0 | S68: =+S62-S65+S66+S67 -> 0 | T68: =+T62-T65+T66+T67 -> 0 | U68: =+U62-U65+U66+U67 -> 0 | V68: =+V62-V65+V66+V67 -> 0 | W68: =+W62-W65+W66+W67 -> 0 | X68: =+X62-X65+X66+X67 -> 3774.767 | ... AJ68: =+AJ62-AJ65+AJ66+AJ67 -> 37065.278
A69: IS_APBT | C69: Calculated | D69: ● | E69: Adjusted PBT | F69: mn | Q69: =+Q68-Q67 -> 0 | R69: =+R68-R67 -> 0 | S69: =+S68-S67 -> 0 | T69: =+T68-T67 -> 0 | U69: =+U68-U67 -> 0 | V69: =+V68-V67 -> 0 | W69: =+W68-W67 -> 0 | X69: =+X68-X67 -> 3774.767 | ... AJ69: =+AJ68-AJ67 -> 37065.278
A70: IS_CURR_TAX | B70: =IF(IF(D70="+",MIN(H70:IU70)>=0,IF(D70="-",MAX(H70:IU70)<=0,TRUE)),"",1) | C70: Input | D70: + | E70: Current Tax | F70: mn
A71: IS_DEF_TAX | B71: =IF(IF(D71="+",MIN(H71:IU71)>=0,IF(D71="-",MAX(H71:IU71)<=0,TRUE)),"",1) | C71: Input | D71: ± | E71: Deferred Tax | F71: mn
A72: IS_OTHR_ADJ | B72: =IF(IF(D72="+",MIN(H72:IU72)>=0,IF(D72="-",MAX(H72:IU72)<=0,TRUE)),"",1) | C72: Input | D72: ± | E72: Other Adjustments | F72: mn
A73: IS_TTL_TAX | C73: Calculated | D73: ● | E73: Total Tax | F73: mn | X73: =Consol!G41 -> 966.63 | Y73: =Consol!H41 -> 118.773 | Z73: =Consol!I41 -> 375.716 | AA73: =Consol!J41 -> 1079.95 | AB73: =Consol!K41 -> 955.46 | AC73: =Consol!L41 -> 614.79 | AD73: =Consol!M41 -> 3043.4 | AE73: =Consol!N41 -> 2813.6 | ... AJ73: =Consol!S41 -> 8154.3612
A74: IS_PAT | C74: Calculated | D74: ● | E74: Profit After Tax | F74: mn | Q74: =+Q68-Q73 -> 0 | R74: =+R68-R73 -> 0 | S74: =+S68-S73 -> 0 | T74: =+T68-T73 -> 0 | U74: =+U68-U73 -> 0 | V74: =+V68-V73 -> 0 | W74: =+W68-W73 -> 0 | X74: =+X68-X73 -> 2808.137 | ... AJ74: =+AJ68-AJ73 -> 28910.917
A75: IS_EXT_ITEM | B75: =IF(IF(D75="+",MIN(H75:IU75)>=0,IF(D75="-",MAX(H75:IU75)<=0,TRUE)),"",1) | C75: Input | D75: ± | E75: Extra Ordinary Items | F75: mn
A76: IS_MIN_INT | B76: =IF(IF(D76="+",MIN(H76:IU76)>=0,IF(D76="-",MAX(H76:IU76)<=0,TRUE)),"",1) | C76: Input | D76: ± | E76: Minority Interest | F76: mn | X76: =Consol!G46 -> 0 | Y76: =Consol!H46 -> 52.405 | Z76: =Consol!I46 -> 61.056 | AA76: =Consol!J46 -> -67.6 | AB76: =Consol!K46 -> 24.91 | AC76: =Consol!L46 -> 96.83 | AD76: =Consol!M46 -> 47.8 | AE76: =Consol!N46 -> 184 | ... AJ76: =Consol!S46 -> 962.34259
A77: IS_ASSOCIATES | B77: =IF(IF(D77="+",MIN(H77:IU77)>=0,IF(D77="-",MAX(H77:IU77)<=0,TRUE)),"",1) | C77: Input | D77: ± | E77: Profit / (Loss) from Associates | F77: mn
A78: IS_RPAT | C78: Calculated | D78: ● | E78: Reported PAT after M.I. | F78: mn | Q78: =+Q74-Q76+Q77 -> 0 | R78: =+R74-R76+R77 -> 0 | S78: =+S74-S76+S77 -> 0 | T78: =+T74-T76+T77 -> 0 | U78: =+U74-U76+U77 -> 0 | V78: =+V74-V76+V77 -> 0 | W78: =+W74-W76+W77 -> 0 | X78: =+X74-X76+X77 -> 2808.137 | ... AJ78: =+AJ74-AJ76+AJ77 -> 27948.574
A79: IS_APAT | C79: Calculated | D79: ● | E79: Adjusted PAT after M.I. | F79: mn | Q79: =+Q78-Q67 -> 0 | R79: =+R78-R67 -> 0 | S79: =+S78-S67 -> 0 | T79: =+T78-T67 -> 0 | U79: =+U78-U67 -> 0 | V79: =+V78-V67 -> 0 | W79: =+W78-W67 -> 0 | X79: =+X78-X67 -> 2808.137 | ... AJ79: =+AJ78-AJ67 -> 27948.574
A80: IS_DIVIDEND | B80: =IF(IF(D80="+",MIN(H80:IU80)>=0,IF(D80="-",MAX(H80:IU80)<=0,TRUE)),"",1) | C80: Input | D80: + | E80: Total dividends | F80: mn | AD80: =Consol!M60 -> 1155 | AE80: =Consol!N60 -> 1680 | AF80: =Consol!O60 -> 1890 | AG80: =Consol!P60 -> 1914.9972 | AH80: =Consol!Q60 -> 2806.6276 | AI80: =Consol!R60 -> 2933.451 | AJ80: =Consol!S60 -> 3353.8289
A81: NO_SHARES | B81: =IF(IF(D81="+",MIN(H81:IU81)>=0,IF(D81="-",MAX(H81:IU81)<=0,TRUE)),"",1) | C81: Input | D81: + | E81: Shares Outstanding (Wt Avg) | F81: mn | X81: =Consol!G53 -> 2100 | Y81: =Consol!H53 -> 2100 | Z81: =Consol!I53 -> 2100 | AA81: =Consol!J53 -> 2100 | AB81: =Consol!K53 -> 2100 | AC81: =Consol!L53 -> 2100 | AD81: =Consol!M53 -> 2100 | AE81: =Consol!N53 -> 2100 | ... AJ81: =Consol!S53 -> 2330
A82: FD_SH_OUT | B82: =IF(IF(D82="+",MIN(H82:IU82)>=0,IF(D82="-",MAX(H82:IU82)<=0,TRUE)),"",1) | C82: Input | D82: + | E82: Fully Diluted Shares Outstanding (Wt Avg) | F82: mn | Q82: =Q81 -> 0 | R82: =R81 -> 0 | S82: =S81 -> 0 | T82: =T81 -> 0 | U82: =U81 -> 0 | V82: =V81 -> 0 | W82: =W81 -> 0 | X82: =X81 -> 2100 | ... AJ82: =AJ81 -> 2330
E84: Balance Sheet
E85: Sources Of Funds
E86: Shareholders' Equity
A87: BS_SHRE_CAP | B87: =IF(IF(D87="+",MIN(H87:IU87)>=0,IF(D87="-",MAX(H87:IU87)<=0,TRUE)),"",1) | C87: Input | D87: + | E87: Paid up Capital | F87: mn | X87: =Consol!G65 -> 601.798 | Y87: =Consol!H65 -> 601.798 | Z87: =Consol!I65 -> 599.29 | AA87: =Consol!J65 -> 599.29 | AB87: =Consol!K65 -> 599.29 | AC87: =Consol!L65 -> 3595.75 | AD87: =Consol!M65 -> 4103 | AE87: =Consol!N65 -> 4147 | ... AJ87: =Consol!S65 -> 4630.4
A88: BS_EMPL_STCK_OPT | B88: =IF(IF(D88="+",MIN(H88:IU88)>=0,IF(D88="-",MAX(H88:IU88)<=0,TRUE)),"",1) | C88: Input | D88: + | E88: Employee Stock Options | F88: mn
A89: BS_TTL_RES_SURP | C89: Calculated | D89: ● | E89: Reserves & Surplus | F89: mn | Q89: =+SUM(Q90:Q94) -> 0 | R89: =+SUM(R90:R94) -> 0 | S89: =+SUM(S90:S94) -> 0 | T89: =+SUM(T90:T94) -> 0 | U89: =+SUM(U90:U94) -> 0 | V89: =+SUM(V90:V94) -> 0 | W89: =+SUM(W90:W94) -> 0 | X89: =+SUM(X90:X94) -> 25528.919 | ... AJ89: =+SUM(AJ90:AJ94) -> 251657.07
A90: BS_TRFR_PL_AC | B90: =IF(IF(D90="+",MIN(H90:IU90)>=0,IF(D90="-",MAX(H90:IU90)<=0,TRUE)),"",1) | C90: Input | D90: + | E90: Trfr P&L A/c | F90: mn
A91: BS_SH_PREM_RES | B91: =IF(IF(D91="+",MIN(H91:IU91)>=0,IF(D91="-",MAX(H91:IU91)<=0,TRUE)),"",1) | C91: Input | D91: + | E91: Share Premium Reserve | F91: mn
A92: BS_GEN_RES | B92: =IF(IF(D92="+",MIN(H92:IU92)>=0,IF(D92="-",MAX(H92:IU92)<=0,TRUE)),"",1) | C92: Input | D92: + | E92: General Reserve | F92: mn
A93: BS_FTA_RES | B93: =IF(IF(D93="+",MIN(H93:IU93)>=0,IF(D93="-",MAX(H93:IU93)<=0,TRUE)),"",1) | C93: Input | D93: ± | E93: Foreign Transaction Reserve | F93: mn
A94: BS_OTHR_RES | B94: =IF(IF(D94="+",MIN(H94:IU94)>=0,IF(D94="-",MAX(H94:IU94)<=0,TRUE)),"",1) | C94: Input | D94: ± | E94: Other Reserves | F94: mn | X94: =Consol!G66 -> 25528.919 | Y94: =Consol!H66 -> 28274.851 | Z94: =Consol!I66 -> 24882.869 | AA94: =Consol!J66 -> 28312.39 | AB94: =Consol!K66 -> 32121.89 | AC94: =Consol!L66 -> 36350.5 | AD94: =Consol!M66 -> 76160.6 | AE94: =Consol!N66 -> 92822 | ... AJ94: =Consol!S66 -> 251657.07
A95: BS_TTL_SH_EQTY | C95: Calculated | D95: ● | E95: Total Shareholders' Equity / Networth | F95: mn | Q95: =+Q89+Q87 -> 0 | R95: =+R89+R87 -> 0 | S95: =+S89+S87 -> 0 | T95: =+T89+T87 -> 0 | U95: =+U89+U87 -> 0 | V95: =+V89+V87 -> 0 | W95: =+W89+W87 -> 0 | X95: =+X89+X87 -> 26130.717 | ... AJ95: =+AJ89+AJ87 -> 256287.47
A96: BS_MIN_INT | B96: =IF(IF(D96="+",MIN(H96:IU96)>=0,IF(D96="-",MAX(H96:IU96)<=0,TRUE)),"",1) | C96: Input | D96: + | E96: Minority Interest | F96: mn | X96: =Consol!G69 -> 1918.253 | Y96: =Consol!H69 -> 1970.534 | Z96: =Consol!I69 -> 2031.004 | AA96: =Consol!J69 -> 1972.63 | AB96: =Consol!K69 -> 1997.59 | AC96: =Consol!L69 -> 942.48 | AD96: =Consol!M69 -> 2046.6 | AE96: =Consol!N69 -> 7918 | ... AJ96: =Consol!S69 -> 10935.271
A97: BS_TTL_SH_EQTY_MINT | C97: Calculated | D97: ● | E97: Total Shareholders' Equity After MI | F97: mn | Q97: =+Q95+Q96 -> 0 | R97: =+R95+R96 -> 0 | S97: =+S95+S96 -> 0 | T97: =+T95+T96 -> 0 | U97: =+U95+U96 -> 0 | V97: =+V95+V96 -> 0 | W97: =+W95+W96 -> 0 | X97: =+X95+X96 -> 28048.97 | ... AJ97: =+AJ95+AJ96 -> 267222.74
A98: BS_TTL_BORROW | C98: Calculated | D98: ● | E98: Total Borrowings | F98: mn | X98: =Consol!G78 -> 16799.911 | Y98: =Consol!H78 -> 20001.206 | Z98: =Consol!I78 -> 27167.16 | AA98: =Consol!J78 -> 39458.18 | AB98: =Consol!K78 -> 44086.94 | AC98: =Consol!L78 -> 42436.98 | AD98: =Consol!M78 -> 43806.8 | AE98: =Consol!N78 -> 46588.3 | ... AJ98: =Consol!S78 -> 153554.57
A99: BS_LTD | B99: =IF(IF(D99="+",MIN(H99:IU99)>=0,IF(D99="-",MAX(H99:IU99)<=0,TRUE)),"",1) | C99: Input | D99: + | E99: Long Term Borrowings | F99: mn
A100: BS_STD | B100: =IF(IF(D100="+",MIN(H100:IU100)>=0,IF(D100="-",MAX(H100:IU100)<=0,TRUE)),"",1) | C100: Input | D100: + | E100: Short Term Borrowings | F100: mn
A101: BS_LEASE_LIB | B101: =IF(IF(D101="+",MIN(H101:IU101)>=0,IF(D101="-",MAX(H101:IU101)<=0,TRUE)),"",1) | C101: Input | D101: + | E101: Lease Liability | F101: mn
A102: BS_DEF_TAX_LIAB | B102: =IF(IF(D102="+",MIN(H102:IU102)>=0,IF(D102="-",MAX(H102:IU102)<=0,TRUE)),"",1) | C102: Input | D102: + | E102: Deferred Tax Liability | F102: mn
A103: BS_LT_PROV | B103: =IF(IF(D103="+",MIN(H103:IU103)>=0,IF(D103="-",MAX(H103:IU103)<=0,TRUE)),"",1) | C103: Input | D103: + | E103: Long Term Provisions | F103: mn
...

Sheet EquibaseQTR
C1: Input | D1: =IF(SUM(B3:B5023)=0,"✓","×") -> ✓ | E1: 7 | H1: 41791 | I1: =EOMONTH(H1,2)+1 -> 41883 | J1: =EOMONTH(I1,2)+1 -> 41974 | K1: =EOMONTH(J1,2)+1 -> 42064 | L1: =EOMONTH(K1,2)+1 -> 42156 | M1: =EOMONTH(L1,2)+1 -> 42248 | N1: =EOMONTH(M1,2)+1 -> 42339 | O1: =EOMONTH(N1,2)+1 -> 42430 | P1: =EOMONTH(O1,2)+1 -> 42522 | ... BB1: =EOMONTH(BA1,2)+1 -> 45992
A2: Item Codes | C2: Calculated | E2: Actual/Estimate | F2: UNITS | H2: =IF(H1<=$G$21,"A","E") -> A | I2: =IF(I1<=$G$21,"A","E") -> A | J2: =IF(J1<=$G$21,"A","E") -> A | K2: =IF(K1<=$G$21,"A","E") -> A | L2: =IF(L1<=$G$21,"A","E") -> A | M2: =IF(M1<=$G$21,"A","E") -> A | N2: =IF(N1<=$G$21,"A","E") -> A | O2: =IF(O1<=$G$21,"A","E") -> A | ... AZ2: =IF(AZ1<=$G$21,"A","E") -> A | BA2: A | BB2: A
C3: Input | E3: Months | H3: 3 | I3: 3 | J3: 3 | K3: 3 | L3: 3 | M3: 3 | N3: 3 | O3: 3 | P3: 3 | Q3: 3 | R3: 3 | S3: 3 | T3: 3 | U3: 3 | V3: 3 | W3: 3 | X3: 3 | Y3: 3 | Z3: 3 | AA3: 3 | AB3: 3 | AC3: 3 | AD3: 3 | AE3: 3 | AF3: 3 | AG3: 3 | AH3: 3 | AI3: 3 | AJ3: 3 | AK3: 3 | AL3: 3 | AM3: 3 | AN3: 3 | AO3: 3 | AP3: 3 | AQ3: 3 | AR3: 3 | AS3: 3 | AT3: 3 | AU3: 3 | AV3: 3 | AW3: 3 | AX3: 3 | AY3: 3 | AZ3: 3 | BA3: 3 | BB3: 3
C4: Input | E4: Period Type | H4: Quarterly | I4: Quarterly | J4: Quarterly | K4: Quarterly | L4: Quarterly | M4: Quarterly | N4: Quarterly | O4: Quarterly | P4: Quarterly | Q4: Quarterly | R4: Quarterly | S4: Quarterly | T4: Quarterly | U4: Quarterly | V4: Quarterly | W4: Quarterly | X4: Quarterly | Y4: Quarterly | Z4: Quarterly | AA4: Quarterly | AB4: Quarterly | AC4: Quarterly | AD4: Quarterly | AE4: Quarterly | AF4: Quarterly | AG4: Quarterly | AH4: Quarterly | AI4: Quarterly | AJ4: Quarterly | AK4: Quarterly | AL4: Quarterly | AM4: Quarterly | AN4: Quarterly | AO4: Quarterly | AP4: Quarterly | AQ4: Quarterly | AR4: Quarterly | AS4: Quarterly | AT4: Quarterly | AU4: Quarterly | AV4: Quarterly | AW4: Quarterly | AX4: Quarterly | AY4: Quarterly | AZ4: Quarterly | BA4: Quarterly | BB4: Quarterly
C5: Input | E5: Year End | H5: =H1 -> 41791 | I5: =I1 -> 41883 | J5: =J1 -> 41974 | K5: =K1 -> 42064 | L5: =L1 -> 42156 | M5: =M1 -> 42248 | N5: =N1 -> 42339 | O5: =O1 -> 42430 | ... BB5: =BB1 -> 45992
C6: Calculated | E6: Year Label | H6: =_xlfn.CONCAT((IF(MONTH(H1)=3,4,IF(MONTH(H1)=6,1,IF(MONTH(H1)=9,2,3)))),"Q",IF(MONTH(H1)=12,"FY"&TEXT(DATE(YEAR(H1)+1,1,1),"YY"),"FY"&TEXT(DATE(YEAR(H1)+IF(MONTH(H1)>=4,1,0),1,1),"YY"))&H2) -> 1QFY15A | I6: =_xlfn.CONCAT((IF(MONTH(I1)=3,4,IF(MONTH(I1)=6,1,IF(MONTH(I1)=9,2,3)))),"Q",IF(MONTH(I1)=12,"FY"&TEXT(DATE(YEAR(I1)+1,1,1),"YY"),"FY"&TEXT(DATE(YEAR(I1)+IF(MONTH(I1)>=4,1,0),1,1),"YY"))&I2) -> 2QFY15A | J6: =_xlfn.CONCAT((IF(MONTH(J1)=3,4,IF(MONTH(J1)=6,1,IF(MONTH(J1)=9,2,3)))),"Q",IF(MONTH(J1)=12,"FY"&TEXT(DATE(YEAR(J1)+1,1,1),"YY"),"FY"&TEXT(DATE(YEAR(J1)+IF(MONTH(J1)>=4,1,0),1,1),"YY"))&J2) -> 3QFY15A | K6: =_xlfn.CONCAT((IF(MONTH(K1)=3,4,IF(MONTH(K1)=6,1,IF(MONTH(K1)=9,2,3)))),"Q",IF(MONTH(K1)=12,"FY"&TEXT(DATE(YEAR(K1)+1,1,1),"YY"),"FY"&TEXT(DATE(YEAR(K1)+IF(MONTH(K1)>=4,1,0),1,1),"YY"))&K2) -> 4QFY15A | L6: =_xlfn.CONCAT((IF(MONTH(L1)=3,4,IF(MONTH(L1)=6,1,IF(MONTH(L1)=9,2,3)))),"Q",IF(MONTH(L1)=12,"FY"&TEXT(DATE(YEAR(L1)+1,1,1),"YY"),"FY"&TEXT(DATE(YEAR(L1)+IF(MONTH(L1)>=4,1,0),1,1),"YY"))&L2) -> 1QFY16A | M6: =_xlfn.CONCAT((IF(MONTH(M1)=3,4,IF(MONTH(M1)=6,1,IF(MONTH(M1)=9,2,3)))),"Q",IF(MONTH(M1)=12,"FY"&TEXT(DATE(YEAR(M1)+1,1,1),"YY"),"FY"&TEXT(DATE(YEAR(M1)+IF(MONTH(M1)>=4,1,0),1,1),"YY"))&M2) -> 2QFY16A | N6: =_xlfn.CONCAT((IF(MONTH(N1)=3,4,IF(MONTH(N1)=6,1,IF(MONTH(N1)=9,2,3)))),"Q",IF(MONTH(N1)=12,"FY"&TEXT(DATE(YEAR(N1)+1,1,1),"YY"),"FY"&TEXT(DATE(YEAR(N1)+IF(MONTH(N1)>=4,1,0),1,1),"YY"))&N2) -> 3QFY16A | O6: =_xlfn.CONCAT((IF(MONTH(O1)=3,4,IF(MONTH(O1)=6,1,IF(MONTH(O1)=9,2,3)))),"Q",IF(MONTH(O1)=12,"FY"&TEXT(DATE(YEAR(O1)+1,1,1),"YY"),"FY"&TEXT(DATE(YEAR(O1)+IF(MONTH(O1)>=4,1,0),1,1),"YY"))&O2) -> 4QFY16A | ... BB6: =_xlfn.CONCAT((IF(MONTH(BB1)=3,4,IF(MONTH(BB1)=6,1,IF(MONTH(BB1)=9,2,3)))),"Q",IF(MONTH(BB1)=12,"FY"&TEXT(DATE(YEAR(BB1)+1,1,1),"YY"),"FY"&TEXT(DATE(YEAR(BB1)+IF(MONTH(BB1)>=4,1,0),1,1),"YY"))&BB2) -> 3QFY26A
A7: EQ_COMPANY_NAME | C7: Calculated | E7: Full Name Of Company | G7: JSW Infrastructure | H7: <-- Use EQUIDATA
A8: COMPANY_SHORT_NAME | C8: Calculated | E8: Short Name For Company | G8: JSW Infra | H8: <-- Use EQUIDATA
A9: EQ_SECTOR_NAME | C9: Calculated | E9: Sector | G9: Infrastructure | H9: <-- Use EQUIDATA
A10: EQ_INDUSTRY_NAME | C10: Calculated | E10: Industry | H10: <-- Use EQUIDATA
A11: EQ_SUBINDUSTRY_NAME | C11: Calculated | E11: Sub-Industry | H11: <-- Use EQUIDATA
A12: BB | C12: Input | E12: Bloomberg code | G12: JSWINFRA IN EQUITY | H12: <-- Analyst to enter
A13: RATING | C13: Input | E13: Recommendation | G13: ADD | H13: <-- Analyst to enter
A14: PRIOR_RATING | C14: Calculated | E14: Prior Rating | H14: <-- Use EQUIDATA
A15: DATE_RATING_CHG | C15: Input | E15: Date of Recommendation Change | H15: <-- Analyst to enter
A16: FREE_FLOAT | C16: Calculated | E16: Free Float | F16: % | H16: <-- Use EQUIDATA
A17: CMP | C17: Calculated | E17: Share Price (Rs) | G17: 310 | H17: <-- Use EQUIDATA
A18: EQ_PXDT | C18: Calculated | E18: Price Date | G18: 46038 | H18: <-- Use EQUIDATA
A19: PRICE_TARGET | C19: Input | E19: Target Price (Rs) | G19: 290 | H19: <-- Analyst to enter
A20: SHARES_OS_CUR | C20: Input | E20: Current Shares Out (m) | F20: mn | G20: {=_xll.EQUIDATA($G$12,$A20,"private")} -> 2100.002 | H20: <-- Analyst to enter
A21: LAST_REPORT_DATE | C21: Input | E21: Last Reported Result Date | G21: 45930 | H21: <-- Analyst to enter
A22: FISCAL_YEAR_END | C22: Input | E22: Fiscal Year End | H22: <-- Analyst to enter
A23: COMPANY_TYPE | C23: Input | E23: Consolidated/Standalone | H23: <-- Analyst to enter
A24: BSE_SENSEX | C24: Calculated | E24: BSE Sensex | H24: <-- Use EQUIDATA
A25: INR CURNCY | C25: Calculated | E25: Exchange rate (Rs:USD) | H25: <-- Use EQUIDATA
A26: FIFTY_TWO_WEEK_HIGH | C26: Calculated | E26: 52-week High | G26: {=_xll.EQUIDATA($G$12,$A26,"private")} -> 349 | H26: <-- Use EQUIDATA
A27: FIFTY_TWO_WEEK_LOW | C27: Calculated | E27: 52-week Low | G27: {=_xll.EQUIDATA($G$12,$A27,"private")} -> 233.42 | H27: <-- Use EQUIDATA
A28: CURR_MKT_CAP_RS | C28: Calculated | E28: Current Market cap | G28: =NewFinSumm!I76 -> 731745 | H28: <-- Use EQUIDATA
A29: CURR_MKT_CAP_USD | C29: Calculated | E29: Current Market cap USD | G29: {=_xll.EQUIDATA($G$12,$A29,"private")} -> 6982.3877 | H29: <-- Use EQUIDATA
A30: TABLE1_SCALE | C30: Input | E30: Financial Summary (scale) | G30: Rs mn
A31: TABLE2_SCALE | C31: Input | E31: Income Statement (scale) | G31: Rs mn
A32: TABLE3_SCALE | C32: Input | E32: Balance Sheet (scale) | G32: Rs mn
A33: TABLE4_SCALE | C33: Input | E33: Cash Flow (scale) | G33: Rs mn
A34: TABLE5_SCALE | C34: Input | E34: Old vs. New Table (scale) | G34: Rs mn
E37: Profit & Loss statement
A38: IS_GR_SALES | B38: =IF(IF(D38="+",MIN(H38:IU38)>=0,IF(D38="-",MAX(H38:IU38)<=0,TRUE)),"",1) | C38: Input | D38: + | E38: Gross Sales | F38: mn
A39: IS_DUTIES | B39: =IF(IF(D39="+",MIN(H39:IU39)>=0,IF(D39="-",MAX(H39:IU39)<=0,TRUE)),"",1) | C39: Input | D39: + | E39: Less: Duties | F39: mn
A40: IS_NET_SALES | C40: Calculated | D40: ● | E40: Net Sales | F40: mn
A41: IS_NET_SALES_USD | B41: =IF(IF(D41="+",MIN(H41:IU41)>=0,IF(D41="-",MAX(H41:IU41)<=0,TRUE)),"",1) | C41: Input | D41: + | E41: Net Sales ($) | F41: mn
A42: IS_OOP_INC | B42: =IF(IF(D42="+",MIN(H42:IU42)>=0,IF(D42="-",MAX(H42:IU42)<=0,TRUE)),"",1) | C42: Input | D42: + | E42: Other Operating Income | F42: mn
A43: IS_TTL_REV | C43: Calculated | D43: ● | E43: Total Revenue | F43: mn | H43: =H40 -> 0 | I43: =I40 -> 0 | J43: =J40 -> 0 | K43: =K40 -> 0 | L43: =L40 -> 0 | M43: =M40 -> 0 | N43: =N40 -> 0 | O43: =O40 -> 0 | ... AM43: =AM40 -> 0 | AN43: =Qtrly!I68 -> 8197 | AO43: =Qtrly!J68 -> 6620 | AP43: =Qtrly!K68 -> 7977.3 | AQ43: =Qtrly!L68 -> 9153 | AR43: =Qtrly!M68 -> 8781 | AS43: =Qtrly!N68 -> 8483.1 | AT43: =Qtrly!O68 -> 9401.1 | AU43: =Qtrly!P68 -> 10963.8 | ... BB43: =Qtrly!W68 -> 13496.6
A44: IS_RAW_MATERIALS | B44: =IF(IF(D44="+",MIN(H44:IU44)>=0,IF(D44="-",MAX(H44:IU44)<=0,TRUE)),"",1) | C44: Input | D44: + | E44: Raw material expenses | F44: mn
A45: IS_DIRECT_EXP | B45: =IF(IF(D45="+",MIN(H45:IU45)>=0,IF(D45="-",MAX(H45:IU45)<=0,TRUE)),"",1) | C45: Input | D45: + | E45: Direct /Employee Costs | F45: mn
A46: IS_GROSS_PRFT | C46: Calculated | D46: ● | E46: Gross Profit | F46: mn
A47: IS_EMPL_EXP | B47: =IF(IF(D47="+",MIN(H47:IU47)>=0,IF(D47="-",MAX(H47:IU47)<=0,TRUE)),"",1) | C47: Input | D47: + | E47: Employee Expenses | F47: mn | AN47: =Qtrly!I72 -> 454.1 | AO47: =Qtrly!J72 -> 431.3 | AP47: =Qtrly!K72 -> 497.4 | AQ47: =Qtrly!L72 -> 916.7 | AR47: =Qtrly!M72 -> 689.2 | AS47: =Qtrly!N72 -> 707.1 | AT47: =Qtrly!O72 -> 694.6 | AU47: =Qtrly!P72 -> 717.9 | ... BB47: =Qtrly!W72 -> 562.3
A48: IS_PROM_EXP | B48: =IF(IF(D48="+",MIN(H48:IU48)>=0,IF(D48="-",MAX(H48:IU48)<=0,TRUE)),"",1) | C48: Input | D48: + | E48: Promotion Expenses | F48: mn
A49: IS_FND_EXP | B49: =IF(IF(D49="+",MIN(H49:IU49)>=0,IF(D49="-",MAX(H49:IU49)<=0,TRUE)),"",1) | C49: Input | D49: + | E49: Freight & Distribution Expenses | F49: mn
A50: IS_REPAIR_MAIN | B50: =IF(IF(D50="+",MIN(H50:IU50)>=0,IF(D50="-",MAX(H50:IU50)<=0,TRUE)),"",1) | C50: Input | D50: + | E50: Repairs & maintenance | F50: mn
A51: IS_RENT | B51: =IF(IF(D51="+",MIN(H51:IU51)>=0,IF(D51="-",MAX(H51:IU51)<=0,TRUE)),"",1) | C51: Input | D51: + | E51: Rent | F51: mn
A52: IS_POWER_FUEL | B52: =IF(IF(D52="+",MIN(H52:IU52)>=0,IF(D52="-",MAX(H52:IU52)<=0,TRUE)),"",1) | C52: Input | D52: + | E52: Power & fuel | F52: mn
A53: IS_RD_EXPENSE | B53: =IF(IF(D53="+",MIN(H53:IU53)>=0,IF(D53="-",MAX(H53:IU53)<=0,TRUE)),"",1) | C53: Input | D53: + | E53: R&D Expense | F53: mn
A54: IS_PROV | B54: =IF(IF(D54="+",MIN(H54:IU54)>=0,IF(D54="-",MAX(H54:IU54)<=0,TRUE)),"",1) | C54: Input | D54: + | E54: Provisions | F54: mn
A55: IS_FND_EXP | B55: =IF(IF(D55="+",MIN(H55:IU55)>=0,IF(D55="-",MAX(H55:IU55)<=0,TRUE)),"",1) | C55: Input | D55: + | E55: Royalty | F55: mn
A56: IS_OOP_EXP | B56: =IF(IF(D56="+",MIN(H56:IU56)>=0,IF(D56="-",MAX(H56:IU56)<=0,TRUE)),"",1) | C56: Input | D56: + | E56: Other Operating Expenses | F56: mn | AN56: =+Qtrly!I71+Qtrly!I73 -> 3433 | AO56: =+Qtrly!J71+Qtrly!J73 -> 2779.1 | AP56: =+Qtrly!K71+Qtrly!K73 -> 3715.6 | AQ56: =+Qtrly!L71+Qtrly!L73 -> 3518.3 | AR56: =+Qtrly!M71+Qtrly!M73 -> 3540.9 | AS56: =+Qtrly!N71+Qtrly!N73 -> 3254.3 | AT56: =+Qtrly!O71+Qtrly!O73 -> 3907.6 | AU56: =+Qtrly!P71+Qtrly!P73 -> 4434.1 | ... BB56: =+Qtrly!W71+Qtrly!W73 -> 6497.3
A57: IS_TTL_EXP | C57: Calculated | D57: ● | E57: Total Operating Expenses | F57: mn | H57: =+SUM(H47:H56) -> 0 | I57: =+SUM(I47:I56) -> 0 | J57: =+SUM(J47:J56) -> 0 | K57: =+SUM(K47:K56) -> 0 | L57: =+SUM(L47:L56) -> 0 | M57: =+SUM(M47:M56) -> 0 | N57: =+SUM(N47:N56) -> 0 | O57: =+SUM(O47:O56) -> 0 | ... BB57: =+SUM(BB47:BB56) -> 7059.6
A58: EBITDA | C58: Calculated | D58: ● | E58: EBITDA | F58: mn | H58: =+H43-H57 -> 0 | I58: =+I43-I57 -> 0 | J58: =+J43-J57 -> 0 | K58: =+K43-K57 -> 0 | L58: =+L43-L57 -> 0 | M58: =+M43-M57 -> 0 | N58: =+N43-N57 -> 0 | O58: =+O43-O57 -> 0 | ... BB58: =+BB43-BB57 -> 6437
A59: IS_DEP | B59: =IF(IF(D59="+",MIN(H59:IU59)>=0,IF(D59="-",MAX(H59:IU59)<=0,TRUE)),"",1) | C59: Input | D59: + | E59: Depreciation | F59: mn | AN59: =Qtrly!I81 -> 916.7 | AO59: =Qtrly!J81 -> 992.7 | AP59: =Qtrly!K81 -> 1023 | AQ59: =Qtrly!L81 -> 979.9 | AR59: =Qtrly!M81 -> 947.4 | AS59: =Qtrly!N81 -> 1005.1 | AT59: =Qtrly!O81 -> 1075.8 | AU59: =Qtrly!P81 -> 1336.5 | ... BB59: =Qtrly!W81 -> 1639.8
A60: IS_AMRT | B60: =IF(IF(D60="+",MIN(H60:IU60)>=0,IF(D60="-",MAX(H60:IU60)<=0,TRUE)),"",1) | C60: Input | D60: + | E60: Amortisation | F60: mn
A61: IS_TTL_DNA | C61: Calculated | D61: ● | E61: Total D&A | F61: mn | H61: =+H59+H60 -> 0 | I61: =+I59+I60 -> 0 | J61: =+J59+J60 -> 0 | K61: =+K59+K60 -> 0 | L61: =+L59+L60 -> 0 | M61: =+M59+M60 -> 0 | N61: =+N59+N60 -> 0 | O61: =+O59+O60 -> 0 | ... BB61: =+BB59+BB60 -> 1639.8
A62: IS_EBIT | C62: Calculated | D62: ● | E62: EBIT | F62: mn | H62: =+H58-H61 -> 0 | I62: =+I58-I61 -> 0 | J62: =+J58-J61 -> 0 | K62: =+K58-K61 -> 0 | L62: =+L58-L61 -> 0 | M62: =+M58-M61 -> 0 | N62: =+N58-N61 -> 0 | O62: =+O58-O61 -> 0 | ... BB62: =+BB58-BB61 -> 4797.2
A63: IS_INT_INC | B63: =IF(IF(D63="+",MIN(H63:IU63)>=0,IF(D63="-",MAX(H63:IU63)<=0,TRUE)),"",1) | C63: Input | D63: + | E63: Interest Income | F63: mn
A64: IS_INT_EXP | B64: =IF(IF(D64="+",MIN(H64:IU64)>=0,IF(D64="-",MAX(H64:IU64)<=0,TRUE)),"",1) | C64: Input | D64: ± | E64: Interest Expenses | F64: mn | AN64: =+Qtrly!I85+Qtrly!I86 -> 1398.4 | AO64: =+Qtrly!J85+Qtrly!J86 -> 1091.6 | AP64: =+Qtrly!K85+Qtrly!K86 -> 2108.1 | AQ64: =+Qtrly!L85+Qtrly!L86 -> 1362.8 | AR64: =+Qtrly!M85+Qtrly!M86 -> -157.5 | AS64: =+Qtrly!N85+Qtrly!N86 -> 706.7 | AT64: =+Qtrly!O85+Qtrly!O86 -> 1434.5 | AU64: =+Qtrly!P85+Qtrly!P86 -> 1340.8 | ... BB64: =+Qtrly!W85+Qtrly!W86 -> 930.3
A65: IS_NET_NET | C65: Calculated | D65: ● | E65: Net Interest | F65: mn | H65: =+H63+H64 -> 0 | I65: =+I63+I64 -> 0 | J65: =+J63+J64 -> 0 | K65: =+K63+K64 -> 0 | L65: =+L63+L64 -> 0 | M65: =+M63+M64 -> 0 | N65: =+N63+N64 -> 0 | O65: =+O63+O64 -> 0 | ... BB65: =+BB63+BB64 -> 930.3
A66: IS_OTHR_NOP_INC | B66: =IF(IF(D66="+",MIN(H66:IU66)>=0,IF(D66="-",MAX(H66:IU66)<=0,TRUE)),"",1) | C66: Input | D66: + | E66: Other Non Operating Income | F66: mn | AN66: =Qtrly!I80 -> 414.2 | AO66: =Qtrly!J80 -> 345.1 | AP66: =Qtrly!K80 -> 442.9 | AQ66: =Qtrly!L80 -> 579 | AR66: =Qtrly!M80 -> 401.3 | AS66: =Qtrly!N80 -> 471.7 | AT66: =Qtrly!O80 -> 781.9 | AU66: =Qtrly!P80 -> 1039.2 | ... BB66: =Qtrly!W80 -> 597.2
A67: IS_EXCPT_ITEM | B67: =IF(IF(D67="+",MIN(H67:IU67)>=0,IF(D67="-",MAX(H67:IU67)<=0,TRUE)),"",1) | C67: Input | D67: ± | E67: Exceptional Items | F67: mn | AN67: =-Qtrly!I89 -> 0 | AO67: =-Qtrly!J89 -> 0 | AP67: =-Qtrly!K89 -> 0 | AQ67: =-Qtrly!L89 -> 0 | AR67: =-Qtrly!M89 -> 0 | AS67: =-Qtrly!N89 -> 0 | AT67: =-Qtrly!O89 -> 0 | AU67: =-Qtrly!P89 -> 0 | ... BB67: =-Qtrly!W89 -> -72.4
A68: IS_RPBT | C68: Calculated | D68: ● | E68: Reported PBT | F68: mn | H68: =+H62-H65+H66+H67 -> 0 | I68: =+I62-I65+I66+I67 -> 0 | J68: =+J62-J65+J66+J67 -> 0 | K68: =+K62-K65+K66+K67 -> 0 | L68: =+L62-L65+L66+L67 -> 0 | M68: =+M62-M65+M66+M67 -> 0 | N68: =+N62-N65+N66+N67 -> 0 | O68: =+O62-O65+O66+O67 -> 0 | ... BB68: =+BB62-BB65+BB66+BB67 -> 4391.7
A69: IS_APBT | C69: Calculated | D69: ● | E69: Adjusted PBT | F69: mn | H69: =+H68-H67 -> 0 | I69: =+I68-I67 -> 0 | J69: =+J68-J67 -> 0 | K69: =+K68-K67 -> 0 | L69: =+L68-L67 -> 0 | M69: =+M68-M67 -> 0 | N69: =+N68-N67 -> 0 | O69: =+O68-O67 -> 0 | ... BB69: =+BB68-BB67 -> 4464.1
A70: IS_CURR_TAX | B70: =IF(IF(D70="+",MIN(H70:IU70)>=0,IF(D70="-",MAX(H70:IU70)<=0,TRUE)),"",1) | C70: Input | D70: + | E70: Current Tax | F70: mn
A71: IS_DEF_TAX | B71: =IF(IF(D71="+",MIN(H71:IU71)>=0,IF(D71="-",MAX(H71:IU71)<=0,TRUE)),"",1) | C71: Input | D71: ± | E71: Deferred Tax | F71: mn
A72: IS_OTHR_ADJ | B72: =IF(IF(D72="+",MIN(H72:IU72)>=0,IF(D72="-",MAX(H72:IU72)<=0,TRUE)),"",1) | C72: Input | D72: ± | E72: Other Adjustments | F72: mn
A73: IS_TTL_TAX | C73: Calculated | D73: ● | E73: Total Tax | F73: mn | AN73: =Qtrly!I93 -> 483.5 | AO73: =Qtrly!J93 -> 287.5 | AP73: =Qtrly!K93 -> -87.7 | AQ73: =Qtrly!L93 -> -68.3 | AR73: =Qtrly!M93 -> 902.9 | AS73: =Qtrly!N93 -> 722.9 | AT73: =Qtrly!O93 -> 534.8 | AU73: =Qtrly!P93 -> 882.9 | ... BB73: =Qtrly!W93 -> 743.2
A74: IS_PAT | C74: Calculated | D74: ● | E74: Profit After Tax | F74: mn | H74: =+H68-H73 -> 0 | I74: =+I68-I73 -> 0 | J74: =+J68-J73 -> 0 | K74: =+K68-K73 -> 0 | L74: =+L68-L73 -> 0 | M74: =+M68-M73 -> 0 | N74: =+N68-N73 -> 0 | O74: =+O68-O73 -> 0 | ... BB74: =+BB68-BB73 -> 3648.5
A75: IS_EXT_ITEM | B75: =IF(IF(D75="+",MIN(H75:IU75)>=0,IF(D75="-",MAX(H75:IU75)<=0,TRUE)),"",1) | C75: Input | D75: ± | E75: Extra Ordinary Items | F75: mn
A76: IS_MIN_INT | B76: =IF(IF(D76="+",MIN(H76:IU76)>=0,IF(D76="-",MAX(H76:IU76)<=0,TRUE)),"",1) | C76: Input | D76: ± | E76: Minority Interest | F76: mn | AN76: =Qtrly!I97 -> 27.3 | AO76: =Qtrly!J97 -> 36.5 | AP76: =Qtrly!K97 -> 14.9 | AQ76: =Qtrly!L97 -> 18.2 | AR76: =Qtrly!M97 -> 13.2 | AS76: =Qtrly!N97 -> 14.7 | AT76: =Qtrly!O97 -> 29.1 | AU76: =Qtrly!P97 -> -9.3 | ... BB76: =Qtrly!W97 -> 57.5
A77: IS_ASSOCIATES | B77: =IF(IF(D77="+",MIN(H77:IU77)>=0,IF(D77="-",MAX(H77:IU77)<=0,TRUE)),"",1) | C77: Input | D77: ± | E77: Profit / (Loss) from Associates | F77: mn
A78: IS_RPAT | C78: Calculated | D78: ● | E78: Reported PAT after M.I. | F78: mn | H78: =+H74-H76+H77 -> 0 | I78: =+I74-I76+I77 -> 0 | J78: =+J74-J76+J77 -> 0 | K78: =+K74-K76+K77 -> 0 | L78: =+L74-L76+L77 -> 0 | M78: =+M74-M76+M77 -> 0 | N78: =+N74-N76+N77 -> 0 | O78: =+O74-O76+O77 -> 0 | ... BB78: =+BB74-BB76+BB77 -> 3591
A79: IS_APAT | C79: Calculated | D79: ● | E79: Adjusted PAT after M.I. | F79: mn | H79: =+H78-H67 -> 0 | I79: =+I78-I67 -> 0 | J79: =+J78-J67 -> 0 | K79: =+K78-K67 -> 0 | L79: =+L78-L67 -> 0 | M79: =+M78-M67 -> 0 | N79: =+N78-N67 -> 0 | O79: =+O78-O67 -> 0 | ... BB79: =+BB78-BB67 -> 3663.4
A80: IS_DIVIDEND | B80: =IF(IF(D80="+",MIN(H80:IU80)>=0,IF(D80="-",MAX(H80:IU80)<=0,TRUE)),"",1) | C80: Input | D80: + | E80: Total dividends | F80: mn
A81: NO_SHARES | B81: =IF(IF(D81="+",MIN(H81:IU81)>=0,IF(D81="-",MAX(H81:IU81)<=0,TRUE)),"",1) | C81: Input | D81: + | E81: Shares Outstanding (Wt Avg) | F81: mn | N81: 0
A82: FD_SH_OUT | B82: =IF(IF(D82="+",MIN(H82:IU82)>=0,IF(D82="-",MAX(H82:IU82)<=0,TRUE)),"",1) | C82: Input | D82: + | E82: Fully Diluted Shares Outstanding (Wt Avg) | F82: mn | N82: =N81 -> 0
E84: Balance Sheet
E85: Sources Of Funds
E86: Shareholders' Equity
A87: BS_SHRE_CAP | B87: =IF(IF(D87="+",MIN(H87:IU87)>=0,IF(D87="-",MAX(H87:IU87)<=0,TRUE)),"",1) | C87: Input | D87: + | E87: Paid up Capital | F87: mn
A88: BS_EMPL_STCK_OPT | B88: =IF(IF(D88="+",MIN(H88:IU88)>=0,IF(D88="-",MAX(H88:IU88)<=0,TRUE)),"",1) | C88: Input | D88: + | E88: Employee Stock Options | F88: mn
A89: BS_TTL_RES_SURP | C89: Calculated | D89: ● | E89: Reserves & Surplus | F89: mn
A90: BS_TRFR_PL_AC | B90: =IF(IF(D90="+",MIN(H90:IU90)>=0,IF(D90="-",MAX(H90:IU90)<=0,TRUE)),"",1) | C90: Input | D90: + | E90: Trfr P&L A/c | F90: mn
A91: BS_SH_PREM_RES | B91: =IF(IF(D91="+",MIN(H91:IU91)>=0,IF(D91="-",MAX(H91:IU91)<=0,TRUE)),"",1) | C91: Input | D91: + | E91: Share Premium Reserve | F91: mn
A92: BS_GEN_RES | B92: =IF(IF(D92="+",MIN(H92:IU92)>=0,IF(D92="-",MAX(H92:IU92)<=0,TRUE)),"",1) | C92: Input | D92: + | E92: General Reserve | F92: mn
A93: BS_FTA_RES | B93: =IF(IF(D93="+",MIN(H93:IU93)>=0,IF(D93="-",MAX(H93:IU93)<=0,TRUE)),"",1) | C93: Input | D93: ± | E93: Foreign Transaction Reserve | F93: mn
A94: BS_OTHR_RES | B94: =IF(IF(D94="+",MIN(H94:IU94)>=0,IF(D94="-",MAX(H94:IU94)<=0,TRUE)),"",1) | C94: Input | D94: ± | E94: Other Reserves | F94: mn
A95: BS_TTL_SH_EQTY | C95: Calculated | D95: ● | E95: Total Shareholders' Equity / Networth | F95: mn
A96: BS_MIN_INT | B96: =IF(IF(D96="+",MIN(H96:IU96)>=0,IF(D96="-",MAX(H96:IU96)<=0,TRUE)),"",1) | C96: Input | D96: + | E96: Minority Interest | F96: mn
A97: BS_TTL_SH_EQTY_MINT | C97: Calculated | D97: ● | E97: Total Shareholders' Equity After MI | F97: mn
A98: BS_TTL_BORROW | C98: Calculated | D98: ● | E98: Total Borrowings | F98: mn
A99: BS_LTD | B99: =IF(IF(D99="+",MIN(H99:IU99)>=0,IF(D99="-",MAX(H99:IU99)<=0,TRUE)),"",1) | C99: Input | D99: + | E99: Long Term Borrowings | F99: mn
A100: BS_STD | B100: =IF(IF(D100="+",MIN(H100:IU100)>=0,IF(D100="-",MAX(H100:IU100)<=0,TRUE)),"",1) | C100: Input | D100: + | E100: Short Term Borrowings | F100: mn
A101: BS_LEASE_LIB | B101: =IF(IF(D101="+",MIN(H101:IU101)>=0,IF(D101="-",MAX(H101:IU101)<=0,TRUE)),"",1) | C101: Input | D101: + | E101: Lease Liability | F101: mn
A102: BS_DEF_TAX_LIAB | B102: =IF(IF(D102="+",MIN(H102:IU102)>=0,IF(D102="-",MAX(H102:IU102)<=0,TRUE)),"",1) | C102: Input | D102: + | E102: Deferred Tax Liability | F102: mn
A103: BS_LT_PROV | B103: =IF(IF(D103="+",MIN(H103:IU103)>=0,IF(D103="-",MAX(H103:IU103)<=0,TRUE)),"",1) | C103: Input | D103: + | E103: Long Term Provisions | F103: mn
...

Sheet NewFinSumm
B2: Consolidated Financial Statements
B3: Rs. mn | C3: FY18 | D3: FY19 | E3: FY20 | F3: FY21 | G3: FY22 | H3: FY23 | I3: FY24 | J3: FY25 | K3: FY26 | L3: FY27E | M3: FY28E | N3: FY29E | O3: FY30E
B4: Profit & Loss
B5: Revenue | C5: =Consol!G16 -> 9980.936 | D5: =Consol!H16 -> 10802.602 | E5: =Consol!I16 -> 11431.453 | F5: =Consol!J16 -> 16035.705 | G5: =Consol!K16 -> 22730.588 | H5: =Consol!L16 -> 31947.396 | I5: =Consol!M16 -> 37628.9 | J5: =Consol!N16 -> 44761.4 | ... O5: =Consol!S16 -> 188550.74 | P5: =(N5/J5)^(1/4)-1 -> 0.34007521
B6: Gross profit
B7: EBITDA | C7: =Consol!G23 -> 5878.356 | D7: =Consol!H23 -> 6121.407 | E7: =Consol!I23 -> 6191.962 | F7: =Consol!J23 -> 8164.395 | G7: =Consol!K23 -> 11094.308 | H7: =Consol!L23 -> 16201.896 | I7: =Consol!M23 -> 19645.6 | J7: =Consol!N23 -> 22621.8 | ... O7: =Consol!S23 -> 75506.814 | P7: =(N7/J7)^(1/4)-1 -> 0.26520921
B8: Depreciation | C8: =Consol!G28 -> 1571.402 | D8: =Consol!H28 -> 2524.951 | E8: =Consol!I28 -> 2018.573 | F8: =Consol!J28 -> 2706.55 | G8: =Consol!K28 -> 3695.05 | H8: =Consol!L28 -> 3912.23 | I8: =Consol!M28 -> 4364.8 | J8: =Consol!N28 -> 5465.5 | ... O8: =Consol!S28 -> 24495.596
B9: EBIT | C9: =C7-C8 -> 4306.954 | D9: =D7-D8 -> 3596.456 | E9: =E7-E8 -> 4173.389 | F9: =F7-F8 -> 5457.845 | G9: =G7-G8 -> 7399.258 | H9: =H7-H8 -> 12289.666 | I9: =I7-I8 -> 15280.8 | J9: =J7-J8 -> 17156.3 | ... O9: =O7-O8 -> 51011.218
B10: Other Income | C10: =Consol!G27 -> 766.755 | D10: =Consol!H27 -> 1013.331 | E10: =Consol!I27 -> 942.207 | F10: =Consol!J27 -> 746.93 | G10: =Consol!K27 -> 1056.79 | H10: =Consol!L27 -> 1781.13 | I10: =Consol!M27 -> 2694.1 | J10: =Consol!N27 -> 3529.5 | ... O10: =Consol!S27 -> 1594.2853
B11: Interest expense | C11: =Consol!G32 -> 1298.942 | D11: =Consol!H32 -> 1771.365 | E11: =Consol!I32 -> 2774.583 | F11: =Consol!J32 -> 2278.57 | G11: =Consol!K32 -> 4196.22 | H11: =Consol!L32 -> 5960.8 | I11: =Consol!M32 -> 3324.6 | J11: =Consol!N32 -> 2657.4 | ... O11: =Consol!S32 -> 15540.225 | P11: =(N11/J11)^(1/4)-1 -> 0.42414851
B12: Exceptional items | C12: =Consol!G33 -> 0 | D12: =Consol!H33 -> 0 | E12: =Consol!I33 -> 0 | F12: =Consol!J33 -> 0 | G12: =Consol!K33 -> 0 | H12: =Consol!L33 -> 0 | I12: =Consol!M33 -> 0 | J12: =Consol!N33 -> 0 | ... O12: =Consol!S33 -> 0
B13: PBT | C13: =Consol!G35 -> 3774.767 | D13: =Consol!H35 -> 2838.422 | E13: =Consol!I35 -> 2341.013 | F13: =Consol!J35 -> 3926.205 | G13: =Consol!K35 -> 4259.828 | H13: =Consol!L35 -> 8109.996 | I13: =Consol!M35 -> 14650.3 | J13: =Consol!N35 -> 18028.4 | ... O13: =Consol!S35 -> 37065.278
B14: Reported PAT (after minority interest) | C14: =Consol!G49 -> 2808.137 | D14: =Consol!H49 -> 2667.244 | E14: =Consol!I49 -> 1904.241 | F14: =Consol!J49 -> 2913.855 | G14: =Consol!K49 -> 3279.458 | H14: =Consol!L49 -> 7398.376 | I14: =Consol!M49 -> 11559.1 | J14: =Consol!N49 -> 15030.8 | ... O14: =Consol!S49 -> 27948.574
B15: Adj PAT | C15: =C14+C12 -> 2808.137 | D15: =D14+D12 -> 2667.244 | E15: =E14+E12 -> 1904.241 | F15: =F14+F12 -> 2913.855 | G15: =G14+G12 -> 3279.458 | H15: =H14+H12 -> 7398.376 | I15: =I14+I12 -> 11559.1 | J15: =J14+J12 -> 15030.8 | ... O15: =O14+O12 -> 27948.574
B16: EPS (Rs.) | C16: =C15/C75 -> 1.3372081 | D16: =D15/D75 -> 1.2701162 | E16: =E15/E75 -> 0.90678143 | F16: =F15/F75 -> 1.38755 | G16: =G15/G75 -> 1.5616467 | H16: =H15/H75 -> 3.5230362 | I16: =I15/I75 -> 5.5043333 | J16: =J15/J75 -> 7.1575238 | ... O16: =O15/O75 -> 11.995096 | P16: =(N16/J16)^(1/4)-1 -> 0.1003218
B17: Balance Sheet | I17: =+I15/H15-1 -> 0.56238342 | J17: =+J16/I16-1 -> 0.30034345 | K17: =+K16/J16-1 -> 0.066503446 | S17: Total Share count (Mn) | T17: =Valuation!$C$3 -> 2330
B18: Net Worth | C18: =Consol!G65+Consol!G66+Consol!G69 -> 28048.97 | D18: =Consol!H65+Consol!H66+Consol!H69 -> 30847.183 | E18: =Consol!I65+Consol!I66+Consol!I69 -> 27513.163 | F18: =Consol!J65+Consol!J66+Consol!J69 -> 30884.31 | G18: =Consol!K65+Consol!K66+Consol!K69 -> 34718.77 | H18: =Consol!L65+Consol!L66+Consol!L69 -> 40888.73 | I18: =Consol!M65+Consol!M66+Consol!M69 -> 82310.2 | J18: =Consol!N65+Consol!N66+Consol!N69 -> 104887 | ... O18: =Consol!S65+Consol!S66+Consol!S69 -> 267222.74
B19: Total debt | C19: =Consol!G78 -> 16799.911 | D19: =Consol!H78 -> 20001.206 | E19: =Consol!I78 -> 27167.16 | F19: =Consol!J78 -> 39458.18 | G19: =Consol!K78 -> 44086.94 | H19: =Consol!L78 -> 42436.98 | I19: =Consol!M78 -> 43806.8 | J19: =Consol!N78 -> 46588.3 | ... O19: =Consol!S78 -> 153554.57
B20: Other liabilities and provisions | C20: =Consol!G79+Consol!G80+Consol!G81+Consol!G111+Consol!G112 -> 6182.269 | D20: =Consol!H79+Consol!H80+Consol!H81+Consol!H111+Consol!H112 -> 7355.923 | E20: =Consol!I79+Consol!I80+Consol!I81+Consol!I111+Consol!I112 -> 13119.782 | F20: =Consol!J79+Consol!J80+Consol!J81+Consol!J111+Consol!J112 -> 10051.65 | G20: =Consol!K79+Consol!K80+Consol!K81+Consol!K111+Consol!K112 -> 12741 | H20: =Consol!L79+Consol!L80+Consol!L81+Consol!L111+Consol!L112 -> 8165.01 | I20: =Consol!M79+Consol!M80+Consol!M81+Consol!M111+Consol!M112 -> 8596.4 | J20: =Consol!N79+Consol!N80+Consol!N81+Consol!N111+Consol!N112 -> 14316.1 | ... O20: =Consol!S79+Consol!S80+Consol!S81+Consol!S111+Consol!S112 -> 18813.7 | S20: CRYSTAL BALL GAZING
B21: Total Networth and liabilities | C21: =SUM(C18:C20) -> 51031.15 | D21: =SUM(D18:D20) -> 58204.312 | E21: =SUM(E18:E20) -> 67800.105 | F21: =SUM(F18:F20) -> 80394.14 | G21: =SUM(G18:G20) -> 91546.71 | H21: =SUM(H18:H20) -> 91490.72 | I21: =SUM(I18:I20) -> 134713.4 | J21: =SUM(J18:J20) -> 165791.4 | ... O21: =SUM(O18:O20) -> 439591.01
B22: Gross Fixed assets | C22: =Consol!G87 -> 29525.534 | D22: =Consol!H87 -> 32684.214 | E22: =Consol!I87 -> 41579.557 | F22: =Consol!J87 -> 44786.871 | G22: =Consol!K87 -> 47405.001 | H22: =Consol!L87 -> 48886.498 | I22: =Consol!M87 -> 64231 | J22: =Consol!N87 -> 84934.2 | ... O22: =Consol!S87 -> 438250.33 | S22: Consolidated | V22: FY20-FY25 | W22: FY25-FY30E | AB22: Valuation Table
B23: Net fixed assets | C23: =Consol!G89 -> 27368.261 | D23: =Consol!H89 -> 29180.329 | E23: =Consol!I89 -> 36437.466 | F23: =Consol!J89 -> 36938.23 | G23: =Consol!K89 -> 38712.123 | H23: =Consol!L89 -> 38451.017 | I23: =Consol!M89 -> 51128.1 | J23: =Consol!N89 -> 68131.7 | ... O23: =Consol!S89 -> 352488.2 | S23: Revenues CAGR | V23: =(J5/E5)^(1/5)-1 -> 0.31389435 | W23: =(O5/J5)^(1/5)-1 -> 0.3332295 | AB23: Business | AC23: EV/EBITDA Multiple | AD23: FY29E EBITDA (Rs. bn) | AE23: Equity Value (Rs/share)
B24: Capital work-in-progress | C24: =Consol!G90+Consol!G94 -> 6326.228 | D24: =Consol!H90+Consol!H94 -> 8619.909 | E24: =Consol!I90+Consol!I94 -> 7515.751 | F24: =Consol!J90+Consol!J94 -> 11250.46 | G24: =Consol!K90+Consol!K94 -> 796.81 | H24: =Consol!L90+Consol!L94 -> 460.13 | I24: =Consol!M90+Consol!M94 -> 1320.4 | J24: =Consol!N90+Consol!N94 -> 20202.4 | ... O24: =Consol!S90+Consol!S94 -> 410.2 | S24: EBITDA CAGR | V24: =(J7/E7)^(1/5)-1 -> 0.29580537 | W24: =(O7/J7)^(1/5)-1 -> 0.27259964 | AB24: Ports | AC24: 15 | AD24: =Consol!$S$23/1000 -> 75.506814 | AE24: =AD24*AC24*1000/$T$17 -> 486.09537
B25: Intangible Assets | C25: =Consol!G93 -> 3671.532 | D25: =Consol!H93 -> 3384.563 | E25: =Consol!I93 -> 3042.448 | F25: =Consol!J93 -> 12301.71 | G25: =Consol!K93 -> 22626.79 | H25: =Consol!L93 -> 21294.55 | I25: =Consol!M93 -> 26446.4 | J25: =Consol!N93 -> 25797.6 | ... O25: =Consol!S93 -> 30357.4 | S25: EBITDA margin | V25: =AVERAGE(E57:J57) -> 0.51224905 | W25: =AVERAGE(J57:O57) -> 0.43907948 | AB25: Ports | AC25: 20 | AD25: =Consol!$S$23/1000 -> 75.506814 | AE25: =AD25*AC25*1000/$T$17 -> 648.12716
B26: Investments | C26: =Consol!G96+Consol!G102 -> 283.762 | D26: =Consol!H96+Consol!H102 -> 2297.624 | E26: =Consol!I96+Consol!I102 -> 3764.403 | F26: =Consol!J96+Consol!J102 -> 2955.08 | G26: =Consol!K96+Consol!K102 -> 2830.08 | H26: =Consol!L96+Consol!L102 -> 3070.28 | I26: =Consol!M96+Consol!M102 -> 2444.9 | J26: =Consol!N96+Consol!N102 -> 3127.6 | ... O26: =Consol!S96+Consol!S102 -> 1218.4 | S26: EPS CAGR | V26: =(J15/E15)^(1/5)-1 -> 0.51165274 | W26: =(O16/J16)^(1/5)-1 -> 0.10878716
B27: Cash and bank balances | C27: =Consol!G105 -> 3284.496 | D27: =Consol!H105 -> 1017.636 | E27: =Consol!I105 -> 1626.074 | F27: =Consol!J105 -> 2648.4 | G27: =Consol!K105 -> 10382.35 | H27: =Consol!L105 -> 16316.43 | I27: =Consol!M105 -> 40902.2 | J27: =Consol!N105 -> 24820.7 | ... O27: =Consol!S105 -> 3310.0258 | S27: Total Asset Turnover (x) | V27: =AVERAGE(E67:J67) -> 0.27365789 | W27: =AVERAGE(J67:O67) -> 0.33530143
B28: Loans & advances and other assets | C28: =Consol!G97+Consol!G98+Consol!G99+Consol!G106+Consol!G107 -> 8212.357 | D28: =Consol!H97+Consol!H98+Consol!H99+Consol!H106+Consol!H107 -> 9113.039 | E28: =Consol!I97+Consol!I98+Consol!I99+Consol!I106+Consol!I107 -> 9939.229 | F28: =Consol!J97+Consol!J98+Consol!J99+Consol!J106+Consol!J107 -> 10642.21 | G28: =Consol!K97+Consol!K98+Consol!K99+Consol!K106+Consol!K107 -> 12079.01 | H28: =Consol!L97+Consol!L98+Consol!L99+Consol!L106+Consol!L107 -> 9868.85 | I28: =Consol!M97+Consol!M98+Consol!M99+Consol!M106+Consol!M107 -> 8148.2 | J28: =Consol!N97+Consol!N98+Consol!N99+Consol!N106+Consol!N107 -> 17776.6 | ... O28: =Consol!S97+Consol!S98+Consol!S99+Consol!S106+Consol!S107 -> 30945.4 | S28: Total WC days | V28: =AVERAGE(E73:J73) -> 72.955676 | W28: =AVERAGE(J73:O73) -> 52.700473 | AB28: Upside calculation
B29: Net working capital | C29: =Consol!G103+Consol!G104-Consol!G110 -> 1884.514 | D29: =Consol!H103+Consol!H104-Consol!H110 -> 4591.213 | E29: =Consol!I103+Consol!I104-Consol!I110 -> 5474.736 | F29: =Consol!J103+Consol!J104-Consol!J110 -> 3658.04 | G29: =Consol!K103+Consol!K104-Consol!K110 -> 4119.6 | H29: =Consol!L103+Consol!L104-Consol!L110 -> 2029.47 | I29: =Consol!M103+Consol!M104-Consol!M110 -> 4323.1 | J29: =Consol!N103+Consol!N104-Consol!N110 -> 5934.7 | ... O29: =Consol!S103+Consol!S104-Consol!S110 -> 20861.383 | S29: Pre-tax OCF/EBITDA (%) | V29: =AVERAGE(E60:J60) -> 1.0424607 | W29: =AVERAGE(J60:O60) -> 0.99781384 | AB29: Entry Price (CMP) | AC29: Rs/share | AD29: =Valuation!C2 -> 348.45
B30: Total assets | C30: =SUM(C23:C29) -> 51031.15 | D30: =SUM(D23:D29) -> 58204.313 | E30: =SUM(E23:E29) -> 67800.107 | F30: =SUM(F23:F29) -> 80394.13 | G30: =SUM(G23:G29) -> 91546.763 | H30: =SUM(H23:H29) -> 91490.727 | I30: =SUM(I23:I29) -> 134713.3 | J30: =SUM(J23:J29) -> 165791.3 | ... O30: =SUM(O23:O29) -> 439591.01 | S30: OCF as a % of IC | V30: =AVERAGE(E61:J61) -> 0.18517911 | W30: =AVERAGE(J61:O61) -> 0.16715751
B31: Capital Employed | C31: =C30-C20 -> 44848.881 | D31: =D30-D20 -> 50848.39 | E31: =E30-E20 -> 54680.325 | F31: =F30-F20 -> 70342.48 | G31: =G30-G20 -> 78805.763 | H31: =H30-H20 -> 83325.717 | I31: =I30-I20 -> 126116.9 | J31: =J30-J20 -> 151475.2 | ... O31: =O30-O20 -> 420777.31 | S31: Net Debt/EBITDA | V31: =AVERAGE(E70:J70) -> 2.3989567 | W31: =AVERAGE(J70:O70) -> 1.5850449 | AB31: Target Price | AC31: Rs/share | AD31: =AE24 -> 486.09537
B32: Invested Capital (CE - cash - CWIP) | C32: =C31-C42-C24 -> 34954.395 | D32: =D31-D42-D24 -> 38913.221 | E32: =E31-E42-E24 -> 44864.097 | F32: =F31-F42-F24 -> 56443.62 | G32: =G31-G42-G24 -> 67626.603 | H32: =H31-H42-H24 -> 63504.247 | I32: =I31-I42-I24 -> 81695.9 | J32: =J31-J42-J24 -> 104854.3 | ... O32: =O31-O42-O24 -> 417036.98 | AB32: Cumulative Dividends | AC32: Rs/share | AD32: =SUM(Consol!P58:R58) -> 3.2854403
B33: Net debt | C33: =C19-C27 -> 13515.415 | D33: =D19-D27 -> 18983.57 | E33: =E19-E27 -> 25541.086 | F33: =F19-F27 -> 36809.78 | G33: =G19-G27 -> 33704.59 | H33: =H19-H27 -> 26120.55 | I33: =I19-I27 -> 2904.6 | J33: =J19-J27 -> 21767.6 | ... O33: =O19-O27 -> 150244.55 | AB33: Total Return | AC33: Rs/share | AD33: =AD31+AD32 -> 489.38081
B34: Cash Flows | S34: Consolidated | V34: =V22 -> FY20-FY25 | W34: =W22 -> FY25-FY30E | AB34: Upside/(Downside) | AC34: % | AD34: =(AD33/AD29-1) -> 0.4044506
B35: Cash flows from Operations (Pre-tax) | C35: =Consol!G138 -> 7018.043 | D35: =Consol!H138 -> 3578.053 | E35: =Consol!I138 -> 2950.405 | F35: =Consol!J138 -> 10562.76 | G35: =Consol!K138 -> 12984.77 | H35: =Consol!L138 -> 19778.84 | I35: =Consol!M138 -> 20507.6 | J35: =Consol!N138 -> 23740.8 | ... O35: =Consol!S138 -> 73742.646 | S35: RoE (%) | V35: =AVERAGE(E62:J62) -> 0.14152918 | W35: =AVERAGE(J62:O62) -> 0.12781053
B36: Cash flows from Operations (post-tax) | C36: =Consol!G141 -> 5999.008 | D36: =Consol!H141 -> 3280.213 | E36: =Consol!I141 -> 2587.043 | F36: =Consol!J141 -> 9901.88 | G36: =Consol!K141 -> 11762.3 | H36: =Consol!L141 -> 17972.27 | I36: =Consol!M141 -> 18032.1 | J36: =Consol!N141 -> 21004.4 | ... O36: =Consol!S141 -> 65588.285 | S36: RoCE (%) | V36: =AVERAGE(E63:J63) -> 0.094519019 | W36: =AVERAGE(J63:O63) -> 0.091140632 | AC36: Mar'24 | AD36: Jun'24 | AE36: Sep'24
B37: Capex + Acquisitions | C37: =Consol!G147+Consol!G151 -> -9378.02 | D37: =Consol!H147+Consol!H151 -> -5518.759 | E37: =Consol!I147+Consol!I151 -> -6737.866 | F37: =Consol!J147+Consol!J151 -> -17226.12 | G37: =Consol!K147+Consol!K151 -> -5090.77 | H37: =Consol!L147+Consol!L151 -> -2793.56 | I37: =Consol!M147+Consol!M151 -> -20711.6 | J37: =Consol!N147+Consol!N151 -> -30400.1 | ... O37: =Consol!S147+Consol!S151 -> -67266.454 | S37: RoIC (%) | V37: =AVERAGE(E64:J64) -> 0.13397606 | W37: =AVERAGE(J64:O64) -> 0.12741382 | AB37: Promoters | AC37: 85.61 | AD37: 85.61 | AE37: 85.61
B38: Free cashflows | C38: =C36+C37 -> -3379.012 | D38: =D36+D37 -> -2238.546 | E38: =E36+E37 -> -4150.823 | F38: =F36+F37 -> -7324.24 | G38: =G36+G37 -> 6671.53 | H38: =H36+H37 -> 15178.71 | I38: =I36+I37 -> -2679.5 | J38: =J36+J37 -> -9395.7 | ... O38: =O36+O37 -> -1678.1693 | S38: Average 1 yr fwd | X38: <From Bloomberg Crystal Ball Gazing file | AB38: FII | AC38: 2.34 | AD38: 4.15 | AE38: 4.2
B39: Free cashflows (post interest costs) | C39: =C38+Consol!G165 -> -4573.664 | D39: =D38+Consol!H165 -> -3460.104 | E39: =E38+Consol!I165 -> -6306.892 | F39: =F38+Consol!J165 -> -9573.66 | G39: =G38+Consol!K165 -> 3050.87 | H39: =H38+Consol!L165 -> 12451.8 | I39: =I38+Consol!M165 -> -5158.4 | J39: =J38+Consol!N165 -> -12460.4 | ... O39: =O38+Consol!S165 -> -17218.394 | S39: PE (x) | AB39: DII | AC39: 3.59 | AD39: 2.74 | AE39: 2.5
B40: Cash flows from Investing | C40: =Consol!G154 -> -10983.644 | D40: =Consol!H154 -> -4948.901 | E40: =Consol!I154 -> -3930.804 | F40: =Consol!J154 -> -16367.94 | G40: =Consol!K154 -> -8013.22 | H40: =Consol!L154 -> -6207.92 | I40: =Consol!M154 -> -42046.8 | J40: =Consol!N154 -> -16968.8 | ... O40: =Consol!S154 -> -67266.454 | S40: EV/EBITDA (x) | AB40: Public | AC40: 6.14 | AD40: 5.79 | AE40: 6.32
B41: Cash flows from Financing | C41: =Consol!G169 -> 5397.38 | D41: =Consol!H169 -> 1398.918 | E41: =Consol!I169 -> 2407.796 | F41: =Consol!J169 -> 6408.57 | G41: =Consol!K169 -> 25.53 | H41: =Consol!L169 -> -10865.62 | I41: =Consol!M169 -> 25038.8 | J41: =Consol!N169 -> -5213.4 | ... O41: =Consol!S169 -> -2404.6212 | S41: PB (x)
B42: Total cash & liquid investments | C42: =C27+Consol!G102 -> 3568.258 | D42: =D27+Consol!H102 -> 3315.26 | E42: =E27+Consol!I102 -> 2300.477 | F42: =F27+Consol!J102 -> 2648.4 | G42: =G27+Consol!K102 -> 10382.35 | H42: =H27+Consol!L102 -> 19361.34 | I42: =I27+Consol!M102 -> 43100.6 | J42: =J27+Consol!N102 -> 26418.5 | ... O42: =O27+Consol!S102 -> 3330.1258 | S42: Peak 1 yr fwd | X42: <From Bloomberg Crystal Ball Gazing file | AB42: Promoter | AC42: =AC37 -> 85.61 | AD42: =AD37 -> 85.61 | AE42: =AE37 -> 85.61
S43: PE (x) | AB43: Institutions | AC43: =AC38+AC39 -> 5.93 | AD43: =AD38+AD39 -> 6.89 | AE43: =AE38+AE39 -> 6.7
S44: EV/EBITDA (x) | AB44: Public | AC44: =100-SUM(AC42:AC43) -> 8.46 | AD44: =100-SUM(AD42:AD43) -> 7.5 | AE44: =100-SUM(AE42:AE43) -> 7.69
S45: PB (x)
C46: =C3 -> FY18 | D46: =D3 -> FY19 | E46: =E3 -> FY20 | F46: =F3 -> FY21 | G46: =G3 -> FY22 | H46: =H3 -> FY23 | I46: =I3 -> FY24 | J46: =J3 -> FY25 | ... O46: =O3 -> FY30E
B47: Key variables (sector specific)
S48: First Page Summary
S50: Rs. mn | T50: Revenue | U50: Revenue growth | V50: EBITDA | W50: Revenue growth | X50: EBITDA Margin | Y50: PAT (Rs. Mn) | Z50: Revenue growth | AA50: EPS (Rs/share) | AB50: P/E | AC50: EV/EBITDA | AD50: RoIC,% (Pre tax) | AE50: RoE(%)
B51: Growth ratios | S51: FY20 | T51: =E5 -> 11431.453 | U51: =E5/D5-1 -> 0.058212919 | V51: =X51*T51 -> 6191.962 | W51: =E7/D7-1 -> 0.011525945 | X51: =E57 -> 0.5416601 | Y51: =E14 -> 1904.241 | Z51: =E14/D14-1 -> -0.28606419 | AA51: =E16 -> 0.90678143 | AB51: =Valuation!$C$2/NewFinSumm!AA51 -> 384.27121 | AC51: =E80 -> 122.19256 | AD51: =E65 -> 0.099630523 | AE51: =E62 -> 0.070061912
B52: Revenue | D52: =D5/C5-1 -> 0.082323542 | E52: =E5/D5-1 -> 0.058212919 | F52: =F5/E5-1 -> 0.4027705 | G52: =G5/F5-1 -> 0.41749851 | H52: =H5/G5-1 -> 0.4054804 | I52: =I5/H5-1 -> 0.17783935 | J52: =J5/I5-1 -> 0.18954846 | K52: =K5/J5-1 -> 0.19778202 | ... O52: =O5/N5-1 -> 0.30619457 | S52: FY21 | T52: =F5 -> 16035.705 | U52: =T52/T51-1 -> 0.4027705 | V52: =X52*T52 -> 8164.395 | W52: =V52/V51-1 -> 0.31854734 | X52: =F57 -> 0.50913851 | Y52: =F14 -> 2913.855 | Z52: =Y52/Y51-1 -> 0.53019234 | AA52: =F16 -> 1.38755 | AB52: =Valuation!$C$2/NewFinSumm!AA52 -> 251.12609 | AC52: =F80 -> 94.134933 | AD52: =F65 -> 0.10774786 | AE52: =F62 -> 0.10713916
B53: EBITDA | D53: =D7/C7-1 -> 0.041346764 | E53: =E7/D7-1 -> 0.011525945 | F53: =F7/E7-1 -> 0.31854734 | G53: =G7/F7-1 -> 0.35886468 | H53: =H7/G7-1 -> 0.46037914 | I53: =I7/H7-1 -> 0.21254944 | J53: =J7/I7-1 -> 0.15149448 | K53: =K7/J7-1 -> 0.15098268 | ... O53: =O7/N7-1 -> 0.30259561 | S53: FY22 | T53: =G5 -> 22730.588 | U53: =T53/T52-1 -> 0.41749851 | V53: =X53*T53 -> 11094.308 | W53: =V53/V52-1 -> 0.35886468 | X53: =G57 -> 0.48807836 | Y53: =G14 -> 3279.458 | Z53: =Y53/Y52-1 -> 0.12547055 | AA53: =G16 -> 1.5616467 | AB53: =Valuation!$C$2/NewFinSumm!AA53 -> 223.12986 | AC53: =G80 -> 68.994803 | AD53: =G65 -> 0.11927532 | AE53: =G62 -> 0.10641914
B54: Adj PAT | D54: =IF(OR(D15<0,C15<0),"NM",D15/C15-1) -> -0.050173122 | E54: =IF(OR(E15<0,D15<0),"NM",E15/D15-1) -> -0.28606419 | F54: =IF(OR(F15<0,E15<0),"NM",F15/E15-1) -> 0.53019234 | G54: =IF(OR(G15<0,F15<0),"NM",G15/F15-1) -> 0.12547055 | H54: =IF(OR(H15<0,G15<0),"NM",H15/G15-1) -> 1.2559752 | I54: =IF(OR(I15<0,H15<0),"NM",I15/H15-1) -> 0.56238342 | J54: =IF(OR(J15<0,I15<0),"NM",J15/I15-1) -> 0.30034345 | K54: =IF(OR(K15<0,J15<0),"NM",K15/J15-1) -> 0.066503446 | ... O54: =IF(OR(O15<0,N15<0),"NM",O15/N15-1) -> 0.14330489 | S54: FY23 | T54: =H5 -> 31947.396 | U54: =T54/T53-1 -> 0.4054804 | V54: =X54*T54 -> 16201.896 | W54: =V54/V53-1 -> 0.46037914 | X54: =H57 -> 0.50714293 | Y54: =H14 -> 7398.376 | Z54: =Y54/Y53-1 -> 1.2559752 | AA54: =H16 -> 3.5230362 | AB54: =Valuation!$C$2/NewFinSumm!AA54 -> 98.906165 | AC54: =H80 -> 46.588414 | AD54: =H65 -> 0.18744126 | AE54: =H62 -> 0.20362289
B55: Margin ratios | S55: FY24 | T55: =I5 -> 37628.9 | U55: =T55/T54-1 -> 0.17783935 | V55: =X55*T55 -> 19645.6 | W55: =V55/V54-1 -> 0.21254944 | X55: =I57 -> 0.52208808 | Y55: =I14 -> 11559.1 | Z55: =Y55/Y54-1 -> 0.56238342 | AA55: =I16 -> 5.5043333 | AB55: =Valuation!$C$2/NewFinSumm!AA55 -> 63.304669 | AC55: =I80 -> 37.283219 | AD55: =I65 -> 0.21047913 | AE55: =I62 -> 0.19231536
B56: Gross | S56: FY25E | T56: =J5 -> 44761.4 | U56: =T56/T55-1 -> 0.18954846 | V56: =X56*T56 -> 22621.8 | W56: =V56/V55-1 -> 0.15149448 | X56: =J57 -> 0.50538634 | Y56: =J14 -> 15030.8 | Z56: =Y56/Y55-1 -> 0.30034345 | AA56: =J16 -> 7.1575238 | AB56: =Valuation!$C$2/NewFinSumm!AA56 -> 48.683037 | AC56: =J80 -> 33.238504 | AD56: =J65 -> 0.18393226 | AE56: =J62 -> 0.16961665
B57: EBITDA | C57: =C7/C5 -> 0.58895839 | D57: =D7/D5 -> 0.56666042 | E57: =E7/E5 -> 0.5416601 | F57: =F7/F5 -> 0.50913851 | G57: =G7/G5 -> 0.48807836 | H57: =H7/H5 -> 0.50714293 | I57: =I7/I5 -> 0.52208808 | J57: =J7/J5 -> 0.50538634 | ... O57: =O7/O5 -> 0.40045887 | R57: 100 | S57: FY26E | T57: =K5 -> 53614.4 | U57: =T57/T56-1 -> 0.19778202 | V57: =X57*T57 -> 26037.3 | W57: =V57/V56-1 -> 0.15098268 | X57: =K57 -> 0.48564005 | Y57: =K14 -> 15233.1 | Z57: =Y57/Y56-1 -> 0.013459031 | AA57: =K16 -> 7.6335238 | AB57: =Valuation!$C$2/NewFinSumm!AA57 -> 45.647333 | AC57: =K80 -> 28.878371 | AD57: =K65 -> 0.17241085 | AE57: =K62 -> 0.14807819
B58: Adj PAT | C58: =C15/C5 -> 0.28135007 | D58: =D15/D5 -> 0.24690755 | E58: =E15/E5 -> 0.16657909 | F58: =F15/F5 -> 0.18171044 | G58: =G15/G5 -> 0.14427511 | H58: =H15/H5 -> 0.23157994 | I58: =I15/I5 -> 0.30718676 | J58: =J15/J5 -> 0.33579825 | ... O58: =O15/O5 -> 0.1482284 | S58: FY27E | T58: =L5 -> 72935.368 | U58: =T58/T57-1 -> 0.360369 | V58: =X58*T58 -> 29530.876 | W58: =V58/V57-1 -> 0.13417583 | X58: =L57 -> 0.40489103 | Y58: =L14 -> 15958.31 | Z58: =Y58/Y57-1 -> 0.047607488 | AA58: =L16 -> 6.8490599 | AB58: =Valuation!$C$2/NewFinSumm!AA58 -> 50.875595 | AC58: =L80 -> 26.164019 | AD58: =L65 -> 0.15631752 | AE58: =L62 -> 0.10696857
B59: Performance ratios
B60: Pre-tax OCF/EBITDA (%) | C60: =C35/C7 -> 1.1938785 | D60: =D35/D7 -> 0.5845148 | E60: =E35/E7 -> 0.47648952 | F60: =F35/F7 -> 1.2937591 | G60: =G35/G7 -> 1.1703993 | H60: =H35/H7 -> 1.2207732 | I60: =I35/I7 -> 1.0438775 | J60: =J35/J7 -> 1.0494656 | ... O60: =O35/O7 -> 0.97663564
B61: OCF/IC (%) | C61: =C36/C32 -> 0.17162385 | D61: =D36/D32 -> 0.084295592 | E61: =E36/E32 -> 0.057663994 | F61: =F36/F32 -> 0.17542957 | G61: =G36/G32 -> 0.17393007 | H61: =H36/H32 -> 0.28300895 | I61: =I36/I32 -> 0.22072221 | J61: =J36/J32 -> 0.20031987 | ... O61: =O36/O32 -> 0.15727211
B62: RoE (%) | C62: =Consol!G221 -> 0.21492996 | D62: =Consol!H221 -> 0.096977703 | E62: =Consol!I221 -> 0.070061912 | F62: =Consol!J221 -> 0.10713916 | G62: =Consol!K221 -> 0.10641914 | H62: =Consol!L221 -> 0.20362289 | I62: =Consol!M221 -> 0.19231536 | J62: =Consol!N221 -> 0.16961665 | ... O62: =Consol!S221 -> 0.11454799
B63: RoCE (%) | C63: =Consol!G222 -> 0.07982528 | D63: =Consol!H222 -> 0.083184229 | E63: =Consol!I222 -> 0.070667832 | F63: =Consol!J222 -> 0.057397406 | G63: =Consol!K222 -> 0.074227295 | H63: =Consol!L222 -> 0.14636347 | I63: =Consol!M222 -> 0.10780053 | J63: =Consol!N222 -> 0.11065758 | ... O63: =Consol!S222 -> 0.095771964
B64: RoCE (Pre-tax) | C64: =(C9+C10)/AVERAGE(C31:C31) -> 0.113129 | D64: =(D9+D10)/AVERAGE(C31:D31) -> 0.096341034 | E64: =(E9+E10)/AVERAGE(D31:E31) -> 0.096951735 | F64: =(F9+F10)/AVERAGE(E31:F31) -> 0.099258291 | G64: =(G9+G10)/AVERAGE(F31:G31) -> 0.11339118 | H64: =(H9+H10)/AVERAGE(G31:H31) -> 0.17357266 | I64: =(I9+I10)/AVERAGE(H31:I31) -> 0.17164511 | J64: =(J9+J10)/AVERAGE(I31:J31) -> 0.14903738 | K64: =(K9+K10)/AVERAGE(J31:K31) -> 0.14048435 | ... O64: =(O9+O10)/AVERAGE(N31:O31) -> 0.13159467 | T64: FY26E | W64: FY27E
B65: RoIC (Pre-tax) | C65: =C9/AVERAGE(C32:C32) -> 0.12321638 | D65: =D9/AVERAGE(C32:D32) -> 0.097375716 | E65: =E9/AVERAGE(D32:E32) -> 0.099630523 | F65: =F9/AVERAGE(E32:F32) -> 0.10774786 | G65: =G9/AVERAGE(F32:G32) -> 0.11927532 | H65: =H9/AVERAGE(G32:H32) -> 0.18744126 | I65: =I9/AVERAGE(H32:I32) -> 0.21047913 | J65: =J9/AVERAGE(I32:J32) -> 0.18393226 | K65: =K9/AVERAGE(J32:K32) -> 0.17241085 | ... O65: =O9/AVERAGE(N32:O32) -> 0.13929478 | T65: Old | U65: New | V65: Change (%) | W65: Old | X65: New | Y65: Change (%)
B66: Fixed asset turnover (x) | C66: =(C5+C25)/AVERAGE(B22:C22) -> 0.46239529 | D66: =(D5+D25)/AVERAGE(C22:D22) -> 0.45610746 | E66: =(E5+E25)/AVERAGE(D22:E22) -> 0.38979709 | F66: =(F5+F25)/AVERAGE(E22:F22) -> 0.65621366 | G66: =(G5+G25)/AVERAGE(F22:G22) -> 0.98397781 | H66: =(H5+H25)/AVERAGE(G22:H22) -> 1.1058494 | I66: =(I5+I25)/AVERAGE(H22:I22) -> 1.1328981 | J66: =(J5+J25)/AVERAGE(I22:J22) -> 0.94605176 | ... O66: =(O5+O25)/AVERAGE(N22:O22) -> 0.58088109 | P66: <---change in formula from other stocks | S66: Sales | T66: 54885 | U66: =T57 -> 53614.4 | V66: =IFERROR((U66/T66-1),"NA") -> -0.023150223 | W66: 65610 | X66: =T58 -> 72935.368 | Y66: =IFERROR((X66/W66-1),"NA") -> 0.11165017
B67: Total asset turnover (x) | C67: =C5/AVERAGE(C30:C30) -> 0.19558517 | D67: =D5/AVERAGE(C30:D30) -> 0.19778562 | E67: =E5/AVERAGE(D30:E30) -> 0.18144527 | F67: =F5/AVERAGE(E30:F30) -> 0.21641469 | G67: =G5/AVERAGE(F30:G30) -> 0.26440002 | H67: =H5/AVERAGE(G30:H30) -> 0.34908036 | I67: =I5/AVERAGE(H30:I30) -> 0.33269876 | J67: =J5/AVERAGE(I30:J30) -> 0.29790825 | K67: =K5/AVERAGE(J30:K30) -> 0.29327062 | ... O67: =O5/AVERAGE(N30:O30) -> 0.45046647 | S67: EBITDA (%) | T67: 0.45 | U67: =X57 -> 0.48564005 | V67: =+(U67-T67)*10000 -> 356.40052 | W67: 0.42 | X67: =X58 -> 0.40489103 | Y67: =+(X67-W67)*10000 -> -151.08966
B68: Financial stability ratios | S68: PAT | T68: 13640 | U68: =Y57 -> 15233.1 | V68: =IFERROR((U68/T68-1),"NA") -> 0.11679619 | W68: 13809 | X68: =Y58 -> 15958.31 | Y68: =IFERROR((X68/W68-1),"NA") -> 0.15564557
B69: Net Debt to Equity (x) | C69: =C33/C18 -> 0.48185067 | D69: =D33/D18 -> 0.61540692 | E69: =E33/E18 -> 0.92832242 | F69: =F33/F18 -> 1.1918602 | G69: =G33/G18 -> 0.97078871 | H69: =H33/H18 -> 0.63882028 | I69: =I33/I18 -> 0.035288458 | J69: =J33/J18 -> 0.20753382 | ... O69: =O33/O18 -> 0.56224461 | S69: EPS | T69: 6.5 | U69: =AA57 -> 7.6335238 | V69: =IFERROR((U69/T69-1),"NA") -> 0.17438828 | W69: 6.6 | X69: =AA58 -> 6.8490599 | Y69: =IFERROR((X69/W69-1),"NA") -> 0.037736352
B70: Net Debt to EBITDA (x) | C70: =C33/C7 -> 2.2991828 | D70: =D33/D7 -> 3.1011776 | E70: =E33/E7 -> 4.1248777 | F70: =F33/F7 -> 4.5085741 | G70: =G33/G7 -> 3.0380074 | H70: =H33/H7 -> 1.6121909 | I70: =I33/I7 -> 0.1478499 | J70: =J33/J7 -> 0.96223996 | ... O70: =O33/O7 -> 1.9898144 | S70: Method | T70: After Results | U70: EV/EBITDA 18x | W70: After Results | X70: EV/EBITDA 18x
B71: Interest cover (x) | C71: =C36/C11 -> 4.6183802 | D71: =D36/D11 -> 1.8517996 | E71: =E36/E11 -> 0.93240786 | F71: =F36/F11 -> 4.3456554 | G71: =G36/G11 -> 2.8030704 | H71: =H36/H11 -> 3.0150768 | I71: =I36/I11 -> 5.4238405 | J71: =J36/J11 -> 7.9041168 | ... O71: =O36/O11 -> 4.2205493 | U71: =U67-T67 -> 0.035640052
B72: Cash conversion days | C72: =C29/C5*365 -> 68.916143 | D72: =D29/D5*365 -> 155.12862 | E72: =E29/E5*365 -> 174.80531 | F72: =F29/F5*365 -> 83.26323 | G72: =G29/G5*365 -> 66.151126 | H72: =H29/H5*365 -> 23.186758 | I72: =I29/I5*365 -> 41.934032 | J72: =J29/J5*365 -> 48.393605 | ... O72: =O29/O5*365 -> 40.38385
B73: Working capital days | C73: =Consol!G211 -> 68.916143 | D73: =Consol!H211 -> 155.12862 | E73: =Consol!I211 -> 174.80531 | F73: =Consol!J211 -> 83.26323 | G73: =Consol!K211 -> 66.151126 | H73: =Consol!L211 -> 23.186758 | I73: =Consol!M211 -> 41.934032 | J73: =Consol!N211 -> 48.393605 | ... O73: =Consol!S211 -> 47.561847
B74: Valuation metrics
B75: Fully Diluted Shares (mn) | C75: =Consol!G53 -> 2100 | D75: =Consol!H53 -> 2100 | E75: =Consol!I53 -> 2100 | F75: =Consol!J53 -> 2100 | G75: =Consol!K53 -> 2100 | H75: =Consol!L53 -> 2100 | I75: =Consol!M53 -> 2100 | J75: =Consol!N53 -> 2100 | ... O75: =Consol!S53 -> 2330 | P75: =C88 -> 348.45
B76: Market cap (Rs.mn) | I76: =I75*Valuation!$C$2 -> 731745
B77: P/E (x) | C77: =$P$75/C16 -> 260.58024 | D77: =$P$75/D16 -> 274.34498 | E77: =$P$75/E16 -> 384.27121 | F77: =$P$75/F16 -> 251.12609 | G77: =$P$75/G16 -> 223.12986 | H77: =$P$75/H16 -> 98.906165 | I77: =$P$75/I16 -> 63.304669 | J77: =$P$75/J16 -> 48.683037 | ... O77: =$P$75/O16 -> 29.049371
B78: P/OCF(x) | C78: =$I$76/C36 -> 121.97767 | D78: =$I$76/D36 -> 223.0785 | E78: =$I$76/E36 -> 282.84996 | F78: =$I$76/F36 -> 73.899603 | G78: =$I$76/G36 -> 62.211047 | H78: =$I$76/H36 -> 40.715224 | I78: =$I$76/I36 -> 40.580132 | J78: =$I$76/J36 -> 34.837701 | ... O78: =$I$76/O36 -> 11.156642 | Q78: =K80/'[1]New FinSumm'!$Y$81-1 -> 0.48337006 | S78: 85.61 | Y78: =320/300-1 -> 0.066666667
B79: EV (Rs.mn) (ex-CWIP) | C79: =$I$76+C19-C42 -> 744976.65 | D79: =$I$76+D19-D42 -> 748430.95 | E79: =$I$76+E19-E42 -> 756611.68 | F79: =$I$76+F19-F42 -> 768554.78 | G79: =$I$76+G19-G42 -> 765449.59 | H79: =$I$76+H19-H42 -> 754820.64 | I79: =$I$76+I19-I42 -> 732451.2 | J79: =$I$76+J19-J42 -> 751914.8 | K79: =$I$76+J19-J42 -> 751914.8 | L79: =$I$76+K19-K42 -> 772646.4 | M79: =$I$76+L19-L42 -> 758757.94 | N79: =$I$76+M19-M42 -> 818734.76 | O79: =$I$76+N19-N42 -> 861397.22 | S79: =4.75+2.69 -> 7.44
B80: EV/ EBITDA (x) | C80: =C79/C7 -> 126.73214 | D80: =D79/D7 -> 122.26453 | E80: =E79/E7 -> 122.19256 | F80: =F79/F7 -> 94.134933 | G80: =G79/G7 -> 68.994803 | H80: =H79/H7 -> 46.588414 | I80: =I79/I7 -> 37.283219 | J80: =J79/J7 -> 33.238504 | ... O80: =O79/O7 -> 11.408205 | S80: =100-S78-S79 -> 6.95
B81: EV/ OCF(x) | C81: =C79/C36 -> 124.18331 | D81: =D79/D36 -> 228.16535 | E81: =E79/E36 -> 292.46197 | F81: =F79/F36 -> 77.617057 | G81: =G79/G36 -> 65.076523 | H81: =H79/H36 -> 41.999182 | I81: =I79/I36 -> 40.619296 | J81: =J79/J36 -> 35.797966 | ... O81: =O79/O36 -> 13.133401
B82: FCF Yield (%) | C82: =C38/$I$76 -> -0.0046177453 | D82: =D38/$I$76 -> -0.0030591887 | E82: =E38/$I$76 -> -0.0056724993 | F82: =F38/$I$76 -> -0.010009279 | G82: =G38/$I$76 -> 0.0091172881 | H82: =H38/$I$76 -> 0.020743169 | I82: =I38/$I$76 -> -0.0036617948 | J82: =J38/$I$76 -> -0.012840129 | ... O82: =O38/$I$76 -> -0.0022933799
B83: Price to BV (x) | C83: =$I$76/C18 -> 26.088124 | D83: =$I$76/D18 -> 23.721615 | E83: =$I$76/E18 -> 26.596179 | F83: =$I$76/F18 -> 23.693099 | G83: =$I$76/G18 -> 21.076351 | H83: =$I$76/H18 -> 17.896007 | I83: =$I$76/I18 -> 8.890089 | J83: =$I$76/J18 -> 6.9765081 | ... O83: =$I$76/O18 -> 2.7383336
B84: BV/Share (x) | C84: =C18/C75 -> 13.356652 | D84: =D18/D75 -> 14.689135 | E84: =E18/E75 -> 13.101506 | F84: =F18/F75 -> 14.706814 | G84: =G18/G75 -> 16.532748 | H84: =H18/H75 -> 19.470824 | I84: =I18/I75 -> 39.195333 | J84: =J18/J75 -> 49.94619 | ... O84: =O18/O75 -> 114.68787
B85: Dividend pay-out (%) | C85: =Consol!G59 -> 0 | D85: =Consol!H59 -> 0 | E85: =Consol!I59 -> 0 | F85: =Consol!J59 -> 0 | G85: =Consol!K59 -> 0 | H85: =Consol!L59 -> 0 | I85: =Consol!M59 -> 0.099921274 | J85: =Consol!N59 -> 0.1117705 | ... O85: =Consol!S59 -> 0.12
B86: Dividend yield (%) | C86: =Consol!G58/NewFinSumm!$P$75 -> 0 | D86: =Consol!H58/NewFinSumm!$P$75 -> 0 | E86: =Consol!I58/NewFinSumm!$P$75 -> 0 | F86: =Consol!J58/NewFinSumm!$P$75 -> 0 | G86: =Consol!K58/NewFinSumm!$P$75 -> 0 | H86: =Consol!L58/NewFinSumm!$P$75 -> 0 | I86: =Consol!M58/NewFinSumm!$P$75 -> 0.0015784187 | J86: =Consol!N58/NewFinSumm!$P$75 -> 0.0022958818 | ... O86: =Consol!S58/NewFinSumm!$P$75 -> 0.0041308984
B88: #VALUE! | C88: {=_FV(B88,"Price")} -> 348.45
D89: =D57*100 -> 56.666042 | E89: =E57*100 -> 54.16601 | F89: =F57*100 -> 50.913851 | G89: =G57*100 -> 48.807836 | H89: =H57*100 -> 50.714293 | I89: =I57*100 -> 52.208808 | J89: =J57*100 -> 50.538634 | K89: =K57*100 -> 48.564005 | ... M89: =M57*100 -> 43.653529
D90: =D58*100 -> 24.690755 | E90: =E58*100 -> 16.657909 | F90: =F58*100 -> 18.171044 | G90: =G58*100 -> 14.427511 | H90: =H58*100 -> 23.157994 | I90: =I58*100 -> 30.718676 | J90: =J58*100 -> 33.579825 | K90: =K58*100 -> 29.89943 | ... M90: =M58*100 -> 21.522044

Sheet Key
B2: Operational Capacity
B3: Port Asset | C3: Entity | D3: Stake, % | E3: Acquired or Created? | F3: Acquiried From? | G3: Acq Consideration, Rs. mn | H3: Asset Type | I3: Type of Agreement (Concession/Lease/License/O&M) | J3: State | K3: Capacity, MT | L3: Draft, m | M3: Cargo Type | N3: Major Cargoes Handled | O3: Expansion Plans, MTPA | P3: Expansion - Cargo type | Q3: Hinterland | R3: Key Customers | S3: Evacuation Plan/ Infrastructure | T3: CoD | U3: Concession, years | V3: Concession Expiry | W3: Concession With | X3: Guaranteed Throughput | Y3: No of Berths | Z3: Berth Length, mtrs | AA3: Annual/Lease charges (Rs. mn) | AB3: Tariff | AC3: Revenue Share | AD3: CAPEX, Rs. mn | AE3: Concession Years Left | AF3: Customer | AG3: Check in RHP Once
B4: Dharamtar | C4: JSW Dharmatar Port Private Ltd | D4: 1 | E4: Created | F4: - | G4: - | H4: Port | I4: Lease | J4: Maharashtra | K4: 34 | L4: 3.5 | M4: Bulk | N4: limestone, dolomite, iron ore, coal, and scrap | O4: NA | P4: NA | R4: JSW Steel and JSW Cement | S4: The Dharamtar Port is located in close proximity to the Mumbai and Jawaharlal Nehru Port Trust (Nhava Sheva harbors), NH-66 and the Konkan railway network and almost all the cargo is evacuated through its conveyor system. It is also directly connected to the premises of JSW Steel’s manufacturing facility through a mechanized conveyor system. | T4: 2012 | U4: NA | V4: 2044 | W4: Maharashtra Maritime Board | X4: None | Y4: 5 | Z4: 771 | AA4: NA | AB4: Negotiated | AC4: As per Maharashtra Maritime Board | AE4: =V4-2026 -> 18 | AF4: All group | AG4: Exclusive to Steel | AH4: Dolvi plant
B5: Jaigarh | C5: JSW Jaigarh Port Ltd | D5: 1 | E5: Created | F5: - | G5: - | H5: Port | I5: Concession | J5: Maharashtra | K5: 55 | L5: 17.5 | M5: Multi-Cargo | N5: multi-purpose, all weather port. LNG, LPG, molasses, sugar, steel coil, bauxite, fly ash, thermal coal, coking coal, iron ore, limestone, fertilizers, coated pipes, rock phosphate, sulphur, steel coil, containers, gypsum, and edible oil | O5: 2 | P5: LPG | Q5: parts of northern Goa, southern and western Maharashtra, and Northern and central Karnataka | R5: JSW Energy, JSW Steel | S5: Jaigarh Port is connected to NH-66 (Mumbai-Goa) at Nivali through SH 106. The Jaigarh Port is at a distance of about 55 kilometres from Ratnagiri on the Konkan railway network. Trans-ship cargo from the Jaigarh Port to other locations including the Dharamtar Port through mini bulk carriers. | T5: 2010 | U5: 50 | V5: 2058 | W5: Maharashtra Maritime Board | X5: None | Y5: 7 | Z5: 2319 | AA5: =25.2+6.4 -> 31.6 | AB5: Negotiated | AC5: JSW Energy: 15 per MMT in the first year of operations, subject to revisions by the Maharashtra Maritime Board Other customers: ₹3 per MMT in the first year of operations, escalated by 20% annually till the 15th year of operation; and from the 16th year of operations, escalated by 3% every fifth financial year | AE5: =V5-2026 -> 32 | AF5: 70% is group | AG5: JSW Steel biggest customer, H Energy | AJ5: Trans Shipment to Dharamtar
B6: South West (Goa) | C6: South West Port Limited | D6: 0.9 | E6: Acquired | H6: Terminal | I6: License | J6: Goa | K6: 11 | L6: 14 | M6: Bulk | N6: Coal, Steel and Limestone | O6: NA | P6: NA | R6: JSW Steel | S6: The South West Port is connected to both NH 66 and NH 748, with NH 748 providing connectivity to NH 566, a major highway that connects Mumbai and Bengaluru. The South West Port has a railway connection with the Southwest Railway rail head entering the harbor to touch the terminal, allowing for smooth transportation of goods by rail. The Zuari and Mandovi rivers provide inland waterway transport facilities, connecting the Mormugao Harbor – and the South West Port – with mines and manufacturing plants in the hinterland. | T6: 2004 | U6: 30 | V6: 2029 | W6: Mormugao Port | X6: 5 MMT | Y6: 2 | Z6: 450 | AA6: 15.22 | AB6: Until Fiscal 2022 – regulated Post 2022 – WPI linked | AC6: 18% of gross revenue excludin g berth hire income | AE6: =V6-2026 -> 3 | AF6: All group | AG6: Largely JSW Steel | AH6: Vijaynagar Steel Plant | AJ6: Company can operate if the shed is made with capex of 100crs - should complete by year end
B7: New Mangalore Coal | C7: Mangalore Coal Terminal Pvt Ltd | D7: 1 | E7: Acquired | H7: Terminal | I7: Concession | J7: Karnataka | K7: 8.1 | L7: 14 | M7: Bulk | N7: Coal, Limestone, and dolomite cargo | O7: NA | P7: NA | Q7: New Mangalore Coal Terminal is located in NMPT and is a modern all-weather terminal situated at Panambur, Mangalore on the west coast of India, 170 nautical miles south of Mormugao Port and 191 nautical miles north of Cochin Port. | R7: The terminal’s key customers are the power plants located around the hinterland belts of Karnataka and Tamil Nadu. | S7: New Mangalore Port is connected to NH 75, NH 66, NH 52, NH 50 and NH 275, which permits our terminals to connect with all of Karnataka, Goa and other parts of southern part of India through Mangalore, Kerala, Chennai. | T7: 2020 | U7: 30 | V7: 2047 | W7: New Mangalore Port Authority | X7: 3.7 MMT | Y7: 1 | Z7: 315 | AA7: MCTPL is required to pay to the Board of Trustees for NMPT certain license fees. License fee for land area being equivalent to the product of extent of land area in square meter and license fee per square meter per year (derived with 2% compounded annual increment) corresponding to a base license fee of ₹19.21 square meter per month, with an additional 10% surcharge on custom notified areas. License fee for water area being equivalent to the product of extent of water area in square meter and license fee per square meter per year (derived with 2% compounded annual increment) corresponding to a base license fee of ₹9.61 per square meter per month, with an additional 10% surcharge on custom notified areas. | AB7: Fixed at bidding and WPI linked | AC7: 31% of Gross Revenue | AE7: =V7-2026 -> 21 | AF7: 70% is group | AG7: Largely JSW Steel
B8: New Mangalore Container | C8: JSW Mangalore Container Terminal Pvt Ltd | D8: 1 | E8: Created | F8: - | G8: - | H8: Terminal | I8: Concession | J8: Karnataka | K8: =4.2 -> 4.2 | L8: 14 | M8: Container | N8: Containers and other bulk | O8: =6.02-K8 -> 1.82 | P8: To further our diversification strategy with focus on expanding footprint in containers cargo, pursuing opportunities in synergistic businesses and increasing our third-party customer base, we are in the process of expanding our existing facilities at Mangalore Container Terminal by developing an additional yard and procure additional equipment | S8: connectivity to NH-75, NH-66, NH-52, NH-50 and NH-275, which permits our terminals to connect with all of Karnataka, Goa and other parts of southern India through Mangalore, Kerala and Chennai | T8: 2022 | U8: 30 | V8: 2050 | W8: New Mangalore Port Authority - to mechanization of berth 14 for providing equipment for handling containers and other cargoes at New Mangalore Port on DBFOT basis | X8: minimum 91,000 TEU | Y8: 1 | Z8: 350 | AA8: MTPL’s payment obligations comprise (i) license fee equal to the product of extent of land area in square meter and license fee per square meter per year (derived with 2% compounded annual increment) corresponding to base license fee of ₹24.83 per square meter per month, with an additional 10% surcharge on custom notified areas; | AB8: Fixed at bidding and WPI linked | AC8: INR 951 per TEU | AE8: =V8-2026 -> 24 | AF8: All third Party
B9: Ennore Coal | C9: Ennore Coal Terminal Pvt Ltd | D9: 1 | E9: Acquired | H9: Terminal | I9: License | J9: Tamil Nadu | K9: 11 | L9: 16 | M9: Bulk | N9: Coal | O9: NA | P9: NA | S9: Ennore Port is connected to NH 4, NH 5 and NH 45 and a dedicated freight corridor between Chennai and Bangalore/Mumbai and Delhi/Kolkata. Our terminals are connected by rail to the Chennai-Gudur Section (North- East Line) of the Southern Railway. The connection involves two lines – the South Connectivity Line and the North Connectivity Line, both located in the terminal area, and another a 6 km rail line connecting to the Chennai- Kolkata line. | T9: 2020 | U9: 30 | V9: 2038 | W9: Kamarajar Port Ltd | X9: Rs. 50mn | Y9: 1 | Z9: 348 | AA9: NA | AB9: Fixed by the operator for various services across customers | AC9: 52.52% of Gross Revenue | AE9: =V9-2026 -> 12 | AF9: Third Party and Group | AG9: JSW Steel
B10: Ennore Bulk | C10: Ennore Bulk Terminal Pvt Ltd | D10: 1 | E10: Acquired | H10: Terminal | I10: Concession | J10: Tamil Nadu | K10: 2 | L10: 14.5 | M10: Bulk | N10: Dry Bulk (Clean cargo other than coal,iron ore, POL and automobile) | O10: NA | P10: NA | S10: Ennore Port is connected to NH 4, NH 5 and NH 45 and a dedicated freight corridor between Chennai and Bangalore/Mumbai and Delhi/Kolkata. Our terminals are connected by rail to the Chennai-Gudur Section (North- East Line) of the Southern Railway. The connection involves two lines – the South Connectivity Line and the North Connectivity Line, both located in the terminal area, and another a 6 km rail line connecting to the Chennai- Kolkata line. | T10: 2020 | U10: 30 | V10: 2045 | W10: Kamarajar Port Ltd | X10: 1.4 MMT | Y10: 1 | Z10: 270 | AA10: 10.66 | AB10: Fixed by the operator for various services across customers | AC10: 36% of Gross Revenue | AE10: =V10-2026 -> 19 | AF10: 80% Third Party
B11: Paradip Iron Ore | C11: JSW Paradip Terminal Pvt Ltd | D11: 0.974 | E11: Created | F11: - | G11: - | H11: Terminal | I11: Concession | J11: Orissa | K11: 10 | L11: 16 | M11: Bulk | N11: Iron ore and pellets | O11: NA | P11: NA | S11: The terminal is connected with its hinterland through a network of roads and railways. It is connected by a state highway with Cuttack in the state of Odisha and the state capital Bhubaneswar and is also linked to NH 5A. The Indian Railways serves the port through a direct broad gauge double line connected to Cuttack, the commercial hub of Odisha. | T11: 2019 | U11: 30 | V11: 2045 | W11: Paradip Port Trust | X11: 7 MTPA | Y11: 1 | Z11: 370 | AA11: 9 | AB11: Fixed at bidding and WPI linked | AC11: 21% of Gross Revenue | AE11: =V11-2026 -> 19 | AF11: 70% third party. 30% Group | AG11: Merchant Pellet Plant owners and Miners in Orissa
B12: Paradip Coal Exports | C12: Paradip East Quay Coal Terminal Ltd | D12: 0.974 | E12: Created | F12: - | G12: - | H12: Terminal | I12: Concession | J12: Orissa | K12: 30 | L12: 15 | M12: Bulk | N12: Coal | O12: NA | P12: NA | S12: The terminal is connected to NH 5 through a dedicated four-lane road. The terminal also connected to East Coast Railways network leading to Cuttack in Odisha, through the Paradip Port Trust’s rail network within the port area (broad-gauge double line tracks). | T12: 2021 | U12: 30 | V12: 2047 | W12: Paradip Port Trust | X12: 8 MTPA | Y12: 2 | Z12: 686 | AA12: 23.3 | AB12: Fixed at bidding and WPI linked | AC12: 31.7% of Gross Revenue | AE12: =V12-2026 -> 21 | AF12: All third Party | AH12: Usually inland transport of Coal to Telangana and Tamil Nadu, TANGEDCO, Sembcorp
A13: Recently Acquired | B13: PNP Port | C13: PNP Maritime Services | D13: 50% stepdown subsidairy of JSW Dharmatar Port Private Ltd | E13: Acquired | F13: Shapoorji Pallonji Group (SP Port Maintenance Private Limited). The Company has vision to expand its cargo handling capacity and cargo volume/ throughput in all types of cargoes. Considering the same, this acquisition would help the Company to achieve its growth & expand its footprint. | G13: 2700mn Equity, 7000mn EV | H13: Port | I13: License | J13: Maharashtra | K13: 8 | M13: Bulk | N13: PNP Port is operating multi-purpose jetties at Shahabad in Raigad district of Maharashtra - Steel, Cement and Coal | O13: 19 | Q13: This acquisition is part of JSW Infrastructure’s strategic direction to explore opportunities to expand organically and inorganically, to provide end to end logistics services near the cargo consumption / generation centres. PNP port is expected to strengthen JSW Infrastructure’s position to provide Hub & Spoke model services to customers, thereby saving substantially in the logistics costs. JSW Infrastructure intends to upgrade the PNP Port facilities and expand its capacity from current 5 MTPA to 19 MTPA in a phased manner. This acquisition furthers its vision to increase the use of waterways and existing railway facility at PNP adds synergies to the last mile connectivity. The acquisition of PNP Port is a strategic asset for JSW infrastructure. It will allow the company to service growing share of 3rd party customers in India and derive huge synergies with our existing ports & terminals. It will be able to participate in the Govt. of India Maritime Vision to move cargo through Rail- Sea- Rail route and coastal cargo. At PNP Port, development of Port based industries will be a key focus area and service to multipurpose cargo of Bulk, Container, Liquid etc. The PNP Port is an operational port, connected with Road & Rail facilities, and servicing to various industries in the hinterland i.e. Maharashtra, Madhya Pradesh, Karnataka etc. It has a very strategic locational advantage on West Coast of India and having direct access to large cargo centres such as Mumbai, Pune, Mumbai, Palghar, Thane, Pune, Solapur, Bhiwandi, Nasik etc. PNP Port is connected with the Central & Konkan Railway network which is a very important cargo evacuation mode. With the well-connected railway system, it will be able to service customers for container, Liquid and bulk cargo in future. The Port also has very good road connectivity with Mumbai- Goa Highway. | R13: This acquisition is part of JSW Infrastructure’s strategic direction to explore opportunities to expand organically and inorganically, to provide end to end logistics services near the cargo consumption / generation centres. PNP port is expected to strengthen JSW Infrastructure’s position to provide Hub & Spoke model services to customers, thereby saving substantially in the logistics costs. JSW Infrastructure intends to upgrade the PNP Port facilities and expand its capacity from current 5 MTPA to 19 MTPA in a phased manner. This acquisition furthers its vision to increase the use of waterways and existing railway facility at PNP adds synergies to the last mile connectivity. The acquisition of PNP Port is a strategic asset for JSW infrastructure. It will allow the company to service growing share of 3rd party customers in India and derive huge synergies with our existing ports & terminals. It will be able to participate in the Govt. of India Maritime Vision to move cargo through Rail- Sea- Rail route and coastal cargo. At PNP Port, development of Port based industries will be a key focus area and service to multipurpose cargo of Bulk, Container, Liquid etc. The PNP Port is an operational port, connected with Road & Rail facilities, and servicing to various industries in the hinterland i.e. Maharashtra, Madhya Pradesh, Karnataka etc. It has a very strategic locational advantage on West Coast of India and having direct access to large cargo centres such as Mumbai, Pune, Mumbai, Palghar, Thane, Pune, Solapur, Bhiwandi, Nasik etc. PNP Port is connected with the Central & Konkan Railway network which is a very important cargo evacuation mode. With the well-connected railway system, it will be able to service customers for container, Liquid and bulk cargo in future. The Port also has very good road connectivity with Mumbai- Goa Highway. | S13: PNP Port is well connected with road and Railway facilities. | T13: 1999 | U13: 30 | V13: =+T13+U13 -> 2029 | W13: Maharashtra Maritime Board | AA13: - | AC13: NO ROYALTY, why? | AE13: =V13-2026 -> 3 | AF13: All third Party | AG13: Cement,Clinker - local traders of coal | AL13: Realisations are Similar to Dharamtar, rn margins are lower and will improve, wil spend 45-50crs and margin to come to 45-50%
A14: Recently Acquired | B14: Fujairah Liquid | C14: JSW Terminal (Middle East) FZE acquired Marine Oil Terminal Corp | D14: 1 | E14: Acquired | F14: MPT Commodities Limited, British Virgin Islands (Mercuria Group) in December 19, 2023 | G14: $187m EV, Implied EV/EBITDA valuation of 8.5x-9.5x (FY24 EBITDA) | H14: Terminal | I14: Land lease | J14: Overseas | K14: 5 | L14: - | M14: Liquid | N14: Class I to III products including fuel oil, gas oil, diesel & naphtha | O14: - | P14: - | Q14: Overseas | R14: Oil traders, Fuel operators and commodity trading companies | S14: Overseas | T14: 2015 | U14: NA | V14: NA | W14: NA | X14: NA | Y14: 15 tanks | Z14: - | AA14: - | AC14: - | AD14: - | AE14: NA | AF14: All third Party
A15: https://infra.economictimes.indiatimes.com/news/ports-shipping/did-jsw-infra-miscalculate-in-quoting-rs252-a-ton-as-royalty-to-clinch-liquid-cargo-berth-at-j-n-port/107606649 | B15: JNPT Liquid Terminal | C15: JSW JNPT Liquid Terminal Pvt Ltd | D15: 1 | E15: Created | F15: - | G15: - | H15: Terminal | I15: Concession | J15: Maharashtra | K15: 4.5 | L15: - | M15: Liquid | N15: POL, Chemical, Molasses | O15: - | P15: - | Q15: Maharashtra, Gujarat | R15: oil importers/refiners, POL & petroleum product handlers | S15: 19 pipelines of varying diameters, 6 Marine Loading Arms, From tank farms, onward evacuation to hinterland is via road tankers and rail through the JNPA logistics network | T15: 2026 | U15: 30 | V15: =+T15+U15 -> 2056 | W15: Jawaharlal Nehru Port | X15: - | Y15: 2 | Z15: 600 | AA15: - | AB15: - | AC15: Rs. 252/ tonne | AD15: 1000 | AE15: =V15-2026 -> 30 | AF15: All third Party
B16: XX | K16: 0 | O16: - | P16: -
K17: =SUM(K4:K16) -> 182.8
M18: 113.4 | N18: 51.6 | O18: =M18/$K$17 -> 0.62035011 | P18: =N18/$K$17 -> 0.28227571
B19: O&M | W19: Revenue is only 2 million USD, booked under International subsidiary
B20: Fujairah Sea Port (UAE) | C20: JSW Terminal (Middle East) FZE | J20: UAE | V20: 2027 | AB20: With effect from Fiscal 2022, the NMAGI is as follows: (i) AED 47 million if the actual cargo loaded quantity is more than 17 MTPA; (ii) AED 43.87 million if the cargo loaded quantity is between 15 MTPA and 17 MTPA; and (iii) AED 40.73 million if the actual cargo loaded quantity is between 13 MTPA and 15 MTPA.
B21: Dibba Terminal (UAE) | C21: JSW Terminal (Middle East) FZE | J21: UAE | V21: 2028 | AB21: Re-imbursement of actual costs incurred and O&M fees of AED 0.45/MMT for actual qty loaded
B24: Under Construction
B25: Port Asset | C25: Entity | D25: Stake, % | E25: Acquired or Created? | F25: Acquiried From? | G25: Acq Consideration, Rs. mn | H25: Asset Type | I25: Type of Agreement (Concession/Lease/License/O&M) | J25: State | K25: Capacity, MT | L25: Draft, m | M25: Cargo Type | N25: Major Cargoes Handled | O25: Expansion Plans, MTPA | P25: Expansion - Cargo type | Q25: Hinterland | R25: Key Customers | S25: Evacuation Plan/ Infrastructure | T25: CoD | U25: Concession, years | V25: Concession Expiry | W25: Concession With | X25: Guaranteed Throughput | Y25: No of Berths | Z25: Berth Length, mtrs | AA25: Annual/Lease charges (Rs. mn) | AB25: Tariff | AC25: Revenue Share | AD25: CAPEX, Rs. mn | AF25: Customer | AG25: Check in RHP Once
B26: Keni Greenfield | C26: JSW Keni Port Pvt Ltd | D26: 1 | E26: Created | F26: - | G26: - | H26: Port | I26: Concession | J26: Karnataka | K26: 30 | L26: - | M26: Multi-Cargo | N26: Multi-Cargo, The proposed Keni Port is located strategically between two operational Major Ports viz. Mormugao Port in the north and New Mangalore Port in the south. The proposed port’s hinterland is primarily of coal and coke cargo which is being utilized for steel, cement and power plants. It is also further supported by Iron ore, limestone, dolomite handlings and export of finished steel products. | O26: with further potential to increase substantially in the long run | P26: - | Q26: to serve the industries in the area covering Bellary, Hosapete, Hubballi, Kalaburagi and South Maharashtra | S26: Rail connectivity to the Keni Port site is proposed to be in southern side and will be connected with the existing Konkan line to north of the Ankola Station. The proposed railway alignment will be developed with a total length of approximately 8 km. The proposed port shall be well connected with Road and Railway Connectivity. | T26: 47178 | U26: 30 | V26: 56189 | W26: Karnataka Maritime Board | X26: - | Y26: - | Z26: - | AA26: - | AB26: - | AC26: Rs. 17/ tonne | AD26: 41190 | AG26: 1 tonne of steel requires 3 tonnes of raw material (2 tonnes of iron ore, 0.8 coking coal and 0.2 tonnes of others)
B27: Tuticorin Dry Bulk | C27: JSW Tuticorin Multipurpose Terminal Limited | D27: 1 | E27: Created | F27: - | G27: - | H27: Terminal | I27: Concession | J27: Tamil Nadu | K27: 6.96 | L27: 14.2 | M27: Bulk | N27: Coal / Coke ii) Limestone iii) Gypsum iv) Rock Phosphate v) Copper Concentrate | O27: - | P27: - | Q27: Primarily Tamil Nadu, and Kerala, Karnataka, Andhra Pradesh connected via state and NHs | R27: TANGEDCO, NTPL, Cement manufacturers, Fertiliser & chemical companies | S27: Rail — VOC Port owns and operates a 17.6 km internal railway network connecting berths to the broader Indian Railways broad-gauge network, Road — Connected to National Highways and State Highways serving Tamil Nadu, Kerala, Karnataka, and Andhra Pradesh., Conveyor system (direct) — A Link Conveyor system connects the Tuticorin Thermal Power Station's conveyor to the port's coal yard, discharging over 1,500 TPH of bulk cargo directly to the adjacent power plant. | T27: 46447 | U27: 30 | V27: 56431 | W27: V.O. CHIDAMBARANAR PORT TRUST | X27: 2.5 - 3 MT | Y27: North Cargo Berth 3 Mechanisation inculding Dredging for Handling Bulk Cargo | AB27: The Concessionaire shall, in consideration of its investment and services, be entitled to levy and collect a pre-determined user fee | AC27: Rs. 72/ tonne + WPI | AD27: 6000 | AE27: <-- RFQ document say 356cr? | AF27: All third Party | AG27: If JSW Infra exports this^ then it totally gets 4MT of Cargo
B28: Jatadhar | C28: JSW Jatadhar Marine Services Pvt Ltd | D28: 1 | E28: Created | F28: - | G28: - | H28: Port | I28: Concession | J28: Orissa | K28: 30 | L28: - | M28: Bulk | N28: Bulk - thermal coal, coking coal, iron ore, limestone | O28: 22 | P28: - | Q28: Odisha, Jagatsinghpur district — home to JSW Utkal Steel's , Nuagaon iron ore mines (Jajang, Odisha) | R28: JSW Steel | S28: Slurry Pipeline, Connected to National Highway NH-16, Rail: Howrah–Chennai main line | T28: FY28 | U28: 30 | V28: 56795 | W28: Orissa Maritime Board | X28: - | Y28: - | Z28: - | AA28: - | AB28: - | AC28: NO ROYALTY, why? | AD28: 30000
B29: Jaigarh Expansion | C29: JSW Jaigarh Port Ltd | D29: 1 | E29: Created | F29: - | G29: - | H29: Port | I29: Concession | J29: Maharashtra | K29: 15 | L29: - | M29: Multi-Cargo | N29: Bulk | O29: - | P29: - | Q29: Southern & Western Maharashtra, Northern & Central Karnataka | R29: JSW Steel, JSW Energy | S29: Connected to NH-66 (Mumbai–Goa highway) at Nivali via SH-106 (42 km four-laned highway), Jaigarh Digni Rail Line — 33.7 km new railway corridor connecting Jaigarh Port to Digni station on the Konkan Railway network | T29: 46447 | U29: 34 | V29: 57891 | W29: Maharashtra Maritime Board | X29: - | Y29: - | Z29: - | AA29: - | AB29: - | AC29: - | AD29: =K29/(K29+K30)*23590 -> 9829.1667
B30: Dharamtar Expansion | C30: JSW Dharmatar Port Private Ltd | D30: 1 | E30: Created | F30: - | G30: - | H30: Port | I30: Lease | J30: Maharashtra | K30: 21 | L30: - | M30: Bulk | N30: Bulk | O30: - | P30: - | Q30: Dolvi, Maharashtra; Kalmeshwar, Maharashtra; Mumbai & Raigad industrial belt | R30: JSW Steel, JSW Cement | S30: Direct conveyor to Dolvi Steel Plant, Mini Bulk Carriers, Connected to NH-66 (Mumbai–Goa); located 80 km south of Mumbai, 135 km from Pune, Just 2 km from Pen railway station on the Mumbai–Goa rail route | T30: 46447 | U30: - | V30: - | W30: Maharashtra Maritime Board | X30: - | Y30: 3 | Z30: - | AA30: - | AB30: - | AC30: - | AD30: =23590-AD29 -> 13760.833
B31: Slurry Pipeline Phase I | C31: XX | D31: 1 | E31: Created | F31: - | G31: - | H31: Slurry Pipeline | I31: Captive | J31: Orissa | K31: 30 | L31: - | M31: Multi-Cargo | N31: Iron Ore | O31: - | P31: - | Q31: - | R31: JSW Steel | S31: Jatdhar Port | T31: 46478 | U31: 20 | V31: 53783 | W31: - | X31: 18 MTPA take-or-pay; full capacity 30 MTPA | Y31: - | Z31: 300km Pipeline | AA31: - | AB31: 500-550Rs/tonne | AC31: - | AD31: 40000 | AF31: JSW Steel
A32: https://infra.economictimes.indiatimes.com/news/ports-shipping/maharashtra-seeks-bids-for-a-new-port-at-murbe-under-swiss-challenge-after-jsw-infra-place-suo-moto-offer/107983282 | B32: Murbe Port | C32: JSW Murbe Port Pvt Ltd | D32: 1 | E32: Created | F32: - | G32: - | H32: Port | I32: Concession | J32: Maharashtra | K32: 33 | L32: - | M32: Container | N32: Container | O32: - | P32: - | Q32: Major industrial centres and business hubs in the hinterland of the proposed por .. Read more at: https://infra.economictimes.indiatimes.com/news/ports-shipping/maharashtra-seeks-bids-for-a-new-port-at-murbe-under-swiss-challenge-after-jsw-infra-place-suo-moto-offer/107983282 | R32: JSW group, MIDC | S32: Road: NH-8 (Mumbai–Ahmedabad national highway); Rail: Located near Delhi-Mumbai trunk rail route and the Dedicated Western Freight Corridor (DWFC) | W32: Maharashtra Maritime Board | X32: - | Y32: - | Z32: - | AA32: - | AB32: - | AC32: - | AD32: 42590
B33: Oman Port | C33: XX | D33: 1 | E33: Created | F33: - | G33: - | H33: Port | I33: Concession | J33: Overseas | K33: 27 | L33: - | M33: Bulk | N33: Steel | O33: - | P33: - | Q33: - | R33: - | S33: - | T33: - | U33: - | V33: - | W33: - | X33: - | Y33: - | Z33: - | AA33: - | AB33: - | AC33: - | AD33: =300*84 -> 25200
B34: Goa shed | C34: =C6 -> South West Port Limited | E34: Created | F34: - | G34: - | H34: Port | J34: Goa | K34: =6.5-Assumptions!K116 -> 4 | M34: Bulk | N34: - | O34: - | P34: - | Q34: - | R34: - | S34: - | T34: - | U34: - | V34: - | W34: - | X34: - | Y34: - | Z34: - | AA34: - | AB34: - | AC34: -
B35: LPG terminal | C35: =C29 -> JSW Jaigarh Port Ltd | D35: 1 | E35: Created | F35: - | G35: - | H35: Port | J35: Maharashtra | K35: 2 | M35: Liquid | N35: - | O35: - | P35: - | Q35: - | R35: - | S35: - | T35: - | U35: - | V35: - | W35: - | X35: - | Y35: - | Z35: - | AA35: - | AB35: - | AC35: -
B36: Mangalore Container Expansion | C36: =C8 -> JSW Mangalore Container Terminal Pvt Ltd | D36: 1 | E36: Created | F36: - | G36: - | H36: Port | J36: Karnataka | K36: 1.82 | M36: Container | N36: - | O36: - | P36: - | Q36: - | R36: - | S36: - | T36: - | U36: - | V36: - | W36: - | X36: - | Y36: - | Z36: - | AA36: - | AB36: - | AC36: -
B37: Kolkata Container Terminal | C37: XX | D37: 1 | E37: Created | F37: - | G37: - | H37: Terminal | J37: West Bengal | K37: 7 | M37: Container | N37: Container | Q37: eastern India, Nepal, Bhutan, and the northeastern states | R37: Garment & textile exporters ,Engineering goods manufacturers | S37: Rail: NSD is directly connected to Indian Railways' Howrah–Chennai trunk line and the Eastern Railway network, Road: Connected to NH-12 and Kolkata's arterial road network; proximity to NH-19 (Golden Quadrilateral) for road-based evacuation | T37: 46631 | U37: 30 | V37: 56887 | W37: SMPKA, Kolkata | X37: - | Y37: 2 | Z37: - | AA37: - | AB37: - | AC37: Rs. 4,678/TEU | AD37: 7400
B38: Kolkata Container Terminal - 2 | C38: XX | D38: 1 | E38: Created | F38: - | G38: - | H38: Terminal | J38: West Bengal | K38: =C239 -> 12 | M38: Container | N38: Container | Q38: eastern India, Nepal, Bhutan, and the northeastern states | R38: Garment & textile exporters ,Engineering goods manufacturers | S38: Rail: NSD is directly connected to Indian Railways' Howrah–Chennai trunk line and the Eastern Railway network, Road: Connected to NH-12 and Kolkata's arterial road network; proximity to NH-19 (Golden Quadrilateral) for road-based evacuation | T38: 47149 | U38: 30 | V38: 58106 | W38: SMPKA, Kolkata | X38: - | Y38: =5+2 -> 7 | Z38: - | AA38: - | AB38: - | AC38: Rs. 3,701/TEU | AD38: 8322.5
K39: =SUM(K26:K38) -> 219.78
B41: Pipeline
C48: MT | E48: =Consol!L3 -> 0.15246338 | F48: <- forex exposure in revenues
B49: Operational | E49: =32886.7/Consol!L78 -> 0.77495383 | F49: <-The compnay has raised H 2,99,028.00 lakhs [USD 400 million] on 21st January, 2022 by issuing USD denominated senior secured “4.95 per cent. Senior Notes due 2029” (also referred as the notes)
B50: Port | C50: =SUMIF($H$4:$H$16,"Port",$K$4:$K$16) -> 97 | E50: 0.0495
B51: Terminal | C51: =SUMIF($H$4:$H$16,"Terminal",$K$4:$K$16) -> 85.8 | E51: 400
B52: Slurry Pipeline | C52: =SUMIF($H$4:$H$16,"Slurry Pipeline",$K$4:$K$16) -> 0 | E52: =E51*83 -> 33200
B53: Total | C53: =SUM(C50:C52) -> 182.8 | E53: =+E50*E52 -> 1643.4
B54: Under Construction/Upcoming | E54: net long exposure to USD
B55: Port | C55: =SUMIF($H$26:$H$37,"Port",$K$26:$K$37) -> 163.82
B56: Terminal | C56: =SUMIF($H$26:$H$37,"Terminal",$K$26:$K$37) -> 13.96
B57: Slurry Pipeline | C57: =SUMIF($H$26:$H$37,"Slurry Pipeline",$K$26:$K$37) -> 30 | E57: Capacity | F57: MTPA
B58: Total | C58: =SUM(C55:C57) -> 207.78 | E58: Operational
B59: Operational + Under Construction | E59: Port | F59: 97
B60: Port | C60: =+C50+C55 -> 260.82 | E60: Terminal | F60: 79.9
B61: Terminal | C61: =+C51+C56 -> 99.76 | E61: Slurry Pipeline | F61: 0
B62: Slurry Pipeline | C62: =+C52+C57 -> 30 | E62: Total | F62: 176.9
B63: Total | C63: =SUM(C60:C62) -> 390.58 | E63: Under Construction/Upcoming
E64: Port | F64: 163.82
B65: Operational + Under Construction | C65: MT | E65: Terminal | F65: 18.46
B66: Maharashtra | C66: =SUMIF($J$4:$J$36,$B66,$K$4:$K$36) -> 172.5 | D66: West | E66: Slurry Pipeline | F66: 30
B67: Orissa | C67: =SUMIF($J$4:$J$36,$B67,$K$4:$K$36) -> 100 | D67: East | E67: Total | F67: 212.28
B68: Karnataka | C68: =SUMIF($J$4:$J$36,$B68,$K$4:$K$36) -> 44.12 | D68: West | E68: Operational + Under Construction
B69: Tamil Nadu | C69: =SUMIF($J$4:$J$36,$B69,$K$4:$K$36) -> 19.96 | D69: East | E69: Port | F69: 260.82
B70: Overseas | C70: =SUMIF($J$4:$J$36,$B70,$K$4:$K$36) -> 32 | E70: Terminal | F70: 98.36
B71: Goa | C71: =SUMIF($J$4:$J$36,$B71,$K$4:$K$36) -> 15 | D71: West | E71: Slurry Pipeline | F71: 30
B72: Total | C72: =SUM(C66:C71) -> 383.58 | E72: Total | F72: 389.18
B74: Capacity | C74: MT | E74: Capacity | F74: MTPA
B75: Operational | E75: Operational
B76: Bulk | C76: =SUMIF($M$4:$M$16,$B76,$K$4:$K$16) -> 114.1 | E76: Bulk | F76: 112.7
B77: Multi-Cargo | C77: =SUMIF($M$4:$M$16,$B77,$K$4:$K$16) -> 55 | E77: Multi-Cargo | F77: 55
B78: Liquid | C78: =SUMIF($M$4:$M$16,$B78,$K$4:$K$16) -> 9.5 | E78: Liquid | F78: 5
B79: Container | C79: =SUMIF($M$4:$M$16,$B79,$K$4:$K$16) -> 4.2 | E79: Container | F79: 4.2
B80: Total | C80: =SUM(C76:C79) -> 182.8 | E80: Total | F80: 176.9
B81: Under Construction | E81: Under Construction/Upcoming
B82: Bulk | C82: =SUMIF($M$26:$M$37,$B82,$K$26:$K$37) -> 88.96 | E82: Bulk | F82: 82.96
B83: Multi-Cargo | C83: =SUMIF($M$26:$M$37,$B83,$K$26:$K$37) -> 75 | E83: Multi-Cargo | F83: 81
B84: Liquid | C84: =SUMIF($M$26:$M$37,$B84,$K$26:$K$37) -> 2 | E84: Liquid | F84: 6.5
B85: Container | C85: =SUMIF($M$26:$M$37,$B85,$K$26:$K$37) -> 41.82 | E85: Container | F85: 41.82
B86: Total | C86: =SUM(C82:C85) -> 207.78 | E86: Total | F86: 212.28
B87: Operational + Under Construction | E87: Operational + Under Construction
B88: Bulk | C88: =+C76+C82 -> 203.06 | E88: Bulk | F88: 195.66
B89: Multi-Cargo | C89: =+C77+C83 -> 130 | E89: Multi-Cargo | F89: 136
B90: Liquid | C90: =+C78+C84 -> 11.5 | E90: Liquid | F90: 11.5
B91: Container | C91: =+C79+C85 -> 46.02 | E91: Container | F91: 46.02
B92: Total | C92: =SUM(C88:C91) -> 390.58 | E92: Total | F92: 389.18
C94: MT
B95: Operational - as at end of FY24
B96: Captive
B97: 3rd Party
B98: Total | C98: =SUM(C95:C97) -> 0
B99: Under Construction
B100: Captive
B101: 3rd Party
B102: Total | C102: =SUM(C100:C101) -> 0
B103: Operational + Under Construction
B104: Captive | C104: =+C96+C100 -> 0
B105: 3rd Party | C105: =+C97+C101 -> 0
B106: Total
B108: IPO | C108: Shares - nos. | J108: Key Managerial Personnel
B109: No. of Shares pre-IPO | C109: 1864707450 | H109: =C109/C111 -> 0.88795527 | J109: Sajjan Jindal | K109: Chairman
B110: New Shares | C110: 235294117 | H110: =C110/C111 -> 0.11204473 | J110: Arun Sitaram Maheshwari | K110: Joint MD and CEO | AC110: Jaigarh | AD110: 9500 | AE110: 20 MT
B111: Equity Shares outstanding after the Issue | C111: =SUM(C109:C110) -> 2100001567 | H111: =C111/C111 -> 1 | J111: Lalit Chandanmal Singhvi | K111: CFO | O111: 2 berths in goa | AC111: Dharamtart | AD111: =18400-AD110 -> 8900 | AE111: 16 MT
B112: Dilution | C112: =1-C109/C111 -> 0.11204473 | O112: 1 in standalone | P112: belonged to adani and was not able to do minimum thorughput
O113: 1 in south west goa
...

Sheet Assumptions
S1: CAGR
B2: Volumes by Port, MT | C2: Port | D2: FY18 | E2: FY19 | F2: FY20 | G2: FY21 | H2: FY22 | I2: FY23 | J2: FY24 | K2: FY25 | L2: FY26 | M2: FY27E | N2: FY28E | O2: FY29E | P2: FY30E | S2: FY26-28E | T2: FY26-30E
B3: Standalone | D3: 0 | E3: 4.19 | F3: 3.1759323 | G3: 3.59 | H3: 3.0277206 | I3: 2.7 | J3: 2.65 | K3: 2.4 | L3: 2.99 | M3: =M943 -> 2.99 | N3: =N943 -> 3.0498 | O3: =O943 -> 3.110796 | P3: =P943 -> 3.1730119 | R3: =N3-M3 -> 0.0598 | S3: =IF(ISERROR((N3/L3)^(1/6)-1)," ",(N3/L3)^(1/2)-1) -> 0.0099504938 | T3: =IF(ISERROR((P3/L3)^(1/6)-1)," ",(P3/L3)^(1/4)-1) -> 0.014962809 | X3: =E2 -> FY19 | Y3: =F2 -> FY20 | Z3: =G2 -> FY21 | AA3: =H2 -> FY22 | AB3: =I2 -> FY23 | AC3: =J2 -> FY24
B4: Jaigarh | D4: 9.535 | E4: 13.05 | F4: 10.370319 | G4: 9.238 | H4: 14.019484 | I4: 20.237 | J4: 21.51 | K4: 19.9 | L4: 20.27 | M4: =M468 -> 21.0808 | N4: =N468 -> 26.303368 | O4: =O468 -> 28.933705 | P4: =P468 -> 30.38039 | Q4: << without transhipment volumes of large ships, trans shipment revenue booked in Jaigarh | R4: =N4-M4 -> 5.222568 | S4: =IF(ISERROR((N4/L4)^(1/6)-1)," ",(N4/L4)^(1/2)-1) -> 0.13914447 | T4: =IF(ISERROR((P4/L4)^(1/6)-1)," ",(P4/L4)^(1/4)-1) -> 0.10645791 | W4: East Coast | X4: =E7+E8+E9+E10 -> 0 | Y4: =F7+F8+F9+F10 -> 1.013 | Z4: =G7+G8+G9+G10 -> 11.96 | AA4: =H7+H8+H9+H10 -> 16.989441 | AB4: =I7+I8+I9+I10 -> 32.148 | AC4: =J7+J8+J9+J10 -> 39.91
B5: Dharmatar | D5: 11.66 | E5: 12.88 | F5: 12.840226 | G5: 12.9 | H5: 17.209493 | I5: 24.03 | J5: 25.14 | K5: 23.1 | L5: 24.53 | M5: =M551 -> 25.47996 | N5: =N551 -> 31.6482 | O5: =O551 -> 34.73232 | P5: =P551 -> 35.75008 | Q5: <<< Includes transhipment volumes of large ships, books cargo handling charges | R5: =N5-M5 -> 6.16824 | S5: =IF(ISERROR((N5/L5)^(1/6)-1)," ",(N5/L5)^(1/2)-1) -> 0.13586243 | T5: =IF(ISERROR((P5/L5)^(1/6)-1)," ",(P5/L5)^(1/4)-1) -> 0.098739825 | W5: West Coast | X5: =E4+E5+E6+E11+E12+E13 -> 31.18 | Y5: =F4+F5+F6+F11+F12+F13 -> 29.821524 | Z5: =G4+G5+G6+G11+G12+G13 -> 29.988 | AA5: =H4+H5+H6+H11+H12+H13 -> 41.945488 | AB5: =I4+I5+I6+I11+I12+I13 -> 57.962998 | AC5: =J4+J5+J6+J11+J12+J13 -> 62.478162
B6: Goa | D6: 10.9 | E6: 5.25 | F6: 6.610979 | G6: 6.83 | H6: 6.9256087 | I6: 7.068 | J6: 7.156 | K6: 6.4 | L6: 8.55 | M6: =M600 -> 9.3918 | N6: =N600 -> 10.80057 | O6: =O600 -> 11.273465 | P6: =P600 -> 11.767319 | R6: =N6-M6 -> 1.40877 | S6: =IF(ISERROR((N6/L6)^(1/6)-1)," ",(N6/L6)^(1/2)-1) -> 0.12393263 | T6: =IF(ISERROR((P6/L6)^(1/6)-1)," ",(P6/L6)^(1/4)-1) -> 0.083123194 | X6: =SUM(X5:X5) -> 31.18 | Y6: =SUM(Y5:Y5) -> 29.821524 | Z6: =SUM(Z5:Z5) -> 29.988 | AA6: =SUM(AA5:AA5) -> 41.945488 | AB6: =SUM(AB5:AB5) -> 57.962998 | AC6: =SUM(AC5:AC5) -> 62.478162
B7: Paradip Iron Ore | D7: 0 | E7: 0 | F7: 1.013 | G7: 8.43 | H7: 7.516115 | I7: 9.52 | J7: 12.37 | K7: 11.4 | L7: 7.26 | M7: =M649 -> 9.438 | N7: =N649 -> 9.53238 | O7: =O649 -> 9.6277038 | P7: =P649 -> 9.7239808 | R7: =N7-M7 -> 0.09438 | S7: =IF(ISERROR((N7/L7)^(1/6)-1)," ",(N7/L7)^(1/2)-1) -> 0.14586212 | T7: =IF(ISERROR((P7/L7)^(1/6)-1)," ",(P7/L7)^(1/4)-1) -> 0.075788428 | X7: =+X4/X$6 -> 0 | Y7: =+Y4/Y$6 -> 0.033968754 | Z7: =+Z4/Z$6 -> 0.3988262 | AA7: =+AA4/AA$6 -> 0.40503621 | AB7: =+AB4/AB$6 -> 0.5546297 | AC7: =+AC4/AC$6 -> 0.63878319
B8: Paradip Coal | D8: 0 | E8: 0 | F8: 0 | G8: 0 | H8: 0.280675 | I8: 12.034 | J8: 16.77 | K8: 18.9 | L8: 19.01 | M8: =M698 -> 19.3902 | N8: =N698 -> 20.553612 | O8: =O698 -> 21.786829 | P8: =P698 -> 23.094038 | R8: =N8-M8 -> 1.163412 | S8: =IF(ISERROR((N8/L8)^(1/6)-1)," ",(N8/L8)^(1/2)-1) -> 0.039807675 | T8: =IF(ISERROR((P8/L8)^(1/6)-1)," ",(P8/L8)^(1/4)-1) -> 0.049855292 | X8: =+X5/X$6 -> 1 | Y8: =+Y5/Y$6 -> 1 | Z8: =+Z5/Z$6 -> 1 | AA8: =+AA5/AA$6 -> 1 | AB8: =+AB5/AB$6 -> 1 | AC8: =+AC5/AC$6 -> 1
B9: Ennore Coal | D9: 0 | E9: 0 | F9: 0 | G9: 3.14 | H9: 8.032416 | I9: 8.704 | J9: 9.31 | K9: 10.2 | L9: 10.38 | M9: =M747 -> 10.4838 | N9: =N747 -> 10.588638 | O9: =O747 -> 10.694524 | P9: =P747 -> 10.80147 | R9: =N9-M9 -> 0.104838 | S9: =IF(ISERROR((N9/L9)^(1/6)-1)," ",(N9/L9)^(1/2)-1) -> 0.01 | T9: =IF(ISERROR((P9/L9)^(1/6)-1)," ",(P9/L9)^(1/4)-1) -> 0.01
B10: Ennore Bulk | D10: 0 | E10: 0 | F10: 0 | G10: 0.39 | H10: 1.1602351 | I10: 1.89 | J10: 1.46 | K10: 2.1 | L10: 1.65 | M10: =M796 -> 1.72935 | N10: =N796 -> 1.8158175 | O10: =O796 -> 1.9066084 | P10: =P796 -> 2.0019388 | R10: =N10-M10 -> 0.0864675 | S10: =IF(ISERROR((N10/L10)^(1/6)-1)," ",(N10/L10)^(1/2)-1) -> 0.04904502 | T10: =IF(ISERROR((P10/L10)^(1/6)-1)," ",(P10/L10)^(1/4)-1) -> 0.049522402
B11: Mangalore Coal | D11: 0 | E11: 0 | F11: 0 | G11: 1.02 | H11: 3.7909015 | I11: 4.454 | J11: 4.77 | K11: 6.3 | L11: 6.27 | M11: =M845 -> 6.5835 | N11: =N845 -> 6.912675 | O11: =O845 -> 7.2583088 | P11: =P845 -> 7.6212242 | R11: =N11-M11 -> 0.329175 | S11: =IF(ISERROR((N11/L11)^(1/6)-1)," ",(N11/L11)^(1/2)-1) -> 0.05 | T11: =IF(ISERROR((P11/L11)^(1/6)-1)," ",(P11/L11)^(1/4)-1) -> 0.05
B12: Mangalore Container | D12: 0 | E12: 0 | F12: 0 | G12: 0 | H12: 0 | I12: 2.1739977 | J12: 2.5821624 | K12: 2.4 | L12: 2.49 | M12: =M894 -> 3.1175 | N12: =N894 -> 3.42925 | O12: =O894 -> 3.635005 | P12: =P894 -> 3.8531053 | R12: =N12-M12 -> 0.31175 | S12: =IF(ISERROR((N12/L12)^(1/6)-1)," ",(N12/L12)^(1/2)-1) -> 0.17354541 | T12: =IF(ISERROR((P12/L12)^(1/6)-1)," ",(P12/L12)^(1/4)-1) -> 0.11532871
B13: PNP Port | J13: 1.32 | K13: 5.5 | L13: 5.34 | M13: =M991 -> 6.1387 | N13: =N991 -> 6.261474 | O13: =O991 -> 6.5745477 | P13: =P991 -> 6.9032751 | R13: =N13-M13 -> 0.122774 | S13: =IF(ISERROR((N13/L13)^(1/6)-1)," ",(N13/L13)^(1/2)-1) -> 0.082848408 | T13: =IF(ISERROR((P13/L13)^(1/6)-1)," ",(P13/L13)^(1/4)-1) -> 0.06629772
B14: Fujairah Liquid Storage | J14: 2 | K14: 7.3 | L14: 5.71 | M14: =M1041 -> 2.855 | N14: =N1041 -> 4.99625 | O14: =O1041 -> 5.9955 | P14: =P1041 -> 6.23532 | R14: =N14-M14 -> 2.14125 | S14: =IF(ISERROR((N14/L14)^(1/6)-1)," ",(N14/L14)^(1/2)-1) -> -0.064585653 | T14: =IF(ISERROR((P14/L14)^(1/6)-1)," ",(P14/L14)^(1/4)-1) -> 0.022246564
B15: Tuticorin Dry Bulk | K15: 0.9 | L15: 4.99 | M15: =M1090 -> 5.25 | N15: =N1090 -> 5.25 | O15: =O1090 -> 5.25 | P15: =P1090 -> 5.25 | R15: =N15-M15 -> 0 | S15: =IF(ISERROR((N15/L15)^(1/6)-1)," ",(N15/L15)^(1/2)-1) -> 0.025721311 | T15: =IF(ISERROR((P15/L15)^(1/6)-1)," ",(P15/L15)^(1/4)-1) -> 0.012779004
B16: JNPT Liquid | K16: 0.2 | L16: 1.3 | M16: =M1139 -> 2.925 | N16: =N1139 -> 3.15 | O16: =O1139 -> 3.375 | P16: =P1139 -> 3.375 | R16: =N16-M16 -> 0.225 | S16: =IF(ISERROR((N16/L16)^(1/6)-1)," ",(N16/L16)^(1/2)-1) -> 0.55662356 | T16: =IF(ISERROR((P16/L16)^(1/6)-1)," ",(P16/L16)^(1/4)-1) -> 0.26935356
B17: Keni | M17: =M1188 -> 0 | N17: =N1188 -> 0 | O17: =O1188 -> 1.5 | P17: =P1188 -> 9 | Q17: =+P17/P27 -> 0.037912272 | R17: =N17-M17 -> 0 | S17: =IF(ISERROR((N17/L17)^(1/6)-1)," ",(N17/L17)^(1/2)-1) | T17: =IF(ISERROR((P17/L17)^(1/6)-1)," ",(P17/L17)^(1/4)-1)
B18: Jatadhar | M18: =M1237 -> 0 | N18: =N1237 -> 10.05 | O18: =O1237 -> 16.5 | P18: =P1237 -> 21 | R18: =N18-M18 -> 10.05 | S18: =IF(ISERROR((N18/L18)^(1/6)-1)," ",(N18/L18)^(1/2)-1) | T18: =IF(ISERROR((P18/L18)^(1/6)-1)," ",(P18/L18)^(1/4)-1)
B19: Slurry Pipeline Phase I | M19: =M1286 -> 0 | N19: =N1286 -> 12 | O19: =O1286 -> 18 | P19: =P1286 -> 18 | R19: =N19-M19 -> 12 | S19: =IF(ISERROR((N19/L19)^(1/6)-1)," ",(N19/L19)^(1/2)-1) | T19: =IF(ISERROR((P19/L19)^(1/6)-1)," ",(P19/L19)^(1/4)-1)
B20: Slurry Pipeline Phase II | M20: =M1335 -> 0 | N20: =N1335 -> 0 | O20: =O1335 -> 0 | P20: =P1335 -> 0 | R20: =N20-M20 -> 0 | S20: =IF(ISERROR((N20/L20)^(1/6)-1)," ",(N20/L20)^(1/2)-1) | T20: =IF(ISERROR((P20/L20)^(1/6)-1)," ",(P20/L20)^(1/4)-1) | W20: JSW Infrastructure | X20: FY23 | Y20: FY24 | Z20: FY25 | AA20: FY26 | AB20: FY27E | AC20: FY28E | AD20: CAGR
B21: Murbe | M21: =M1384 -> 0 | N21: =N1384 -> 0 | O21: =O1384 -> 0 | P21: =P1384 -> 8.25 | Q21: =+P21/P27 -> 0.034752916 | R21: =N21-M21 -> 0 | S21: =IF(ISERROR((N21/L21)^(1/6)-1)," ",(N21/L21)^(1/2)-1) | T21: =IF(ISERROR((P21/L21)^(1/6)-1)," ",(P21/L21)^(1/4)-1) | W21: Port wise volumes- mn tonnes | AD21: FY26-28E
B22: Oman Port | M22: =M1423 -> 0 | N22: =N1423 -> 0 | O22: =O1423 -> 0 | P22: =P1432 -> 10.8 | Q22: =+P22/P27 -> 0.045494726 | R22: =N22-M22 -> 0 | S22: =IF(ISERROR((N22/L22)^(1/6)-1)," ",(N22/L22)^(1/2)-1) | T22: =IF(ISERROR((P22/L22)^(1/6)-1)," ",(P22/L22)^(1/4)-1) | W22: =B3 -> Standalone | X22: =I3 -> 2.7 | Y22: =J3 -> 2.65 | Z22: =K3 -> 2.4 | AA22: =L3 -> 2.99 | AB22: =M3 -> 2.99 | AC22: =N3 -> 3.0498 | AD22: =IFERROR((AC22/AA22)^(0.5)-1, "NM") -> 0.0099504938
B23: Kolkata Container Terminal | M23: =M1481 -> 1.1025 | N23: =N1481 -> 2.205 | O23: =O1481 -> 3.78 | P23: =P1481 -> 4.41 | R23: =N23-M23 -> 1.1025 | S23: =IF(ISERROR((N23/L23)^(1/6)-1)," ",(N23/L23)^(1/2)-1) | T23: =IF(ISERROR((P23/L23)^(1/6)-1)," ",(P23/L23)^(1/4)-1) | W23: =B4 -> Jaigarh | X23: =I4 -> 20.237 | Y23: =J4 -> 21.51 | Z23: =K4 -> 19.9 | AA23: =L4 -> 20.27 | AB23: =M4 -> 21.0808 | AC23: =N4 -> 26.303368 | AD23: =IFERROR((AC23/AA23)^(0.5)-1, "NM") -> 0.13914447
B24: Kolkata Container Terminal 2 | M24: =M1530 -> 0 | N24: =N1530 -> 0 | O24: =O1530 -> 3 | P24: =P1530 -> 6 | R24: =N24-M24 -> 0 | S24: =IF(ISERROR((N24/L24)^(1/6)-1)," ",(N24/L24)^(1/2)-1) | T24: =IF(ISERROR((P24/L24)^(1/6)-1)," ",(P24/L24)^(1/4)-1) | W24: =B5 -> Dharmatar | X24: =I5 -> 24.03 | Y24: =J5 -> 25.14 | Z24: =K5 -> 23.1 | AA24: =L5 -> 24.53 | AB24: =M5 -> 25.47996 | AC24: =N5 -> 31.6482 | AD24: =IFERROR((AC24/AA24)^(0.5)-1, "NM") -> 0.13586243
B25: xxx | M25: 0 | N25: 0 | O25: 0 | P25: 0 | R25: =N25-M25 -> 0 | S25: =IF(ISERROR((N25/L25)^(1/6)-1)," ",(N25/L25)^(1/2)-1) | T25: =IF(ISERROR((P25/L25)^(1/6)-1)," ",(P25/L25)^(1/4)-1) | W25: =B6 -> Goa | X25: =I6 -> 7.068 | Y25: =J6 -> 7.156 | Z25: =K6 -> 6.4 | AA25: =L6 -> 8.55 | AB25: =M6 -> 9.3918 | AC25: =N6 -> 10.80057 | AD25: =IFERROR((AC25/AA25)^(0.5)-1, "NM") -> 0.12393263
B26: xxx | R26: =N26-M26 -> 0 | S26: =IF(ISERROR((N26/L26)^(1/6)-1)," ",(N26/L26)^(1/2)-1) | T26: =IF(ISERROR((P26/L26)^(1/6)-1)," ",(P26/L26)^(1/4)-1) | W26: =B7 -> Paradip Iron Ore | X26: =I7 -> 9.52 | Y26: =J7 -> 12.37 | Z26: =K7 -> 11.4 | AA26: =L7 -> 7.26 | AB26: =M7 -> 9.438 | AC26: =N7 -> 9.53238 | AD26: =IFERROR((AC26/AA26)^(0.5)-1, "NM") -> 0.14586212
B27: Total Cargo Handled | D27: =SUM(D3:D26) -> 32.095 | E27: =SUM(E3:E26) -> 35.37 | F27: =SUM(F3:F26) -> 34.010456 | G27: =SUM(G3:G26) -> 45.538 | H27: =SUM(H3:H26) -> 61.962649 | I27: =SUM(I3:I26) -> 92.810998 | J27: =SUM(J3:J26) -> 107.03816 | K27: =SUM(K3:K26) -> 117 | ... P27: =SUM(P3:P26) -> 237.39015 | Q27: =(L27/J27)^(1/2)-1 -> 0.062077634 | R27: =N27-M27 -> 40.590924 | S27: =IF(ISERROR((N27/L27)^(1/2)-1)," ",(N27/L27)^(1/2)-1) -> 0.18150339 | T27: =IF(ISERROR((P27/L27)^(1/4)-1)," ",(P27/L27)^(1/4)-1) -> 0.18413954 | U27: =(N27/L27)^(1/2)-1 -> 0.18150339 | V27: =(P27/L27)^(1/4)-1 -> 0.18413954 | W27: =B8 -> Paradip Coal | X27: =I8 -> 12.034 | Y27: =J8 -> 16.77 | Z27: =K8 -> 18.9 | AA27: =L8 -> 19.01 | AB27: =M8 -> 19.3902 | AC27: =N8 -> 20.553612 | AD27: =IFERROR((AC27/AA27)^(0.5)-1, "NM") -> 0.039807675
F28: =Consol!I16/Assumptions!F27 -> 336.11584 | W28: =B9 -> Ennore Coal | X28: =I9 -> 8.704 | Y28: =J9 -> 9.31 | Z28: =K9 -> 10.2 | AA28: =L9 -> 10.38 | AB28: =M9 -> 10.4838 | AC28: =N9 -> 10.588638 | AD28: =IFERROR((AC28/AA28)^(0.5)-1, "NM") -> 0.01
B29: O&M Volumes | W29: =B10 -> Ennore Bulk | X29: =I10 -> 1.89 | Y29: =J10 -> 1.46 | Z29: =K10 -> 2.1 | AA29: =L10 -> 1.65 | AB29: =M10 -> 1.72935 | AC29: =N10 -> 1.8158175 | AD29: =IFERROR((AC29/AA29)^(0.5)-1, "NM") -> 0.04904502
B30: Fujairah | G30: 13.17 | H30: 13.78 | I30: 11.78 | W30: =B11 -> Mangalore Coal | X30: =I11 -> 4.454 | Y30: =J11 -> 4.77 | Z30: =K11 -> 6.3 | AA30: =L11 -> 6.27 | AB30: =M11 -> 6.5835 | AC30: =N11 -> 6.912675 | AD30: =IFERROR((AC30/AA30)^(0.5)-1, "NM") -> 0.05
B31: Dibba | G31: 0 | H31: 0 | I31: 0 | W31: =B12 -> Mangalore Container | X31: =I12 -> 2.1739977 | Y31: =J12 -> 2.5821624 | Z31: =K12 -> 2.4 | AA31: =L12 -> 2.49 | AB31: =M12 -> 3.1175 | AC31: =N12 -> 3.42925 | AD31: =IFERROR((AC31/AA31)^(0.5)-1, "NM") -> 0.17354541
W32: =B13 -> PNP Port | X32: =I13 -> 0 | Y32: =J13 -> 1.32 | Z32: =K13 -> 5.5 | AA32: =L13 -> 5.34 | AB32: =M13 -> 6.1387 | AC32: =N13 -> 6.261474 | AD32: =IFERROR((AC32/AA32)^(0.5)-1, "NM") -> 0.082848408
B33: Growth, yoy % | W33: =B14 -> Fujairah Liquid Storage | X33: =I14 -> 0 | Y33: =J14 -> 2 | Z33: =K14 -> 7.3 | AA33: =L14 -> 5.71 | AB33: =M14 -> 2.855 | AC33: =N14 -> 4.99625 | AD33: =IFERROR((AC33/AA33)^(0.5)-1, "NM") -> -0.064585653
B34: Standalone | E34: =IFERROR(E3/D3-1,"--") -> -- | F34: =IFERROR(F3/E3-1,"--") -> -0.24202094 | G34: =IFERROR(G3/F3-1,"--") -> 0.13037675 | H34: =IFERROR(H3/G3-1,"--") -> -0.15662379 | I34: =IFERROR(I3/H3-1,"--") -> -0.10824004 | J34: =IFERROR(J3/I3-1,"--") -> -0.018518519 | K34: =IFERROR(K3/J3-1,"--") -> -0.094339623 | L34: =IFERROR(L3/K3-1,"--") -> 0.24583333 | ... P34: =IFERROR(P3/O3-1,"--") -> 0.02 | W34: =B15 -> Tuticorin Dry Bulk | X34: =I15 -> 0 | Y34: =J15 -> 0 | Z34: =K15 -> 0.9 | AA34: =L15 -> 4.99 | AB34: =M15 -> 5.25 | AC34: =N15 -> 5.25 | AD34: =IFERROR((AC34/AA34)^(0.5)-1, "NM") -> 0.025721311
B35: Jaigarh | E35: =IFERROR(E4/D4-1,"--") -> 0.36864185 | F35: =IFERROR(F4/E4-1,"--") -> -0.20533956 | G35: =IFERROR(G4/F4-1,"--") -> -0.10918842 | H35: =IFERROR(H4/G4-1,"--") -> 0.51758866 | I35: =IFERROR(I4/H4-1,"--") -> 0.44349107 | J35: =IFERROR(J4/I4-1,"--") -> 0.062904581 | K35: =IFERROR(K4/J4-1,"--") -> -0.074848907 | L35: =IFERROR(L4/K4-1,"--") -> 0.018592965 | ... P35: =IFERROR(P4/O4-1,"--") -> 0.05 | W35: =B16 -> JNPT Liquid | X35: =I16 -> 0 | Y35: =J16 -> 0 | Z35: =K16 -> 0.2 | AA35: =L16 -> 1.3 | AB35: =M16 -> 2.925 | AC35: =N16 -> 3.15 | AD35: =IFERROR((AC35/AA35)^(0.5)-1, "NM") -> 0.55662356
B36: Dharmatar | E36: =IFERROR(E5/D5-1,"--") -> 0.10463122 | F36: =IFERROR(F5/E5-1,"--") -> -0.0030880435 | G36: =IFERROR(G5/F5-1,"--") -> 0.004655214 | H36: =IFERROR(H5/G5-1,"--") -> 0.33406925 | I36: =IFERROR(I5/H5-1,"--") -> 0.39632234 | J36: =IFERROR(J5/I5-1,"--") -> 0.04619226 | K36: =IFERROR(K5/J5-1,"--") -> -0.081145585 | L36: =IFERROR(L5/K5-1,"--") -> 0.061904762 | ... P36: =IFERROR(P5/O5-1,"--") -> 0.029302955 | W36: =B18 -> Jatadhar | X36: =I18 -> 0 | Y36: =J18 -> 0 | Z36: =K18 -> 0 | AA36: =L18 -> 0 | AB36: =M18 -> 0 | AC36: =N18 -> 10.05 | AD36: =IFERROR((AC36/AA36)^(0.5)-1, "NM") -> NM
B37: Goa | E37: =IFERROR(E6/D6-1,"--") -> -0.51834862 | F37: =IFERROR(F6/E6-1,"--") -> 0.2592341 | G37: =IFERROR(G6/F6-1,"--") -> 0.033129889 | H37: =IFERROR(H6/G6-1,"--") -> 0.013998351 | I37: =IFERROR(I6/H6-1,"--") -> 0.020560108 | J37: =IFERROR(J6/I6-1,"--") -> 0.012450481 | K37: =IFERROR(K6/J6-1,"--") -> -0.10564561 | L37: =IFERROR(L6/K6-1,"--") -> 0.3359375 | ... P37: =IFERROR(P6/O6-1,"--") -> 0.043806794 | W37: =B19 -> Slurry Pipeline Phase I | X37: =I19 -> 0 | Y37: =J19 -> 0 | Z37: =K19 -> 0 | AA37: =L19 -> 0 | AB37: =M19 -> 0 | AC37: =N19 -> 12 | AD37: =IFERROR((AC37/AA37)^(0.5)-1, "NM") -> NM
B38: Paradip Iron Ore | E38: =IFERROR(E7/D7-1,"--") -> -- | F38: =IFERROR(F7/E7-1,"--") -> -- | G38: =IFERROR(G7/F7-1,"--") -> 7.3218164 | H38: =IFERROR(H7/G7-1,"--") -> -0.10840866 | I38: =IFERROR(I7/H7-1,"--") -> 0.26661181 | J38: =IFERROR(J7/I7-1,"--") -> 0.29936975 | K38: =IFERROR(K7/J7-1,"--") -> -0.078415521 | L38: =IFERROR(L7/K7-1,"--") -> -0.36315789 | ... P38: =IFERROR(P7/O7-1,"--") -> 0.01 | W38: =B23 -> Kolkata Container Terminal | X38: =I23 -> 0 | Y38: =J23 -> 0 | Z38: =K23 -> 0 | AA38: =L23 -> 0 | AB38: =M23 -> 1.1025 | AC38: =N23 -> 2.205 | AD38: =IFERROR((AC38/AA38)^(0.5)-1, "NM") -> NM
B39: Paradip Coal | E39: =IFERROR(E8/D8-1,"--") -> -- | F39: =IFERROR(F8/E8-1,"--") -> -- | G39: =IFERROR(G8/F8-1,"--") -> -- | H39: =IFERROR(H8/G8-1,"--") -> -- | I39: =IFERROR(I8/H8-1,"--") -> 41.875212 | J39: =IFERROR(J8/I8-1,"--") -> 0.3935516 | K39: =IFERROR(K8/J8-1,"--") -> 0.12701252 | L39: =IFERROR(L8/K8-1,"--") -> 0.0058201058 | ... P39: =IFERROR(P8/O8-1,"--") -> 0.06 | W39: Total | X39: =SUM(X22:X38) -> 92.810998 | Y39: =SUM(Y22:Y38) -> 107.03816 | Z39: =SUM(Z22:Z38) -> 117 | AA39: =SUM(AA22:AA38) -> 120.74 | AB39: =SUM(AB22:AB38) -> 127.95611 | AC39: =SUM(AC22:AC38) -> 168.54703 | AD39: =IFERROR((AC39/AA39)^(0.5)-1, "NM") -> 0.18150339
B40: Ennore Coal | E40: =IFERROR(E9/D9-1,"--") -> -- | F40: =IFERROR(F9/E9-1,"--") -> -- | G40: =IFERROR(G9/F9-1,"--") -> -- | H40: =IFERROR(H9/G9-1,"--") -> 1.5580943 | I40: =IFERROR(I9/H9-1,"--") -> 0.083609215 | J40: =IFERROR(J9/I9-1,"--") -> 0.069623162 | K40: =IFERROR(K9/J9-1,"--") -> 0.095596133 | L40: =IFERROR(L9/K9-1,"--") -> 0.017647059 | ... P40: =IFERROR(P9/O9-1,"--") -> 0.01
B41: Ennore Bulk | E41: =IFERROR(E10/D10-1,"--") -> -- | F41: =IFERROR(F10/E10-1,"--") -> -- | G41: =IFERROR(G10/F10-1,"--") -> -- | H41: =IFERROR(H10/G10-1,"--") -> 1.9749618 | I41: =IFERROR(I10/H10-1,"--") -> 0.62898021 | J41: =IFERROR(J10/I10-1,"--") -> -0.22751323 | K41: =IFERROR(K10/J10-1,"--") -> 0.43835616 | L41: =IFERROR(L10/K10-1,"--") -> -0.21428571 | ... P41: =IFERROR(P10/O10-1,"--") -> 0.05 | W41: Growth,yoy
B42: Mangalore Coal | E42: =IFERROR(E11/D11-1,"--") -> -- | F42: =IFERROR(F11/E11-1,"--") -> -- | G42: =IFERROR(G11/F11-1,"--") -> -- | H42: =IFERROR(H11/G11-1,"--") -> 2.7165701 | I42: =IFERROR(I11/H11-1,"--") -> 0.17491843 | J42: =IFERROR(J11/I11-1,"--") -> 0.070947463 | K42: =IFERROR(K11/J11-1,"--") -> 0.32075472 | L42: =IFERROR(L11/K11-1,"--") -> -0.0047619048 | ... P42: =IFERROR(P11/O11-1,"--") -> 0.05 | W42: =W22 -> Standalone | Y42: =IF(ISERROR(Y22/X22-1), "-", (Y22/X22-1)) -> -0.018518519 | Z42: =IF(ISERROR(Z22/Y22-1), "-", (Z22/Y22-1)) -> -0.094339623 | AA42: =IF(ISERROR(AA22/Z22-1), "-", (AA22/Z22-1)) -> 0.24583333 | AB42: =IF(ISERROR(AB22/AA22-1), "-", (AB22/AA22-1)) -> 2.220446e-16 | AC42: =IF(ISERROR(AC22/AB22-1), "-", (AC22/AB22-1)) -> 0.02
B43: Mangalore Container | E43: =IFERROR(E12/D12-1,"--") -> -- | F43: =IFERROR(F12/E12-1,"--") -> -- | G43: =IFERROR(G12/F12-1,"--") -> -- | H43: =IFERROR(H12/G12-1,"--") -> -- | I43: =IFERROR(I12/H12-1,"--") -> -- | J43: =IFERROR(J12/I12-1,"--") -> 0.18774848 | K43: =IFERROR(K12/J12-1,"--") -> -0.07054647 | L43: =IFERROR(L12/K12-1,"--") -> 0.0375 | ... P43: =IFERROR(P12/O12-1,"--") -> 0.06 | W43: =W23 -> Jaigarh | Y43: =IF(ISERROR(Y23/X23-1), "-", (Y23/X23-1)) -> 0.062904581 | Z43: =IF(ISERROR(Z23/Y23-1), "-", (Z23/Y23-1)) -> -0.074848907 | AA43: =IF(ISERROR(AA23/Z23-1), "-", (AA23/Z23-1)) -> 0.018592965 | AB43: =IF(ISERROR(AB23/AA23-1), "-", (AB23/AA23-1)) -> 0.04 | AC43: =IF(ISERROR(AC23/AB23-1), "-", (AC23/AB23-1)) -> 0.2477405
B44: PNP Port | E44: =IFERROR(E13/D13-1,"--") -> -- | F44: =IFERROR(F13/E13-1,"--") -> -- | G44: =IFERROR(G13/F13-1,"--") -> -- | H44: =IFERROR(H13/G13-1,"--") -> -- | I44: =IFERROR(I13/H13-1,"--") -> -- | J44: =IFERROR(J13/I13-1,"--") -> -- | K44: =IFERROR(K13/J13-1,"--") -> 3.1666667 | L44: =IFERROR(L13/K13-1,"--") -> -0.029090909 | ... P44: =IFERROR(P13/O13-1,"--") -> 0.05 | W44: =W24 -> Dharmatar | Y44: =IF(ISERROR(Y24/X24-1), "-", (Y24/X24-1)) -> 0.04619226 | Z44: =IF(ISERROR(Z24/Y24-1), "-", (Z24/Y24-1)) -> -0.081145585 | AA44: =IF(ISERROR(AA24/Z24-1), "-", (AA24/Z24-1)) -> 0.061904762 | AB44: =IF(ISERROR(AB24/AA24-1), "-", (AB24/AA24-1)) -> 0.038726457 | AC44: =IF(ISERROR(AC24/AB24-1), "-", (AC24/AB24-1)) -> 0.24208201
B45: Fujairah Liquid Storage | E45: =IFERROR(E14/D14-1,"--") -> -- | F45: =IFERROR(F14/E14-1,"--") -> -- | G45: =IFERROR(G14/F14-1,"--") -> -- | H45: =IFERROR(H14/G14-1,"--") -> -- | I45: =IFERROR(I14/H14-1,"--") -> -- | J45: =IFERROR(J14/I14-1,"--") -> -- | K45: =IFERROR(K14/J14-1,"--") -> 2.65 | L45: =IFERROR(L14/K14-1,"--") -> -0.21780822 | ... P45: =IFERROR(P14/O14-1,"--") -> 0.04 | W45: =W25 -> Goa | Y45: =IF(ISERROR(Y25/X25-1), "-", (Y25/X25-1)) -> 0.012450481 | Z45: =IF(ISERROR(Z25/Y25-1), "-", (Z25/Y25-1)) -> -0.10564561 | AA45: =IF(ISERROR(AA25/Z25-1), "-", (AA25/Z25-1)) -> 0.3359375 | AB45: =IF(ISERROR(AB25/AA25-1), "-", (AB25/AA25-1)) -> 0.09845614 | AC45: =IF(ISERROR(AC25/AB25-1), "-", (AC25/AB25-1)) -> 0.15
B46: Tuticorin Dry Bulk | E46: =IFERROR(E15/D15-1,"--") -> -- | F46: =IFERROR(F15/E15-1,"--") -> -- | G46: =IFERROR(G15/F15-1,"--") -> -- | H46: =IFERROR(H15/G15-1,"--") -> -- | I46: =IFERROR(I15/H15-1,"--") -> -- | J46: =IFERROR(J15/I15-1,"--") -> -- | K46: =IFERROR(K15/J15-1,"--") -> -- | L46: =IFERROR(L15/K15-1,"--") -> 4.5444444 | ... P46: =IFERROR(P15/O15-1,"--") -> 0 | W46: =W26 -> Paradip Iron Ore | Y46: =IF(ISERROR(Y26/X26-1), "-", (Y26/X26-1)) -> 0.29936975 | Z46: =IF(ISERROR(Z26/Y26-1), "-", (Z26/Y26-1)) -> -0.078415521 | AA46: =IF(ISERROR(AA26/Z26-1), "-", (AA26/Z26-1)) -> -0.36315789 | AB46: =IF(ISERROR(AB26/AA26-1), "-", (AB26/AA26-1)) -> 0.3 | AC46: =IF(ISERROR(AC26/AB26-1), "-", (AC26/AB26-1)) -> 0.01
B47: JNPT Liquid | E47: =IFERROR(E16/D16-1,"--") -> -- | F47: =IFERROR(F16/E16-1,"--") -> -- | G47: =IFERROR(G16/F16-1,"--") -> -- | H47: =IFERROR(H16/G16-1,"--") -> -- | I47: =IFERROR(I16/H16-1,"--") -> -- | J47: =IFERROR(J16/I16-1,"--") -> -- | K47: =IFERROR(K16/J16-1,"--") -> -- | L47: =IFERROR(L16/K16-1,"--") -> 5.5 | ... P47: =IFERROR(P16/O16-1,"--") -> 0 | W47: =W27 -> Paradip Coal | Y47: =IF(ISERROR(Y27/X27-1), "-", (Y27/X27-1)) -> 0.3935516 | Z47: =IF(ISERROR(Z27/Y27-1), "-", (Z27/Y27-1)) -> 0.12701252 | AA47: =IF(ISERROR(AA27/Z27-1), "-", (AA27/Z27-1)) -> 0.0058201058 | AB47: =IF(ISERROR(AB27/AA27-1), "-", (AB27/AA27-1)) -> 0.02 | AC47: =IF(ISERROR(AC27/AB27-1), "-", (AC27/AB27-1)) -> 0.06
B48: Keni | E48: =IFERROR(E17/D17-1,"--") -> -- | F48: =IFERROR(F17/E17-1,"--") -> -- | G48: =IFERROR(G17/F17-1,"--") -> -- | H48: =IFERROR(H17/G17-1,"--") -> -- | I48: =IFERROR(I17/H17-1,"--") -> -- | J48: =IFERROR(J17/I17-1,"--") -> -- | K48: =IFERROR(K17/J17-1,"--") -> -- | L48: =IFERROR(L17/K17-1,"--") -> -- | ... P48: =IFERROR(P17/O17-1,"--") -> 5 | W48: =W28 -> Ennore Coal | Y48: =IF(ISERROR(Y28/X28-1), "-", (Y28/X28-1)) -> 0.069623162 | Z48: =IF(ISERROR(Z28/Y28-1), "-", (Z28/Y28-1)) -> 0.095596133 | AA48: =IF(ISERROR(AA28/Z28-1), "-", (AA28/Z28-1)) -> 0.017647059 | AB48: =IF(ISERROR(AB28/AA28-1), "-", (AB28/AA28-1)) -> 0.01 | AC48: =IF(ISERROR(AC28/AB28-1), "-", (AC28/AB28-1)) -> 0.01
B49: Jatadhar | E49: =IFERROR(E18/D18-1,"--") -> -- | F49: =IFERROR(F18/E18-1,"--") -> -- | G49: =IFERROR(G18/F18-1,"--") -> -- | H49: =IFERROR(H18/G18-1,"--") -> -- | I49: =IFERROR(I18/H18-1,"--") -> -- | J49: =IFERROR(J18/I18-1,"--") -> -- | K49: =IFERROR(K18/J18-1,"--") -> -- | L49: =IFERROR(L18/K18-1,"--") -> -- | ... P49: =IFERROR(P18/O18-1,"--") -> 0.27272727 | W49: =W29 -> Ennore Bulk | Y49: =IF(ISERROR(Y29/X29-1), "-", (Y29/X29-1)) -> -0.22751323 | Z49: =IF(ISERROR(Z29/Y29-1), "-", (Z29/Y29-1)) -> 0.43835616 | AA49: =IF(ISERROR(AA29/Z29-1), "-", (AA29/Z29-1)) -> -0.21428571 | AB49: =IF(ISERROR(AB29/AA29-1), "-", (AB29/AA29-1)) -> 0.048090909 | AC49: =IF(ISERROR(AC29/AB29-1), "-", (AC29/AB29-1)) -> 0.05
B50: Slurry Pipeline Phase I | E50: =IFERROR(E19/D19-1,"--") -> -- | F50: =IFERROR(F19/E19-1,"--") -> -- | G50: =IFERROR(G19/F19-1,"--") -> -- | H50: =IFERROR(H19/G19-1,"--") -> -- | I50: =IFERROR(I19/H19-1,"--") -> -- | J50: =IFERROR(J19/I19-1,"--") -> -- | K50: =IFERROR(K19/J19-1,"--") -> -- | L50: =IFERROR(L19/K19-1,"--") -> -- | ... P50: =IFERROR(P19/O19-1,"--") -> 0 | W50: =W30 -> Mangalore Coal | Y50: =IF(ISERROR(Y30/X30-1), "-", (Y30/X30-1)) -> 0.070947463 | Z50: =IF(ISERROR(Z30/Y30-1), "-", (Z30/Y30-1)) -> 0.32075472 | AA50: =IF(ISERROR(AA30/Z30-1), "-", (AA30/Z30-1)) -> -0.0047619048 | AB50: =IF(ISERROR(AB30/AA30-1), "-", (AB30/AA30-1)) -> 0.05 | AC50: =IF(ISERROR(AC30/AB30-1), "-", (AC30/AB30-1)) -> 0.05
B51: Slurry Pipeline Phase II | E51: =IFERROR(E20/D20-1,"--") -> -- | F51: =IFERROR(F20/E20-1,"--") -> -- | G51: =IFERROR(G20/F20-1,"--") -> -- | H51: =IFERROR(H20/G20-1,"--") -> -- | I51: =IFERROR(I20/H20-1,"--") -> -- | J51: =IFERROR(J20/I20-1,"--") -> -- | K51: =IFERROR(K20/J20-1,"--") -> -- | L51: =IFERROR(L20/K20-1,"--") -> -- | ... P51: =IFERROR(P20/O20-1,"--") -> -- | W51: =W31 -> Mangalore Container | Y51: =IF(ISERROR(Y31/X31-1), "-", (Y31/X31-1)) -> 0.18774848 | Z51: =IF(ISERROR(Z31/Y31-1), "-", (Z31/Y31-1)) -> -0.07054647 | AA51: =IF(ISERROR(AA31/Z31-1), "-", (AA31/Z31-1)) -> 0.0375 | AB51: =IF(ISERROR(AB31/AA31-1), "-", (AB31/AA31-1)) -> 0.25200803 | AC51: =IF(ISERROR(AC31/AB31-1), "-", (AC31/AB31-1)) -> 0.1
B52: Murbe | E52: =IFERROR(E21/D21-1,"--") -> -- | F52: =IFERROR(F21/E21-1,"--") -> -- | G52: =IFERROR(G21/F21-1,"--") -> -- | H52: =IFERROR(H21/G21-1,"--") -> -- | I52: =IFERROR(I21/H21-1,"--") -> -- | J52: =IFERROR(J21/I21-1,"--") -> -- | K52: =IFERROR(K21/J21-1,"--") -> -- | L52: =IFERROR(L21/K21-1,"--") -> -- | ... P52: =IFERROR(P21/O21-1,"--") -> -- | W52: =W32 -> PNP Port | Y52: =IF(ISERROR(Y32/X32-1), "-", (Y32/X32-1)) -> - | Z52: =IF(ISERROR(Z32/Y32-1), "-", (Z32/Y32-1)) -> 3.1666667 | AA52: =IF(ISERROR(AA32/Z32-1), "-", (AA32/Z32-1)) -> -0.029090909 | AB52: =IF(ISERROR(AB32/AA32-1), "-", (AB32/AA32-1)) -> 0.14956929 | AC52: =IF(ISERROR(AC32/AB32-1), "-", (AC32/AB32-1)) -> 0.02
B53: Oman Port | E53: =IFERROR(E22/D22-1,"--") -> -- | F53: =IFERROR(F22/E22-1,"--") -> -- | G53: =IFERROR(G22/F22-1,"--") -> -- | H53: =IFERROR(H22/G22-1,"--") -> -- | I53: =IFERROR(I22/H22-1,"--") -> -- | J53: =IFERROR(J22/I22-1,"--") -> -- | K53: =IFERROR(K22/J22-1,"--") -> -- | L53: =IFERROR(L22/K22-1,"--") -> -- | ... P53: =IFERROR(P22/O22-1,"--") -> -- | W53: =W33 -> Fujairah Liquid Storage | Y53: =IF(ISERROR(Y33/X33-1), "-", (Y33/X33-1)) -> - | Z53: =IF(ISERROR(Z33/Y33-1), "-", (Z33/Y33-1)) -> 2.65 | AA53: =IF(ISERROR(AA33/Z33-1), "-", (AA33/Z33-1)) -> -0.21780822 | AB53: =IF(ISERROR(AB33/AA33-1), "-", (AB33/AA33-1)) -> -0.5 | AC53: =IF(ISERROR(AC33/AB33-1), "-", (AC33/AB33-1)) -> 0.75
B54: Kolkata Container Terminal | E54: =IFERROR(E23/D23-1,"--") -> -- | F54: =IFERROR(F23/E23-1,"--") -> -- | G54: =IFERROR(G23/F23-1,"--") -> -- | H54: =IFERROR(H23/G23-1,"--") -> -- | I54: =IFERROR(I23/H23-1,"--") -> -- | J54: =IFERROR(J23/I23-1,"--") -> -- | K54: =IFERROR(K23/J23-1,"--") -> -- | L54: =IFERROR(L23/K23-1,"--") -> -- | ... P54: =IFERROR(P23/O23-1,"--") -> 0.16666667 | W54: =W34 -> Tuticorin Dry Bulk | Y54: =IF(ISERROR(Y34/X34-1), "-", (Y34/X34-1)) -> - | Z54: =IF(ISERROR(Z34/Y34-1), "-", (Z34/Y34-1)) -> - | AA54: NM | AB54: =IF(ISERROR(AB34/AA34-1), "-", (AB34/AA34-1)) -> 0.052104208 | AC54: =IF(ISERROR(AC34/AB34-1), "-", (AC34/AB34-1)) -> 0
B55: Kolkata Container Terminal 2 | E55: =IFERROR(E24/D24-1,"--") -> -- | F55: =IFERROR(F24/E24-1,"--") -> -- | G55: =IFERROR(G24/F24-1,"--") -> -- | H55: =IFERROR(H24/G24-1,"--") -> -- | I55: =IFERROR(I24/H24-1,"--") -> -- | J55: =IFERROR(J24/I24-1,"--") -> -- | K55: =IFERROR(K24/J24-1,"--") -> -- | L55: =IFERROR(L24/K24-1,"--") -> -- | ... P55: =IFERROR(P24/O24-1,"--") -> 1 | W55: =W35 -> JNPT Liquid | Y55: =IF(ISERROR(Y35/X35-1), "-", (Y35/X35-1)) -> - | Z55: =IF(ISERROR(Z35/Y35-1), "-", (Z35/Y35-1)) -> - | AA55: NM | AB55: =IF(ISERROR(AB35/AA35-1), "-", (AB35/AA35-1)) -> 1.25 | AC55: =IF(ISERROR(AC35/AB35-1), "-", (AC35/AB35-1)) -> 0.076923077
B56: xxx | E56: =IFERROR(E25/D25-1,"--") -> -- | F56: =IFERROR(F25/E25-1,"--") -> -- | G56: =IFERROR(G25/F25-1,"--") -> -- | H56: =IFERROR(H25/G25-1,"--") -> -- | I56: =IFERROR(I25/H25-1,"--") -> -- | J56: =IFERROR(J25/I25-1,"--") -> -- | K56: =IFERROR(K25/J25-1,"--") -> -- | L56: =IFERROR(L25/K25-1,"--") -> -- | ... P56: =IFERROR(P25/O25-1,"--") -> -- | W56: =W36 -> Jatadhar | Y56: =IF(ISERROR(Y36/X36-1), "-", (Y36/X36-1)) -> - | Z56: =IF(ISERROR(Z36/Y36-1), "-", (Z36/Y36-1)) -> - | AA56: =IF(ISERROR(AA36/Z36-1), "-", (AA36/Z36-1)) -> - | AB56: =IF(ISERROR(AB36/AA36-1), "-", (AB36/AA36-1)) -> - | AC56: =IF(ISERROR(AC36/AB36-1), "-", (AC36/AB36-1)) -> -
B57: xxx | E57: =IFERROR(E26/D26-1,"--") -> -- | F57: =IFERROR(F26/E26-1,"--") -> -- | G57: =IFERROR(G26/F26-1,"--") -> -- | H57: =IFERROR(H26/G26-1,"--") -> -- | I57: =IFERROR(I26/H26-1,"--") -> -- | J57: =IFERROR(J26/I26-1,"--") -> -- | K57: =IFERROR(K26/J26-1,"--") -> -- | L57: =IFERROR(L26/K26-1,"--") -> -- | ... P57: =IFERROR(P26/O26-1,"--") -> -- | W57: =W37 -> Slurry Pipeline Phase I | Y57: =IF(ISERROR(Y37/X37-1), "-", (Y37/X37-1)) -> - | Z57: =IF(ISERROR(Z37/Y37-1), "-", (Z37/Y37-1)) -> - | AA57: =IF(ISERROR(AA37/Z37-1), "-", (AA37/Z37-1)) -> - | AB57: =IF(ISERROR(AB37/AA37-1), "-", (AB37/AA37-1)) -> - | AC57: =IF(ISERROR(AC37/AB37-1), "-", (AC37/AB37-1)) -> -
B58: Total Cargo Handled | E58: =IFERROR(E27/D27-1,"--") -> 0.10204082 | F58: =IFERROR(F27/E27-1,"--") -> -0.038437772 | G58: =IFERROR(G27/F27-1,"--") -> 0.33894118 | H58: =IFERROR(H27/G27-1,"--") -> 0.36068007 | I58: =IFERROR(I27/H27-1,"--") -> 0.49785393 | J58: =IFERROR(J27/I27-1,"--") -> 0.1532918 | K58: =IFERROR(K27/J27-1,"--") -> 0.093068092 | L58: =IFERROR(L27/K27-1,"--") -> 0.031965812 | ... P58: =IFERROR(P27/O27-1,"--") -> 0.2054281 | W58: =W38 -> Kolkata Container Terminal | Y58: =IF(ISERROR(Y38/X38-1), "-", (Y38/X38-1)) -> - | Z58: =IF(ISERROR(Z38/Y38-1), "-", (Z38/Y38-1)) -> - | AA58: =IF(ISERROR(AA38/Z38-1), "-", (AA38/Z38-1)) -> - | AB58: =IF(ISERROR(AB38/AA38-1), "-", (AB38/AA38-1)) -> - | AC58: =IF(ISERROR(AC38/AB38-1), "-", (AC38/AB38-1)) -> 1
W59: =W39 -> Total | Y59: =IF(ISERROR(Y39/X39-1), "-", (Y39/X39-1)) -> 0.1532918 | Z59: =IF(ISERROR(Z39/Y39-1), "-", (Z39/Y39-1)) -> 0.093068092 | AA59: =IF(ISERROR(AA39/Z39-1), "-", (AA39/Z39-1)) -> 0.031965812 | AB59: =IF(ISERROR(AB39/AA39-1), "-", (AB39/AA39-1)) -> 0.059765695 | AC59: =IF(ISERROR(AC39/AB39-1), "-", (AC39/AB39-1)) -> 0.31722537
B60: Composition %
B61: Standalone | D61: =D3/D$27 -> 0 | E61: =E3/E$27 -> 0.11846197 | F61: =F3/F$27 -> 0.093381055 | G61: =G3/G$27 -> 0.078835258 | H61: =H3/H$27 -> 0.04886364 | I61: =I3/I$27 -> 0.02909138 | J61: =J3/J$27 -> 0.024757525 | K61: =K3/K$27 -> 0.020512821 | ... P61: =P3/P$27 -> 0.013366232
B62: Jaigarh | D62: =D4/D$27 -> 0.29708677 | E62: =E4/E$27 -> 0.36895674 | F62: =F4/F$27 -> 0.3049156 | G62: =G4/G$27 -> 0.20286354 | H62: =H4/H$27 -> 0.22625701 | I62: =I4/I$27 -> 0.21804528 | J62: =J4/J$27 -> 0.20095636 | K62: =K4/K$27 -> 0.17008547 | ... P62: =P4/P$27 -> 0.12797662
B63: Dharmatar | D63: =D5/D$27 -> 0.36329646 | E63: =E5/E$27 -> 0.36415041 | F63: =F5/F$27 -> 0.3775376 | G63: =G5/G$27 -> 0.2832799 | H63: =H5/H$27 -> 0.27773979 | I63: =I5/I$27 -> 0.25891328 | J63: =J5/J$27 -> 0.2348695 | K63: =K5/K$27 -> 0.1974359 | ... P63: =P5/P$27 -> 0.1505963
B64: Goa | D64: =D6/D$27 -> 0.33961676 | E64: =E6/E$27 -> 0.14843087 | F64: =F6/F$27 -> 0.19438078 | G64: =G6/G$27 -> 0.14998463 | H64: =H6/H$27 -> 0.1117707 | I64: =I6/I$27 -> 0.076154768 | J64: =J6/J$27 -> 0.06685466 | K64: =K6/K$27 -> 0.054700855 | ... P64: =P6/P$27 -> 0.049569534
B65: Paradip Iron Ore | D65: =D7/D$27 -> 0 | E65: =E7/E$27 -> 0 | F65: =F7/F$27 -> 0.029784958 | G65: =G7/G$27 -> 0.18512012 | H65: =H7/H$27 -> 0.12130074 | I65: =I7/I$27 -> 0.10257405 | J65: =J7/J$27 -> 0.11556626 | K65: =K7/K$27 -> 0.097435897 | ... P65: =P7/P$27 -> 0.040962023
B66: Paradip Coal | D66: =D8/D$27 -> 0 | E66: =E8/E$27 -> 0 | F66: =F8/F$27 -> 0 | G66: =G8/G$27 -> 0 | H66: =H8/H$27 -> 0.004529745 | I66: =I8/I$27 -> 0.12966136 | J66: =J8/J$27 -> 0.15667309 | K66: =K8/K$27 -> 0.16153846 | ... P66: =P8/P$27 -> 0.097283051
B67: Ennore Coal | D67: =D9/D$27 -> 0 | E67: =E9/E$27 -> 0 | F67: =F9/F$27 -> 0 | G67: =G9/G$27 -> 0.068953402 | H67: =H9/H$27 -> 0.12963319 | I67: =I9/I$27 -> 0.093781989 | J67: =J9/J$27 -> 0.086978324 | K67: =K9/K$27 -> 0.087179487 | ... P67: =P9/P$27 -> 0.045500917
B68: Ennore Bulk | D68: =D10/D$27 -> 0 | E68: =E10/E$27 -> 0 | F68: =F10/F$27 -> 0 | G68: =G10/G$27 -> 0.008564276 | H68: =H10/H$27 -> 0.01872475 | I68: =I10/I$27 -> 0.020363966 | J68: =J10/J$27 -> 0.013639995 | K68: =K10/K$27 -> 0.017948718 | ... P68: =P10/P$27 -> 0.0084331164
B69: Mangalore Coal | D69: =D11/D$27 -> 0 | E69: =E11/E$27 -> 0 | F69: =F11/F$27 -> 0 | G69: =G11/G$27 -> 0.022398876 | H69: =H11/H$27 -> 0.061180429 | I69: =I11/I$27 -> 0.047990002 | J69: =J11/J$27 -> 0.044563545 | K69: =K11/K$27 -> 0.053846154 | ... P69: =P11/P$27 -> 0.032104214
B70: Mangalore Container | D70: =D12/D$27 -> 0 | E70: =E12/E$27 -> 0 | F70: =F12/F$27 -> 0 | G70: =G12/G$27 -> 0 | H70: =H12/H$27 -> 0 | I70: =I12/I$27 -> 0.023423923 | J70: =J12/J$27 -> 0.024123755 | K70: =K12/K$27 -> 0.020512821 | ... P70: =P12/P$27 -> 0.016231108
B71: PNP Port | D71: =D13/D$27 -> 0 | E71: =E13/E$27 -> 0 | F71: =F13/F$27 -> 0 | G71: =G13/G$27 -> 0 | H71: =H13/H$27 -> 0 | I71: =I13/I$27 -> 0 | J71: =J13/J$27 -> 0.01233205 | K71: =K13/K$27 -> 0.047008547 | ... P71: =P13/P$27 -> 0.029079871
B72: Fujairah Liquid Storage | D72: =D14/D$27 -> 0 | E72: =E14/E$27 -> 0 | F72: =F14/F$27 -> 0 | G72: =G14/G$27 -> 0 | H72: =H14/H$27 -> 0 | I72: =I14/I$27 -> 0 | J72: =J14/J$27 -> 0.018684925 | K72: =K14/K$27 -> 0.062393162 | ... P72: =P14/P$27 -> 0.026266127
... B84: xxx | D84: =D26/D$27 -> 0 | E84: =E26/E$27 -> 0 | F84: =F26/F$27 -> 0 | G84: =G26/G$27 -> 0 | H84: =H26/H$27 -> 0 | I84: =I26/I$27 -> 0 | J84: =J26/J$27 -> 0 | K84: =K26/K$27 -> 0 | ... P84: =P26/P$27 -> 0
B85: Total Cargo Handled | D85: =SUM(D61:D83) -> 1 | E85: =SUM(E61:E83) -> 1 | F85: =SUM(F61:F83) -> 1 | G85: =SUM(G61:G83) -> 1 | H85: =SUM(H61:H83) -> 1 | I85: =SUM(I61:I83) -> 1 | J85: =SUM(J61:J83) -> 1 | K85: =SUM(K61:K83) -> 1 | ... P85: =SUM(P61:P83) -> 1
B87: Capacity, MTPA | X87: FY20 | Y87: FY21 | Z87: FY22 | AA87: FY23 | AB87: FY24 | AC87: FY25 | AD87: FY26 | AE87: FY27E | AF87: FY28E | AG87: FY29E | AH87: FY30E
B88: Jaigarh | F88: 45 | G88: 50 | H88: 55 | I88: 55 | J88: 55 | K88: 55 | L88: 55 | M88: =L88+SUMIF($C$1578:$C$1592,$B88,AT$1578:AT$1592) -> 57 | N88: =M88+SUMIF($C$1578:$C$1592,$B88,AU$1578:AU$1592) -> 77 | O88: =N88+SUMIF($C$1578:$C$1592,$B88,AV$1578:AV$1592) -> 77 | P88: =O88+SUMIF($C$1578:$C$1592,$B88,AW$1578:AW$1592) -> 77 | S88: =IF(ISERROR((J88/D88)^(1/6)-1)," ",(J88/D88)^(1/6)-1) | T88: =IF(ISERROR((P88/J88)^(1/6)-1)," ",(P88/J88)^(1/6)-1) -> 0.057680926 | W88: Domestic Port | X88: =F88+F89+F97+F101+F102+F105 -> 60 | Y88: =G88+G89+G97+G101+G102+G105 -> 84 | Z88: =H88+H89+H97+H101+H102+H105 -> 89 | AA88: =I88+I89+I97+I101+I102+I105 -> 89 | AB88: =J88+J89+J97+J101+J102+J105 -> 94 | AC88: =K88+K89+K97+K101+K102+K105 -> 97 | AD88: =L88+L89+L97+L101+L102+L105 -> 97 | AE88: =M88+M89+M97+M101+M102+M105 -> 99 | ... AH88: =P88+P89+P97+P101+P102+P105 -> 228 | AK88: =AH88-AD88+P106 -> 158
B89: Dharmatar | F89: 15 | G89: 34 | H89: 34 | I89: 34 | J89: 34 | K89: 34 | L89: 34 | M89: =L89+SUMIF($C$1578:$C$1592,$B89,AT$1578:AT$1592) -> 34 | N89: =M89+SUMIF($C$1578:$C$1592,$B89,AU$1578:AU$1592) -> 50 | O89: =N89+SUMIF($C$1578:$C$1592,$B89,AV$1578:AV$1592) -> 50 | P89: =O89+SUMIF($C$1578:$C$1592,$B89,AW$1578:AW$1592) -> 50 | S89: =IF(ISERROR((J89/F89)^(1/4)-1)," ",(J89/F89)^(1/4)-1) -> 0.22700664 | T89: =IF(ISERROR((P89/J89)^(1/6)-1)," ",(P89/J89)^(1/6)-1) -> 0.066387833 | W89: Domestic Terminals | X89: =F90+F91+F92+F93+F94+F95+F96+F99+F100+F107 -> 25 | Y89: =G90+G91+G92+G93+G94+G95+G96+G99+G100+G107 -> 27 | Z89: =H90+H91+H92+H93+H94+H95+H96+H99+H100+H107 -> 65.2 | AA89: =I90+I91+I92+I93+I94+I95+I96+I99+I100+I107 -> 69.4 | AB89: =J90+J91+J92+J93+J94+J95+J96+J99+J100+J107 -> 71 | AC89: =K90+K91+K92+K93+K94+K95+K96+K99+K100+K107 -> 74.9 | AD89: =L90+L91+L92+L93+L94+L95+L96+L99+L100+L107 -> 80.8 | AE89: =M90+M91+M92+M93+M94+M95+M96+M99+M100+M107 -> 93.62 | ... AH89: =P90+P91+P92+P93+P94+P95+P96+P99+P100+P107 -> 99.92 | AK89: =AH89-AD89 -> 19.12
B90: Goa | F90: 15 | G90: 15 | H90: 8.5 | I90: 8.5 | J90: 8.5 | K90: 11 | L90: 11 | M90: =L90+SUMIF($C$1578:$C$1592,$B90,AT$1578:AT$1592) -> 15 | N90: =M90+SUMIF($C$1578:$C$1592,$B90,AU$1578:AU$1592) -> 15 | O90: =N90+SUMIF($C$1578:$C$1592,$B90,AV$1578:AV$1592) -> 15 | P90: =O90+SUMIF($C$1578:$C$1592,$B90,AW$1578:AW$1592) -> 15 | S90: =IF(ISERROR((J90/F90)^(1/4)-1)," ",(J90/F90)^(1/4)-1) -> -0.13237528 | T90: =IF(ISERROR((P90/J90)^(1/6)-1)," ",(P90/J90)^(1/6)-1) -> 0.099289439 | W90: Overseas | X90: =F98+F106 -> 0 | Y90: =G98+G106 -> 0 | Z90: =H98+H106 -> 0 | AA90: =I98+I106 -> 0 | AB90: =J98+J106 -> 5 | AC90: =K98+K106 -> 5 | AD90: =L98+L106 -> 5 | AE90: =M98+M106 -> 5 | ... AH90: =P98+P106 -> 32 | AK90: =AH90-AD90-P106 -> 0
B91: Paradip Iron Ore | F91: 10 | G91: 10 | H91: 10 | I91: 10 | J91: 10 | K91: 10 | L91: 10 | M91: =L91+SUMIF($C$1578:$C$1592,$B91,AT$1578:AT$1592) -> 10 | N91: =M91+SUMIF($C$1578:$C$1592,$B91,AU$1578:AU$1592) -> 10 | O91: =N91+SUMIF($C$1578:$C$1592,$B91,AV$1578:AV$1592) -> 10 | P91: =O91+SUMIF($C$1578:$C$1592,$B91,AW$1578:AW$1592) -> 10 | S91: =IF(ISERROR((J91/F91)^(1/4)-1)," ",(J91/F91)^(1/4)-1) -> 0 | T91: =IF(ISERROR((P91/J91)^(1/6)-1)," ",(P91/J91)^(1/6)-1) -> 0 | W91: Others | X91: =F103+F104 -> 0 | Y91: =G103+G104 -> 0 | Z91: =H103+H104 -> 0 | AA91: =I103+I104 -> 0 | AB91: =J103+J104 -> 0 | AC91: =K103+K104 -> 0 | AD91: =L103+L104 -> 0 | AE91: =M103+M104 -> 0 | ... AH91: =P103+P104 -> 30 | AK91: =AH91-AD91 -> 30
B92: Paradip Coal | F92: 0 | G92: 0 | H92: 30 | I92: 30 | J92: 30 | K92: 30 | L92: 30 | M92: =L92+SUMIF($C$1578:$C$1592,$B92,AT$1578:AT$1592) -> 30 | N92: =M92+SUMIF($C$1578:$C$1592,$B92,AU$1578:AU$1592) -> 30 | O92: =N92+SUMIF($C$1578:$C$1592,$B92,AV$1578:AV$1592) -> 30 | P92: =O92+SUMIF($C$1578:$C$1592,$B92,AW$1578:AW$1592) -> 30 | S92: =IF(ISERROR((J92/F92)^(1/4)-1)," ",(J92/F92)^(1/4)-1) | T92: =IF(ISERROR((P92/J92)^(1/6)-1)," ",(P92/J92)^(1/6)-1) -> 0 | X92: =SUM(X88:X91) -> 85 | Y92: =SUM(Y88:Y91) -> 111 | Z92: =SUM(Z88:Z91) -> 154.2 | AA92: =SUM(AA88:AA91) -> 158.4 | AB92: =SUM(AB88:AB91) -> 170 | AC92: =SUM(AC88:AC91) -> 176.9 | AD92: =SUM(AD88:AD91) -> 182.8 | AE92: =SUM(AE88:AE91) -> 197.62 | ... AH92: =SUM(AH88:AH91) -> 389.92 | AK92: =AH92-AD92 -> 207.12
B93: Ennore Coal | F93: 0 | G93: 0 | H93: 8 | I93: 8 | J93: 9.6 | K93: 9.6 | L93: 11 | M93: =L93+SUMIF($C$1578:$C$1592,$B93,AT$1578:AT$1592) -> 11 | N93: =M93+SUMIF($C$1578:$C$1592,$B93,AU$1578:AU$1592) -> 11 | O93: =N93+SUMIF($C$1578:$C$1592,$B93,AV$1578:AV$1592) -> 11 | P93: =O93+SUMIF($C$1578:$C$1592,$B93,AW$1578:AW$1592) -> 11 | S93: =IF(ISERROR((J93/F93)^(1/4)-1)," ",(J93/F93)^(1/4)-1) | T93: =IF(ISERROR((P93/J93)^(1/6)-1)," ",(P93/J93)^(1/6)-1) -> 0.022948042
B94: Ennore Bulk | F94: 0 | G94: 2 | H94: 2 | I94: 2 | J94: 2 | K94: 2 | L94: 2 | M94: =L94+SUMIF($C$1578:$C$1592,$B94,AT$1578:AT$1592) -> 2 | N94: =M94+SUMIF($C$1578:$C$1592,$B94,AU$1578:AU$1592) -> 2 | O94: =N94+SUMIF($C$1578:$C$1592,$B94,AV$1578:AV$1592) -> 2 | P94: =O94+SUMIF($C$1578:$C$1592,$B94,AW$1578:AW$1592) -> 2 | S94: =IF(ISERROR((J94/F94)^(1/4)-1)," ",(J94/F94)^(1/4)-1) | T94: =IF(ISERROR((P94/J94)^(1/6)-1)," ",(P94/J94)^(1/6)-1) -> 0
B95: Mangalore Coal | F95: 0 | G95: 0 | H95: 6.7 | I95: 6.7 | J95: 6.7 | K95: 8.1 | L95: 8.1 | M95: =L95+SUMIF($C$1578:$C$1592,$B95,AT$1578:AT$1592) -> 8.1 | N95: =M95+SUMIF($C$1578:$C$1592,$B95,AU$1578:AU$1592) -> 8.1 | O95: =N95+SUMIF($C$1578:$C$1592,$B95,AV$1578:AV$1592) -> 8.1 | P95: =O95+SUMIF($C$1578:$C$1592,$B95,AW$1578:AW$1592) -> 8.1 | S95: =IF(ISERROR((J95/F95)^(1/4)-1)," ",(J95/F95)^(1/4)-1) | T95: =IF(ISERROR((P95/J95)^(1/6)-1)," ",(P95/J95)^(1/6)-1) -> 0.032131508
B96: Mangalore Container | F96: 0 | G96: 0 | H96: 0 | I96: 4.2 | J96: 4.2 | K96: 4.2 | L96: 4.2 | M96: =L96+SUMIF($C$1578:$C$1592,$B96,AT$1578:AT$1592) -> 6.02 | N96: =M96+SUMIF($C$1578:$C$1592,$B96,AU$1578:AU$1592) -> 6.02 | O96: =N96+SUMIF($C$1578:$C$1592,$B96,AV$1578:AV$1592) -> 6.02 | P96: =O96+SUMIF($C$1578:$C$1592,$B96,AW$1578:AW$1592) -> 6.02 | S96: =IF(ISERROR((J96/F96)^(1/4)-1)," ",(J96/F96)^(1/4)-1) | T96: =IF(ISERROR((P96/J96)^(1/6)-1)," ",(P96/J96)^(1/6)-1) -> 0.06183703
B97: PNP Port | F97: 0 | G97: 0 | H97: 0 | I97: 0 | J97: 5 | K97: 8 | L97: 8 | M97: =L97+SUMIF($C$1578:$C$1592,$B97,AT$1578:AT$1592) -> 8 | N97: =M97+SUMIF($C$1578:$C$1592,$B97,AU$1578:AU$1592) -> 8 | O97: =N97+SUMIF($C$1578:$C$1592,$B97,AV$1578:AV$1592) -> 8 | P97: =O97+SUMIF($C$1578:$C$1592,$B97,AW$1578:AW$1592) -> 8 | S97: =IF(ISERROR((J97/F97)^(1/4)-1)," ",(J97/F97)^(1/4)-1) | T97: =IF(ISERROR((P97/J97)^(1/6)-1)," ",(P97/J97)^(1/6)-1) -> 0.081483747
B98: Fujairah Liquid Storage | F98: 0 | G98: 0 | H98: 0 | I98: 0 | J98: 5 | K98: 5 | L98: 5 | M98: =L98+SUMIF($C$1578:$C$1592,$B98,AT$1578:AT$1592) -> 5 | N98: =M98+SUMIF($C$1578:$C$1592,$B98,AU$1578:AU$1592) -> 5 | O98: =N98+SUMIF($C$1578:$C$1592,$B98,AV$1578:AV$1592) -> 5 | P98: =O98+SUMIF($C$1578:$C$1592,$B98,AW$1578:AW$1592) -> 5 | S98: =IF(ISERROR((J98/F98)^(1/4)-1)," ",(J98/F98)^(1/4)-1) | T98: =IF(ISERROR((P98/J98)^(1/6)-1)," ",(P98/J98)^(1/6)-1) -> 0
B99: Tuticorin Dry Bulk | F99: 0 | G99: 0 | H99: 0 | I99: 0 | J99: 0 | K99: 0 | L99: 0 | M99: =L99+SUMIF($C$1578:$C$1592,$B99,AT$1578:AT$1592) -> 7 | N99: =M99+SUMIF($C$1578:$C$1592,$B99,AU$1578:AU$1592) -> 7 | O99: =N99+SUMIF($C$1578:$C$1592,$B99,AV$1578:AV$1592) -> 7 | P99: =O99+SUMIF($C$1578:$C$1592,$B99,AW$1578:AW$1592) -> 7 | S99: =IF(ISERROR((J99/F99)^(1/4)-1)," ",(J99/F99)^(1/4)-1) | T99: =IF(ISERROR((P99/J99)^(1/6)-1)," ",(P99/J99)^(1/6)-1)
B100: JNPT Liquid | F100: 0 | G100: 0 | H100: 0 | I100: 0 | J100: 0 | K100: 0 | L100: 4.5 | M100: =L100+SUMIF($C$1578:$C$1592,$B100,AT$1578:AT$1592) -> 4.5 | N100: =M100+SUMIF($C$1578:$C$1592,$B100,AU$1578:AU$1592) -> 4.5 | O100: =N100+SUMIF($C$1578:$C$1592,$B100,AV$1578:AV$1592) -> 4.5 | P100: =O100+SUMIF($C$1578:$C$1592,$B100,AW$1578:AW$1592) -> 4.5 | S100: =IF(ISERROR((J100/F100)^(1/4)-1)," ",(J100/F100)^(1/4)-1) | T100: =IF(ISERROR((P100/J100)^(1/6)-1)," ",(P100/J100)^(1/6)-1)
B101: Keni | F101: 0 | G101: 0 | H101: 0 | I101: 0 | J101: 0 | K101: 0 | L101: 0 | M101: =L101+SUMIF($C$1578:$C$1592,$B101,AT$1578:AT$1592) -> 0 | N101: =M101+SUMIF($C$1578:$C$1592,$B101,AU$1578:AU$1592) -> 0 | O101: =N101+SUMIF($C$1578:$C$1592,$B101,AV$1578:AV$1592) -> 30 | P101: =O101+SUMIF($C$1578:$C$1592,$B101,AW$1578:AW$1592) -> 30 | Q101: =+P101/$P$111 -> 0.07464172 | S101: =IF(ISERROR((J101/F101)^(1/4)-1)," ",(J101/F101)^(1/4)-1) | T101: =IF(ISERROR((P101/J101)^(1/6)-1)," ",(P101/J101)^(1/6)-1)
B102: Jatadhar | F102: 0 | G102: 0 | H102: 0 | I102: 0 | J102: 0 | K102: 0 | L102: 0 | M102: =L102+SUMIF($C$1578:$C$1592,$B102,AT$1578:AT$1592) -> 0 | N102: =M102+SUMIF($C$1578:$C$1592,$B102,AU$1578:AU$1592) -> 30 | O102: =N102+SUMIF($C$1578:$C$1592,$B102,AV$1578:AV$1592) -> 30 | P102: =O102+SUMIF($C$1578:$C$1592,$B102,AW$1578:AW$1592) -> 30 | S102: =IF(ISERROR((J102/F102)^(1/4)-1)," ",(J102/F102)^(1/4)-1) | T102: =IF(ISERROR((P102/J102)^(1/6)-1)," ",(P102/J102)^(1/6)-1)
B103: Slurry Pipeline Phase I | F103: 0 | G103: 0 | H103: 0 | I103: 0 | J103: 0 | K103: 0 | L103: 0 | M103: =L103+SUMIF($C$1578:$C$1592,$B103,AT$1578:AT$1592) -> 0 | N103: =M103+SUMIF($C$1578:$C$1592,$B103,AU$1578:AU$1592) -> 30 | O103: =N103+SUMIF($C$1578:$C$1592,$B103,AV$1578:AV$1592) -> 30 | P103: =O103+SUMIF($C$1578:$C$1592,$B103,AW$1578:AW$1592) -> 30 | S103: =IF(ISERROR((J103/F103)^(1/4)-1)," ",(J103/F103)^(1/4)-1) | T103: =IF(ISERROR((P103/J103)^(1/6)-1)," ",(P103/J103)^(1/6)-1) | W103: Cargo mix
B104: Slurry Pipeline Phase II | F104: 0 | G104: 0 | H104: 0 | I104: 0 | J104: 0 | K104: 0 | L104: 0 | M104: =L104+SUMIF($C$1578:$C$1592,$B104,AT$1578:AT$1592) -> 0 | N104: =M104+SUMIF($C$1578:$C$1592,$B104,AU$1578:AU$1592) -> 0 | O104: =N104+SUMIF($C$1578:$C$1592,$B104,AV$1578:AV$1592) -> 0 | P104: =O104+SUMIF($C$1578:$C$1592,$B104,AW$1578:AW$1592) -> 0 | S104: =IF(ISERROR((J104/F104)^(1/4)-1)," ",(J104/F104)^(1/4)-1) | T104: =IF(ISERROR((P104/J104)^(1/6)-1)," ",(P104/J104)^(1/6)-1) | W104: Growth
B105: Murbe | F105: 0 | G105: 0 | H105: 0 | I105: 0 | J105: 0 | K105: 0 | L105: 0 | M105: =L105+SUMIF($C$1578:$C$1592,$B105,AT$1578:AT$1592) -> 0 | N105: =M105+SUMIF($C$1578:$C$1592,$B105,AU$1578:AU$1592) -> 0 | O105: =N105+SUMIF($C$1578:$C$1592,$B105,AV$1578:AV$1592) -> 0 | P105: =O105+SUMIF($C$1578:$C$1592,$B105,AW$1578:AW$1592) -> 33 | Q105: =+P105/$P$111 -> 0.082105892 | T105: =IF(ISERROR((P105/J105)^(1/6)-1)," ",(P105/J105)^(1/6)-1) | W105: EV/EBITDA
B106: Oman Port | F106: 0 | G106: 0 | H106: 0 | I106: 0 | J106: 0 | K106: 0 | L106: 0 | M106: =L106+SUMIF($C$1578:$C$1592,$B106,AT$1578:AT$1592) -> 0 | N106: =M106+SUMIF($C$1578:$C$1592,$B106,AU$1578:AU$1592) -> 0 | O106: =N106+SUMIF($C$1578:$C$1592,$B106,AV$1578:AV$1592) -> 0 | P106: =O106+SUMIF($C$1578:$C$1592,$B106,AW$1578:AW$1592) -> 27 | Q106: =+P106/$P$111 -> 0.067177548 | T106: =IF(ISERROR((P106/J106)^(1/6)-1)," ",(P106/J106)^(1/6)-1)
B107: Kolkata Container Terminal | F107: 0 | G107: 0 | H107: 0 | I107: 0 | J107: 0 | K107: 0 | L107: 0 | M107: =L107+SUMIF($C$1578:$C$1592,$B107,AT$1578:AT$1592) -> 0 | N107: =M107+SUMIF($C$1578:$C$1592,$B107,AU$1578:AU$1592) -> 6.3 | O107: =N107+SUMIF($C$1578:$C$1592,$B107,AV$1578:AV$1592) -> 6.3 | P107: =O107+SUMIF($C$1578:$C$1592,$B107,AW$1578:AW$1592) -> 6.3
B108: Kolkata Container Terminal 2 | F108: 0 | G108: 0 | H108: 0 | I108: 0 | J108: 0 | K108: 0 | L108: 0 | M108: =L108+SUMIF($C$1578:$C$1592,$B108,AT$1578:AT$1592) -> 0 | N108: =M108+SUMIF($C$1578:$C$1592,$B108,AU$1578:AU$1592) -> 0 | O108: =N108+SUMIF($C$1578:$C$1592,$B108,AV$1578:AV$1592) -> 12 | P108: =O108+SUMIF($C$1578:$C$1592,$B108,AW$1578:AW$1592) -> 12
B109: xxx | F109: 0 | G109: 0 | H109: 0 | I109: 0 | J109: 0 | K109: 0 | L109: 0 | M109: =L109+SUMIF($C$1578:$C$1592,$B109,AT$1578:AT$1592) -> 0 | N109: =M109+SUMIF($C$1578:$C$1592,$B109,AU$1578:AU$1592) -> 0 | O109: =N109+SUMIF($C$1578:$C$1592,$B109,AV$1578:AV$1592) -> 0 | P109: =O109+SUMIF($C$1578:$C$1592,$B109,AW$1578:AW$1592) -> 0 | S109: =IF(ISERROR((J109/F109)^(1/4)-1)," ",(J109/F109)^(1/4)-1) | T109: =IF(ISERROR((P109/J109)^(1/6)-1)," ",(P109/J109)^(1/6)-1)
B110: xxx | F110: 0 | G110: 0 | H110: 0 | I110: 0 | J110: 0 | K110: 0 | L110: 0 | M110: =L110+SUMIF($C$1578:$C$1592,$B110,AT$1578:AT$1592) -> 0 | N110: =M110+SUMIF($C$1578:$C$1592,$B110,AU$1578:AU$1592) -> 0 | O110: =N110+SUMIF($C$1578:$C$1592,$B110,AV$1578:AV$1592) -> 0 | P110: =O110+SUMIF($C$1578:$C$1592,$B110,AW$1578:AW$1592) -> 0 | S110: =IF(ISERROR((J110/F110)^(1/4)-1)," ",(J110/F110)^(1/4)-1) | T110: =IF(ISERROR((P110/J110)^(1/6)-1)," ",(P110/J110)^(1/6)-1)
B111: Total JSW Infra | F111: =SUM(F88:F110) -> 85 | G111: =SUM(G88:G110) -> 111 | H111: =SUM(H88:H110) -> 154.2 | I111: =SUM(I88:I110) -> 158.4 | J111: =SUM(J88:J110) -> 170 | K111: =SUM(K88:K110) -> 176.9 | L111: =SUM(L88:L110) -> 182.8 | M111: =SUM(M88:M110) -> 197.62 | ... P111: =SUM(P88:P110) -> 401.92 | Q111: =(K111/G111)^(1/4)-1 -> 0.12357279 | R111: =(N111/L111)^(1/2)-1 -> 0.28089821 | S111: =IF(ISERROR((J111/F111)^(1/4)-1)," ",(J111/F111)^(1/4)-1) -> 0.18920712 | T111: =IF(ISERROR((P111/J111)^(1/6)-1)," ",(P111/J111)^(1/6)-1) -> 0.15420189 | U111: =IF(ISERROR((P111/K111)^(1/5)-1)," ",(P111/K111)^(1/5)-1) -> 0.17837184
S112: =IF(ISERROR((J112/D112)^(1/6)-1)," ",(J112/D112)^(1/6)-1) | T112: =IF(ISERROR((P112/J112)^(1/6)-1)," ",(P112/J112)^(1/6)-1)
...

Sheet Consol
B1: Consolidated | U1: CAGR | Y1: Logistics
B2: P&L, Rs. mn | C2: FY14 | D2: FY15 | E2: FY16 | F2: FY17 | G2: FY18 | H2: FY19 | I2: FY20 | J2: FY21 | K2: FY22 | L2: FY23 | M2: FY24 | N2: FY25 | O2: FY26 | P2: FY27E | Q2: FY28E | R2: FY29E | S2: FY30E | U2: FY24-26 | V2: FY26-28 | W2: FY26-30E | Y2: FY25 | Z2: FY26 | AA2: FY27E | AB2: FY28E | AC2: FY29E | AD2: FY30E
G3: =SUM(G4:G6)/G16 -> 0.17794193 | H3: =SUM(H4:H6)/H16 -> 0.17005477 | I3: =SUM(I4:I6)/I16 -> 0.15583881 | J3: =SUM(J4:J6)/J16 -> 0.132641 | K3: =SUM(K4:K6)/K16 -> 0.1506364 | L3: =SUM(L4:L6)/L16 -> 0.15246338 | M3: =SUM(M4:M6)/M16 -> 0.13645363 | N3: =SUM(N4:N6)/N16 -> 0.126551 | O3: =SUM(O4:O6)/O16 -> 0
B4: Vessel Charges - Port Dues | G4: 182.729 | H4: 207.289 | I4: 191.247 | J4: 189.898 | K4: 301.634 | L4: 421.828
B5: Vessel Charges - Pilotage & Tug hire | G5: 267.276 | H5: 306.054 | I5: 269.994 | J5: 286.254 | K5: 568.995 | L5: 863.706
B6: Vessel Charges - Berth Hire Charges | G6: 1326.022 | H6: 1323.691 | I6: 1320.223 | J6: 1650.84 | K6: 2553.425 | L6: 3585.274 | M6: 5134.6 | N6: 5664.6
B7: Cargo Handling - Cargo Handling Income | G7: 5867.109 | H7: 7005.164 | I7: 7605.756 | J7: 11256.104 | K7: 15247.286 | L7: 22285.075 | M7: 28357.1 | N7: 29919
B8: Cargo Handling - Wharfage Income | G8: 309.914 | H8: 427.007 | I8: 303.907 | J8: 217.61 | K8: 838.439 | L8: 1206.469
B9: Cargo Handling - Storage Income | G9: 292.944 | H9: 455.608 | I9: 329.884 | J9: 559.561 | K9: 1280.436 | L9: 1103.109 | M9: 2182.4 | N9: 4854.7
B10: Cargo Handling - Cape dredging Income | G10: 674.362 | H10: 555.907 | I10: 505.271 | J10: 499.226 | K10: 583.071 | L10: 933.965
B11: Cargo Handling - Grabs Transportation Charges | G11: 3.463 | H11: 4.081 | I11: 2.485 | J11: 1.93 | K11: 4.415 | L11: 8.361
B12: Cargo Handling - Other Port Service income | G12: 30.951 | H12: 12.156 | I12: 32.037 | J12: 915.363 | K12: 967.713 | L12: 1015.118 | M12: 1564.7 | N12: 1825.8
B13: Cargo Handling - Paradip railway project Income | H13: - | I13: 301.455 | J13: 206.47 | K13: 127.592 | L13: 129.457
B14: Cargo Handling - Other Operating Income | G14: =22.1+750+254.066 -> 1026.166 | H14: =(4836.78+219.67)/10 -> 505.645 | I14: =(5551.3+140.64)/10 -> 569.194 | J14: =(2524.49)/10 -> 252.449 | K14: 257.582 | L14: 395.034 | M14: 390.1
B15: Revenue from Logistics | N15: =1600.7+848.4+48.2 -> 2497.3 | AH15: Revenue, Rs. bn | AI15: FY25 | AJ15: FY26E | AK15: FY27E | AL15: FY28E | AM15: FY29E | AN15: FY30E
B16: Revenue from Operations | G16: =SUM(G4:G15) -> 9980.936 | H16: =SUM(H4:H15) -> 10802.602 | I16: =SUM(I4:I15) -> 11431.453 | J16: =SUM(J4:J15) -> 16035.705 | K16: =SUM(K4:K15) -> 22730.588 | L16: =SUM(L4:L15) -> 31947.396 | M16: =SUM(M4:M15) -> 37628.9 | N16: =SUM(N4:N15) -> 44761.4 | O16: 53614.4 | P16: =Assumptions!M233+AA16 -> 72935.368 | Q16: =Assumptions!N233+AB16 -> 108672.59 | R16: =Assumptions!O233+AC16 -> 144351.19 | S16: =Assumptions!P233+AD16 -> 188550.74 | U16: =(O16/M16)^(1/2)-1 -> 0.19365814 | V16: =(Q16/O16)^(1/2)-1 -> 0.42370263 | W16: =(S16/O16)^(1/4)-1 -> 0.36942009 | X16: =(Q16/O16)^(1/2)-1 -> 0.42370263 | Y16: =Logistics!C16 -> 2497.3 | Z16: =Logistics!D16 -> 7145.3 | AA16: =Logistics!E16 -> 16156.991 | AB16: =Logistics!F16 -> 28029.626 | AC16: =Logistics!G16 -> 53305.665 | AD16: =Logistics!H16 -> 76214.874 | AH16: Ports | AI16: =+AI18-AI17 -> 42.2641 | AJ16: =(Assumptions!L233)/1000 -> 51.577909 | AK16: =(Assumptions!M233)/1000 -> 56.778376 | AL16: =(Assumptions!N233)/1000 -> 80.642965 | AM16: =(Assumptions!O233)/1000 -> 91.045521 | AN16: =(Assumptions!P233)/1000 -> 112.33586
B17: growth, % | C17: =IF(ISERROR(C16/#REF!-1)," ",C16/#REF!-1) | D17: =IF(ISERROR(D16/#REF!-1)," ",D16/#REF!-1) | E17: =IF(ISERROR(E16/#REF!-1)," ",E16/#REF!-1) | F17: =IF(ISERROR(F16/#REF!-1)," ",F16/#REF!-1) | G17: =IF(ISERROR(G16/F16-1)," ",G16/F16-1) | H17: =IF(ISERROR(H16/G16-1)," ",H16/G16-1) -> 0.082323542 | I17: =IF(ISERROR(I16/H16-1)," ",I16/H16-1) -> 0.058212919 | J17: =IF(ISERROR(J16/I16-1)," ",J16/I16-1) -> 0.4027705 | K17: =IF(ISERROR(K16/J16-1)," ",K16/J16-1) -> 0.41749851 | L17: =IF(ISERROR(L16/K16-1)," ",L16/K16-1) -> 0.4054804 | M17: =IF(ISERROR(M16/L16-1)," ",M16/L16-1) -> 0.17783935 | N17: =IF(ISERROR(N16/M16-1)," ",N16/M16-1) -> 0.18954846 | ... S17: =IF(ISERROR(S16/R16-1)," ",S16/R16-1) -> 0.30619457 | Y17: =IF(ISERROR(Y16/#REF!-1)," ",Y16/#REF!-1) | Z17: =IF(ISERROR(Z16/Y16-1)," ",Z16/Y16-1) -> 1.8612101 | AA17: =IF(ISERROR(AA16/Z16-1)," ",AA16/Z16-1) -> 1.2612055 | AB17: =IF(ISERROR(AB16/AA16-1)," ",AB16/AA16-1) -> 0.73482955 | AC17: =IF(ISERROR(AC16/AB16-1)," ",AC16/AB16-1) -> 0.90176155 | AD17: =IF(ISERROR(AD16/AC16-1)," ",AD16/AC16-1) -> 0.42977063 | AH17: Logistics | AI17: =(+Y16)/1000 -> 2.4973 | AJ17: =(+Z16)/1000 -> 7.1453 | AK17: =(+AA16)/1000 -> 16.156991 | AL17: =(+AB16)/1000 -> 28.029626 | AM17: =(+AC16)/1000 -> 53.305665 | AN17: =(+AD16)/1000 -> 76.214874
AH18: Consol | AI18: =(+N16)/1000 -> 44.7614 | AJ18: =SUM(AJ16:AJ17) -> 58.723209 | AK18: =SUM(AK16:AK17) -> 72.935368 | AL18: =SUM(AL16:AL17) -> 108.67259 | AM18: =SUM(AM16:AM17) -> 144.35119 | AN18: =SUM(AN16:AN17) -> 188.55074
B19: Operating Expenses | G19: 2210.381 | H19: 3379.552 | I19: 3454.403 | J19: 5746.02 | K19: 8581.91 | L19: 12065.7 | M19: 13587.3 | N19: 17434.7 | O19: 22855.2 | P19: =O19/O$22*P22 -> 35972.54 | Q19: =P19/P$22*Q22 -> 50748.496 | R19: =Q19/Q$22*R22 -> 71593.494 | S19: =R19/R$22*S22 -> 93687.931
B20: Employee benefits expense | G20: 569.579 | H20: 596.223 | I20: 746.658 | J20: 1113.5 | K20: 1496.51 | L20: 2299.58 | M20: 2846.4 | N20: 2406.5 | O20: 2386.9 | P20: =O20/O$22*P22 -> 3756.8193 | Q20: =P20/P$22*Q22 -> 5299.9573 | R20: =Q20/Q$22*R22 -> 7476.9203 | S20: =R20/R$22*S22 -> 9784.3695 | AH20: =(O16/M16)^(1/2)-1 -> 0.19365814 | AI20: =(S16/O16)^(1/4)-1 -> 0.36942009
B21: Other expenses | G21: =722.865+599.755 -> 1322.62 | H21: 705.42 | I21: 1038.43 | J21: 1011.79 | K21: 1557.86 | L21: 1380.22 | M21: 1549.6 | N21: 2298.4 | O21: 2335 | P21: =O21/O$22*P22 -> 3675.1322 | Q21: =P21/P$22*Q22 -> 5184.7167 | R21: =Q21/Q$22*R22 -> 7314.3446 | S21: =R21/R$22*S22 -> 9571.6212
B22: Total Expenditure | G22: =SUM(G19:G21) -> 4102.58 | H22: =SUM(H19:H21) -> 4681.195 | I22: =SUM(I19:I21) -> 5239.491 | J22: =SUM(J19:J21) -> 7871.31 | K22: =SUM(K19:K21) -> 11636.28 | L22: =SUM(L19:L21) -> 15745.5 | M22: =SUM(M19:M21) -> 17983.3 | N22: =SUM(N19:N21) -> 22139.6 | O22: =SUM(O19:O21) -> 27577.1 | P22: =P16-P23 -> 43404.491 | Q22: =Q16-Q23 -> 61233.17 | R22: =R16-R23 -> 86384.759 | S22: =S16-S23 -> 113043.92
B23: EBITDA | C23: =C16-SUM(C19:C21) -> 0 | D23: =D16-SUM(D19:D21) -> 0 | E23: =E16-SUM(E19:E21) -> 0 | F23: =F16-SUM(F19:F21) -> 0 | G23: =G16-SUM(G19:G21) -> 5878.356 | H23: =H16-SUM(H19:H21) -> 6121.407 | I23: =I16-SUM(I19:I21) -> 6191.962 | J23: =J16-SUM(J19:J21) -> 8164.395 | ... O23: =O16-SUM(O19:O21) -> 26037.3 | P23: =Assumptions!M289+AA23 -> 29530.876 | Q23: =Assumptions!N289+AB23 -> 47439.421 | R23: =Assumptions!O289+AC23 -> 57966.428 | S23: =Assumptions!P289+AD23 -> 75506.814 | U23: =(O23/M23)^(1/2)-1 -> 0.15123855 | V23: =(Q23/O23)^(1/2)-1 -> 0.34980713 | W23: =(S23/O23)^(1/4)-1 -> 0.30496105 | X23: =(Q23/O23)^(1/2)-1 -> 0.34980713 | Y23: =Logistics!C23 -> 311 | Z23: =Logistics!D23 -> 1417.5 | AA23: =Logistics!E23 -> 3934.1364 | AB23: =Logistics!F23 -> 6554.6446 | AC23: =Logistics!G23 -> 11414.799 | AD23: =Logistics!H23 -> 16310.648 | AE23: =(AD23/Z23)^(1/4)-1 -> 0.84177698
B24: margin, % | C24: =IF(ISERROR(C23/C16)," ",C23/C16) | D24: =IF(ISERROR(D23/D16)," ",D23/D16) | E24: =IF(ISERROR(E23/E16)," ",E23/E16) | F24: =IF(ISERROR(F23/F16)," ",F23/F16) | G24: =IF(ISERROR(G23/G16)," ",G23/G16) -> 0.58895839 | H24: =IF(ISERROR(H23/H16)," ",H23/H16) -> 0.56666042 | I24: =IF(ISERROR(I23/I16)," ",I23/I16) -> 0.5416601 | J24: =IF(ISERROR(J23/J16)," ",J23/J16) -> 0.50913851 | ... S24: =IF(ISERROR(S23/S16)," ",S23/S16) -> 0.40045887 | Y24: =IF(ISERROR(Y23/Y16)," ",Y23/Y16) -> 0.1245345 | Z24: =IF(ISERROR(Z23/Z16)," ",Z23/Z16) -> 0.19838215 | AA24: =IF(ISERROR(AA23/AA16)," ",AA23/AA16) -> 0.24349437 | AB24: =IF(ISERROR(AB23/AB16)," ",AB23/AB16) -> 0.23384702 | AC24: =IF(ISERROR(AC23/AC16)," ",AC23/AC16) -> 0.21413857 | AD24: =IF(ISERROR(AD23/AD16)," ",AD23/AD16) -> 0.21400873
B25: growth, % | C25: =IF(ISERROR(C23/#REF!-1)," ",C23/#REF!-1) | D25: =IF(ISERROR(D23/#REF!-1)," ",D23/#REF!-1) | E25: =IF(ISERROR(E23/#REF!-1)," ",E23/#REF!-1) | F25: =IF(ISERROR(F23/#REF!-1)," ",F23/#REF!-1) | H25: =IF(ISERROR(H23/G23-1)," ",H23/G23-1) -> 0.041346764 | I25: =IF(ISERROR(I23/H23-1)," ",I23/H23-1) -> 0.011525945 | J25: =IF(ISERROR(J23/I23-1)," ",J23/I23-1) -> 0.31854734 | K25: =IF(ISERROR(K23/J23-1)," ",K23/J23-1) -> 0.35886468 | L25: =IF(ISERROR(L23/K23-1)," ",L23/K23-1) -> 0.46037914 | M25: =IF(ISERROR(M23/L23-1)," ",M23/L23-1) -> 0.21254944 | N25: =IF(ISERROR(N23/M23-1)," ",N23/M23-1) -> 0.15149448 | O25: =IF(ISERROR(O23/N23-1)," ",O23/N23-1) -> 0.15098268 | ... S25: =IF(ISERROR(S23/R23-1)," ",S23/R23-1) -> 0.30259561 | Y25: =IF(ISERROR(Y23/#REF!-1)," ",Y23/#REF!-1) | Z25: =IF(ISERROR(Z23/Y23-1)," ",Z23/Y23-1) -> 3.5578778 | AA25: =IF(ISERROR(AA23/Z23-1)," ",AA23/Z23-1) -> 1.7754049 | AB25: =IF(ISERROR(AB23/AA23-1)," ",AB23/AA23-1) -> 0.6660949 | AC25: =IF(ISERROR(AC23/AB23-1)," ",AC23/AB23-1) -> 0.74148248 | AD25: =IF(ISERROR(AD23/AC23-1)," ",AD23/AC23-1) -> 0.42890373
B27: Other Income | G27: 766.755 | H27: 1013.331 | I27: 942.207 | J27: 746.93 | K27: 1056.79 | L27: 1781.13 | M27: 2694.1 | N27: 3529.5 | O27: 3459.5 | P27: =P244+AA27 -> 3758.2464 | Q27: =Q244+AB27 -> 4332.542 | R27: =R244+AC27 -> 2879.4492 | S27: =S244+AD27 -> 1594.2853 | AH27: =(O23/M23)^(1/2)-1 -> 0.15123855 | AI27: =(S23/O23)^(1/4)-1 -> 0.30496105
B28: Depreciation and Amortisation | G28: 1571.402 | H28: =1705.884+819.067 -> 2524.951 | I28: 2018.573 | J28: 2706.55 | K28: 3695.05 | L28: 3912.23 | M28: 4364.8 | N28: 5465.5 | O28: 6141.2 | P28: =P29*AVERAGE(O87:P87) -> 7453.8825 | Q28: =Q29*AVERAGE(P87:Q87) -> 12460.684 | R28: =R29*AVERAGE(Q87:R87) -> 18408.265 | S28: =S29*AVERAGE(R87:S87) -> 24495.596
N29: =N28/AVERAGE(M87:N87) -> 0.073281167 | O29: =O28/AVERAGE(N87:O87) -> 0.067550072 | P29: 0.065 | Q29: 0.065 | R29: 0.065 | S29: 0.065
B30: EBIT | C30: =C23+C27-C28 -> 0 | D30: =D23+D27-D28 -> 0 | E30: =E23+E27-E28 -> 0 | F30: =F23+F27-F28 -> 0 | G30: =G23+G27-G28 -> 5073.709 | H30: =H23+H27-H28 -> 4609.787 | I30: =I23+I27-I28 -> 5115.596 | J30: =J23+J27-J28 -> 6204.775 | ... S30: =S23+S27-S28 -> 52605.503 | U30: =(O30/M30)^(1/2)-1 -> 0.13988824 | V30: =(Q30/O30)^(1/2)-1 -> 0.29736767 | W30: =(S30/O30)^(1/4)-1 -> 0.22506755
N31: =N32/AVERAGE(M78:N78) -> 0.058795222 | O31: =O32/AVERAGE(N78:O78) -> 0.06920247 | P31: =P32/AVERAGE(O78:P78) -> 0.057159902 | Q31: =Q32/AVERAGE(P78:Q78) -> 0.072401675 | R31: =R32/AVERAGE(Q78:R78) -> 0.080906688 | S31: =S32/AVERAGE(R78:S78) -> 0.10694543 | Z31: 0.08 | AA31: 0.07 | AB31: 0.06 | AC31: 0.06 | AD31: 0.06
B32: Finance Expenses | G32: 1298.942 | H32: 1771.365 | I32: 2774.583 | J32: 2278.57 | K32: 4196.22 | L32: 5960.8 | M32: =2891.6+433 -> 3324.6 | N32: =3401-743.6 -> 2657.4 | O32: =3565.6+264.3 -> 3829.9 | P32: =P261+AA32 -> 4783.0375 | Q32: =Q261+AB32 -> 8558.4778 | R32: =R261+AC32 -> 10931.457 | S32: =S261+AD32 -> 15540.225 | AA32: =AVERAGE(Y78:Z78)*AA31 -> 1050 | AB32: =AVERAGE(Z78:AA78)*AB31 -> 1395 | AC32: =AVERAGE(AA78:AB78)*AC31 -> 2350 | AD32: =AVERAGE(AB78:AC78)*AD31 -> 3160
B33: Prior Period Items/Exceptional Items | O33: 797.3
B35: PBT | C35: =C30-C32-C33 -> 0 | D35: =D30-D32-D33 -> 0 | E35: =E30-E32-E33 -> 0 | F35: =F30-F32-F33 -> 0 | G35: =G30-G32-G33 -> 3774.767 | H35: =H30-H32-H33 -> 2838.422 | I35: =I30-I32-I33 -> 2341.013 | J35: =J30-J32-J33 -> 3926.205 | ... S35: =S30-S32-S33 -> 37065.278 | U35: =(O35/M35)^(1/2)-1 -> 0.13064712 | V35: =(Q35/O35)^(1/2)-1 -> 0.28142149 | W35: =(S35/O35)^(1/4)-1 -> 0.18608728
B37: Tax
B38: Current Tax | G38: 626.202 | H38: 538.608 | I38: 308.063 | J38: 761.25 | K38: 1175.58 | L38: 1610.83 | M38: 2637.9 | N38: 3030.4 | O38: 3134 | P38: =P41 -> 4631.4846 | Q38: =Q41 -> 6765.6163 | R38: =R41 -> 6301.2309 | S38: =S41 -> 8154.3612
B39: Deferred Tax | G39: 340.428 | H39: -419.835 | I39: 67.653 | J39: 318.7 | K39: -220.12 | L39: -1081.34 | M39: 401.4 | N39: 111.3 | O39: 131.7
B40: Prior Period Tax | L40: 85.3 | M40: 4.1 | N40: -328.1 | O40: -6.3
B41: Total Tax | C41: =SUM(C38:C40) -> 0 | D41: =SUM(D38:D40) -> 0 | E41: =SUM(E38:E40) -> 0 | F41: =SUM(F38:F40) -> 0 | G41: =SUM(G38:G40) -> 966.63 | H41: =SUM(H38:H40) -> 118.773 | I41: =SUM(I38:I40) -> 375.716 | J41: =SUM(J38:J40) -> 1079.95 | ... O41: =SUM(O38:O40) -> 3259.4 | P41: =P35*P42 -> 4631.4846 | Q41: =Q35*Q42 -> 6765.6163 | R41: =R35*R42 -> 6301.2309 | S41: =S35*S42 -> 8154.3612
B42: Effective tax rate, % | C42: =IF(ISERROR(C41/C35)," ",C41/C35) | D42: =IF(ISERROR(D41/D35)," ",D41/D35) | E42: =IF(ISERROR(E41/E35)," ",E41/E35) | F42: =IF(ISERROR(F41/F35)," ",F41/F35) | G42: =IF(ISERROR(G41/G35)," ",G41/G35) -> 0.25607673 | H42: =IF(ISERROR(H41/H35)," ",H41/H35) -> 0.041844729 | I42: =IF(ISERROR(I41/I35)," ",I41/I35) -> 0.16049291 | J42: =IF(ISERROR(J41/J35)," ",J41/J35) -> 0.27506205 | ... O42: =IF(ISERROR(O41/O35)," ",O41/O35) -> 0.17403516 | P42: 0.22 | Q42: 0.22 | R42: 0.2 | S42: 0.22
B44: PAT before Minority | C44: =C35-C36-C41 -> 0 | D44: =D35-D36-D41 -> 0 | E44: =E35-E36-E41 -> 0 | F44: =F35-F36-F41 -> 0 | G44: =G35-G36-G41 -> 2808.137 | H44: =H35-H36-H41 -> 2719.649 | I44: =I35-I36-I41 -> 1965.297 | J44: =J35-J36-J41 -> 2846.255 | ... S44: =S35-S36-S41 -> 28910.917 | U44: =(O44/M44)^(1/2)-1 -> 0.15444434 | V44: =(Q44/O44)^(1/2)-1 -> 0.24525565 | W44: =(S44/O44)^(1/4)-1 -> 0.16922988
B46: Less: Minority share | H46: 52.405 | I46: 61.056 | J46: -67.6 | K46: 24.91 | L46: 96.83 | M46: 47.8 | N46: 184 | O46: 235.9 | P46: =(Assumptions!M977*0.2)*0.5+(Logistics!O53*(1-Logistics!$K$1)) -> 462.40863 | Q46: =(Assumptions!N977*0.2)*0.5+(Logistics!P53*(1-Logistics!$K$1)) -> 598.62168 | R46: =(Assumptions!O977*0.2)*0.5+(Logistics!Q53*(1-Logistics!$K$1)) -> 759.49835 | S46: =(Assumptions!P977*0.2)*0.5+(Logistics!R53*(1-Logistics!$K$1)) -> 962.34259
B47: Add: Associates share
B49: PAT after Minority | C49: =C44-C46+C47 -> 0 | D49: =D44-D46+D47 -> 0 | E49: =E44-E46+E47 -> 0 | F49: =F44-F46+F47 -> 0 | G49: =G44-G46+G47 -> 2808.137 | H49: =H44-H46+H47 -> 2667.244 | I49: =I44-I46+I47 -> 1904.241 | J49: =J44-J46+J47 -> 2913.855 | ... S49: =S44-S46+S47 -> 27948.574 | U49: =(O49/M49)^(1/2)-1 -> 0.14797422 | V49: =(Q49/O49)^(1/2)-1 -> 0.23910362 | W49: =(S49/O49)^(1/4)-1 -> 0.16383883 | X49: =(Q49/O49)^(1/2)-1 -> 0.23910362
B50: margin, % | C50: =IF(ISERROR(C49/C16)," ",C49/C16) | D50: =IF(ISERROR(D49/D16)," ",D49/D16) | E50: =IF(ISERROR(E49/E16)," ",E49/E16) | F50: =IF(ISERROR(F49/F16)," ",F49/F16) | G50: =IF(ISERROR(G49/G16)," ",G49/G16) -> 0.28135007 | H50: =IF(ISERROR(H49/H16)," ",H49/H16) -> 0.24690755 | I50: =IF(ISERROR(I49/I16)," ",I49/I16) -> 0.16657909 | J50: =IF(ISERROR(J49/J16)," ",J49/J16) -> 0.18171044 | ... S50: =IF(ISERROR(S49/S16)," ",S49/S16) -> 0.1482284
B51: growth, % | C51: =IF(ISERROR(C49/B49-1)," ",C49/B49-1) | D51: =IF(ISERROR(D49/C49-1)," ",D49/C49-1) | E51: =IF(ISERROR(E49/D49-1)," ",E49/D49-1) | F51: =IF(ISERROR(F49/E49-1)," ",F49/E49-1) | G51: =IF(ISERROR(G49/F49-1)," ",G49/F49-1) | H51: =IF(ISERROR(H49/G49-1)," ",H49/G49-1) -> -0.050173122 | I51: =IF(ISERROR(I49/H49-1)," ",I49/H49-1) -> -0.28606419 | J51: =IF(ISERROR(J49/I49-1)," ",J49/I49-1) -> 0.53019234 | ... S51: =IF(ISERROR(S49/R49-1)," ",S49/R49-1) -> 0.14330489
B53: No. of shares | G53: 2100 | H53: 2100 | I53: 2100 | J53: 2100 | K53: 2100 | L53: 2100 | M53: 2100 | N53: =M53 -> 2100 | O53: =N53 -> 2100 | P53: =O53+Valuation!C69 -> 2330 | Q53: =P53 -> 2330 | R53: =Q53 -> 2330 | S53: =R53 -> 2330
B54: EPS | G54: =G49/G53 -> 1.3372081 | H54: =H49/H53 -> 1.2701162 | I54: =I49/I53 -> 0.90678143 | J54: =J49/J53 -> 1.38755 | K54: =K49/K53 -> 1.5616467 | L54: =L49/L53 -> 3.5230362 | M54: =M49/M53 -> 5.5043333 | N54: =N49/N53 -> 7.1575238 | ... S54: =S49/S53 -> 11.995096
B55: P/E | G55: =NewFinSumm!C77 -> 260.58024 | H55: =NewFinSumm!D77 -> 274.34498 | I55: =NewFinSumm!E77 -> 384.27121 | J55: =NewFinSumm!F77 -> 251.12609 | K55: =NewFinSumm!G77 -> 223.12986 | L55: =NewFinSumm!H77 -> 98.906165 | M55: =NewFinSumm!I77 -> 63.304669 | N55: =NewFinSumm!J77 -> 48.683037 | ... S55: =NewFinSumm!O77 -> 29.049371
B56: BV/ Share | G56: =SUM(G65:G66)/G53 -> 12.443199 | H56: =SUM(H65:H66)/H53 -> 13.750785 | I56: =SUM(I65:I66)/I53 -> 12.134361 | J56: =SUM(J65:J66)/J53 -> 13.767467 | K56: =SUM(K65:K66)/K53 -> 15.581514 | L56: =SUM(L65:L66)/L53 -> 19.022024 | M56: =SUM(M65:M66)/M53 -> 38.220762 | N56: =SUM(N65:N66)/N53 -> 46.175714 | ... S56: =SUM(S65:S66)/S53 -> 109.99462
B57: P/BV | G57: =NewFinSumm!C83 -> 26.088124 | H57: =NewFinSumm!D83 -> 23.721615 | I57: =NewFinSumm!E83 -> 26.596179 | J57: =NewFinSumm!F83 -> 23.693099 | K57: =NewFinSumm!G83 -> 21.076351 | L57: =NewFinSumm!H83 -> 17.896007 | M57: =NewFinSumm!I83 -> 8.890089 | N57: =NewFinSumm!J83 -> 6.9765081 | ... S57: =NewFinSumm!O83 -> 2.7383336
B58: DPS | M58: 0.55 | N58: 0.8 | O58: 0.9 | P58: =P54*P59 -> 0.82188719 | Q58: =Q54*Q59 -> 1.2045612 | R58: =R54*R59 -> 1.2589919 | S58: =S54*S59 -> 1.4394116
B59: Dividend Payout | M59: =M58/M54 -> 0.099921274 | N59: =N58/N54 -> 0.1117705 | O59: =O58/O54 -> 0.12407192 | P59: 0.12 | Q59: 0.12 | R59: 0.12 | S59: 0.12
B60: Dividend | M60: =M58*M53 -> 1155 | N60: =N53*N58 -> 1680 | O60: =O53*O58 -> 1890 | P60: =P53*P58 -> 1914.9972 | Q60: =Q53*Q58 -> 2806.6276 | R60: =R53*R58 -> 2933.451 | S60: =S53*S58 -> 3353.8289
B63: Balance Sheet
B64: Shareholder's funds
B65: Share Capital | G65: 601.798 | H65: 601.798 | I65: 599.29 | J65: 599.29 | K65: 599.29 | L65: 3595.75 | M65: 4103 | N65: 4147 | O65: 4170.4 | P65: =O65+Valuation!C72 -> 4630.4 | Q65: =P65 -> 4630.4 | R65: =Q65 -> 4630.4 | S65: =R65 -> 4630.4
B66: Reserves & Surplus | G66: 25528.919 | H66: 28274.851 | I66: 24882.869 | J66: 28312.39 | K66: 32121.89 | L66: 36350.5 | M66: 76160.6 | N66: 92822 | O66: 104604.6 | P66: =O66+P49-P60+Valuation!C73 -> 184968.41 | Q66: =P66+Q49-Q60 -> 205550.35 | R66: =Q66+R49-R60 -> 227062.32 | S66: =R66+S49-S60 -> 251657.07
B67: Share application money pending allotment
B69: Minority Interest | G69: 1918.253 | H69: 1970.534 | I69: 2031.004 | J69: 1972.63 | K69: 1997.59 | L69: 942.48 | M69: 2046.6 | N69: 7918 | O69: 8152.4 | P69: =O69+P46 -> 8614.8086 | Q69: =P69+Q46 -> 9213.4303 | R69: =Q69+R46 -> 9972.9287 | S69: =R69+S46 -> 10935.271
B71: Long Term Borrowings | G71: 13638.761 | H71: =20001.206 -> 20001.206 | I71: =26112.07 -> 26112.07 | J71: 33904.54 | K71: 40946.82 | L71: 40954.4 | M71: 42701.8 | N71: 44390.1 | O71: 59516.6 | P71: =O71/O$77*P77 -> 95876.793 | Q71: =P71/P$77*Q77 -> 123640.21 | R71: =Q71/Q$77*R77 -> 127267.42 | S71: =R71/R$77*S77 -> 142578.16
B72: Short Term Borrowings | G72: 3161.15 | H72: 0 | I72: =1055.09 -> 1055.09 | J72: 5553.64 | K72: =3140.12-K73 -> 2318.707 | L72: =1482.58-L73 -> 677.462 | M72: 1105 | N72: 2198.2 | O72: 4581.9 | P72: =O72/O$77*P77 -> 7381.0983 | Q72: =P72/P$77*Q77 -> 9518.4717 | R72: =Q72/Q$77*R77 -> 9797.7138 | S72: =R72/R$77*S77 -> 10976.414
B73: Current Maturities of Long Term Borrowings | H73: 0 | I73: 0 | J73: 0 | K73: =821.413 -> 821.413 | L73: =805.118 -> 805.118 | M73: 0
B74: opening | C74: =C71+C72+C73 -> 0 | D74: =D71+D72+D73 -> 0 | E74: =E71+E72+E73 -> 0 | F74: =F71+F72+F73 -> 0 | G74: =G71+G72+G73 -> 16799.911 | H74: =H71+H72+H73 -> 20001.206 | I74: =I71+I72+I73 -> 27167.16 | J74: =J71+J72+J73 -> 39458.18 | ... O74: =O71+O72+O73 -> 64098.5 | P74: =O78 -> 64098.5 | Q74: =P78 -> 103257.89 | R74: =Q78 -> 133158.68 | S74: =R78 -> 137065.14 | AA74: =Z78 -> 15000 | AB74: =AA78 -> 31500 | AC74: =AB78 -> 46833.333 | AD74: =AC78 -> 58500
B75: addition | P75: =SUM(Assumptions!DQ1578:DQ1592)+AA75 -> 50187.391 | Q75: =SUM(Assumptions!DR1578:DR1592)+AB75 -> 37601.287 | R75: =SUM(Assumptions!DS1578:DS1592)+AC75 -> 47401.344 | S75: =SUM(Assumptions!DT1578:DT1592)+AD75 -> 25570.668 | Z75: =Logistics!D79 -> 15000 | AA75: =Logistics!E79 -> 17500 | AB75: =Logistics!F79 -> 17500 | AC75: =Logistics!G79 -> 15000 | AD75: =Logistics!H79 -> 15000
B76: repayment | P76: =SUM(Assumptions!EC1578:EC1592)+AA76+10000 -> 11028 | Q76: =SUM(Assumptions!ED1578:ED1592)+AB76+5000 -> 7700.4987 | R76: =SUM(Assumptions!EE1578:EE1592)+AC76+400*92 -> 43494.885 | S76: =SUM(Assumptions!EF1578:EF1592)+AD76 -> 9081.2354 | Z76: =Logistics!D80 -> 0 | AA76: =Logistics!E80 -> 1000 | AB76: =Logistics!F80 -> 2166.6667 | AC76: =Logistics!G80 -> 3333.3333 | AD76: =Logistics!H80 -> 4333.3333
B77: closing | C77: =C74+C75-C76 -> 0 | D77: =D74+D75-D76 -> 0 | E77: =E74+E75-E76 -> 0 | F77: =F74+F75-F76 -> 0 | G77: =G74+G75-G76 -> 16799.911 | H77: =H74+H75-H76 -> 20001.206 | I77: =I74+I75-I76 -> 27167.16 | J77: =J74+J75-J76 -> 39458.18 | ... S77: =S74+S75-S76 -> 153554.57
B78: Long term borrowings | C78: =C77 -> 0 | D78: =D77 -> 0 | E78: =E77 -> 0 | F78: =F77 -> 0 | G78: =G77 -> 16799.911 | H78: =H77 -> 20001.206 | I78: =I77 -> 27167.16 | J78: =J77 -> 39458.18 | ... S78: =S77 -> 153554.57 | Z78: =Z74+Z75-Z76 -> 15000 | AA78: =AA74+AA75-AA76 -> 31500 | AB78: =AB74+AB75-AB76 -> 46833.333 | AC78: =AC74+AC75-AC76 -> 58500 | AD78: =AD74+AD75-AD76 -> 69166.667
B79: Deferred Tax Liabilities (net) | G79: 735.373 | H79: 462.317 | I79: 1242.051 | J79: 1708.18 | K79: 2519.99 | L79: 1385.05 | M79: 1339.7 | N79: 1214.2 | O79: 1433.4 | P79: =O79 -> 1433.4 | Q79: =P79 -> 1433.4 | R79: =Q79 -> 1433.4 | S79: =R79 -> 1433.4
B80: Other long term liabilities | G80: =570.842+1094.818 -> 1665.66 | H80: =733.346+1016.536 -> 1749.882 | I80: =1838.177+2962.561 -> 4800.738 | J80: =2377.7+980.16+2892.4 -> 6250.26 | K80: =3219.24+889.68+2863.07 -> 6971.99 | L80: =3091.62+238.18+774.98 -> 4104.78 | M80: =3634.9+240.7+692.6 -> 4568.2 | N80: =3623.1+840.6+418.6 -> 4882.3 | O80: =921.4+4579.8+381.1 -> 5882.3 | P80: =O80 -> 5882.3 | Q80: =P80 -> 5882.3 | R80: =Q80 -> 5882.3 | S80: =R80 -> 5882.3
B81: Long term provisions | G81: 33.981 | H81: =37.117 -> 37.117 | I81: =48.229 -> 48.229 | J81: 66.33 | K81: 71.3 | L81: 32.71 | M81: 79 | N81: 189.5 | O81: 344.4 | P81: =O81 -> 344.4 | Q81: =P81 -> 344.4 | R81: =Q81 -> 344.4 | S81: =R81 -> 344.4
B83: Total Liabilities | C83: =SUM(C65:C66)+C69+SUM(C78:C81) -> 0 | D83: =SUM(D65:D66)+D69+SUM(D78:D81) -> 0 | E83: =SUM(E65:E66)+E69+SUM(E78:E81) -> 0 | F83: =SUM(F65:F66)+F69+SUM(F78:F81) -> 0 | G83: =SUM(G65:G66)+G69+SUM(G78:G81) -> 47283.895 | H83: =SUM(H65:H66)+H69+SUM(H78:H81) -> 53097.705 | I83: =SUM(I65:I66)+I69+SUM(I78:I81) -> 60771.341 | J83: =SUM(J65:J66)+J69+SUM(J78:J81) -> 78367.26 | ... S83: =SUM(S65:S66)+S69+SUM(S78:S81) -> 428437.41
B85: Non current assets
B86: Fixed assets
B87: Gross block | G87: 29525.534 | H87: =32684.214 -> 32684.214 | I87: =40511.62+1067.937 -> 41579.557 | J87: =J88+J89 -> 44786.871 | K87: =42611.974+4793.027 -> 47405.001 | L87: =43996.417+4890.081 -> 48886.498 | M87: =58757.8+5473.2 -> 64231 | N87: =79291.3+5642.9 -> 84934.2 | O87: =87663.9+6980.6 -> 94644.5 | P87: =O87+SUM(Assumptions!FM1578:FM1592)+AA87 -> 132457.83 | Q87: =P87+SUM(Assumptions!FN1578:FN1592)+AB87 -> 250947.83 | R87: =Q87+SUM(Assumptions!FO1578:FO1592)+AC87 -> 315460.33 | S87: =R87+SUM(Assumptions!FP1578:FP1592)+AD87 -> 438250.33 | Z87: =Logistics!D190 -> 15000 | AA87: =Logistics!E190 -> 17500 | AB87: =Logistics!F190 -> 17500 | AC87: =Logistics!G190 -> 15000 | AD87: =Logistics!H190 -> 15000
B88: Accumulated depreciation | G88: 2157.273 | H88: =3503.885 -> 3503.885 | I88: =5060.267+81.824 -> 5142.091 | J88: =I88+J28 -> 7848.641 | K88: =8350.277+342.601 -> 8692.878 | L88: =9780.488+654.993 -> 10435.481 | M88: =12205.9+897 -> 13102.9 | N88: =1191+15611.5 -> 16802.5 | O88: =19121.2+1574.6 -> 20695.8 | P88: =O88+P28 -> 30397.582 | Q88: =P88+Q28 -> 42858.266 | R88: =Q88+R28 -> 61266.532 | S88: =R88+S28 -> 85762.128
B89: Net block | G89: =G87-G88 -> 27368.261 | H89: =H87-H88 -> 29180.329 | I89: =I87-I88 -> 36437.466 | J89: =33189.18+3749.05 -> 36938.23 | K89: =K87-K88 -> 38712.123 | L89: =L87-L88 -> 38451.017 | M89: =M87-M88 -> 51128.1 | N89: =N87-N88 -> 68131.7 | O89: =O87-O88 -> 73948.7 | P89: =P87-P88 -> 102060.25 | Q89: =Q87-Q88 -> 208089.56 | R89: =R87-R88 -> 254193.8 | S89: =S87-S88 -> 352488.2
B90: Capital work in progress | G90: 6222.801 | H90: =8594.167 -> 8594.167 | I90: =7502.798 -> 7502.798 | J90: 2921.06 | K90: 700.84 | L90: 450.32 | M90: 1088.6 | N90: 18586.4 | O90: 31474.2 | P90: =SUM(Assumptions!FY1578:FY1592) -> 68297.287 | Q90: =SUM(Assumptions!FZ1578:FZ1592) -> 38869.411 | R90: =SUM(Assumptions!GA1578:GA1592) -> 55523.546 | S90: =SUM(Assumptions!GB1578:GB1592) -> 0
B92: Tangible Assets
B93: Intangible Assets | G93: 3671.532 | H93: =3384.563 -> 3384.563 | I93: =3042.448 -> 3042.448 | J93: =11939.27+362.44 -> 12301.71 | K93: =22264.35+362.44 -> 22626.79 | L93: =20932.11+362.44 -> 21294.55 | M93: =19476.7+6969.7 -> 26446.4 | N93: =7126+18671.6 -> 25797.6 | O93: =7678.9+22678.5 -> 30357.4 | P93: =O93 -> 30357.4 | Q93: =P93 -> 30357.4 | R93: =Q93 -> 30357.4 | S93: =R93 -> 30357.4
B94: Intangible Assets Under Development | G94: 103.427 | H94: =25.742 -> 25.742 | I94: =12.953 -> 12.953 | J94: 8329.4 | K94: 95.97 | L94: 9.81 | M94: 231.8 | N94: 1616 | O94: 410.2 | P94: =O94 -> 410.2 | Q94: =P94 -> 410.2 | R94: =Q94 -> 410.2 | S94: =R94 -> 410.2
B96: Non current investments | G96: 0 | H96: 0 | I96: =3090 -> 3090 | J96: 2955.08 | K96: 2830.08 | L96: 25.37 | M96: 246.5 | N96: =1300+229.8 -> 1529.8 | O96: =964.8+233.5 -> 1198.3 | P96: =O96 -> 1198.3 | Q96: =P96 -> 1198.3 | R96: =Q96 -> 1198.3 | S96: =R96 -> 1198.3
B97: Deferred tax assets (net) | G97: 845.222 | H97: =1060.228 -> 1060.228 | I97: 1129.895 | J97: 2469.29 | K97: 3489.03 | L97: 3505.63 | M97: 3255.4 | N97: 4589.5 | O97: 5236.6 | P97: =O97 -> 5236.6 | Q97: =P97 -> 5236.6 | R97: =Q97 -> 5236.6 | S97: =R97 -> 5236.6
B98: Long term loans & advances | G98: 19 | H98: =15.2 -> 15.2 | I98: =15.2 -> 15.2 | J98: 249.77 | K98: 145 | L98: 0 | M98: 0 | P98: =O98 -> 0 | Q98: =P98 -> 0 | R98: =Q98 -> 0 | S98: =R98 -> 0
B99: Other non-current assets | G99: =819.067+494.332+1758.587 -> 3071.986 | H99: =161.036+1992.46 -> 2153.496 | I99: =135.945+916.935 -> 1052.88 | J99: =1099.19+624.34+631.78 -> 2355.31 | K99: =1062.95+760.08+509.23 -> 2332.26 | L99: =1355.15+1004.47+508.16 -> 2867.78 | M99: =340+1036.1+620.8 -> 1996.9 | N99: =5062.5+986+1599.4 -> 7647.9 | O99: =9497.8+1447.6+5789.2 -> 16734.6 | P99: =O99 -> 16734.6 | Q99: =P99 -> 16734.6 | R99: =Q99 -> 16734.6 | S99: =R99 -> 16734.6
B101: Current Assets
B102: Current Investments | G102: 283.762 | H102: 2297.624 | I102: 674.403 | J102: 0 | K102: 0 | L102: 3044.91 | M102: 2198.4 | N102: 1597.8 | O102: 20.1 | P102: =O102 -> 20.1 | Q102: =P102 -> 20.1 | R102: =Q102 -> 20.1 | S102: =R102 -> 20.1
B103: Inventories | G103: 499.394 | H103: =758.528 -> 758.528 | I103: =1251.534 -> 1251.534 | J103: 991.48 | K103: 854.06 | L103: 1021.6 | M103: 1117.4 | N103: 1338 | O103: 1473.3 | P103: =O103 -> 1473.3 | Q103: =P103 -> 1473.3 | R103: =Q103 -> 1473.3 | S103: =R103 -> 1473.3
B104: Trade receivabels | G104: 2942.713 | H104: =3904.977 -> 3904.977 | I104: =5021.875 -> 5021.875 | J104: 4817.96 | K104: 6013.45 | L104: 4023.72 | M104: 6767.9 | N104: 8090.3 | O104: 10579.9 | P104: =P16/365*P209 -> 14392.568 | Q104: =Q16/365*Q209 -> 21444.708 | R104: =R16/365*R209 -> 27298.83 | S104: =S16/365*S209 -> 34107.852
B105: Cash and bank balances | G105: =772.735+2511.761 -> 3284.496 | H105: =502.965+514.671 -> 1017.636 | I105: =1571.013+55.061 -> 1626.074 | J105: =1513.52+1134.88 -> 2648.4 | K105: =5288.15+5094.2 -> 10382.35 | L105: =6186.9+10129.53 -> 16316.43 | M105: =7233.9+33668.3 -> 40902.2 | N105: =6112.5+18708.2 -> 24820.7 | O105: =7977.5+15199.5 -> 23177 | P105: =P175 -> 76224.856 | Q105: =Q175 -> 46148.822 | R105: =R175 -> 7392.8163 | S105: =S175 -> 3310.0258
B106: Short term loans and advances | G106: 1495.037 | H106: =358.796 -> 358.796 | I106: =651.759 -> 651.759 | J106: 2458.91 | K106: 2333.33 | L106: 585.49 | M106: 73.6 | N106: 0 | P106: =O106 -> 0 | Q106: =P106 -> 0 | R106: =Q106 -> 0 | S106: =R106 -> 0
B107: Other current assets | G107: =332.996+231.822+2216.294 -> 2781.112 | H107: =13862.88-SUM(H102:H106) -> 5525.319 | I107: =16315.14-SUM(I102:I106) -> 7089.495 | J107: =502.96+2605.97 -> 3108.93 | K107: =458.15+3321.24 -> 3779.39 | L107: =142.79+2767.16 -> 2909.95 | M107: =818+2004.3 -> 2822.3 | N107: =1420.3+4118.9 -> 5539.2 | O107: =1731.9+7117.7+124.6 -> 8974.2 | P107: =O107 -> 8974.2 | Q107: =P107 -> 8974.2 | R107: =Q107 -> 8974.2 | S107: =R107 -> 8974.2
B108: Total Current Assets | C108: =SUM(C102:C107) -> 0 | D108: =SUM(D102:D107) -> 0 | E108: =SUM(E102:E107) -> 0 | F108: =SUM(F102:F107) -> 0 | G108: =SUM(G102:G107) -> 11286.514 | H108: =SUM(H102:H107) -> 13862.88 | I108: =SUM(I102:I107) -> 16315.14 | J108: =SUM(J102:J107) -> 14025.68 | ... S108: =SUM(S102:S107) -> 47885.478
B110: Trade payables | G110: =2.557+1555.036 -> 1557.593 | H110: =67.321+4.971 -> 72.292 | I110: =5.102+793.571 -> 798.673 | J110: =108.95+2042.45 -> 2151.4 | K110: =99.54+2648.37 -> 2747.91 | L110: =219.36+2796.49 -> 3015.85 | M110: =350.2+3212 -> 3562.2 | N110: =425.9+3067.7 -> 3493.6 | O110: =746.2+2998.7 -> 3744.9 | P110: =(P16/365*P210) -> 5094.4459 | Q110: =(Q16/365*Q210) -> 7590.647 | R110: =(R16/365*R210) -> 11269.201 | S110: =(S16/365*S210) -> 14719.769
B111: Other current liabilities | G111: =3565.338+162.246+13.964 -> 3741.548 | H111: =1196.901+3904.058 -> 5100.959 | I111: =6813.458+208.793 -> 7022.251 | J111: =101.99+1216.26+693.42 -> 2011.67 | K111: =95.52+1929.92+1082.22+52.44 -> 3160.1 | L111: =147.49+1620.55+828.22 -> 2596.26 | M111: =914.1+143.1+1499.4 -> 2556.6 | N111: =209.9+6682.3+985.4 -> 7877.6 | O111: =310.9+9430.8+1200 -> 10941.7 | P111: =O111 -> 10941.7 | Q111: =P111 -> 10941.7 | R111: =Q111 -> 10941.7 | S111: =R111 -> 10941.7
B112: Short term provisions | G112: 5.707 | H112: 5.648 | I112: =6.513 -> 6.513 | J112: 15.21 | K112: 17.62 | L112: 46.21 | M112: 52.9 | N112: 152.5 | O112: 211.9 | P112: =O112 -> 211.9 | Q112: =P112 -> 211.9 | R112: =Q112 -> 211.9 | S112: =R112 -> 211.9
B113: Total Current Liabilities | C113: =SUM(C110:C112) -> 0 | D113: =SUM(D110:D112) -> 0 | E113: =SUM(E110:E112) -> 0 | F113: =SUM(F110:F112) -> 0 | G113: =SUM(G110:G112) -> 5304.848 | H113: =SUM(H110:H112) -> 5178.899 | I113: =SUM(I110:I112) -> 7827.437 | J113: =SUM(J110:J112) -> 4178.28 | ... S113: =SUM(S110:S112) -> 25873.369
B115: Net Current Assets | C115: =C108-C113 -> 0 | D115: =D108-D113 -> 0 | E115: =E108-E113 -> 0 | F115: =F108-F113 -> 0 | G115: =G108-G113 -> 5981.666 | H115: =H108-H113 -> 8683.981 | I115: =I108-I113 -> 8487.703 | J115: =J108-J113 -> 9847.4 | ... S115: =S108-S113 -> 22012.108
B117: Total Assets | C117: =SUM(C89:C94)+SUM(C96:C99)+C115 -> 0 | D117: =SUM(D89:D94)+SUM(D96:D99)+D115 -> 0 | E117: =SUM(E89:E94)+SUM(E96:E99)+E115 -> 0 | F117: =SUM(F89:F94)+SUM(F96:F99)+F115 -> 0 | G117: =SUM(G89:G94)+SUM(G96:G99)+G115 -> 47283.895 | H117: =SUM(H89:H94)+SUM(H96:H99)+H115 -> 53097.706 | I117: =SUM(I89:I94)+SUM(I96:I99)+I115 -> 60771.343 | J117: =SUM(J89:J94)+SUM(J96:J99)+J115 -> 78367.25 | ... S117: =SUM(S89:S94)+SUM(S96:S99)+S115 -> 428437.41
C118: =C83-C117 -> 0 | D118: =D83-D117 -> 0 | E118: =E83-E117 -> 0 | F118: =F83-F117 -> 0 | G118: =G83-G117 -> 0 | H118: =H83-H117 -> -0.001 | I118: =I83-I117 -> -0.002 | J118: =J83-J117 -> 0.01 | ... S118: =S83-S117 -> 0
B120: Cash Flows | C120: =C2 -> FY14 | D120: =D2 -> FY15 | E120: =E2 -> FY16 | F120: =F2 -> FY17
...

Sheet Valuation
B2: CMP, Rs./ share | C2: =F2 -> 348.45 | E2: #VALUE! | F2: {=_FV(E2,"Price")} -> 348.45 | H2: =+H33/C2-1 -> -0.15680739
B3: No. of Shares, mn | C3: =Consol!P53 -> 2330
B4: Mcap, Rs. mn | C4: =C2*C3 -> 811888.5 | D4: =+C4+H15 -> 898878.26 | E4: =+D4/20 -> 44943.913
B6: JSW Infra | K6: CAGR, % | P6: 360
D7: FY24 | E7: FY25 | F7: FY26 | G7: FY27E | H7: FY28E | I7: FY29E | J7: FY30E | K7: FY26-30E | L7: FY25-30E | P7: 285
B8: Capacity | C8: MT | D8: =Assumptions!J111 -> 170 | E8: =Assumptions!K111 -> 176.9 | F8: =Assumptions!L111 -> 182.8 | G8: =Assumptions!M111 -> 197.62 | H8: =Assumptions!N111 -> 299.92 | I8: =Assumptions!O111 -> 341.92 | J8: =Assumptions!P111 -> 401.92 | K8: =(J8/F8)^(1/4)-1 -> 0.21770154 | L8: =(J8/E8)^(1/5)-1 -> 0.17837184 | P8: =P7/P6-1 -> -0.20833333
B9: Volumes | C9: MT | D9: =Assumptions!J27 -> 107.03816 | E9: =Assumptions!K27 -> 117 | F9: =Assumptions!L27 -> 120.74 | G9: =Assumptions!M27 -> 127.95611 | H9: =Assumptions!N27 -> 168.54703 | I9: =Assumptions!O27 -> 196.93431 | J9: =Assumptions!P27 -> 237.39015 | K9: =(J9/F9)^(1/4)-1 -> 0.18413954 | L9: =(J9/F9)^(1/4)-1 -> 0.18413954
B10: Revenue | C10: Rs. mn | D10: =Consol!M16 -> 37628.9 | E10: =Consol!N16 -> 44761.4 | F10: =Consol!O16 -> 53614.4 | G10: =Consol!P16 -> 72935.368 | H10: =Consol!Q16 -> 108672.59 | I10: =Consol!R16 -> 144351.19 | J10: =Consol!S16 -> 188550.74 | K10: =(J10/F10)^(1/4)-1 -> 0.36942009 | L10: =(J10/E10)^(1/5)-1 -> 0.3332295
B11: EBITDA | C11: Rs. mn | D11: =Consol!M23 -> 19645.6 | E11: =Consol!N23 -> 22621.8 | F11: =Consol!O23 -> 26037.3 | G11: =Consol!P23 -> 29530.876 | H11: =Consol!Q23 -> 47439.421 | I11: =Consol!R23 -> 57966.428 | J11: =Consol!S23 -> 75506.814 | K11: =(J11/F11)^(1/4)-1 -> 0.30496105 | L11: =(J11/E11)^(1/5)-1 -> 0.27259964
B13: Debt | C13: Rs. mn | D13: =Consol!M78 -> 43806.8 | E13: =Consol!N78 -> 46588.3 | F13: =Consol!O78 -> 64098.5 | G13: =Consol!P78 -> 103257.89 | H13: =Consol!Q78 -> 133158.68 | I13: =Consol!R78 -> 137065.14 | J13: =Consol!S78 -> 153554.57
B14: Cash | C14: Rs. mn | D14: =Consol!M105+Consol!M102 -> 43100.6 | E14: =Consol!N105+Consol!N102 -> 26418.5 | F14: =Consol!O105+Consol!O102 -> 23197.1 | G14: =Consol!P105+Consol!P102 -> 76244.956 | H14: =Consol!Q105+Consol!Q102 -> 46168.922 | I14: =Consol!R105+Consol!R102 -> 7412.9163 | J14: =Consol!S105+Consol!S102 -> 3330.1258
B15: Net Debt | C15: Rs. mn | D15: =D13-D14 -> 706.2 | E15: =E13-E14 -> 20169.8 | F15: =F13-F14 -> 40901.4 | G15: =G13-G14 -> 27012.935 | H15: =H13-H14 -> 86989.757 | I15: =I13-I14 -> 129652.22 | J15: =J13-J14 -> 150224.45
B17: =CONCATENATE("-@CMP of Rs.",C2,"/ share it is trading at") -> -@CMP of Rs.348.45/ share it is trading at | C17: x | E17: =($C$4+D15)/E11 -> 35.920868 | F17: =($C$4+E15)/F11 -> 31.956397 | G17: =($C$4+F15)/G11 -> 28.877907 | H17: =($C$4+G15)/H11 -> 17.683636 | I17: =($C$4+H15)/I11 -> 15.506877 | J17: =($C$4+I15)/J11 -> 12.469613
B19: JSW Infra - Valuation | K19: Upside | R19: ~15% expected long-term (FY24-30E) cargo growth profile
D20: FY24 | E20: FY25 | F20: FY26 | G20: FY27E | H20: FY28E | I20: FY29E | J20: FY30E | K20: FY25E/ FY24 | L20: FY26E/ FY24 | M20: FY27E/ FY24 | N20: FY28E/ FY24 | O20: FY29E/ FY24 | P20: FY30E/ FY24 | R20: MT | S20: FY24 | U20: FY30E | V20: FY24-30E
B21: P/E methodology | R21: 1.JSW Group Cargo growth due to expansion at Steel Plants | S21: Existing Volumes | T21: Incremental Volumes | V21: CAGR
B22: Consolidated EPS | C22: Rs./ share | D22: =Consol!M54 -> 5.5043333 | E22: =Consol!N54 -> 7.1575238 | F22: =Consol!O54 -> 7.2538571 | G22: =Consol!P54 -> 6.8490599 | H22: =Consol!Q54 -> 10.03801 | I22: =Consol!R54 -> 10.491599 | J22: =Consol!S54 -> 11.995096 | R22: =CONCATENATE("Due to addition of ",Assumptions!Q1602,"MT capacity at JSW Steel Plants - Dolvi, Vijayanagar, Orissa") -> Due to addition of 16MT capacity at JSW Steel Plants - Dolvi, Vijayanagar, Orissa | S22: =+Assumptions!J192 -> 64.480897 | T22: =Assumptions!AA1660-Assumptions!Z1660-X22 -> 30.75075 | U22: =+S22+T22 -> 95.231647 | V22: =+(U22/S22)^(0.166666666666667)-1 -> 0.06714894 | X22: 3
B23: =CONCATENATE("At CMP of Rs. ",ROUND($C$2,0),"/share") -> At CMP of Rs. 348/share | C23: implied P/E | D23: =$C$2/D22 -> 63.304669 | E23: =$C$2/E22 -> 48.683037 | F23: =$C$2/F22 -> 48.036513 | G23: =$C$2/G22 -> 50.875595 | H23: =$C$2/H22 -> 34.713056 | I23: =$C$2/I22 -> 33.212288 | J23: =$C$2/J22 -> 29.049371 | R23: 2.JSW Group Cargo growth due to addition of new Steel Assets
A24: 30 | B24: =CONCATENATE("-Target Price @",ROUND(A24,0),"x P/E") -> -Target Price @30x P/E | C24: Rs./ share | D24: =D$22*$A24 -> 165.13 | E24: =E$22*$A24 -> 214.72571 | F24: =F$22*$A24 -> 217.61571 | G24: =G$22*$A24 -> 205.4718 | H24: =H$22*$A24 -> 301.1403 | I24: =I$22*$A24 -> 314.74797 | J24: =J$22*$A24 -> 359.85289 | K24: =E24/$C$2-1 -> -0.38376894 | L24: =F24/$C$2-1 -> -0.37547506 | M24: =G24/$C$2-1 -> -0.41032631 | N24: =H24/$C$2-1 -> -0.13577185 | O24: =I24/$C$2-1 -> -0.096719856 | P24: =J24/$C$2-1 -> 0.032724605 | R24: =CONCATENATE("Due to creation of Slurry Pipelines of 60MT and Jatadhar Port 30MT addition") -> Due to creation of Slurry Pipelines of 60MT and Jatadhar Port 30MT addition | S24: 0 | T24: =Assumptions!P1355+Assumptions!P1306+Assumptions!P1257-X24 -> 30.75 | U24: =+S24+T24 -> 30.75 | V24: - | X24: 3
A25: 40 | B25: =CONCATENATE("-Target Price @",ROUND(A25,0),"x P/E") -> -Target Price @40x P/E | C25: Rs./ share | D25: =D$22*$A25 -> 220.17333 | E25: =E$22*$A25 -> 286.30095 | F25: =F$22*$A25 -> 290.15429 | G25: =G$22*$A25 -> 273.9624 | H25: =H$22*$A25 -> 401.5204 | I25: =I$22*$A25 -> 419.66395 | J25: =J$22*$A25 -> 479.80385 | K25: =E25/$C$2-1 -> -0.17835858 | L25: =F25/$C$2-1 -> -0.16730008 | M25: =G25/$C$2-1 -> -0.21376841 | N25: =H25/$C$2-1 -> 0.1523042 | O25: =I25/$C$2-1 -> 0.20437353 | P25: =J25/$C$2-1 -> 0.37696614 | R25: 3.3rd Party Cargo Growth due to addition of new Port Assets
A26: 50 | B26: =CONCATENATE("-Target Price @",ROUND(A26,0),"x P/E") -> -Target Price @50x P/E | C26: Rs./ share | D26: =D$22*$A26 -> 275.21667 | E26: =E$22*$A26 -> 357.87619 | F26: =F$22*$A26 -> 362.69286 | G26: =G$22*$A26 -> 342.453 | H26: =H$22*$A26 -> 501.9005 | I26: =I$22*$A26 -> 524.57994 | J26: =J$22*$A26 -> 599.75481 | K26: =E26/$C$2-1 -> 0.027051774 | L26: =F26/$C$2-1 -> 0.040874895 | M26: =G26/$C$2-1 -> -0.017210515 | N26: =H26/$C$2-1 -> 0.44038025 | O26: =I26/$C$2-1 -> 0.50546691 | P26: =J26/$C$2-1 -> 0.72120767 | R26: =CONCATENATE("Due to port asset additions at Keni 30MT, Jatadhar 30MT, Murbe 33MT and others") -> Due to port asset additions at Keni 30MT, Jatadhar 30MT, Murbe 33MT and others | S26: =+Assumptions!J193 -> 42.987265 | T26: =Assumptions!P1405+Assumptions!P1356+Assumptions!P1307+Assumptions!P1258+Assumptions!P1209+Assumptions!P1160+Assumptions!P1111+(Assumptions!P1062-Assumptions!J1062)+(Assumptions!P13-Assumptions!J13)-X26 -> 38.513595 | U26: =+S26+T26 -> 81.50086 | V26: =+(U26/S26)^(0.166666666666667)-1 -> 0.1125095 | X26: 3
R27: Total JSW Cargo Volumes | S27: =+S22+S24+S26 -> 107.46816 | T27: =+T22+T24+T26 -> 100.01435 | U27: =+U22+U24+U26 -> 207.48251 | V27: =+(U27/S27)^(0.166666666666667)-1 -> 0.11587859
B28: EV/ EBITDA methodology
B29: Consolidated EBITDA | C29: Rs. mn | D29: =Consol!M23 -> 19645.6 | E29: =Consol!N23 -> 22621.8 | F29: =Consol!O23 -> 26037.3 | G29: =Consol!P23 -> 29530.876 | H29: =Consol!Q23 -> 47439.421 | I29: =Consol!R23 -> 57966.428 | J29: =Consol!S23 -> 75506.814
B30: =CONCATENATE("At CMP of Rs. ",ROUND($C$2,0),"/share") -> At CMP of Rs. 348/share | C30: implied EV/ EBITDA | D30: =($C$4-D15)/D$29 -> 41.290788 | E30: =($C$4+D15)/E$11 -> 35.920868 | F30: =($C$4+E15)/F$11 -> 31.956397 | G30: =($C$4+F15)/G$11 -> 28.877907 | H30: =($C$4+G15)/H$11 -> 17.683636 | I30: =($C$4+H15)/I$11 -> 15.506877 | J30: =($C$4+I15)/J$11 -> 12.469613
A31: 10 | B31: =CONCATENATE("-Target Price @",ROUND(A31,0),"x EV/EBITDA") -> -Target Price @10x EV/EBITDA | C31: Rs./ share | D31: =((D$29*$A31)-(Consol!L$78-Consol!L$105-Consol!L$102))/$C$3 -> 74.412172 | E31: =((E$29*$A31)-(D$15))/$C$3 -> 96.78618 | F31: =((F$29*$A31)-(E$15))/$C$3 -> 103.0915 | G31: =((G$29*$A31)-(F$15))/$C$3 -> 109.18771 | H31: =((H$29*$A31)-(G$15))/$C$3 -> 192.00913 | I31: =((I$29*$A31)-(H$15))/$C$3 -> 211.44829 | J31: =((J$29*$A31)-(I$15))/$C$3 -> 268.41885 | K31: =E31/$C$2-1 -> -0.72223797 | L31: =F31/$C$2-1 -> -0.70414263 | M31: =G31/$C$2-1 -> -0.68664741 | N31: =H31/$C$2-1 -> -0.44896217 | O31: =I31/$C$2-1 -> -0.39317465 | P31: =J31/$C$2-1 -> -0.22967757
A32: 12 | B32: =CONCATENATE("-Target Price @",ROUND(A32,0),"x EV/EBITDA") -> -Target Price @12x EV/EBITDA | C32: Rs./ share | D32: =((D$29*$A32)-(Consol!L$78-Consol!L$105-Consol!L$102))/$C$3 -> 91.275348 | E32: =((E$29*$A32)-(D$15))/$C$3 -> 116.20403 | F32: =((F$29*$A32)-(E$15))/$C$3 -> 125.44112 | G32: =((G$29*$A32)-(F$15))/$C$3 -> 134.5361 | H32: =((H$29*$A32)-(G$15))/$C$3 -> 232.72966 | I32: =((I$29*$A32)-(H$15))/$C$3 -> 261.20488 | J32: =((J$29*$A32)-(I$15))/$C$3 -> 333.23157 | K32: =E32/$C$2-1 -> -0.6665116 | L32: =F32/$C$2-1 -> -0.64000254 | M32: =G32/$C$2-1 -> -0.61390127 | N32: =H32/$C$2-1 -> -0.33210026 | O32: =I32/$C$2-1 -> -0.25038059 | P32: =J32/$C$2-1 -> -0.043674658
A33: 15 | B33: =CONCATENATE("-Target Price @",ROUND(A33,0),"x EV/EBITDA") -> -Target Price @15x EV/EBITDA | C33: Rs./ share | D33: =((D$29*$A33)-(Consol!L$78-Consol!L$105-Consol!L$102))/$C$3 -> 116.57011 | E33: =((E$29*$A33)-(D$15))/$C$3 -> 145.33082 | F33: =((F$29*$A33)-(E$15))/$C$3 -> 158.96554 | G33: =((G$29*$A33)-(F$15))/$C$3 -> 172.55869 | H33: =((H$29*$A33)-(G$15))/$C$3 -> 293.81046 | I33: =((I$29*$A33)-(H$15))/$C$3 -> 335.83977 | J33: =((J$29*$A33)-(I$15))/$C$3 -> 430.45064 | K33: =E33/$C$2-1 -> -0.58292204 | L33: =F33/$C$2-1 -> -0.5437924 | M33: =G33/$C$2-1 -> -0.50478207 | N33: =H33/$C$2-1 -> -0.15680739 | O33: =I33/$C$2-1 -> -0.036189503 | P33: =J33/$C$2-1 -> 0.23532972
A34: 18 | B34: =CONCATENATE("-Target Price @",ROUND(A34,0),"x EV/EBITDA") -> -Target Price @18x EV/EBITDA | C34: Rs./ share | D34: =((D$29*$A34)-(Consol!L$78-Consol!L$105-Consol!L$102))/$C$3 -> 141.86488 | E34: =((E$29*$A34)-(D$15))/$C$3 -> 174.4576 | F34: =((F$29*$A34)-(E$15))/$C$3 -> 192.48996 | G34: =((G$29*$A34)-(F$15))/$C$3 -> 210.58128 | H34: =((H$29*$A34)-(G$15))/$C$3 -> 354.89126 | I34: =((I$29*$A34)-(H$15))/$C$3 -> 410.47465 | J34: =((J$29*$A34)-(I$15))/$C$3 -> 527.66971 | K34: =E34/$C$2-1 -> -0.49933248 | L34: =F34/$C$2-1 -> -0.44758227 | M34: =G34/$C$2-1 -> -0.39566286 | N34: =H34/$C$2-1 -> 0.018485473 | O34: =I34/$C$2-1 -> 0.17800159 | P34: =J34/$C$2-1 -> 0.51433409
A35: 30 | B35: =CONCATENATE("-Target Price @",ROUND(A35,0),"x EV/EBITDA") -> -Target Price @30x EV/EBITDA | C35: Rs./ share | D35: =((D$29*$A35)-(Consol!L$78-Consol!L$105-Consol!L$102))/$C$3 -> 243.04393 | E35: =((E$29*$A35)-(D$15))/$C$3 -> 290.96472 | F35: =((F$29*$A35)-(E$15))/$C$3 -> 326.58764 | G35: =((G$29*$A35)-(F$15))/$C$3 -> 362.67163 | H35: =((H$29*$A35)-(G$15))/$C$3 -> 599.21446 | I35: =((I$29*$A35)-(H$15))/$C$3 -> 709.0142 | J35: =((J$29*$A35)-(I$15))/$C$3 -> 916.54601 | K35: =E35/$C$2-1 -> -0.16497425 | L35: =F35/$C$2-1 -> -0.062741743 | M35: =G35/$C$2-1 -> 0.040813969 | N35: =H35/$C$2-1 -> 0.71965694 | O35: =I35/$C$2-1 -> 1.034766 | P35: =J35/$C$2-1 -> 1.6303516
J36: =J33/(1.12)^3 -> 306.38626 | K36: << Discount it till end of FY26E till 3Q and FY27 from 4Q | N36: =H36/$C$2-1 -> -1 | O36: =I36/$C$2-1 -> -1
B37: DCF
B38: Rs. mn | D38: FY24 | E38: FY25 | F38: FY26E | G38: FY27E | H38: FY28E | I38: FY29E | J38: FY30E | R38: =13/12-1 -> 0.083333333
B40: Net Income | D40: =Consol!M49 -> 11559.1 | E40: =Consol!N49 -> 15030.8 | F40: =Consol!O49 -> 15233.1 | G40: =Consol!P49 -> 15958.31 | H40: =Consol!Q49 -> 23388.563 | I40: =Consol!R49 -> 24445.425 | J40: =Consol!S49 -> 27948.574
B41: Add: Depreciation | D41: =Consol!M28 -> 4364.8 | E41: =Consol!N28 -> 5465.5 | F41: =Consol!O28 -> 6141.2 | G41: =Consol!P28 -> 7453.8825 | H41: =Consol!Q28 -> 12460.684 | I41: =Consol!R28 -> 18408.265 | J41: =Consol!S28 -> 24495.596
B42: Less: Working Capital changes | D42: =Consol!M188 -> 1141 | E42: =Consol!N188 -> -41 | F42: =Consol!O188 -> 3204 | G42: =Consol!P188 -> 2463.1221 | H42: =Consol!Q188 -> 4555.9387 | I42: =Consol!R188 -> 2175.5683 | J42: =Consol!S188 -> 3358.4533
B43: Less: CAPEX | D43: =Consol!M190 -> 2487.1 | E43: =Consol!N190 -> 20755.7 | F43: =Consol!O190 -> 24916.4 | G43: =Consol!P190 -> 72388.517 | H43: =Consol!Q190 -> 89062.125 | I43: =Consol!R190 -> 81166.634 | J43: =Consol!S190 -> 67266.454
B44: Add: Net Borrowing | D44: =Consol!M182 -> 13.7 | E44: =Consol!N182 -> -714.3 | F44: =Consol!O182 -> 7300.6 | G44: =Consol!P182 -> 39159.391 | H44: =Consol!Q182 -> 29900.789 | I44: =Consol!R182 -> 3906.4587 | J44: =Consol!S182 -> 16489.433
B45: FCFE | D45: =D40+D41-D42-D43+D44 -> 12309.5 | E45: =E40+E41-E42-E43+E44 -> -932.7 | F45: =F40+F41-F42-F43+F44 -> 554.5 | G45: =G40+G41-G42-G43+G44 -> -12280.055 | H45: =H40+H41-H42-H43+H44 -> -27868.028 | I45: =I40+I41-I42-I43+I44 -> -36582.053 | J45: =J40+J41-J42-J43+J44 -> -1691.3041
B47: Present Value of FCFE till FY30E | D47: =NPV($C$55,E45:$J45) -> -49880.133 | E47: =NPV($C$55,F45:$J45) -> -54553.96 | F47: =NPV($C$55,G45:$J45) -> -61240.325 | G47: =NPV($C$55,H45:$J45) -> -55843.682 | H47: =NPV($C$55,I45:$J45) -> -34252.484 | I47: =NPV($C$55,J45:$J45) -> -1520.4101 | J47: =NPV($C$55,$J45:J45) -> -1520.4101
B48: Terminal Value | D48: 0 | E48: 0 | F48: 0 | G48: 0 | H48: 0 | I48: 0 | J48: =J47*((1+$C$56)/($C$55-$C$56)) -> -38368.839
B49: PV of Terminal Value | D49: =NPV($C$55,E48:$J48) -> -20249.429 | E49: =NPV($C$55,F48:$J48) -> -22525.464 | F49: =NPV($C$55,G48:$J48) -> -25057.327 | G49: =NPV($C$55,H48:$J48) -> -27873.77 | H49: =NPV($C$55,I48:$J48) -> -31006.782 | I49: =NPV($C$55,J48:$J48) -> -34491.944 | J49: =NPV($C$55,$J48:J48) -> -34491.944
B50: Equity Value | D50: =D49+D47 -> -70129.562 | E50: =E49+E47 -> -77079.424 | F50: =F49+F47 -> -86297.651 | G50: =G49+G47 -> -83717.452 | H50: =H49+H47 -> -65259.266 | I50: =I49+I47 -> -36012.354 | J50: =J49+J47 -> -36012.354
B51: No. of shares (in mn) | D51: =$C$3 -> 2330 | E51: =$C$3 -> 2330 | F51: =$C$3 -> 2330 | G51: =$C$3 -> 2330 | H51: =$C$3 -> 2330 | I51: =$C$3 -> 2330 | J51: =$C$3 -> 2330
B52: Per Share Value | D52: =D50/D51 -> -30.098524 | E52: =E50/E51 -> -33.081298 | F52: =F50/F51 -> -37.037619 | G52: =G50/G51 -> -35.930237 | H52: =H50/H51 -> -28.008269 | I52: =I50/I51 -> -15.455946 | J52: =J50/J51 -> -15.455946
B53: Upside | D53: =D52/$C$2-1 -> -1.0863783 | E53: =E52/$C$2-1 -> -1.0949384 | F53: =F52/$C$2-1 -> -1.1062925 | G53: =G52/$C$2-1 -> -1.1031145 | H53: =H52/$C$2-1 -> -1.0803796 | I53: =I52/$C$2-1 -> -1.0443563 | J53: =J52/$C$2-1 -> -1.0443563
B55: Cost of Equity | C55: 0.1124 | D55: << From Bloom
B56: Terminal growth rate (%) | C56: 0.07 | K56: <<- past 10 years' volume growth of Non Major Ports in India
B57: Cost of Debt | C57: 0.0764 | D57: << From Bloom
B59: Implied EV/ EBITDA multiple
B60: Value at end of: | D60: FY25 | E60: FY26E | F60: FY27E
B61: Equity Value | D61: =E50 -> -77079.424 | E61: =F50 -> -86297.651 | F61: =G50 -> -83717.452
B62: Net Debt | D62: =D15 -> 706.2 | E62: =E15 -> 20169.8 | F62: =F15 -> 40901.4
B63: EV | D63: =D61+D62 -> -76373.224 | E63: =E61+E62 -> -66127.851 | F63: =F61+F62 -> -42816.052
B64: EBITDA | D64: =E11 -> 22621.8 | E64: =F11 -> 26037.3 | F64: =G11 -> 29530.876
B65: Multiple>> | D65: =D63/D64 -> -3.3760896 | E65: =E63/E64 -> -2.5397354 | F65: =F63/F64 -> -1.4498741
B67: To dilute | C67: 0.8361
C68: =-(75%-C67) -> 0.0861 | R68: =180/153-1 -> 0.17647059
B69: No of shares to dilute (mn) | C69: 230
B70: Fund raise at CMP (Rs. mn) | C70: =C69*D70 -> 66780.5 | D70: =290.35 -> 290.35
B72: Share capital | C72: =C69*2 -> 460
B73: Other Equity | C73: =C70-C72 -> 66320.5
B76: RoE - without minority | C76: FY22 | D76: FY23 | E76: FY24 | F76: FY25 | G76: FY26 | H76: FY27 | I76: FY28 | J76: FY29 | K76: FY30
