Workbook

Sheet README
A1: India residential rooftop solar: households added annually and current target
A2: Scheme: PM Surya Ghar: Muft Bijli Yojana (PMSG:MBY), Ministry of New & Renewable Energy (MNRE). Launched 13 Feb 2024, Cabinet approved 29 Feb 2024, outlay Rs 75,021 crore.
A3: Compiled 1 Oct 2026 from Parliament answers (Lok Sabha / Rajya Sabha), PIB press releases, MNRE, PRS and the scheme's National Portal. Every number carries its source and 'as on' date in the Timeline sheet.
A5: CURRENT TARGET (official, unchanged since Feb 2024): 1 crore (10 million) residential households with rooftop solar by FY 2026-27, i.e. by 31 March 2027. Reaffirmed in Lok Sabha Starred Q.59 answered 22 Jul 2026.
A6: Interim target stated by Minister Pralhad Joshi (PIB, 4 Jun 2026): 75 lakh households by December 2026. Annual target for FY 2025-26 (Rajya Sabha, 8 Dec 2025): 35 lakh households. MNRE Secretary (press, 15 Sep 2026): likely 85-90 lakh by March 2027, i.e. a shortfall vs 1 crore.
A8: HOW TO READ 'ANNUAL ADDITIONS': MNRE does not publish a financial-year-wise series of households added. It publishes cumulative figures with an 'as on' date. The Annual_Additions sheet derives yearly additions as the difference between the nearest official cumulative datapoints to each year-end. Yellow cells are derived/approximate; the anchor dates are shown so you can judge the gap to the actual year-end.
A9: TWO COUNTS: 'RTS systems installed' (one rooftop plant) vs 'households benefitted' (a group-housing-society plant counts many households). Official statements switch between the two; the 'target' is in households. Both are tracked here.
A10: PRE-SCHEME BASELINE: 7.94 lakh residential rooftop installations in the entire decade before Feb 2024 (MNRE, Aug 2026), i.e. roughly 7,000 per month (Minister Joshi, Jun 2026). PM Surya Ghar is now running at 3-5 lakh per month.
A12: Sheets: Annual_Additions | Timeline (all official datapoints) | Targets | Monthly_RunRate | State_wise_Dec2025 (Rajya Sabha annexure) | State_wise_Jan2026 (PRS from portal) | Pre_Scheme_Baseline | Sources
A13: Caveat on sourcing: pmsuryaghar.gov.in blocks automated access, so portal-dashboard figures (Aug 2026 rows) are taken as reported second-hand by JMK Research / Urban Acres and are marked 'portal via secondary'. Everything else is from a primary government document.

Sheet Timeline
A1: As on date | B1: RTS systems installed (nos.) | C1: Households benefitted (nos.) | D1: Applications received (nos.) | E1: Capacity installed (MW) | F1: CFA / subsidy released (Rs crore) | G1: Zero-bill households (nos.) | H1: Source type | I1: Who / document | J1: Source URL | K1: Notes
A2: 45335 | H2: PIB | I2: Scheme launch by PM; Cabinet approval 29 Feb 2024 (PIB 2010133) | J2: https://www.pib.gov.in/PressReleasePage.aspx?PRID=2010133 | K2: Target: 1 crore households; outlay Rs 75,021 cr; 30 GW residential rooftop
A3: 45626 | B3: 400000 | F3: 3100 | H3: PIB | I3: PIB 2080833, 5 Dec 2024 (subsidy disbursed to >4 lakh consumers by Nov 2024) | J3: https://www.pib.gov.in/PressReleasePage.aspx?PRID=2080833 | K3: Column B here = consumers who received subsidy, not installations
A4: 45629 | B4: 630000 | D4: 2638000 | H4: PIB | I4: PIB 2080833 / 2081250, 5 Dec 2024: 6.3 lakh installations in 9 months, avg 70,000/month; 1.45 crore registrations | J4: https://www.pib.gov.in/PressReleasePage.aspx?PRID=2081250 | K4: Roadmap stated: 10 lakh by Mar 2025, 20 lakh by Oct 2025, 40 lakh by Mar 2026, 1 crore by Mar 2027
A5: 45726 | B5: 1009000 | D5: 4730000 | E5: 3000 | F5: 4770 | H5: PIB | I5: PIB 2110283, 13 Mar 2025: 10.09 lakh installations; 6.13 lakh subsidies paid; >3 GW | J5: https://www.pib.gov.in/PressReleasePage.aspx?PRID=2110283 | K5: Closest official datapoint to FY2024-25 year-end
A6: 45923 | C6: 2000000 | H6: Press (MNRE Secretary) | I6: Tribune, 23 Sep 2025: ~20 lakh households covered; 15-20 lakh to be added in FY26, 30-40 lakh next year | J6: https://www.tribuneindia.com/news/business/mnre-secretary-hopeful-of-achieving-one-crore-rooftop-solar-installations-under-pm-suryaghar-in-quick-time/amp | K6: Rounded figure
A7: 45994 | B7: 1917698 | C7: 2396497 | D7: 5354099 | H7: Rajya Sabha / PIB | I7: PIB 2200441, MoS Shripad Naik, RS written reply 8 Dec 2025; 23.96% of target; FY26 target 35 lakh households | J7: https://www.pib.gov.in/PressReleasePage.aspx?PRID=2200441
A8: 46000 | B8: 1945758 | C8: 2435196 | E8: 7075.78 | F8: 13926.25 | G8: 771580 | H8: Rajya Sabha / PIB | I8: PIB 2204466, MoS Naik, RS written reply 16 Dec 2025, state-wise annexure; 7,075.78 MW per AIR 9 Dec 2025 | J8: https://www.pib.gov.in/PressReleasePage.aspx?PRID=2204466 | K8: Full state-wise table in State_wise_Dec2025 sheet
A9: 46022 | B9: 2085514 | C9: 2614446 | F9: 14771.82 | H9: Rajya Sabha | I9: MoS Naik, RS written reply, Feb 2026 (reported SolarQuarter 4 Feb 2026) | J9: https://solarquarter.com/2026/02/04/india-expands-distributed-solar-footprint-under-pm-surya-ghar-with-20-85-lakh-installations-and-26-lakh-beneficiaries/ | K9: Calendar-year 2025 end anchor
A10: 46032 | B10: 2143149 | C10: 2684400 | D10: 5561902 | H10: National Portal via PRS | I10: PRS Demand for Grants 2026-27 analysis, Table 7 (portal data as on 10 Jan 2026) | J10: https://prsindia.org/files/budget/budget_parliament/2026/DfG_Analysis_2026-27-Power.pdf | K10: State-wise in State_wise_Jan2026 sheet
A11: 46086 | B11: 2502217 | H11: Rajya Sabha | I11: MoS Power, RS reply, Mar 2026 | J11: https://www.socialnews.xyz/2026/03/10/over-25-lakh-rooftop-solar-systems-installed-under-pm-surya-ghar-yojana
A12: 46097 | B12: 2587685 | C12: 3202697 | H12: Lok Sabha | I12: Minister Pralhad Joshi, LS reply 18 Mar 2026 (Down To Earth 'As told to Parliament') | J12: https://www.downtoearth.org.in/governance/as-told-to-parliament-march-18-2026-surya-ghar-yojana-benefitting-3202697-households-says-centre
A13: 46100 | B13: 2619879 | C13: 3240000 | E13: 9560 | F13: 17967.53 | H13: Parliament / PIB | I13: MoS Naik reply 24-25 Mar 2026: 26,19,879 systems, 9.56 GW, 32.4 lakh households, CFA Rs 17,967.53 cr | J13: https://solarquarter.com/2026/03/25/pm-surya-ghar-yojana-updates-2026-26-lakh-rooftop-solar-installations-across-india-with-%E2%82%B917967-crore-central-financial-assistance/ | K13: Closest official datapoint to FY2025-26 year-end
A14: 46173 | B14: 3300000 | C14: 4000000 | D14: 6500000 | E14: 12000 | F14: 22750 | G14: 1700000 | H14: PIB | I14: PIB 2268992, 4 Jun 2026: >33 lakh systems, >40 lakh households, >12 GW, Rs 22,750 cr; May 2026 record 3.16 lakh installations; 75 lakh target by Dec 2026 | J14: https://www.pib.gov.in/PressReleasePage.aspx?PRID=2268992 | K14: Rounded ('more than')
A15: 46223 | B15: 3938805 | C15: 4747341 | D15: 7647000 | E15: 14070 | F15: 27323.55 | G15: 1893000 | H15: Lok Sabha | I15: LS Unstarred Q.580 answered 22 Jul 2026 (MoS Naik) + LS reply reported Energetica 24 Jul 2026 | J15: https://sansad.in/getFile/lsapps/loksabhaquestions/annex/188/AU580_5TGlZa.pdf | K15: LS Starred Q.59 same day reaffirms 1 crore by FY2026-27; Tamil Nadu district-wise annexure
A16: 46225 | B16: 3972447 | C16: 4802717 | G16: 1890000 | H16: Rajya Sabha | I16: MoS Naik, RS written reply 29 Jul 2026 (SolarQuarter) | J16: https://solarquarter.com/2026/07/29/pm-surya-ghar-scheme-nears-4-million-rooftop-solar-installations-over-1-89-million-households-report-zero-power-bills/ | K16: Budget spend: FY25 Rs 7,822.92 cr; FY26 Rs 16,166.23 cr; FY27 BE Rs 22,000 cr (Rs 10,392 cr spent to 22 Jul 2026)
A17: 46234 | C17: 5006000 | E17: 14800 | F17: 28024 | G17: 1900000 | H17: MNRE / PIB | I17: MNRE release 4 Aug 2026 (DD India / pv magazine): 50.06 lakh households; July 2026 record 5.06 lakh; 14.8 GW; vs 7.94 lakh in prior decade | J17: https://ddindia.co.in/2026/08/pm-surya-ghar-scheme-crosses-50-lakh-rooftop-solar-installations/ | K17: Households, not systems
A18: 46244 | B18: 4190000 | C18: 5040000 | D18: 7770000 | E18: 14894.95 | F18: 28390.5 | H18: Rajya Sabha | I18: MoS Naik, RS reply ~11 Aug 2026 (Hans India): 41.9 lakh systems, 50.4 lakh households, 14,894.95 MW, Rs 28,390.50 cr | J18: https://www.thehansindia.com/amp/business/pm-surya-ghar-scheme-receives-777-million-applications-installs-419-million-solar-systems-1108246 | K18: Latest Parliament datapoint; FY2026-27 YTD anchor (official)
A19: 46265 | B19: 4644000 | C19: 5528000 | D19: 8062000 | E19: 16369 | F19: 30885 | H19: Portal via secondary | I19: PMSG:MBY portal data compiled by JMK Research, reported Urban Acres 5 Sep 2026: 46.44 lakh installations, 55.28 lakh households, 16,369 MW; alt snapshot 54,65,417 hh / 16,185.48 MW | J19: https://urbanacres.in/pm-surya-ghars-rooftop-solar-push-reveals-a-scale-up-gap/ | K19: NOT a primary government document; portal blocks automated access so could not be verified directly

Sheet Annual_Additions
A1: Period | B1: Anchor date used (end of period) | C1: Cumulative RTS systems at anchor | D1: Cumulative households at anchor | E1: Systems added in period | F1: Households added in period | G1: Official target for the period (households) | H1: Achievement vs target | I1: Basis / caveat
A2: Pre-scheme decade (2014 to Feb 2024) | C2: 794000 | E2: 794000 | I2: MNRE, Aug 2026: 7.94 lakh residential rooftop installations in the decade before the scheme (~80,000/yr; ~7,000/month per Minister Joshi, Jun 2026)
A3: FY 2023-24 (13 Feb - 31 Mar 2024) | B3: 45382 | I3: Negligible; scheme launched 13 Feb 2024, subsidy disbursal only began Jun 2024 after elections. No official figure published.
A4: FY 2024-25 | B4: =Timeline!A5 | C4: =Timeline!B5 | E4: =C4 | I4: Anchor = 10 Mar 2025 (10.09 lakh systems). True 31 Mar 2025 figure not published; at the then run-rate (~1 lakh/month) FY25 close is ~10.7-11 lakh systems.
A5: FY 2025-26 | B5: =Timeline!A13 | C5: =Timeline!B13 | D5: =Timeline!C13 | E5: =C5-C4 | G5: 3500000 | H5: =E5/G5 | I5: Achievement = systems added / household target (slightly understates, since households > systems). Anchor = 19 Mar 2026 (26,19,879 systems / 32.4 lakh households). Target 35 lakh households for FY26 (RS, 8 Dec 2025). Households added in FY26 ~ 19-20 lakh if FY25-end households were ~13 lakh (not published).
A6: FY 2026-27 YTD (Apr - ~10 Aug 2026), official | B6: =Timeline!A18 | C6: =Timeline!B18 | D6: =Timeline!C18 | E6: =C6-C5 | F6: =D6-D5 | I6: Anchor = Rajya Sabha reply ~10 Aug 2026 (41.9 lakh systems / 50.4 lakh households). About 4.5 months of FY27.
A7: FY 2026-27 YTD (Apr - Aug 2026), portal | B7: =Timeline!A19 | C7: =Timeline!B19 | D7: =Timeline!C19 | E7: =C7-C5 | F7: =D7-D5 | I7: Anchor = portal snapshot end-Aug 2026 via JMK/Urban Acres (46.44 lakh systems / 55.28 lakh households). Secondary source.
A8: Calendar 2024 (13 Feb - 3 Dec 2024) | B8: =Timeline!A4 | C8: =Timeline!B4 | E8: =C8 | I8: PIB 5 Dec 2024: 6.3 lakh installations in first 9 months. CY2024 close likely ~7 lakh.
A9: Calendar 2025 | B9: =Timeline!A9 | C9: =Timeline!B9 | D9: =Timeline!C9 | E9: =C9-C8 | I9: 31 Dec 2025 official: 20,85,514 systems / 26,14,446 households (RS reply). Households added in CY2025 ~ 18-19 lakh (CY2024-end households not published).
A10: Calendar 2026 YTD (Jan - ~10 Aug 2026), official | B10: =Timeline!A18 | C10: =Timeline!B18 | D10: =Timeline!C18 | E10: =C10-C9 | F10: =D10-D9 | G10: 7500000 | H10: =D10/G10 | I10: Target column = Minister's stated 75 lakh households by Dec 2026 (PIB 4 Jun 2026); achievement = cumulative households at anchor / 75 lakh. Households added Jan-Aug 2026 ~ 24 lakh.
A11: Cumulative since launch to ~10 Aug 2026 | B11: =Timeline!A18 | C11: =Timeline!B18 | D11: =Timeline!C18 | G11: 10000000 | H11: =D11/G11 | I11: Scheme target: 1 crore households by FY 2026-27 (31 Mar 2027). ~50% reached with ~7.5 months left; MNRE Secretary (15 Sep 2026) expects 85-90 lakh by Mar 2027.
A13: Yellow = derived by subtraction between nearest official cumulative datapoints; anchors are not exact year-ends. Formulas link to the Timeline sheet.

Sheet Targets
A1: Target / milestone | B1: Value | C1: Deadline | D1: Set by / stated in | E1: Date stated | F1: Status as of Sep 2026 | G1: Source URL
A2: Scheme target (households) | B2: 1 crore (10,000,000) households | C2: FY 2026-27 (31 Mar 2027) | D2: Union Cabinet approval; reaffirmed LS Starred Q.59, 22 Jul 2026 | E2: 45351 | F2: ~50.4 lakh households by ~10 Aug 2026 (official); 55.28 lakh end-Aug (portal). MNRE Secretary (15 Sep 2026): 85-90 lakh likely by Mar 2027. | G2: https://www.pib.gov.in/PressReleasePage.aspx?PRID=2010133
A3: Scheme target (capacity) | B3: 30 GW residential rooftop | C3: Mar 2027 | D3: Cabinet approval; PIB 10-lakh release said '27 GW more by Mar 2027' | E3: 45351 | F3: 14,894.95 MW by Aug 2026 (RS); ~16.4 GW end-Aug (portal). Roughly half. | G3: https://www.pib.gov.in/PressReleasePage.aspx?PRID=2110283
A4: Financial outlay | B4: Rs 75,021 crore | C4: FY 2026-27 | D4: Cabinet | E4: 45351 | F4: Rs 28,390.50 cr CFA released to Aug 2026 (RS). Budget: FY25 actual 7,822.92 cr; FY26 actual 16,166.23 cr (BE 20,000); FY27 BE 22,000 cr. | G4: https://www.pib.gov.in/PressReleasePage.aspx?PRID=2010133
A5: Interim roadmap (PIB, Dec 2024) | B5: 10 lakh by Mar 2025; 20 lakh by Oct 2025; 40 lakh by Mar 2026; 1 crore by Mar 2027 | C5: see value | D5: PIB 2080833 / 2081250 | E5: 45631 | F5: 10 lakh: met (10 Mar 2025). 20 lakh by Oct 2025: ~20 lakh households by Sep 2025 (met on households, not systems). 40 lakh by Mar 2026: MISSED (26.2 lakh systems / 32.4 lakh households). | G5: https://www.pib.gov.in/PressReleasePage.aspx?PRID=2081250
A6: Annual target FY 2025-26 | B6: 35 lakh households | C6: 31 Mar 2026 | D6: MoS Shripad Naik, Rajya Sabha written reply | E6: 45999 | F6: MISSED: ~16 lakh systems / ~19-20 lakh households added in FY26 (derived). | G6: https://www.pib.gov.in/PressReleasePage.aspx?PRID=2200441
A7: MNRE Secretary projection FY26 / FY27 | B7: 15-20 lakh added in FY 2025-26; 30-40 lakh in FY 2026-27 | C7: Mar 2027 | D7: Secretary Santosh Kumar Sarangi (press) | E7: 45923 | F7: FY26 landed inside the 15-20 lakh range. FY27 pace (Apr-Aug ~18-21 lakh households in 5 months) is ahead of the 30-40 lakh projection. | G7: https://www.tribuneindia.com/news/business/mnre-secretary-hopeful-of-achieving-one-crore-rooftop-solar-installations-under-pm-suryaghar-in-quick-time/amp
A8: Interim target (Minister) | B8: 75 lakh households | C8: Dec 2026 | D8: Minister Pralhad Joshi, 'Two years of PM Surya Ghar' event, PIB 2268992 | E8: 46177 | F8: Needs ~20-25 lakh more households in Sep-Dec 2026, i.e. ~5-6 lakh/month vs July 2026 record 5.06 lakh. Achievable only if the July pace holds. | G8: https://www.pib.gov.in/PressReleasePage.aspx?PRID=2268992
A9: Secretary's revised expectation | B9: 85-90 lakh households | C9: Mar 2027 | D9: MNRE Secretary Sarangi (press) | E9: 46280 | F9: Implicit admission that 1 crore by Mar 2027 is unlikely. No official revision of the 1 crore target or of the 31 Mar 2027 scheme end has been notified. | G9: https://www.energetica-india.net/news/pm-surya-ghar-scheme-crosses-50-lakh-rooftop-solar-installations-14-8-gw-capacity-commissioned
A10: Utility-Led Aggregation (ULA) pipeline | B10: ~30 lakh installations planned via DISCOMs | C10: n/a | D10: Minister Joshi, PIB 2268992 | E10: 46177 | F10: Pipeline, not achievement. | G10: https://www.pib.gov.in/PressReleasePage.aspx?PRID=2268992

Sheet Monthly_RunRate
A1: Period | B1: Installations / households per month | C1: Per day | D1: Capacity added in month (MW) | E1: Source
A2: Pre-scheme (before Feb 2024) | B2: 7000 | E2: Minister Joshi, PIB 2268992 (4 Jun 2026): 'about 7,000 per month before the scheme'
A3: Feb-Nov 2024 average | B3: 70000 | E3: PIB 2080833 (5 Dec 2024): 6.3 lakh in 9 months, ~70,000/month
A4: Oct 2025 | C4: 5038 | E4: MNRE release 4 Aug 2026: 5,038 installations per day
A5: Mar 2026 (5-19 Mar) | B5: 252000 | E5: Derived: 25,02,217 (5 Mar) to 26,19,879 (19 Mar) = 1.18 lakh in 14 days
A6: May 2026 | B6: 316000 | C6: 15000 | E6: PIB 2268992: record 3.16 lakh installations; 15,000 in one day
A7: Jul 2026 | B7: 506000 | C7: 16328 | D7: 1592 | E7: MNRE release 4 Aug 2026 (households); JMK/Urban Acres for MW
A8: Aug 2026 | D8: 1407 | E8: JMK/Urban Acres (portal): ~1,407 MW, 11.6% below July

Sheet State_wise_Dec2025
A1: S No. | B1: State/UT | C1: RTS installations (nos.) | D1: Households benefitted (nos.) | E1: Consumers with zero energy charges (nos.) | F1: CFA disbursed (nos.) | G1: CFA amount (Rs crore) | H1: Loan applications sanctioned (nos.)
A2: 1 | B2: Andhra Pradesh | C2: 76617 | D2: 79210 | E2: 36381 | F2: 66070 | G2: 511.11 | H2: 61607
A3: 2 | B3: Arunachal Pradesh | C3: 1 | D3: 1 | E3: 0 | F3: 1 | G3: 0.01 | H3: 74
A4: 3 | B4: Assam | C4: 63887 | D4: 64525 | E4: 4973 | F4: 51894 | G4: 442.26 | H4: 69883
A5: 4 | B5: Bihar | C5: 13649 | D5: 14096 | E5: 0 | F5: 12640 | G5: 97.5 | H5: 9204
A6: 5 | B6: Chhattisgarh | C6: 16498 | D6: 17847 | E6: 987 | F6: 10900 | G6: 84.42 | H6: 16121
A7: 6 | B7: Goa | C7: 1304 | D7: 1596 | E7: 798 | F7: 1110 | G7: 8.78 | H7: 264
A8: 7 | B8: Gujarat | C8: 493161 | D8: 710102 | E8: 362675 | F8: 474051 | G8: 3714.47 | H8: 42408
A9: 8 | B9: Haryana | C9: 44937 | D9: 50434 | E9: 1575 | F9: 41921 | G9: 310.16 | H9: 18717
A10: 9 | B10: Himachal Pradesh | C10: 5556 | D10: 5679 | E10: 502 | F10: 5018 | G10: 42.94 | H10: 2994
A11: 10 | B11: Jharkhand | C11: 1308 | D11: 1310 | E11: 357 | F11: 1146 | G11: 8.89 | H11: 997
A12: 11 | B12: Karnataka | C12: 14471 | D12: 22833 | E12: 245 | F12: 13456 | G12: 108.68 | H12: 4426
A13: 12 | B13: Kerala | C13: 169227 | D13: 174097 | E13: 117697 | F13: 155907 | G13: 1216.82 | H13: 76421
... A37: 36 | B37: DNH&DD | C37: 482 | D37: 482 | E37: 51 | F37: 453 | G37: 3.52 | H37: 128
B38: Total | C38: =SUM(C2:C37) | D38: =SUM(D2:D37) | E38: =SUM(E2:E37) | F38: =SUM(F2:F37) | G38: =SUM(G2:G37) | H38: =SUM(H2:H37)
A40: Source: Annexure to Rajya Sabha written reply by MoS Shripad Yesso Naik, 16 Dec 2025, as on 09.12.2025 (PIB Release ID 2204466). Official totals: 19,45,758 systems; 24,35,196 households; 7,71,580 zero-bill; Rs 13,926.25 cr CFA. https://www.pib.gov.in/PressReleasePage.aspx?PRID=2204466

Sheet State_wise_Jan2026
A1: State/UT | B1: Applications | C1: Installations (nos.) | D1: Installations as % of applications | E1: Households covered
A2: Andaman and Nicobar | B2: 654 | C2: 183 | D2: =IF(B2=0,0,C2/B2) | E2: 202
A3: Andhra Pradesh | B3: 1175634 | C3: 87984 | D3: =IF(B3=0,0,C3/B3) | E3: 90864
A4: Arunachal Pradesh | B4: 88 | C4: 1 | D4: =IF(B4=0,0,C4/B4) | E4: 1
A5: Assam | B5: 484444 | C5: 75177 | D5: =IF(B5=0,0,C5/B5) | E5: 75883
A6: Bihar | B6: 55543 | C6: 14500 | D6: =IF(B6=0,0,C6/B6) | E6: 15148
A7: Chandigarh | B7: 1510 | C7: 1001 | D7: =IF(B7=0,0,C7/B7) | E7: 1001
A8: Chhattisgarh | B8: 121687 | C8: 23404 | D8: =IF(B8=0,0,C8/B8) | E8: 24825
A9: Dadra & Nagar Haveli and Daman & Diu | B9: 1949 | C9: 496 | D9: =IF(B9=0,0,C9/B9) | E9: 496
A10: Delhi | B10: 17149 | C10: 5589 | D10: =IF(B10=0,0,C10/B10) | E10: 9471
A11: Goa | B11: 2687 | C11: 1461 | D11: =IF(B11=0,0,C11/B11) | E11: 1814
A12: Gujarat | B12: 617917 | C12: 524808 | D12: =IF(B12=0,0,C12/B12) | E12: 757016
A13: Haryana | B13: 104038 | C13: 49473 | D13: =IF(B13=0,0,C13/B13) | E13: 56562
... A37: West Bengal | B37: 12112 | C37: 1145 | D37: =IF(B37=0,0,C37/B37) | E37: 1208
A38: All-India | B38: =SUM(B2:B37) | C38: =SUM(C2:C37) | D38: =IF(B38=0,0,C38/B38) | E38: =SUM(E2:E37)
A40: Source: PRS Legislative Research, Demand for Grants 2026-27 Analysis: Power and New & Renewable Energy, Table 7 (PMSG:MBY National Portal, as on 10 Jan 2026). PRS totals: 55,61,902 applications; 21,43,149 installations; 26,84,400 households. https://prsindia.org/files/budget/budget_parliament/2026/DfG_Analysis_2026-27-Power.pdf

Sheet Pre_Scheme_Baseline
A1: Metric | B1: Value | C1: As on | D1: Source
A2: Residential rooftop installations in the decade before PM Surya Ghar | B2: 7.94 lakh (794,000) | C2: Feb 2024 | D2: MNRE release 4 Aug 2026 (DD India / pv magazine): '7.94 lakh in the preceding decade'
A3: Pre-scheme monthly installation rate | B3: ~7,000 per month | C3: 2023 | D3: Minister Pralhad Joshi, PIB 2268992, 4 Jun 2026
A4: Rooftop Solar Programme Phase-II residential target | B4: 4,000 MW residential capacity under CFA | C4: Launched 8 Mar 2019 | D4: PIB 1989806, 23 Dec 2023 (LS reply 21 Dec 2023)
A5: Phase-II residential capacity installed under subsidy | B5: 2,651.10 MW | C5: 30 Nov 2023 | D5: PIB 1989806 (state-wise table; Gujarat 1,956.85 MW of it)
A6: All-sector grid-connected rooftop capacity | B6: 1.8 GW (31 Mar 2019) -> 10.4 GW (30 Nov 2023), CAGR ~46% | C6: 30 Nov 2023 | D6: PIB 1989806
A7: All-sector grid-connected rooftop capacity | B7: 22.42 GW | C7: Oct 2025 | D7: PIB 2199729 (India's Solar Momentum)
A8: All-sector grid-connected rooftop capacity | B8: 32.59 GW | C8: 31 Aug 2026 | D8: MNRE Physical Progress page, https://mnre.gov.in/en/physical-progress/

Sheet Sources
A1: # | B1: Document | C1: Date | D1: Type | E1: URL
A2: 1 | B2: Cabinet approves PM-Surya Ghar for 1 crore households (PIB 2010133) | C2: 45351 | D2: PIB press release | E2: https://www.pib.gov.in/PressReleasePage.aspx?PRID=2010133
A3: 2 | B3: PMSGMBY set to surpass 10 lakh by Mar 2025 (PIB 2080833) | C3: 45631 | D3: PIB press release | E3: https://www.pib.gov.in/PressReleasePage.aspx?PRID=2080833
A4: 3 | B4: PM Surya Ghar backgrounder, roadmap to 1 crore (PIB 2081250) | C4: 45631 | D4: PIB backgrounder | E4: https://www.pib.gov.in/PressReleasePage.aspx?PRID=2081250
A5: 4 | B5: Crosses 10 lakh installations (PIB 2110283) | C5: 45729 | D5: PIB press release | E5: https://www.pib.gov.in/PressReleasePage.aspx?PRID=2110283
A6: 5 | B6: MNRE Secretary: 15-20 lakh in FY26, 30-40 lakh next year (Tribune) | C6: 45923 | D6: Press | E6: https://www.tribuneindia.com/news/business/mnre-secretary-hopeful-of-achieving-one-crore-rooftop-solar-installations-under-pm-suryaghar-in-quick-time/amp
A7: 6 | B7: 23.96 lakh households, 35 lakh FY26 target, RS reply (PIB 2200441) | C7: 45999 | D7: Rajya Sabha / PIB | E7: https://www.pib.gov.in/PressReleasePage.aspx?PRID=2200441
A8: 7 | B8: 7,075.78 MW installed under PMSG:MBY (AIR) | C8: 46000 | D8: Rajya Sabha / AIR | E8: https://www.newsonair.gov.in/7075-78-mw-rooftop-solar-installed-under-pm-surya-ghar-muft-bijli-yojana
A9: 8 | B9: Zero bills to 7.7 lakh households, state-wise annexure as on 9 Dec 2025 (PIB 2204466) | C9: 46007 | D9: Rajya Sabha / PIB | E9: https://www.pib.gov.in/PressReleasePage.aspx?PRID=2204466
A10: 9 | B10: India's Solar Momentum: 23.9 lakh households, 7 GW (PIB 2199729) | C10: 46011 | D10: PIB backgrounder | E10: https://www.pib.gov.in/PressReleasePage.aspx?PRID=2199729
A11: 10 | B11: RS reply: 20,85,514 systems / 26,14,446 households as on 31 Dec 2025 (SolarQuarter) | C11: 46057 | D11: Rajya Sabha via press | E11: https://solarquarter.com/2026/02/04/india-expands-distributed-solar-footprint-under-pm-surya-ghar-with-20-85-lakh-installations-and-26-lakh-beneficiaries/
A12: 11 | B12: PRS Demand for Grants 2026-27 analysis, Power & MNRE (Table 7 state-wise, 10 Jan 2026) | C12: 46063 | D12: PRS | E12: https://prsindia.org/files/budget/budget_parliament/2026/DfG_Analysis_2026-27-Power.pdf
A13: 12 | B13: LS reply: 25,87,685 systems / 32,02,697 households as on 16 Mar 2026 (Down To Earth) | C13: 46099 | D13: Lok Sabha via press | E13: https://www.downtoearth.org.in/governance/as-told-to-parliament-march-18-2026-surya-ghar-yojana-benefitting-3202697-households-says-centre
... A26: 25 | B26: Rooftop Solar Programme Phase-II, pre-scheme state-wise capacity (PIB 1989806) | C26: 45283 | D26: PIB press release | E26: https://www.pib.gov.in/PressReleasePage.aspx?PRID=1989806
