Workbook

Sheet Time Series
A1: ULTRATECH CEMENT — ELECTRICITY COST TIME SERIES
A2: FY2005 to FY2026. Standalone UltraTech Cement Limited. All rupee figures in Rs. billion. Black cells are formulas driven by the Workings tab.
A3: FY15-FY23 cannot be computed: Form A was withdrawn from the statutory format in 2014 and the investor decks reported a combined energy cost until FY24. See Notes.
A5: Particulars | B5: FY05 | C5: FY06 | D5: FY07 | E5: FY08 | F5: FY09 | G5: FY10 | H5: FY11 | I5: FY12 | J5: FY13 | K5: FY14 | L5: FY15 | M5: FY16 | N5: FY17 | O5: FY18 | P5: FY19 | Q5: FY20 | R5: FY21 | S5: FY22 | T5: FY23 | U5: FY24 | V5: FY25 | W5: FY26
A6: Electricity cost (Rs. bn) | B6: =(Workings!B6*Workings!C6+Workings!D6*Workings!E6+Workings!F6*Workings!G6+Workings!H6*Workings!I6+Workings!J6*Workings!K6+Workings!L6*Workings!M6+Workings!N6*Workings!O6)*1000/1000000000 -> 4.1138545 | C6: =(Workings!B7*Workings!C7+Workings!D7*Workings!E7+Workings!F7*Workings!G7+Workings!H7*Workings!I7+Workings!J7*Workings!K7+Workings!L7*Workings!M7+Workings!N7*Workings!O7)*1000/1000000000 -> 4.9064243 | D6: =(Workings!B8*Workings!C8+Workings!D8*Workings!E8+Workings!F8*Workings!G8+Workings!H8*Workings!I8+Workings!J8*Workings!K8+Workings!L8*Workings!M8+Workings!N8*Workings!O8)*1000/1000000000 -> 5.8964173 | E6: =(Workings!B9*Workings!C9+Workings!D9*Workings!E9+Workings!F9*Workings!G9+Workings!H9*Workings!I9+Workings!J9*Workings!K9+Workings!L9*Workings!M9+Workings!N9*Workings!O9)*1000/1000000000 -> 5.9630981 | F6: =(Workings!B10*Workings!C10+Workings!D10*Workings!E10+Workings!F10*Workings!G10+Workings!H10*Workings!I10+Workings!J10*Workings!K10+Workings!L10*Workings!M10+Workings!N10*Workings!O10)*1000/1000000000 -> 6.7721666 | G6: =(Workings!B11*Workings!C11+Workings!D11*Workings!E11+Workings!F11*Workings!G11+Workings!H11*Workings!I11+Workings!J11*Workings!K11+Workings!L11*Workings!M11+Workings!N11*Workings!O11)*1000/1000000000 -> 6.0098523 | H6: =(Workings!B12*Workings!C12+Workings!D12*Workings!E12+Workings!F12*Workings!G12+Workings!H12*Workings!I12+Workings!J12*Workings!K12+Workings!L12*Workings!M12+Workings!N12*Workings!O12)*1000/1000000000 -> 11.914671 | I6: =(Workings!B13*Workings!C13+Workings!D13*Workings!E13+Workings!F13*Workings!G13+Workings!H13*Workings!I13+Workings!J13*Workings!K13+Workings!L13*Workings!M13+Workings!N13*Workings!O13)*1000/1000000000 -> 15.352198 | J6: =(Workings!B14*Workings!C14+Workings!D14*Workings!E14+Workings!F14*Workings!G14+Workings!H14*Workings!I14+Workings!J14*Workings!K14+Workings!L14*Workings!M14+Workings!N14*Workings!O14)*1000/1000000000 -> 16.279181 | K6: =(Workings!B15*Workings!C15+Workings!D15*Workings!E15+Workings!F15*Workings!G15+Workings!H15*Workings!I15+Workings!J15*Workings!K15+Workings!L15*Workings!M15+Workings!N15*Workings!O15)*1000/1000000000 -> 15.423102 | L6: n/a | M6: n/a | N6: n/a | O6: n/a | P6: n/a | Q6: n/a | R6: n/a | S6: n/a | T6: n/a | U6: =SUMPRODUCT(Workings!B19:E19,Workings!F19:I19)/1000 -> 46.48844 | V6: =SUMPRODUCT(Workings!B20:E20,Workings!F20:I20)/1000 -> 48.50814 | W6: =SUMPRODUCT(Workings!B21:E21,Workings!F21:I21)/1000 -> 48.77095
A7: Revenue (Rs. bn) | B7: =Workings!P6/100 -> 26.069 | C7: =Workings!P7/100 -> 32.9945 | D7: =Workings!P8/100 -> 49.1052 | E7: =Workings!P9/100 -> 55.0922 | F7: =Workings!P10/100 -> 63.83 | G7: =Workings!P11/100 -> 70.5 | H7: =Workings!P12/100 -> 132.06 | I7: =Workings!P13/100 -> 181.58 | J7: =Workings!P14/100 -> 200.23 | K7: =Workings!P15/100 -> 200.78 | L7: n/a | M7: n/a | N7: n/a | O7: n/a | P7: n/a | Q7: n/a | R7: n/a | S7: n/a | T7: n/a | U7: =Workings!K19/100 -> 598.24 | V7: =Workings!K20/100 -> 622.05 | W7: =Workings!K21/100 -> 706.66
A8: Electricity as % of revenue | B8: =B6/B7 -> 0.15780638 | C8: =C6/C7 -> 0.14870431 | D8: =D6/D7 -> 0.12007725 | E8: =E6/E7 -> 0.10823852 | F8: =F6/F7 -> 0.10609692 | G8: =G6/G7 -> 0.085246132 | H8: =H6/H7 -> 0.090221647 | I8: =I6/I7 -> 0.084547846 | ... K8: =K6/K7 -> 0.076815927 | L8: n/a | M8: n/a | N8: n/a | O8: n/a | P8: n/a | Q8: n/a | R8: n/a | S8: n/a | T8: n/a | U8: =U6/U7 -> 0.077708679 | V8: =V6/V7 -> 0.077981095 | W8: =W6/W7 -> 0.069016146
A9: Units consumed (mn kWh) | B9: =(Workings!B6+Workings!D6+Workings!F6+Workings!H6+Workings!J6+Workings!L6+Workings!N6)/1000 -> 1205.377 | C9: =(Workings!B7+Workings!D7+Workings!F7+Workings!H7+Workings!J7+Workings!L7+Workings!N7)/1000 -> 1277.06 | D9: =(Workings!B8+Workings!D8+Workings!F8+Workings!H8+Workings!J8+Workings!L8+Workings!N8)/1000 -> 1410.787 | E9: =(Workings!B9+Workings!D9+Workings!F9+Workings!H9+Workings!J9+Workings!L9+Workings!N9)/1000 -> 1441.702 | F9: =(Workings!B10+Workings!D10+Workings!F10+Workings!H10+Workings!J10+Workings!L10+Workings!N10)/1000 -> 1531.732 | G9: =(Workings!B11+Workings!D11+Workings!F11+Workings!H11+Workings!J11+Workings!L11+Workings!N11)/1000 -> 1623.537 | H9: =(Workings!B12+Workings!D12+Workings!F12+Workings!H12+Workings!J12+Workings!L12+Workings!N12)/1000 -> 2882.112 | I9: =(Workings!B13+Workings!D13+Workings!F13+Workings!H13+Workings!J13+Workings!L13+Workings!N13)/1000 -> 3322.765 | J9: =(Workings!B14+Workings!D14+Workings!F14+Workings!H14+Workings!J14+Workings!L14+Workings!N14)/1000 -> 3450.632 | K9: =(Workings!B15+Workings!D15+Workings!F15+Workings!H15+Workings!J15+Workings!L15+Workings!N15)/1000 -> 3370.156 | L9: n/a | M9: n/a | N9: n/a | O9: n/a | P9: n/a | Q9: n/a | R9: n/a | S9: n/a | T9: n/a | U9: =U12*Workings!J19 -> 8013.936 | V9: =V12*Workings!J20 -> 8845.277 | W9: =W12*Workings!J21 -> 9646
A10: Blended cost per unit (Rs./kWh) | B10: =B6*1000/B9 -> 3.4129194 | C10: =C6*1000/C9 -> 3.8419685 | D10: =D6*1000/D9 -> 4.1795233 | E10: =E6*1000/E9 -> 4.1361516 | F10: =F6*1000/F9 -> 4.4212477 | G10: =G6*1000/G9 -> 3.7017033 | H10: =H6*1000/H9 -> 4.1340068 | I10: =I6*1000/I9 -> 4.6203081 | ... K10: =K6*1000/K9 -> 4.5763762 | L10: n/a | M10: n/a | N10: n/a | O10: n/a | P10: n/a | Q10: n/a | R10: n/a | S10: n/a | T10: n/a | U10: =U6*1000/U9 -> 5.8009497 | V10: =V6*1000/V9 -> 5.4840725 | W10: =W6*1000/W9 -> 5.0560802
A11: Renewable energy cost per unit (Rs./kWh) | B11: =IFERROR((Workings!L6*Workings!M6+Workings!N6*Workings!O6)/(Workings!L6+Workings!N6),"-") -> - | C11: =IFERROR((Workings!L7*Workings!M7+Workings!N7*Workings!O7)/(Workings!L7+Workings!N7),"-") -> - | D11: =IFERROR((Workings!L8*Workings!M8+Workings!N8*Workings!O8)/(Workings!L8+Workings!N8),"-") -> - | E11: =IFERROR((Workings!L9*Workings!M9+Workings!N9*Workings!O9)/(Workings!L9+Workings!N9),"-") -> - | F11: =IFERROR((Workings!L10*Workings!M10+Workings!N10*Workings!O10)/(Workings!L10+Workings!N10),"-") -> - | G11: =IFERROR((Workings!L11*Workings!M11+Workings!N11*Workings!O11)/(Workings!L11+Workings!N11),"-") -> - | H11: =IFERROR((Workings!L12*Workings!M12+Workings!N12*Workings!O12)/(Workings!L12+Workings!N12),"-") -> - | I11: =IFERROR((Workings!L13*Workings!M13+Workings!N13*Workings!O13)/(Workings!L13+Workings!N13),"-") -> - | J11: =IFERROR((Workings!L14*Workings!M14+Workings!N14*Workings!O14)/(Workings!L14+Workings!N14),"-") -> 0.57723953 | K11: =IFERROR((Workings!L15*Workings!M15+Workings!N15*Workings!O15)/(Workings!L15+Workings!N15),"-") -> 1.121418 | L11: n/a | M11: n/a | N11: n/a | O11: n/a | P11: n/a | Q11: n/a | R11: n/a | S11: n/a | T11: n/a | U11: n/a | V11: ='Source Rates'!H26 -> 4.4726634 | W11: ='Source Rates'!H27 -> 4.4840976
A12: Cement volume (MnT) | B12: - | C12: - | D12: - | E12: - | F12: - | G12: - | H12: - | I12: - | J12: - | K12: - | L12: n/a | M12: n/a | N12: n/a | O12: n/a | P12: n/a | Q12: n/a | R12: n/a | S12: n/a | T12: n/a | U12: =SUM(Workings!B19:E19) -> 112.24 | V12: =SUM(Workings!B20:E20) -> 125.11 | W12: =SUM(Workings!B21:E21) -> 140
A13: Electricity cost (Rs./t) | B13: - | C13: - | D13: - | E13: - | F13: - | G13: - | H13: - | I13: - | J13: - | K13: - | L13: n/a | M13: n/a | N13: n/a | O13: n/a | P13: n/a | Q13: n/a | R13: n/a | S13: n/a | T13: n/a | U13: =U6*1000/U12 -> 414.18781 | V13: =V6*1000/V12 -> 387.72392 | W13: =W6*1000/W12 -> 348.36393
A14: Basis | B14: Form A | C14: Form A | D14: Form A | E14: Form A | F14: Form A | G14: Form A | H14: Form A | I14: Form A | J14: Form A | K14: Form A | L14: not disclosed | M14: not disclosed | N14: not disclosed | O14: not disclosed | P14: not disclosed | Q14: not disclosed | R14: not disclosed | S14: not disclosed | T14: not disclosed | U14: Quarterly decks | V14: Quarterly decks | W14: Quarterly decks
A15: Memo: FY26 on own-manufactured volume (134.67 MnT) | W15: =W6/140*134.67 -> 46.91417

Sheet Workings
A1: WORKINGS — raw inputs transcribed from source documents
A2: Blue = input from a filing. Block A is Form A of the Directors' Report (reported). Block B is built from quarterly investor presentations.
A4: BLOCK A — FORM A, POWER AND FUEL CONSUMPTION (units in '000 kWh, cost per unit in Rs.)
A5: Financial year | B5: Purchased (grid) — units | C5: Purchased (grid) — Rs./kWh | D5: Diesel generator — units | E5: Diesel generator — Rs./kWh | F5: Captive power - coal — units | G5: Captive power - coal — Rs./kWh | H5: Captive power - naphtha — units | I5: Captive power - naphtha — Rs./kWh | J5: Waste heat recovery — units | K5: Waste heat recovery — Rs./kWh | L5: Solar — units | M5: Solar — Rs./kWh | N5: Wind — units | O5: Wind — Rs./kWh | P5: Net sales (Rs. Cr)
A6: FY05 | B6: 288469 | C6: 4.23 | D6: 291512 | E6: 3.61 | F6: 318523 | G6: 1.32 | H6: 306873 | I6: 4.63 | P6: 2606.9
A7: FY06 | B7: 423050 | C7: 4.01 | D7: 305267 | E7: 4.27 | F7: 256036 | G7: 1.41 | H7: 292707 | I7: 5.28 | P7: 3299.45
A8: FY07 | B8: 847582 | C8: 4.79 | D8: 188908 | E8: 4.91 | F8: 309571 | G8: 1.4 | H8: 64249 | I8: 7.4 | J8: 477.05 | K8: 0.25 | P8: 4910.52
A9: FY08 | B9: 923400 | C9: 4.69 | D9: 176961 | E9: 5.62 | F9: 316750 | G9: 1.73 | H9: 5527 | I9: 15.05 | J9: 19064 | K9: 0.35 | P9: 5509.22
A10: FY09 | B10: 817938 | C10: 4.83 | D10: 99071 | E10: 6.31 | F10: 593848 | G10: 3.64 | H10: 1394 | I10: 19.78 | J10: 19481 | K10: 0.37 | P10: 6383
A11: FY10 | B11: 361072 | C11: 5.02 | D11: 61264 | E11: 6.99 | F11: 1187204 | G11: 3.17 | J11: 13997 | K11: 0.4 | P11: 7050
A12: FY11 | B12: 543606 | C12: 5.35 | D12: 71112 | E12: 9.07 | F12: 2251369 | G12: 3.71 | J12: 16025 | K12: 0.55 | P12: 13206
A13: FY12 | B13: 663933 | C13: 5.54 | D13: 55640 | E13: 13.8 | F13: 2588989 | G13: 4.21 | J13: 14203 | K13: 0.46 | P13: 18158
A14: FY13 | B14: 652499 | C14: 6.33 | D14: 62995 | E14: 13.57 | F14: 2719775 | G14: 4.15 | J14: 11447 | K14: 0.41 | L14: 2065 | M14: 0.27 | N14: 1851 | O14: 0.92 | P14: 20023
A15: FY14 | B15: 583398 | C15: 6.67 | D15: 35818 | E15: 14.76 | F15: 2735008 | G15: 4.02 | J15: 10953 | K15: 0.26 | L15: 2928 | M15: 0.52 | N15: 2051 | O15: 1.98 | P15: 20078
A17: BLOCK B — QUARTERLY BUILD FROM INVESTOR PRESENTATIONS
A18: Financial year | B18: Q1 volume | C18: Q2 volume | D18: Q3 volume | E18: Q4 volume | F18: Q1 Rs./t | G18: Q2 Rs./t | H18: Q3 Rs./t | I18: Q4 Rs./t | J18: kWh/t (FY) | K18: Grey cement domestic revenue (Rs. Cr) | L18: Consolidated net sales (Rs. Cr)
A19: FY24 | B19: 28.5 | C19: 25.08 | D19: 25.44 | E19: 33.22 | F19: 413 | G19: 431 | H19: 424 | I19: 395 | J19: 71.4 | K19: 59824 | L19: 69810
A20: FY25 | B20: 31.91 | C20: 27.28 | D20: 29.45 | E20: 36.47 | F20: 389 | G20: 403 | H20: 409 | I20: 358 | J20: 70.7 | K20: 62205 | L20: 74936
A21: FY26 | B21: 33.07 | C21: 29.9 | D21: 35.02 | E21: 42.01 | F21: 356 | G21: 372 | H21: 349 | I21: 325 | J21: 68.9 | K21: 70666 | L21: 87384

Sheet Source Rates
A1: COST PER UNIT BY SOURCE (Rs./kWh)
A2: FY05-FY14 reported in Form A. FY25-FY26 from the power mix tables in the quarterly decks; the two blocks are not directly comparable — see Notes.
A4: FY05 - FY14 | Reported in Form A
A5: Financial year | B5: Purchased (grid) | C5: Diesel generator | D5: Captive power - coal | E5: Captive power - naphtha | F5: Waste heat recovery | G5: Solar | H5: Wind | I5: Blended
A6: FY05 | B6: =IF(Workings!C6="","",Workings!C6) -> 4.23 | C6: =IF(Workings!E6="","",Workings!E6) -> 3.61 | D6: =IF(Workings!G6="","",Workings!G6) -> 1.32 | E6: =IF(Workings!I6="","",Workings!I6) -> 4.63 | F6: =IF(Workings!K6="","",Workings!K6) | G6: =IF(Workings!M6="","",Workings!M6) | H6: =IF(Workings!O6="","",Workings!O6) | I6: ='Time Series'!B10 -> 3.4129194
A7: FY06 | B7: =IF(Workings!C7="","",Workings!C7) -> 4.01 | C7: =IF(Workings!E7="","",Workings!E7) -> 4.27 | D7: =IF(Workings!G7="","",Workings!G7) -> 1.41 | E7: =IF(Workings!I7="","",Workings!I7) -> 5.28 | F7: =IF(Workings!K7="","",Workings!K7) | G7: =IF(Workings!M7="","",Workings!M7) | H7: =IF(Workings!O7="","",Workings!O7) | I7: ='Time Series'!C10 -> 3.8419685
A8: FY07 | B8: =IF(Workings!C8="","",Workings!C8) -> 4.79 | C8: =IF(Workings!E8="","",Workings!E8) -> 4.91 | D8: =IF(Workings!G8="","",Workings!G8) -> 1.4 | E8: =IF(Workings!I8="","",Workings!I8) -> 7.4 | F8: =IF(Workings!K8="","",Workings!K8) -> 0.25 | G8: =IF(Workings!M8="","",Workings!M8) | H8: =IF(Workings!O8="","",Workings!O8) | I8: ='Time Series'!D10 -> 4.1795233
A9: FY08 | B9: =IF(Workings!C9="","",Workings!C9) -> 4.69 | C9: =IF(Workings!E9="","",Workings!E9) -> 5.62 | D9: =IF(Workings!G9="","",Workings!G9) -> 1.73 | E9: =IF(Workings!I9="","",Workings!I9) -> 15.05 | F9: =IF(Workings!K9="","",Workings!K9) -> 0.35 | G9: =IF(Workings!M9="","",Workings!M9) | H9: =IF(Workings!O9="","",Workings!O9) | I9: ='Time Series'!E10 -> 4.1361516
A10: FY09 | B10: =IF(Workings!C10="","",Workings!C10) -> 4.83 | C10: =IF(Workings!E10="","",Workings!E10) -> 6.31 | D10: =IF(Workings!G10="","",Workings!G10) -> 3.64 | E10: =IF(Workings!I10="","",Workings!I10) -> 19.78 | F10: =IF(Workings!K10="","",Workings!K10) -> 0.37 | G10: =IF(Workings!M10="","",Workings!M10) | H10: =IF(Workings!O10="","",Workings!O10) | I10: ='Time Series'!F10 -> 4.4212477
A11: FY10 | B11: =IF(Workings!C11="","",Workings!C11) -> 5.02 | C11: =IF(Workings!E11="","",Workings!E11) -> 6.99 | D11: =IF(Workings!G11="","",Workings!G11) -> 3.17 | E11: =IF(Workings!I11="","",Workings!I11) | F11: =IF(Workings!K11="","",Workings!K11) -> 0.4 | G11: =IF(Workings!M11="","",Workings!M11) | H11: =IF(Workings!O11="","",Workings!O11) | I11: ='Time Series'!G10 -> 3.7017033
A12: FY11 | B12: =IF(Workings!C12="","",Workings!C12) -> 5.35 | C12: =IF(Workings!E12="","",Workings!E12) -> 9.07 | D12: =IF(Workings!G12="","",Workings!G12) -> 3.71 | E12: =IF(Workings!I12="","",Workings!I12) | F12: =IF(Workings!K12="","",Workings!K12) -> 0.55 | G12: =IF(Workings!M12="","",Workings!M12) | H12: =IF(Workings!O12="","",Workings!O12) | I12: ='Time Series'!H10 -> 4.1340068
A13: FY12 | B13: =IF(Workings!C13="","",Workings!C13) -> 5.54 | C13: =IF(Workings!E13="","",Workings!E13) -> 13.8 | D13: =IF(Workings!G13="","",Workings!G13) -> 4.21 | E13: =IF(Workings!I13="","",Workings!I13) | F13: =IF(Workings!K13="","",Workings!K13) -> 0.46 | G13: =IF(Workings!M13="","",Workings!M13) | H13: =IF(Workings!O13="","",Workings!O13) | I13: ='Time Series'!I10 -> 4.6203081
A14: FY13 | B14: =IF(Workings!C14="","",Workings!C14) -> 6.33 | C14: =IF(Workings!E14="","",Workings!E14) -> 13.57 | D14: =IF(Workings!G14="","",Workings!G14) -> 4.15 | E14: =IF(Workings!I14="","",Workings!I14) | F14: =IF(Workings!K14="","",Workings!K14) -> 0.41 | G14: =IF(Workings!M14="","",Workings!M14) -> 0.27 | H14: =IF(Workings!O14="","",Workings!O14) -> 0.92 | I14: ='Time Series'!J10 -> 4.7177389
A15: FY14 | B15: =IF(Workings!C15="","",Workings!C15) -> 6.67 | C15: =IF(Workings!E15="","",Workings!E15) -> 14.76 | D15: =IF(Workings!G15="","",Workings!G15) -> 4.02 | E15: =IF(Workings!I15="","",Workings!I15) | F15: =IF(Workings!K15="","",Workings!K15) -> 0.26 | G15: =IF(Workings!M15="","",Workings!M15) -> 0.52 | H15: =IF(Workings!O15="","",Workings!O15) -> 1.98 | I15: ='Time Series'!K10 -> 4.5763762
A17: FY25 - FY26 | Power mix tables in the quarterly decks
A18: Period | B18: Captive thermal power — mix | C18: State grid and others — mix | D18: Renewable energy — mix | E18: Waste heat recovery system — mix | F18: Captive thermal power — Rs./kWh | G18: State grid and others — Rs./kWh | H18: Renewable energy — Rs./kWh | I18: Waste heat recovery system — Rs./kWh | J18: Blended (Rs./kWh) | K18: kWh/t | L18: Units (mn kWh)
A19: Q2FY25 | B19: 0.461 | C19: 0.237 | D19: 0.128 | E19: 0.174 | F19: 7.1 | G19: 6.7 | H19: 4.6 | I19: 0.7 | J19: 5.6 | K19: 72.4 | L19: =Workings!C20*K19 -> 1975.072
A20: Q3FY25 | B20: 0.454 | C20: 0.231 | D20: 0.127 | E20: 0.187 | F20: 7.1 | G20: 8.1 | H20: 4.5 | I20: 0.8 | J20: 5.8 | K20: 70.8 | L20: =Workings!D20*K20 -> 2085.06
A21: Q4FY25 | B21: 0.42 | C21: 0.236 | D21: 0.139 | E21: 0.205 | F21: 6.48 | G21: 6.97 | H21: 4.36 | I21: 0.71 | J21: 5.19 | K21: 69.04 | L21: =Workings!E20*K21 -> 2517.8888
A22: Q1FY26 | B22: 0.384 | C22: 0.221 | D22: 0.191 | E22: 0.204 | F22: 6.7 | G22: 7.1 | H22: 4.5 | I22: 0.8 | J22: 5.1 | K22: 69.3 | L22: =Workings!B21*K22 -> 2291.751
A23: Q2FY26 | B23: 0.381 | C23: 0.203 | D23: 0.223 | E23: 0.192 | F23: 6.9 | G23: 7.1 | H23: 4.6 | I23: 0.8 | J23: 5.3 | K23: 70.7 | L23: =Workings!C21*K23 -> 2113.93
A24: Q3FY26 | B24: 0.358 | C24: 0.22 | D24: 0.206 | E24: 0.215 | F24: 6.5 | G24: 7.4 | H24: 4.4 | I24: 0.7 | J24: 5.1 | K24: 69 | L24: =Workings!D21*K24 -> 2416.38
A25: Q4FY26 | B25: 0.364 | C25: 0.206 | D25: 0.204 | E25: 0.226 | F25: 5.99 | G25: 7.62 | H25: 4.45 | I25: 0.6 | J25: 4.81 | K25: 67.54 | L25: =Workings!E21*K25 -> 2837.3554
A26: FY25 weighted (Q2-Q4 only) | B26: =(B19*L19+B20*L20+B21*L21)/(L19+L20+L21) -> 0.44308749 | C26: =(C19*L19+C20*L20+C21*L21)/(L19+L20+L21) -> 0.23471538 | D26: =(D19*L19+D20*L20+D21*L21)/(L19+L20+L21) -> 0.13189353 | E26: =(E19*L19+E20*L20+E21*L21)/(L19+L20+L21) -> 0.18998662 | F26: =(B19*L19*F19+B20*L20*F20+B21*L21*F21)/(B19*L19+B20*L20+B21*L21) -> 6.8750465 | G26: =(C19*L19*G19+C20*L20*G20+C21*L21*G21)/(C19*L19+C20*L20+C21*L21) -> 7.2406531 | H26: =(D19*L19*H19+D20*L20*H20+D21*L21*H21)/(D19*L19+D20*L20+D21*L21) -> 4.4726634 | I26: =(E19*L19*I19+E20*L20*I20+E21*L21*I21)/(E19*L19+E20*L20+E21*L21) -> 0.7353293 | J26: =SUMPRODUCT(J19:J21,L19:L21)/SUM(L19:L21) -> 5.5064578
A27: FY26 weighted | B27: =(B22*L22+B23*L23+B24*L24+B25*L25)/(L22+L23+L24+L25) -> 0.37096456 | C27: =(C22*L22+C23*L23+C24*L24+C25*L25)/(L22+L23+L24+L25) -> 0.21240451 | D27: =(D22*L22+D23*L23+D24*L24+D25*L25)/(L22+L23+L24+L25) -> 0.20557408 | E27: =(E22*L22+E23*L23+E24*L24+E25*L25)/(L22+L23+L24+L25) -> 0.21058786 | F27: =(B22*L22*F22+B23*L23*F23+B24*L24*F24+B25*L25*F25)/(B22*L22+B23*L23+B24*L24+B25*L25) -> 6.4920305 | G27: =(C22*L22*G22+C23*L23*G23+C24*L24*G24+C25*L25*G25)/(C22*L22+C23*L23+C24*L24+C25*L25) -> 7.3258701 | H27: =(D22*L22*H22+D23*L23*H23+D24*L24*H24+D25*L25*H25)/(D22*L22+D23*L23+D24*L24+D25*L25) -> 4.4840976 | I27: =(E22*L22*I22+E23*L23*I23+E24*L24*I24+E25*L25*I25)/(E22*L22+E23*L23+E24*L24+E25*L25) -> 0.71141257 | J27: ='Time Series'!W10 -> 5.0560802 | K27: =Workings!J21 -> 68.9
A28: Sourced power excluding waste heat recovery, FY26 | J28: =((B27*F27)+(C27*G27)+(D27*H27))/(B27+C27+D27) -> 6.1933174
A29: Note: FY25 cannot be weighted for a full year — the Q1FY25 deck does not publish a power mix table.

Sheet Notes & Sources
B1: NOTES, SOURCES AND CAVEATS
B3: 1. What this file contains
B4: Three series for UltraTech Cement Limited (standalone), laid out with years across the columns and all rupee figures in billions: electricity cost in absolute rupees, electricity cost as a percentage of revenue, and the cost per unit of electricity by source. FY2005 to FY2014 and FY2024 to FY2026, with a nine-year hole in between that cannot be filled from public disclosure.
B6: 2. Why FY15 to FY23 is blank
B7: Form A of the Directors' Report, which carried electricity units, total amount and rate per unit by source, was withdrawn from the statutory format by the Companies (Accounts) Rules, 2014. From FY15 the Conservation of Energy disclosure is narrative only - it names the fan blades and cyclone modifications but gives no numbers. The FY16, FY19 and FY21 Annual Reports were checked directly and contain no energy quantities.
B8: The investor presentations do not bridge the gap either: until FY23 they reported a single combined 'Energy cost (Rs./Mt)' covering power and fuel together. The power and fuel split first appears in the Q4FY24 deck.
B9: The reported P&L carries only a combined 'Power and Fuel Expense' line in every year, with no breakup note, so electricity cannot be separated from coal and petcoke from the accounts either.
B11: 3. FY05 to FY14 - reported, not derived
B12: Every figure comes from Form A in the Annual Report: units in thousands of kWh and cost per unit in rupees, for each source separately. Total cost is the sum across sources of units multiplied by cost per unit. Sources: purchased grid power, diesel generator, captive power from coal, captive power from naphtha, waste heat recovery, solar and wind.
B13: Annual Reports used, each of which carries the current and prior year: 2005-06 (FY05, FY06), 2007-08 (FY07, FY08), 2009-10 (FY09, FY10), 2011-12 (FY11, FY12) and 2013-14 (FY13, FY14). Revenue is net sales from the financial highlights of the same reports.
B15: 4. The structural break at FY11
B16: UltraTech merged with Samruddhi Cement, the Grasim cement business, with effect from July 2010. Net sales jump from Rs. 7,050 Cr in FY10 to Rs. 13,206 Cr in FY11 and electricity units from 1.62 to 2.88 billion kWh. FY10 and earlier describe a company roughly half the size. Do not read the FY10 to FY11 step as organic.
... B39: The Q4FY26 deck is the same document as the BSE filing of 27 April 2026.
