Workbook

Sheet P&L
A1: MV Electrosystems Ltd (NSE: MVELECTRO, BSE: 544851) - Model v1 (historicals). Standalone = consolidated: no subsidiary, associate or JV (FY26 AR, CARO cl. ix(e)). Rs. crore unless stated. | M1: Colour code: blue = hardcoded historical [A]/[S]; black = formula; red = check/tax-rate input; yellow fill = input cell (v2). FY20-FY22 = Indian GAAP audited statements, headline rows only. FY23-FY26 = ACE Equity dump (Ind AS), overridden by the audited AR/prospectus where they conflict (see Sources sheet).
A2: P&L Statement (Rs. crore) | B2: FY20 | C2: FY21 | D2: FY22 | E2: FY23 | F2: FY24 | G2: FY25 | H2: FY26 | I2: FY27E | J2: FY28E | K2: FY29E | L2: FY30E | M2: FY27E-FY30E = MANAGEMENT GUIDANCE CASE. Every forecast cell is a formula fed by the Drivers sheet; change assumptions there. Other expenses are spread across rows 11 and 13-16 in their FY26 proportions.
A3: Net Sales | B3: 83.836 | C3: 57.372 | D3: 58.067 | E3: 68.071 | F3: 49.957 | G3: 62.637 | H3: 49.428 | I3: =Segments!D8 -> 389.12 | J3: =Segments!E8 -> 864.07967 | K3: =Segments!F8 -> 889.61733 | L3: =Segments!G8 -> 831.92
A4: Growth, % | C4: =+C3/B3-1 -> -0.31566392 | D4: =+D3/C3-1 -> 0.012113923 | E4: =+E3/D3-1 -> 0.17228374 | F4: =+F3/E3-1 -> -0.26610451 | G4: =+G3/F3-1 -> 0.25381828 | H4: =+H3/G3-1 -> -0.21088175 | I4: =+I3/H3-1 -> 6.872461 | J4: =+J3/I3-1 -> 1.2205995 | ... L4: =+L3/K3-1 -> -0.06485635
A5: EXPENDITURE
A6: (Increase)/Decrease in Stock | E6: -5.396 | F6: 1.436 | G6: -1.227 | H6: -3.485 | I6: =0 -> 0 | J6: =0 -> 0 | K6: =0 -> 0 | L6: =0 -> 0
A7: Raw Material Consumed | E7: 51.195 | F7: 24.723 | G7: 38.483 | H7: 38.362 | I7: =Drivers!C29 -> 319.572 | J7: =Drivers!D29 -> 657.73894 | K7: =Drivers!E29 -> 677.40295 | L7: =Drivers!F29 -> 632.976
A8: Variable Cost | E8: =+E6+E7 -> 45.799 | F8: =+F6+F7 -> 26.159 | G8: =+G6+G7 -> 37.256 | H8: =+H6+H7 -> 34.877 | I8: =+I6+I7 -> 319.572 | J8: =+J6+J7 -> 657.73894 | K8: =+K6+K7 -> 677.40295 | L8: =+L6+L7 -> 632.976
A9: Gross Profit | E9: =+E3-E8 -> 22.272 | F9: =+F3-F8 -> 23.798 | G9: =+G3-G8 -> 25.381 | H9: =+H3-H8 -> 14.551 | I9: =+I3-I8 -> 69.548 | J9: =+J3-J8 -> 206.34072 | K9: =+K3-K8 -> 212.21439 | L9: =+L3-L8 -> 198.944
A10: Gross Margin | E10: =+E9/E3 -> 0.32718779 | F10: =+F9/F3 -> 0.47636968 | G10: =+G9/G3 -> 0.40520778 | H10: =+H9/H3 -> 0.2943878 | I10: =+I9/I3 -> 0.1787315 | J10: =+J9/J3 -> 0.23879826 | K10: =+K9/K3 -> 0.2385457 | L10: =+L9/L3 -> 0.23913838
A11: Power & Fuel Cost | E11: 1.171 | F11: 0.875 | G11: 0.791 | H11: 1.062 | I11: =Drivers!C33*$H11/($H$11+SUM($H$13:$H$16)) -> 2.2658042 | J11: =Drivers!D33*$H11/($H$11+SUM($H$13:$H$16)) -> 3.7252684 | K11: =Drivers!E33*$H11/($H$11+SUM($H$13:$H$16)) -> 3.894305 | L11: =Drivers!F33*$H11/($H$11+SUM($H$13:$H$16)) -> 3.8243485
A12: Employee Cost | E12: 7.67 | F12: 9.191 | G12: 9.566 | H12: 13.76 | I12: =Drivers!C30 -> 22 | J12: =Drivers!D30 -> 30 | K12: =Drivers!E30 -> 33 | L12: =Drivers!F30 -> 36
A13: Other Manufacturing Expenses | E13: 4.001 | F13: 4.042 | G13: 4.004 | H13: 4.891 | I13: =Drivers!C33*$H13/($H$11+SUM($H$13:$H$16)) -> 10.435074 | J13: =Drivers!D33*$H13/($H$11+SUM($H$13:$H$16)) -> 17.15658 | K13: =Drivers!E33*$H13/($H$11+SUM($H$13:$H$16)) -> 17.935071 | L13: =Drivers!F33*$H13/($H$11+SUM($H$13:$H$16)) -> 17.612889
A14: General & Administration Expenses | E14: 2.625 | F14: 3.013 | G14: 2.594 | H14: 4.461 | I14: =Drivers!C33*$H14/($H$11+SUM($H$13:$H$16)) -> 9.5176577 | J14: =Drivers!D33*$H14/($H$11+SUM($H$13:$H$16)) -> 15.648232 | K14: =Drivers!E33*$H14/($H$11+SUM($H$13:$H$16)) -> 16.358281 | L14: =Drivers!F33*$H14/($H$11+SUM($H$13:$H$16)) -> 16.064424
A15: Selling & Distribution Expenses | E15: 0.33 | F15: 0.46 | G15: 0.489 | H15: 0.208 | I15: =Drivers!C33*$H15/($H$11+SUM($H$13:$H$16)) -> 0.44377332 | J15: =Drivers!D33*$H15/($H$11+SUM($H$13:$H$16)) -> 0.72961942 | K15: =Drivers!E33*$H15/($H$11+SUM($H$13:$H$16)) -> 0.7627264 | L15: =Drivers!F33*$H15/($H$11+SUM($H$13:$H$16)) -> 0.74902495
A16: Miscellaneous Expenses | E16: 0.275 | F16: 0.422 | G16: 1.02 | H16: 0.474 | I16: =Drivers!C33*$H16/($H$11+SUM($H$13:$H$16)) -> 1.0112911 | J16: =Drivers!D33*$H16/($H$11+SUM($H$13:$H$16)) -> 1.6626904 | K16: =Drivers!E33*$H16/($H$11+SUM($H$13:$H$16)) -> 1.7381361 | L16: =Drivers!F33*$H16/($H$11+SUM($H$13:$H$16)) -> 1.7069126
A17: Total Expenditure | E17: =SUM(E11:E16)+E8 -> 61.871 | F17: =SUM(F11:F16)+F8 -> 44.162 | G17: =SUM(G11:G16)+G8 -> 55.72 | H17: =SUM(H11:H16)+H8 -> 59.733 | I17: =SUM(I11:I16)+I8 -> 365.2456 | J17: =SUM(J11:J16)+J8 -> 726.66133 | K17: =SUM(K11:K16)+K8 -> 751.09147 | L17: =SUM(L11:L16)+L8 -> 708.9336
A19: EBITDA | B19: 6.6 | C19: 3.94 | D19: 4.53 | E19: =E3-E17 -> 6.2 | F19: =F3-F17 -> 5.795 | G19: =G3-G17 -> 6.917 | H19: =H3-H17 -> -10.305 | I19: =I3-I17 -> 23.8744 | J19: =J3-J17 -> 137.41833 | K19: =K3-K17 -> 138.52587 | L19: =L3-L17 -> 122.9864
A20: Growth, % | C20: =IF(B19>0,C19/B19-1,"n.m.") -> -0.4030303 | D20: =IF(C19>0,D19/C19-1,"n.m.") -> 0.14974619 | E20: =IF(D19>0,E19/D19-1,"n.m.") -> 0.36865342 | F20: =IF(E19>0,F19/E19-1,"n.m.") -> -0.065322581 | G20: =IF(F19>0,G19/F19-1,"n.m.") -> 0.19361519 | H20: =IF(G19>0,H19/G19-1,"n.m.") -> -2.4898077 | I20: =IF(H19>0,I19/H19-1,"n.m.") -> n.m. | J20: =IF(I19>0,J19/I19-1,"n.m.") -> 4.7558864 | ... L20: =IF(K19>0,L19/K19-1,"n.m.") -> -0.11217736
A21: Margin, % | B21: =+B19/B3 -> 0.07872513 | C21: =+C19/C3 -> 0.068674615 | D21: =+D19/D3 -> 0.078013329 | E21: =+E19/E3 -> 0.091081371 | F21: =+F19/F3 -> 0.11599976 | G21: =+G19/G3 -> 0.11042994 | H21: =+H19/H3 -> -0.20848507 | I21: =+I19/I3 -> 0.061354852 | ... L21: =+L19/L3 -> 0.14783441
A22: Other Income | E22: 0.061 | F22: 0.608 | G22: 1.999 | H22: 0.363 | I22: =Drivers!C38*(H80+0.5*(N(Drivers!C40)-N(Drivers!C41))) -> 8.2814875 | J22: =Drivers!D38*(I80+0.5*(N(Drivers!D40)-N(Drivers!D41))) -> 14.677169 | K22: =Drivers!E38*(J80+0.5*(N(Drivers!E40)-N(Drivers!E41))) -> 13.385699 | L22: =Drivers!F38*(K80+0.5*(N(Drivers!F40)-N(Drivers!F41))) -> 19.589834
A23: Depreciation | E23: 2.595 | F23: 2.839 | G23: 3.473 | H23: 3.365 | I23: =Drivers!C36*AVERAGE(H65,I65) -> 6.46572 | J23: =Drivers!D36*AVERAGE(I65,J65) -> 7.96572 | K23: =Drivers!E36*AVERAGE(J65,K65) -> 9.16572 | L23: =Drivers!F36*AVERAGE(K65,L65) -> 10.48572
A24: EBIT | E24: =E19+E22-E23 -> 3.666 | F24: =F19+F22-F23 -> 3.564 | G24: =G19+G22-G23 -> 5.443 | H24: =H19+H22-H23 -> -13.307 | I24: =I19+I22-I23 -> 25.690168 | J24: =J19+J22-J23 -> 144.12978 | K24: =K19+K22-K23 -> 142.74585 | L24: =L19+L22-L23 -> 132.09051
A25: Interest | E25: 1.902 | F25: 2.5 | G25: 3.042 | H25: 3.49 | I25: =Drivers!C37*(H47+H48+H57) -> 4.9893 | J25: =Drivers!D37*(I47+I48+I57) -> 4.9893 | K25: =Drivers!E37*(J47+J48+J57) -> 4.9893 | L25: =Drivers!F37*(K47+K48+K57) -> 4.9893
A26: Exceptional Income / (Expenses) | E26: -0.001 | F26: -0.08 | G26: 0.163 | H26: 0 | I26: =0 -> 0 | J26: =0 -> 0 | K26: =0 -> 0 | L26: =0 -> 0
A27: PBT | E27: =+E24-E25+E26 -> 1.763 | F27: =+F24-F25+F26 -> 0.984 | G27: =+G24-G25+G26 -> 2.564 | H27: =+H24-H25+H26 -> -16.797 | I27: =+I24-I25+I26 -> 20.700868 | J27: =+J24-J25+J26 -> 139.14048 | K27: =+K24-K25+K26 -> 137.75655 | L27: =+L24-L25+L26 -> 127.10121
A28: Provision for Tax | E28: 0.572 | F28: 0.459 | G28: 1.162 | H28: -4.168 | I28: =I27*Drivers!C39 -> 5.2104083 | J28: =J27*Drivers!D39 -> 35.021659 | K28: =K27*Drivers!E39 -> 34.673323 | L28: =L27*Drivers!F39 -> 31.991376
A29: Tax Rate % | E29: =IF(E27=0,0,E28/E27) -> 0.32444697 | F29: =IF(F27=0,0,F28/F27) -> 0.46646341 | G29: =IF(G27=0,0,G28/G27) -> 0.45319813 | H29: =IF(H27=0,0,H28/H27) -> 0.24813955 | I29: =IF(I27=0,0,I28/I27) -> 0.2517 | J29: =IF(J27=0,0,J28/J27) -> 0.2517 | K29: =IF(K27=0,0,K28/K27) -> 0.2517 | L29: =IF(L27=0,0,L28/L27) -> 0.2517
A30: PAT | B30: 3.091 | C30: 0.211 | D30: 0.579 | E30: =+E27-E28 -> 1.191 | F30: =+F27-F28 -> 0.525 | G30: =+G27-G28 -> 1.402 | H30: =+H27-H28 -> -12.629 | I30: =+I27-I28 -> 15.490459 | J30: =+J27-J28 -> 104.11882 | K30: =+K27-K28 -> 103.08322 | L30: =+L27-L28 -> 95.109838
A31: Growth, % | C31: =IF(B30>0,C30/B30-1,"n.m.") -> -0.9317373 | D31: =IF(C30>0,D30/C30-1,"n.m.") -> 1.7440758 | E31: =IF(D30>0,E30/D30-1,"n.m.") -> 1.0569948 | F31: =IF(E30>0,F30/E30-1,"n.m.") -> -0.55919395 | G31: =IF(F30>0,G30/F30-1,"n.m.") -> 1.6704762 | H31: =IF(G30>0,H30/G30-1,"n.m.") -> -10.007846 | I31: =IF(H30>0,I30/H30-1,"n.m.") -> n.m. | J31: =IF(I30>0,J30/I30-1,"n.m.") -> 5.7214808 | ... L31: =IF(K30>0,L30/K30-1,"n.m.") -> -0.077349006
A32: Margin, % | B32: =+B30/B3 -> 0.036869603 | C32: =+C30/C3 -> 0.0036777522 | D32: =+D30/D3 -> 0.0099712401 | E32: =+E30/E3 -> 0.017496438 | F32: =+F30/F3 -> 0.010509038 | G32: =+G30/G3 -> 0.022382937 | H32: =+H30/H3 -> -0.25550295 | I32: =+I30/I3 -> 0.039808951 | ... L32: =+L30/L3 -> 0.1143257
A33: No. of Shares, crore (current FV Rs.5 equivalent, year-end) | B33: 1.4624 | C33: 1.4624 | D33: 1.4624 | E33: 1.4624 | F33: 1.4624 | G33: 1.828 | H33: 2.0459 | I33: =H33+N(Drivers!C42) -> 2.7282528 | J33: =I33+N(Drivers!D42) -> 2.7282528 | K33: =J33+N(Drivers!E42) -> 2.7282528 | L33: =K33+N(Drivers!F42) -> 2.7282528
A34: EPS (Rs., on current share count) | B34: =+B30/B33 -> 2.1136488 | C34: =+C30/C33 -> 0.14428337 | D34: =+D30/D33 -> 0.39592451 | E34: =+E30/E33 -> 0.81441466 | F34: =+F30/F33 -> 0.35899891 | G34: =+G30/G33 -> 0.76695842 | H34: =+H30/H33 -> -6.1728335 | I34: =+I30/I33 -> 5.6777946 | ... L34: =+L30/L33 -> 34.86108
A35: Dividend | E35: 0 | F35: 0 | G35: 0 | H35: 0 | I35: =0 -> 0 | J35: =0 -> 0 | K35: =0 -> 0 | L35: =0 -> 0
A36: DPS | E36: 0 | F36: 0 | G36: 0 | H36: 0 | I36: =0 -> 0 | J36: =0 -> 0 | K36: =0 -> 0 | L36: =0 -> 0
A38: Balance Sheet (Rs. crore) | B38: FY20 | C38: FY21 | D38: FY22 | E38: FY23 | F38: FY24 | G38: FY25 | H38: FY26 | I38: FY27E | J38: FY28E | K38: FY29E | L38: FY30E
A39: EQUITY AND LIABILITIES
A40: Share Capital | B40: 0.2285 | C40: 0.2285 | D40: 0.2285 | E40: 0.229 | F40: 7.372 | G40: 9.14 | H40: 10.23 | I40: =H40+N(Drivers!C42)*N(Drivers!C43) -> 13.641764 | J40: =I40+N(Drivers!D42)*N(Drivers!D43) -> 13.641764 | K40: =J40+N(Drivers!E42)*N(Drivers!E43) -> 13.641764 | L40: =K40+N(Drivers!F42)*N(Drivers!F43) -> 13.641764
A41: Share Warrants & Outstandings | E41: 0 | F41: 0 | G41: 0 | H41: 0 | I41: =0 -> 0 | J41: =0 -> 0 | K41: =0 -> 0 | L41: =0 -> 0
A42: Total Reserves | B42: 10.897 | C42: 11.026 | D42: 11.596 | E42: 12.394 | F42: 9.154 | G42: 8.77 | H42: 52.341 | I42: =H42+I30-I35+N(Drivers!C40)-N(Drivers!C41)-N(Drivers!C42)*N(Drivers!C43) -> 318.8787 | J42: =I42+J30-J35+N(Drivers!D40)-N(Drivers!D41)-N(Drivers!D42)*N(Drivers!D43) -> 422.99752 | K42: =J42+K30-K35+N(Drivers!E40)-N(Drivers!E41)-N(Drivers!E42)*N(Drivers!E43) -> 526.08074 | L42: =K42+L30-L35+N(Drivers!F40)-N(Drivers!F41)-N(Drivers!F42)*N(Drivers!F43) -> 621.19058
A43: Shareholder's Funds | B43: =SUM(B40:B42) -> 11.1255 | C43: =SUM(C40:C42) -> 11.2545 | D43: =SUM(D40:D42) -> 11.8245 | E43: =SUM(E40:E42) -> 12.623 | F43: =SUM(F40:F42) -> 16.526 | G43: =SUM(G40:G42) -> 17.91 | H43: =SUM(H40:H42) -> 62.571 | I43: =SUM(I40:I42) -> 332.52046 | ... L43: =SUM(L40:L42) -> 634.83234
A44: Minority Interest | E44: 0 | F44: 0 | G44: 0 | H44: 0 | I44: =0 -> 0 | J44: =0 -> 0 | K44: =0 -> 0 | L44: =0 -> 0
A46: Non-Current Liabilities
A47: Secured Loans | B47: 4.415 | C47: 4.565 | D47: 2.678 | E47: 6.202 | F47: 5.065 | G47: 4.973 | H47: 9.543 | I47: =H47 -> 9.543 | J47: =I47 -> 9.543 | K47: =J47 -> 9.543 | L47: =K47 -> 9.543
A48: Unsecured Loans | E48: 0 | F48: 2.15 | G48: 0.1 | H48: 0 | I48: =H48 -> 0 | J48: =I48 -> 0 | K48: =J48 -> 0 | L48: =K48 -> 0
A49: Deferred Tax Liabilities / (Assets) | E49: -0.577 | F49: -0.885 | G49: -1.656 | H49: -5.848 | I49: =H49 -> -5.848 | J49: =I49 -> -5.848 | K49: =J49 -> -5.848 | L49: =K49 -> -5.848
A50: Other Long Term Liabilities (lease liabilities) | E50: 0 | F50: 5.481 | G50: 4.846 | H50: 5.076 | I50: =H50 -> 5.076 | J50: =I50 -> 5.076 | K50: =J50 -> 5.076 | L50: =K50 -> 5.076
A51: Long Term Provisions | E51: 0.624 | F51: 0.718 | G51: 1.053 | H51: 1.555 | I51: =H51 -> 1.555 | J51: =I51 -> 1.555 | K51: =J51 -> 1.555 | L51: =K51 -> 1.555
A52: Total Non-Current Liabilities | E52: =SUM(E47:E51) -> 6.249 | F52: =SUM(F47:F51) -> 12.529 | G52: =SUM(G47:G51) -> 9.316 | H52: =SUM(H47:H51) -> 10.326 | I52: =SUM(I47:I51) -> 10.326 | J52: =SUM(J47:J51) -> 10.326 | K52: =SUM(K47:K51) -> 10.326 | L52: =SUM(L47:L51) -> 10.326
A54: Current Liabilities
A55: Trade Payables | B55: 16.226 | C55: 5.12 | D55: 4.63 | E55: 8.556 | F55: 12.411 | G55: 18.507 | H55: 21.923 | I55: =Drivers!C47/365*Drivers!C29 -> 39.399288 | J55: =Drivers!D47/365*Drivers!D29 -> 81.091103 | K55: =Drivers!E47/365*Drivers!E29 -> 83.515432 | L55: =Drivers!F47/365*Drivers!F29 -> 78.038137
A56: Other Current Liabilities | E56: 4.596 | F56: 2.257 | G56: 2.539 | H56: 4.573 | I56: =Drivers!C49/365*Drivers!C23 -> 20.255562 | J56: =Drivers!D49/365*Drivers!D23 -> 44.979489 | K56: =Drivers!E49/365*Drivers!E23 -> 46.308847 | L56: =Drivers!F49/365*Drivers!F23 -> 43.305425
A57: Short Term Borrowings | B57: 7.998 | C57: 9.317 | D57: 8.416 | E57: 11.913 | F57: 20.4 | G57: 22.429 | H57: 40.35 | I57: =H57 -> 40.35 | J57: =I57 -> 40.35 | K57: =J57 -> 40.35 | L57: =K57 -> 40.35
A58: Short Term Provisions | E58: 0.242 | F58: 1.05 | G58: 2.554 | H58: 1.825 | I58: =H58 -> 1.825 | J58: =I58 -> 1.825 | K58: =J58 -> 1.825 | L58: =K58 -> 1.825
A59: Total Current Liabilities | E59: =SUM(E55:E58) -> 25.307 | F59: =SUM(F55:F58) -> 36.118 | G59: =SUM(G55:G58) -> 46.029 | H59: =SUM(H55:H58) -> 68.671 | I59: =SUM(I55:I58) -> 101.82985 | J59: =SUM(J55:J58) -> 168.24559 | K59: =SUM(K55:K58) -> 171.99928 | L59: =SUM(L55:L58) -> 163.51856
A61: TOTAL EQUITY AND LIABILITIES | E61: =E43+E44+E52+E59 -> 44.179 | F61: =F43+F44+F52+F59 -> 65.173 | G61: =G43+G44+G52+G59 -> 73.255 | H61: =H43+H44+H52+H59 -> 141.568 | I61: =I43+I44+I52+I59 -> 444.67631 | J61: =J43+J44+J52+J59 -> 615.21087 | K61: =K43+K44+K52+K59 -> 722.04778 | L61: =L43+L44+L52+L59 -> 808.67691
A63: ASSETS
A64: Non-Current Assets
A65: Gross Block | E65: 20.124 | F65: 27.944 | G65: 28.391 | H65: 46.381 | I65: =H65+Drivers!C35 -> 61.381 | J65: =I65+Drivers!D35 -> 71.381 | K65: =J65+Drivers!E35 -> 81.381 | L65: =K65+Drivers!F35 -> 93.381
A66: Less: Accumulated Depreciation | E66: 12.839 | F66: 15.009 | G66: 16.477 | H66: 19.403 | I66: =H66+I23 -> 25.86872 | J66: =I66+J23 -> 33.83444 | K66: =J66+K23 -> 43.00016 | L66: =K66+L23 -> 53.48588
A67: Net Block | B67: 8.208 | C67: 11.829 | D67: 9.021 | E67: =E65-E66 -> 7.285 | F67: =F65-F66 -> 12.935 | G67: =G65-G66 -> 11.914 | H67: =H65-H66 -> 26.978 | I67: =I65-I66 -> 35.51228 | J67: =J65-J66 -> 37.54656 | K67: =K65-K66 -> 38.38084 | L67: =L65-L66 -> 39.89512
A68: Capital Work in Progress | E68: 4.079 | F68: 0.748 | G68: 0.195 | H68: 1.948 | I68: =H68 -> 1.948 | J68: =I68 -> 1.948 | K68: =J68 -> 1.948 | L68: =K68 -> 1.948
A69: Intangible Assets under Development | E69: 0 | F69: 0 | G69: 0 | H69: 0 | I69: =H69 -> 0 | J69: =I69 -> 0 | K69: =J69 -> 0 | L69: =K69 -> 0
A70: Investment Property (ACE label: Assets in Transit) | E70: 6.36 | F70: 11.433 | G70: 10.951 | H70: 10.515 | I70: =H70 -> 10.515 | J70: =I70 -> 10.515 | K70: =J70 -> 10.515 | L70: =K70 -> 10.515
A71: Non-Current Investments | E71: 0.03 | F71: 0.035 | G71: 0 | H71: 0 | I71: =H71 -> 0 | J71: =I71 -> 0 | K71: =J71 -> 0 | L71: =K71 -> 0
A72: Long Term Loans & Advances | E72: 0.4 | F72: 0.402 | G72: 0.415 | H72: 1.455 | I72: =H72 -> 1.455 | J72: =I72 -> 1.455 | K72: =J72 -> 1.455 | L72: =K72 -> 1.455
A73: Other Non-Current Assets | E73: 0.43 | F73: 0.46 | G73: 0.541 | H73: 0.726 | I73: =H73 -> 0.726 | J73: =I73 -> 0.726 | K73: =J73 -> 0.726 | L73: =K73 -> 0.726
A74: Total Non-Current Assets | E74: =E67+SUM(E68:E73) -> 18.584 | F74: =F67+SUM(F68:F73) -> 26.013 | G74: =G67+SUM(G68:G73) -> 24.016 | H74: =H67+SUM(H68:H73) -> 41.622 | I74: =I67+SUM(I68:I73) -> 50.15628 | J74: =J67+SUM(J68:J73) -> 52.19056 | K74: =K67+SUM(K68:K73) -> 53.02484 | L74: =L67+SUM(L68:L73) -> 54.53912
A76: Current Assets
A77: Current Investments | E77: 0 | F77: 0 | G77: 0 | H77: 0 | I77: =0 -> 0 | J77: =0 -> 0 | K77: =0 -> 0 | L77: =0 -> 0
A78: Inventories | B78: 3.153 | C78: 8.864 | D78: 9.426 | E78: 13.669 | F78: 24.445 | G78: 31.756 | H78: 67.485 | I78: =Drivers!C45/365*Drivers!C29 -> 91.931671 | J78: =Drivers!D45/365*Drivers!D29 -> 189.21257 | K78: =Drivers!E45/365*Drivers!E29 -> 194.86934 | L78: =Drivers!F45/365*Drivers!F29 -> 182.08899
A79: Sundry Debtors | B79: 25.692 | C79: 8.687 | D79: 5.898 | E79: 8.163 | F79: 12.594 | G79: 14.574 | H79: 10.406 | I79: =Drivers!C46/365*Drivers!C23 -> 63.964932 | J79: =Drivers!D46/365*Drivers!D23 -> 142.04049 | K79: =Drivers!E46/365*Drivers!E23 -> 146.23847 | L79: =Drivers!F46/365*Drivers!F23 -> 136.75397
A80: Cash and Bank | B80: 3.216 | C80: 2.089 | D80: 1.907 | E80: 2.35 | F80: 0.153 | G80: 0.076 | H80: 0.178 | I80: =I137 -> 225.8026 | J80: =J137 -> 205.93383 | K80: =K137 -> 301.38206 | L80: =L137 -> 410.3425
A81: Other Current Assets | E81: 0.1 | F81: 0.114 | G81: 0.3 | H81: 2.16 | I81: =H81 -> 2.16 | J81: =I81 -> 2.16 | K81: =J81 -> 2.16 | L81: =K81 -> 2.16
A82: Short Term Loans and Advances (FY26: advances to suppliers Rs.7.4 cr) | E82: 1.313 | F82: 1.854 | G82: 2.533 | H82: 19.717 | I82: =Drivers!C48/365*Drivers!C23 -> 10.660822 | J82: =Drivers!D48/365*Drivers!D23 -> 23.673416 | K82: =Drivers!E48/365*Drivers!E23 -> 24.373078 | L82: =Drivers!F48/365*Drivers!F23 -> 22.792329
A83: Total Current Assets | E83: =SUM(E77:E82) -> 25.595 | F83: =SUM(F77:F82) -> 39.16 | G83: =SUM(G77:G82) -> 49.239 | H83: =SUM(H77:H82) -> 99.946 | I83: =SUM(I77:I82) -> 394.52003 | J83: =SUM(J77:J82) -> 563.02031 | K83: =SUM(K77:K82) -> 669.02294 | L83: =SUM(L77:L82) -> 754.13779
A84: Miscellaneous Expenses not Written Off | E84: 0 | F84: 0 | G84: 0 | H84: 0 | I84: =0 -> 0 | J84: =0 -> 0 | K84: =0 -> 0 | L84: =0 -> 0
A86: TOTAL ASSETS | E86: =E74+E83+E84 -> 44.179 | F86: =F74+F83+F84 -> 65.173 | G86: =G74+G83+G84 -> 73.255 | H86: =H74+H83+H84 -> 141.568 | I86: =I74+I83+I84 -> 444.67631 | J86: =J74+J83+J84 -> 615.21087 | K86: =K74+K83+K84 -> 722.04778 | L86: =L74+L83+L84 -> 808.67691
A88: CHECK: | E88: =E86-E61 -> 0 | F88: =F86-F61 -> 0 | G88: =G86-G61 -> 0 | H88: =H86-H61 -> 0 | I88: =I86-I61 -> 0 | J88: =J86-J61 -> 0 | K88: =K86-K61 -> 0 | L88: =L86-L61 -> 0
A90: Cash Flow Statement (Rs. crore) | B90: FY20 | C90: FY21 | D90: FY22 | E90: FY23 | F90: FY24 | G90: FY25 | H90: FY26 | I90: FY27E | J90: FY28E | K90: FY29E | L90: FY30E
A91: Profit Before Tax (per CF as reported) | E91: 1.763 | F91: 1.142 | G91: 2.537 | H91: -16.887 | I91: =I27 -> 20.700868 | J91: =J27 -> 139.14048 | K91: =K27 -> 137.75655 | L91: =L27 -> 127.10121
A93: Adjustments (non-cash / non-operating)
A94: Depreciation | E94: 2.595 | F94: 2.839 | G94: 3.473 | H94: 3.365 | I94: =I23 -> 6.46572 | J94: =J23 -> 7.96572 | K94: =K23 -> 9.16572 | L94: =L23 -> 10.48572
A95: Interest Expenses | E95: 1.549 | F95: 2.47 | G95: 3.042 | H95: 3.49 | I95: =I25 -> 4.9893 | J95: =J25 -> 4.9893 | K95: =K25 -> 4.9893 | L95: =L25 -> 4.9893
A96: Profit/Loss on Sale of Fixed Assets | E96: 0.001 | F96: 0.08 | G96: -0.163 | H96: 0 | I96: =0 -> 0 | J96: =0 -> 0 | K96: =0 -> 0 | L96: =0 -> 0
A97: Interest Income | E97: -0.021 | F97: -0.584 | G97: -0.472 | H97: -0.293 | I97: =-I22 -> -8.2814875 | J97: =-J22 -> -14.677169 | K97: =-K22 -> -13.385699 | L97: =-L22 -> -19.589834
A98: Provisions & Write-offs | E98: 0.2 | F98: 0.173 | G98: 1.242 | H98: 0.611 | I98: =0 -> 0 | J98: =0 -> 0 | K98: =0 -> 0 | L98: =0 -> 0
A99: Excess of Cost over Fair Value of Investments | E99: -0.004 | F99: -0.005 | G99: -0.009 | H99: 0 | I99: =0 -> 0 | J99: =0 -> 0 | K99: =0 -> 0 | L99: =0 -> 0
A100: Bad Debts Written Off | E100: 0 | F100: 0 | G100: -0.023 | H100: 0 | I100: =0 -> 0 | J100: =0 -> 0 | K100: =0 -> 0 | L100: =0 -> 0
A101: Other Adjustments | E101: -0.013 | F101: -0.074 | G101: -0.042 | H101: -0.044 | I101: =0 -> 0 | J101: =0 -> 0 | K101: =0 -> 0 | L101: =0 -> 0
A102: Total Adjustments | E102: =SUM(E94:E101) -> 4.307 | F102: =SUM(F94:F101) -> 4.899 | G102: =SUM(G94:G101) -> 7.048 | H102: =SUM(H94:H101) -> 7.129 | I102: =SUM(I94:I101) -> 3.1735325 | J102: =SUM(J94:J101) -> -1.7221492 | K102: =SUM(K94:K101) -> 0.76932086 | L102: =SUM(L94:L101) -> -4.1148139
A104: Changes in Working Capital
A105: Trade & Other Receivables | E105: 0 | F105: -4.431 | G105: -2.015 | H105: 4.167 | I105: =(H79+H81)-(I79+I81) -> -53.558932 | J105: =(I79+I81)-(J79+J81) -> -78.075562 | K105: =(J79+J81)-(K79+K81) -> -4.1979726 | L105: =(K79+K81)-(L79+L81) -> 9.4844932
A106: Inventories | E106: -4.243 | F106: -10.776 | G106: -7.311 | H106: -35.729 | I106: =H78-I78 -> -24.446671 | J106: =I78-J78 -> -97.280902 | K106: =J78-K78 -> -5.6567681 | L106: =K78-L78 -> 12.780355
A107: Loans & Advances (FY26: advances to suppliers) | E107: -2.482 | F107: -0.076 | G107: -0.553 | H107: -17.926 | I107: =H82-I82 -> 9.0561781 | J107: =I82-J82 -> -13.012594 | K107: =J82-K82 -> -0.6996621 | L107: =K82-L82 -> 1.5807489
A108: Trade & Other Payables | E108: 3.677 | F108: 4.642 | G108: 6.219 | H108: 4.848 | I108: =(I55+I56+I58)-(H55+H56+H58) -> 33.158849 | J108: =(J55+J56+J58)-(I55+I56+I58) -> 66.415743 | K108: =(K55+K56+K58)-(J55+J56+J58) -> 3.7536872 | L108: =(L55+L56+L58)-(K55+K56+K58) -> -8.4807176
A109: Other Non-Current Assets | E109: 0.696 | F109: -0.137 | G109: -0.094 | H109: -1.237 | I109: =0 -> 0 | J109: =0 -> 0 | K109: =0 -> 0 | L109: =0 -> 0
A110: Total Changes in Working Capital | E110: =SUM(E105:E109) -> -2.352 | F110: =SUM(F105:F109) -> -10.778 | G110: =SUM(G105:G109) -> -3.754 | H110: =SUM(H105:H109) -> -45.877 | I110: =SUM(I105:I109) -> -35.790575 | J110: =SUM(J105:J109) -> -121.95331 | K110: =SUM(K105:K109) -> -6.8007156 | L110: =SUM(L105:L109) -> 15.364879
A112: Cash Flow after Working Capital Changes | E112: =E91+E102+E110 -> 3.718 | F112: =F91+F102+F110 -> -4.737 | G112: =G91+G102+G110 -> 5.831 | H112: =H91+H102+H110 -> -55.635 | I112: =I91+I102+I110 -> -11.916175 | J112: =J91+J102+J110 -> 15.465019 | K112: =K91+K102+K110 -> 131.72515 | L112: =L91+L102+L110 -> 138.35128
A113: Direct Taxes Paid | E113: -0.342 | F113: -0.478 | G113: -0.792 | H113: -1.91 | I113: =-I28 -> -5.2104083 | J113: =-J28 -> -35.021659 | K113: =-K28 -> -34.673323 | L113: =-L28 -> -31.991376
...

Sheet Drivers
A1: Forecast drivers - MANAGEMENT GUIDANCE CASE (to be tweaked); Rs. crore unless stated
A2: Every forecast number in P&L, Segments and the balance sheet flows from this sheet. Blue = input, black = formula, yellow = the inputs that move the answer most. Sources: call 27-Aug-2026 [M], Q1FY27 PPT p.16 [M], Prospectus [A], analyst [E].
A4: Driver | B4: Unit | C4: FY27E | D4: FY28E | E4: FY29E | F4: FY30E | G4: Source / basis
A5: 1. Locomotive propulsion
A6: Opening order book | B6: sets | C6: 569 | D6: =C9 -> 809 | E6: =D9 -> 779 | F6: =E9 -> 749 | G6: [A] 564 sets outstanding at 30-Jun-2026 (Pro p.216) + 5 delivered in 1QFY27 [E: 9 delivered to 30-Jun-2026 less 1 prototype (Feb-2024) less 3 in FY26] = 569 at 1-Apr-2026.
A7: New orders won | B7: sets | C7: 450 | D7: 450 | E7: 450 | F7: 450 | G7: [M] "confident to get similar order book ... every year" (call). FY26 actual: 450 sets = 27% of 1,659 tendered (Pro p.126). First test: CLW 748-locomotive tender (due 31-Aug-2026).
A8: Sets delivered | B8: sets | C8: =SUM(C53:C56) -> 210 | D8: 480 | E8: 480 | F8: 480 | G8: [M] FY27 from the quarterly ramp below; FY28 onward 40 sets a month = 480 (call: "we want to stand on 40 propulsion systems per month"). Capacity: 114 + 171 = 285 a year single shift; two shifts planned (call).
A9: Closing order book | B9: sets | C9: =C6+C7-C8 -> 809 | D9: =D6+D7-D8 -> 779 | E9: =E6+E7-E8 -> 749 | F9: =F6+F7-F8 -> 719 | G9: Check: must stay positive, else deliveries exceed orders.
A10: Book cover at next year's run-rate | B10: years | C10: =C9/D8 -> 1.6854167 | D10: =D9/E8 -> 1.6229167 | E10: =E9/F8 -> 1.5604167 | G10: Closing book / next year's deliveries.
A11: Realisation per set, ex GST | B11: Rs cr | C11: 1.64 | D11: 1.64 | E11: 1.64 | F11: 1.64 | G11: [A] PO basic rate Rs.16.40 mn (CLW, BLW), Rs.16.50 mn (PLW); book average Rs.16.34 mn (Pro p.216). Held flat: tenders are fixed-price, L1-set.
A12: Locomotive propulsion revenue | B12: Rs cr | C12: =C8*C11 -> 344.4 | D12: =D8*D11 -> 787.2 | E12: =E8*E11 -> 787.2 | F12: =F8*F11 -> 787.2 | G12: Sets x realisation.
A13: 2. Developmental orders (MEMU, converters)
A14: MEMU 12-car rakes delivered | B14: rakes | C14: 0 | D14: 2 | E14: 4 | F14: 0 | G14: [A] LoA MCF Raebareli 27-Jun-2026, 6 rakes, 24-month delivery (Pro p.217). [M] design 8-10 months + RDSO approval ~3 quarters (call). Phasing [E].
A15: Price per MEMU rake | B15: Rs cr | C15: =86.546/6 -> 14.424333 | D15: =C15 -> 14.424333 | E15: =D15 -> 14.424333 | F15: =E15 -> 14.424333 | G15: [A] Rs.865.46 mn / 6 rakes (Pro p.217).
A16: MEMU revenue | B16: Rs cr | C16: =C14*C15 -> 0 | D16: =D14*D15 -> 28.848667 | E16: =E14*E15 -> 57.697333 | F16: =F14*F15 -> 0
A17: Composite converter + hotel load converter | B17: Rs cr | C17: 0 | D17: 3.311 | E17: 0 | F17: 0 | G17: [A] CLW Rs.25.11 mn (10-Sep-2025) + BLW Rs.8.00 mn (14-Nov-2025) (Pro p.217); delivery after RDSO trials [E].
A18: 3. Other revenue
A19: AMC on delivered sets | B19: Rs cr | C19: 0 | D19: 0 | E19: 0 | F19: 0 | G19: [A] Warranty 72 months from delivery or 60 months from commissioning, whichever earlier (Pro p.61). AMC (Rs.1.2 mn per set over 3 yrs) starts ~FY32: zero in this horizon.
A20: Fault locators (OHE, with PNC) | B20: Rs cr | C20: 0 | D20: 0 | E20: 0 | F20: 0 | G20: [M] "very hopeful" of tender wins (call); no order disclosed. Zero until an order is filed.
A21: Legacy lines growth | B21: % | C21: 0 | D21: 0 | E21: 0 | F21: 0 | G21: [E] No guidance. FY26 Rs.44.7 cr after a 29% fall; cable lines moving to Unit 2. Held flat.
A22: Legacy revenue (conduits, harnesses, panels) | B22: Rs cr | C22: =SUM(Segments!C4:C6)*(1+C21) -> 44.72 | D22: =C22*(1+D21) -> 44.72 | E22: =D22*(1+E21) -> 44.72 | F22: =E22*(1+F21) -> 44.72 | G22: FY26 base Rs.44.72 cr (AR26 note 39).
A23: Total revenue from operations | B23: Rs cr | C23: =C12+C16+C17+C19+C20+C22 -> 389.12 | D23: =D12+D16+D17+D19+D20+D22 -> 864.07967 | E23: =E12+E16+E17+E19+E20+E22 -> 889.61733 | F23: =F12+F16+F17+F19+F20+F22 -> 831.92
A24: Management revenue guidance | B24: Rs cr | C24: 400 | G24: [M] "This year we are targeting to achieve INR400 crores" (call). FY28: "~INR70-odd crores" a month at 40 sets (call) = ~Rs.840 cr.
A25: Model vs guidance | B25: % | C25: =C23/C24-1 -> -0.0272
A26: 4. Costs
A27: Material cost, propulsion and developmental | B27: % of rev | C27: 0.85 | D27: 0.77 | E27: 0.77 | F27: 0.77 | G27: [A/E] Prospectus working-capital plan implies ~87% FY27 / ~82% FY28 (Pro p.133); [M] "10%+ PAT" at run-rate implies ~77%; 1QFY27 actual gross margin 8.8% (PPT p.21). Management case uses 77% from FY28.
A28: Material cost, legacy lines | B28: % of rev | C28: 0.6 | D28: 0.6 | E28: 0.6 | F28: 0.6 | G28: [A] FY25 gross margin 40.5% (PPT p.22) when legacy was ~100% of sales.
A29: Material cost | B29: Rs cr | C29: =C27*(C12+C16+C17)+C28*C22 -> 319.572 | D29: =D27*(D12+D16+D17)+D28*D22 -> 657.73894 | E29: =E27*(E12+E16+E17)+E28*E22 -> 677.40295 | F29: =F27*(F12+F16+F17)+F28*F22 -> 632.976
A30: Employee cost | B30: Rs cr | C30: 22 | D30: 30 | E30: 33 | F30: 36 | G30: [A] FY26 Rs.13.8 cr; 1QFY27 Rs.4.35 cr (Res). [E] FY27 = Q1 run-rate + second shift; FY28 two shifts in two units + R&D team expansion (call).
A31: Other expenses, fixed part | B31: Rs cr | C31: 12 | D31: 13 | E31: 14 | F31: 15 | G31: [A] FY26 other expenses Rs.11.1 cr; 1QFY27 Rs.2.2 cr (Res). [E] grows ~8-10% a year. Includes R&D consumables (mgmt R&D ~Rs.9 cr a year, call).
A32: Other expenses, variable part | B32: % of rev | C32: 0.03 | D32: 0.03 | E32: 0.03 | F32: 0.03 | G32: [E] Freight, warranty provision, liquidated damages, power.
A33: Other expenses | B33: Rs cr | C33: =C31+C32*C23 -> 23.6736 | D33: =D31+D32*D23 -> 38.92239 | E33: =E31+E32*E23 -> 40.68852 | F33: =F31+F32*F23 -> 39.9576
A34: 5. Capex, financing, tax
A35: Capex | B35: Rs cr | C35: 15 | D35: 10 | E35: 10 | F35: 12 | G35: [M] "No capex required on machinery ... only ... testing" (call); [A] 2 test set-ups ordered, Unit 2 shift (PPT p.15). [E] amounts.
A36: Depreciation, % of average gross block | B36: % | C36: 0.12 | D36: 0.12 | E36: 0.12 | F36: 0.12 | G36: [E] Calibrated to 1QFY27 depreciation Rs.1.51 cr x 4 = Rs.6.0 cr (Res).
A37: Interest rate on opening debt | B37: % | C37: 0.1 | D37: 0.1 | E37: 0.1 | F37: 0.1 | G37: [A] Bajaj Finance 9.5% floating (AR26 note 13); cash credit ~10%. Debt held flat at FY26 level.
A38: Yield on cash | B38: % | C38: 0.065 | D38: 0.065 | E38: 0.065 | F38: 0.065 | G38: [E] Fixed deposits. FY27: half the net IPO cash assumed earning for the year.
A39: Tax rate | B39: % | C39: 0.2517 | D39: 0.2517 | E39: 0.2517 | F39: 0.2517 | G39: [A] Section 115BAA rate 25.17%.
A40: IPO gross proceeds | B40: Rs cr | C40: 290 | G40: [A] 68,23,528 shares at Rs.425 (Pro p.124).
A41: IPO expenses | B41: Rs cr | C41: 35.541 | G41: [A] Total estimated issue expenses Rs.355.41 mn; net proceeds Rs.2,544.59 mn (Pro p.124, break-up p.142-143). Charged to securities premium.
A42: New shares issued | B42: crore | C42: 0.6823528 | G42: [A] 68,23,528 shares, FV Rs.5.
A43: Face value | B43: Rs | C43: 5 | G43: [A]
A44: 6. Working capital (prospectus plan, board-approved 23-Jul-2026)
A45: Inventory | B45: days of material cost | C45: 105 | D45: 105 | E45: 105 | F45: 105 | G45: [A] Pro p.133-137: 105 days of cost of goods sold for FY27 and FY28.
A46: Trade receivables | B46: days of revenue | C46: 60 | D46: 60 | E46: 60 | F46: 60 | G46: [A] Pro p.133-137: 60 days. [M] last three dispatches paid within ~15 days (call).
A47: Trade payables | B47: days of material cost | C47: 45 | D47: 45 | E47: 45 | F47: 45 | G47: [A] Derived from the FY27 projection table: payables Rs.519.19 mn on implied COGS Rs.4,211 mn (Pro p.133).
A48: Advances to suppliers and other current assets | B48: days of revenue | C48: 10 | D48: 10 | E48: 10 | F48: 10 | G48: [A] Pro p.133: other financial assets 5 days + other current assets 5 days.
A49: Other current liabilities | B49: days of revenue | C49: 19 | D49: 19 | E49: 19 | F49: 19 | G49: [A] Pro p.133: other financial liabilities 13 + other current liabilities 1 + tax 5 days.
A51: 7. FY27 delivery ramp (sets)
A52: Quarter | C52: Sets | G52: Basis
A53: 1QFY27 (Apr-Jun) | C53: 5 | G53: [E] 9 delivered to 30-Jun-2026 (Pro p.216) less prototype and FY26's 3.
A54: 2QFY27 (Jul-Sep) | C54: 15 | G54: [M] "September ... just 10" (call) plus a few in Jul-Aug.
A55: 3QFY27 (Oct-Dec) | C55: 70 | G55: [M] "~70 propulsion sets by Q3FY27" (PPT p.16); 25 in November (call).
A56: 4QFY27 (Jan-Mar) | C56: 120 | G56: [M] "40 in the month of January" and steady thereafter (call).

Sheet TAM
A1: Total addressable market (TAM), Rs. crore per year - rough first cut, 25-Oct-2026
A2: Built from the customer's own numbers (Indian Railways production and orders) where they exist; management unit prices from the 27-Aug-2026 call; [E] marks analyst placeholders to be replaced. Blue = input, black = formula, yellow = the base assumption that matters most.
A4: Segment | B4: MV status today | C4: Unit | D4: Units/yr Low | E4: Base | F4: High | G4: Rs cr per unit | H4: TAM Low | I4: TAM Base | J4: TAM High | K4: Tag | L4: Basis and source
A5: A. Addressable now - MV is an approved supplier
A6: Locomotive propulsion, new build (CLW, BLW, PLW) | B6: Approved Sep-2025; 564 sets in hand; won 27% of FY26 tenders | C6: Sets tendered per year | D6: 1500 | E6: 1659 | F6: 1900 | G6: 1.64 | H6: =IF(OR(D6="",G6=""),"n.s.",D6*G6) -> 2460 | I6: =IF(OR(E6="",G6=""),"n.s.",E6*G6) -> 2720.76 | J6: =IF(OR(F6="",G6=""),"n.s.",F6*G6) -> 3116 | K6: A / S | L6: Base = sets tendered by the three railway loco works for FY26 (Prospectus p.126: programme 1,700, tendered 1,659). FY26 output ~1,700 (BLW 572 PTI 31-Mar-26; CLW incl. Dankuni 800 Rail Analysis; PLW programme 325). High = output keeps rising; Low = FY27 programme cut (one BLW FY27 target report says 468 vs 572 built). Price = PO basic rate ex GST (Pro p.26).
A7: Locomotive propulsion, maintenance contracts (AMC) - steady state | B7: Bundled in every PO; starts after warranty | C7: Locos under AMC per year x 3-yr fee | D7: 1500 | E7: 1659 | F7: 1900 | G7: =0.1225 -> 0.1225 | H7: =IF(OR(D7="",G7=""),"n.s.",D7*G7) -> 183.75 | I7: =IF(OR(E7="",G7=""),"n.s.",E7*G7) -> 203.2275 | J7: =IF(OR(F7="",G7=""),"n.s.",F7*G7) -> 232.75 | K7: A / E | L7: Each PO carries a 3-year AMC worth Rs.12.3 lakh per set (Pro p.26: Rs.551.22 mn / 450 sets). Steady state, three cohorts are under AMC at once, so annual AMC pool = one year's sets x full 3-yr fee. Warranty length not disclosed, so timing of first AMC revenue unknown.
A8: Coach electricals: conduits, harnesses, switchgear panels | B8: MV's legacy line; Rs.44.7 cr FY26 | C8: - | H8: =IF(OR(D8="",G8=""),"n.s.",D8*G8) -> n.s. | I8: =IF(OR(E8="",G8=""),"n.s.",E8*G8) -> n.s. | J8: =IF(OR(F8="",G8=""),"n.s.",F8*G8) -> n.s. | K8: n.s. | L8: Not sized: no disclosure of content per coach or the competitor set. MV FY26 revenue Rs.44.7 cr (AR26 note 39) is the only hard number; utilisation fell to 46-71% on conduit lines in FY26 (Pro p.245).
A9: B. Addressable now by tender, no order yet
A10: Automatic fault locators for 25 kV overhead lines (with PNC Technologies, Korea) | B10: 3-yr exclusive tie-up Aug-2025; bids submitted, no win disclosed | C10: Traction-substation spans per year | D10: =E22*0.7 -> 181.18333 | E10: =E22 -> 258.83333 | F10: =E22*1.4 -> 362.36667 | G10: =E21 -> 0.82344828 | H10: =IF(OR(D10="",G10=""),"n.s.",D10*G10) -> 149.1951 | I10: =IF(OR(E10="",G10=""),"n.s.",E10*G10) -> 213.13586 | J10: =IF(OR(F10="",G10=""),"n.s.",F10*G10) -> 298.39021 | K10: E / M | L10: Stock of ~1,550 substation spans (helper block below) rolled out over 5-7 years per management, priced at Rs.36/24/12 lakh per substation / sectioning / sub-sectioning locator (call 27-Aug-26). Likely partly a replacement market: fault locators already exist on many sections. High uncertainty.
A11: C. Needs a new approval (12-24 months)
A12: EMU / MEMU propulsion (12-car rakes) | B12: One developmental order: 6 MEMU rakes, MCF Raebareli, Rs.86.5 cr; RDSO approval ~15-16 months away | C12: Rakes per year | D12: 80 | E12: 120 | F12: 250 | G12: =86.546/6 -> 14.424333 | H12: =IF(OR(D12="",G12=""),"n.s.",D12*G12) -> 1153.9467 | I12: =IF(OR(E12="",G12=""),"n.s.",E12*G12) -> 1730.92 | J12: =IF(OR(F12="",G12=""),"n.s.",F12*G12) -> 3606.0833 | K12: A / S / M | L12: Price from the MCF LoA (Pro p.25): Rs.86.5 cr for 6 rakes = Rs.14.4 cr per rake (mgmt: ~Rs.16 cr incl. electrics). Units: 238 AC EMU rakes for Mumbai 2027-2030 (~60/yr, Statesman) plus other EMU/MEMU; mgmt says 300-500 EMUs tendered this year - unclear if rakes or cars, so used only as the high case.
A13: D. Long-dated: incumbent OEMs, bundled supply or no programme yet
A14: Vande Bharat trainset propulsion and electrics (16-car) | B14: No order, no approval; same distributed-traction platform as EMU | C14: Rakes per year | D14: 30 | E14: 60 | F14: 120 | G14: 40 | H14: =IF(OR(D14="",G14=""),"n.s.",D14*G14) -> 1200 | I14: =IF(OR(E14="",G14=""),"n.s.",E14*G14) -> 2400 | J14: =IF(OR(F14="",G14=""),"n.s.",F14*G14) -> 4800 | K14: S / M | L14: Price: mgmt Rs.~40 cr per 16-car rake incl. associated electrics (call). Units: ~100 Vande Bharat-platform trains built by end-2025 since 2019 (~15/yr actual); plan of 3,200 coaches for 2025-27 (~100 rakes/yr, Swarajya); 1,300 rakes sanctioned in the Rolling Stock Programme 2026-27 (Pro p.193). Base 60 = between history and plan. Much of new-generation Vande Bharat is awarded to OEM consortia that bring their own propulsion.
A15: Metro propulsion | B15: No product; metro OEMs (Alstom, BEML, Titagarh, Hitachi) bundle propulsion | C15: - | H15: =IF(OR(D15="",G15=""),"n.s.",D15*G15) -> n.s. | I15: =IF(OR(E15="",G15=""),"n.s.",E15*G15) -> n.s. | J15: =IF(OR(F15="",G15=""),"n.s.",F15*G15) -> n.s. | K15: n.s. | L15: Not sized: no national metro-car demand figure found. CareEdge (Pro p.200) puts metro + Vande Bharat + Amrit Bharat propulsion at ~USD 114 mn in CY25, i.e. ~Rs.970 cr - lower than the Vande Bharat row above because actual Vande Bharat output so far is far below plan.
A16: Locomotive propulsion retrofit (GTO-era three-phase fleet) | B16: Mentioned by mgmt; no tender or RDSO programme found | C16: Sets per year | D16: 0 | E16: 100 | F16: 200 | G16: 1.2 | H16: =IF(OR(D16="",G16=""),"n.s.",D16*G16) -> 0 | I16: =IF(OR(E16="",G16=""),"n.s.",E16*G16) -> 120 | J16: =IF(OR(F16="",G16=""),"n.s.",F16*G16) -> 240 | K16: E | L16: PLACEHOLDER. Early WAG-9/WAP-5/WAP-7 units carry GTO converters (Wikipedia; first IGBT WAG-9 was no. 31248). No retrofit tender or count of GTO units found. 100 sets/yr at Rs.1.2 cr (converters only) is a guess to be replaced; excluded from every case total.
A17: Rest of the integrated propulsion kit (traction motors, transformer, bogies) for loco tenders | B17: MV makes none of these; Korean motor partner (Hansung) mentioned | C17: Implied from CareEdge loco market | E17: =E25 -> 4032.49 | G17: =1 -> 1 | H17: =IF(OR(D17="",G17=""),"n.s.",D17*G17) -> n.s. | I17: =IF(OR(E17="",G17=""),"n.s.",E17*G17) -> 4032.49 | J17: =IF(OR(F17="",G17=""),"n.s.",F17*G17) -> n.s. | K17: S / E | L17: Railway Board directive Mar-2025: loco works to buy an integrated propulsion kit (Pro p.54, risk factor 27; p.226). CareEdge loco propulsion market USD 794.5 mn CY25 (~Rs.6,750 cr) vs ~Rs.2,720 cr for MV-type electronics bottom-up; the gap (~Rs.4,000 cr) is roughly the rest of the kit plus non-railway-works locos (Siemens 9,000 HP, Alstom 12,000 HP). Addressable only with partners.
A18: TOTALS
A19: 1. Addressable today: approved product + open tenders (rows 6, 7, 10) | H19: =H6+H7+H10 -> 2792.9451 | I19: =I6+I7+I10 -> 3137.1234 | J19: =J6+J7+J10 -> 3647.1402 | L19: Excludes coach electricals and metro (not sized), the retrofit placeholder, and the rest of the kit (row 17, partners only).
A20: 2. Plus EMU/MEMU and Vande Bharat once approved (rows 12, 14) | H20: =H19+H12+H14 -> 5146.8918 | I20: =I19+I12+I14 -> 7268.0434 | J20: =J19+J12+J14 -> 12053.224
A21: Helper: fault-locator value per substation span, Rs cr | E21: =(36+E26*24+E27*12)/100 -> 0.82344828
A22: Helper: substation spans rolled out per year | E22: =E23/E24 -> 258.83333
A23: Electrified route km / substation spacing (km) = substation spans | E23: =ROUND(E28/E29,0) -> 1553
A24: Roll-out period, years (mgmt: 5-7) | E24: 6
A25: Helper: CareEdge loco propulsion market, Rs cr, less MV-type electronics base TAM | E25: =E30*E31/10-I6 -> 4032.49
A26: Sectioning posts per substation (Prayagraj division: 33 / 29) | E26: =33/29 -> 1.137931
A27: Sub-sectioning posts per substation (Prayagraj division: 46 / 29) | E27: =46/29 -> 1.5862069
A28: Electrified broad-gauge route km (Pro p.196) | E28: 69873
A29: Average substation spacing, km (Western Railway TRD: 35-50) | E29: 45
A30: CareEdge India loco propulsion market CY25, USD mn (Pro p.200) | E30: 794.5
A31: USD/INR | E31: 85
A33: What locomotive propulsion alone is worth to MV at different shares (base TAM, row 6)
A34: Share of sets tendered | D34: Sets per year | E34: Revenue Rs cr | F34: x FY26 revenue
A35: 0.15 | D35: =ROUND(A35*$E$6,0) -> 249 | E35: =D35*$G$6 -> 408.36 | F35: =E35/'P&L'!H3 -> 8.261714
A36: 0.2 | D36: =ROUND(A36*$E$6,0) -> 332 | E36: =D36*$G$6 -> 544.48 | F36: =E36/'P&L'!H3 -> 11.015619
A37: 0.25 | D37: =ROUND(A37*$E$6,0) -> 415 | E37: =D37*$G$6 -> 680.6 | F37: =E37/'P&L'!H3 -> 13.769523
A38: 0.271 | D38: =ROUND(A38*$E$6,0) -> 450 | E38: =D38*$G$6 -> 738 | F38: =E38/'P&L'!H3 -> 14.930808 | G38: <- FY26 actual share (450 / 1,659)
A39: 0.3 | D39: =ROUND(A39*$E$6,0) -> 498 | E39: =D39*$G$6 -> 816.72 | F39: =E39/'P&L'!H3 -> 16.523428
A41: Read-across: management's 40 sets a month = 480 sets = 29% of base tenders; today MV earns Rs.49 cr against a Rs.~2,900 cr pool it is approved for.

Sheet Quarterly
A1: Quarterly P&L, standalone (Rs. crore). Only three quarters are public: the company listed on 6-Aug-2026. Source: Q1FY27 results filing 25-Aug-2026 (ACE quarterly dump has Q1FY26 and Q1FY27 only). Periods verified from the results table header ("Quarter ended 30-06-2026").
A2: Rs. crore | B2: 1QFY26 | C2: 4QFY26 | D2: 1QFY27
A3: Revenue from operations | B3: 13.448 | C3: 14.933 | D3: 12.771
A4: Other income | B4: 0.065 | C4: 0.121 | D4: 0.026
A5: Raw material consumed | B5: 8.977 | C5: 14.275 | D5: 12.326
A6: Change in inventories | B6: 3.458 | C6: -0.451 | D6: -0.682
A7: Employee cost | B7: 2.501 | C7: 3.794 | D7: 4.347
A8: Other expenses | B8: 2.002 | C8: 3.166 | D8: 2.155
A9: EBITDA | B9: =B3-B5-B6-B7-B8 -> -3.49 | C9: =C3-C5-C6-C7-C8 -> -5.851 | D9: =D3-D5-D6-D7-D8 -> -5.375
A10: EBITDA margin | B10: =B9/B3 -> -0.25951814 | C10: =C9/C3 -> -0.39181678 | D10: =D9/D3 -> -0.42087542
A11: Depreciation | B11: 0.743 | C11: 1.063 | D11: 1.512
A12: Finance cost | B12: 0.762 | C12: 1.133 | D12: 1.178
A13: PBT | B13: =B9+B4-B11-B12 -> -4.93 | C13: =C9+C4-C11-C12 -> -7.926 | D13: =D9+D4-D11-D12 -> -8.039
A14: Tax | B14: 0.804 | C14: -5.014 | D14: -1.152
A15: PAT | B15: =B13-B14 -> -5.734 | C15: =C13-C14 -> -2.912 | D15: =D13-D14 -> -6.887
A16: PAT margin | B16: =B15/B3 -> -0.42638311 | C16: =C15/C3 -> -0.19500435 | D16: =D15/D3 -> -0.53926866
A17: Reported PAT (check) | B17: -5.733 | C17: -2.913 | D17: -6.886
A18: CHECK | B18: =B15-B17 -> -0.001 | C18: =C15-C17 -> 0.001 | D18: =D15-D17 -> -0.001
A20: Propulsion sets delivered in quarter (mgmt: 3 sets in FY26, "2-3 small batches" by Aug-26; Sep-26 target 10, Nov 25, Jan-27 40/month) [M]
A21: R&D expense inside opex: ~Rs.2 cr in 1QFY27; Rs.7.9 cr in FY26 (16% of revenue); not capitalised [M, PPT p.14/21; call]

Sheet Segments
A1: Revenue by product group (Rs. crore). One Ind AS 108 segment; split per AR FY26 note 39 [A]. FY27E-FY30E from the Drivers sheet (management guidance case); legacy lines split by FY26 mix.
A3: Rs. crore | B3: FY25A | C3: FY26A | D3: FY27E | E3: FY28E | F3: FY29E | G3: FY30E
A4: Cable protection, interconnect, switchgear & panels - Indian Railways | B4: 45.7 | C4: 33.214 | D4: =Drivers!C22*$C4/SUM($C$4:$C$6) -> 33.214 | E4: =Drivers!D22*$C4/SUM($C$4:$C$6) -> 33.214 | F4: =Drivers!E22*$C4/SUM($C$4:$C$6) -> 33.214 | G4: =Drivers!F22*$C4/SUM($C$4:$C$6) -> 33.214
A5: Cable protection, interconnect, switchgear & panels - private sector | B5: 16.486 | C5: 7.879 | D5: =Drivers!C22*$C5/SUM($C$4:$C$6) -> 7.879 | E5: =Drivers!D22*$C5/SUM($C$4:$C$6) -> 7.879 | F5: =Drivers!E22*$C5/SUM($C$4:$C$6) -> 7.879 | G5: =Drivers!F22*$C5/SUM($C$4:$C$6) -> 7.879
A6: Cable protection, interconnect, switchgear & panels - group companies | B6: 0.45 | C6: 3.627 | D6: =Drivers!C22*$C6/SUM($C$4:$C$6) -> 3.627 | E6: =Drivers!D22*$C6/SUM($C$4:$C$6) -> 3.627 | F6: =Drivers!E22*$C6/SUM($C$4:$C$6) -> 3.627 | G6: =Drivers!F22*$C6/SUM($C$4:$C$6) -> 3.627
A7: Rolling stock electrics & propulsion - Indian Railways (forecast incl. MEMU, converters, AMC, fault locators) | B7: 0 | C7: 4.708 | D7: =Drivers!C12+Drivers!C16+Drivers!C17+Drivers!C19+Drivers!C20 -> 344.4 | E7: =Drivers!D12+Drivers!D16+Drivers!D17+Drivers!D19+Drivers!D20 -> 819.35967 | F7: =Drivers!E12+Drivers!E16+Drivers!E17+Drivers!E19+Drivers!E20 -> 844.89733 | G7: =Drivers!F12+Drivers!F16+Drivers!F17+Drivers!F19+Drivers!F20 -> 787.2
A8: Total revenue from operations | B8: =SUM(B4:B7) -> 62.636 | C8: =SUM(C4:C7) -> 49.428 | D8: =SUM(D4:D7) -> 389.12 | E8: =SUM(E4:E7) -> 864.07967 | F8: =SUM(F4:F7) -> 889.61733 | G8: =SUM(G4:G7) -> 831.92
A9: Check vs P&L | B9: =B8-'P&L'!G3 -> -0.001 | C9: =C8-'P&L'!H3 -> 0
A10: Propulsion share of revenue | B10: =B7/B8 -> 0 | C10: =C7/C8 -> 0.095249656 | D10: =D7/D8 -> 0.88507401 | E10: =E7/E8 -> 0.94824551 | F10: =F7/F8 -> 0.9497312 | G10: =G7/G8 -> 0.94624483
A11: Legacy lines YoY | C11: =SUM(C4:C6)/SUM(B4:B6)-1 -> -0.28603359
A13: Order book, 3-phase propulsion (as on 30-Jun-2026) [A: prospectus p.23, 25-26, 126; PPT p.16]
A14: Customer / order | B14: PO date | C14: Sets | D14: Rate per set (Rs. cr, ex GST) | E14: Equipment value (Rs. cr) | F14: AMC 3 yrs (Rs. cr) | G14: Total (Rs. cr)
A15: CLW (Chittaranjan) | B15: 24-Dec-2025 | C15: 200 | D15: 1.64 | E15: =C15*D15 -> 328 | F15: 24.6 | G15: =E15+F15 -> 352.6
A16: BLW (Banaras) | B16: 09-Jan-2026 | C16: 161 | D16: 1.64 | E16: =C16*D16 -> 264.04 | F16: 19.803 | G16: =E16+F16 -> 283.843
A17: PLW (Patiala) | B17: 16-Jan-2026 | C17: 76 | D17: 1.65 | E17: =C17*D17 -> 125.4 | F17: 9.12 | G17: =E17+F17 -> 134.52
A18: BLW (Banaras) | B18: 27-Jan-2026 | C18: 13 | D18: 1.64 | E18: =C18*D18 -> 21.32 | F18: 1.599 | G18: =E18+F18 -> 22.919
A19: Earlier developmental / other POs (balance to 564 sets) | B19: FY25-FY26 | C19: 114 | D19: =E19/C19 -> 1.6042105 | E19: =921.64-SUM(E15:E18) -> 182.88 | F19: =67.678-SUM(F15:F18) -> 12.556 | G19: =E19+F19 -> 195.436
A20: Total executable propulsion order book | C20: =SUM(C15:C19) -> 564 | E20: =SUM(E15:E19) -> 921.64 | F20: =SUM(F15:F19) -> 67.678 | G20: =SUM(G15:G19) -> 989.318
A21: Developmental: MEMU 6 rakes (MCF Raebareli LoA 27-Jun-2026, 24-month delivery) + composite converter + hotel load converter | C21: 8 | E21: 89.86 | F21: 4.87 | G21: =E21+F21 -> 94.73
A22: Other orders in hand: cable management & control panels (approx.) [M] | E22: 20 | G22: =E22 -> 20
A23: Total orders in hand | E23: =E20+E21+E22 -> 1031.5 | G23: =G20+G21+G22 -> 1104.048
A24: Order book / FY26 revenue (x) | E24: =E23/'P&L'!H3 -> 20.868738
A25: FY26 tender share: 450 of 1,659 sets tendered by CLW/BLW/PLW = 27.1% [A: prospectus p.126]
A27: Capacity (single shift, chartered engineer certificate 7-Jul-2026) [A: prospectus p.245; PPT p.15]
A28: Product | B28: Unit | C28: Installed capacity | D28: FY24 production | E28: FY25 production | F28: FY26 production | G28: FY26 utilisation
A29: Switchboard cabinet panels | B29: nos | C29: 1650 | D29: 1650 | E29: 1623 | F29: 1650 | G29: =F29/C29 -> 1
A30: Cable protection conduit tubing | B30: metres | C30: 1950000 | D30: 1500000 | E30: 1650000 | F30: 900700 | G30: =F30/C30 -> 0.46189744
A31: Conduit end fittings | B31: nos | C31: 225000 | D31: 185000 | E31: 210000 | F31: 114632 | G31: =F31/C31 -> 0.50947556
A32: Expandable cable jackets | B32: metres | C32: 660000 | D32: 580000 | E32: 570000 | F32: 472000 | G32: =F32/C32 -> 0.71515152
A33: Propulsion systems, Unit 1 | B33: sets | C33: 114 | D33: 0 | E33: 0 | F33: 3 | G33: =F33/C33 -> 0.026315789
A34: Propulsion systems, Unit 2 (consent to operate Jun-2026; certified 171 sets/yr) - combined 285/yr single shift; mgmt says up to 55/month with two shifts [M]
A35: Mgmt delivery plan [M, call 27-Aug-26]: ~10 sets Sep-26, ~25 Nov-26, ~40/month from Jan-27; ~70 sets by 3QFY27; FY27 revenue target Rs.400 cr; PAT 10%+ at run-rate; R&D ~Rs.9 cr/yr

Sheet Valuations
B2: CMP (Rs.) - NSE close 22-Oct-2026 [S]; replace with Bloomberg CMP and date | C2: 788
B3: No. of shares, crore (post-IPO: 2,04,59,200 + 68,23,528) [A] | C3: 2.7283
B4: Market Cap (Rs. crore) | C4: =C2*C3 -> 2149.9004
B5: IPO price (Rs.), 6-Aug-2026 listing | C5: 425
B6: Pre-IPO placement price, Oct-2025 (Rs.547 FV10 = Rs.273.5 FV5) [A] | C6: 273.5
B7: Net debt at FY26 end (Rs. crore) [A] | C7: ='P&L'!H180 -> 49.715
B8: IPO gross proceeds (Rs. crore) [A] | C8: 290
B9: IPO expenses (Rs. crore) [A] Pro p.124, 142-143 | C9: =Drivers!C41 -> 35.541
B10: Pro-forma net cash post-IPO before FY27 working-capital build (Rs. crore) | C10: =C8-C9-C7 -> 204.744
B11: Pro-forma EV at CMP (Rs. crore) | C11: =C4-C10 -> 1945.1564
B13: What the price implies - trailing (FY26A)
B14: EV / FY26A sales | C14: =C11/'P&L'!H3 -> 39.35333
B15: Price / post-money book (NAV Rs.129.2/sh at issue price, prospectus p.149) | C15: =C2/129.23 -> 6.0976553
B16: P/E FY26A | C16: n.m. (loss)
B18: What the price implies - on management guidance (NOT a base case; base case = committed only, built in v2)
B19: Sets per month at run-rate [M] | C19: 40
B20: Realisation per set, Rs. crore ex GST [A: PO rates] | C20: 1.64
B21: Propulsion revenue at run-rate, annualised (Rs. crore) | C21: =C19*12*C20 -> 787.2
B22: Legacy lines revenue, FY26 level (Rs. crore) | C22: =SUM(Segments!C4:C6) -> 44.72
B23: Implied annual revenue at run-rate (Rs. crore) | C23: =C21+C22 -> 831.92
B24: PAT margin guided [M] | C24: 0.1
B25: Implied PAT at run-rate (Rs. crore) | C25: =C23*C24 -> 83.192
B26: P/E on run-rate PAT at CMP | C26: =C4/C25 -> 25.842634
B27: Sets needed per year to hold the run-rate | C27: =C19*12 -> 480
B28: Executable order book (sets) / sets per year = months of cover at run-rate | C28: =Segments!C20/C27*12 -> 14.1
B29: FY26 tender share won (sets) vs sets needed per year | C29: =450/C27 -> 0.9375
B31: v2: primary method (P/E on FY28E, EPC/capital-goods engine: order book x execution + new orders), EV/EBITDA cross-check, reverse DCF; bull/base/bear; net debt from year before valuation year.

Sheet Sources
A1: Tag key | B1: [A] audited / statutory filing; [M] management statement (PPT, call, directors report); [S] secondary (NSE price, ACE); [E] analyst estimate
A2: ACE dump | B2: MV_Ace_Data_Dump.xlsx - P&L, BS, CF (standalone, FY23-FY26), quarterly (Jun-25, Jun-26). Used as the base for FY23-FY26.
A3: Audited AR FY26 | B3: Annual Report 2025-26 (filed NSE 3-Sep-2026): P&L p.59, BS, CF, notes 7 (receivables), 10 (other current assets), 13 (borrowings), 24-27 (expenses), 33 (related parties), 34 (contingent), 39 (revenue disaggregation). Auditor Sanmarks & Associates, unmodified opinion, emphasis of matter on MSME interest not provided; CARO: no internal audit system in FY26.
A4: Prospectus | B4: Prospectus dated 3-Aug-2026 (SEBI / company website): capital history p.104-106, 153; customers p.22, 218; order book p.23-26, 126, 216; capacity p.245; purchase orders p.26; working-capital plan p.133; LD terms p.31; contingent liabilities p.85; related parties p.86; KPIs and peers p.148-153; competition p.246.
A5: Q1FY27 results | B5: Outcome of board meeting 25-Aug-2026: standalone unaudited results for quarter ended 30-Jun-2026 with comparatives 4QFY26 and 1QFY26 (Rs. million).
A6: Q1FY27 PPT / call | B6: Investor presentation filed 26-Aug-2026; earnings call 27-Aug-2026 transcript filed 1-Sep-2026.
A7: Pre-listing audited statements | B7: Company website: FY2020-21 (Jugal Arora & Co, signed 19-Oct-2021; comparatives give FY20) and FY2021-22 (signed 5-Sep-2022), Indian GAAP, scanned; read from rendered pages. Headline rows only.
A8: Market data | B8: NSE historical closes 5-Aug-2026 to 22-Oct-2026 (secondary). Bloomberg CMP to be supplied by the investor with date.
A9: Conflicts resolved | B9: 1) ACE FY25/FY26 employee cost and interest differ from audited AR (ACE 9.48/13.14 vs AR 9.57/13.76 employee; ACE 3.55/4.14 vs AR 3.04/3.49 interest). PBT and PAT tie. Audited used; EBITDA FY26 = -10.3 (audited) vs -9.7 (ACE). 2) ACE "Assets in transit" Rs.10.5 cr is Investment property per AR. 3) PPT covering letter says "standalone & consolidated"; there is no consolidation. 4) Prospectus top-customer table: FY26 76.72% vs AR note 39 Indian Railways 67.20%+9.53% = 76.73% - consistent. 5) Share count: PPT shows 2.73 cr and Mcap Rs.1,539 cr at Rs.560.15 (implies 2.75 cr); AR + IPO allotment give 2,72,82,728 - used.
