Workbook
Name \a: #REF!
Name \a: #REF!
Name \b: #REF!
Name \b: #REF!
Name \c: #REF!
Name \c: #REF!
Name \d: #REF!
Name \e: #REF!
Name \F: #REF!
Name \g: #REF!
Name \h: #REF!
Name \i: #REF!
Name \j: #REF!
Name \l: #REF!
Name \M: [1]bajaj_copeland!$D$508
Name \M: #REF!
Name \n: #REF!
Name \o: #REF!
Name \p: #REF!
Name \q: #REF!
Name \r: #REF!
Name \s: #REF!
Name \t: #REF!
Name \u: #REF!
Name \u: [2]Header!#REF!
Name \v: #REF!
Name \VAL: #REF!
Name \w: #REF!
Name \x: #REF!
Name \y: #REF!
Name \z: #REF!
Name __________Less_Misc_expenditure: #REF!
Name __________Reserves_n_surplus: #REF!
Name __________Revaluation_reserves: #REF!
Name ______Current_Year_maturity: #REF!
Name ______Current_Year_maturity: #REF!
Name ______Long_term_borrowings: #REF!
Name ______Long_term_borrowings: #REF!
Name ______Short_term_borrowings: #REF!
Name ______Short_term_borrowings: #REF!
Name ______Trade_Payables: #REF!
Name ______Trade_Payables: #REF!
Name _____Deferred_tax_Assets: #REF!
Name _____Deferred_tax_Assets: #REF!
Name _____Fixed_assets_Net_block: #REF!
Name _____Fixed_assets_Net_block: #REF!
Name _____Goodwill_on_Consolidation: #REF!
Name _____Goodwill_on_Consolidation: #REF!
Name _____Long_Term_loans_and_advances: #REF!
Name _____Non_current_Investments: #REF!
Name _____Other_non_current_assets: #REF!
Name _____Share_Capital: #REF!
Name _____Share_Capital: #REF!
Name ____Minorities_interests_BS: #REF!
Name ____Minorities_interests_BS: #REF!
Name ____Share_application_money_pending_allotment: #REF!
Name ____Share_application_money_pending_allotment: #REF!
Name ____Shareholders_funds: #REF!
Name ____Shareholders_funds: #REF!
Name ___Adjusted_EPS_Rs: #REF!

Sheet Key (2)
B2: Name of Project SPV(s) | C2: Status | D2: State | E2: Type | F2: Capacity (in MW) | G2: Off-taker | H2: Tariff (INR/kWh) | I2: COD | J2: PPA Tenor (years) | K2: LOA
B3: ACME Solar Technologies (Gujarat) Private Limited | C3: Operational | D3: Gujarat | E3: Solar | F3: 15 | G3: GUVNL | H3: 5 | I3: 40969 | J3: 25
B4: ACME Solar Energy MP Private Limited | C4: Operational | D4: Madhya Pradesh | E4: Solar | F4: 25 | G4: MPPMCL | H4: 8.05 | I4: 41670 | J4: 25
B5: ACME Odisha Solar Power Private Limited | C5: Operational | D5: Odisha | E5: Solar | F5: 25 | G5: Off-taker | H5: 7.28 | I5: 42156 | J5: 25
B6: Acme Raipur Solar Power Private Limited | C6: Operational | D6: Chhattisgarh | E6: Solar | F6: 30 | G6: CSPDCL | H6: 6.46 | I6: 42460 | J6: 25
B7: Acme Solar Rooftop Systems Private Limited | C7: Operational | D7: Punjab | E7: Solar | F7: 30 | G7: PSPCL | H7: 7.57 | I7: 42521 | J7: 25
B8: Aarohi Solar Power Private Limited | C8: Operational | D8: Andhra Pradesh | E8: Solar | F8: 50 | G8: APSPDCL | H8: 5.63 | I8: 42460 | J8: 25
B9: Acme Jaisalmer Solar Power Private Limited | C9: Operational | D9: Andhra Pradesh | E9: Solar | F9: 20 | G9: APSPDCL | H9: 5.63 | I9: 42521 | J9: 25
B10: Dayanidhi Solar Power Private Limited | C10: Operational | D10: Andhra Pradesh | E10: Solar | F10: 40 | G10: APSPDCL | H10: 5.97 | I10: 42490 | J10: 25
B11: Niranjana Solar Power Private Limited | C11: Operational | D11: Andhra Pradesh | E11: Solar | F11: 20 | G11: APSPDCL | H11: 5.71 | I11: 42460 | J11: 25
B12: Viswatma Solar Energy Private Limited | C12: Operational | D12: Andhra Pradesh | E12: Solar | F12: 30 | G12: APSPDCL | H12: 5.71 | I12: 42490 | J12: 25
B13: ACME Magadh Solar Power Private Limited | C13: Operational | D13: Bihar | E13: Solar | F13: 10 | G13: SBPDCL and NBPDCL | H13: 8.73 | I13: 42551 | J13: 25
B14: ACME Nalanda Solar Power Private Limited | C14: Operational | D14: Bihar | E14: Solar | F14: 15 | G14: SBPDCL and NBPDCL | H14: 8.73 | I14: 42551 | J14: 25
... B33: Acme Eco Clean Energy Pvt. Ltd. | C33: Operational | D33: Gujarat | E33: Wind | F33: 72 | G33: GUVNL | H33: 3.01 | I33: 45945 | J33: 25
B34: ACME Eco Clean Energy Private Limited | C34: Under Construction | E34: Wind | F34: 28 | G34: GUVNL | H34: 3.01 | I34: 46053 | J34: 25
B35: ACME Surya Power Private Limited | C35: Under Construction | E35: FDRE | F35: 250 | G35: SJVN | H35: 4.38 | I35: 46173 | J35: 25 | K35: 45245
B36: ACME Sun Power Private Limited | C36: Under Construction | E36: FDRE | F36: 320 | G36: SJVN | H36: 4.38 | I36: 46173 | J36: 25 | K36: 45245
B37: ACME Urja One Private Limited | C37: Under Construction | E37: FDRE | F37: 190 | G37: SECI | H37: 4.73 | I37: 46203 | J37: 25 | K37: 45031
B38: ACME Renewtech Private Limited | C38: Under Construction | E38: Hybrid | F38: 300 | G38: NTPC | H38: 3.36 | I38: 46477 | J38: 25 | K38: 45275
B39: ACME Platinum Urja Private Limited | C39: Under Construction | E39: FDRE | F39: 350 | G39: SECI | H39: 3.42 | I39: 46295 | J39: 25 | K39: 45488
B40: Acme Venue Urja Pvt Ltd | C40: Under Construction | E40: FDRE | F40: 400 | G40: NHPC | H40: 4.64 | I40: 46477 | J40: 25 | K40: 45337
B41: ACME Hybrid Urja Private Limited | C41: Under Construction | E41: FDRE | F41: 280 | G41: NHPC | H41: 4.64 | I41: =+K41+30*30 -> 46237 | J41: 25 | K41: 45337
B42: Acme Renewtech Fifth Pvt Ltd | C42: Under Construction | E42: FDRE | F42: 250 | G42: NHPC | H42: 4.56 | I42: 46361 | J42: 25 | K42: 45641
A43: TPDDL, 250 MW, RE with ESS, Pan India, April 2025 | B43: ACME Sigma Urja Private Limited | C43: Under Construction | E43: FDRE | F43: 50 | G43: TPDDL | H43: 4.43 | I43: =+K43+24*30 -> 46604 | J43: 25 | K43: 45884
B44: ACME Urja One Private Limited | C44: Under Construction | E44: FDRE | F44: 250 | G44: NHPC | H44: 4.33 | J44: 25
B45: ACME Greentech Nineth Pvt. Ltd. | C45: Under Construction | E45: BESS | F45: 450 | G45: NHPC | H45: 2.22 lakhs/MW/Month | I45: =+K45+18*30 -> 46363 | J45: 25 | K45: 45823
B46: ACME Greentech Nineth Pvt. Ltd. | C46: Under Construction | E46: BESS | F46: 100 | G46: NHPC | H46: 2.22 lakhs/MW/Month | I46: =+K46+18*30 -> 46363 | J46: 25 | K46: 45823
A47: SECI, 1200 MW, Wind Solar Hybrid with ESS )Tranche VI, Pan India Nov 2022 | B47: Acme Urja One Pvt. Ltd. | C47: L1 | E47: FDRE | F47: 190 | G47: SECI | H47: 4.73 | I47: =+K47+50*30 -> 46531 | K47: 45031
A48: SECI, 1200 MW , ISTS Connected Solar with 600 MW/1200 MWh ESS (ISTS-XV), Pan India, Mar 2024 | B48: ACME Marigold Urja Pvt. Ltd. | C48: L1 | E48: FDRE | F48: 130 | G48: SECI | H48: 4.35 | I48: =+K48+35*30 -> 46538 | K48: 45488
B49: Acme Alpha Renewables Pvt. Ltd. | C49: L1 | E49: Hybrid | F49: 150 | G49: NTPC | H49: 3.32 | I49: =+K49+40*30 -> 46566 | K49: 45366
B50: Acme Omega Urja Pvt. Ltd. | C50: L1 | E50: Solar | F50: 300 | G50: SJVN | H50: 2.52 | I50: =+K50+40*30 -> 46719 | K50: 45519
B51: Acme Renewtech Second Pvt. Ltd. | C51: L1 | E51: Hybrid | F51: 300 | G51: SECI | H51: 3.25 | I51: =+K51+32*30 -> 46540 | K51: 45580
B52: Acme Marigold Urja Pvt. Ltd. | C52: L1 | E52: FDRE | F52: 400 | G52: NTPC | H52: 4.7 | I52: =+K52+36*30 -> 46691 | K52: 45611
A53: https://www.mercomindia.com/acme-and-ceigall-win-rumsls-600-mw-solar-plus-storage-auction | B53: Acme Renewtech Fourth Pvt. Ltd. | C53: L1 | E53: FDRE | F53: 220 | H53: 2.764 | I53: =+K53+36*30 -> 47002 | K53: 45922
A54: SJVN, 6000 MWh, peak power supply from ISTS connected RE Power with ESS, Pan India, Dec 2024 | B54: ACME Greentech Seventh Pvt. Ltd | C54: L1 | E54: FDRE | F54: 450 | G54: SJVN | H54: 6.74 | I54: =+K54+36*30 -> 47025 | K54: 45945
B57: Operational
B58: Solar | C58: =+SUMIFS($F$3:$F$54,$E$3:$E$54,$B58,$C$3:$C$54,$B$57) -> 2840
B59: Wind | C59: =+SUMIFS($F$3:$F$54,$E$3:$E$54,$B59,$C$3:$C$54,$B$57) -> 122
B60: FDRE | C60: =+SUMIFS($F$3:$F$54,$E$3:$E$54,$B60,$C$3:$C$54,$B$57) -> 0
B61: Hybrid | C61: =+SUMIFS($F$3:$F$54,$E$3:$E$54,$B61,$C$3:$C$54,$B$57) -> 0
B62: BESS | C62: =+SUMIFS($F$3:$F$54,$E$3:$E$54,$B62,$C$3:$C$54,$B$57) -> 0
B63: Total | C63: =SUM(C58:C62) -> 2962
B65: Under Construction
B66: Solar | C66: =+SUMIFS($F$3:$F$54,$E$3:$E$54,$B66,$C$3:$C$54,$B$65) -> 0
B67: Wind | C67: =+SUMIFS($F$3:$F$54,$E$3:$E$54,$B67,$C$3:$C$54,$B$65) -> 28
B68: FDRE | C68: =+SUMIFS($F$3:$F$54,$E$3:$E$54,$B68,$C$3:$C$54,$B$65) -> 2340
B69: Hybrid | C69: =+SUMIFS($F$3:$F$54,$E$3:$E$54,$B69,$C$3:$C$54,$B$65) -> 300
B70: BESS | C70: =+SUMIFS($F$3:$F$54,$E$3:$E$54,$B70,$C$3:$C$54,$B$65) -> 550 | D70: Mwh
B71: Total | C71: =SUM(C66:C69) -> 2668 | D71: =+C71-2668 -> 0
B73: L1
B74: Solar | C74: =+SUMIFS($F$3:$F$54,$E$3:$E$54,$B74,$C$3:$C$54,$B$73) -> 300
B75: Wind | C75: =+SUMIFS($F$3:$F$54,$E$3:$E$54,$B75,$C$3:$C$54,$B$73) -> 0
B76: FDRE | C76: =+SUMIFS($F$3:$F$54,$E$3:$E$54,$B76,$C$3:$C$54,$B$73) -> 1390
B77: Hybrid | C77: =+SUMIFS($F$3:$F$54,$E$3:$E$54,$B77,$C$3:$C$54,$B$73) -> 450
B78: BESS | C78: =+SUMIFS($F$3:$F$54,$E$3:$E$54,$B78,$C$3:$C$54,$B$73) -> 0
B79: Total | C79: =SUM(C74:C78) -> 2140
B81: Total | C81: =+C79+C71+C63 -> 7770

Sheet Key_New
A2: # | B2: Project SPV | C2: Status | D2: State | E2: Technology | F2: Capacity (MW) | G2: BESS (MWh) | H2: Off-taker | I2: Off-taker category | J2: Tariff (INR/kWh) | K2: PPA tenor (yrs) | L2: PPA signed | M2: LoA / award date | N2: Company SCOD / guidance | O2: Model COD | P2: COD FY | Q2: Debt tied up | R2: Grid connectivity | S2: Tariff adoption | T2: Company SCOD basis | U2: Notes
A3: 1 | B3: ACME Solar Technologies (Gujarat) Pvt Ltd | C3: Operational | D3: Gujarat | E3: Solar | F3: 15 | H3: GUVNL | I3: =IF($H3="","–",IF($H3="GUVNL","GUVNL",IF(OR($H3="SECI",$H3="NTPC",$H3="SJVN",$H3="NHPC"),"Central","State & Other"))) -> GUVNL | J3: 5 | K3: 25 | L3: Yes | O3: 40999 | P3: =IF($O3="","–",IF(MONTH($O3)<=3,YEAR($O3),YEAR($O3)+1)) -> 2012 | T3: Actual (commissioned) | U3: Tariff INR 15.00/kWh for first 12 years, INR 5.00/kWh for next 13 years
A4: 2 | B4: ACME Solar Energy MP Pvt Ltd | C4: Operational | D4: Madhya Pradesh | E4: Solar | F4: 25 | H4: MPPMCL | I4: =IF($H4="","–",IF($H4="GUVNL","GUVNL",IF(OR($H4="SECI",$H4="NTPC",$H4="SJVN",$H4="NHPC"),"Central","State & Other"))) -> State & Other | J4: 8.05 | K4: 25 | L4: Yes | O4: 41670 | P4: =IF($O4="","–",IF(MONTH($O4)<=3,YEAR($O4),YEAR($O4)+1)) -> 2014 | T4: Actual (commissioned) | U4: Phase I 10 MW Dec-13; Phase II 15 MW Jan-14
A5: 3 | B5: ACME Odisha Solar Power Pvt Ltd | C5: Operational | D5: Odisha | E5: Solar | F5: 25 | H5: GRIDCO | I5: =IF($H5="","–",IF($H5="GUVNL","GUVNL",IF(OR($H5="SECI",$H5="NTPC",$H5="SJVN",$H5="NHPC"),"Central","State & Other"))) -> State & Other | J5: 7.28 | K5: 25 | L5: Yes | O5: 42185 | P5: =IF($O5="","–",IF(MONTH($O5)<=3,YEAR($O5),YEAR($O5)+1)) -> 2016 | T5: Actual (commissioned)
A6: 4 | B6: ACME Raipur Solar Power Pvt Ltd | C6: Operational | D6: Chhattisgarh | E6: Solar | F6: 30 | H6: CSPDCL | I6: =IF($H6="","–",IF($H6="GUVNL","GUVNL",IF(OR($H6="SECI",$H6="NTPC",$H6="SJVN",$H6="NHPC"),"Central","State & Other"))) -> State & Other | J6: 6.46 | K6: 25 | L6: Yes | O6: 42460 | P6: =IF($O6="","–",IF(MONTH($O6)<=3,YEAR($O6),YEAR($O6)+1)) -> 2016 | T6: Actual (commissioned) | U6: Phase I 23 MW Jan-16; Phase II 7 MW Mar-16
A7: 5 | B7: ACME Solar Rooftop Systems Pvt Ltd | C7: Operational | D7: Punjab | E7: Solar | F7: 30 | H7: PSPCL | I7: =IF($H7="","–",IF($H7="GUVNL","GUVNL",IF(OR($H7="SECI",$H7="NTPC",$H7="SJVN",$H7="NHPC"),"Central","State & Other"))) -> State & Other | J7: 7.57 | K7: 25 | L7: Yes | O7: 42521 | P7: =IF($O7="","–",IF(MONTH($O7)<=3,YEAR($O7),YEAR($O7)+1)) -> 2017 | T7: Actual (commissioned)
A8: 6 | B8: Aarohi Solar Power Pvt Ltd | C8: Operational | D8: Andhra Pradesh | E8: Solar | F8: 50 | H8: APSPDCL | I8: =IF($H8="","–",IF($H8="GUVNL","GUVNL",IF(OR($H8="SECI",$H8="NTPC",$H8="SJVN",$H8="NHPC"),"Central","State & Other"))) -> State & Other | J8: 7.35 | K8: 25 | L8: Yes | O8: 42460 | P8: =IF($O8="","–",IF(MONTH($O8)<=3,YEAR($O8),YEAR($O8)+1)) -> 2016 | T8: Actual (commissioned)
A9: 7 | B9: ACME Jaisalmer Solar Power Pvt Ltd | C9: Operational | D9: Andhra Pradesh | E9: Solar | F9: 20 | H9: APSPDCL | I9: =IF($H9="","–",IF($H9="GUVNL","GUVNL",IF(OR($H9="SECI",$H9="NTPC",$H9="SJVN",$H9="NHPC"),"Central","State & Other"))) -> State & Other | J9: 7.35 | K9: 25 | L9: Yes | O9: 42521 | P9: =IF($O9="","–",IF(MONTH($O9)<=3,YEAR($O9),YEAR($O9)+1)) -> 2017 | T9: Actual (commissioned)
A10: 8 | B10: Dayanidhi Solar Power Pvt Ltd | C10: Operational | D10: Andhra Pradesh | E10: Solar | F10: 40 | H10: APSPDCL | I10: =IF($H10="","–",IF($H10="GUVNL","GUVNL",IF(OR($H10="SECI",$H10="NTPC",$H10="SJVN",$H10="NHPC"),"Central","State & Other"))) -> State & Other | J10: 7.79 | K10: 25 | L10: Yes | O10: 42490 | P10: =IF($O10="","–",IF(MONTH($O10)<=3,YEAR($O10),YEAR($O10)+1)) -> 2017 | T10: Actual (commissioned)
A11: 9 | B11: Niranjana Solar Power Pvt Ltd | C11: Operational | D11: Andhra Pradesh | E11: Solar | F11: 20 | H11: APSPDCL | I11: =IF($H11="","–",IF($H11="GUVNL","GUVNL",IF(OR($H11="SECI",$H11="NTPC",$H11="SJVN",$H11="NHPC"),"Central","State & Other"))) -> State & Other | J11: 7.45 | K11: 25 | L11: Yes | O11: 42460 | P11: =IF($O11="","–",IF(MONTH($O11)<=3,YEAR($O11),YEAR($O11)+1)) -> 2016 | T11: Actual (commissioned)
A12: 10 | B12: Viswatma Solar Energy Pvt Ltd | C12: Operational | D12: Andhra Pradesh | E12: Solar | F12: 30 | H12: APSPDCL | I12: =IF($H12="","–",IF($H12="GUVNL","GUVNL",IF(OR($H12="SECI",$H12="NTPC",$H12="SJVN",$H12="NHPC"),"Central","State & Other"))) -> State & Other | J12: 7.45 | K12: 25 | L12: Yes | O12: 42490 | P12: =IF($O12="","–",IF(MONTH($O12)<=3,YEAR($O12),YEAR($O12)+1)) -> 2017 | T12: Actual (commissioned)
A13: 11 | B13: ACME Magadh Solar Power Pvt Ltd | C13: Operational | D13: Bihar | E13: Solar | F13: 10 | H13: SBPDCL & NBPDCL | I13: =IF($H13="","–",IF($H13="GUVNL","GUVNL",IF(OR($H13="SECI",$H13="NTPC",$H13="SJVN",$H13="NHPC"),"Central","State & Other"))) -> State & Other | J13: 8.73 | K13: 25 | L13: Yes | O13: 42551 | P13: =IF($O13="","–",IF(MONTH($O13)<=3,YEAR($O13),YEAR($O13)+1)) -> 2017 | T13: Actual (commissioned)
A14: 12 | B14: ACME Nalanda Solar Power Pvt Ltd | C14: Operational | D14: Bihar | E14: Solar | F14: 15 | H14: SBPDCL & NBPDCL | I14: =IF($H14="","–",IF($H14="GUVNL","GUVNL",IF(OR($H14="SECI",$H14="NTPC",$H14="SJVN",$H14="NHPC"),"Central","State & Other"))) -> State & Other | J14: 8.73 | K14: 25 | L14: Yes | O14: 42551 | P14: =IF($O14="","–",IF(MONTH($O14)<=3,YEAR($O14),YEAR($O14)+1)) -> 2017 | T14: Actual (commissioned)
A15: 13 | B15: Dayakara Solar Power Pvt Ltd | C15: Operational | D15: Telangana | E15: Solar | F15: 30 | H15: TSSPDCL | I15: =IF($H15="","–",IF($H15="GUVNL","GUVNL",IF(OR($H15="SECI",$H15="NTPC",$H15="SJVN",$H15="NHPC"),"Central","State & Other"))) -> State & Other | J15: 6.848 | K15: 25 | L15: Yes | O15: 42582 | P15: =IF($O15="","–",IF(MONTH($O15)<=3,YEAR($O15),YEAR($O15)+1)) -> 2017 | T15: Actual (commissioned) | U15: Phase I 14 MW Jun-16; Phase II 16 MW Jul-16
A16: 14 | B16: Grahati Solar Power Pvt Ltd | C16: Operational | D16: Telangana | E16: Solar | F16: 50 | H16: TSSPDCL | I16: =IF($H16="","–",IF($H16="GUVNL","GUVNL",IF(OR($H16="SECI",$H16="NTPC",$H16="SJVN",$H16="NHPC"),"Central","State & Other"))) -> State & Other | J16: 6.737 | K16: 25 | L16: Yes | O16: 42613 | P16: =IF($O16="","–",IF(MONTH($O16)<=3,YEAR($O16),YEAR($O16)+1)) -> 2017 | T16: Actual (commissioned) | U16: Phase I 20 MW Jul-16; Phase II 30 MW Aug-16
A17: 15 | B17: ACME PV Powertech Pvt Ltd | C17: Operational | D17: Telangana | E17: Solar | F17: 50 | H17: TSNPDCL | I17: =IF($H17="","–",IF($H17="GUVNL","GUVNL",IF(OR($H17="SECI",$H17="NTPC",$H17="SJVN",$H17="NHPC"),"Central","State & Other"))) -> State & Other | J17: 5.595 | K17: 25 | L17: Yes | O17: 42978 | P17: =IF($O17="","–",IF(MONTH($O17)<=3,YEAR($O17),YEAR($O17)+1)) -> 2018 | T17: Actual (commissioned) | U17: Phase I 40 MW Jul-17; Phase II 10 MW Aug-17
A18: 16 | B18: ACME Solar Power Technology Pvt Ltd | C18: Operational | D18: Telangana | E18: Solar | F18: 50 | H18: TSNPDCL | I18: =IF($H18="","–",IF($H18="GUVNL","GUVNL",IF(OR($H18="SECI",$H18="NTPC",$H18="SJVN",$H18="NHPC"),"Central","State & Other"))) -> State & Other | J18: 5.59 | K18: 25 | L18: Yes | O18: 43159 | P18: =IF($O18="","–",IF(MONTH($O18)<=3,YEAR($O18),YEAR($O18)+1)) -> 2018 | T18: Actual (commissioned)
A19: 17 | B19: ACME Yamunanagar Solar Power Pvt Ltd | C19: Operational | D19: Telangana | E19: Solar | F19: 20 | H19: NTPC | I19: =IF($H19="","–",IF($H19="GUVNL","GUVNL",IF(OR($H19="SECI",$H19="NTPC",$H19="SJVN",$H19="NHPC"),"Central","State & Other"))) -> Central | J19: 4.67 | K19: 25 | L19: Yes | O19: 43008 | P19: =IF($O19="","–",IF(MONTH($O19)<=3,YEAR($O19),YEAR($O19)+1)) -> 2018 | T19: Actual (commissioned)
A20: 18 | B20: ACME Mahbubnagar Solar Energy Pvt Ltd | C20: Operational | D20: Telangana | E20: Solar | F20: 30 | H20: NTPC | I20: =IF($H20="","–",IF($H20="GUVNL","GUVNL",IF(OR($H20="SECI",$H20="NTPC",$H20="SJVN",$H20="NHPC"),"Central","State & Other"))) -> Central | J20: 4.67 | K20: 25 | L20: Yes | O20: 43008 | P20: =IF($O20="","–",IF(MONTH($O20)<=3,YEAR($O20),YEAR($O20)+1)) -> 2018 | T20: Actual (commissioned)
A21: 19 | B21: Nirosha Power Pvt Ltd | C21: Operational | D21: Uttar Pradesh | E21: Solar | F21: 30 | H21: UPPCL | I21: =IF($H21="","–",IF($H21="GUVNL","GUVNL",IF(OR($H21="SECI",$H21="NTPC",$H21="SJVN",$H21="NHPC"),"Central","State & Other"))) -> State & Other | J21: 8.93 | K21: 12 | L21: Yes | O21: 42643 | P21: =IF($O21="","–",IF(MONTH($O21)<=3,YEAR($O21),YEAR($O21)+1)) -> 2017 | T21: Actual (commissioned) | U21: PPA tenor 12 years, renewable for a further 13 years
A22: 20 | B22: ACME Sidlaghatta Solar Energy Pvt Ltd | C22: Operational | D22: Karnataka | E22: Solar | F22: 20 | H22: BESCOM | I22: =IF($H22="","–",IF($H22="GUVNL","GUVNL",IF(OR($H22="SECI",$H22="NTPC",$H22="SJVN",$H22="NHPC"),"Central","State & Other"))) -> State & Other | J22: 2.97 | K22: 25 | L22: Yes | O22: 43769 | P22: =IF($O22="","–",IF(MONTH($O22)<=3,YEAR($O22),YEAR($O22)+1)) -> 2020 | T22: Actual (commissioned)
A23: 21 | B23: ACME Jodhpur Solar Power Pvt Ltd | C23: Operational | D23: Rajasthan | E23: Solar | F23: 100 | H23: SECI | I23: =IF($H23="","–",IF($H23="GUVNL","GUVNL",IF(OR($H23="SECI",$H23="NTPC",$H23="SJVN",$H23="NHPC"),"Central","State & Other"))) -> Central | J23: 2.44 | K23: 25 | L23: Yes | O23: 43373 | P23: =IF($O23="","–",IF(MONTH($O23)<=3,YEAR($O23),YEAR($O23)+1)) -> 2019 | T23: Actual (commissioned)
A24: 22 | B24: ACME Rewa Solar Power Pvt Ltd | C24: Operational | D24: Rajasthan | E24: Solar | F24: 100 | H24: SECI | I24: =IF($H24="","–",IF($H24="GUVNL","GUVNL",IF(OR($H24="SECI",$H24="NTPC",$H24="SJVN",$H24="NHPC"),"Central","State & Other"))) -> Central | J24: 2.44 | K24: 25 | L24: Yes | O24: 43404 | P24: =IF($O24="","–",IF(MONTH($O24)<=3,YEAR($O24),YEAR($O24)+1)) -> 2019 | T24: Actual (commissioned)
A25: 23 | B25: ACME Heergarh Powertech Pvt Ltd | C25: Operational | D25: Rajasthan | E25: Solar | F25: 300 | H25: MSEDCL | I25: =IF($H25="","–",IF($H25="GUVNL","GUVNL",IF(OR($H25="SECI",$H25="NTPC",$H25="SJVN",$H25="NHPC"),"Central","State & Other"))) -> State & Other | J25: 2.74 | K25: 25 | L25: Yes | O25: 44712 | P25: =IF($O25="","–",IF(MONTH($O25)<=3,YEAR($O25),YEAR($O25)+1)) -> 2023 | T25: Actual (commissioned) | U25: Phase I 100 MW Apr-22; Phase II 200 MW May-22. ICRA AA- rated
A26: 24 | B26: ACME Aklera Power Technology Pvt Ltd | C26: Operational | D26: Rajasthan | E26: Solar | F26: 250 | H26: SECI | I26: =IF($H26="","–",IF($H26="GUVNL","GUVNL",IF(OR($H26="SECI",$H26="NTPC",$H26="SJVN",$H26="NHPC"),"Central","State & Other"))) -> Central | J26: 2.48 | K26: 25 | L26: Yes | O26: 45322 | P26: =IF($O26="","–",IF(MONTH($O26)<=3,YEAR($O26),YEAR($O26)+1)) -> 2024 | T26: Actual (commissioned) | U26: Phase I 200 MW Jul-23; Phase II 50 MW Jan-24
A27: 25 | B27: ACME Raisar Solar Energy Pvt Ltd | C27: Operational | D27: Rajasthan | E27: Solar | F27: 300 | H27: SECI | I27: =IF($H27="","–",IF($H27="GUVNL","GUVNL",IF(OR($H27="SECI",$H27="NTPC",$H27="SJVN",$H27="NHPC"),"Central","State & Other"))) -> Central | J27: 2.44 | K27: 25 | L27: Yes | O27: 45688 | P27: =IF($O27="","–",IF(MONTH($O27)<=3,YEAR($O27),YEAR($O27)+1)) -> 2025 | T27: Actual (commissioned) | U27: Phase I 272 MW Dec-24; Phase II 28 MW Jan-25
A28: 26 | B28: ACME Dhaulpur Powertech Pvt Ltd | C28: Operational | D28: Rajasthan | E28: Solar | F28: 300 | H28: SECI | I28: =IF($H28="","–",IF($H28="GUVNL","GUVNL",IF(OR($H28="SECI",$H28="NTPC",$H28="SJVN",$H28="NHPC"),"Central","State & Other"))) -> Central | J28: 2.44 | K28: 25 | L28: Yes | O28: 45688 | P28: =IF($O28="","–",IF(MONTH($O28)<=3,YEAR($O28),YEAR($O28)+1)) -> 2025 | T28: Actual (commissioned) | U28: Phase I 238 MW Dec-24; Phase II 62 MW Jan-25
A29: 27 | B29: ACME Deoghar Solar Power Pvt Ltd | C29: Operational | D29: Rajasthan | E29: Solar | F29: 300 | H29: SECI | I29: =IF($H29="","–",IF($H29="GUVNL","GUVNL",IF(OR($H29="SECI",$H29="NTPC",$H29="SJVN",$H29="NHPC"),"Central","State & Other"))) -> Central | J29: 2.44 | K29: 25 | L29: Yes | O29: 45688 | P29: =IF($O29="","–",IF(MONTH($O29)<=3,YEAR($O29),YEAR($O29)+1)) -> 2025 | T29: Actual (commissioned) | U29: Phase I 253 MW Dec-24; Phase II 47 MW Jan-25
A30: 28 | B30: ACME Phalodi Solar Energy Pvt Ltd | C30: Operational | D30: Rajasthan | E30: Solar | F30: 300 | H30: SECI | I30: =IF($H30="","–",IF($H30="GUVNL","GUVNL",IF(OR($H30="SECI",$H30="NTPC",$H30="SJVN",$H30="NHPC"),"Central","State & Other"))) -> Central | J30: 2.44 | K30: 25 | L30: Yes | O30: 45688 | P30: =IF($O30="","–",IF(MONTH($O30)<=3,YEAR($O30),YEAR($O30)+1)) -> 2025 | T30: Actual (commissioned) | U30: Phase I 260 MW Dec-24; Phase II 40 MW Jan-25
A31: 29 | B31: ACME Sikar Solar Pvt Ltd | C31: Operational | D31: Rajasthan | E31: Solar | F31: 300 | H31: SECI | I31: =IF($H31="","–",IF($H31="GUVNL","GUVNL",IF(OR($H31="SECI",$H31="NTPC",$H31="SJVN",$H31="NHPC"),"Central","State & Other"))) -> Central | J31: 3.05 | K31: 25 | L31: Yes | O31: 45838 | P31: =IF($O31="","–",IF(MONTH($O31)<=3,YEAR($O31),YEAR($O31)+1)) -> 2026 | T31: Actual (commissioned) | U31: Commissioned May-Jun 25
A32: 30 | B32: ACME Pokhran Solar Pvt Ltd | C32: Operational | D32: Gujarat | E32: Wind | F32: 50 | H32: GUVNL | I32: =IF($H32="","–",IF($H32="GUVNL","GUVNL",IF(OR($H32="SECI",$H32="NTPC",$H32="SJVN",$H32="NHPC"),"Central","State & Other"))) -> GUVNL | J32: 2.9 | K32: 25 | L32: Yes | O32: 45838 | P32: =IF($O32="","–",IF(MONTH($O32)<=3,YEAR($O32),YEAR($O32)+1)) -> 2026 | T32: Actual (commissioned) | U32: CRISIL A+ rated
A33: 31 | B33: ACME Eco Clean Energy Pvt Ltd (Ph I-II) | C33: Operational | D33: Gujarat | E33: Wind | F33: 72 | H33: GUVNL | I33: =IF($H33="","–",IF($H33="GUVNL","GUVNL",IF(OR($H33="SECI",$H33="NTPC",$H33="SJVN",$H33="NHPC"),"Central","State & Other"))) -> GUVNL | J33: 3.01 | K33: 25 | L33: Yes | O33: 46053 | P33: =IF($O33="","–",IF(MONTH($O33)<=3,YEAR($O33),YEAR($O33)+1)) -> 2026 | T33: Actual (commissioned) | U33: Phase I 28 MW Oct-25; Phase II 44 MW Jan-26. CRISIL A+ rated
A34: 32 | B34: ACME Eco Clean Energy Pvt Ltd (Ph III) | C34: Operational | D34: Gujarat | E34: Wind | F34: 20 | H34: GUVNL | I34: =IF($H34="","–",IF($H34="GUVNL","GUVNL",IF(OR($H34="SECI",$H34="NTPC",$H34="SJVN",$H34="NHPC"),"Central","State & Other"))) -> GUVNL | J34: 3.01 | K34: 25 | L34: Yes | O34: 46112 | P34: =IF($O34="","–",IF(MONTH($O34)<=3,YEAR($O34),YEAR($O34)+1)) -> 2026 | T34: Actual (commissioned) | U34: Phase III commissioned Feb-Apr 26; split estimated so FY26 close ties to 2,982 MW per AR26
A35: 33 | B35: ACME Eco Clean Energy Pvt Ltd (Ph IV) | C35: Operational | D35: Gujarat | E35: Wind | F35: 8 | H35: GUVNL | I35: =IF($H35="","–",IF($H35="GUVNL","GUVNL",IF(OR($H35="SECI",$H35="NTPC",$H35="SJVN",$H35="NHPC"),"Central","State & Other"))) -> GUVNL | J35: 3.01 | K35: 25 | L35: Yes | O35: 46142 | P35: =IF($O35="","–",IF(MONTH($O35)<=3,YEAR($O35),YEAR($O35)+1)) -> 2027 | T35: Actual (commissioned) | U35: 8 MW commissioned after 31-Mar-26 (AR26 fn 54); takes operational portfolio to 2,990 MW
A36: 34 | B36: ACME Surya Power Pvt Ltd | C36: Under Construction | D36: Rajasthan | E36: FDRE | F36: 250 | H36: SJVN | I36: =IF($H36="","–",IF($H36="GUVNL","GUVNL",IF(OR($H36="SECI",$H36="NTPC",$H36="SJVN",$H36="NHPC"),"Central","State & Other"))) -> Central | J36: 4.38 | K36: 25 | L36: Yes | M36: 45245 | N36: 46568 | O36: 46568 | P36: =IF($O36="","–",IF(MONTH($O36)<=3,YEAR($O36),YEAR($O36)+1)) -> 2028 | Q36: Yes | R36: Secured | S36: Tariff adopted | T36: Disclosed (deck SCOD) | U36: Fatehgarh II. Night-time GNA Dec-26. Mgmt will not commission on TGNA — solar awaits daytime GNA; battery operated first
A37: 35 | B37: ACME Sun Power Pvt Ltd | C37: Under Construction | D37: Rajasthan | E37: FDRE | F37: 320 | H37: SJVN | I37: =IF($H37="","–",IF($H37="GUVNL","GUVNL",IF(OR($H37="SECI",$H37="NTPC",$H37="SJVN",$H37="NHPC"),"Central","State & Other"))) -> Central | J37: 4.38 | K37: 25 | L37: Yes | M37: 45245 | N37: 46568 | O37: 46568 | P37: =IF($O37="","–",IF(MONTH($O37)<=3,YEAR($O37),YEAR($O37)+1)) -> 2028 | Q37: Yes | R37: Secured | S37: Tariff adopted | T37: Disclosed (deck SCOD) | U37: Fatehgarh II. Night-time GNA Dec-26. Mgmt will not commission on TGNA — solar awaits daytime GNA; battery operated first
A38: 36 | B38: ACME Urja One Pvt Ltd (SECI) | C38: Under Construction | D38: Andhra Pradesh / Maharashtra | E38: FDRE | F38: 380 | H38: SECI | I38: =IF($H38="","–",IF($H38="GUVNL","GUVNL",IF(OR($H38="SECI",$H38="NTPC",$H38="SJVN",$H38="NHPC"),"Central","State & Other"))) -> Central | J38: 4.73 | K38: 25 | L38: Yes | M38: 45031 | N38: 46326 | O38: 46433 | P38: =IF($O38="","–",IF(MONTH($O38)<=3,YEAR($O38),YEAR($O38)+1)) -> 2027 | Q38: Yes | R38: Secured | S38: Tariff adopted | T38: Disclosed (phased from Sep-26) | U38: Deck shows phased commissioning from Sep-26 but carries only 190 MW of the 380 MW in the FY27 target table. Dating the full capacity at mid-Feb-27 approximates half the capacity running from Sep-26 plus the balance later, without splitting the row.
A39: 37 | B39: ACME Renewtech Pvt Ltd | C39: Under Construction | D39: Rajasthan / Maharashtra | E39: Hybrid | F39: 300 | H39: NTPC | I39: =IF($H39="","–",IF($H39="GUVNL","GUVNL",IF(OR($H39="SECI",$H39="NTPC",$H39="SJVN",$H39="NHPC"),"Central","State & Other"))) -> Central | J39: 3.36 | K39: 25 | L39: Yes | M39: 45275 | N39: 46660 | O39: 46660 | P39: =IF($O39="","–",IF(MONTH($O39)<=3,YEAR($O39),YEAR($O39)+1)) -> 2028 | Q39: Yes | R39: Secured | S39: Tariff adopted | T39: Disclosed (deck SCOD) | U39: Returned to the contractual SCOD of Sep-27 per the Q1 FY27 deck. The earlier FY27 placement assumed commissioning well ahead of SCOD on the Bikaner III GNA being available from Sep-26, which proved too aggressive.
A40: 38 | B40: ACME Platinum Urja Pvt Ltd | C40: Under Construction | D40: Karnataka | E40: FDRE | F40: 350 | H40: SECI | I40: =IF($H40="","–",IF($H40="GUVNL","GUVNL",IF(OR($H40="SECI",$H40="NTPC",$H40="SJVN",$H40="NHPC"),"Central","State & Other"))) -> Central | J40: 3.42 | K40: 25 | L40: Yes | M40: 45488 | N40: 46477 | O40: 46433 | P40: =IF($O40="","–",IF(MONTH($O40)<=3,YEAR($O40),YEAR($O40)+1)) -> 2027 | Q40: Yes | R40: Secured | S40: Tariff adopted | T40: Disclosed (deck SCOD) | U40: Deck SCOD is Mar-27 and the FY27 target table carries only 150 MW of the 350 MW. Dated mid-Feb-27 so it commissions within FY27 but contributes only ~6 weeks of generation.
A41: 39 | B41: ACME Venus Urja Pvt Ltd | C41: Under Construction | D41: – | E41: FDRE | F41: 400 | H41: NHPC | I41: =IF($H41="","–",IF($H41="GUVNL","GUVNL",IF(OR($H41="SECI",$H41="NTPC",$H41="SJVN",$H41="NHPC"),"Central","State & Other"))) -> Central | J41: 4.64 | K41: 25 | L41: Yes | M41: 45337 | O41: 46660 | P41: =IF($O41="","–",IF(MONTH($O41)<=3,YEAR($O41),YEAR($O41)+1)) -> 2028 | Q41: Yes | R41: Secured | S41: Tariff adopted | T41: Not disclosed
A42: 40 | B42: ACME Hybrid Urja Pvt Ltd | C42: Under Construction | D42: – | E42: FDRE | F42: 280 | H42: NHPC | I42: =IF($H42="","–",IF($H42="GUVNL","GUVNL",IF(OR($H42="SECI",$H42="NTPC",$H42="SJVN",$H42="NHPC"),"Central","State & Other"))) -> Central | J42: 4.64 | K42: 25 | L42: Yes | M42: 45337 | O42: 46660 | P42: =IF($O42="","–",IF(MONTH($O42)<=3,YEAR($O42),YEAR($O42)+1)) -> 2028 | Q42: Yes | R42: Secured | S42: Tariff adopted | T42: Not disclosed | U42: COD aligned with ACME Venus Urja — same NHPC tender, same LoA date (Feb-24) and same tariff of INR 4.64/kWh, so no basis for a 3-month stagger.
A43: 41 | B43: ACME Sigma Urja Pvt Ltd (NHPC) | C43: Under Construction | D43: Madhya Pradesh | E43: FDRE | F43: 250 | H43: NHPC | I43: =IF($H43="","–",IF($H43="GUVNL","GUVNL",IF(OR($H43="SECI",$H43="NTPC",$H43="SJVN",$H43="NHPC"),"Central","State & Other"))) -> Central | J43: 4.56 | K43: 25 | L43: Yes | M43: 45641 | N43: 46265 | O43: 46387 | P43: =IF($O43="","–",IF(MONTH($O43)<=3,YEAR($O43),YEAR($O43)+1)) -> 2027 | Q43: Yes | R43: Secured | S43: Tariff adopted | T43: Disclosed (phased from Aug-26) | U43: Neemuch is disclosed as phased commissioning from Aug-26. Dating the full 250 MW at Dec-26 approximates a phased ramp rather than the whole block arriving in September.
A44: 42 | B44: ACME Sigma Urja Pvt Ltd (Tata Power-DD) | C44: Under Construction | D44: Madhya Pradesh | E44: FDRE | F44: 50 | H44: Tata Power-DD | I44: =IF($H44="","–",IF($H44="GUVNL","GUVNL",IF(OR($H44="SECI",$H44="NTPC",$H44="SJVN",$H44="NHPC"),"Central","State & Other"))) -> State & Other | J44: 4.43 | K44: 25 | L44: Yes | M44: 45884 | N44: 46265 | O44: 46387 | P44: =IF($O44="","–",IF(MONTH($O44)<=3,YEAR($O44),YEAR($O44)+1)) -> 2027 | Q44: Yes | R44: Secured | S44: Tariff adopted | T44: Disclosed (phased from Aug-26) | U44: Neemuch, phased from Aug-26. Dated Dec-26 on the same basis as the 250 MW block.
A45: 43 | B45: ACME Urja One Pvt Ltd (NHPC) | C45: Under Construction | D45: – | E45: FDRE | F45: 250 | H45: NHPC | I45: =IF($H45="","–",IF($H45="GUVNL","GUVNL",IF(OR($H45="SECI",$H45="NTPC",$H45="SJVN",$H45="NHPC"),"Central","State & Other"))) -> Central | J45: 4.33 | K45: 25 | L45: Yes | O45: 47026 | P45: =IF($O45="","–",IF(MONTH($O45)<=3,YEAR($O45),YEAR($O45)+1)) -> 2029 | Q45: Yes | R45: Secured | S45: Order reserved | T45: Not disclosed | U45: Award date not disclosed
A46: 44 | B46: ACME Greentech Seventh Pvt Ltd | C46: Under Construction | D46: – | E46: FDRE | F46: 450 | H46: SJVN | I46: =IF($H46="","–",IF($H46="GUVNL","GUVNL",IF(OR($H46="SECI",$H46="NTPC",$H46="SJVN",$H46="NHPC"),"Central","State & Other"))) -> Central | J46: 6.74 | K46: 25 | L46: Yes | M46: 45945 | O46: 47118 | P46: =IF($O46="","–",IF(MONTH($O46)<=3,YEAR($O46),YEAR($O46)+1)) -> 2029 | Q46: Yes | R46: Secured | S46: Tariff adopted | T46: Not disclosed | U46: Solar + ESS. ALMM List-II applicable (SJVN FDRE)
A47: 45 | B47: ACME Renewtech Sixth Pvt Ltd | C47: Under Construction | D47: – | E47: FDRE | F47: 300 | H47: SECI | I47: =IF($H47="","–",IF($H47="GUVNL","GUVNL",IF(OR($H47="SECI",$H47="NTPC",$H47="SJVN",$H47="NHPC"),"Central","State & Other"))) -> Central | J47: 6.28 | K47: 25 | L47: Yes | M47: 46203 | O47: 47026 | P47: =IF($O47="","–",IF(MONTH($O47)<=3,YEAR($O47),YEAR($O47)+1)) -> 2029 | Q47: Under process | R47: In-principle grant awaited | S47: Order reserved | T47: Not disclosed | U47: PPA signed Q1 FY27. Awarded 301 MW, classified 300 MW. ALMM List-II applicable (SECI FDRE)
A48: 46 | B48: ACME Renewtech Fifth Pvt Ltd | C48: Under Construction | D48: – | E48: Hybrid | F48: 300 | H48: SECI | I48: =IF($H48="","–",IF($H48="GUVNL","GUVNL",IF(OR($H48="SECI",$H48="NTPC",$H48="SJVN",$H48="NHPC"),"Central","State & Other"))) -> Central | J48: 3.25 | K48: 25 | L48: Yes | M48: 46203 | O48: 47026 | P48: =IF($O48="","–",IF(MONTH($O48)<=3,YEAR($O48),YEAR($O48)+1)) -> 2029 | Q48: Under process | R48: Secured | S48: Tariff adopted | T48: Not disclosed | U48: PPA signed Q1 FY27. 1 hour of battery offered vs standard configuration
A49: 47 | B49: ACME Greentech Nineth Pvt Ltd | C49: Under Construction | D49: – | E49: BESS | F49: 0 | G49: 450 | H49: NHPC | I49: =IF($H49="","–",IF($H49="GUVNL","GUVNL",IF(OR($H49="SECI",$H49="NTPC",$H49="SJVN",$H49="NHPC"),"Central","State & Other"))) -> Central | K49: 25 | L49: Yes | M49: 45823 | O49: 46433 | P49: =IF($O49="","–",IF(MONTH($O49)<=3,YEAR($O49),YEAR($O49)+1)) -> 2027 | Q49: In-principle | R49: Secured | S49: Tariff adopted | T49: Not disclosed | U49: Standalone BESS — no generation capacity. Capacity charge INR 2.22 lakhs/MW/month (not INR/kWh). Pre-identified state substation
A50: 48 | B50: ACME Greentech Tenth Pvt Ltd | C50: Under Construction | D50: – | E50: BESS | F50: 0 | G50: 100 | H50: NHPC | I50: =IF($H50="","–",IF($H50="GUVNL","GUVNL",IF(OR($H50="SECI",$H50="NTPC",$H50="SJVN",$H50="NHPC"),"Central","State & Other"))) -> Central | K50: 25 | L50: Yes | M50: 45823 | O50: 46433 | P50: =IF($O50="","–",IF(MONTH($O50)<=3,YEAR($O50),YEAR($O50)+1)) -> 2027 | Q50: In-principle | R50: Secured | S50: Tariff adopted | T50: Not disclosed | U50: Standalone BESS — no generation capacity. Capacity charge INR 2.10 lakhs/MW/month (not INR/kWh). Pre-identified state substation
A51: 49 | B51: ACME Alpha Renewables Pvt Ltd | C51: LoA Awarded | D51: – | E51: Hybrid | F51: 150 | H51: NTPC | I51: =IF($H51="","–",IF($H51="GUVNL","GUVNL",IF(OR($H51="SECI",$H51="NTPC",$H51="SJVN",$H51="NHPC"),"Central","State & Other"))) -> Central | J51: 3.32 | K51: 25 | L51: No | M51: 45366 | O51: 47026 | P51: =IF($O51="","–",IF(MONTH($O51)<=3,YEAR($O51),YEAR($O51)+1)) -> 2029 | R51: Secured | S51: Tariff adopted | T51: Not disclosed | U51: LoA awarded; PPA expected to sign in FY27 (Q1 FY27 call: LoA projects 'progressing well and expected to get signed soon'). PPA signing plus a 24-month hybrid build puts COD in FY29.
A52: 50 | B52: ACME Omega Urja Pvt Ltd | C52: LoA Awarded | D52: – | E52: Solar | F52: 300 | H52: SJVN | I52: =IF($H52="","–",IF($H52="GUVNL","GUVNL",IF(OR($H52="SECI",$H52="NTPC",$H52="SJVN",$H52="NHPC"),"Central","State & Other"))) -> Central | J52: 2.52 | K52: 25 | L52: No | M52: 45519 | O52: 46660 | P52: =IF($O52="","–",IF(MONTH($O52)<=3,YEAR($O52),YEAR($O52)+1)) -> 2028 | R52: Secured | S52: Tariff adopted | T52: Not disclosed | U52: LoA awarded; PPA expected FY27. Solar-only build is faster than FDRE, so an 18-month construction period from signing puts COD in FY28.
A53: 51 | B53: ACME Marigold Urja Pvt Ltd (NTPC) | C53: LoA Awarded | D53: – | E53: FDRE | F53: 400 | H53: NTPC | I53: =IF($H53="","–",IF($H53="GUVNL","GUVNL",IF(OR($H53="SECI",$H53="NTPC",$H53="SJVN",$H53="NHPC"),"Central","State & Other"))) -> Central | J53: 4.7 | K53: 25 | L53: No | M53: 45580 | O53: 47118 | P53: =IF($O53="","–",IF(MONTH($O53)<=3,YEAR($O53),YEAR($O53)+1)) -> 2029 | R53: Secured | S53: Tariff adopted | T53: Not disclosed | U53: LoA awarded; PPA expected FY27 plus a 24-month FDRE build puts COD in FY29.
A54: 52 | B54: ACME Greentech Sixteen Pvt Ltd | C54: LoA Awarded | D54: Madhya Pradesh | E54: FDRE | F54: 220 | H54: MPPMCL | I54: =IF($H54="","–",IF($H54="GUVNL","GUVNL",IF(OR($H54="SECI",$H54="NTPC",$H54="SJVN",$H54="NHPC"),"Central","State & Other"))) -> State & Other | J54: 2.764 | K54: 25 | L54: No | M54: 45915 | O54: 47026 | P54: =IF($O54="","–",IF(MONTH($O54)<=3,YEAR($O54),YEAR($O54)+1)) -> 2029 | R54: Secured (by procurer) | S54: Tariff adopted | T54: Not disclosed | U54: LoA awarded Sep-25, PPA expected FY27 plus a 24-month FDRE build puts COD at the FY29 year end. Morena Solar Park — connectivity provided by the procurer.
A55: 53 | B55: ACME Marigold Urja Pvt Ltd (REMC) | C55: LoA Awarded | D55: – | E55: FDRE | F55: 130 | H55: REMC Limited | I55: =IF($H55="","–",IF($H55="GUVNL","GUVNL",IF(OR($H55="SECI",$H55="NTPC",$H55="SJVN",$H55="NHPC"),"Central","State & Other"))) -> State & Other | J55: 4.35 | K55: 25 | L55: No | M55: 45488 | O55: 47026 | P55: =IF($O55="","–",IF(MONTH($O55)<=3,YEAR($O55),YEAR($O55)+1)) -> 2029 | R55: Secured | S55: Not applicable | T55: Not disclosed | U55: Management said on the Q1 FY27 call this is '100% going to be signed very soon' with REMCL, delayed only by the Supreme Court review of railway open-access status. PPA signing plus a 24-month build puts COD in FY29.
A56: 54 | B56: BESS — Bhadla-II (Ph I) | C56: Operational | D56: Rajasthan | E56: BESS | F56: 0 | G56: 1324 | H56: Short-term / merchant | I56: =IF($H56="","–",IF($H56="GUVNL","GUVNL",IF(OR($H56="SECI",$H56="NTPC",$H56="SJVN",$H56="NHPC"),"Central","State & Other"))) -> State & Other | L56: n.a. | O56: 46112 | P56: =IF($O56="","–",IF(MONTH($O56)<=3,YEAR($O56),YEAR($O56)+1)) -> 2026 | R56: Secured | S56: n.a. | T56: Disclosed | U56: Commissioned BESS as at 31-Mar-26 per AR26 (1,324 MWh). Site allocation estimated.
A57: 55 | B57: BESS — Bhadla-II (Ph II) | C57: Operational | D57: Rajasthan | E57: BESS | F57: 0 | G57: 80 | H57: Short-term / merchant | I57: =IF($H57="","–",IF($H57="GUVNL","GUVNL",IF(OR($H57="SECI",$H57="NTPC",$H57="SJVN",$H57="NHPC"),"Central","State & Other"))) -> State & Other | L57: n.a. | O57: 46203 | P57: =IF($O57="","–",IF(MONTH($O57)<=3,YEAR($O57),YEAR($O57)+1)) -> 2027 | R57: Secured | S57: n.a. | T57: Disclosed | U57: Balancing tranche so Bhadla-II totals 1,404 MWh per the Q1 FY27 commissioning plan.
A58: 56 | B58: BESS — Bikaner-II (Ph I) | C58: Operational | D58: Rajasthan | E58: BESS | F58: 0 | G58: 1103 | H58: Short-term / merchant | I58: =IF($H58="","–",IF($H58="GUVNL","GUVNL",IF(OR($H58="SECI",$H58="NTPC",$H58="SJVN",$H58="NHPC"),"Central","State & Other"))) -> State & Other | L58: n.a. | O58: 46203 | P58: =IF($O58="","–",IF(MONTH($O58)<=3,YEAR($O58),YEAR($O58)+1)) -> 2027 | R58: Secured | S58: n.a. | T58: Disclosed | U58: Commissioned by Q1 FY27. Bay charged.
A59: 57 | B59: BESS — Bikaner-II (Ph II) | C59: Under Construction | D59: Rajasthan | E59: BESS | F59: 0 | G59: 200 | H59: Short-term / merchant | I59: =IF($H59="","–",IF($H59="GUVNL","GUVNL",IF(OR($H59="SECI",$H59="NTPC",$H59="SJVN",$H59="NHPC"),"Central","State & Other"))) -> State & Other | L59: n.a. | O59: 46387 | P59: =IF($O59="","–",IF(MONTH($O59)<=3,YEAR($O59),YEAR($O59)+1)) -> 2027 | R59: Secured | S59: n.a. | T59: Disclosed | U59: Q3 FY27E per company commissioning plan.
A60: 58 | B60: BESS — Bikaner-III (Ph I) | C60: Under Construction | D60: Rajasthan | E60: BESS | F60: 0 | G60: 550 | H60: Short-term / merchant | I60: =IF($H60="","–",IF($H60="GUVNL","GUVNL",IF(OR($H60="SECI",$H60="NTPC",$H60="SJVN",$H60="NHPC"),"Central","State & Other"))) -> State & Other | L60: n.a. | O60: 46295 | P60: =IF($O60="","–",IF(MONTH($O60)<=3,YEAR($O60),YEAR($O60)+1)) -> 2027 | R60: Secured | S60: n.a. | T60: Disclosed | U60: Q2 FY27E. Co-located with ACME Renewtech (Bikaner III).
A61: 59 | B61: BESS — Bikaner-III (Ph II) | C61: Under Construction | D61: Rajasthan | E61: BESS | F61: 0 | G61: 1000 | H61: Short-term / merchant | I61: =IF($H61="","–",IF($H61="GUVNL","GUVNL",IF(OR($H61="SECI",$H61="NTPC",$H61="SJVN",$H61="NHPC"),"Central","State & Other"))) -> State & Other | L61: n.a. | O61: 46387 | P61: =IF($O61="","–",IF(MONTH($O61)<=3,YEAR($O61),YEAR($O61)+1)) -> 2027 | R61: Secured | S61: n.a. | T61: Disclosed | U61: Q3 FY27E.
A62: 60 | B62: BESS — Fatehgarh-I (Ph I) | C62: Operational | D62: Rajasthan | E62: BESS | F62: 0 | G62: 601 | H62: Short-term / merchant | I62: =IF($H62="","–",IF($H62="GUVNL","GUVNL",IF(OR($H62="SECI",$H62="NTPC",$H62="SJVN",$H62="NHPC"),"Central","State & Other"))) -> State & Other | L62: n.a. | O62: 46203 | P62: =IF($O62="","–",IF(MONTH($O62)<=3,YEAR($O62),YEAR($O62)+1)) -> 2027 | R62: Secured | S62: n.a. | T62: Disclosed | U62: Commissioned by Q1 FY27. Bay charged.
A63: 61 | B63: BESS — Fatehgarh-I (Ph II) | C63: Under Construction | D63: Rajasthan | E63: BESS | F63: 0 | G63: 750 | H63: Short-term / merchant | I63: =IF($H63="","–",IF($H63="GUVNL","GUVNL",IF(OR($H63="SECI",$H63="NTPC",$H63="SJVN",$H63="NHPC"),"Central","State & Other"))) -> State & Other | L63: n.a. | O63: 46295 | P63: =IF($O63="","–",IF(MONTH($O63)<=3,YEAR($O63),YEAR($O63)+1)) -> 2027 | R63: Secured | S63: n.a. | T63: Disclosed | U63: Q2 FY27E.
A64: 62 | B64: BESS — Fatehgarh-I (Ph III) | C64: Under Construction | D64: Rajasthan | E64: BESS | F64: 0 | G64: 2500 | H64: Short-term / merchant | I64: =IF($H64="","–",IF($H64="GUVNL","GUVNL",IF(OR($H64="SECI",$H64="NTPC",$H64="SJVN",$H64="NHPC"),"Central","State & Other"))) -> State & Other | L64: n.a. | O64: 46387 | P64: =IF($O64="","–",IF(MONTH($O64)<=3,YEAR($O64),YEAR($O64)+1)) -> 2027 | R64: Secured | S64: n.a. | T64: Disclosed | U64: Q3 FY27E. Largest single tranche.
A65: 63 | B65: BESS — Fatehgarh-I (Ph IV) | C65: Under Construction | D65: Rajasthan | E65: BESS | F65: 0 | G65: 1500 | H65: Short-term / merchant | I65: =IF($H65="","–",IF($H65="GUVNL","GUVNL",IF(OR($H65="SECI",$H65="NTPC",$H65="SJVN",$H65="NHPC"),"Central","State & Other"))) -> State & Other | L65: n.a. | O65: 46433 | P65: =IF($O65="","–",IF(MONTH($O65)<=3,YEAR($O65),YEAR($O65)+1)) -> 2027 | R65: Secured | S65: n.a. | T65: Disclosed | U65: Q4 FY27E.
A66: 64 | B66: BESS — Neemuch (Ph I) | C66: Under Construction | D66: Madhya Pradesh | E66: BESS | F66: 0 | G66: 600 | H66: Short-term / merchant | I66: =IF($H66="","–",IF($H66="GUVNL","GUVNL",IF(OR($H66="SECI",$H66="NTPC",$H66="SJVN",$H66="NHPC"),"Central","State & Other"))) -> State & Other | L66: n.a. | O66: 46295 | P66: =IF($O66="","–",IF(MONTH($O66)<=3,YEAR($O66),YEAR($O66)+1)) -> 2027 | R66: Secured | S66: n.a. | T66: Disclosed | U66: Q2 FY27E. Charging from Aug-26. Co-located with ACME Sigma Urja.
A67: 65 | B67: BESS — Neemuch (Ph II) | C67: Under Construction | D67: Madhya Pradesh | E67: BESS | F67: 0 | G67: 750 | H67: Short-term / merchant | I67: =IF($H67="","–",IF($H67="GUVNL","GUVNL",IF(OR($H67="SECI",$H67="NTPC",$H67="SJVN",$H67="NHPC"),"Central","State & Other"))) -> State & Other | L67: n.a. | O67: 46387 | P67: =IF($O67="","–",IF(MONTH($O67)<=3,YEAR($O67),YEAR($O67)+1)) -> 2027 | R67: Secured | S67: n.a. | T67: Disclosed | U67: Q3 FY27E.
A68: 66 | B68: Future awards — tranche 1 (modelled) | C68: Future Awards | D68: – | E68: FDRE | F68: 800 | G68: 0 | H68: SECI / NTPC / SJVN (assumed) | I68: =IF($H68="","–",IF($H68="GUVNL","GUVNL",IF(OR($H68="SECI",$H68="NTPC",$H68="SJVN",$H68="NHPC"),"Central","State & Other"))) -> State & Other | J68: 4.4 | K68: 25 | L68: No | O68: 47391 | P68: =IF($O68="","–",IF(MONTH($O68)<=3,YEAR($O68),YEAR($O68)+1)) -> 2030 | R68: Assumed | S68: Modelled | T68: Modelled capacity beyond the reported 8,070 MW portfolio. Management guides to 10 GW of generation by 2030; this tranche plus tranche 2 bridges the gap, deliberately set below the full target.
A69: 67 | B69: Future awards — tranche 2 (modelled) | C69: Future Awards | D69: – | E69: FDRE | F69: 400 | G69: 0 | H69: SECI / NTPC / SJVN (assumed) | I69: =IF($H69="","–",IF($H69="GUVNL","GUVNL",IF(OR($H69="SECI",$H69="NTPC",$H69="SJVN",$H69="NHPC"),"Central","State & Other"))) -> State & Other | J69: 4.4 | K69: 25 | L69: No | O69: 47756 | P69: =IF($O69="","–",IF(MONTH($O69)<=3,YEAR($O69),YEAR($O69)+1)) -> 2031 | R69: Assumed | S69: Modelled | T69: Second tranche of modelled future awards. Tariff set at the under-construction weighted average of INR 4.4/kWh.
B70: Total master list | F70: =SUM(F3:F69) -> 9270 | G70: =SUM(G3:G69) -> 11508 | J70: =SUMPRODUCT($F$3:$F$55,$J$3:$J$55)/$F$70 -> 3.5032492
A74: PORTFOLIO SUMMARY — CAPACITY
B75: Category | C75: Capacity (MW) | D75: BESS (MWh)
B76: Operational
B77: Solar | C77: =SUMIFS($F$3:$F$67,$E$3:$E$67,$B77,$C$3:$C$67,$B$76) -> 2840 | D77: =SUMIFS($G$3:$G$67,$E$3:$E$67,$B77,$C$3:$C$67,$B$76) -> 0
B78: Wind | C78: =SUMIFS($F$3:$F$67,$E$3:$E$67,$B78,$C$3:$C$67,$B$76) -> 150 | D78: =SUMIFS($G$3:$G$67,$E$3:$E$67,$B78,$C$3:$C$67,$B$76) -> 0
B79: Hybrid | C79: =SUMIFS($F$3:$F$67,$E$3:$E$67,$B79,$C$3:$C$67,$B$76) -> 0 | D79: =SUMIFS($G$3:$G$67,$E$3:$E$67,$B79,$C$3:$C$67,$B$76) -> 0
B80: FDRE | C80: =SUMIFS($F$3:$F$67,$E$3:$E$67,$B80,$C$3:$C$67,$B$76) -> 0 | D80: =SUMIFS($G$3:$G$67,$E$3:$E$67,$B80,$C$3:$C$67,$B$76) -> 0
B81: BESS | C81: =SUMIFS($F$3:$F$67,$E$3:$E$67,$B81,$C$3:$C$67,$B$76) -> 0 | D81: =SUMIFS($G$3:$G$67,$E$3:$E$67,$B81,$C$3:$C$67,$B$76) -> 3108
B82: Total Operational | C82: =SUM(C77:C81) -> 2990 | D82: =SUM(D77:D81) -> 3108
B84: Under Construction
B85: Solar | C85: =SUMIFS($F$3:$F$67,$E$3:$E$67,$B85,$C$3:$C$67,$B$84) -> 0 | D85: =SUMIFS($G$3:$G$67,$E$3:$E$67,$B85,$C$3:$C$67,$B$84) -> 0
B86: Wind | C86: =SUMIFS($F$3:$F$67,$E$3:$E$67,$B86,$C$3:$C$67,$B$84) -> 0 | D86: =SUMIFS($G$3:$G$67,$E$3:$E$67,$B86,$C$3:$C$67,$B$84) -> 0
B87: Hybrid | C87: =SUMIFS($F$3:$F$67,$E$3:$E$67,$B87,$C$3:$C$67,$B$84) -> 600 | D87: =SUMIFS($G$3:$G$67,$E$3:$E$67,$B87,$C$3:$C$67,$B$84) -> 0
B88: FDRE | C88: =SUMIFS($F$3:$F$67,$E$3:$E$67,$B88,$C$3:$C$67,$B$84) -> 3280 | D88: =SUMIFS($G$3:$G$67,$E$3:$E$67,$B88,$C$3:$C$67,$B$84) -> 0
B89: BESS | C89: =SUMIFS($F$3:$F$67,$E$3:$E$67,$B89,$C$3:$C$67,$B$84) -> 0 | D89: =SUMIFS($G$3:$G$67,$E$3:$E$67,$B89,$C$3:$C$67,$B$84) -> 8400
B90: Total Under Construction | C90: =SUM(C85:C89) -> 3880 | D90: =SUM(D85:D89) -> 8400
B92: LoA Awarded
B93: Solar | C93: =SUMIFS($F$3:$F$67,$E$3:$E$67,$B93,$C$3:$C$67,$B$92) -> 300 | D93: =SUMIFS($G$3:$G$67,$E$3:$E$67,$B93,$C$3:$C$67,$B$92) -> 0
B94: Wind | C94: =SUMIFS($F$3:$F$67,$E$3:$E$67,$B94,$C$3:$C$67,$B$92) -> 0 | D94: =SUMIFS($G$3:$G$67,$E$3:$E$67,$B94,$C$3:$C$67,$B$92) -> 0
B95: Hybrid | C95: =SUMIFS($F$3:$F$67,$E$3:$E$67,$B95,$C$3:$C$67,$B$92) -> 150 | D95: =SUMIFS($G$3:$G$67,$E$3:$E$67,$B95,$C$3:$C$67,$B$92) -> 0
B96: FDRE | C96: =SUMIFS($F$3:$F$67,$E$3:$E$67,$B96,$C$3:$C$67,$B$92) -> 750 | D96: =SUMIFS($G$3:$G$67,$E$3:$E$67,$B96,$C$3:$C$67,$B$92) -> 0
B97: BESS | C97: =SUMIFS($F$3:$F$67,$E$3:$E$67,$B97,$C$3:$C$67,$B$92) -> 0 | D97: =SUMIFS($G$3:$G$67,$E$3:$E$67,$B97,$C$3:$C$67,$B$92) -> 0
B98: Total LoA Awarded | C98: =SUM(C93:C97) -> 1200 | D98: =SUM(D93:D97) -> 0
B100: Total Portfolio | C100: =C82+C90+C98 -> 8070 | D100: =D82+D90+D98 -> 11508

Sheet Consolidated
B2: P&L, Rs. Mn - Consolidated | D2: 2018 | E2: 2019 | F2: 2020 | G2: 2021 | H2: 2022 | I2: 2023 | J2: 2024 | K2: 2025 | L2: =+K2+1 -> 2026 | M2: 2027E | N2: 2028E | O2: 2029E | P2: 2030E
B5: Revenue from Operations | D5: 10961.34 | E5: 16718.99 | F5: 17772.54 | G5: 16917.45 | H5: 14879.02 | I5: 12949.04 | J5: 13192.5 | K5: 14051.31 | L5: =20229.59+4.2 -> 20233.79 | M5: =Assumptions!G6 -> 40060.235 | N5: =Assumptions!H6 -> 69187.16 | O5: =Assumptions!I6 -> 95080.807 | P5: =Assumptions!J6 -> 113592.78 | Q5: =(N5/K5)^(1/3)-1 -> 0.70125558 | R5: =(P5/K5)^(1/5)-1 -> 0.51889161 | T5: Consensus | U5: FY27E | V5: FY28E | W5: FY29E
B6: growth, % | I6: =I5/H5-1 -> -0.1297115 | J6: =J5/I5-1 -> 0.018801394 | K6: =K5/J5-1 -> 0.065098351 | L6: =L5/K5-1 -> 0.43999314 | M6: =M5/L5-1 -> 0.97986808 | N6: =N5/M5-1 -> 0.72707824 | O6: =O5/N5-1 -> 0.37425509 | P6: =P5/O5-1 -> 0.19469726 | T6: Revenue | U6: =[111]Sheet1!U14 -> 37816.8 | V6: =[111]Sheet1!V14 -> 69856.533 | W6: =[111]Sheet1!W14 -> 95602.615
T7: EBITDA | U7: =[111]Sheet1!U28 -> 31581.8 | V7: =[111]Sheet1!V28 -> 59535.667 | W7: =[111]Sheet1!W28 -> 81852.357
B8: Cost of material consumed | D8: 544.85 | E8: 691.95 | F8: 146.06 | G8: 0 | H8: 938.5 | T8: EBITDAM | U8: =+U7/U6 -> 0.83512619 | V8: =+V7/V6 -> 0.85225624 | W8: =+W7/W6 -> 0.85617278
B9: Employee benefit expenses | D9: 517.58 | E9: 100.25 | F9: 60.16 | G9: 301.36 | H9: 382.37 | I9: 346.44 | J9: 589.95 | K9: 649.75 | L9: 619.69 | T9: PAT | U9: =[111]Sheet1!U43 -> 8163.1333 | V9: =[111]Sheet1!V43 -> 16047.133 | W9: =[111]Sheet1!W43 -> 22406.769
B10: Other expenses | D10: 1070.12 | E10: 1407.89 | F10: 1080.59 | G10: 1088.42 | H10: 1154.93 | I10: 876.67 | J10: 1711.07 | K10: 1047.56 | L10: 1800.74 | T10: Depreciation | U10: =[111]Sheet1!U26 -> 7696.7394 | V10: =[111]Sheet1!V26 -> 14101.158 | W10: =[111]Sheet1!W26 -> 19495.897
B11: Total Expenses | D11: =SUM(D8:D10) -> 2132.55 | E11: =SUM(E8:E10) -> 2200.09 | F11: =SUM(F8:F10) -> 1286.81 | G11: =SUM(G8:G10) -> 1389.78 | H11: =SUM(H8:H10) -> 2475.8 | I11: =SUM(I8:I10) -> 1223.11 | J11: =SUM(J8:J10) -> 2301.02 | K11: =SUM(K8:K10) -> 1697.31 | L11: =SUM(L8:L10) -> 2420.43 | M11: =M5-M15 -> 7084.3125 | N11: =N5-N15 -> 8370.8169 | O11: =O5-O15 -> 11253.7 | P11: =P5-P15 -> 10910.831 | T11: Finance Cost | U11: =[111]Sheet1!U32 -> 17153.037 | V11: =[111]Sheet1!V32 -> 28234.251 | W11: =[111]Sheet1!W32 -> 37833.531
B12: growth, % | I12: =I11/H11-1 -> -0.50597383 | J12: =J11/I11-1 -> 0.88128623 | K12: =K11/J11-1 -> -0.26236625 | L12: =L11/K11-1 -> 0.42603885 | M12: =M11/L11-1 -> 1.9268818 | N12: =N11/M11-1 -> 0.18159905 | O12: =O11/N11-1 -> 0.34439683 | P12: =P11/O11-1 -> -0.03046721 | T12: Capex | U12: =-[111]Sheet1!U129 -> 162186.16 | V12: =-[111]Sheet1!V129 -> 179571.71 | W12: =-[111]Sheet1!W129 -> 117350.28
B13: as% of revenues | I13: =I11/I5 -> 0.094455651 | J13: =J11/J5 -> 0.1744188 | K13: =K11/K5 -> 0.12079372 | L13: =L11/L5 -> 0.11962317 | M13: =M11/M5 -> 0.17684151 | N13: =N11/N5 -> 0.12098801 | O13: =O11/O5 -> 0.11835932 | P13: =P11/P5 -> 0.096052152 | T13: Other Income | U13: =-[111]Sheet1!U33 -> 4937.7468 | V13: =-[111]Sheet1!V33 -> 5359.8467 | W13: =-[111]Sheet1!W33 -> 5610.8569
B15: EBITDA | D15: =D5-SUM(D8:D10) -> 8828.79 | E15: =E5-SUM(E8:E10) -> 14518.9 | F15: =F5-SUM(F8:F10) -> 16485.73 | G15: =G5-SUM(G8:G10) -> 15527.67 | H15: =H5-SUM(H8:H10) -> 12403.22 | I15: =I5-SUM(I8:I10) -> 11725.93 | J15: =J5-SUM(J8:J10) -> 10891.48 | K15: =K5-SUM(K8:K10) -> 12354 | L15: =L5-SUM(L8:L10) -> 17813.36 | M15: =Assumptions!G41 -> 32975.922 | N15: =Assumptions!H41 -> 60816.343 | O15: =Assumptions!I41 -> 83827.107 | P15: =Assumptions!J41 -> 102681.95 | Q15: =(N15/K15)^(1/3)-1 -> 0.70113025 | R15: =(P15/K15)^(1/5)-1 -> 0.52734554 | T15: Spark
B16: margin, % | D16: =IF(ISERROR(D15/D5)," ",D15/D5) -> 0.80544806 | E16: =IF(ISERROR(E15/E5)," ",E15/E5) -> 0.86840772 | F16: =IF(ISERROR(F15/F5)," ",F15/F5) -> 0.92759561 | G16: =IF(ISERROR(G15/G5)," ",G15/G5) -> 0.91784932 | H16: =IF(ISERROR(H15/H5)," ",H15/H5) -> 0.83360463 | I16: =IF(ISERROR(I15/I5)," ",I15/I5) -> 0.90554435 | J16: =IF(ISERROR(J15/J5)," ",J15/J5) -> 0.8255812 | K16: =IF(ISERROR(K15/K5)," ",K15/K5) -> 0.87920628 | L16: =IF(ISERROR(L15/L5)," ",L15/L5) -> 0.88037683 | M16: =IFERROR(M15/M5,"–") -> 0.82315849 | N16: =IFERROR(N15/N5,"–") -> 0.87901199 | O16: =IFERROR(O15/O5,"–") -> 0.88164068 | P16: =IFERROR(P15/P5,"–") -> 0.90394785 | T16: Revenue | U16: =M5 -> 40060.235 | V16: =N5 -> 69187.16 | W16: =O5 -> 95080.807
B17: growth, % | I17: =I15/H15-1 -> -0.054605981 | J17: =J15/I15-1 -> -0.071162799 | K17: =K15/J15-1 -> 0.13428111 | L17: =L15/K15-1 -> 0.44191031 | M17: =M15/L15-1 -> 0.85119048 | N17: =N15/M15-1 -> 0.8442651 | O17: =O15/N15-1 -> 0.37836481 | P17: =P15/O15-1 -> 0.22492535 | T17: EBITDA | U17: =M15 -> 32975.922 | V17: =N15 -> 60816.343 | W17: =O15 -> 83827.107
T18: EBITDAM | U18: =+U17/U16 -> 0.82315849 | V18: =+V17/V16 -> 0.87901199 | W18: =+W17/W16 -> 0.88164068
B19: Other Income | D19: 901.32 | E19: 1304.23 | F19: 776.58 | G19: 2184.67 | H19: 748.24 | I19: 664.69 | J19: 1470.17 | K19: 1701.1 | L19: 4837.01 | M19: =M215 -> 4246.5051 | N19: =N215 -> 5795.6285 | O19: =O215 -> 7246.9913 | P19: =P215 -> 7874.3622 | T19: PAT | U19: =M43 -> 8891.3067 | V19: =N43 -> 16962.06 | W19: =O43 -> 23112.177
B20: Depreciation and Amortisation | D20: 3668.95 | E20: 5708.07 | F20: 7000.8 | G20: 6217.8 | H20: 5462.75 | I20: 4848.02 | J20: 3081.38 | K20: 2873.13 | L20: 4679.02 | M20: =SUM(Assumptions!BP53:BP133) -> 7198.5436 | N20: =SUM(Assumptions!BQ53:BQ133) -> 15339.542 | O20: =SUM(Assumptions!BR53:BR133) -> 21812.595 | P20: =SUM(Assumptions!BS53:BS133) -> 29531.773 | T20: Depreciation | U20: =M20 -> 7198.5436 | V20: =N20 -> 15339.542 | W20: =O20 -> 21812.595
T21: Finance Cost | U21: =M24 -> 17937.057 | V21: =N24 -> 28214.235 | W21: =O24 -> 37842.85
B22: EBIT | D22: =D15+D19-D20 -> 6061.16 | E22: =E15+E19-E20 -> 10115.06 | F22: =F15+F19-F20 -> 10261.51 | G22: =G15+G19-G20 -> 11494.54 | H22: =H15+H19-H20 -> 7688.71 | I22: =I15+I19-I20 -> 7542.6 | J22: =J15+J19-J20 -> 9280.27 | K22: =K15+K19-K20 -> 11181.97 | ... P22: =P15+P19-P20 -> 81024.538 | T22: Capex | U22: =-M143 -> 197107.33 | V22: =-N143 -> 218628.95 | W22: =-O143 -> 139541.89
T23: Other Income | U23: =+M19 -> 4246.5051 | V23: =+N19 -> 5795.6285 | W23: =+O19 -> 7246.9913
B24: Finance Expenses | D24: 6503.15 | E24: 10173.2 | F24: 12368.28 | G24: 11505.63 | H24: 9960.08 | I24: 8090.97 | J24: 7672.93 | K24: 7592.07 | L24: 11229.88 | M24: =M237 -> 17937.057 | N24: =N237 -> 28214.235 | O24: =O237 -> 37842.85 | P24: =P237 -> 42004.948
T25: Revenue | U25: =+U16/U6-1 -> 0.059323764 | V25: =+V16/V6-1 -> -0.0095821157 | W25: =+W16/W6-1 -> -0.0054581007
T26: EBITDA | U26: =+U17/U7-1 -> 0.044143224 | V26: =+V17/V7-1 -> 0.021511078 | W26: =+W17/W7-1 -> 0.024125755
B27: PBT Before Exceptionals | D27: =D22-D24 -> -441.99 | E27: =E22-E24 -> -58.14 | F27: =F22-F24 -> -2106.77 | G27: =G22-G24 -> -11.09 | H27: =H22-H24 -> -2271.37 | I27: =I22-I24 -> -548.37 | J27: =J22-J24 -> 1607.34 | K27: =K22-K24-K25 -> 3589.9 | L27: =L22-L24-L25 -> 6741.47 | M27: =M22-M24 -> 12086.827 | N27: =N22-N24-N25 -> 23058.194 | O27: =O22-O24-O25 -> 31418.654 | P27: =P22-P24-P25 -> 39019.59 | T27: PAT | U27: =+U19/U9-1 -> 0.089202679 | V27: =+V19/V9-1 -> 0.057014936 | W27: =+W19/W9-1 -> 0.031481919
B28: Exceptional item | D28: 0 | E28: 0 | F28: 0 | G28: 0 | H28: 3295.63 | I28: 394.36 | J28: 7486.91 | K28: -209.84 | L28: 26.77 | T28: Depreciation | U28: =+U20/U10-1 -> -0.06472817 | V28: =+V20/V10-1 -> 0.087821474 | W28: =+W20/W10-1 -> 0.11883001
T29: Finance Cost | U29: =+U21/U11-1 -> 0.045707358 | V29: =+V21/V11-1 -> -0.00070891655 | W29: =+W21/W11-1 -> 0.00024632272
B30: PBT after Exceptional | D30: =D27+D28 -> -441.99 | E30: =E27+E28 -> -58.14 | F30: =F27+F28 -> -2106.77 | G30: =G27+G28 -> -11.09 | H30: =H27+H28 -> 1024.26 | I30: =I27+I28 -> -154.01 | J30: =J27+J28 -> 9094.25 | K30: =K27+K28 -> 3380.06 | ... P30: =P27+P28 -> 39019.59 | T30: Capex | U30: =+U22/U12-1 -> 0.21531537 | V30: =+V22/V12-1 -> 0.2175022 | W30: =+W22/W12-1 -> 0.18910571
T31: Other Income | U31: =+U23/U13-1 -> -0.13999132 | V31: =+V23/V13-1 -> 0.081304887 | W31: =+W23/W13-1 -> 0.29160152
B32: Tax
B33: Current Tax | D33: 61.24 | E33: 223.35 | F33: 56.63 | G33: 215.17 | H33: 27.26 | I33: 55.48 | J33: 1069.21 | K33: 730.48 | L33: 1685.06
B34: Deferred Tax | D34: 1900.31 | E34: 187.17 | F34: -3019.77 | G34: -378.39 | H34: 511.92 | I34: -179.21 | J34: 1046.38 | K34: 141.67 | L34: 104.33
B35: Prior Period Tax | D35: 0 | E35: 0 | F35: 0 | G35: 0 | H35: -135.02 | I35: 1.46 | J35: 0.85
B36: Total Tax | D36: =SUM(D33:D35) -> 1961.55 | E36: =SUM(E33:E35) -> 410.52 | F36: =SUM(F33:F35) -> -2963.14 | G36: =SUM(G33:G35) -> -163.22 | H36: =SUM(H33:H35) -> 404.16 | I36: =SUM(I33:I35) -> -122.27 | J36: =SUM(J33:J35) -> 2116.44 | K36: =SUM(K33:K35) -> 872.15 | L36: =SUM(L33:L35) -> 1789.39 | M36: =M30*M37 -> 3195.5201 | N36: =N30*N37 -> 6096.1346 | O36: =O30*O37 -> 8306.4762 | P36: =P30*P37 -> 10316.015
B37: Effective tax rate, % | D37: =IF(ISERROR(D36/D30)," ",D36/D30) -> -4.4379963 | E37: =IF(ISERROR(E36/E30)," ",E36/E30) -> -7.0608875 | F37: =IF(ISERROR(F36/F30)," ",F36/F30) -> 1.4064848 | G37: =IF(ISERROR(G36/G30)," ",G36/G30) -> 14.717764 | H37: =IF(ISERROR(H36/H30)," ",H36/H30) -> 0.39458731 | I37: =IF(ISERROR(I36/I30)," ",I36/I30) -> 0.79390949 | J37: =IF(ISERROR(J36/J30)," ",J36/J30) -> 0.23272287 | K37: =IF(ISERROR(K36/K30)," ",K36/K30) -> 0.25802796 | L37: =IF(ISERROR(L36/L30)," ",L36/L30) -> 0.2643804 | M37: =L37 -> 0.2643804 | N37: =M37 -> 0.2643804 | O37: =N37 -> 0.2643804 | P37: =O37 -> 0.2643804
B39: PAT before Minority | D39: =D30-D36 -> -2403.54 | E39: =E30-E36 -> -468.66 | F39: =F30-F36 -> 856.37 | G39: =G30-G36 -> 152.13 | H39: =H30-H36 -> 620.1 | I39: =I30-I36 -> -31.74 | J39: =J30-J36 -> 6977.81 | K39: =K30-K36 -> 2507.91 | ... P39: =P30-P36 -> 28703.575
B41: Minority share | D41: 0 | E41: 0 | F41: 0 | G41: 0 | H41: -0.24 | I41: -0.33 | J41: -0.17 | K41: -12.87 | L41: -10.3
B43: PAT after Minority | D43: =D39-D41 -> -2403.54 | E43: =E39-E41 -> -468.66 | F43: =F39-F41 -> 856.37 | G43: =G39-G41 -> 152.13 | H43: =H39-H41 -> 620.34 | I43: =I39-I41 -> -31.41 | J43: =J39-J41 -> 6977.98 | K43: =K39-K41 -> 2520.78 | ... P43: =P39-P41 -> 28703.575
B44: margin, % | D44: =IF(ISERROR(D43/D5)," ",D43/D5) -> -0.21927429 | E44: =IF(ISERROR(E43/E5)," ",E43/E5) -> -0.028031598 | F44: =IF(ISERROR(F43/F5)," ",F43/F5) -> 0.048185009 | G44: =IF(ISERROR(G43/G5)," ",G43/G5) -> 0.00899249 | H44: =IF(ISERROR(H43/H5)," ",H43/H5) -> 0.041692262 | I44: =IF(ISERROR(I43/I5)," ",I43/I5) -> -0.0024256624 | J44: =IF(ISERROR(J43/J5)," ",J43/J5) -> 0.52893538 | K44: =IF(ISERROR(K43/K5)," ",K43/K5) -> 0.17939822 | ... P44: =IF(ISERROR(P43/P5)," ",P43/P5) -> 0.25268838
B45: growth, %
B46: Adjusted PAT | D46: =D43-D28 -> -2403.54 | E46: =E43-E28 -> -468.66 | F46: =F43-F28 -> 856.37 | G46: =G43-G28 -> 152.13 | H46: =H43-H28 -> -2675.29 | I46: =I43-I28 -> -425.77 | J46: =J43-J28 -> -508.93 | K46: =K43-K28 -> 2730.62 | ... P46: =P43-P28 -> 28703.575 | Q46: =(N46/K46)^(1/3)-1 -> 0.83825507 | R46: =(P46/K46)^(1/5)-1 -> 0.60079215
B47: margin, % | D47: =D46/D5 -> -0.21927429 | E47: =E46/E5 -> -0.028031598 | F47: =F46/F5 -> 0.048185009 | G47: =G46/G5 -> 0.00899249 | H47: =H46/H5 -> -0.17980284 | I47: =I46/I5 -> -0.03288043 | J47: =J46/J5 -> -0.038577222 | K47: =K46/K5 -> 0.19433206 | ... P47: =P46/P5 -> 0.25268838
B48: growth, % | M48: =M46/L46-1 -> 0.79174241 | N48: =N46/M46-1 -> 0.9077128 | O48: =O46/N46-1 -> 0.36258083 | P48: =P46/O46-1 -> 0.24192433
B50: No. of shares | D50: 522.21 | E50: 522.21 | F50: 522.21 | G50: 522.21 | J50: 605.1 | K50: 605.1 | L50: 605.1 | M50: =L50+Valuation!$C$36 -> 705.27889 | N50: =M50 -> 705.27889 | O50: =N50 -> 705.27889 | P50: =O50 -> 705.27889
B51: EPS | J51: =J43/J50 -> 11.531945 | K51: =K43/K50 -> 4.1658899 | L51: =L43/L50 -> 8.2451661 | M51: =M43/M50 -> 12.606795 | N51: =N43/N50 -> 24.050145 | O51: =O43/O50 -> 32.770267 | P51: =P43/P50 -> 40.698191
B52: Dividend+Dividend tax
D53: =+SUM(D56:D58)/$J$50 -> 19.124409 | E53: =+SUM(E56:E58)/$J$50 -> 18.35057 | F53: =+SUM(F56:F58)/$J$50 -> 30.442902 | G53: =+SUM(G56:G58)/$J$50 -> 30.697405 | H53: =+SUM(H56:H58)/$J$50 -> 31.544588 | I53: =+SUM(I56:I58)/$J$50 -> 31.409073 | J53: =+SUM(J56:J58)/$J$50 -> 42.817204 | K53: =+SUM(K56:K58)/$J$50 -> 74.54272 | ... P53: =+SUM(P56:P58)/$J$50 -> 258.27787
B54: Balance Sheet | D54: =D2 -> 2018 | E54: =E2 -> 2019 | F54: =F2 -> 2020 | G54: =G2 -> 2021 | H54: =H2 -> 2022 | I54: =I2 -> 2023 | J54: =J2 -> 2024 | K54: =K2 -> 2025 | L54: =L2 -> 2026 | M54: 2027E | N54: 2027E | O54: 2027E | P54: 2027E
B55: Shareholder's funds
B56: Share Capital | D56: 1044.42 | E56: 1044.42 | F56: 1044.42 | G56: 1044.42 | H56: 1044.42 | I56: 1044.42 | J56: 1044.42 | K56: 1210.18 | L56: 1210.78 | M56: =L56+Valuation!$C$42 -> 1411.1378 | N56: =M56 -> 1411.1378 | O56: =N56 -> 1411.1378 | P56: =O56 -> 1411.1378
B57: Reserves & Surplus | D57: 10527.76 | E57: 10059.51 | F57: 10876.58 | G57: 11030.58 | H57: 11543.21 | I57: 11461.21 | J57: 18364.27 | K57: 43895.62 | L57: 49404.04 | M57: =L57+M46-M52+Valuation!$C$43 -> 86094.989 | N57: =M57+N46-N52 -> 103057.05 | O57: =N57+O46-O52 -> 126169.23 | P57: =O57+P46-P52 -> 154872.8
B58: Instrument entirely in the nature of equity | D58: 0 | E58: 0 | F58: 6500 | G58: 6500 | H58: 6500 | I58: 6500 | J58: 6500 | K58: 0 | M58: =L58 -> 0 | N58: =M58 -> 0 | O58: =N58 -> 0 | P58: =O58 -> 0
B60: Minority Interest | D60: 0 | E60: 0 | F60: 0 | G60: 0 | H60: 1003.92 | I60: 298.99 | J60: 0.04 | K60: -12.88 | L60: -13.14 | M60: =L60 -> -13.14 | N60: =M60 -> -13.14 | O60: =N60 -> -13.14 | P60: =O60 -> -13.14
B62: Long Term Borrowings | D62: 81030.16 | E62: 91424.42 | F62: 92246.34 | G62: 82263.99 | H62: 69508.98 | I62: 80992.6 | J62: 76964.28 | K62: 98571.7 | L62: 167398.76
B63: Short Term Borrowings | D63: 11709.23 | E63: 4649.49 | F63: 8888.86 | G63: 3450.09 | H63: 6127.04 | I63: 5580.89 | J63: 5211.65 | K63: 5655.31 | L63: 22481.73
B64: Current Maturities of Long Term Borrowings
B65: opening | D65: =D62+D63+D64 -> 92739.39 | E65: =E62+E63+E64 -> 96073.91 | F65: =F62+F63+F64 -> 101135.2 | G65: =G62+G63+G64 -> 85714.08 | H65: =H62+H63+H64 -> 75636.02 | I65: =I62+I63+I64 -> 86573.49 | J65: =J62+J63+J64 -> 82175.93 | K65: =K62+K63+K64 -> 104227.01 | L65: =L62+L63+L64 -> 189880.49 | M65: =L68 -> 189880.49 | N65: =M68 -> 310810.27 | O65: =N68 -> 476755.19 | P65: =O68 -> 579581.16
B66: addition | M66: =SUM(Assumptions!DD88:DD135)-Valuation!$C$41 -> 126057.14 | N66: =SUM(Assumptions!DE88:DE135) -> 174903.16 | O66: =SUM(Assumptions!DF88:DF135) -> 117384.21 | P66: =SUM(Assumptions!DG88:DG135) -> 35224.077
B67: repayment | M67: =SUM(Assumptions!DL53:DL135) -> 5127.36 | N67: =SUM(Assumptions!DM53:DM135) -> 8958.24 | O67: =SUM(Assumptions!DN53:DN135) -> 14558.24 | P67: =SUM(Assumptions!DO53:DO135) -> 21870.24
B68: closing | D68: =D65+D66-D67 -> 92739.39 | E68: =E65+E66-E67 -> 96073.91 | F68: =F65+F66-F67 -> 101135.2 | G68: =G65+G66-G67 -> 85714.08 | H68: =H65+H66-H67 -> 75636.02 | I68: =I65+I66-I67 -> 86573.49 | J68: =J65+J66-J67 -> 82175.93 | K68: =K65+K66-K67 -> 104227.01 | ... P68: =P65+P66-P67 -> 592934.99
B69: Long term borrowings | D69: =D68 -> 92739.39 | E69: =E68 -> 96073.91 | F69: =F68 -> 101135.2 | G69: =G68 -> 85714.08 | H69: =H68 -> 75636.02 | I69: =I68 -> 86573.49 | J69: =J68 -> 82175.93 | K69: =K68 -> 104227.01 | ... P69: =P68 -> 592934.99
B70: Deferred Tax Liabilities (net) | D70: 1920.64 | E70: 2245.44 | F70: 255.87 | G70: 175.08 | H70: 901.29 | I70: 1600.13 | J70: 2119.85 | K70: 2968.3 | L70: 4388.86 | M70: =L70 -> 4388.86 | N70: =M70 -> 4388.86 | O70: =N70 -> 4388.86 | P70: =O70 -> 4388.86
B71: Other long term liabilities | D71: =141.37+768.27 -> 909.64 | E71: =0+2526.87 -> 2526.87 | F71: =2961.60+1912.20 -> 4873.8 | G71: =3368.52+3592.95 -> 6961.47 | H71: =3198+2681.99 -> 5879.99 | I71: =3253.29+381.06+6588.91 -> 10223.26 | J71: =2882+1035.1+10702.16 -> 14619.26 | K71: =5048.31+1916.17+17144.12 -> 24108.6 | L71: =8449.45+2483.15+19735.02 -> 30667.62 | M71: =L71 -> 30667.62 | N71: =M71 -> 30667.62 | O71: =N71 -> 30667.62 | P71: =O71 -> 30667.62
B72: Trade Payables
B73: Long term provisions | D73: 1.07 | E73: 3.4 | F73: 14.27 | G73: 15.92 | H73: 24.36 | I73: 52.89 | J73: 65.1 | K73: 100.57 | L73: 144.58 | M73: =L73 -> 144.58 | N73: =M73 -> 144.58 | O73: =N73 -> 144.58 | P73: =O73 -> 144.58
B75: Total Liabilities | D75: =SUM(D56:D57)+D60+SUM(D69:D73)+D58 -> 107142.92 | E75: =SUM(E56:E57)+E60+SUM(E69:E73)+E58 -> 111953.55 | F75: =SUM(F56:F57)+F60+SUM(F69:F73)+F58 -> 124700.14 | G75: =SUM(G56:G57)+G60+SUM(G69:G73)+G58 -> 111441.55 | H75: =SUM(H56:H57)+H60+SUM(H69:H73)+H58 -> 102533.21 | I75: =SUM(I56:I57)+I60+SUM(I69:I73)+I58 -> 117754.39 | J75: =SUM(J56:J57)+J60+SUM(J69:J73)+J58 -> 124888.87 | K75: =SUM(K56:K57)+K60+SUM(K69:K73)+K58 -> 176497.4 | ... P75: =SUM(P56:P57)+P60+SUM(P69:P73)+P58 -> 784406.85
B77: Non current assets
B78: Fixed assets | S78: =141444.1+7402.91 -> 148847.01
B79: Gross block | D79: 86689.27 | E79: 118243.78 | F79: =108690.98+5057.07 -> 113748.05 | G79: =107768.10+5226.63 -> 112994.73 | H79: =79602.57+5010.81 -> 84613.38 | I79: =88831.88+5221.28 -> 94053.16 | J79: =85619.81+4720.37 -> 90340.18 | K79: =141444.1+7402.91 -> 148847.01 | L79: =175940.88+11894.59 -> 187835.47 | M79: =L79+SUM(Assumptions!FH53:FH133) -> 306250.47 | N79: =M79+SUM(Assumptions!FI53:FI133) -> 481250.47 | O79: =N79+SUM(Assumptions!FJ53:FJ133) -> 709750.47 | P79: =O79+SUM(Assumptions!FK53:FK133) -> 797750.47 | S79: =890.74+24819.12 -> 25709.86
B80: Accumulated depreciation | D80: 6783.65 | E80: 12491.57 | F80: =17570.89+187.59 -> 17758.48 | G80: =22843.44+312.20 -> 23155.64 | H80: =22391.94+450.64 -> 22842.58 | I80: =27107.95+636.1 -> 27744.05 | J80: =22094.53+680.75 -> 22775.28 | K80: =24819.12+890.74 -> 25709.86 | L80: =29302.6+1216.79 -> 30519.39 | M80: =L80+M20 -> 37717.934 | N80: =M80+N20 -> 53057.476 | O80: =N80+O20 -> 74870.071 | P80: =O80+P20 -> 104401.84 | S80: =S78-S79 -> 123137.15
B81: Net block | D81: =D79-D80 -> 79905.62 | E81: =E79-E80 -> 105752.21 | F81: =F79-F80 -> 95989.57 | G81: =G79-G80 -> 89839.09 | H81: =H79-H80 -> 61770.8 | I81: =I79-I80 -> 66309.11 | J81: =J79-J80 -> 67564.9 | K81: =+K79-K80 -> 123137.15 | L81: =+L79-L80 -> 157316.08 | M81: =M79-M80 -> 268532.54 | N81: =N79-N80 -> 428192.99 | O81: =O79-O80 -> 634880.4 | P81: =P79-P80 -> 693348.63
B82: Capital work in progress | D82: 5047.28 | E82: 528.36 | F82: 2195.27 | G82: 972.01 | H82: 12728.02 | I82: 21473.36 | J82: 28284.25 | K82: 13623.37 | L82: 43576.6 | M82: =SUM(Assumptions!FP53:FP133) -> 122268.93 | N82: =SUM(Assumptions!FQ53:FQ133) -> 165897.88 | O82: =SUM(Assumptions!FR53:FR133) -> 76939.767 | P82: =SUM(Assumptions!FS53:FS133) -> 32969.863
B84: Tangible Assets
B85: Intangible Assets | D85: 3.61 | E85: 3.46 | F85: 3.31 | G85: 3.16 | H85: 0.32 | I85: 0.3 | J85: 0.28 | M85: =L85 -> 0 | N85: =M85 -> 0 | O85: =N85 -> 0 | P85: =O85 -> 0
B86: Intangible Assets Under Development
B88: Non current investments | D88: 0 | E88: 0 | F88: 0 | G88: 245.33 | H88: 245.33 | I88: 226.67 | J88: 14.02 | K88: =14.02+2750 -> 2764.02 | L88: 2750 | M88: =L88 -> 2750 | N88: =M88 -> 2750 | O88: =N88 -> 2750 | P88: =O88 -> 2750
B89: Deferred tax assets (net) | D89: 218.39 | E89: 355.86 | F89: 1299.28 | G89: 1613.73 | H89: 1597.55 | I89: 2475.51 | J89: 1928.5 | K89: 2634.51 | L89: 3949.72 | M89: =L89 -> 3949.72 | N89: =M89 -> 3949.72 | O89: =N89 -> 3949.72 | P89: =O89 -> 3949.72
B90: Trade Receivables
B91: Long term loans & advances | J91: 1168.02 | K91: 1874.35 | M91: =L91 -> 0 | N91: =M91 -> 0 | O91: =N91 -> 0 | P91: =O91 -> 0
B92: Other non-current assets | D92: =20.21+2376.88+204.25+12107.56 -> 14708.9 | E92: =37.50+678.84+289.22+4839.46 -> 5845.02 | F92: =31.23+934.90+339.26+1938.21 -> 3243.6 | G92: =26.56+2723.72+166.90+6643.81 -> 9560.99 | H92: =1223.37+412.69+7489.98 -> 9126.04 | I92: =1618.32+898.05+1846.82 -> 4363.19 | J92: =549.42+315.62+2619.85 -> 3484.89 | K92: =1188.84+651.1+346.33 -> 2186.27 | L92: =0.25+3161.33+262.59+4529.14 -> 7953.31 | M92: =L92 -> 7953.31 | N92: =M92 -> 7953.31 | O92: =N92 -> 7953.31 | P92: =O92 -> 7953.31
B94: Current Assets
B95: Current Investments | J95: 1498.68 | M95: =L95 -> 0 | N95: =M95 -> 0 | O95: =N95 -> 0 | P95: =O95 -> 0
B96: Inventories | D96: 0 | E96: 0 | F96: 0 | G96: 0 | K96: 39.27 | L96: 173.73 | M96: =L96 -> 173.73 | N96: =M96 -> 173.73 | O96: =N96 -> 173.73 | P96: =O96 -> 173.73
B97: Trade receivabels | D97: 1729.76 | E97: 5470.28 | F97: 6733.42 | G97: 7226.13 | H97: 9314.38 | I97: 6992.97 | J97: 4208.85 | K97: 3808.19 | L97: 3329.47 | M97: =(M219/365)*M$5 -> 3.9511465 | N97: =(N219/365)*N$5 -> 6.8239391 | O97: =(O219/365)*O$5 -> 9.377833 | P97: =(P219/365)*P$5 -> 11.203671
B98: Cash and bank balances | D98: =17296.47+5454.47 -> 22750.94 | E98: =11968.54+4069.17 -> 16037.71 | F98: =3200.88+3395.29 -> 6596.17 | G98: =4391.67+5038.25 -> 9429.92 | H98: =2846.35+4784.56 -> 7630.91 | I98: =5474.49+7910.09 -> 13384.58 | J98: =3091.59+10057.16 -> 13148.75 | K98: =12842.73+16317.59 -> 29160.32 | L98: =22309.43+39271.48 -> 61580.91 | M98: =M176 -> 35041.83 | N98: =N176 -> 16383.924 | O98: =O176 -> 26125.864 | P98: =P176 -> 54780.993
B99: Short term loans and advances | D99: 238.13 | E99: 722.48 | F99: 1202.87 | G99: 1621.99 | H99: 1623.18 | I99: 3439.39 | M99: =L99 -> 0 | N99: =M99 -> 0 | O99: =N99 -> 0 | P99: =O99 -> 0
B100: Other current assets | D100: =641.84+1021.13 -> 1662.97 | E100: =514.91+7176.28 -> 7691.19 | F100: =382.66+11588.12+25107.01 -> 37077.79 | G100: =606.42+3948.98 -> 4555.4 | H100: =1641.74+0.05+3188.85 -> 4830.64 | I100: =1050.03+0.05+2154.37 -> 3204.45 | J100: =10987.29+126.1+1583.48 -> 12696.87 | K100: =1744.06+2969.25+95.37 -> 4808.68 | L100: =1450.93+3226.58+95.76 -> 4773.27 | M100: =L100 -> 4773.27 | N100: =M100 -> 4773.27 | O100: =N100 -> 4773.27 | P100: =O100 -> 4773.27
B101: Total Current Assets | D101: =SUM(D95:D100) -> 26381.8 | E101: =SUM(E95:E100) -> 29921.66 | F101: =SUM(F95:F100) -> 51610.25 | G101: =SUM(G95:G100) -> 22833.44 | H101: =SUM(H95:H100) -> 23399.11 | I101: =SUM(I95:I100) -> 27021.39 | J101: =SUM(J95:J100) -> 31553.15 | K101: =SUM(K95:K100) -> 37816.46 | ... P101: =SUM(P95:P100) -> 59739.197
B103: Current Liabilities
B104: Trade payables | D104: =3.65+325.94 -> 329.59 | E104: =5.85+333.41 -> 339.26 | F104: =14.74+485.28 -> 500.02 | G104: =10.06+1486.58 -> 1496.64 | H104: =366.01+2364.09 -> 2730.1 | I104: =70.38+550.72 -> 621.1 | J104: =66.93+670.65 -> 737.58 | K104: =71.71+2175.55 -> 2247.26 | L104: =41.15+111.55 -> 152.7 | M104: =(M222/365)*M$5 -> 2375.8021 | N104: =(N222/365)*N$5 -> 4103.1961 | O104: =(O222/365)*O$5 -> 5638.8381 | P104: =(P222/365)*P$5 -> 6736.7044
B105: Other current liabilities | D105: =18561.00+195.59+36.50 -> 18793.09 | E105: =29577.95+433.74+101.92 -> 30113.61 | F105: =9312.51+608.63+0.04+19217.90 -> 29139.08 | G105: =11518.64+502.76+106.71 -> 12128.11 | H105: =311.34+2868.27+418.18+3.64 -> 3601.43 | I105: =308.73+2403.39+777.04+0.13 -> 3489.29 | J105: =305.55+6769.29+1031.97+259.69 -> 8366.5 | K105: =481.97+3323.42+1474.33 -> 5279.72 | L105: =633+6802.35+1637.53+477.09 -> 9549.97 | M105: =L105 -> 9549.97 | N105: =M105 -> 9549.97 | O105: =N105 -> 9549.97 | P105: =O105 -> 9549.97
B106: Short term provisions | D106: 0 | E106: 0.15 | F106: 2.04 | G106: 1.45 | H106: 2.43 | I106: 4.75 | J106: 5.06 | K106: 11.55 | L106: 17.19 | M106: =L106 -> 17.19 | N106: =M106 -> 17.19 | O106: =N106 -> 17.19 | P106: =O106 -> 17.19
B107: Total Current Liabilities | D107: =SUM(D104:D106) -> 19122.68 | E107: =SUM(E104:E106) -> 30453.02 | F107: =SUM(F104:F106) -> 29641.14 | G107: =SUM(G104:G106) -> 13626.2 | H107: =SUM(H104:H106) -> 6333.96 | I107: =SUM(I104:I106) -> 4115.14 | J107: =SUM(J104:J106) -> 9109.14 | K107: =SUM(K104:K106) -> 7538.53 | ... P107: =SUM(P104:P106) -> 16303.864
B109: Net Current Assets | D109: =D101-D107 -> 7259.12 | E109: =E101-E107 -> -531.36 | F109: =F101-F107 -> 21969.11 | G109: =G101-G107 -> 9207.24 | H109: =H101-H107 -> 17065.15 | I109: =I101-I107 -> 22906.25 | J109: =J101-J107 -> 22444.01 | K109: =K101-K107 -> 30277.93 | ... P109: =P101-P107 -> 43435.332
B111: Total Assets | D111: =SUM(D81:D86)+SUM(D88:D92)+D109 -> 107142.92 | E111: =SUM(E81:E86)+SUM(E88:E92)+E109 -> 111953.55 | F111: =SUM(F81:F86)+SUM(F88:F92)+F109 -> 124700.14 | G111: =SUM(G81:G86)+SUM(G88:G92)+G109 -> 111441.55 | H111: =SUM(H81:H86)+SUM(H88:H92)+H109 -> 102533.21 | I111: =SUM(I81:I86)+SUM(I88:I92)+I109 -> 117754.39 | J111: =SUM(J81:J86)+SUM(J88:J92)+J109 -> 124888.87 | K111: =SUM(K81:K86)+SUM(K88:K92)+K109 -> 176497.6 | ... P111: =SUM(P81:P86)+SUM(P88:P92)+P109 -> 784406.85
B112: Check | D112: =D75-D111 -> 0 | E112: =E75-E111 -> 1.4551915e-11 | F112: =F75-F111 -> 0 | G112: =G75-G111 -> -1.4551915e-11 | H112: =H75-H111 -> 0 | I112: =I75-I111 -> 0 | J112: =J75-J111 -> 0 | K112: =K75-K111 -> -0.2 | ... P112: =P75-P111 -> 0
B114: CASH FLOWS FROM OPERATING ACTIVITIES | D114: =D2 -> 2018 | E114: =E2 -> 2019 | F114: =F2 -> 2020 | G114: =G2 -> 2021 | H114: =H2 -> 2022 | I114: =I2 -> 2023 | J114: =J2 -> 2024 | K114: =K2 -> 2025 | ... P114: =P2 -> 2030E
B115: Profit/ (Loss) before tax | D115: -441.99 | E115: -58.14 | F115: -2106.77 | G115: -11.09 | H115: 1024.26 | I115: -154.01 | J115: 9094.25 | K115: 3380.36 | L115: 6768.24 | M115: =M30 -> 12086.827 | N115: =N30 -> 23058.194 | O115: =O30 -> 31418.654 | P115: =P30 -> 39019.59
B116: Adjustments for:
B117: Depreciation and amortisation expense | D117: 3668.95 | E117: 5708.07 | F117: 7000.8 | G117: 6217.8 | H117: 5462.75 | I117: 4848.02 | J117: 3081.38 | K117: 2873.13 | L117: 4679.02 | M117: =M20 -> 7198.5436 | N117: =N20 -> 15339.542 | O117: =O20 -> 21812.595 | P117: =P20 -> 29531.773
B118: Finance costs | D118: 6503.15 | E118: 10173.2 | F118: 12368.28 | G118: 11505.63 | H118: 9960.08 | I118: 8090.97 | J118: 7672.93 | K118: 7592.07 | L118: 11229.88 | M118: =M24 -> 17937.057 | N118: =N24 -> 28214.235 | O118: =O24 -> 37842.85 | P118: =P24 -> 42004.948
B119: Interest income | D119: -599.2 | E119: -1130.4 | F119: -616.15 | G119: -684.74 | H119: -513.08 | I119: -536.15 | J119: -1208.58 | K119: -1335.89 | L119: -2555.82 | M119: =-M19 -> -4246.5051 | N119: =-N19 -> -5795.6285 | O119: =-O19 -> -7246.9913 | P119: =-P19 -> -7874.3622
...

Sheet Assumptions
BN1: =IF(AND($J360>DG$304,$J360<=DI$304),IF($I360>DG$304,$J360-$I360,$J360-DG$304),IF($J360<=DG$304,0,IF(AND($I360>DG$304,$I360<=DI$304),DI$304-$I360,IF($I360>DI$304,0,DI$304-DG$304)))) -> 0
B2: Operational metrics | C2: Units | D2: FY24A | E2: FY25A | F2: FY26A | G2: FY27E | H2: FY28E | I2: FY29E | J2: FY30E | K2: FY31E | Y2: Year of operation
B3: REVENUE | C3: INR mn | R3: BESS assumptions
B4: Generation | E4: 14051.31 | F4: 20233.79 | G4: {=SUMPRODUCT(($D$53:$D$133<>"BESS")*FX$53:FX$133*AZ$53:AZ$133)} -> 25063.567 | H4: {=SUMPRODUCT(($D$53:$D$133<>"BESS")*FY$53:FY$133*BA$53:BA$133)} -> 52196.35 | I4: {=SUMPRODUCT(($D$53:$D$133<>"BESS")*FZ$53:FZ$133*BB$53:BB$133)} -> 75437.119 | J4: {=SUMPRODUCT(($D$53:$D$133<>"BESS")*GA$53:GA$133*BC$53:BC$133)} -> 97636.751 | K4: {=SUMPRODUCT(($D$53:$D$133<>"BESS")*GB$53:GB$133*BD$53:BD$133)} -> 97636.751 | R4: Storage sizing — FDRE (MWh/MW) | S4: 4
B5: BESS | G5: {=SUMPRODUCT(($D$53:$D$133="BESS")*FX$53:FX$133*AZ$53:AZ$133)} -> 14996.668 | H5: {=SUMPRODUCT(($D$53:$D$133="BESS")*FY$53:FY$133*BA$53:BA$133)} -> 16990.81 | I5: {=SUMPRODUCT(($D$53:$D$133="BESS")*FZ$53:FZ$133*BB$53:BB$133)} -> 19643.688 | J5: {=SUMPRODUCT(($D$53:$D$133="BESS")*GA$53:GA$133*BC$53:BC$133)} -> 15956.028 | K5: {=SUMPRODUCT(($D$53:$D$133="BESS")*GB$53:GB$133*BD$53:BD$133)} -> 15956.028 | R5: Storage sizing — Hybrid (MWh/MW) | S5: 1
B6: Total | E6: =E4+E5 -> 14051.31 | F6: =F4+F5 -> 20233.79 | G6: =G4+G5 -> 40060.235 | H6: =H4+H5 -> 69187.16 | I6: =I4+I5 -> 95080.807 | J6: =J4+J5 -> 113592.78 | K6: =K4+K5 -> 113592.78 | R6: Capex (INR mn/MWh) | S6: 9.3
B7: Growth | C7: % | F7: =IFERROR(F6/E6-1,"–") -> 0.43999314 | G7: =IFERROR(G6/F6-1,"–") -> 0.97986808 | H7: =IFERROR(H6/G6-1,"–") -> 0.72707824 | I7: =IFERROR(I6/H6-1,"–") -> 0.37425509 | J7: =IFERROR(J6/I6-1,"–") -> 0.19469726 | K7: =IFERROR(K6/J6-1,"–") -> 0 | R7: Cycles per day | S7: 1
B9: Fiscal year (helper) | D9: 2024 | E9: 2025 | F9: 2026 | G9: 2027 | H9: 2028 | I9: 2029 | J9: 2030 | K9: 2031 | R9: Depth of discharge | S9: 0.93
B10: OPERATIONAL CAPACITY (year-end) | R10: Round-trip efficiency | S10: 0.89
B11: Solar | C11: MW | D11: 1340 | E11: 2540 | F11: 2840 | G11: =SUMIFS($F$53:$F$133,$D$53:$D$133,$B11,$I$53:$I$133,"<="&G$9) -> 2840 | H11: =SUMIFS($F$53:$F$133,$D$53:$D$133,$B11,$I$53:$I$133,"<="&H$9) -> 3140 | I11: =SUMIFS($F$53:$F$133,$D$53:$D$133,$B11,$I$53:$I$133,"<="&I$9) -> 3140 | J11: =SUMIFS($F$53:$F$133,$D$53:$D$133,$B11,$I$53:$I$133,"<="&J$9) -> 3140 | K11: =SUMIFS($F$53:$F$133,$D$53:$D$133,$B11,$I$53:$I$133,"<="&K$9) -> 3140 | R11: Availability | S11: 0.99
B12: Wind | C12: MW | D12: 0 | E12: 0 | F12: 142 | G12: =SUMIFS($F$53:$F$133,$D$53:$D$133,$B12,$I$53:$I$133,"<="&G$9) -> 150 | H12: =SUMIFS($F$53:$F$133,$D$53:$D$133,$B12,$I$53:$I$133,"<="&H$9) -> 150 | I12: =SUMIFS($F$53:$F$133,$D$53:$D$133,$B12,$I$53:$I$133,"<="&I$9) -> 150 | J12: =SUMIFS($F$53:$F$133,$D$53:$D$133,$B12,$I$53:$I$133,"<="&J$9) -> 150 | K12: =SUMIFS($F$53:$F$133,$D$53:$D$133,$B12,$I$53:$I$133,"<="&K$9) -> 150 | R12: Discharge duration (hours) | S12: 4
B13: BESS (MWh) | D13: 0 | E13: 0 | F13: 1324 | G13: =SUMIFS($F$53:$F$133,$D$53:$D$133,"BESS",$I$53:$I$133,"<="&G$9) -> 11508 | H13: =SUMIFS($F$53:$F$133,$D$53:$D$133,"BESS",$I$53:$I$133,"<="&H$9) -> 16508 | I13: =SUMIFS($F$53:$F$133,$D$53:$D$133,"BESS",$I$53:$I$133,"<="&I$9) -> 23958 | J13: =SUMIFS($F$53:$F$133,$D$53:$D$133,"BESS",$I$53:$I$133,"<="&J$9) -> 23958 | K13: =SUMIFS($F$53:$F$133,$D$53:$D$133,"BESS",$I$53:$I$133,"<="&K$9) -> 23958 | R13: Tariff — short term (INR/kWh) | S13: 9
B14: Complex | C14: MW | D14: =D15+D16 -> 0 | E14: =E15+E16 -> 0 | F14: =F15+F16 -> 0 | G14: =G15+G16 -> 1030 | H14: =H15+H16 -> 2580 | I14: =I15+I16 -> 4780 | J14: =J15+J16 -> 5580 | K14: =K15+K16 -> 5980 | R14: Charging power cost (INR/kWh) | S14: 1.4
B15: Hybrid | C15: MW | D15: 0 | E15: 0 | F15: 0 | G15: =SUMIFS($F$53:$F$133,$D$53:$D$133,$B15,$I$53:$I$133,"<="&G$9) -> 0 | H15: =SUMIFS($F$53:$F$133,$D$53:$D$133,$B15,$I$53:$I$133,"<="&H$9) -> 300 | I15: =SUMIFS($F$53:$F$133,$D$53:$D$133,$B15,$I$53:$I$133,"<="&I$9) -> 750 | J15: =SUMIFS($F$53:$F$133,$D$53:$D$133,$B15,$I$53:$I$133,"<="&J$9) -> 750 | K15: =SUMIFS($F$53:$F$133,$D$53:$D$133,$B15,$I$53:$I$133,"<="&K$9) -> 750 | R15: Capacity charge — contracted (INR lakh/MW/month) | S15: 2.22
B16: FDRE | C16: MW | D16: 0 | E16: 0 | F16: 0 | G16: =SUMIFS($F$53:$F$133,$D$53:$D$133,$B16,$I$53:$I$133,"<="&G$9) -> 1030 | H16: =SUMIFS($F$53:$F$133,$D$53:$D$133,$B16,$I$53:$I$133,"<="&H$9) -> 2280 | I16: =SUMIFS($F$53:$F$133,$D$53:$D$133,$B16,$I$53:$I$133,"<="&I$9) -> 4030 | J16: =SUMIFS($F$53:$F$133,$D$53:$D$133,$B16,$I$53:$I$133,"<="&J$9) -> 4830 | K16: =SUMIFS($F$53:$F$133,$D$53:$D$133,$B16,$I$53:$I$133,"<="&K$9) -> 5230 | R16: O&M (INR mn/MWh/yr) | S16: 0.09
B17: Installed Capacity | C17: MW | D17: =D11+D12+D14 -> 1340 | E17: =E11+E12+E14 -> 2540 | F17: =F11+F12+F14 -> 2982 | G17: =G11+G12+G14 -> 4020 | H17: =H11+H12+H14 -> 5870 | I17: =I11+I12+I14 -> 8070 | J17: =J11+J12+J14 -> 8870 | K17: =K11+K12+K14 -> 9270 | R17: Depreciation life (years) | S17: 20
R18: Years on short-term before PPA | S18: 1
B19: CAPACITY ADDITIONS | C19: MW | R19: Construction period — BESS (months) | S19: 9
B20: Solar | D20: =SUMIFS($F$53:$F$133,$D$53:$D$133,$B20,$I$53:$I$133,D$9) -> 250 | E20: =SUMIFS($F$53:$F$133,$D$53:$D$133,$B20,$I$53:$I$133,E$9) -> 1200 | F20: =SUMIFS($F$53:$F$133,$D$53:$D$133,$B20,$I$53:$I$133,F$9) -> 300 | G20: =SUMIFS($F$53:$F$133,$D$53:$D$133,$B20,$I$53:$I$133,G$9) -> 0 | H20: =SUMIFS($F$53:$F$133,$D$53:$D$133,$B20,$I$53:$I$133,H$9) -> 300 | I20: =SUMIFS($F$53:$F$133,$D$53:$D$133,$B20,$I$53:$I$133,I$9) -> 0 | J20: =SUMIFS($F$53:$F$133,$D$53:$D$133,$B20,$I$53:$I$133,J$9) -> 0 | K20: =SUMIFS($F$53:$F$133,$D$53:$D$133,$B20,$I$53:$I$133,K$9) -> 0 | R20: Equivalent CUF | S20: =365*S7*S9*S11/8760 -> 0.0383625
B21: Wind | D21: =SUMIFS($F$53:$F$133,$D$53:$D$133,$B21,$I$53:$I$133,D$9) -> 0 | E21: =SUMIFS($F$53:$F$133,$D$53:$D$133,$B21,$I$53:$I$133,E$9) -> 0 | F21: =SUMIFS($F$53:$F$133,$D$53:$D$133,$B21,$I$53:$I$133,F$9) -> 142 | G21: =SUMIFS($F$53:$F$133,$D$53:$D$133,$B21,$I$53:$I$133,G$9) -> 8 | H21: =SUMIFS($F$53:$F$133,$D$53:$D$133,$B21,$I$53:$I$133,H$9) -> 0 | I21: =SUMIFS($F$53:$F$133,$D$53:$D$133,$B21,$I$53:$I$133,I$9) -> 0 | J21: =SUMIFS($F$53:$F$133,$D$53:$D$133,$B21,$I$53:$I$133,J$9) -> 0 | K21: =SUMIFS($F$53:$F$133,$D$53:$D$133,$B21,$I$53:$I$133,K$9) -> 0 | R21: Tariff — contracted equivalent (INR/kWh) | S21: =(S15/10*12/S12)/(8.766*S20) -> 1.980459
B22: BESS (MWh) | D22: =SUMIFS($F$53:$F$133,$D$53:$D$133,"BESS",$I$53:$I$133,D$9) -> 0 | E22: =SUMIFS($F$53:$F$133,$D$53:$D$133,"BESS",$I$53:$I$133,E$9) -> 0 | F22: =SUMIFS($F$53:$F$133,$D$53:$D$133,"BESS",$I$53:$I$133,F$9) -> 1324 | G22: =SUMIFS($F$53:$F$133,$D$53:$D$133,"BESS",$I$53:$I$133,G$9) -> 10184 | H22: =SUMIFS($F$53:$F$133,$D$53:$D$133,"BESS",$I$53:$I$133,H$9) -> 5000 | I22: =SUMIFS($F$53:$F$133,$D$53:$D$133,"BESS",$I$53:$I$133,I$9) -> 7450 | J22: =SUMIFS($F$53:$F$133,$D$53:$D$133,"BESS",$I$53:$I$133,J$9) -> 0 | K22: =SUMIFS($F$53:$F$133,$D$53:$D$133,"BESS",$I$53:$I$133,K$9) -> 0 | R22: Capex spend calibration
B23: Complex | D23: =D24+D25 -> 0 | E23: =E24+E25 -> 0 | F23: =F24+F25 -> 0 | G23: =G24+G25 -> 1030 | H23: =H24+H25 -> 1550 | I23: =I24+I25 -> 2200 | J23: =J24+J25 -> 800 | K23: =K24+K25 -> 400 | R23: Spend factor vs elapsed time | S23: 0.4109
B24: Hybrid | D24: =SUMIFS($F$53:$F$133,$D$53:$D$133,$B24,$I$53:$I$133,D$9) -> 0 | E24: =SUMIFS($F$53:$F$133,$D$53:$D$133,$B24,$I$53:$I$133,E$9) -> 0 | F24: =SUMIFS($F$53:$F$133,$D$53:$D$133,$B24,$I$53:$I$133,F$9) -> 0 | G24: =SUMIFS($F$53:$F$133,$D$53:$D$133,$B24,$I$53:$I$133,G$9) -> 0 | H24: =SUMIFS($F$53:$F$133,$D$53:$D$133,$B24,$I$53:$I$133,H$9) -> 300 | I24: =SUMIFS($F$53:$F$133,$D$53:$D$133,$B24,$I$53:$I$133,I$9) -> 450 | J24: =SUMIFS($F$53:$F$133,$D$53:$D$133,$B24,$I$53:$I$133,J$9) -> 0 | K24: =SUMIFS($F$53:$F$133,$D$53:$D$133,$B24,$I$53:$I$133,K$9) -> 0 | R24: CWIP implied by spend factor (INR mn) | S24: =SUMPRODUCT($K$53:$K$133,$O$53:$O$133) -> 48317.393
B25: FDRE | D25: =SUMIFS($F$53:$F$133,$D$53:$D$133,$B25,$I$53:$I$133,D$9) -> 0 | E25: =SUMIFS($F$53:$F$133,$D$53:$D$133,$B25,$I$53:$I$133,E$9) -> 0 | F25: =SUMIFS($F$53:$F$133,$D$53:$D$133,$B25,$I$53:$I$133,F$9) -> 0 | G25: =SUMIFS($F$53:$F$133,$D$53:$D$133,$B25,$I$53:$I$133,G$9) -> 1030 | H25: =SUMIFS($F$53:$F$133,$D$53:$D$133,$B25,$I$53:$I$133,H$9) -> 1250 | I25: =SUMIFS($F$53:$F$133,$D$53:$D$133,$B25,$I$53:$I$133,I$9) -> 1750 | J25: =SUMIFS($F$53:$F$133,$D$53:$D$133,$B25,$I$53:$I$133,J$9) -> 800 | K25: =SUMIFS($F$53:$F$133,$D$53:$D$133,$B25,$I$53:$I$133,K$9) -> 400 | R25: CWIP actual at 31-Mar-26 (INR mn) | S25: 43577
B26: Total Additions | D26: =D20+D21+D23 -> 250 | E26: =E20+E21+E23 -> 1200 | F26: =F20+F21+F23 -> 442 | G26: =G20+G21+G23 -> 1038 | H26: =H20+H21+H23 -> 1850 | I26: =I20+I21+I23 -> 2200 | J26: =J20+J21+J23 -> 800 | K26: =K20+K21+K23 -> 400 | R26: Construction period — generation (months) | S26: 24
R27: Cost escalation (p.a.) | S27: 0.05
B28: SEGMENT FINANCIALS
B29: Revenue — RE generation | C29: INR mn | D29: =D4 -> 0 | E29: =E4 -> 14051.31 | F29: =F4 -> 20233.79 | G29: =G4 -> 25063.567 | H29: =H4 -> 52196.35 | I29: =I4 -> 75437.119 | J29: =J4 -> 97636.751 | K29: =K4 -> 97636.751
B30: Revenue — BESS | C30: INR mn | D30: =D5 -> 0 | E30: =E5 -> 0 | F30: =F5 -> 0 | G30: =G5 -> 14996.668 | H30: =H5 -> 16990.81 | I30: =I5 -> 19643.688 | J30: =J5 -> 15956.028 | K30: =K5 -> 15956.028
B31: Total revenue | C31: INR mn | D31: =D29+D30 -> 0 | E31: =E29+E30 -> 14051.31 | F31: =F29+F30 -> 20233.79 | G31: =G29+G30 -> 40060.235 | H31: =H29+H30 -> 69187.16 | I31: =I29+I30 -> 95080.807 | J31: =J29+J30 -> 113592.78 | K31: =K29+K30 -> 113592.78
B33: Cost of power purchased — BESS charging | C33: INR mn | D33: {=IFERROR(SUMPRODUCT(($D$53:$D$133="BESS")*(Y$53:Y$133>0)*(Y$53:Y$133<=$S$18)*AW$53:AW$133)*D34/$S$10,0)} -> 0 | E33: {=IFERROR(SUMPRODUCT(($D$53:$D$133="BESS")*(Z$53:Z$133>0)*(Z$53:Z$133<=$S$18)*AX$53:AX$133)*E34/$S$10,0)} -> 0 | F33: {=IFERROR(SUMPRODUCT(($D$53:$D$133="BESS")*(AA$53:AA$133>0)*(AA$53:AA$133<=$S$18)*AY$53:AY$133)*F34/$S$10,0)} -> 0 | G33: {=IFERROR(SUMPRODUCT(($D$53:$D$133="BESS")*(AB$53:AB$133>0)*(AB$53:AB$133<=$S$18)*AZ$53:AZ$133)*G34/$S$10,0)} -> 2621.1405 | H33: {=IFERROR(SUMPRODUCT(($D$53:$D$133="BESS")*(AC$53:AC$133>0)*(AC$53:AC$133<=$S$18)*BA$53:BA$133)*H34/$S$10,0)} -> 1630.0968 | I33: {=IFERROR(SUMPRODUCT(($D$53:$D$133="BESS")*(AD$53:AD$133>0)*(AD$53:AD$133<=$S$18)*BB$53:BB$133)*I34/$S$10,0)} -> 1511.7483 | J33: {=IFERROR(SUMPRODUCT(($D$53:$D$133="BESS")*(AE$53:AE$133>0)*(AE$53:AE$133<=$S$18)*BC$53:BC$133)*J34/$S$10,0)} -> 0 | K33: {=IFERROR(SUMPRODUCT(($D$53:$D$133="BESS")*(AF$53:AF$133>0)*(AF$53:AF$133<=$S$18)*BD$53:BD$133)*K34/$S$10,0)} -> 0
B34: charging cost | C34: INR / kWh | E34: =$S$14 -> 1.4 | F34: =$S$14 -> 1.4 | G34: =$S$14 -> 1.4 | H34: =$S$14 -> 1.4 | I34: =$S$14 -> 1.4 | J34: =$S$14 -> 1.4 | K34: =$S$14 -> 1.4
B35: Employee benefit expenses | C35: INR mn | D35: =D36*D17 -> 0 | E35: =E36*E17 -> 528.32 | F35: =F36*F17 -> 620.256 | G35: =G36*G17 -> 877.968 | H35: =H36*H17 -> 1346.1084 | I35: =I36*I17 -> 1943.143 | J35: =J36*J17 -> 2242.5604 | K35: =K36*K17 -> 2460.8751
B36: employee cost per MW | C36: INR mn / MW | D36: =D29*D33 -> 0 | E36: 0.208 | F36: 0.208 | G36: =F36*(1+$S$27) -> 0.2184 | H36: =G36*(1+$S$27) -> 0.22932 | I36: =H36*(1+$S$27) -> 0.240786 | J36: =I36*(1+$S$27) -> 0.2528253 | K36: =J36*(1+$S$27) -> 0.26546657
B37: Other expenses (O&M, insurance, admin) | C37: INR mn | D37: =D38*D17+D13*$S$16 -> 0 | E37: =E38*E17+E13*$S$16 -> 1534.16 | F37: =F38*F17+F13*$S$16 -> 1920.288 | G37: =G38*G17+G13*$S$16 -> 3585.204 | H37: =H38*H17+H13*$S$16 -> 5394.6117 | I37: =I38*I17+I13*$S$16 -> 7798.8084 | J37: =J38*J17+J13*$S$16 -> 8668.2704 | K37: =K38*K17+K13*$S$16 -> 9302.2226
B38: other expenses per MW | C38: INR mn / MW | D38: =D36+D37 -> 0 | E38: 0.604 | F38: 0.604 | G38: =F38*(1+$S$27) -> 0.6342 | H38: =G38*(1+$S$27) -> 0.66591 | I38: =H38*(1+$S$27) -> 0.6992055 | J38: =I38*(1+$S$27) -> 0.73416578 | K38: =J38*(1+$S$27) -> 0.77087406
B39: Total expenses | C39: INR mn | D39: =D33+D35+D37 -> 0 | E39: =E33+E35+E37 -> 2062.48 | F39: =F33+F35+F37 -> 2540.544 | G39: =G33+G35+G37 -> 7084.3125 | H39: =H33+H35+H37 -> 8370.8169 | I39: =I33+I35+I37 -> 11253.7 | J39: =J33+J35+J37 -> 10910.831 | K39: =K33+K35+K37 -> 11763.098
B41: EBITDA | C41: INR mn | D41: =D31-D39 -> 0 | E41: =E31-E39 -> 11988.83 | F41: =F31-F39 -> 17693.246 | G41: =G31-G39 -> 32975.922 | H41: =H31-H39 -> 60816.343 | I41: =I31-I39 -> 83827.107 | J41: =J31-J39 -> 102681.95 | K41: =K31-K39 -> 101829.68
B42: EBITDA margin — blended | C42: % | D42: =IFERROR(D41/D31,"–") -> – | E42: =IFERROR(E41/E31,"–") -> 0.85321796 | F42: =IFERROR(F41/F31,"–") -> 0.87444053 | G42: =IFERROR(G41/G31,"–") -> 0.82315849 | H42: =IFERROR(H41/H31,"–") -> 0.87901199 | I42: =IFERROR(I41/I31,"–") -> 0.88164068 | J42: =IFERROR(J41/J31,"–") -> 0.90394785 | K42: =IFERROR(K41/K31,"–") -> 0.89644502
B44: EBITDA — RE generation | C44: INR mn | D44: =IFERROR(D29-(D35+D37)*D29/D31,0) -> 0 | E44: =IFERROR(E29-(E35+E37)*E29/E31,0) -> 11988.83 | F44: =IFERROR(F29-(F35+F37)*F29/F31,0) -> 17693.246 | G44: =IFERROR(G29-(G35+G37)*G29/G31,0) -> 22271.197 | H44: =IFERROR(H29-(H35+H37)*H29/H31,0) -> 47110.999 | I44: =IFERROR(I29-(I35+I37)*I29/I31,0) -> 67707.854 | J44: =IFERROR(J29-(J35+J37)*J29/J31,0) -> 88258.531 | K44: =IFERROR(K29-(K35+K37)*K29/K31,0) -> 87525.98
B45: EBITDA — BESS | C45: INR mn | D45: =IFERROR(D30-D33-(D35+D37)*D30/D31,0) -> 0 | E45: =IFERROR(E30-E33-(E35+E37)*E30/E31,0) -> 0 | F45: =IFERROR(F30-F33-(F35+F37)*F30/F31,0) -> 0 | G45: =IFERROR(G30-G33-(G35+G37)*G30/G31,0) -> 10704.726 | H45: =IFERROR(H30-H33-(H35+H37)*H30/H31,0) -> 13705.344 | I45: =IFERROR(I30-I33-(I35+I37)*I30/I31,0) -> 16119.253 | J45: =IFERROR(J30-J33-(J35+J37)*J30/J31,0) -> 14423.417 | K45: =IFERROR(K30-K33-(K35+K37)*K30/K31,0) -> 14303.702
B46: EBITDA margin — RE generation | C46: % | D46: =IFERROR(D44/D29,"–") -> – | E46: =IFERROR(E44/E29,"–") -> 0.85321796 | F46: =IFERROR(F44/F29,"–") -> 0.87444053 | G46: =IFERROR(G44/G29,"–") -> 0.88858847 | H46: =IFERROR(H44/H29,"–") -> 0.90257267 | I46: =IFERROR(I44/I29,"–") -> 0.89754029 | J46: =IFERROR(J44/J29,"–") -> 0.90394785 | K46: =IFERROR(K44/K29,"–") -> 0.89644502
B47: EBITDA margin — BESS | C47: % | D47: =IFERROR(D45/D30,"–") -> – | E47: =IFERROR(E45/E30,"–") -> – | F47: =IFERROR(F45/F30,"–") -> – | G47: =IFERROR(G45/G30,"–") -> 0.71380695 | H47: =IFERROR(H45/H30,"–") -> 0.80663276 | I47: =IFERROR(I45/I30,"–") -> 0.82058182 | J47: =IFERROR(J45/J30,"–") -> 0.90394785 | K47: =IFERROR(K45/K30,"–") -> 0.89644502 | DZ47: Interest | EP47: Interest on Working Capital (interest on 1 month of O&M, 15% of O&M, 45days receivables)
B49: Projects | P49: 45382 | Q49: 45747 | R49: 46112 | S49: 46477 | T49: 46843 | U49: 47208 | V49: 47573 | W49: 47938 | Y49: 45382 | Z49: 45747 | AA49: 46112 | AB49: 46477 | AC49: 46843 | AD49: 47208 | AE49: 47573 | AF49: 47938 | AH49: 45747 | AI49: 46112 | AJ49: 46477 | AK49: 46843 | AL49: 47208 | AM49: 47573 | AN49: 47938 | AP49: 45747 | AQ49: 46112 | AR49: 46477 | AS49: 46843 | AT49: 47208 | AU49: 47573 | AV49: 47938 | AX49: 45747 | AY49: 46112 | AZ49: 46477 | BA49: 46843 | BB49: 47208 | BC49: 47573 | BD49: 47938 | BF49: 45747 | BG49: 46112 | BH49: 46477 | BI49: 46843 | BJ49: 47208 | BK49: 47573 | BL49: 47938 | BN49: 45747 | BO49: 46112 | BP49: 46477 | BQ49: 46843 | BR49: 47208 | BS49: 47573 | BT49: 47938 | BV49: 45747 | BW49: 46112 | BX49: 46477 | BY49: 46843 | BZ49: 47208 | CA49: 47573 | CB49: 47938 | CD49: 45747 | CE49: 46112 | CF49: 46477 | CG49: 46843 | CH49: 47208 | CI49: 47573 | CJ49: 47938 | CL49: 45747 | CM49: 46112 | CN49: 46477 | CO49: 46843 | CP49: 47208 | CQ49: 47573 | CR49: 47938 | CT49: 45747 | CU49: 46112 | CV49: 46477 | CW49: 46843 | CX49: 47208 | CY49: 47573 | CZ49: 47938 | DB49: 45747 | DC49: 46112 | DD49: 46477 | DE49: 46843 | DF49: 47208 | DG49: 47573 | DH49: 47938 | DJ49: 45747 | DK49: 46112 | DL49: 46477 | DM49: 46843 | DN49: 47208 | DO49: 47573 | DP49: 47938 | DR49: 45747 | DS49: 46112 | DT49: 46477 | DU49: 46843 | DV49: 47208 | DW49: 47573 | DX49: 47938 | DZ49: 45747 | EA49: 46112 | EB49: 46477 | EC49: 46843 | ED49: 47208 | EE49: 47573 | EF49: 47938 | EH49: 45747 | EI49: 46112 | EJ49: 46477 | EK49: 46843 | EL49: 47208 | EM49: 47573 | EN49: 47938 | EP49: 45747 | EQ49: 46112 | ER49: 46477 | ES49: 46843 | ET49: 47208 | EU49: 47573 | EV49: 47938 | EX49: 45747 | EY49: 46112 | EZ49: 46477 | FA49: 46843 | FB49: 47208 | FC49: 47573 | FD49: 47938 | FF49: 45747 | FG49: 46112 | FH49: 46477 | FI49: 46843 | FJ49: 47208 | FK49: 47573 | FL49: 47938 | FN49: 45747 | FO49: 46112 | FP49: 46477 | FQ49: 46843 | FR49: 47208 | FS49: 47573 | FT49: 47938 | FV49: 45747 | FW49: 46112 | FX49: 46477 | FY49: 46843 | FZ49: 47208 | GA49: 47573 | GB49: 47938
B50: Operational | C50: Entity | D50: Type | E50: Status | F50: Capacity | G50: Construction start | H50: COD | I50: COD FY | J50: CAPEX | K50: CAPEX | L50: ROE % | M50: Tax % | N50: Tariff | O50: Spent to 31-Mar-26 | P50: No. of days operational | Y50: Year of operation | AH50: Capacity Operational | AP50: CUF/PLF | AX50: Generation MU | BF50: ROE pre-tax | BN50: Depreciation | BV50: Execution Spacing Days | CD50: Execution Spacing % | CL50: CAPEX each year | CT50: Equity Infusion each year | DB50: Debt Taken each year | DJ50: Repayment of Loan (1 yr moratorium, 25 year repayment) | DR50: Loans Outstanding | DY50: MCLR | DZ50: 0.07 | EA50: 0.07 | EB50: 0.07 | EC50: 0.07 | ED50: 0.07 | EE50: 0.07 | EF50: 0.07 | EH50: O&M | EI50: 0.0572 | EJ50: 0.0572 | EK50: 0.0572 | EL50: 0.0572 | EM50: 0.0572 | EN50: 0.0572 | EO50: MCLR | EP50: 0.07 | EQ50: 0.07 | ER50: 0.07 | ES50: 0.07 | ET50: 0.07 | EU50: 0.07 | EV50: 0.07 | EX50: Total | FF50: Gross Block Addition | FN50: CWIP | FV50: Tariff (INR/kWh)
B51: Projects | F51: In MW | G51: COD less build period | J51: (Rs mn/MW) | K51: (Rs mn.) | N51: (INR/kWh) | O51: % of capex | DY51: MCLR + 300bps | DZ51: =DZ50+3% -> 0.1 | EA51: =EA50+3% -> 0.1 | EB51: =EB50+3% -> 0.1 | EC51: =EC50+3% -> 0.1 | ED51: =ED50+3% -> 0.1 | EE51: =EE50+3% -> 0.1 | EG51: Solar | EH51: 0.8 | EI51: =EH51*(1+EI$50) -> 0.84576 | EJ51: =EI51*(1+EJ$50) -> 0.89413747 | EK51: =EJ51*(1+EK$50) -> 0.94528214 | EL51: =EK51*(1+EL$50) -> 0.99935227 | EM51: =EL51*(1+EM$50) -> 1.0565152 | EO51: MCLR + 300bps | EP51: =EP50+3% -> 0.1 | EQ51: =EQ50+3% -> 0.1 | ER51: =ER50+3% -> 0.1 | ES51: =ES50+3% -> 0.1 | ET51: =ET50+3% -> 0.1 | EU51: =EU50+3% -> 0.1
G52: =IF(NOT(ISNUMBER($H52)),"",IF($H52<=DATE(2026,3,31),$H52,EDATE($H52,-IF($D52="BESS",$S$19,$S$26)))) | BO52: 0.8 | CE52: =IF(SUM($BX52:$CB52)=0,0,BX52/SUM($BX52:$CB52)*(1-$O52)) -> 0 | CF52: =IF(SUM($BX52:$CB52)=0,0,BY52/SUM($BX52:$CB52)*(1-$O52)) -> 0 | CG52: =IF(SUM($BX52:$CB52)=0,0,BZ52/SUM($BX52:$CB52)*(1-$O52)) -> 0 | EG52: Others | EH52: 1 | EI52: =EH52*(1+EI$50) -> 1.0572 | EJ52: =EI52*(1+EJ$50) -> 1.1176718 | EK52: =EJ52*(1+EK$50) -> 1.1816027 | EL52: =EK52*(1+EL$50) -> 1.2491903 | EM52: =EL52*(1+EM$50) -> 1.320644
B53: =Key_New!D3 -> Gujarat | C53: =Key_New!B3 -> ACME Solar Technologies (Gujarat) Pvt Ltd | D53: =Key_New!E3 -> Solar | E53: =Key_New!C3 -> Operational | F53: =Key_New!F3 -> 15 | G53: =IF(NOT(ISNUMBER($H53)),"",IF($H53<=DATE(2026,3,31),$H53,EDATE($H53,-IF($D53="BESS",$S$19,$S$26)))) -> 40999 | H53: =Key_New!O3 -> 40999 | I53: =IF(MONTH(H53)<=3,YEAR(H53),YEAR(H53)+1) -> 2012 | J53: 70 | K53: =J53*F53 -> 1050 | L53: 0.12 | M53: 0.25 | N53: =Key_New!J3 -> 5 | O53: =IF(OR(NOT(ISNUMBER($G53)),NOT(ISNUMBER($H53)),$H53<=DATE(2026,3,31)),0,MIN(1,MAX(0,(DATE(2026,3,31)-$G53)/($H53-$G53)))*$S$23) -> 0 | P53: =IF(OR(ISERROR(P$49-$H53),(P$49-$H53)>=365),365,IF((P$49-$H53)<=0,0,P$49-$H53)) -> 365 | Q53: =IF(OR(ISERROR(Q$49-$H53),(Q$49-$H53)>=365),365,IF((Q$49-$H53)<=0,0,Q$49-$H53)) -> 365 | R53: =IF(OR(ISERROR(R$49-$H53),(R$49-$H53)>=365),365,IF((R$49-$H53)<=0,0,R$49-$H53)) -> 365 | S53: =IF(OR(ISERROR(S$49-$H53),(S$49-$H53)>=365),365,IF((S$49-$H53)<=0,0,S$49-$H53)) -> 365 | T53: =IF(OR(ISERROR(T$49-$H53),(T$49-$H53)>=365),365,IF((T$49-$H53)<=0,0,T$49-$H53)) -> 365 | U53: =IF(OR(ISERROR(U$49-$H53),(U$49-$H53)>=365),365,IF((U$49-$H53)<=0,0,U$49-$H53)) -> 365 | V53: =IF(OR(ISERROR(V$49-$H53),(V$49-$H53)>=365),365,IF((V$49-$H53)<=0,0,V$49-$H53)) -> 365 | W53: =IF(OR(ISERROR(W$49-$H53),(W$49-$H53)>=365),365,IF((W$49-$H53)<=0,0,W$49-$H53)) -> 365 | Y53: 12 | Z53: =IF(AND(P53=0,Q53>0),1,IF(Y53=0,0,Y53+1)) -> 13 | AA53: =IF(AND(Q53=0,R53>0),1,IF(Z53=0,0,Z53+1)) -> 14 | AB53: =IF(AND(R53=0,S53>0),1,IF(AA53=0,0,AA53+1)) -> 15 | AC53: =IF(AND(S53=0,T53>0),1,IF(AB53=0,0,AB53+1)) -> 16 | AD53: =IF(AND(T53=0,U53>0),1,IF(AC53=0,0,AC53+1)) -> 17 | AE53: =IF(AND(U53=0,V53>0),1,IF(AD53=0,0,AD53+1)) -> 18 | AF53: =IF(AND(V53=0,W53>0),1,IF(AE53=0,0,AE53+1)) -> 19 | AH53: =IF(AND(P53<=0,Q53>0),$F53,IF(P53>0,$F53,0)) -> 15 | AI53: =IF(AND(Q53<=0,R53>0),$F53,IF(Q53>0,$F53,0)) -> 15 | AJ53: =IF(AND(R53<=0,S53>0),$F53,IF(R53>0,$F53,0)) -> 15 | AK53: =IF(AND(S53<=0,T53>0),$F53,IF(S53>0,$F53,0)) -> 15 | AL53: =IF(AND(T53<=0,U53>0),$F53,IF(T53>0,$F53,0)) -> 15 | AM53: =IF(AND(U53<=0,V53>0),$F53,IF(U53>0,$F53,0)) -> 15 | AN53: =IF(AND(V53<=0,W53>0),$F53,IF(V53>0,$F53,0)) -> 15 | AP53: 0.25 | AQ53: 0.25 | AR53: 0.25 | AS53: 0.25 | AT53: 0.25 | AU53: 0.25 | AV53: 0.25 | AX53: =$F53*8.766*AP53*(Q53/365) -> 32.8725 | AY53: =$F53*8.766*AQ53*(R53/365) -> 32.8725 | AZ53: =$F53*8.766*AR53*(S53/365) -> 32.8725 | BA53: =$F53*8.766*AS53*(T53/365) -> 32.8725 | BB53: =$F53*8.766*AT53*(U53/365) -> 32.8725 | BC53: =$F53*8.766*AU53*(V53/365) -> 32.8725 | BD53: =$F53*8.766*AV53*(W53/365) -> 32.8725 | BE53: 0.2 | BF53: =$BE53*$K53*(Q53/365)*($L53/(1-$M53)) -> 33.6 | BG53: =$BE53*$K53*(R53/365)*($L53/(1-$M53)) -> 33.6 | BH53: =$BE53*$K53*(S53/365)*($L53/(1-$M53)) -> 33.6 | BI53: =$BE53*$K53*(T53/365)*($L53/(1-$M53)) -> 33.6 | BJ53: =$BE53*$K53*(U53/365)*($L53/(1-$M53)) -> 33.6 | BK53: =$BE53*$K53*(V53/365)*($L53/(1-$M53)) -> 33.6 | BL53: =$BE53*$K53*(W53/365)*($L53/(1-$M53)) -> 33.6 | BM53: 0.04 | BN53: =$BM53*$K53*(Q53/365) -> 42 | BO53: =($BM53*$K53*(R53/365)) -> 42 | BP53: =$BM53*$K53*(S53/365) -> 42 | BQ53: =$BM53*$K53*(T53/365) -> 42 | BR53: =$BM53*$K53*(U53/365) -> 42 | BS53: =$BM53*$K53*(V53/365) -> 42 | BT53: =$BM53*$K53*(W53/365) -> 42 | CC53: 0 | CD53: 0 | CE53: =IF(SUM($BX53:$CB53)=0,0,BX53/SUM($BX53:$CB53)*(1-$O53)) -> 0 | CF53: =IF(SUM($BX53:$CB53)=0,0,BY53/SUM($BX53:$CB53)*(1-$O53)) -> 0 | CG53: =IF(SUM($BX53:$CB53)=0,0,BZ53/SUM($BX53:$CB53)*(1-$O53)) -> 0 | CH53: =IF(SUM($BX53:$CB53)=0,0,CA53/SUM($BX53:$CB53)*(1-$O53)) -> 0 | CI53: =IF(SUM($BX53:$CB53)=0,0,CB53/SUM($BX53:$CB53)*(1-$O53)) -> 0 | CJ53: =$O53+SUM(CC53:CI53) -> 0 | CL53: =IF($K53*CC53<=0,,$K53*CC53) -> 0 | CM53: =IF($K53*CD53<=0,,$K53*CD53) -> 0 | CN53: =IF($K53*CE53<=0,,$K53*CE53) -> 0 | CO53: =IF($K53*CF53<=0,,$K53*CF53) -> 0 | CP53: =IF($K53*CG53<=0,,$K53*CG53) -> 0 | CQ53: =IF($K53*CH53<=0,,$K53*CH53) -> 0 | CR53: =IF($K53*CI53<=0,,$K53*CI53) -> 0 | CT53: =$BE53*CL53 -> 0 | CU53: =$BE53*CM53 -> 0 | CV53: =$BE53*CN53 -> 0 | CW53: =$BE53*CO53 -> 0 | CX53: =$BE53*CP53 -> 0 | CY53: =$BE53*CQ53 -> 0 | CZ53: =$BE53*CR53 -> 0 | DB53: =CL53-CT53 -> 0 | DC53: =CM53-CU53 -> 0 | DD53: =CN53-CV53 -> 0 | DE53: =CO53-CW53 -> 0 | DF53: =CP53-CX53 -> 0 | DG53: =CQ53-CY53 -> 0 | DH53: =CR53-CZ53 -> 0 | DJ53: =IF(Z53<=26,IF(AND(P53=0,Q53>0),0,IF(Q53>0,($K53*(1-$BE53))/25,0)),0) -> 33.6 | DK53: =IF(AA53<=26,IF(AND(Q53=0,R53>0),0,IF(R53>0,($K53*(1-$BE53))/25,0)),0) -> 33.6 | DL53: =IF(AB53<=26,IF(AND(R53=0,S53>0),0,IF(S53>0,($K53*(1-$BE53))/25,0)),0) -> 33.6 | DM53: =IF(AC53<=26,IF(AND(S53=0,T53>0),0,IF(T53>0,($K53*(1-$BE53))/25,0)),0) -> 33.6 | DN53: =IF(AD53<=26,IF(AND(T53=0,U53>0),0,IF(U53>0,($K53*(1-$BE53))/25,0)),0) -> 33.6 | DO53: =IF(AE53<=26,IF(AND(U53=0,V53>0),0,IF(V53>0,($K53*(1-$BE53))/25,0)),0) -> 33.6 | DP53: =IF(AF53<=26,IF(AND(V53=0,W53>0),0,IF(W53>0,($K53*(1-$BE53))/25,0)),0) -> 33.6 | DR53: =+IF(Z53>0,$K53*(1-$BE53)-SUM($DJ53:DJ53),DB53) -> 806.4 | DS53: =+IF(AA53>0,$K53*(1-$BE53)-SUM($DJ53:DK53),DC53) -> 772.8 | DT53: =+IF(AB53>0,$K53*(1-$BE53)-SUM($DJ53:DL53),DD53) -> 739.2 | DU53: =+IF(AC53>0,$K53*(1-$BE53)-SUM($DJ53:DM53),DE53) -> 705.6 | DV53: =+IF(AD53>0,$K53*(1-$BE53)-SUM($DJ53:DN53),DF53) -> 672 | DW53: =+IF(AE53>0,$K53*(1-$BE53)-SUM($DJ53:DO53),DG53) -> 638.4 | DX53: =+IF(AF53>0,$K53*(1-$BE53)-SUM($DJ53:DP53),DH53) -> 604.8 | DZ53: =DR53*(DZ$51)*(Q53/365) -> 80.64 | EA53: =DS53*(EA$51)*(R53/365) -> 77.28 | EB53: =DT53*(EB$51)*(S53/365) -> 73.92 | EC53: =DU53*(EC$51)*(T53/365) -> 70.56 | ED53: =DV53*(ED$51)*(U53/365) -> 67.2 | EE53: =DW53*(EE$51)*(V53/365) -> 63.84 | EF53: =DY53*(EF$51)*(W53/365) -> 0 | FM53: 0 | FN53: 0 | FO53: =IF(AA53<1,$K53*$O53,0) -> 0 | FV53: =IF($D53="BESS",IF(Z53<=$S$18,$S$13,$S$21),$N53) -> 5 | FW53: =IF($D53="BESS",IF(AA53<=$S$18,$S$13,$S$21),$N53) -> 5 | FX53: =IF($D53="BESS",IF(AB53<=$S$18,$S$13,$S$21),$N53) -> 5 | FY53: =IF($D53="BESS",IF(AC53<=$S$18,$S$13,$S$21),$N53) -> 5 | FZ53: =IF($D53="BESS",IF(AD53<=$S$18,$S$13,$S$21),$N53) -> 5 | GA53: =IF($D53="BESS",IF(AE53<=$S$18,$S$13,$S$21),$N53) -> 5 | GB53: =IF($D53="BESS",IF(AF53<=$S$18,$S$13,$S$21),$N53) -> 5
B54: =Key_New!D4 -> Madhya Pradesh | C54: =Key_New!B4 -> ACME Solar Energy MP Pvt Ltd | D54: =Key_New!E4 -> Solar | E54: =Key_New!C4 -> Operational | F54: =Key_New!F4 -> 25 | G54: =IF(NOT(ISNUMBER($H54)),"",IF($H54<=DATE(2026,3,31),$H54,EDATE($H54,-IF($D54="BESS",$S$19,$S$26)))) -> 41670 | H54: =Key_New!O4 -> 41670 | I54: =IF(MONTH(H54)<=3,YEAR(H54),YEAR(H54)+1) -> 2014 | J54: 70 | K54: =J54*F54 -> 1750 | L54: 0.12 | M54: 0.25 | N54: =Key_New!J4 -> 8.05 | O54: =IF(OR(NOT(ISNUMBER($G54)),NOT(ISNUMBER($H54)),$H54<=DATE(2026,3,31)),0,MIN(1,MAX(0,(DATE(2026,3,31)-$G54)/($H54-$G54)))*$S$23) -> 0 | P54: =IF(OR(ISERROR(P$49-$H54),(P$49-$H54)>=365),365,IF((P$49-$H54)<=0,0,P$49-$H54)) -> 365 | Q54: =IF(OR(ISERROR(Q$49-$H54),(Q$49-$H54)>=365),365,IF((Q$49-$H54)<=0,0,Q$49-$H54)) -> 365 | R54: =IF(OR(ISERROR(R$49-$H54),(R$49-$H54)>=365),365,IF((R$49-$H54)<=0,0,R$49-$H54)) -> 365 | S54: =IF(OR(ISERROR(S$49-$H54),(S$49-$H54)>=365),365,IF((S$49-$H54)<=0,0,S$49-$H54)) -> 365 | T54: =IF(OR(ISERROR(T$49-$H54),(T$49-$H54)>=365),365,IF((T$49-$H54)<=0,0,T$49-$H54)) -> 365 | U54: =IF(OR(ISERROR(U$49-$H54),(U$49-$H54)>=365),365,IF((U$49-$H54)<=0,0,U$49-$H54)) -> 365 | V54: =IF(OR(ISERROR(V$49-$H54),(V$49-$H54)>=365),365,IF((V$49-$H54)<=0,0,V$49-$H54)) -> 365 | W54: =IF(OR(ISERROR(W$49-$H54),(W$49-$H54)>=365),365,IF((W$49-$H54)<=0,0,W$49-$H54)) -> 365 | Y54: 10 | Z54: =IF(AND(P54=0,Q54>0),1,IF(Y54=0,0,Y54+1)) -> 11 | AA54: =IF(AND(Q54=0,R54>0),1,IF(Z54=0,0,Z54+1)) -> 12 | AB54: =IF(AND(R54=0,S54>0),1,IF(AA54=0,0,AA54+1)) -> 13 | AC54: =IF(AND(S54=0,T54>0),1,IF(AB54=0,0,AB54+1)) -> 14 | AD54: =IF(AND(T54=0,U54>0),1,IF(AC54=0,0,AC54+1)) -> 15 | AE54: =IF(AND(U54=0,V54>0),1,IF(AD54=0,0,AD54+1)) -> 16 | AF54: =IF(AND(V54=0,W54>0),1,IF(AE54=0,0,AE54+1)) -> 17 | AH54: =IF(AND(P54<=0,Q54>0),$F54,IF(P54>0,$F54,0)) -> 25 | AI54: =IF(AND(Q54<=0,R54>0),$F54,IF(Q54>0,$F54,0)) -> 25 | AJ54: =IF(AND(R54<=0,S54>0),$F54,IF(R54>0,$F54,0)) -> 25 | AK54: =IF(AND(S54<=0,T54>0),$F54,IF(S54>0,$F54,0)) -> 25 | AL54: =IF(AND(T54<=0,U54>0),$F54,IF(T54>0,$F54,0)) -> 25 | AM54: =IF(AND(U54<=0,V54>0),$F54,IF(U54>0,$F54,0)) -> 25 | AN54: =IF(AND(V54<=0,W54>0),$F54,IF(V54>0,$F54,0)) -> 25 | AP54: 0.25 | AQ54: 0.25 | AR54: 0.25 | AS54: 0.25 | AT54: 0.25 | AU54: 0.25 | AV54: 0.25 | AX54: =$F54*8.766*AP54*(Q54/365) -> 54.7875 | AY54: =$F54*8.766*AQ54*(R54/365) -> 54.7875 | AZ54: =$F54*8.766*AR54*(S54/365) -> 54.7875 | BA54: =$F54*8.766*AS54*(T54/365) -> 54.7875 | BB54: =$F54*8.766*AT54*(U54/365) -> 54.7875 | BC54: =$F54*8.766*AU54*(V54/365) -> 54.7875 | BD54: =$F54*8.766*AV54*(W54/365) -> 54.7875 | BE54: 0.2 | BF54: =$BE54*$K54*(Q54/365)*($L54/(1-$M54)) -> 56 | BG54: =$BE54*$K54*(R54/365)*($L54/(1-$M54)) -> 56 | BH54: =$BE54*$K54*(S54/365)*($L54/(1-$M54)) -> 56 | BI54: =$BE54*$K54*(T54/365)*($L54/(1-$M54)) -> 56 | BJ54: =$BE54*$K54*(U54/365)*($L54/(1-$M54)) -> 56 | BK54: =$BE54*$K54*(V54/365)*($L54/(1-$M54)) -> 56 | BL54: =$BE54*$K54*(W54/365)*($L54/(1-$M54)) -> 56 | BM54: 0.04 | BN54: =$BM54*$K54*(Q54/365) -> 70 | BO54: =($BM54*$K54*(R54/365)) -> 70 | BP54: =$BM54*$K54*(S54/365) -> 70 | BQ54: =$BM54*$K54*(T54/365) -> 70 | BR54: =$BM54*$K54*(U54/365) -> 70 | BS54: =$BM54*$K54*(V54/365) -> 70 | BT54: =$BM54*$K54*(W54/365) -> 70 | CC54: 0 | CD54: 0 | CE54: =IF(SUM($BX54:$CB54)=0,0,BX54/SUM($BX54:$CB54)*(1-$O54)) -> 0 | CF54: =IF(SUM($BX54:$CB54)=0,0,BY54/SUM($BX54:$CB54)*(1-$O54)) -> 0 | CG54: =IF(SUM($BX54:$CB54)=0,0,BZ54/SUM($BX54:$CB54)*(1-$O54)) -> 0 | CH54: =IF(SUM($BX54:$CB54)=0,0,CA54/SUM($BX54:$CB54)*(1-$O54)) -> 0 | CI54: =IF(SUM($BX54:$CB54)=0,0,CB54/SUM($BX54:$CB54)*(1-$O54)) -> 0 | CJ54: =$O54+SUM(CC54:CI54) -> 0 | CL54: =IF($K54*CC54<=0,,$K54*CC54) -> 0 | CM54: =IF($K54*CD54<=0,,$K54*CD54) -> 0 | CN54: =IF($K54*CE54<=0,,$K54*CE54) -> 0 | CO54: =IF($K54*CF54<=0,,$K54*CF54) -> 0 | CP54: =IF($K54*CG54<=0,,$K54*CG54) -> 0 | CQ54: =IF($K54*CH54<=0,,$K54*CH54) -> 0 | CR54: =IF($K54*CI54<=0,,$K54*CI54) -> 0 | CT54: =$BE54*CL54 -> 0 | CU54: =$BE54*CM54 -> 0 | CV54: =$BE54*CN54 -> 0 | CW54: =$BE54*CO54 -> 0 | CX54: =$BE54*CP54 -> 0 | CY54: =$BE54*CQ54 -> 0 | CZ54: =$BE54*CR54 -> 0 | DB54: =CL54-CT54 -> 0 | DC54: =CM54-CU54 -> 0 | DD54: =CN54-CV54 -> 0 | DE54: =CO54-CW54 -> 0 | DF54: =CP54-CX54 -> 0 | DG54: =CQ54-CY54 -> 0 | DH54: =CR54-CZ54 -> 0 | DJ54: =IF(Z54<=26,IF(AND(P54=0,Q54>0),0,IF(Q54>0,($K54*(1-$BE54))/25,0)),0) -> 56 | DK54: =IF(AA54<=26,IF(AND(Q54=0,R54>0),0,IF(R54>0,($K54*(1-$BE54))/25,0)),0) -> 56 | DL54: =IF(AB54<=26,IF(AND(R54=0,S54>0),0,IF(S54>0,($K54*(1-$BE54))/25,0)),0) -> 56 | DM54: =IF(AC54<=26,IF(AND(S54=0,T54>0),0,IF(T54>0,($K54*(1-$BE54))/25,0)),0) -> 56 | DN54: =IF(AD54<=26,IF(AND(T54=0,U54>0),0,IF(U54>0,($K54*(1-$BE54))/25,0)),0) -> 56 | DO54: =IF(AE54<=26,IF(AND(U54=0,V54>0),0,IF(V54>0,($K54*(1-$BE54))/25,0)),0) -> 56 | DP54: =IF(AF54<=26,IF(AND(V54=0,W54>0),0,IF(W54>0,($K54*(1-$BE54))/25,0)),0) -> 56 | DR54: =+IF(Z54>0,$K54*(1-$BE54)-SUM($DJ54:DJ54),DB54) -> 1344 | DS54: =+IF(AA54>0,$K54*(1-$BE54)-SUM($DJ54:DK54),DC54) -> 1288 | DT54: =+IF(AB54>0,$K54*(1-$BE54)-SUM($DJ54:DL54),DD54) -> 1232 | DU54: =+IF(AC54>0,$K54*(1-$BE54)-SUM($DJ54:DM54),DE54) -> 1176 | DV54: =+IF(AD54>0,$K54*(1-$BE54)-SUM($DJ54:DN54),DF54) -> 1120 | DW54: =+IF(AE54>0,$K54*(1-$BE54)-SUM($DJ54:DO54),DG54) -> 1064 | DX54: =+IF(AF54>0,$K54*(1-$BE54)-SUM($DJ54:DP54),DH54) -> 1008 | DZ54: =DR54*(DZ$51)*(Q54/365) -> 134.4 | EA54: =DS54*(EA$51)*(R54/365) -> 128.8 | EB54: =DT54*(EB$51)*(S54/365) -> 123.2 | EC54: =DU54*(EC$51)*(T54/365) -> 117.6 | ED54: =DV54*(ED$51)*(U54/365) -> 112 | EE54: =DW54*(EE$51)*(V54/365) -> 106.4 | EF54: =DY54*(EF$51)*(W54/365) -> 0 | FM54: 0 | FN54: 0 | FO54: =IF(AA54<1,$K54*$O54,0) -> 0 | FV54: =IF($D54="BESS",IF(Z54<=$S$18,$S$13,$S$21),$N54) -> 8.05 | FW54: =IF($D54="BESS",IF(AA54<=$S$18,$S$13,$S$21),$N54) -> 8.05 | FX54: =IF($D54="BESS",IF(AB54<=$S$18,$S$13,$S$21),$N54) -> 8.05 | FY54: =IF($D54="BESS",IF(AC54<=$S$18,$S$13,$S$21),$N54) -> 8.05 | FZ54: =IF($D54="BESS",IF(AD54<=$S$18,$S$13,$S$21),$N54) -> 8.05 | GA54: =IF($D54="BESS",IF(AE54<=$S$18,$S$13,$S$21),$N54) -> 8.05 | GB54: =IF($D54="BESS",IF(AF54<=$S$18,$S$13,$S$21),$N54) -> 8.05
B55: =Key_New!D5 -> Odisha | C55: =Key_New!B5 -> ACME Odisha Solar Power Pvt Ltd | D55: =Key_New!E5 -> Solar | E55: =Key_New!C5 -> Operational | F55: =Key_New!F5 -> 25 | G55: =IF(NOT(ISNUMBER($H55)),"",IF($H55<=DATE(2026,3,31),$H55,EDATE($H55,-IF($D55="BESS",$S$19,$S$26)))) -> 42185 | H55: =Key_New!O5 -> 42185 | I55: =IF(MONTH(H55)<=3,YEAR(H55),YEAR(H55)+1) -> 2016 | J55: 70 | K55: =J55*F55 -> 1750 | L55: 0.12 | M55: 0.25 | N55: =Key_New!J5 -> 7.28 | O55: =IF(OR(NOT(ISNUMBER($G55)),NOT(ISNUMBER($H55)),$H55<=DATE(2026,3,31)),0,MIN(1,MAX(0,(DATE(2026,3,31)-$G55)/($H55-$G55)))*$S$23) -> 0 | P55: =IF(OR(ISERROR(P$49-$H55),(P$49-$H55)>=365),365,IF((P$49-$H55)<=0,0,P$49-$H55)) -> 365 | Q55: =IF(OR(ISERROR(Q$49-$H55),(Q$49-$H55)>=365),365,IF((Q$49-$H55)<=0,0,Q$49-$H55)) -> 365 | R55: =IF(OR(ISERROR(R$49-$H55),(R$49-$H55)>=365),365,IF((R$49-$H55)<=0,0,R$49-$H55)) -> 365 | S55: =IF(OR(ISERROR(S$49-$H55),(S$49-$H55)>=365),365,IF((S$49-$H55)<=0,0,S$49-$H55)) -> 365 | T55: =IF(OR(ISERROR(T$49-$H55),(T$49-$H55)>=365),365,IF((T$49-$H55)<=0,0,T$49-$H55)) -> 365 | U55: =IF(OR(ISERROR(U$49-$H55),(U$49-$H55)>=365),365,IF((U$49-$H55)<=0,0,U$49-$H55)) -> 365 | V55: =IF(OR(ISERROR(V$49-$H55),(V$49-$H55)>=365),365,IF((V$49-$H55)<=0,0,V$49-$H55)) -> 365 | W55: =IF(OR(ISERROR(W$49-$H55),(W$49-$H55)>=365),365,IF((W$49-$H55)<=0,0,W$49-$H55)) -> 365 | Y55: 8 | Z55: =IF(AND(P55=0,Q55>0),1,IF(Y55=0,0,Y55+1)) -> 9 | AA55: =IF(AND(Q55=0,R55>0),1,IF(Z55=0,0,Z55+1)) -> 10 | AB55: =IF(AND(R55=0,S55>0),1,IF(AA55=0,0,AA55+1)) -> 11 | AC55: =IF(AND(S55=0,T55>0),1,IF(AB55=0,0,AB55+1)) -> 12 | AD55: =IF(AND(T55=0,U55>0),1,IF(AC55=0,0,AC55+1)) -> 13 | AE55: =IF(AND(U55=0,V55>0),1,IF(AD55=0,0,AD55+1)) -> 14 | AF55: =IF(AND(V55=0,W55>0),1,IF(AE55=0,0,AE55+1)) -> 15 | AH55: =IF(AND(P55<=0,Q55>0),$F55,IF(P55>0,$F55,0)) -> 25 | AI55: =IF(AND(Q55<=0,R55>0),$F55,IF(Q55>0,$F55,0)) -> 25 | AJ55: =IF(AND(R55<=0,S55>0),$F55,IF(R55>0,$F55,0)) -> 25 | AK55: =IF(AND(S55<=0,T55>0),$F55,IF(S55>0,$F55,0)) -> 25 | AL55: =IF(AND(T55<=0,U55>0),$F55,IF(T55>0,$F55,0)) -> 25 | AM55: =IF(AND(U55<=0,V55>0),$F55,IF(U55>0,$F55,0)) -> 25 | AN55: =IF(AND(V55<=0,W55>0),$F55,IF(V55>0,$F55,0)) -> 25 | AP55: 0.25 | AQ55: 0.25 | AR55: 0.25 | AS55: 0.25 | AT55: 0.25 | AU55: 0.25 | AV55: 0.25 | AX55: =$F55*8.766*AP55*(Q55/365) -> 54.7875 | AY55: =$F55*8.766*AQ55*(R55/365) -> 54.7875 | AZ55: =$F55*8.766*AR55*(S55/365) -> 54.7875 | BA55: =$F55*8.766*AS55*(T55/365) -> 54.7875 | BB55: =$F55*8.766*AT55*(U55/365) -> 54.7875 | BC55: =$F55*8.766*AU55*(V55/365) -> 54.7875 | BD55: =$F55*8.766*AV55*(W55/365) -> 54.7875 | BE55: 0.2 | BF55: =$BE55*$K55*(Q55/365)*($L55/(1-$M55)) -> 56 | BG55: =$BE55*$K55*(R55/365)*($L55/(1-$M55)) -> 56 | BH55: =$BE55*$K55*(S55/365)*($L55/(1-$M55)) -> 56 | BI55: =$BE55*$K55*(T55/365)*($L55/(1-$M55)) -> 56 | BJ55: =$BE55*$K55*(U55/365)*($L55/(1-$M55)) -> 56 | BK55: =$BE55*$K55*(V55/365)*($L55/(1-$M55)) -> 56 | BL55: =$BE55*$K55*(W55/365)*($L55/(1-$M55)) -> 56 | BM55: 0.04 | BN55: =$BM55*$K55*(Q55/365) -> 70 | BO55: =($BM55*$K55*(R55/365)) -> 70 | BP55: =$BM55*$K55*(S55/365) -> 70 | BQ55: =$BM55*$K55*(T55/365) -> 70 | BR55: =$BM55*$K55*(U55/365) -> 70 | BS55: =$BM55*$K55*(V55/365) -> 70 | BT55: =$BM55*$K55*(W55/365) -> 70 | CC55: 0 | CD55: 0 | CE55: =IF(SUM($BX55:$CB55)=0,0,BX55/SUM($BX55:$CB55)*(1-$O55)) -> 0 | CF55: =IF(SUM($BX55:$CB55)=0,0,BY55/SUM($BX55:$CB55)*(1-$O55)) -> 0 | CG55: =IF(SUM($BX55:$CB55)=0,0,BZ55/SUM($BX55:$CB55)*(1-$O55)) -> 0 | CH55: =IF(SUM($BX55:$CB55)=0,0,CA55/SUM($BX55:$CB55)*(1-$O55)) -> 0 | CI55: =IF(SUM($BX55:$CB55)=0,0,CB55/SUM($BX55:$CB55)*(1-$O55)) -> 0 | CJ55: =$O55+SUM(CC55:CI55) -> 0 | CL55: =IF($K55*CC55<=0,,$K55*CC55) -> 0 | CM55: =IF($K55*CD55<=0,,$K55*CD55) -> 0 | CN55: =IF($K55*CE55<=0,,$K55*CE55) -> 0 | CO55: =IF($K55*CF55<=0,,$K55*CF55) -> 0 | CP55: =IF($K55*CG55<=0,,$K55*CG55) -> 0 | CQ55: =IF($K55*CH55<=0,,$K55*CH55) -> 0 | CR55: =IF($K55*CI55<=0,,$K55*CI55) -> 0 | CT55: =$BE55*CL55 -> 0 | CU55: =$BE55*CM55 -> 0 | CV55: =$BE55*CN55 -> 0 | CW55: =$BE55*CO55 -> 0 | CX55: =$BE55*CP55 -> 0 | CY55: =$BE55*CQ55 -> 0 | CZ55: =$BE55*CR55 -> 0 | DB55: =CL55-CT55 -> 0 | DC55: =CM55-CU55 -> 0 | DD55: =CN55-CV55 -> 0 | DE55: =CO55-CW55 -> 0 | DF55: =CP55-CX55 -> 0 | DG55: =CQ55-CY55 -> 0 | DH55: =CR55-CZ55 -> 0 | DJ55: =IF(Z55<=26,IF(AND(P55=0,Q55>0),0,IF(Q55>0,($K55*(1-$BE55))/25,0)),0) -> 56 | DK55: =IF(AA55<=26,IF(AND(Q55=0,R55>0),0,IF(R55>0,($K55*(1-$BE55))/25,0)),0) -> 56 | DL55: =IF(AB55<=26,IF(AND(R55=0,S55>0),0,IF(S55>0,($K55*(1-$BE55))/25,0)),0) -> 56 | DM55: =IF(AC55<=26,IF(AND(S55=0,T55>0),0,IF(T55>0,($K55*(1-$BE55))/25,0)),0) -> 56 | DN55: =IF(AD55<=26,IF(AND(T55=0,U55>0),0,IF(U55>0,($K55*(1-$BE55))/25,0)),0) -> 56 | DO55: =IF(AE55<=26,IF(AND(U55=0,V55>0),0,IF(V55>0,($K55*(1-$BE55))/25,0)),0) -> 56 | DP55: =IF(AF55<=26,IF(AND(V55=0,W55>0),0,IF(W55>0,($K55*(1-$BE55))/25,0)),0) -> 56 | DR55: =+IF(Z55>0,$K55*(1-$BE55)-SUM($DJ55:DJ55),DB55) -> 1344 | DS55: =+IF(AA55>0,$K55*(1-$BE55)-SUM($DJ55:DK55),DC55) -> 1288 | DT55: =+IF(AB55>0,$K55*(1-$BE55)-SUM($DJ55:DL55),DD55) -> 1232 | DU55: =+IF(AC55>0,$K55*(1-$BE55)-SUM($DJ55:DM55),DE55) -> 1176 | DV55: =+IF(AD55>0,$K55*(1-$BE55)-SUM($DJ55:DN55),DF55) -> 1120 | DW55: =+IF(AE55>0,$K55*(1-$BE55)-SUM($DJ55:DO55),DG55) -> 1064 | DX55: =+IF(AF55>0,$K55*(1-$BE55)-SUM($DJ55:DP55),DH55) -> 1008 | DZ55: =DR55*(DZ$51)*(Q55/365) -> 134.4 | EA55: =DS55*(EA$51)*(R55/365) -> 128.8 | EB55: =DT55*(EB$51)*(S55/365) -> 123.2 | EC55: =DU55*(EC$51)*(T55/365) -> 117.6 | ED55: =DV55*(ED$51)*(U55/365) -> 112 | EE55: =DW55*(EE$51)*(V55/365) -> 106.4 | EF55: =DY55*(EF$51)*(W55/365) -> 0 | FM55: 0 | FN55: 0 | FO55: =IF(AA55<1,$K55*$O55,0) -> 0 | FV55: =IF($D55="BESS",IF(Z55<=$S$18,$S$13,$S$21),$N55) -> 7.28 | FW55: =IF($D55="BESS",IF(AA55<=$S$18,$S$13,$S$21),$N55) -> 7.28 | FX55: =IF($D55="BESS",IF(AB55<=$S$18,$S$13,$S$21),$N55) -> 7.28 | FY55: =IF($D55="BESS",IF(AC55<=$S$18,$S$13,$S$21),$N55) -> 7.28 | FZ55: =IF($D55="BESS",IF(AD55<=$S$18,$S$13,$S$21),$N55) -> 7.28 | GA55: =IF($D55="BESS",IF(AE55<=$S$18,$S$13,$S$21),$N55) -> 7.28 | GB55: =IF($D55="BESS",IF(AF55<=$S$18,$S$13,$S$21),$N55) -> 7.28
B56: =Key_New!D6 -> Chhattisgarh | C56: =Key_New!B6 -> ACME Raipur Solar Power Pvt Ltd | D56: =Key_New!E6 -> Solar | E56: =Key_New!C6 -> Operational | F56: =Key_New!F6 -> 30 | G56: =IF(NOT(ISNUMBER($H56)),"",IF($H56<=DATE(2026,3,31),$H56,EDATE($H56,-IF($D56="BESS",$S$19,$S$26)))) -> 42460 | H56: =Key_New!O6 -> 42460 | I56: =IF(MONTH(H56)<=3,YEAR(H56),YEAR(H56)+1) -> 2016 | J56: 70 | K56: =J56*F56 -> 2100 | L56: 0.12 | M56: 0.25 | N56: =Key_New!J6 -> 6.46 | O56: =IF(OR(NOT(ISNUMBER($G56)),NOT(ISNUMBER($H56)),$H56<=DATE(2026,3,31)),0,MIN(1,MAX(0,(DATE(2026,3,31)-$G56)/($H56-$G56)))*$S$23) -> 0 | P56: =IF(OR(ISERROR(P$49-$H56),(P$49-$H56)>=365),365,IF((P$49-$H56)<=0,0,P$49-$H56)) -> 365 | Q56: =IF(OR(ISERROR(Q$49-$H56),(Q$49-$H56)>=365),365,IF((Q$49-$H56)<=0,0,Q$49-$H56)) -> 365 | R56: =IF(OR(ISERROR(R$49-$H56),(R$49-$H56)>=365),365,IF((R$49-$H56)<=0,0,R$49-$H56)) -> 365 | S56: =IF(OR(ISERROR(S$49-$H56),(S$49-$H56)>=365),365,IF((S$49-$H56)<=0,0,S$49-$H56)) -> 365 | T56: =IF(OR(ISERROR(T$49-$H56),(T$49-$H56)>=365),365,IF((T$49-$H56)<=0,0,T$49-$H56)) -> 365 | U56: =IF(OR(ISERROR(U$49-$H56),(U$49-$H56)>=365),365,IF((U$49-$H56)<=0,0,U$49-$H56)) -> 365 | V56: =IF(OR(ISERROR(V$49-$H56),(V$49-$H56)>=365),365,IF((V$49-$H56)<=0,0,V$49-$H56)) -> 365 | W56: =IF(OR(ISERROR(W$49-$H56),(W$49-$H56)>=365),365,IF((W$49-$H56)<=0,0,W$49-$H56)) -> 365 | Y56: 8 | Z56: =IF(AND(P56=0,Q56>0),1,IF(Y56=0,0,Y56+1)) -> 9 | AA56: =IF(AND(Q56=0,R56>0),1,IF(Z56=0,0,Z56+1)) -> 10 | AB56: =IF(AND(R56=0,S56>0),1,IF(AA56=0,0,AA56+1)) -> 11 | AC56: =IF(AND(S56=0,T56>0),1,IF(AB56=0,0,AB56+1)) -> 12 | AD56: =IF(AND(T56=0,U56>0),1,IF(AC56=0,0,AC56+1)) -> 13 | AE56: =IF(AND(U56=0,V56>0),1,IF(AD56=0,0,AD56+1)) -> 14 | AF56: =IF(AND(V56=0,W56>0),1,IF(AE56=0,0,AE56+1)) -> 15 | AH56: =IF(AND(P56<=0,Q56>0),$F56,IF(P56>0,$F56,0)) -> 30 | AI56: =IF(AND(Q56<=0,R56>0),$F56,IF(Q56>0,$F56,0)) -> 30 | AJ56: =IF(AND(R56<=0,S56>0),$F56,IF(R56>0,$F56,0)) -> 30 | AK56: =IF(AND(S56<=0,T56>0),$F56,IF(S56>0,$F56,0)) -> 30 | AL56: =IF(AND(T56<=0,U56>0),$F56,IF(T56>0,$F56,0)) -> 30 | AM56: =IF(AND(U56<=0,V56>0),$F56,IF(U56>0,$F56,0)) -> 30 | AN56: =IF(AND(V56<=0,W56>0),$F56,IF(V56>0,$F56,0)) -> 30 | AP56: 0.25 | AQ56: 0.25 | AR56: 0.25 | AS56: 0.25 | AT56: 0.25 | AU56: 0.25 | AV56: 0.25 | AX56: =$F56*8.766*AP56*(Q56/365) -> 65.745 | AY56: =$F56*8.766*AQ56*(R56/365) -> 65.745 | AZ56: =$F56*8.766*AR56*(S56/365) -> 65.745 | BA56: =$F56*8.766*AS56*(T56/365) -> 65.745 | BB56: =$F56*8.766*AT56*(U56/365) -> 65.745 | BC56: =$F56*8.766*AU56*(V56/365) -> 65.745 | BD56: =$F56*8.766*AV56*(W56/365) -> 65.745 | BE56: 0.2 | BF56: =$BE56*$K56*(Q56/365)*($L56/(1-$M56)) -> 67.2 | BG56: =$BE56*$K56*(R56/365)*($L56/(1-$M56)) -> 67.2 | BH56: =$BE56*$K56*(S56/365)*($L56/(1-$M56)) -> 67.2 | BI56: =$BE56*$K56*(T56/365)*($L56/(1-$M56)) -> 67.2 | BJ56: =$BE56*$K56*(U56/365)*($L56/(1-$M56)) -> 67.2 | BK56: =$BE56*$K56*(V56/365)*($L56/(1-$M56)) -> 67.2 | BL56: =$BE56*$K56*(W56/365)*($L56/(1-$M56)) -> 67.2 | BM56: 0.04 | BN56: =$BM56*$K56*(Q56/365) -> 84 | BO56: =($BM56*$K56*(R56/365)) -> 84 | BP56: =$BM56*$K56*(S56/365) -> 84 | BQ56: =$BM56*$K56*(T56/365) -> 84 | BR56: =$BM56*$K56*(U56/365) -> 84 | BS56: =$BM56*$K56*(V56/365) -> 84 | BT56: =$BM56*$K56*(W56/365) -> 84 | CC56: 0 | CD56: 0 | CE56: =IF(SUM($BX56:$CB56)=0,0,BX56/SUM($BX56:$CB56)*(1-$O56)) -> 0 | CF56: =IF(SUM($BX56:$CB56)=0,0,BY56/SUM($BX56:$CB56)*(1-$O56)) -> 0 | CG56: =IF(SUM($BX56:$CB56)=0,0,BZ56/SUM($BX56:$CB56)*(1-$O56)) -> 0 | CH56: =IF(SUM($BX56:$CB56)=0,0,CA56/SUM($BX56:$CB56)*(1-$O56)) -> 0 | CI56: =IF(SUM($BX56:$CB56)=0,0,CB56/SUM($BX56:$CB56)*(1-$O56)) -> 0 | CJ56: =$O56+SUM(CC56:CI56) -> 0 | CL56: =IF($K56*CC56<=0,,$K56*CC56) -> 0 | CM56: =IF($K56*CD56<=0,,$K56*CD56) -> 0 | CN56: =IF($K56*CE56<=0,,$K56*CE56) -> 0 | CO56: =IF($K56*CF56<=0,,$K56*CF56) -> 0 | CP56: =IF($K56*CG56<=0,,$K56*CG56) -> 0 | CQ56: =IF($K56*CH56<=0,,$K56*CH56) -> 0 | CR56: =IF($K56*CI56<=0,,$K56*CI56) -> 0 | CT56: =$BE56*CL56 -> 0 | CU56: =$BE56*CM56 -> 0 | CV56: =$BE56*CN56 -> 0 | CW56: =$BE56*CO56 -> 0 | CX56: =$BE56*CP56 -> 0 | CY56: =$BE56*CQ56 -> 0 | CZ56: =$BE56*CR56 -> 0 | DB56: =CL56-CT56 -> 0 | DC56: =CM56-CU56 -> 0 | DD56: =CN56-CV56 -> 0 | DE56: =CO56-CW56 -> 0 | DF56: =CP56-CX56 -> 0 | DG56: =CQ56-CY56 -> 0 | DH56: =CR56-CZ56 -> 0 | DJ56: =IF(Z56<=26,IF(AND(P56=0,Q56>0),0,IF(Q56>0,($K56*(1-$BE56))/25,0)),0) -> 67.2 | DK56: =IF(AA56<=26,IF(AND(Q56=0,R56>0),0,IF(R56>0,($K56*(1-$BE56))/25,0)),0) -> 67.2 | DL56: =IF(AB56<=26,IF(AND(R56=0,S56>0),0,IF(S56>0,($K56*(1-$BE56))/25,0)),0) -> 67.2 | DM56: =IF(AC56<=26,IF(AND(S56=0,T56>0),0,IF(T56>0,($K56*(1-$BE56))/25,0)),0) -> 67.2 | DN56: =IF(AD56<=26,IF(AND(T56=0,U56>0),0,IF(U56>0,($K56*(1-$BE56))/25,0)),0) -> 67.2 | DO56: =IF(AE56<=26,IF(AND(U56=0,V56>0),0,IF(V56>0,($K56*(1-$BE56))/25,0)),0) -> 67.2 | DP56: =IF(AF56<=26,IF(AND(V56=0,W56>0),0,IF(W56>0,($K56*(1-$BE56))/25,0)),0) -> 67.2 | DR56: =+IF(Z56>0,$K56*(1-$BE56)-SUM($DJ56:DJ56),DB56) -> 1612.8 | DS56: =+IF(AA56>0,$K56*(1-$BE56)-SUM($DJ56:DK56),DC56) -> 1545.6 | DT56: =+IF(AB56>0,$K56*(1-$BE56)-SUM($DJ56:DL56),DD56) -> 1478.4 | DU56: =+IF(AC56>0,$K56*(1-$BE56)-SUM($DJ56:DM56),DE56) -> 1411.2 | DV56: =+IF(AD56>0,$K56*(1-$BE56)-SUM($DJ56:DN56),DF56) -> 1344 | DW56: =+IF(AE56>0,$K56*(1-$BE56)-SUM($DJ56:DO56),DG56) -> 1276.8 | DX56: =+IF(AF56>0,$K56*(1-$BE56)-SUM($DJ56:DP56),DH56) -> 1209.6 | DZ56: =DR56*(DZ$51)*(Q56/365) -> 161.28 | EA56: =DS56*(EA$51)*(R56/365) -> 154.56 | EB56: =DT56*(EB$51)*(S56/365) -> 147.84 | EC56: =DU56*(EC$51)*(T56/365) -> 141.12 | ED56: =DV56*(ED$51)*(U56/365) -> 134.4 | EE56: =DW56*(EE$51)*(V56/365) -> 127.68 | EF56: =DY56*(EF$51)*(W56/365) -> 0 | FM56: 0 | FN56: 0 | FO56: =IF(AA56<1,$K56*$O56,0) -> 0 | FV56: =IF($D56="BESS",IF(Z56<=$S$18,$S$13,$S$21),$N56) -> 6.46 | FW56: =IF($D56="BESS",IF(AA56<=$S$18,$S$13,$S$21),$N56) -> 6.46 | FX56: =IF($D56="BESS",IF(AB56<=$S$18,$S$13,$S$21),$N56) -> 6.46 | FY56: =IF($D56="BESS",IF(AC56<=$S$18,$S$13,$S$21),$N56) -> 6.46 | FZ56: =IF($D56="BESS",IF(AD56<=$S$18,$S$13,$S$21),$N56) -> 6.46 | GA56: =IF($D56="BESS",IF(AE56<=$S$18,$S$13,$S$21),$N56) -> 6.46 | GB56: =IF($D56="BESS",IF(AF56<=$S$18,$S$13,$S$21),$N56) -> 6.46
B57: =Key_New!D7 -> Punjab | C57: =Key_New!B7 -> ACME Solar Rooftop Systems Pvt Ltd | D57: =Key_New!E7 -> Solar | E57: =Key_New!C7 -> Operational | F57: =Key_New!F7 -> 30 | G57: =IF(NOT(ISNUMBER($H57)),"",IF($H57<=DATE(2026,3,31),$H57,EDATE($H57,-IF($D57="BESS",$S$19,$S$26)))) -> 42521 | H57: =Key_New!O7 -> 42521 | I57: =IF(MONTH(H57)<=3,YEAR(H57),YEAR(H57)+1) -> 2017 | J57: 70 | K57: =J57*F57 -> 2100 | L57: 0.12 | M57: 0.25 | N57: =Key_New!J7 -> 7.57 | O57: =IF(OR(NOT(ISNUMBER($G57)),NOT(ISNUMBER($H57)),$H57<=DATE(2026,3,31)),0,MIN(1,MAX(0,(DATE(2026,3,31)-$G57)/($H57-$G57)))*$S$23) -> 0 | P57: =IF(OR(ISERROR(P$49-$H57),(P$49-$H57)>=365),365,IF((P$49-$H57)<=0,0,P$49-$H57)) -> 365 | Q57: =IF(OR(ISERROR(Q$49-$H57),(Q$49-$H57)>=365),365,IF((Q$49-$H57)<=0,0,Q$49-$H57)) -> 365 | R57: =IF(OR(ISERROR(R$49-$H57),(R$49-$H57)>=365),365,IF((R$49-$H57)<=0,0,R$49-$H57)) -> 365 | S57: =IF(OR(ISERROR(S$49-$H57),(S$49-$H57)>=365),365,IF((S$49-$H57)<=0,0,S$49-$H57)) -> 365 | T57: =IF(OR(ISERROR(T$49-$H57),(T$49-$H57)>=365),365,IF((T$49-$H57)<=0,0,T$49-$H57)) -> 365 | U57: =IF(OR(ISERROR(U$49-$H57),(U$49-$H57)>=365),365,IF((U$49-$H57)<=0,0,U$49-$H57)) -> 365 | V57: =IF(OR(ISERROR(V$49-$H57),(V$49-$H57)>=365),365,IF((V$49-$H57)<=0,0,V$49-$H57)) -> 365 | W57: =IF(OR(ISERROR(W$49-$H57),(W$49-$H57)>=365),365,IF((W$49-$H57)<=0,0,W$49-$H57)) -> 365 | Y57: 7 | Z57: =IF(AND(P57=0,Q57>0),1,IF(Y57=0,0,Y57+1)) -> 8 | AA57: =IF(AND(Q57=0,R57>0),1,IF(Z57=0,0,Z57+1)) -> 9 | AB57: =IF(AND(R57=0,S57>0),1,IF(AA57=0,0,AA57+1)) -> 10 | AC57: =IF(AND(S57=0,T57>0),1,IF(AB57=0,0,AB57+1)) -> 11 | AD57: =IF(AND(T57=0,U57>0),1,IF(AC57=0,0,AC57+1)) -> 12 | AE57: =IF(AND(U57=0,V57>0),1,IF(AD57=0,0,AD57+1)) -> 13 | AF57: =IF(AND(V57=0,W57>0),1,IF(AE57=0,0,AE57+1)) -> 14 | AH57: =IF(AND(P57<=0,Q57>0),$F57,IF(P57>0,$F57,0)) -> 30 | AI57: =IF(AND(Q57<=0,R57>0),$F57,IF(Q57>0,$F57,0)) -> 30 | AJ57: =IF(AND(R57<=0,S57>0),$F57,IF(R57>0,$F57,0)) -> 30 | AK57: =IF(AND(S57<=0,T57>0),$F57,IF(S57>0,$F57,0)) -> 30 | AL57: =IF(AND(T57<=0,U57>0),$F57,IF(T57>0,$F57,0)) -> 30 | AM57: =IF(AND(U57<=0,V57>0),$F57,IF(U57>0,$F57,0)) -> 30 | AN57: =IF(AND(V57<=0,W57>0),$F57,IF(V57>0,$F57,0)) -> 30 | AP57: 0.25 | AQ57: 0.25 | AR57: 0.25 | AS57: 0.25 | AT57: 0.25 | AU57: 0.25 | AV57: 0.25 | AX57: =$F57*8.766*AP57*(Q57/365) -> 65.745 | AY57: =$F57*8.766*AQ57*(R57/365) -> 65.745 | AZ57: =$F57*8.766*AR57*(S57/365) -> 65.745 | BA57: =$F57*8.766*AS57*(T57/365) -> 65.745 | BB57: =$F57*8.766*AT57*(U57/365) -> 65.745 | BC57: =$F57*8.766*AU57*(V57/365) -> 65.745 | BD57: =$F57*8.766*AV57*(W57/365) -> 65.745 | BE57: 0.2 | BF57: =$BE57*$K57*(Q57/365)*($L57/(1-$M57)) -> 67.2 | BG57: =$BE57*$K57*(R57/365)*($L57/(1-$M57)) -> 67.2 | BH57: =$BE57*$K57*(S57/365)*($L57/(1-$M57)) -> 67.2 | BI57: =$BE57*$K57*(T57/365)*($L57/(1-$M57)) -> 67.2 | BJ57: =$BE57*$K57*(U57/365)*($L57/(1-$M57)) -> 67.2 | BK57: =$BE57*$K57*(V57/365)*($L57/(1-$M57)) -> 67.2 | BL57: =$BE57*$K57*(W57/365)*($L57/(1-$M57)) -> 67.2 | BM57: 0.04 | BN57: =$BM57*$K57*(Q57/365) -> 84 | BO57: =($BM57*$K57*(R57/365)) -> 84 | BP57: =$BM57*$K57*(S57/365) -> 84 | BQ57: =$BM57*$K57*(T57/365) -> 84 | BR57: =$BM57*$K57*(U57/365) -> 84 | BS57: =$BM57*$K57*(V57/365) -> 84 | BT57: =$BM57*$K57*(W57/365) -> 84 | CC57: 0 | CD57: 0 | CE57: =IF(SUM($BX57:$CB57)=0,0,BX57/SUM($BX57:$CB57)*(1-$O57)) -> 0 | CF57: =IF(SUM($BX57:$CB57)=0,0,BY57/SUM($BX57:$CB57)*(1-$O57)) -> 0 | CG57: =IF(SUM($BX57:$CB57)=0,0,BZ57/SUM($BX57:$CB57)*(1-$O57)) -> 0 | CH57: =IF(SUM($BX57:$CB57)=0,0,CA57/SUM($BX57:$CB57)*(1-$O57)) -> 0 | CI57: =IF(SUM($BX57:$CB57)=0,0,CB57/SUM($BX57:$CB57)*(1-$O57)) -> 0 | CJ57: =$O57+SUM(CC57:CI57) -> 0 | CL57: =IF($K57*CC57<=0,,$K57*CC57) -> 0 | CM57: =IF($K57*CD57<=0,,$K57*CD57) -> 0 | CN57: =IF($K57*CE57<=0,,$K57*CE57) -> 0 | CO57: =IF($K57*CF57<=0,,$K57*CF57) -> 0 | CP57: =IF($K57*CG57<=0,,$K57*CG57) -> 0 | CQ57: =IF($K57*CH57<=0,,$K57*CH57) -> 0 | CR57: =IF($K57*CI57<=0,,$K57*CI57) -> 0 | CT57: =$BE57*CL57 -> 0 | CU57: =$BE57*CM57 -> 0 | CV57: =$BE57*CN57 -> 0 | CW57: =$BE57*CO57 -> 0 | CX57: =$BE57*CP57 -> 0 | CY57: =$BE57*CQ57 -> 0 | CZ57: =$BE57*CR57 -> 0 | DB57: =CL57-CT57 -> 0 | DC57: =CM57-CU57 -> 0 | DD57: =CN57-CV57 -> 0 | DE57: =CO57-CW57 -> 0 | DF57: =CP57-CX57 -> 0 | DG57: =CQ57-CY57 -> 0 | DH57: =CR57-CZ57 -> 0 | DJ57: =IF(Z57<=26,IF(AND(P57=0,Q57>0),0,IF(Q57>0,($K57*(1-$BE57))/25,0)),0) -> 67.2 | DK57: =IF(AA57<=26,IF(AND(Q57=0,R57>0),0,IF(R57>0,($K57*(1-$BE57))/25,0)),0) -> 67.2 | DL57: =IF(AB57<=26,IF(AND(R57=0,S57>0),0,IF(S57>0,($K57*(1-$BE57))/25,0)),0) -> 67.2 | DM57: =IF(AC57<=26,IF(AND(S57=0,T57>0),0,IF(T57>0,($K57*(1-$BE57))/25,0)),0) -> 67.2 | DN57: =IF(AD57<=26,IF(AND(T57=0,U57>0),0,IF(U57>0,($K57*(1-$BE57))/25,0)),0) -> 67.2 | DO57: =IF(AE57<=26,IF(AND(U57=0,V57>0),0,IF(V57>0,($K57*(1-$BE57))/25,0)),0) -> 67.2 | DP57: =IF(AF57<=26,IF(AND(V57=0,W57>0),0,IF(W57>0,($K57*(1-$BE57))/25,0)),0) -> 67.2 | DR57: =+IF(Z57>0,$K57*(1-$BE57)-SUM($DJ57:DJ57),DB57) -> 1612.8 | DS57: =+IF(AA57>0,$K57*(1-$BE57)-SUM($DJ57:DK57),DC57) -> 1545.6 | DT57: =+IF(AB57>0,$K57*(1-$BE57)-SUM($DJ57:DL57),DD57) -> 1478.4 | DU57: =+IF(AC57>0,$K57*(1-$BE57)-SUM($DJ57:DM57),DE57) -> 1411.2 | DV57: =+IF(AD57>0,$K57*(1-$BE57)-SUM($DJ57:DN57),DF57) -> 1344 | DW57: =+IF(AE57>0,$K57*(1-$BE57)-SUM($DJ57:DO57),DG57) -> 1276.8 | DX57: =+IF(AF57>0,$K57*(1-$BE57)-SUM($DJ57:DP57),DH57) -> 1209.6 | DZ57: =DR57*(DZ$51)*(Q57/365) -> 161.28 | EA57: =DS57*(EA$51)*(R57/365) -> 154.56 | EB57: =DT57*(EB$51)*(S57/365) -> 147.84 | EC57: =DU57*(EC$51)*(T57/365) -> 141.12 | ED57: =DV57*(ED$51)*(U57/365) -> 134.4 | EE57: =DW57*(EE$51)*(V57/365) -> 127.68 | EF57: =DY57*(EF$51)*(W57/365) -> 0 | FM57: 0 | FN57: 0 | FO57: =IF(AA57<1,$K57*$O57,0) -> 0 | FV57: =IF($D57="BESS",IF(Z57<=$S$18,$S$13,$S$21),$N57) -> 7.57 | FW57: =IF($D57="BESS",IF(AA57<=$S$18,$S$13,$S$21),$N57) -> 7.57 | FX57: =IF($D57="BESS",IF(AB57<=$S$18,$S$13,$S$21),$N57) -> 7.57 | FY57: =IF($D57="BESS",IF(AC57<=$S$18,$S$13,$S$21),$N57) -> 7.57 | FZ57: =IF($D57="BESS",IF(AD57<=$S$18,$S$13,$S$21),$N57) -> 7.57 | GA57: =IF($D57="BESS",IF(AE57<=$S$18,$S$13,$S$21),$N57) -> 7.57 | GB57: =IF($D57="BESS",IF(AF57<=$S$18,$S$13,$S$21),$N57) -> 7.57
B58: =Key_New!D8 -> Andhra Pradesh | C58: =Key_New!B8 -> Aarohi Solar Power Pvt Ltd | D58: =Key_New!E8 -> Solar | E58: =Key_New!C8 -> Operational | F58: =Key_New!F8 -> 50 | G58: =IF(NOT(ISNUMBER($H58)),"",IF($H58<=DATE(2026,3,31),$H58,EDATE($H58,-IF($D58="BESS",$S$19,$S$26)))) -> 42460 | H58: =Key_New!O8 -> 42460 | I58: =IF(MONTH(H58)<=3,YEAR(H58),YEAR(H58)+1) -> 2016 | J58: 70 | K58: =J58*F58 -> 3500 | L58: 0.12 | M58: 0.25 | N58: =Key_New!J8 -> 7.35 | O58: =IF(OR(NOT(ISNUMBER($G58)),NOT(ISNUMBER($H58)),$H58<=DATE(2026,3,31)),0,MIN(1,MAX(0,(DATE(2026,3,31)-$G58)/($H58-$G58)))*$S$23) -> 0 | P58: =IF(OR(ISERROR(P$49-$H58),(P$49-$H58)>=365),365,IF((P$49-$H58)<=0,0,P$49-$H58)) -> 365 | Q58: =IF(OR(ISERROR(Q$49-$H58),(Q$49-$H58)>=365),365,IF((Q$49-$H58)<=0,0,Q$49-$H58)) -> 365 | R58: =IF(OR(ISERROR(R$49-$H58),(R$49-$H58)>=365),365,IF((R$49-$H58)<=0,0,R$49-$H58)) -> 365 | S58: =IF(OR(ISERROR(S$49-$H58),(S$49-$H58)>=365),365,IF((S$49-$H58)<=0,0,S$49-$H58)) -> 365 | T58: =IF(OR(ISERROR(T$49-$H58),(T$49-$H58)>=365),365,IF((T$49-$H58)<=0,0,T$49-$H58)) -> 365 | U58: =IF(OR(ISERROR(U$49-$H58),(U$49-$H58)>=365),365,IF((U$49-$H58)<=0,0,U$49-$H58)) -> 365 | V58: =IF(OR(ISERROR(V$49-$H58),(V$49-$H58)>=365),365,IF((V$49-$H58)<=0,0,V$49-$H58)) -> 365 | W58: =IF(OR(ISERROR(W$49-$H58),(W$49-$H58)>=365),365,IF((W$49-$H58)<=0,0,W$49-$H58)) -> 365 | Y58: 8 | Z58: =IF(AND(P58=0,Q58>0),1,IF(Y58=0,0,Y58+1)) -> 9 | AA58: =IF(AND(Q58=0,R58>0),1,IF(Z58=0,0,Z58+1)) -> 10 | AB58: =IF(AND(R58=0,S58>0),1,IF(AA58=0,0,AA58+1)) -> 11 | AC58: =IF(AND(S58=0,T58>0),1,IF(AB58=0,0,AB58+1)) -> 12 | AD58: =IF(AND(T58=0,U58>0),1,IF(AC58=0,0,AC58+1)) -> 13 | AE58: =IF(AND(U58=0,V58>0),1,IF(AD58=0,0,AD58+1)) -> 14 | AF58: =IF(AND(V58=0,W58>0),1,IF(AE58=0,0,AE58+1)) -> 15 | AH58: =IF(AND(P58<=0,Q58>0),$F58,IF(P58>0,$F58,0)) -> 50 | AI58: =IF(AND(Q58<=0,R58>0),$F58,IF(Q58>0,$F58,0)) -> 50 | AJ58: =IF(AND(R58<=0,S58>0),$F58,IF(R58>0,$F58,0)) -> 50 | AK58: =IF(AND(S58<=0,T58>0),$F58,IF(S58>0,$F58,0)) -> 50 | AL58: =IF(AND(T58<=0,U58>0),$F58,IF(T58>0,$F58,0)) -> 50 | AM58: =IF(AND(U58<=0,V58>0),$F58,IF(U58>0,$F58,0)) -> 50 | AN58: =IF(AND(V58<=0,W58>0),$F58,IF(V58>0,$F58,0)) -> 50 | AP58: 0.25 | AQ58: 0.25 | AR58: 0.25 | AS58: 0.25 | AT58: 0.25 | AU58: 0.25 | AV58: 0.25 | AX58: =$F58*8.766*AP58*(Q58/365) -> 109.575 | AY58: =$F58*8.766*AQ58*(R58/365) -> 109.575 | AZ58: =$F58*8.766*AR58*(S58/365) -> 109.575 | BA58: =$F58*8.766*AS58*(T58/365) -> 109.575 | BB58: =$F58*8.766*AT58*(U58/365) -> 109.575 | BC58: =$F58*8.766*AU58*(V58/365) -> 109.575 | BD58: =$F58*8.766*AV58*(W58/365) -> 109.575 | BE58: 0.2 | BF58: =$BE58*$K58*(Q58/365)*($L58/(1-$M58)) -> 112 | BG58: =$BE58*$K58*(R58/365)*($L58/(1-$M58)) -> 112 | BH58: =$BE58*$K58*(S58/365)*($L58/(1-$M58)) -> 112 | BI58: =$BE58*$K58*(T58/365)*($L58/(1-$M58)) -> 112 | BJ58: =$BE58*$K58*(U58/365)*($L58/(1-$M58)) -> 112 | BK58: =$BE58*$K58*(V58/365)*($L58/(1-$M58)) -> 112 | BL58: =$BE58*$K58*(W58/365)*($L58/(1-$M58)) -> 112 | BM58: 0.04 | BN58: =$BM58*$K58*(Q58/365) -> 140 | BO58: =($BM58*$K58*(R58/365)) -> 140 | BP58: =$BM58*$K58*(S58/365) -> 140 | BQ58: =$BM58*$K58*(T58/365) -> 140 | BR58: =$BM58*$K58*(U58/365) -> 140 | BS58: =$BM58*$K58*(V58/365) -> 140 | BT58: =$BM58*$K58*(W58/365) -> 140 | CC58: 0 | CD58: 0 | CE58: =IF(SUM($BX58:$CB58)=0,0,BX58/SUM($BX58:$CB58)*(1-$O58)) -> 0 | CF58: =IF(SUM($BX58:$CB58)=0,0,BY58/SUM($BX58:$CB58)*(1-$O58)) -> 0 | CG58: =IF(SUM($BX58:$CB58)=0,0,BZ58/SUM($BX58:$CB58)*(1-$O58)) -> 0 | CH58: =IF(SUM($BX58:$CB58)=0,0,CA58/SUM($BX58:$CB58)*(1-$O58)) -> 0 | CI58: =IF(SUM($BX58:$CB58)=0,0,CB58/SUM($BX58:$CB58)*(1-$O58)) -> 0 | CJ58: =$O58+SUM(CC58:CI58) -> 0 | CL58: =IF($K58*CC58<=0,,$K58*CC58) -> 0 | CM58: =IF($K58*CD58<=0,,$K58*CD58) -> 0 | CN58: =IF($K58*CE58<=0,,$K58*CE58) -> 0 | CO58: =IF($K58*CF58<=0,,$K58*CF58) -> 0 | CP58: =IF($K58*CG58<=0,,$K58*CG58) -> 0 | CQ58: =IF($K58*CH58<=0,,$K58*CH58) -> 0 | CR58: =IF($K58*CI58<=0,,$K58*CI58) -> 0 | CT58: =$BE58*CL58 -> 0 | CU58: =$BE58*CM58 -> 0 | CV58: =$BE58*CN58 -> 0 | CW58: =$BE58*CO58 -> 0 | CX58: =$BE58*CP58 -> 0 | CY58: =$BE58*CQ58 -> 0 | CZ58: =$BE58*CR58 -> 0 | DB58: =CL58-CT58 -> 0 | DC58: =CM58-CU58 -> 0 | DD58: =CN58-CV58 -> 0 | DE58: =CO58-CW58 -> 0 | DF58: =CP58-CX58 -> 0 | DG58: =CQ58-CY58 -> 0 | DH58: =CR58-CZ58 -> 0 | DJ58: =IF(Z58<=26,IF(AND(P58=0,Q58>0),0,IF(Q58>0,($K58*(1-$BE58))/25,0)),0) -> 112 | DK58: =IF(AA58<=26,IF(AND(Q58=0,R58>0),0,IF(R58>0,($K58*(1-$BE58))/25,0)),0) -> 112 | DL58: =IF(AB58<=26,IF(AND(R58=0,S58>0),0,IF(S58>0,($K58*(1-$BE58))/25,0)),0) -> 112 | DM58: =IF(AC58<=26,IF(AND(S58=0,T58>0),0,IF(T58>0,($K58*(1-$BE58))/25,0)),0) -> 112 | DN58: =IF(AD58<=26,IF(AND(T58=0,U58>0),0,IF(U58>0,($K58*(1-$BE58))/25,0)),0) -> 112 | DO58: =IF(AE58<=26,IF(AND(U58=0,V58>0),0,IF(V58>0,($K58*(1-$BE58))/25,0)),0) -> 112 | DP58: =IF(AF58<=26,IF(AND(V58=0,W58>0),0,IF(W58>0,($K58*(1-$BE58))/25,0)),0) -> 112 | DR58: =+IF(Z58>0,$K58*(1-$BE58)-SUM($DJ58:DJ58),DB58) -> 2688 | DS58: =+IF(AA58>0,$K58*(1-$BE58)-SUM($DJ58:DK58),DC58) -> 2576 | DT58: =+IF(AB58>0,$K58*(1-$BE58)-SUM($DJ58:DL58),DD58) -> 2464 | DU58: =+IF(AC58>0,$K58*(1-$BE58)-SUM($DJ58:DM58),DE58) -> 2352 | DV58: =+IF(AD58>0,$K58*(1-$BE58)-SUM($DJ58:DN58),DF58) -> 2240 | DW58: =+IF(AE58>0,$K58*(1-$BE58)-SUM($DJ58:DO58),DG58) -> 2128 | DX58: =+IF(AF58>0,$K58*(1-$BE58)-SUM($DJ58:DP58),DH58) -> 2016 | DZ58: =DR58*(DZ$51)*(Q58/365) -> 268.8 | EA58: =DS58*(EA$51)*(R58/365) -> 257.6 | EB58: =DT58*(EB$51)*(S58/365) -> 246.4 | EC58: =DU58*(EC$51)*(T58/365) -> 235.2 | ED58: =DV58*(ED$51)*(U58/365) -> 224 | EE58: =DW58*(EE$51)*(V58/365) -> 212.8 | EF58: =DY58*(EF$51)*(W58/365) -> 0 | FM58: 0 | FN58: 0 | FO58: =IF(AA58<1,$K58*$O58,0) -> 0 | FV58: =IF($D58="BESS",IF(Z58<=$S$18,$S$13,$S$21),$N58) -> 7.35 | FW58: =IF($D58="BESS",IF(AA58<=$S$18,$S$13,$S$21),$N58) -> 7.35 | FX58: =IF($D58="BESS",IF(AB58<=$S$18,$S$13,$S$21),$N58) -> 7.35 | FY58: =IF($D58="BESS",IF(AC58<=$S$18,$S$13,$S$21),$N58) -> 7.35 | FZ58: =IF($D58="BESS",IF(AD58<=$S$18,$S$13,$S$21),$N58) -> 7.35 | GA58: =IF($D58="BESS",IF(AE58<=$S$18,$S$13,$S$21),$N58) -> 7.35 | GB58: =IF($D58="BESS",IF(AF58<=$S$18,$S$13,$S$21),$N58) -> 7.35
B59: =Key_New!D9 -> Andhra Pradesh | C59: =Key_New!B9 -> ACME Jaisalmer Solar Power Pvt Ltd | D59: =Key_New!E9 -> Solar | E59: =Key_New!C9 -> Operational | F59: =Key_New!F9 -> 20 | G59: =IF(NOT(ISNUMBER($H59)),"",IF($H59<=DATE(2026,3,31),$H59,EDATE($H59,-IF($D59="BESS",$S$19,$S$26)))) -> 42521 | H59: =Key_New!O9 -> 42521 | I59: =IF(MONTH(H59)<=3,YEAR(H59),YEAR(H59)+1) -> 2017 | J59: 70 | K59: =J59*F59 -> 1400 | L59: 0.12 | M59: 0.25 | N59: =Key_New!J9 -> 7.35 | O59: =IF(OR(NOT(ISNUMBER($G59)),NOT(ISNUMBER($H59)),$H59<=DATE(2026,3,31)),0,MIN(1,MAX(0,(DATE(2026,3,31)-$G59)/($H59-$G59)))*$S$23) -> 0 | P59: =IF(OR(ISERROR(P$49-$H59),(P$49-$H59)>=365),365,IF((P$49-$H59)<=0,0,P$49-$H59)) -> 365 | Q59: =IF(OR(ISERROR(Q$49-$H59),(Q$49-$H59)>=365),365,IF((Q$49-$H59)<=0,0,Q$49-$H59)) -> 365 | R59: =IF(OR(ISERROR(R$49-$H59),(R$49-$H59)>=365),365,IF((R$49-$H59)<=0,0,R$49-$H59)) -> 365 | S59: =IF(OR(ISERROR(S$49-$H59),(S$49-$H59)>=365),365,IF((S$49-$H59)<=0,0,S$49-$H59)) -> 365 | T59: =IF(OR(ISERROR(T$49-$H59),(T$49-$H59)>=365),365,IF((T$49-$H59)<=0,0,T$49-$H59)) -> 365 | U59: =IF(OR(ISERROR(U$49-$H59),(U$49-$H59)>=365),365,IF((U$49-$H59)<=0,0,U$49-$H59)) -> 365 | V59: =IF(OR(ISERROR(V$49-$H59),(V$49-$H59)>=365),365,IF((V$49-$H59)<=0,0,V$49-$H59)) -> 365 | W59: =IF(OR(ISERROR(W$49-$H59),(W$49-$H59)>=365),365,IF((W$49-$H59)<=0,0,W$49-$H59)) -> 365 | Y59: 7 | Z59: =IF(AND(P59=0,Q59>0),1,IF(Y59=0,0,Y59+1)) -> 8 | AA59: =IF(AND(Q59=0,R59>0),1,IF(Z59=0,0,Z59+1)) -> 9 | AB59: =IF(AND(R59=0,S59>0),1,IF(AA59=0,0,AA59+1)) -> 10 | AC59: =IF(AND(S59=0,T59>0),1,IF(AB59=0,0,AB59+1)) -> 11 | AD59: =IF(AND(T59=0,U59>0),1,IF(AC59=0,0,AC59+1)) -> 12 | AE59: =IF(AND(U59=0,V59>0),1,IF(AD59=0,0,AD59+1)) -> 13 | AF59: =IF(AND(V59=0,W59>0),1,IF(AE59=0,0,AE59+1)) -> 14 | AH59: =IF(AND(P59<=0,Q59>0),$F59,IF(P59>0,$F59,0)) -> 20 | AI59: =IF(AND(Q59<=0,R59>0),$F59,IF(Q59>0,$F59,0)) -> 20 | AJ59: =IF(AND(R59<=0,S59>0),$F59,IF(R59>0,$F59,0)) -> 20 | AK59: =IF(AND(S59<=0,T59>0),$F59,IF(S59>0,$F59,0)) -> 20 | AL59: =IF(AND(T59<=0,U59>0),$F59,IF(T59>0,$F59,0)) -> 20 | AM59: =IF(AND(U59<=0,V59>0),$F59,IF(U59>0,$F59,0)) -> 20 | AN59: =IF(AND(V59<=0,W59>0),$F59,IF(V59>0,$F59,0)) -> 20 | AP59: 0.25 | AQ59: 0.25 | AR59: 0.25 | AS59: 0.25 | AT59: 0.25 | AU59: 0.25 | AV59: 0.25 | AX59: =$F59*8.766*AP59*(Q59/365) -> 43.83 | AY59: =$F59*8.766*AQ59*(R59/365) -> 43.83 | AZ59: =$F59*8.766*AR59*(S59/365) -> 43.83 | BA59: =$F59*8.766*AS59*(T59/365) -> 43.83 | BB59: =$F59*8.766*AT59*(U59/365) -> 43.83 | BC59: =$F59*8.766*AU59*(V59/365) -> 43.83 | BD59: =$F59*8.766*AV59*(W59/365) -> 43.83 | BE59: 0.2 | BF59: =$BE59*$K59*(Q59/365)*($L59/(1-$M59)) -> 44.8 | BG59: =$BE59*$K59*(R59/365)*($L59/(1-$M59)) -> 44.8 | BH59: =$BE59*$K59*(S59/365)*($L59/(1-$M59)) -> 44.8 | BI59: =$BE59*$K59*(T59/365)*($L59/(1-$M59)) -> 44.8 | BJ59: =$BE59*$K59*(U59/365)*($L59/(1-$M59)) -> 44.8 | BK59: =$BE59*$K59*(V59/365)*($L59/(1-$M59)) -> 44.8 | BL59: =$BE59*$K59*(W59/365)*($L59/(1-$M59)) -> 44.8 | BM59: 0.04 | BN59: =$BM59*$K59*(Q59/365) -> 56 | BO59: =($BM59*$K59*(R59/365)) -> 56 | BP59: =$BM59*$K59*(S59/365) -> 56 | BQ59: =$BM59*$K59*(T59/365) -> 56 | BR59: =$BM59*$K59*(U59/365) -> 56 | BS59: =$BM59*$K59*(V59/365) -> 56 | BT59: =$BM59*$K59*(W59/365) -> 56 | CC59: 0 | CD59: 0 | CE59: =IF(SUM($BX59:$CB59)=0,0,BX59/SUM($BX59:$CB59)*(1-$O59)) -> 0 | CF59: =IF(SUM($BX59:$CB59)=0,0,BY59/SUM($BX59:$CB59)*(1-$O59)) -> 0 | CG59: =IF(SUM($BX59:$CB59)=0,0,BZ59/SUM($BX59:$CB59)*(1-$O59)) -> 0 | CH59: =IF(SUM($BX59:$CB59)=0,0,CA59/SUM($BX59:$CB59)*(1-$O59)) -> 0 | CI59: =IF(SUM($BX59:$CB59)=0,0,CB59/SUM($BX59:$CB59)*(1-$O59)) -> 0 | CJ59: =$O59+SUM(CC59:CI59) -> 0 | CL59: =IF($K59*CC59<=0,,$K59*CC59) -> 0 | CM59: =IF($K59*CD59<=0,,$K59*CD59) -> 0 | CN59: =IF($K59*CE59<=0,,$K59*CE59) -> 0 | CO59: =IF($K59*CF59<=0,,$K59*CF59) -> 0 | CP59: =IF($K59*CG59<=0,,$K59*CG59) -> 0 | CQ59: =IF($K59*CH59<=0,,$K59*CH59) -> 0 | CR59: =IF($K59*CI59<=0,,$K59*CI59) -> 0 | CT59: =$BE59*CL59 -> 0 | CU59: =$BE59*CM59 -> 0 | CV59: =$BE59*CN59 -> 0 | CW59: =$BE59*CO59 -> 0 | CX59: =$BE59*CP59 -> 0 | CY59: =$BE59*CQ59 -> 0 | CZ59: =$BE59*CR59 -> 0 | DB59: =CL59-CT59 -> 0 | DC59: =CM59-CU59 -> 0 | DD59: =CN59-CV59 -> 0 | DE59: =CO59-CW59 -> 0 | DF59: =CP59-CX59 -> 0 | DG59: =CQ59-CY59 -> 0 | DH59: =CR59-CZ59 -> 0 | DJ59: =IF(Z59<=26,IF(AND(P59=0,Q59>0),0,IF(Q59>0,($K59*(1-$BE59))/25,0)),0) -> 44.8 | DK59: =IF(AA59<=26,IF(AND(Q59=0,R59>0),0,IF(R59>0,($K59*(1-$BE59))/25,0)),0) -> 44.8 | DL59: =IF(AB59<=26,IF(AND(R59=0,S59>0),0,IF(S59>0,($K59*(1-$BE59))/25,0)),0) -> 44.8 | DM59: =IF(AC59<=26,IF(AND(S59=0,T59>0),0,IF(T59>0,($K59*(1-$BE59))/25,0)),0) -> 44.8 | DN59: =IF(AD59<=26,IF(AND(T59=0,U59>0),0,IF(U59>0,($K59*(1-$BE59))/25,0)),0) -> 44.8 | DO59: =IF(AE59<=26,IF(AND(U59=0,V59>0),0,IF(V59>0,($K59*(1-$BE59))/25,0)),0) -> 44.8 | DP59: =IF(AF59<=26,IF(AND(V59=0,W59>0),0,IF(W59>0,($K59*(1-$BE59))/25,0)),0) -> 44.8 | DR59: =+IF(Z59>0,$K59*(1-$BE59)-SUM($DJ59:DJ59),DB59) -> 1075.2 | DS59: =+IF(AA59>0,$K59*(1-$BE59)-SUM($DJ59:DK59),DC59) -> 1030.4 | DT59: =+IF(AB59>0,$K59*(1-$BE59)-SUM($DJ59:DL59),DD59) -> 985.6 | DU59: =+IF(AC59>0,$K59*(1-$BE59)-SUM($DJ59:DM59),DE59) -> 940.8 | DV59: =+IF(AD59>0,$K59*(1-$BE59)-SUM($DJ59:DN59),DF59) -> 896 | DW59: =+IF(AE59>0,$K59*(1-$BE59)-SUM($DJ59:DO59),DG59) -> 851.2 | DX59: =+IF(AF59>0,$K59*(1-$BE59)-SUM($DJ59:DP59),DH59) -> 806.4 | DZ59: =DR59*(DZ$51)*(Q59/365) -> 107.52 | EA59: =DS59*(EA$51)*(R59/365) -> 103.04 | EB59: =DT59*(EB$51)*(S59/365) -> 98.56 | EC59: =DU59*(EC$51)*(T59/365) -> 94.08 | ED59: =DV59*(ED$51)*(U59/365) -> 89.6 | EE59: =DW59*(EE$51)*(V59/365) -> 85.12 | EF59: =DY59*(EF$51)*(W59/365) -> 0 | FM59: 0 | FN59: 0 | FO59: =IF(AA59<1,$K59*$O59,0) -> 0 | FV59: =IF($D59="BESS",IF(Z59<=$S$18,$S$13,$S$21),$N59) -> 7.35 | FW59: =IF($D59="BESS",IF(AA59<=$S$18,$S$13,$S$21),$N59) -> 7.35 | FX59: =IF($D59="BESS",IF(AB59<=$S$18,$S$13,$S$21),$N59) -> 7.35 | FY59: =IF($D59="BESS",IF(AC59<=$S$18,$S$13,$S$21),$N59) -> 7.35 | FZ59: =IF($D59="BESS",IF(AD59<=$S$18,$S$13,$S$21),$N59) -> 7.35 | GA59: =IF($D59="BESS",IF(AE59<=$S$18,$S$13,$S$21),$N59) -> 7.35 | GB59: =IF($D59="BESS",IF(AF59<=$S$18,$S$13,$S$21),$N59) -> 7.35
B60: =Key_New!D10 -> Andhra Pradesh | C60: =Key_New!B10 -> Dayanidhi Solar Power Pvt Ltd | D60: =Key_New!E10 -> Solar | E60: =Key_New!C10 -> Operational | F60: =Key_New!F10 -> 40 | G60: =IF(NOT(ISNUMBER($H60)),"",IF($H60<=DATE(2026,3,31),$H60,EDATE($H60,-IF($D60="BESS",$S$19,$S$26)))) -> 42490 | H60: =Key_New!O10 -> 42490 | I60: =IF(MONTH(H60)<=3,YEAR(H60),YEAR(H60)+1) -> 2017 | J60: 70 | K60: =J60*F60 -> 2800 | L60: 0.12 | M60: 0.25 | N60: =Key_New!J10 -> 7.79 | O60: =IF(OR(NOT(ISNUMBER($G60)),NOT(ISNUMBER($H60)),$H60<=DATE(2026,3,31)),0,MIN(1,MAX(0,(DATE(2026,3,31)-$G60)/($H60-$G60)))*$S$23) -> 0 | P60: =IF(OR(ISERROR(P$49-$H60),(P$49-$H60)>=365),365,IF((P$49-$H60)<=0,0,P$49-$H60)) -> 365 | Q60: =IF(OR(ISERROR(Q$49-$H60),(Q$49-$H60)>=365),365,IF((Q$49-$H60)<=0,0,Q$49-$H60)) -> 365 | R60: =IF(OR(ISERROR(R$49-$H60),(R$49-$H60)>=365),365,IF((R$49-$H60)<=0,0,R$49-$H60)) -> 365 | S60: =IF(OR(ISERROR(S$49-$H60),(S$49-$H60)>=365),365,IF((S$49-$H60)<=0,0,S$49-$H60)) -> 365 | T60: =IF(OR(ISERROR(T$49-$H60),(T$49-$H60)>=365),365,IF((T$49-$H60)<=0,0,T$49-$H60)) -> 365 | U60: =IF(OR(ISERROR(U$49-$H60),(U$49-$H60)>=365),365,IF((U$49-$H60)<=0,0,U$49-$H60)) -> 365 | V60: =IF(OR(ISERROR(V$49-$H60),(V$49-$H60)>=365),365,IF((V$49-$H60)<=0,0,V$49-$H60)) -> 365 | W60: =IF(OR(ISERROR(W$49-$H60),(W$49-$H60)>=365),365,IF((W$49-$H60)<=0,0,W$49-$H60)) -> 365 | Y60: 7 | Z60: =IF(AND(P60=0,Q60>0),1,IF(Y60=0,0,Y60+1)) -> 8 | AA60: =IF(AND(Q60=0,R60>0),1,IF(Z60=0,0,Z60+1)) -> 9 | AB60: =IF(AND(R60=0,S60>0),1,IF(AA60=0,0,AA60+1)) -> 10 | AC60: =IF(AND(S60=0,T60>0),1,IF(AB60=0,0,AB60+1)) -> 11 | AD60: =IF(AND(T60=0,U60>0),1,IF(AC60=0,0,AC60+1)) -> 12 | AE60: =IF(AND(U60=0,V60>0),1,IF(AD60=0,0,AD60+1)) -> 13 | AF60: =IF(AND(V60=0,W60>0),1,IF(AE60=0,0,AE60+1)) -> 14 | AH60: =IF(AND(P60<=0,Q60>0),$F60,IF(P60>0,$F60,0)) -> 40 | AI60: =IF(AND(Q60<=0,R60>0),$F60,IF(Q60>0,$F60,0)) -> 40 | AJ60: =IF(AND(R60<=0,S60>0),$F60,IF(R60>0,$F60,0)) -> 40 | AK60: =IF(AND(S60<=0,T60>0),$F60,IF(S60>0,$F60,0)) -> 40 | AL60: =IF(AND(T60<=0,U60>0),$F60,IF(T60>0,$F60,0)) -> 40 | AM60: =IF(AND(U60<=0,V60>0),$F60,IF(U60>0,$F60,0)) -> 40 | AN60: =IF(AND(V60<=0,W60>0),$F60,IF(V60>0,$F60,0)) -> 40 | AP60: 0.25 | AQ60: 0.25 | AR60: 0.25 | AS60: 0.25 | AT60: 0.25 | AU60: 0.25 | AV60: 0.25 | AX60: =$F60*8.766*AP60*(Q60/365) -> 87.66 | AY60: =$F60*8.766*AQ60*(R60/365) -> 87.66 | AZ60: =$F60*8.766*AR60*(S60/365) -> 87.66 | BA60: =$F60*8.766*AS60*(T60/365) -> 87.66 | BB60: =$F60*8.766*AT60*(U60/365) -> 87.66 | BC60: =$F60*8.766*AU60*(V60/365) -> 87.66 | BD60: =$F60*8.766*AV60*(W60/365) -> 87.66 | BE60: 0.2 | BF60: =$BE60*$K60*(Q60/365)*($L60/(1-$M60)) -> 89.6 | BG60: =$BE60*$K60*(R60/365)*($L60/(1-$M60)) -> 89.6 | BH60: =$BE60*$K60*(S60/365)*($L60/(1-$M60)) -> 89.6 | BI60: =$BE60*$K60*(T60/365)*($L60/(1-$M60)) -> 89.6 | BJ60: =$BE60*$K60*(U60/365)*($L60/(1-$M60)) -> 89.6 | BK60: =$BE60*$K60*(V60/365)*($L60/(1-$M60)) -> 89.6 | BL60: =$BE60*$K60*(W60/365)*($L60/(1-$M60)) -> 89.6 | BM60: 0.04 | BN60: =$BM60*$K60*(Q60/365) -> 112 | BO60: =($BM60*$K60*(R60/365)) -> 112 | BP60: =$BM60*$K60*(S60/365) -> 112 | BQ60: =$BM60*$K60*(T60/365) -> 112 | BR60: =$BM60*$K60*(U60/365) -> 112 | BS60: =$BM60*$K60*(V60/365) -> 112 | BT60: =$BM60*$K60*(W60/365) -> 112 | CC60: 0 | CD60: 0 | CE60: =IF(SUM($BX60:$CB60)=0,0,BX60/SUM($BX60:$CB60)*(1-$O60)) -> 0 | CF60: =IF(SUM($BX60:$CB60)=0,0,BY60/SUM($BX60:$CB60)*(1-$O60)) -> 0 | CG60: =IF(SUM($BX60:$CB60)=0,0,BZ60/SUM($BX60:$CB60)*(1-$O60)) -> 0 | CH60: =IF(SUM($BX60:$CB60)=0,0,CA60/SUM($BX60:$CB60)*(1-$O60)) -> 0 | CI60: =IF(SUM($BX60:$CB60)=0,0,CB60/SUM($BX60:$CB60)*(1-$O60)) -> 0 | CJ60: =$O60+SUM(CC60:CI60) -> 0 | CL60: =IF($K60*CC60<=0,,$K60*CC60) -> 0 | CM60: =IF($K60*CD60<=0,,$K60*CD60) -> 0 | CN60: =IF($K60*CE60<=0,,$K60*CE60) -> 0 | CO60: =IF($K60*CF60<=0,,$K60*CF60) -> 0 | CP60: =IF($K60*CG60<=0,,$K60*CG60) -> 0 | CQ60: =IF($K60*CH60<=0,,$K60*CH60) -> 0 | CR60: =IF($K60*CI60<=0,,$K60*CI60) -> 0 | CT60: =$BE60*CL60 -> 0 | CU60: =$BE60*CM60 -> 0 | CV60: =$BE60*CN60 -> 0 | CW60: =$BE60*CO60 -> 0 | CX60: =$BE60*CP60 -> 0 | CY60: =$BE60*CQ60 -> 0 | CZ60: =$BE60*CR60 -> 0 | DB60: =CL60-CT60 -> 0 | DC60: =CM60-CU60 -> 0 | DD60: =CN60-CV60 -> 0 | DE60: =CO60-CW60 -> 0 | DF60: =CP60-CX60 -> 0 | DG60: =CQ60-CY60 -> 0 | DH60: =CR60-CZ60 -> 0 | DJ60: =IF(Z60<=26,IF(AND(P60=0,Q60>0),0,IF(Q60>0,($K60*(1-$BE60))/25,0)),0) -> 89.6 | DK60: =IF(AA60<=26,IF(AND(Q60=0,R60>0),0,IF(R60>0,($K60*(1-$BE60))/25,0)),0) -> 89.6 | DL60: =IF(AB60<=26,IF(AND(R60=0,S60>0),0,IF(S60>0,($K60*(1-$BE60))/25,0)),0) -> 89.6 | DM60: =IF(AC60<=26,IF(AND(S60=0,T60>0),0,IF(T60>0,($K60*(1-$BE60))/25,0)),0) -> 89.6 | DN60: =IF(AD60<=26,IF(AND(T60=0,U60>0),0,IF(U60>0,($K60*(1-$BE60))/25,0)),0) -> 89.6 | DO60: =IF(AE60<=26,IF(AND(U60=0,V60>0),0,IF(V60>0,($K60*(1-$BE60))/25,0)),0) -> 89.6 | DP60: =IF(AF60<=26,IF(AND(V60=0,W60>0),0,IF(W60>0,($K60*(1-$BE60))/25,0)),0) -> 89.6 | DR60: =+IF(Z60>0,$K60*(1-$BE60)-SUM($DJ60:DJ60),DB60) -> 2150.4 | DS60: =+IF(AA60>0,$K60*(1-$BE60)-SUM($DJ60:DK60),DC60) -> 2060.8 | DT60: =+IF(AB60>0,$K60*(1-$BE60)-SUM($DJ60:DL60),DD60) -> 1971.2 | DU60: =+IF(AC60>0,$K60*(1-$BE60)-SUM($DJ60:DM60),DE60) -> 1881.6 | DV60: =+IF(AD60>0,$K60*(1-$BE60)-SUM($DJ60:DN60),DF60) -> 1792 | DW60: =+IF(AE60>0,$K60*(1-$BE60)-SUM($DJ60:DO60),DG60) -> 1702.4 | DX60: =+IF(AF60>0,$K60*(1-$BE60)-SUM($DJ60:DP60),DH60) -> 1612.8 | DZ60: =DR60*(DZ$51)*(Q60/365) -> 215.04 | EA60: =DS60*(EA$51)*(R60/365) -> 206.08 | EB60: =DT60*(EB$51)*(S60/365) -> 197.12 | EC60: =DU60*(EC$51)*(T60/365) -> 188.16 | ED60: =DV60*(ED$51)*(U60/365) -> 179.2 | EE60: =DW60*(EE$51)*(V60/365) -> 170.24 | EF60: =DY60*(EF$51)*(W60/365) -> 0 | FM60: 0 | FN60: 0 | FO60: =IF(AA60<1,$K60*$O60,0) -> 0 | FV60: =IF($D60="BESS",IF(Z60<=$S$18,$S$13,$S$21),$N60) -> 7.79 | FW60: =IF($D60="BESS",IF(AA60<=$S$18,$S$13,$S$21),$N60) -> 7.79 | FX60: =IF($D60="BESS",IF(AB60<=$S$18,$S$13,$S$21),$N60) -> 7.79 | FY60: =IF($D60="BESS",IF(AC60<=$S$18,$S$13,$S$21),$N60) -> 7.79 | FZ60: =IF($D60="BESS",IF(AD60<=$S$18,$S$13,$S$21),$N60) -> 7.79 | GA60: =IF($D60="BESS",IF(AE60<=$S$18,$S$13,$S$21),$N60) -> 7.79 | GB60: =IF($D60="BESS",IF(AF60<=$S$18,$S$13,$S$21),$N60) -> 7.79
B61: =Key_New!D11 -> Andhra Pradesh | C61: =Key_New!B11 -> Niranjana Solar Power Pvt Ltd | D61: =Key_New!E11 -> Solar | E61: =Key_New!C11 -> Operational | F61: =Key_New!F11 -> 20 | G61: =IF(NOT(ISNUMBER($H61)),"",IF($H61<=DATE(2026,3,31),$H61,EDATE($H61,-IF($D61="BESS",$S$19,$S$26)))) -> 42460 | H61: =Key_New!O11 -> 42460 | I61: =IF(MONTH(H61)<=3,YEAR(H61),YEAR(H61)+1) -> 2016 | J61: 70 | K61: =J61*F61 -> 1400 | L61: 0.12 | M61: 0.25 | N61: =Key_New!J11 -> 7.45 | O61: =IF(OR(NOT(ISNUMBER($G61)),NOT(ISNUMBER($H61)),$H61<=DATE(2026,3,31)),0,MIN(1,MAX(0,(DATE(2026,3,31)-$G61)/($H61-$G61)))*$S$23) -> 0 | P61: =IF(OR(ISERROR(P$49-$H61),(P$49-$H61)>=365),365,IF((P$49-$H61)<=0,0,P$49-$H61)) -> 365 | Q61: =IF(OR(ISERROR(Q$49-$H61),(Q$49-$H61)>=365),365,IF((Q$49-$H61)<=0,0,Q$49-$H61)) -> 365 | R61: =IF(OR(ISERROR(R$49-$H61),(R$49-$H61)>=365),365,IF((R$49-$H61)<=0,0,R$49-$H61)) -> 365 | S61: =IF(OR(ISERROR(S$49-$H61),(S$49-$H61)>=365),365,IF((S$49-$H61)<=0,0,S$49-$H61)) -> 365 | T61: =IF(OR(ISERROR(T$49-$H61),(T$49-$H61)>=365),365,IF((T$49-$H61)<=0,0,T$49-$H61)) -> 365 | U61: =IF(OR(ISERROR(U$49-$H61),(U$49-$H61)>=365),365,IF((U$49-$H61)<=0,0,U$49-$H61)) -> 365 | V61: =IF(OR(ISERROR(V$49-$H61),(V$49-$H61)>=365),365,IF((V$49-$H61)<=0,0,V$49-$H61)) -> 365 | W61: =IF(OR(ISERROR(W$49-$H61),(W$49-$H61)>=365),365,IF((W$49-$H61)<=0,0,W$49-$H61)) -> 365 | Y61: 8 | Z61: =IF(AND(P61=0,Q61>0),1,IF(Y61=0,0,Y61+1)) -> 9 | AA61: =IF(AND(Q61=0,R61>0),1,IF(Z61=0,0,Z61+1)) -> 10 | AB61: =IF(AND(R61=0,S61>0),1,IF(AA61=0,0,AA61+1)) -> 11 | AC61: =IF(AND(S61=0,T61>0),1,IF(AB61=0,0,AB61+1)) -> 12 | AD61: =IF(AND(T61=0,U61>0),1,IF(AC61=0,0,AC61+1)) -> 13 | AE61: =IF(AND(U61=0,V61>0),1,IF(AD61=0,0,AD61+1)) -> 14 | AF61: =IF(AND(V61=0,W61>0),1,IF(AE61=0,0,AE61+1)) -> 15 | AH61: =IF(AND(P61<=0,Q61>0),$F61,IF(P61>0,$F61,0)) -> 20 | AI61: =IF(AND(Q61<=0,R61>0),$F61,IF(Q61>0,$F61,0)) -> 20 | AJ61: =IF(AND(R61<=0,S61>0),$F61,IF(R61>0,$F61,0)) -> 20 | AK61: =IF(AND(S61<=0,T61>0),$F61,IF(S61>0,$F61,0)) -> 20 | AL61: =IF(AND(T61<=0,U61>0),$F61,IF(T61>0,$F61,0)) -> 20 | AM61: =IF(AND(U61<=0,V61>0),$F61,IF(U61>0,$F61,0)) -> 20 | AN61: =IF(AND(V61<=0,W61>0),$F61,IF(V61>0,$F61,0)) -> 20 | AP61: 0.25 | AQ61: 0.25 | AR61: 0.25 | AS61: 0.25 | AT61: 0.25 | AU61: 0.25 | AV61: 0.25 | AX61: =$F61*8.766*AP61*(Q61/365) -> 43.83 | AY61: =$F61*8.766*AQ61*(R61/365) -> 43.83 | AZ61: =$F61*8.766*AR61*(S61/365) -> 43.83 | BA61: =$F61*8.766*AS61*(T61/365) -> 43.83 | BB61: =$F61*8.766*AT61*(U61/365) -> 43.83 | BC61: =$F61*8.766*AU61*(V61/365) -> 43.83 | BD61: =$F61*8.766*AV61*(W61/365) -> 43.83 | BE61: 0.2 | BF61: =$BE61*$K61*(Q61/365)*($L61/(1-$M61)) -> 44.8 | BG61: =$BE61*$K61*(R61/365)*($L61/(1-$M61)) -> 44.8 | BH61: =$BE61*$K61*(S61/365)*($L61/(1-$M61)) -> 44.8 | BI61: =$BE61*$K61*(T61/365)*($L61/(1-$M61)) -> 44.8 | BJ61: =$BE61*$K61*(U61/365)*($L61/(1-$M61)) -> 44.8 | BK61: =$BE61*$K61*(V61/365)*($L61/(1-$M61)) -> 44.8 | BL61: =$BE61*$K61*(W61/365)*($L61/(1-$M61)) -> 44.8 | BM61: 0.04 | BN61: =$BM61*$K61*(Q61/365) -> 56 | BO61: =($BM61*$K61*(R61/365)) -> 56 | BP61: =$BM61*$K61*(S61/365) -> 56 | BQ61: =$BM61*$K61*(T61/365) -> 56 | BR61: =$BM61*$K61*(U61/365) -> 56 | BS61: =$BM61*$K61*(V61/365) -> 56 | BT61: =$BM61*$K61*(W61/365) -> 56 | CC61: 0 | CD61: 0 | CE61: =IF(SUM($BX61:$CB61)=0,0,BX61/SUM($BX61:$CB61)*(1-$O61)) -> 0 | CF61: =IF(SUM($BX61:$CB61)=0,0,BY61/SUM($BX61:$CB61)*(1-$O61)) -> 0 | CG61: =IF(SUM($BX61:$CB61)=0,0,BZ61/SUM($BX61:$CB61)*(1-$O61)) -> 0 | CH61: =IF(SUM($BX61:$CB61)=0,0,CA61/SUM($BX61:$CB61)*(1-$O61)) -> 0 | CI61: =IF(SUM($BX61:$CB61)=0,0,CB61/SUM($BX61:$CB61)*(1-$O61)) -> 0 | CJ61: =$O61+SUM(CC61:CI61) -> 0 | CL61: =IF($K61*CC61<=0,,$K61*CC61) -> 0 | CM61: =IF($K61*CD61<=0,,$K61*CD61) -> 0 | CN61: =IF($K61*CE61<=0,,$K61*CE61) -> 0 | CO61: =IF($K61*CF61<=0,,$K61*CF61) -> 0 | CP61: =IF($K61*CG61<=0,,$K61*CG61) -> 0 | CQ61: =IF($K61*CH61<=0,,$K61*CH61) -> 0 | CR61: =IF($K61*CI61<=0,,$K61*CI61) -> 0 | CT61: =$BE61*CL61 -> 0 | CU61: =$BE61*CM61 -> 0 | CV61: =$BE61*CN61 -> 0 | CW61: =$BE61*CO61 -> 0 | CX61: =$BE61*CP61 -> 0 | CY61: =$BE61*CQ61 -> 0 | CZ61: =$BE61*CR61 -> 0 | DB61: =CL61-CT61 -> 0 | DC61: =CM61-CU61 -> 0 | DD61: =CN61-CV61 -> 0 | DE61: =CO61-CW61 -> 0 | DF61: =CP61-CX61 -> 0 | DG61: =CQ61-CY61 -> 0 | DH61: =CR61-CZ61 -> 0 | DJ61: =IF(Z61<=26,IF(AND(P61=0,Q61>0),0,IF(Q61>0,($K61*(1-$BE61))/25,0)),0) -> 44.8 | DK61: =IF(AA61<=26,IF(AND(Q61=0,R61>0),0,IF(R61>0,($K61*(1-$BE61))/25,0)),0) -> 44.8 | DL61: =IF(AB61<=26,IF(AND(R61=0,S61>0),0,IF(S61>0,($K61*(1-$BE61))/25,0)),0) -> 44.8 | DM61: =IF(AC61<=26,IF(AND(S61=0,T61>0),0,IF(T61>0,($K61*(1-$BE61))/25,0)),0) -> 44.8 | DN61: =IF(AD61<=26,IF(AND(T61=0,U61>0),0,IF(U61>0,($K61*(1-$BE61))/25,0)),0) -> 44.8 | DO61: =IF(AE61<=26,IF(AND(U61=0,V61>0),0,IF(V61>0,($K61*(1-$BE61))/25,0)),0) -> 44.8 | DP61: =IF(AF61<=26,IF(AND(V61=0,W61>0),0,IF(W61>0,($K61*(1-$BE61))/25,0)),0) -> 44.8 | DR61: =+IF(Z61>0,$K61*(1-$BE61)-SUM($DJ61:DJ61),DB61) -> 1075.2 | DS61: =+IF(AA61>0,$K61*(1-$BE61)-SUM($DJ61:DK61),DC61) -> 1030.4 | DT61: =+IF(AB61>0,$K61*(1-$BE61)-SUM($DJ61:DL61),DD61) -> 985.6 | DU61: =+IF(AC61>0,$K61*(1-$BE61)-SUM($DJ61:DM61),DE61) -> 940.8 | DV61: =+IF(AD61>0,$K61*(1-$BE61)-SUM($DJ61:DN61),DF61) -> 896 | DW61: =+IF(AE61>0,$K61*(1-$BE61)-SUM($DJ61:DO61),DG61) -> 851.2 | DX61: =+IF(AF61>0,$K61*(1-$BE61)-SUM($DJ61:DP61),DH61) -> 806.4 | DZ61: =DR61*(DZ$51)*(Q61/365) -> 107.52 | EA61: =DS61*(EA$51)*(R61/365) -> 103.04 | EB61: =DT61*(EB$51)*(S61/365) -> 98.56 | EC61: =DU61*(EC$51)*(T61/365) -> 94.08 | ED61: =DV61*(ED$51)*(U61/365) -> 89.6 | EE61: =DW61*(EE$51)*(V61/365) -> 85.12 | EF61: =DY61*(EF$51)*(W61/365) -> 0 | FM61: 0 | FN61: 0 | FO61: =IF(AA61<1,$K61*$O61,0) -> 0 | FV61: =IF($D61="BESS",IF(Z61<=$S$18,$S$13,$S$21),$N61) -> 7.45 | FW61: =IF($D61="BESS",IF(AA61<=$S$18,$S$13,$S$21),$N61) -> 7.45 | FX61: =IF($D61="BESS",IF(AB61<=$S$18,$S$13,$S$21),$N61) -> 7.45 | FY61: =IF($D61="BESS",IF(AC61<=$S$18,$S$13,$S$21),$N61) -> 7.45 | FZ61: =IF($D61="BESS",IF(AD61<=$S$18,$S$13,$S$21),$N61) -> 7.45 | GA61: =IF($D61="BESS",IF(AE61<=$S$18,$S$13,$S$21),$N61) -> 7.45 | GB61: =IF($D61="BESS",IF(AF61<=$S$18,$S$13,$S$21),$N61) -> 7.45
B62: =Key_New!D12 -> Andhra Pradesh | C62: =Key_New!B12 -> Viswatma Solar Energy Pvt Ltd | D62: =Key_New!E12 -> Solar | E62: =Key_New!C12 -> Operational | F62: =Key_New!F12 -> 30 | G62: =IF(NOT(ISNUMBER($H62)),"",IF($H62<=DATE(2026,3,31),$H62,EDATE($H62,-IF($D62="BESS",$S$19,$S$26)))) -> 42490 | H62: =Key_New!O12 -> 42490 | I62: =IF(MONTH(H62)<=3,YEAR(H62),YEAR(H62)+1) -> 2017 | J62: 70 | K62: =J62*F62 -> 2100 | L62: 0.12 | M62: 0.25 | N62: =Key_New!J12 -> 7.45 | O62: =IF(OR(NOT(ISNUMBER($G62)),NOT(ISNUMBER($H62)),$H62<=DATE(2026,3,31)),0,MIN(1,MAX(0,(DATE(2026,3,31)-$G62)/($H62-$G62)))*$S$23) -> 0 | P62: =IF(OR(ISERROR(P$49-$H62),(P$49-$H62)>=365),365,IF((P$49-$H62)<=0,0,P$49-$H62)) -> 365 | Q62: =IF(OR(ISERROR(Q$49-$H62),(Q$49-$H62)>=365),365,IF((Q$49-$H62)<=0,0,Q$49-$H62)) -> 365 | R62: =IF(OR(ISERROR(R$49-$H62),(R$49-$H62)>=365),365,IF((R$49-$H62)<=0,0,R$49-$H62)) -> 365 | S62: =IF(OR(ISERROR(S$49-$H62),(S$49-$H62)>=365),365,IF((S$49-$H62)<=0,0,S$49-$H62)) -> 365 | T62: =IF(OR(ISERROR(T$49-$H62),(T$49-$H62)>=365),365,IF((T$49-$H62)<=0,0,T$49-$H62)) -> 365 | U62: =IF(OR(ISERROR(U$49-$H62),(U$49-$H62)>=365),365,IF((U$49-$H62)<=0,0,U$49-$H62)) -> 365 | V62: =IF(OR(ISERROR(V$49-$H62),(V$49-$H62)>=365),365,IF((V$49-$H62)<=0,0,V$49-$H62)) -> 365 | W62: =IF(OR(ISERROR(W$49-$H62),(W$49-$H62)>=365),365,IF((W$49-$H62)<=0,0,W$49-$H62)) -> 365 | Y62: 7 | Z62: =IF(AND(P62=0,Q62>0),1,IF(Y62=0,0,Y62+1)) -> 8 | AA62: =IF(AND(Q62=0,R62>0),1,IF(Z62=0,0,Z62+1)) -> 9 | AB62: =IF(AND(R62=0,S62>0),1,IF(AA62=0,0,AA62+1)) -> 10 | AC62: =IF(AND(S62=0,T62>0),1,IF(AB62=0,0,AB62+1)) -> 11 | AD62: =IF(AND(T62=0,U62>0),1,IF(AC62=0,0,AC62+1)) -> 12 | AE62: =IF(AND(U62=0,V62>0),1,IF(AD62=0,0,AD62+1)) -> 13 | AF62: =IF(AND(V62=0,W62>0),1,IF(AE62=0,0,AE62+1)) -> 14 | AH62: =IF(AND(P62<=0,Q62>0),$F62,IF(P62>0,$F62,0)) -> 30 | AI62: =IF(AND(Q62<=0,R62>0),$F62,IF(Q62>0,$F62,0)) -> 30 | AJ62: =IF(AND(R62<=0,S62>0),$F62,IF(R62>0,$F62,0)) -> 30 | AK62: =IF(AND(S62<=0,T62>0),$F62,IF(S62>0,$F62,0)) -> 30 | AL62: =IF(AND(T62<=0,U62>0),$F62,IF(T62>0,$F62,0)) -> 30 | AM62: =IF(AND(U62<=0,V62>0),$F62,IF(U62>0,$F62,0)) -> 30 | AN62: =IF(AND(V62<=0,W62>0),$F62,IF(V62>0,$F62,0)) -> 30 | AP62: 0.25 | AQ62: 0.25 | AR62: 0.25 | AS62: 0.25 | AT62: 0.25 | AU62: 0.25 | AV62: 0.25 | AX62: =$F62*8.766*AP62*(Q62/365) -> 65.745 | AY62: =$F62*8.766*AQ62*(R62/365) -> 65.745 | AZ62: =$F62*8.766*AR62*(S62/365) -> 65.745 | BA62: =$F62*8.766*AS62*(T62/365) -> 65.745 | BB62: =$F62*8.766*AT62*(U62/365) -> 65.745 | BC62: =$F62*8.766*AU62*(V62/365) -> 65.745 | BD62: =$F62*8.766*AV62*(W62/365) -> 65.745 | BE62: 0.2 | BF62: =$BE62*$K62*(Q62/365)*($L62/(1-$M62)) -> 67.2 | BG62: =$BE62*$K62*(R62/365)*($L62/(1-$M62)) -> 67.2 | BH62: =$BE62*$K62*(S62/365)*($L62/(1-$M62)) -> 67.2 | BI62: =$BE62*$K62*(T62/365)*($L62/(1-$M62)) -> 67.2 | BJ62: =$BE62*$K62*(U62/365)*($L62/(1-$M62)) -> 67.2 | BK62: =$BE62*$K62*(V62/365)*($L62/(1-$M62)) -> 67.2 | BL62: =$BE62*$K62*(W62/365)*($L62/(1-$M62)) -> 67.2 | BM62: 0.04 | BN62: =$BM62*$K62*(Q62/365) -> 84 | BO62: =($BM62*$K62*(R62/365)) -> 84 | BP62: =$BM62*$K62*(S62/365) -> 84 | BQ62: =$BM62*$K62*(T62/365) -> 84 | BR62: =$BM62*$K62*(U62/365) -> 84 | BS62: =$BM62*$K62*(V62/365) -> 84 | BT62: =$BM62*$K62*(W62/365) -> 84 | CC62: 0 | CD62: 0 | CE62: =IF(SUM($BX62:$CB62)=0,0,BX62/SUM($BX62:$CB62)*(1-$O62)) -> 0 | CF62: =IF(SUM($BX62:$CB62)=0,0,BY62/SUM($BX62:$CB62)*(1-$O62)) -> 0 | CG62: =IF(SUM($BX62:$CB62)=0,0,BZ62/SUM($BX62:$CB62)*(1-$O62)) -> 0 | CH62: =IF(SUM($BX62:$CB62)=0,0,CA62/SUM($BX62:$CB62)*(1-$O62)) -> 0 | CI62: =IF(SUM($BX62:$CB62)=0,0,CB62/SUM($BX62:$CB62)*(1-$O62)) -> 0 | CJ62: =$O62+SUM(CC62:CI62) -> 0 | CL62: =IF($K62*CC62<=0,,$K62*CC62) -> 0 | CM62: =IF($K62*CD62<=0,,$K62*CD62) -> 0 | CN62: =IF($K62*CE62<=0,,$K62*CE62) -> 0 | CO62: =IF($K62*CF62<=0,,$K62*CF62) -> 0 | CP62: =IF($K62*CG62<=0,,$K62*CG62) -> 0 | CQ62: =IF($K62*CH62<=0,,$K62*CH62) -> 0 | CR62: =IF($K62*CI62<=0,,$K62*CI62) -> 0 | CT62: =$BE62*CL62 -> 0 | CU62: =$BE62*CM62 -> 0 | CV62: =$BE62*CN62 -> 0 | CW62: =$BE62*CO62 -> 0 | CX62: =$BE62*CP62 -> 0 | CY62: =$BE62*CQ62 -> 0 | CZ62: =$BE62*CR62 -> 0 | DB62: =CL62-CT62 -> 0 | DC62: =CM62-CU62 -> 0 | DD62: =CN62-CV62 -> 0 | DE62: =CO62-CW62 -> 0 | DF62: =CP62-CX62 -> 0 | DG62: =CQ62-CY62 -> 0 | DH62: =CR62-CZ62 -> 0 | DJ62: =IF(Z62<=26,IF(AND(P62=0,Q62>0),0,IF(Q62>0,($K62*(1-$BE62))/25,0)),0) -> 67.2 | DK62: =IF(AA62<=26,IF(AND(Q62=0,R62>0),0,IF(R62>0,($K62*(1-$BE62))/25,0)),0) -> 67.2 | DL62: =IF(AB62<=26,IF(AND(R62=0,S62>0),0,IF(S62>0,($K62*(1-$BE62))/25,0)),0) -> 67.2 | DM62: =IF(AC62<=26,IF(AND(S62=0,T62>0),0,IF(T62>0,($K62*(1-$BE62))/25,0)),0) -> 67.2 | DN62: =IF(AD62<=26,IF(AND(T62=0,U62>0),0,IF(U62>0,($K62*(1-$BE62))/25,0)),0) -> 67.2 | DO62: =IF(AE62<=26,IF(AND(U62=0,V62>0),0,IF(V62>0,($K62*(1-$BE62))/25,0)),0) -> 67.2 | DP62: =IF(AF62<=26,IF(AND(V62=0,W62>0),0,IF(W62>0,($K62*(1-$BE62))/25,0)),0) -> 67.2 | DR62: =+IF(Z62>0,$K62*(1-$BE62)-SUM($DJ62:DJ62),DB62) -> 1612.8 | DS62: =+IF(AA62>0,$K62*(1-$BE62)-SUM($DJ62:DK62),DC62) -> 1545.6 | DT62: =+IF(AB62>0,$K62*(1-$BE62)-SUM($DJ62:DL62),DD62) -> 1478.4 | DU62: =+IF(AC62>0,$K62*(1-$BE62)-SUM($DJ62:DM62),DE62) -> 1411.2 | DV62: =+IF(AD62>0,$K62*(1-$BE62)-SUM($DJ62:DN62),DF62) -> 1344 | DW62: =+IF(AE62>0,$K62*(1-$BE62)-SUM($DJ62:DO62),DG62) -> 1276.8 | DX62: =+IF(AF62>0,$K62*(1-$BE62)-SUM($DJ62:DP62),DH62) -> 1209.6 | DZ62: =DR62*(DZ$51)*(Q62/365) -> 161.28 | EA62: =DS62*(EA$51)*(R62/365) -> 154.56 | EB62: =DT62*(EB$51)*(S62/365) -> 147.84 | EC62: =DU62*(EC$51)*(T62/365) -> 141.12 | ED62: =DV62*(ED$51)*(U62/365) -> 134.4 | EE62: =DW62*(EE$51)*(V62/365) -> 127.68 | EF62: =DY62*(EF$51)*(W62/365) -> 0 | FM62: 0 | FN62: 0 | FO62: =IF(AA62<1,$K62*$O62,0) -> 0 | FV62: =IF($D62="BESS",IF(Z62<=$S$18,$S$13,$S$21),$N62) -> 7.45 | FW62: =IF($D62="BESS",IF(AA62<=$S$18,$S$13,$S$21),$N62) -> 7.45 | FX62: =IF($D62="BESS",IF(AB62<=$S$18,$S$13,$S$21),$N62) -> 7.45 | FY62: =IF($D62="BESS",IF(AC62<=$S$18,$S$13,$S$21),$N62) -> 7.45 | FZ62: =IF($D62="BESS",IF(AD62<=$S$18,$S$13,$S$21),$N62) -> 7.45 | GA62: =IF($D62="BESS",IF(AE62<=$S$18,$S$13,$S$21),$N62) -> 7.45 | GB62: =IF($D62="BESS",IF(AF62<=$S$18,$S$13,$S$21),$N62) -> 7.45
B63: =Key_New!D13 -> Bihar | C63: =Key_New!B13 -> ACME Magadh Solar Power Pvt Ltd | D63: =Key_New!E13 -> Solar | E63: =Key_New!C13 -> Operational | F63: =Key_New!F13 -> 10 | G63: =IF(NOT(ISNUMBER($H63)),"",IF($H63<=DATE(2026,3,31),$H63,EDATE($H63,-IF($D63="BESS",$S$19,$S$26)))) -> 42551 | H63: =Key_New!O13 -> 42551 | I63: =IF(MONTH(H63)<=3,YEAR(H63),YEAR(H63)+1) -> 2017 | J63: 70 | K63: =J63*F63 -> 700 | L63: 0.12 | M63: 0.25 | N63: =Key_New!J13 -> 8.73 | O63: =IF(OR(NOT(ISNUMBER($G63)),NOT(ISNUMBER($H63)),$H63<=DATE(2026,3,31)),0,MIN(1,MAX(0,(DATE(2026,3,31)-$G63)/($H63-$G63)))*$S$23) -> 0 | P63: =IF(OR(ISERROR(P$49-$H63),(P$49-$H63)>=365),365,IF((P$49-$H63)<=0,0,P$49-$H63)) -> 365 | Q63: =IF(OR(ISERROR(Q$49-$H63),(Q$49-$H63)>=365),365,IF((Q$49-$H63)<=0,0,Q$49-$H63)) -> 365 | R63: =IF(OR(ISERROR(R$49-$H63),(R$49-$H63)>=365),365,IF((R$49-$H63)<=0,0,R$49-$H63)) -> 365 | S63: =IF(OR(ISERROR(S$49-$H63),(S$49-$H63)>=365),365,IF((S$49-$H63)<=0,0,S$49-$H63)) -> 365 | T63: =IF(OR(ISERROR(T$49-$H63),(T$49-$H63)>=365),365,IF((T$49-$H63)<=0,0,T$49-$H63)) -> 365 | U63: =IF(OR(ISERROR(U$49-$H63),(U$49-$H63)>=365),365,IF((U$49-$H63)<=0,0,U$49-$H63)) -> 365 | V63: =IF(OR(ISERROR(V$49-$H63),(V$49-$H63)>=365),365,IF((V$49-$H63)<=0,0,V$49-$H63)) -> 365 | W63: =IF(OR(ISERROR(W$49-$H63),(W$49-$H63)>=365),365,IF((W$49-$H63)<=0,0,W$49-$H63)) -> 365 | Y63: 7 | Z63: =IF(AND(P63=0,Q63>0),1,IF(Y63=0,0,Y63+1)) -> 8 | AA63: =IF(AND(Q63=0,R63>0),1,IF(Z63=0,0,Z63+1)) -> 9 | AB63: =IF(AND(R63=0,S63>0),1,IF(AA63=0,0,AA63+1)) -> 10 | AC63: =IF(AND(S63=0,T63>0),1,IF(AB63=0,0,AB63+1)) -> 11 | AD63: =IF(AND(T63=0,U63>0),1,IF(AC63=0,0,AC63+1)) -> 12 | AE63: =IF(AND(U63=0,V63>0),1,IF(AD63=0,0,AD63+1)) -> 13 | AF63: =IF(AND(V63=0,W63>0),1,IF(AE63=0,0,AE63+1)) -> 14 | AH63: =IF(AND(P63<=0,Q63>0),$F63,IF(P63>0,$F63,0)) -> 10 | AI63: =IF(AND(Q63<=0,R63>0),$F63,IF(Q63>0,$F63,0)) -> 10 | AJ63: =IF(AND(R63<=0,S63>0),$F63,IF(R63>0,$F63,0)) -> 10 | AK63: =IF(AND(S63<=0,T63>0),$F63,IF(S63>0,$F63,0)) -> 10 | AL63: =IF(AND(T63<=0,U63>0),$F63,IF(T63>0,$F63,0)) -> 10 | AM63: =IF(AND(U63<=0,V63>0),$F63,IF(U63>0,$F63,0)) -> 10 | AN63: =IF(AND(V63<=0,W63>0),$F63,IF(V63>0,$F63,0)) -> 10 | AP63: 0.25 | AQ63: 0.25 | AR63: 0.25 | AS63: 0.25 | AT63: 0.25 | AU63: 0.25 | AV63: 0.25 | AX63: =$F63*8.766*AP63*(Q63/365) -> 21.915 | AY63: =$F63*8.766*AQ63*(R63/365) -> 21.915 | AZ63: =$F63*8.766*AR63*(S63/365) -> 21.915 | BA63: =$F63*8.766*AS63*(T63/365) -> 21.915 | BB63: =$F63*8.766*AT63*(U63/365) -> 21.915 | BC63: =$F63*8.766*AU63*(V63/365) -> 21.915 | BD63: =$F63*8.766*AV63*(W63/365) -> 21.915 | BE63: 0.2 | BF63: =$BE63*$K63*(Q63/365)*($L63/(1-$M63)) -> 22.4 | BG63: =$BE63*$K63*(R63/365)*($L63/(1-$M63)) -> 22.4 | BH63: =$BE63*$K63*(S63/365)*($L63/(1-$M63)) -> 22.4 | BI63: =$BE63*$K63*(T63/365)*($L63/(1-$M63)) -> 22.4 | BJ63: =$BE63*$K63*(U63/365)*($L63/(1-$M63)) -> 22.4 | BK63: =$BE63*$K63*(V63/365)*($L63/(1-$M63)) -> 22.4 | BL63: =$BE63*$K63*(W63/365)*($L63/(1-$M63)) -> 22.4 | BM63: 0.04 | BN63: =$BM63*$K63*(Q63/365) -> 28 | BO63: =($BM63*$K63*(R63/365)) -> 28 | BP63: =$BM63*$K63*(S63/365) -> 28 | BQ63: =$BM63*$K63*(T63/365) -> 28 | BR63: =$BM63*$K63*(U63/365) -> 28 | BS63: =$BM63*$K63*(V63/365) -> 28 | BT63: =$BM63*$K63*(W63/365) -> 28 | CC63: 0 | CD63: 0 | CE63: =IF(SUM($BX63:$CB63)=0,0,BX63/SUM($BX63:$CB63)*(1-$O63)) -> 0 | CF63: =IF(SUM($BX63:$CB63)=0,0,BY63/SUM($BX63:$CB63)*(1-$O63)) -> 0 | CG63: =IF(SUM($BX63:$CB63)=0,0,BZ63/SUM($BX63:$CB63)*(1-$O63)) -> 0 | CH63: =IF(SUM($BX63:$CB63)=0,0,CA63/SUM($BX63:$CB63)*(1-$O63)) -> 0 | CI63: =IF(SUM($BX63:$CB63)=0,0,CB63/SUM($BX63:$CB63)*(1-$O63)) -> 0 | CJ63: =$O63+SUM(CC63:CI63) -> 0 | CL63: =IF($K63*CC63<=0,,$K63*CC63) -> 0 | CM63: =IF($K63*CD63<=0,,$K63*CD63) -> 0 | CN63: =IF($K63*CE63<=0,,$K63*CE63) -> 0 | CO63: =IF($K63*CF63<=0,,$K63*CF63) -> 0 | CP63: =IF($K63*CG63<=0,,$K63*CG63) -> 0 | CQ63: =IF($K63*CH63<=0,,$K63*CH63) -> 0 | CR63: =IF($K63*CI63<=0,,$K63*CI63) -> 0 | CT63: =$BE63*CL63 -> 0 | CU63: =$BE63*CM63 -> 0 | CV63: =$BE63*CN63 -> 0 | CW63: =$BE63*CO63 -> 0 | CX63: =$BE63*CP63 -> 0 | CY63: =$BE63*CQ63 -> 0 | CZ63: =$BE63*CR63 -> 0 | DB63: =CL63-CT63 -> 0 | DC63: =CM63-CU63 -> 0 | DD63: =CN63-CV63 -> 0 | DE63: =CO63-CW63 -> 0 | DF63: =CP63-CX63 -> 0 | DG63: =CQ63-CY63 -> 0 | DH63: =CR63-CZ63 -> 0 | DJ63: =IF(Z63<=26,IF(AND(P63=0,Q63>0),0,IF(Q63>0,($K63*(1-$BE63))/25,0)),0) -> 22.4 | DK63: =IF(AA63<=26,IF(AND(Q63=0,R63>0),0,IF(R63>0,($K63*(1-$BE63))/25,0)),0) -> 22.4 | DL63: =IF(AB63<=26,IF(AND(R63=0,S63>0),0,IF(S63>0,($K63*(1-$BE63))/25,0)),0) -> 22.4 | DM63: =IF(AC63<=26,IF(AND(S63=0,T63>0),0,IF(T63>0,($K63*(1-$BE63))/25,0)),0) -> 22.4 | DN63: =IF(AD63<=26,IF(AND(T63=0,U63>0),0,IF(U63>0,($K63*(1-$BE63))/25,0)),0) -> 22.4 | DO63: =IF(AE63<=26,IF(AND(U63=0,V63>0),0,IF(V63>0,($K63*(1-$BE63))/25,0)),0) -> 22.4 | DP63: =IF(AF63<=26,IF(AND(V63=0,W63>0),0,IF(W63>0,($K63*(1-$BE63))/25,0)),0) -> 22.4 | DR63: =+IF(Z63>0,$K63*(1-$BE63)-SUM($DJ63:DJ63),DB63) -> 537.6 | DS63: =+IF(AA63>0,$K63*(1-$BE63)-SUM($DJ63:DK63),DC63) -> 515.2 | DT63: =+IF(AB63>0,$K63*(1-$BE63)-SUM($DJ63:DL63),DD63) -> 492.8 | DU63: =+IF(AC63>0,$K63*(1-$BE63)-SUM($DJ63:DM63),DE63) -> 470.4 | DV63: =+IF(AD63>0,$K63*(1-$BE63)-SUM($DJ63:DN63),DF63) -> 448 | DW63: =+IF(AE63>0,$K63*(1-$BE63)-SUM($DJ63:DO63),DG63) -> 425.6 | DX63: =+IF(AF63>0,$K63*(1-$BE63)-SUM($DJ63:DP63),DH63) -> 403.2 | DZ63: =DR63*(DZ$51)*(Q63/365) -> 53.76 | EA63: =DS63*(EA$51)*(R63/365) -> 51.52 | EB63: =DT63*(EB$51)*(S63/365) -> 49.28 | EC63: =DU63*(EC$51)*(T63/365) -> 47.04 | ED63: =DV63*(ED$51)*(U63/365) -> 44.8 | EE63: =DW63*(EE$51)*(V63/365) -> 42.56 | EF63: =DY63*(EF$51)*(W63/365) -> 0 | FM63: 0 | FN63: 0 | FO63: =IF(AA63<1,$K63*$O63,0) -> 0 | FV63: =IF($D63="BESS",IF(Z63<=$S$18,$S$13,$S$21),$N63) -> 8.73 | FW63: =IF($D63="BESS",IF(AA63<=$S$18,$S$13,$S$21),$N63) -> 8.73 | FX63: =IF($D63="BESS",IF(AB63<=$S$18,$S$13,$S$21),$N63) -> 8.73 | FY63: =IF($D63="BESS",IF(AC63<=$S$18,$S$13,$S$21),$N63) -> 8.73 | FZ63: =IF($D63="BESS",IF(AD63<=$S$18,$S$13,$S$21),$N63) -> 8.73 | GA63: =IF($D63="BESS",IF(AE63<=$S$18,$S$13,$S$21),$N63) -> 8.73 | GB63: =IF($D63="BESS",IF(AF63<=$S$18,$S$13,$S$21),$N63) -> 8.73
B64: =Key_New!D14 -> Bihar | C64: =Key_New!B14 -> ACME Nalanda Solar Power Pvt Ltd | D64: =Key_New!E14 -> Solar | E64: =Key_New!C14 -> Operational | F64: =Key_New!F14 -> 15 | G64: =IF(NOT(ISNUMBER($H64)),"",IF($H64<=DATE(2026,3,31),$H64,EDATE($H64,-IF($D64="BESS",$S$19,$S$26)))) -> 42551 | H64: =Key_New!O14 -> 42551 | I64: =IF(MONTH(H64)<=3,YEAR(H64),YEAR(H64)+1) -> 2017 | J64: 70 | K64: =J64*F64 -> 1050 | L64: 0.12 | M64: 0.25 | N64: =Key_New!J14 -> 8.73 | O64: =IF(OR(NOT(ISNUMBER($G64)),NOT(ISNUMBER($H64)),$H64<=DATE(2026,3,31)),0,MIN(1,MAX(0,(DATE(2026,3,31)-$G64)/($H64-$G64)))*$S$23) -> 0 | P64: =IF(OR(ISERROR(P$49-$H64),(P$49-$H64)>=365),365,IF((P$49-$H64)<=0,0,P$49-$H64)) -> 365 | Q64: =IF(OR(ISERROR(Q$49-$H64),(Q$49-$H64)>=365),365,IF((Q$49-$H64)<=0,0,Q$49-$H64)) -> 365 | R64: =IF(OR(ISERROR(R$49-$H64),(R$49-$H64)>=365),365,IF((R$49-$H64)<=0,0,R$49-$H64)) -> 365 | S64: =IF(OR(ISERROR(S$49-$H64),(S$49-$H64)>=365),365,IF((S$49-$H64)<=0,0,S$49-$H64)) -> 365 | T64: =IF(OR(ISERROR(T$49-$H64),(T$49-$H64)>=365),365,IF((T$49-$H64)<=0,0,T$49-$H64)) -> 365 | U64: =IF(OR(ISERROR(U$49-$H64),(U$49-$H64)>=365),365,IF((U$49-$H64)<=0,0,U$49-$H64)) -> 365 | V64: =IF(OR(ISERROR(V$49-$H64),(V$49-$H64)>=365),365,IF((V$49-$H64)<=0,0,V$49-$H64)) -> 365 | W64: =IF(OR(ISERROR(W$49-$H64),(W$49-$H64)>=365),365,IF((W$49-$H64)<=0,0,W$49-$H64)) -> 365 | Y64: 7 | Z64: =IF(AND(P64=0,Q64>0),1,IF(Y64=0,0,Y64+1)) -> 8 | AA64: =IF(AND(Q64=0,R64>0),1,IF(Z64=0,0,Z64+1)) -> 9 | AB64: =IF(AND(R64=0,S64>0),1,IF(AA64=0,0,AA64+1)) -> 10 | AC64: =IF(AND(S64=0,T64>0),1,IF(AB64=0,0,AB64+1)) -> 11 | AD64: =IF(AND(T64=0,U64>0),1,IF(AC64=0,0,AC64+1)) -> 12 | AE64: =IF(AND(U64=0,V64>0),1,IF(AD64=0,0,AD64+1)) -> 13 | AF64: =IF(AND(V64=0,W64>0),1,IF(AE64=0,0,AE64+1)) -> 14 | AH64: =IF(AND(P64<=0,Q64>0),$F64,IF(P64>0,$F64,0)) -> 15 | AI64: =IF(AND(Q64<=0,R64>0),$F64,IF(Q64>0,$F64,0)) -> 15 | AJ64: =IF(AND(R64<=0,S64>0),$F64,IF(R64>0,$F64,0)) -> 15 | AK64: =IF(AND(S64<=0,T64>0),$F64,IF(S64>0,$F64,0)) -> 15 | AL64: =IF(AND(T64<=0,U64>0),$F64,IF(T64>0,$F64,0)) -> 15 | AM64: =IF(AND(U64<=0,V64>0),$F64,IF(U64>0,$F64,0)) -> 15 | AN64: =IF(AND(V64<=0,W64>0),$F64,IF(V64>0,$F64,0)) -> 15 | AP64: 0.25 | AQ64: 0.25 | AR64: 0.25 | AS64: 0.25 | AT64: 0.25 | AU64: 0.25 | AV64: 0.25 | AX64: =$F64*8.766*AP64*(Q64/365) -> 32.8725 | AY64: =$F64*8.766*AQ64*(R64/365) -> 32.8725 | AZ64: =$F64*8.766*AR64*(S64/365) -> 32.8725 | BA64: =$F64*8.766*AS64*(T64/365) -> 32.8725 | BB64: =$F64*8.766*AT64*(U64/365) -> 32.8725 | BC64: =$F64*8.766*AU64*(V64/365) -> 32.8725 | BD64: =$F64*8.766*AV64*(W64/365) -> 32.8725 | BE64: 0.2 | BF64: =$BE64*$K64*(Q64/365)*($L64/(1-$M64)) -> 33.6 | BG64: =$BE64*$K64*(R64/365)*($L64/(1-$M64)) -> 33.6 | BH64: =$BE64*$K64*(S64/365)*($L64/(1-$M64)) -> 33.6 | BI64: =$BE64*$K64*(T64/365)*($L64/(1-$M64)) -> 33.6 | BJ64: =$BE64*$K64*(U64/365)*($L64/(1-$M64)) -> 33.6 | BK64: =$BE64*$K64*(V64/365)*($L64/(1-$M64)) -> 33.6 | BL64: =$BE64*$K64*(W64/365)*($L64/(1-$M64)) -> 33.6 | BM64: 0.04 | BN64: =$BM64*$K64*(Q64/365) -> 42 | BO64: =($BM64*$K64*(R64/365)) -> 42 | BP64: =$BM64*$K64*(S64/365) -> 42 | BQ64: =$BM64*$K64*(T64/365) -> 42 | BR64: =$BM64*$K64*(U64/365) -> 42 | BS64: =$BM64*$K64*(V64/365) -> 42 | BT64: =$BM64*$K64*(W64/365) -> 42 | CC64: 0 | CD64: 0 | CE64: =IF(SUM($BX64:$CB64)=0,0,BX64/SUM($BX64:$CB64)*(1-$O64)) -> 0 | CF64: =IF(SUM($BX64:$CB64)=0,0,BY64/SUM($BX64:$CB64)*(1-$O64)) -> 0 | CG64: =IF(SUM($BX64:$CB64)=0,0,BZ64/SUM($BX64:$CB64)*(1-$O64)) -> 0 | CH64: =IF(SUM($BX64:$CB64)=0,0,CA64/SUM($BX64:$CB64)*(1-$O64)) -> 0 | CI64: =IF(SUM($BX64:$CB64)=0,0,CB64/SUM($BX64:$CB64)*(1-$O64)) -> 0 | CJ64: =$O64+SUM(CC64:CI64) -> 0 | CL64: =IF($K64*CC64<=0,,$K64*CC64) -> 0 | CM64: =IF($K64*CD64<=0,,$K64*CD64) -> 0 | CN64: =IF($K64*CE64<=0,,$K64*CE64) -> 0 | CO64: =IF($K64*CF64<=0,,$K64*CF64) -> 0 | CP64: =IF($K64*CG64<=0,,$K64*CG64) -> 0 | CQ64: =IF($K64*CH64<=0,,$K64*CH64) -> 0 | CR64: =IF($K64*CI64<=0,,$K64*CI64) -> 0 | CT64: =$BE64*CL64 -> 0 | CU64: =$BE64*CM64 -> 0 | CV64: =$BE64*CN64 -> 0 | CW64: =$BE64*CO64 -> 0 | CX64: =$BE64*CP64 -> 0 | CY64: =$BE64*CQ64 -> 0 | CZ64: =$BE64*CR64 -> 0 | DB64: =CL64-CT64 -> 0 | DC64: =CM64-CU64 -> 0 | DD64: =CN64-CV64 -> 0 | DE64: =CO64-CW64 -> 0 | DF64: =CP64-CX64 -> 0 | DG64: =CQ64-CY64 -> 0 | DH64: =CR64-CZ64 -> 0 | DJ64: =IF(Z64<=26,IF(AND(P64=0,Q64>0),0,IF(Q64>0,($K64*(1-$BE64))/25,0)),0) -> 33.6 | DK64: =IF(AA64<=26,IF(AND(Q64=0,R64>0),0,IF(R64>0,($K64*(1-$BE64))/25,0)),0) -> 33.6 | DL64: =IF(AB64<=26,IF(AND(R64=0,S64>0),0,IF(S64>0,($K64*(1-$BE64))/25,0)),0) -> 33.6 | DM64: =IF(AC64<=26,IF(AND(S64=0,T64>0),0,IF(T64>0,($K64*(1-$BE64))/25,0)),0) -> 33.6 | DN64: =IF(AD64<=26,IF(AND(T64=0,U64>0),0,IF(U64>0,($K64*(1-$BE64))/25,0)),0) -> 33.6 | DO64: =IF(AE64<=26,IF(AND(U64=0,V64>0),0,IF(V64>0,($K64*(1-$BE64))/25,0)),0) -> 33.6 | DP64: =IF(AF64<=26,IF(AND(V64=0,W64>0),0,IF(W64>0,($K64*(1-$BE64))/25,0)),0) -> 33.6 | DR64: =+IF(Z64>0,$K64*(1-$BE64)-SUM($DJ64:DJ64),DB64) -> 806.4 | DS64: =+IF(AA64>0,$K64*(1-$BE64)-SUM($DJ64:DK64),DC64) -> 772.8 | DT64: =+IF(AB64>0,$K64*(1-$BE64)-SUM($DJ64:DL64),DD64) -> 739.2 | DU64: =+IF(AC64>0,$K64*(1-$BE64)-SUM($DJ64:DM64),DE64) -> 705.6 | DV64: =+IF(AD64>0,$K64*(1-$BE64)-SUM($DJ64:DN64),DF64) -> 672 | DW64: =+IF(AE64>0,$K64*(1-$BE64)-SUM($DJ64:DO64),DG64) -> 638.4 | DX64: =+IF(AF64>0,$K64*(1-$BE64)-SUM($DJ64:DP64),DH64) -> 604.8 | DZ64: =DR64*(DZ$51)*(Q64/365) -> 80.64 | EA64: =DS64*(EA$51)*(R64/365) -> 77.28 | EB64: =DT64*(EB$51)*(S64/365) -> 73.92 | EC64: =DU64*(EC$51)*(T64/365) -> 70.56 | ED64: =DV64*(ED$51)*(U64/365) -> 67.2 | EE64: =DW64*(EE$51)*(V64/365) -> 63.84 | EF64: =DY64*(EF$51)*(W64/365) -> 0 | FM64: 0 | FN64: 0 | FO64: =IF(AA64<1,$K64*$O64,0) -> 0 | FV64: =IF($D64="BESS",IF(Z64<=$S$18,$S$13,$S$21),$N64) -> 8.73 | FW64: =IF($D64="BESS",IF(AA64<=$S$18,$S$13,$S$21),$N64) -> 8.73 | FX64: =IF($D64="BESS",IF(AB64<=$S$18,$S$13,$S$21),$N64) -> 8.73 | FY64: =IF($D64="BESS",IF(AC64<=$S$18,$S$13,$S$21),$N64) -> 8.73 | FZ64: =IF($D64="BESS",IF(AD64<=$S$18,$S$13,$S$21),$N64) -> 8.73 | GA64: =IF($D64="BESS",IF(AE64<=$S$18,$S$13,$S$21),$N64) -> 8.73 | GB64: =IF($D64="BESS",IF(AF64<=$S$18,$S$13,$S$21),$N64) -> 8.73
... B80: =Key_New!D30 -> Rajasthan | C80: =Key_New!B30 -> ACME Phalodi Solar Energy Pvt Ltd | D80: =Key_New!E30 -> Solar | E80: =Key_New!C30 -> Operational | F80: =Key_New!F30 -> 300 | G80: =IF(NOT(ISNUMBER($H80)),"",IF($H80<=DATE(2026,3,31),$H80,EDATE($H80,-IF($D80="BESS",$S$19,$S$26)))) -> 45688 | H80: =Key_New!O30 -> 45688 | I80: =IF(MONTH(H80)<=3,YEAR(H80),YEAR(H80)+1) -> 2025 | J80: 50 | K80: =J80*F80 -> 15000 | L80: 0.12 | M80: 0.25 | N80: =Key_New!J30 -> 2.44 | O80: =IF(OR(NOT(ISNUMBER($G80)),NOT(ISNUMBER($H80)),$H80<=DATE(2026,3,31)),0,MIN(1,MAX(0,(DATE(2026,3,31)-$G80)/($H80-$G80)))*$S$23) -> 0 | P80: =IF(OR(ISERROR(P$49-$H80),(P$49-$H80)>=365),365,IF((P$49-$H80)<=0,0,P$49-$H80)) -> 0 | Q80: =IF(OR(ISERROR(Q$49-$H80),(Q$49-$H80)>=365),365,IF((Q$49-$H80)<=0,0,Q$49-$H80)) -> 59 | R80: =IF(OR(ISERROR(R$49-$H80),(R$49-$H80)>=365),365,IF((R$49-$H80)<=0,0,R$49-$H80)) -> 365 | S80: =IF(OR(ISERROR(S$49-$H80),(S$49-$H80)>=365),365,IF((S$49-$H80)<=0,0,S$49-$H80)) -> 365 | T80: =IF(OR(ISERROR(T$49-$H80),(T$49-$H80)>=365),365,IF((T$49-$H80)<=0,0,T$49-$H80)) -> 365 | U80: =IF(OR(ISERROR(U$49-$H80),(U$49-$H80)>=365),365,IF((U$49-$H80)<=0,0,U$49-$H80)) -> 365 | V80: =IF(OR(ISERROR(V$49-$H80),(V$49-$H80)>=365),365,IF((V$49-$H80)<=0,0,V$49-$H80)) -> 365 | W80: =IF(OR(ISERROR(W$49-$H80),(W$49-$H80)>=365),365,IF((W$49-$H80)<=0,0,W$49-$H80)) -> 365 | Y80: 0 | Z80: =IF(AND(P80=0,Q80>0),1,IF(Y80=0,0,Y80+1)) -> 1 | AA80: =IF(AND(Q80=0,R80>0),1,IF(Z80=0,0,Z80+1)) -> 2 | AB80: =IF(AND(R80=0,S80>0),1,IF(AA80=0,0,AA80+1)) -> 3 | AC80: =IF(AND(S80=0,T80>0),1,IF(AB80=0,0,AB80+1)) -> 4 | AD80: =IF(AND(T80=0,U80>0),1,IF(AC80=0,0,AC80+1)) -> 5 | AE80: =IF(AND(U80=0,V80>0),1,IF(AD80=0,0,AD80+1)) -> 6 | AF80: =IF(AND(V80=0,W80>0),1,IF(AE80=0,0,AE80+1)) -> 7 | AH80: =IF(AND(P80<=0,Q80>0),$F80,IF(P80>0,$F80,0)) -> 300 | AI80: =IF(AND(Q80<=0,R80>0),$F80,IF(Q80>0,$F80,0)) -> 300 | AJ80: =IF(AND(R80<=0,S80>0),$F80,IF(R80>0,$F80,0)) -> 300 | AK80: =IF(AND(S80<=0,T80>0),$F80,IF(S80>0,$F80,0)) -> 300 | AL80: =IF(AND(T80<=0,U80>0),$F80,IF(T80>0,$F80,0)) -> 300 | AM80: =IF(AND(U80<=0,V80>0),$F80,IF(U80>0,$F80,0)) -> 300 | AN80: =IF(AND(V80<=0,W80>0),$F80,IF(V80>0,$F80,0)) -> 300 | AP80: 0.25 | AQ80: 0.25 | AR80: 0.25 | AS80: 0.25 | AT80: 0.25 | AU80: 0.25 | AV80: 0.25 | AX80: =$F80*8.766*AP80*(Q80/365) -> 106.27274 | AY80: =$F80*8.766*AQ80*(R80/365) -> 657.45 | AZ80: =$F80*8.766*AR80*(S80/365) -> 657.45 | BA80: =$F80*8.766*AS80*(T80/365) -> 657.45 | BB80: =$F80*8.766*AT80*(U80/365) -> 657.45 | BC80: =$F80*8.766*AU80*(V80/365) -> 657.45 | BD80: =$F80*8.766*AV80*(W80/365) -> 657.45 | BE80: 0.2 | BF80: =$BE80*$K80*(Q80/365)*($L80/(1-$M80)) -> 77.589041 | BG80: =$BE80*$K80*(R80/365)*($L80/(1-$M80)) -> 480 | BH80: =$BE80*$K80*(S80/365)*($L80/(1-$M80)) -> 480 | BI80: =$BE80*$K80*(T80/365)*($L80/(1-$M80)) -> 480 | BJ80: =$BE80*$K80*(U80/365)*($L80/(1-$M80)) -> 480 | BK80: =$BE80*$K80*(V80/365)*($L80/(1-$M80)) -> 480 | BL80: =$BE80*$K80*(W80/365)*($L80/(1-$M80)) -> 480 | BM80: 0.04 | BN80: =$BM80*$K80*(Q80/365) -> 96.986301 | BO80: =($BM80*$K80*(R80/365)) -> 600 | BP80: =$BM80*$K80*(S80/365) -> 600 | BQ80: =$BM80*$K80*(T80/365) -> 600 | BR80: =$BM80*$K80*(U80/365) -> 600 | BS80: =$BM80*$K80*(V80/365) -> 600 | BT80: =$BM80*$K80*(W80/365) -> 600 | CC80: 0 | CD80: 0 | CE80: =IF(SUM($BX80:$CB80)=0,0,BX80/SUM($BX80:$CB80)*(1-$O80)) -> 0 | CF80: =IF(SUM($BX80:$CB80)=0,0,BY80/SUM($BX80:$CB80)*(1-$O80)) -> 0 | CG80: =IF(SUM($BX80:$CB80)=0,0,BZ80/SUM($BX80:$CB80)*(1-$O80)) -> 0 | CH80: =IF(SUM($BX80:$CB80)=0,0,CA80/SUM($BX80:$CB80)*(1-$O80)) -> 0 | CI80: =IF(SUM($BX80:$CB80)=0,0,CB80/SUM($BX80:$CB80)*(1-$O80)) -> 0 | CJ80: =$O80+SUM(CC80:CI80) -> 0 | CL80: =IF($K80*CC80<=0,,$K80*CC80) -> 0 | CM80: =IF($K80*CD80<=0,,$K80*CD80) -> 0 | CN80: =IF($K80*CE80<=0,,$K80*CE80) -> 0 | CO80: =IF($K80*CF80<=0,,$K80*CF80) -> 0 | CP80: =IF($K80*CG80<=0,,$K80*CG80) -> 0 | CQ80: =IF($K80*CH80<=0,,$K80*CH80) -> 0 | CR80: =IF($K80*CI80<=0,,$K80*CI80) -> 0 | CT80: =$BE80*CL80 -> 0 | CU80: =$BE80*CM80 -> 0 | CV80: =$BE80*CN80 -> 0 | CW80: =$BE80*CO80 -> 0 | CX80: =$BE80*CP80 -> 0 | CY80: =$BE80*CQ80 -> 0 | CZ80: =$BE80*CR80 -> 0 | DB80: =CL80-CT80 -> 0 | DC80: =CM80-CU80 -> 0 | DD80: =CN80-CV80 -> 0 | DE80: =CO80-CW80 -> 0 | DF80: =CP80-CX80 -> 0 | DG80: =CQ80-CY80 -> 0 | DH80: =CR80-CZ80 -> 0 | DJ80: =IF(Z80<=26,IF(AND(P80=0,Q80>0),0,IF(Q80>0,($K80*(1-$BE80))/25,0)),0) -> 0 | DK80: =IF(AA80<=26,IF(AND(Q80=0,R80>0),0,IF(R80>0,($K80*(1-$BE80))/25,0)),0) -> 480 | DL80: =IF(AB80<=26,IF(AND(R80=0,S80>0),0,IF(S80>0,($K80*(1-$BE80))/25,0)),0) -> 480 | DM80: =IF(AC80<=26,IF(AND(S80=0,T80>0),0,IF(T80>0,($K80*(1-$BE80))/25,0)),0) -> 480 | DN80: =IF(AD80<=26,IF(AND(T80=0,U80>0),0,IF(U80>0,($K80*(1-$BE80))/25,0)),0) -> 480 | DO80: =IF(AE80<=26,IF(AND(U80=0,V80>0),0,IF(V80>0,($K80*(1-$BE80))/25,0)),0) -> 480 | DP80: =IF(AF80<=26,IF(AND(V80=0,W80>0),0,IF(W80>0,($K80*(1-$BE80))/25,0)),0) -> 480 | DR80: =+IF(Z80>0,$K80*(1-$BE80)-SUM($DJ80:DJ80),DB80) -> 12000 | DS80: =+IF(AA80>0,$K80*(1-$BE80)-SUM($DJ80:DK80),DC80) -> 11520 | DT80: =+IF(AB80>0,$K80*(1-$BE80)-SUM($DJ80:DL80),DD80) -> 11040 | DU80: =+IF(AC80>0,$K80*(1-$BE80)-SUM($DJ80:DM80),DE80) -> 10560 | DV80: =+IF(AD80>0,$K80*(1-$BE80)-SUM($DJ80:DN80),DF80) -> 10080 | DW80: =+IF(AE80>0,$K80*(1-$BE80)-SUM($DJ80:DO80),DG80) -> 9600 | DX80: =+IF(AF80>0,$K80*(1-$BE80)-SUM($DJ80:DP80),DH80) -> 9120 | DZ80: =DR80*(DZ$51)*(Q80/365) -> 193.9726 | EA80: =DS80*(EA$51)*(R80/365) -> 1152 | EB80: =DT80*(EB$51)*(S80/365) -> 1104 | EC80: =DU80*(EC$51)*(T80/365) -> 1056 | ED80: =DV80*(ED$51)*(U80/365) -> 1008 | EE80: =DW80*(EE$51)*(V80/365) -> 960 | EF80: =DY80*(EF$51)*(W80/365) -> 0 | FM80: 0 | FN80: 0 | FO80: =IF(AA80<1,$K80*$O80,0) -> 0 | FV80: =IF($D80="BESS",IF(Z80<=$S$18,$S$13,$S$21),$N80) -> 2.44 | FW80: =IF($D80="BESS",IF(AA80<=$S$18,$S$13,$S$21),$N80) -> 2.44 | FX80: =IF($D80="BESS",IF(AB80<=$S$18,$S$13,$S$21),$N80) -> 2.44 | FY80: =IF($D80="BESS",IF(AC80<=$S$18,$S$13,$S$21),$N80) -> 2.44 | FZ80: =IF($D80="BESS",IF(AD80<=$S$18,$S$13,$S$21),$N80) -> 2.44 | GA80: =IF($D80="BESS",IF(AE80<=$S$18,$S$13,$S$21),$N80) -> 2.44 | GB80: =IF($D80="BESS",IF(AF80<=$S$18,$S$13,$S$21),$N80) -> 2.44
B81: =Key_New!D31 -> Rajasthan | C81: =Key_New!B31 -> ACME Sikar Solar Pvt Ltd | D81: =Key_New!E31 -> Solar | E81: =Key_New!C31 -> Operational | F81: =Key_New!F31 -> 300 | G81: =IF(NOT(ISNUMBER($H81)),"",IF($H81<=DATE(2026,3,31),$H81,EDATE($H81,-IF($D81="BESS",$S$19,$S$26)))) -> 45838 | H81: =Key_New!O31 -> 45838 | I81: =IF(MONTH(H81)<=3,YEAR(H81),YEAR(H81)+1) -> 2026 | J81: 45 | K81: =J81*F81 -> 13500 | L81: 0.12 | M81: 0.25 | N81: =Key_New!J31 -> 3.05 | O81: =IF(OR(NOT(ISNUMBER($G81)),NOT(ISNUMBER($H81)),$H81<=DATE(2026,3,31)),0,MIN(1,MAX(0,(DATE(2026,3,31)-$G81)/($H81-$G81)))*$S$23) -> 0 | P81: =IF(OR(ISERROR(P$49-$H81),(P$49-$H81)>=365),365,IF((P$49-$H81)<=0,0,P$49-$H81)) -> 0 | Q81: =IF(OR(ISERROR(Q$49-$H81),(Q$49-$H81)>=365),365,IF((Q$49-$H81)<=0,0,Q$49-$H81)) -> 0 | R81: =IF(OR(ISERROR(R$49-$H81),(R$49-$H81)>=365),365,IF((R$49-$H81)<=0,0,R$49-$H81)) -> 274 | S81: =IF(OR(ISERROR(S$49-$H81),(S$49-$H81)>=365),365,IF((S$49-$H81)<=0,0,S$49-$H81)) -> 365 | T81: =IF(OR(ISERROR(T$49-$H81),(T$49-$H81)>=365),365,IF((T$49-$H81)<=0,0,T$49-$H81)) -> 365 | U81: =IF(OR(ISERROR(U$49-$H81),(U$49-$H81)>=365),365,IF((U$49-$H81)<=0,0,U$49-$H81)) -> 365 | V81: =IF(OR(ISERROR(V$49-$H81),(V$49-$H81)>=365),365,IF((V$49-$H81)<=0,0,V$49-$H81)) -> 365 | W81: =IF(OR(ISERROR(W$49-$H81),(W$49-$H81)>=365),365,IF((W$49-$H81)<=0,0,W$49-$H81)) -> 365 | Y81: =IF(AND(O81=0,P81>0),1,IF(X81=0,0,X81+1)) -> 0 | Z81: =IF(AND(P81=0,Q81>0),1,IF(Y81=0,0,Y81+1)) -> 0 | AA81: =IF(AND(Q81=0,R81>0),1,IF(Z81=0,0,Z81+1)) -> 1 | AB81: =IF(AND(R81=0,S81>0),1,IF(AA81=0,0,AA81+1)) -> 2 | AC81: =IF(AND(S81=0,T81>0),1,IF(AB81=0,0,AB81+1)) -> 3 | AD81: =IF(AND(T81=0,U81>0),1,IF(AC81=0,0,AC81+1)) -> 4 | AE81: =IF(AND(U81=0,V81>0),1,IF(AD81=0,0,AD81+1)) -> 5 | AF81: =IF(AND(V81=0,W81>0),1,IF(AE81=0,0,AE81+1)) -> 6 | AH81: =IF(AND(P81<=0,Q81>0),$F81,IF(P81>0,$F81,0)) -> 0 | AI81: =IF(AND(Q81<=0,R81>0),$F81,IF(Q81>0,$F81,0)) -> 300 | AJ81: =IF(AND(R81<=0,S81>0),$F81,IF(R81>0,$F81,0)) -> 300 | AK81: =IF(AND(S81<=0,T81>0),$F81,IF(S81>0,$F81,0)) -> 300 | AL81: =IF(AND(T81<=0,U81>0),$F81,IF(T81>0,$F81,0)) -> 300 | AM81: =IF(AND(U81<=0,V81>0),$F81,IF(U81>0,$F81,0)) -> 300 | AN81: =IF(AND(V81<=0,W81>0),$F81,IF(V81>0,$F81,0)) -> 300 | AP81: 0.25 | AQ81: 0.25 | AR81: 0.25 | AS81: 0.25 | AT81: 0.25 | AU81: 0.25 | AV81: 0.25 | AX81: =$F81*8.766*AP81*(Q81/365) -> 0 | AY81: =$F81*8.766*AQ81*(R81/365) -> 493.53781 | AZ81: =$F81*8.766*AR81*(S81/365) -> 657.45 | BA81: =$F81*8.766*AS81*(T81/365) -> 657.45 | BB81: =$F81*8.766*AT81*(U81/365) -> 657.45 | BC81: =$F81*8.766*AU81*(V81/365) -> 657.45 | BD81: =$F81*8.766*AV81*(W81/365) -> 657.45 | BE81: 0.2 | BF81: =$BE81*$K81*(Q81/365)*($L81/(1-$M81)) -> 0 | BG81: =$BE81*$K81*(R81/365)*($L81/(1-$M81)) -> 324.29589 | BH81: =$BE81*$K81*(S81/365)*($L81/(1-$M81)) -> 432 | BI81: =$BE81*$K81*(T81/365)*($L81/(1-$M81)) -> 432 | BJ81: =$BE81*$K81*(U81/365)*($L81/(1-$M81)) -> 432 | BK81: =$BE81*$K81*(V81/365)*($L81/(1-$M81)) -> 432 | BL81: =$BE81*$K81*(W81/365)*($L81/(1-$M81)) -> 432 | BM81: 0.04 | BN81: =$BM81*$K81*(Q81/365) -> 0 | BO81: =($BM81*$K81*(R81/365)) -> 405.36986 | BP81: =$BM81*$K81*(S81/365) -> 540 | BQ81: =$BM81*$K81*(T81/365) -> 540 | BR81: =$BM81*$K81*(U81/365) -> 540 | BS81: =$BM81*$K81*(V81/365) -> 540 | BT81: =$BM81*$K81*(W81/365) -> 540 | CC81: 0 | CD81: 0 | CE81: =IF(SUM($BX81:$CB81)=0,0,BX81/SUM($BX81:$CB81)*(1-$O81)) -> 0 | CF81: =IF(SUM($BX81:$CB81)=0,0,BY81/SUM($BX81:$CB81)*(1-$O81)) -> 0 | CG81: =IF(SUM($BX81:$CB81)=0,0,BZ81/SUM($BX81:$CB81)*(1-$O81)) -> 0 | CH81: =IF(SUM($BX81:$CB81)=0,0,CA81/SUM($BX81:$CB81)*(1-$O81)) -> 0 | CI81: =IF(SUM($BX81:$CB81)=0,0,CB81/SUM($BX81:$CB81)*(1-$O81)) -> 0 | CJ81: =$O81+SUM(CC81:CI81) -> 0 | CL81: =IF($K81*CC81<=0,,$K81*CC81) -> 0 | CM81: =IF($K81*CD81<=0,,$K81*CD81) -> 0 | CN81: =IF($K81*CE81<=0,,$K81*CE81) -> 0 | CO81: =IF($K81*CF81<=0,,$K81*CF81) -> 0 | CP81: =IF($K81*CG81<=0,,$K81*CG81) -> 0 | CQ81: =IF($K81*CH81<=0,,$K81*CH81) -> 0 | CR81: =IF($K81*CI81<=0,,$K81*CI81) -> 0 | CT81: =$BE81*CL81 -> 0 | CU81: =$BE81*CM81 -> 0 | CV81: =$BE81*CN81 -> 0 | CW81: =$BE81*CO81 -> 0 | CX81: =$BE81*CP81 -> 0 | CY81: =$BE81*CQ81 -> 0 | CZ81: =$BE81*CR81 -> 0 | DB81: =CL81-CT81 -> 0 | DC81: =CM81-CU81 -> 0 | DD81: =CN81-CV81 -> 0 | DE81: =CO81-CW81 -> 0 | DF81: =CP81-CX81 -> 0 | DG81: =CQ81-CY81 -> 0 | DH81: =CR81-CZ81 -> 0 | DJ81: =IF(Z81<=26,IF(AND(P81=0,Q81>0),0,IF(Q81>0,($K81*(1-$BE81))/25,0)),0) -> 0 | DK81: =IF(AA81<=26,IF(AND(Q81=0,R81>0),0,IF(R81>0,($K81*(1-$BE81))/25,0)),0) -> 0 | DL81: =IF(AB81<=26,IF(AND(R81=0,S81>0),0,IF(S81>0,($K81*(1-$BE81))/25,0)),0) -> 432 | DM81: =IF(AC81<=26,IF(AND(S81=0,T81>0),0,IF(T81>0,($K81*(1-$BE81))/25,0)),0) -> 432 | DN81: =IF(AD81<=26,IF(AND(T81=0,U81>0),0,IF(U81>0,($K81*(1-$BE81))/25,0)),0) -> 432 | DO81: =IF(AE81<=26,IF(AND(U81=0,V81>0),0,IF(V81>0,($K81*(1-$BE81))/25,0)),0) -> 432 | DP81: =IF(AF81<=26,IF(AND(V81=0,W81>0),0,IF(W81>0,($K81*(1-$BE81))/25,0)),0) -> 432 | DR81: =+IF(Z81>0,$K81*(1-$BE81)-SUM($DJ81:DJ81),DB81) -> 0 | DS81: =+IF(AA81>0,$K81*(1-$BE81)-SUM($DJ81:DK81),DC81) -> 10800 | DT81: =+IF(AB81>0,$K81*(1-$BE81)-SUM($DJ81:DL81),DD81) -> 10368 | DU81: =+IF(AC81>0,$K81*(1-$BE81)-SUM($DJ81:DM81),DE81) -> 9936 | DV81: =+IF(AD81>0,$K81*(1-$BE81)-SUM($DJ81:DN81),DF81) -> 9504 | DW81: =+IF(AE81>0,$K81*(1-$BE81)-SUM($DJ81:DO81),DG81) -> 9072 | DX81: =+IF(AF81>0,$K81*(1-$BE81)-SUM($DJ81:DP81),DH81) -> 8640 | DZ81: =DR81*(DZ$51)*(Q81/365) -> 0 | EA81: =DS81*(EA$51)*(R81/365) -> 810.73973 | EB81: =DT81*(EB$51)*(S81/365) -> 1036.8 | EC81: =DU81*(EC$51)*(T81/365) -> 993.6 | ED81: =DV81*(ED$51)*(U81/365) -> 950.4 | EE81: =DW81*(EE$51)*(V81/365) -> 907.2 | EF81: =DY81*(EF$51)*(W81/365) -> 0 | FM81: 0 | FN81: 0 | FO81: =IF(AA81<1,$K81*$O81,0) -> 0 | FV81: =IF($D81="BESS",IF(Z81<=$S$18,$S$13,$S$21),$N81) -> 3.05 | FW81: =IF($D81="BESS",IF(AA81<=$S$18,$S$13,$S$21),$N81) -> 3.05 | FX81: =IF($D81="BESS",IF(AB81<=$S$18,$S$13,$S$21),$N81) -> 3.05 | FY81: =IF($D81="BESS",IF(AC81<=$S$18,$S$13,$S$21),$N81) -> 3.05 | FZ81: =IF($D81="BESS",IF(AD81<=$S$18,$S$13,$S$21),$N81) -> 3.05 | GA81: =IF($D81="BESS",IF(AE81<=$S$18,$S$13,$S$21),$N81) -> 3.05 | GB81: =IF($D81="BESS",IF(AF81<=$S$18,$S$13,$S$21),$N81) -> 3.05
B82: =Key_New!D32 -> Gujarat | C82: =Key_New!B32 -> ACME Pokhran Solar Pvt Ltd | D82: =Key_New!E32 -> Wind | E82: =Key_New!C32 -> Operational | F82: =Key_New!F32 -> 50 | G82: =IF(NOT(ISNUMBER($H82)),"",IF($H82<=DATE(2026,3,31),$H82,EDATE($H82,-IF($D82="BESS",$S$19,$S$26)))) -> 45838 | H82: =Key_New!O32 -> 45838 | I82: =IF(MONTH(H82)<=3,YEAR(H82),YEAR(H82)+1) -> 2026 | J82: 65 | K82: =J82*F82 -> 3250 | L82: 0.12 | M82: 0.25 | N82: =Key_New!J32 -> 2.9 | O82: =IF(OR(NOT(ISNUMBER($G82)),NOT(ISNUMBER($H82)),$H82<=DATE(2026,3,31)),0,MIN(1,MAX(0,(DATE(2026,3,31)-$G82)/($H82-$G82)))*$S$23) -> 0 | P82: =IF(OR(ISERROR(P$49-$H82),(P$49-$H82)>=365),365,IF((P$49-$H82)<=0,0,P$49-$H82)) -> 0 | Q82: =IF(OR(ISERROR(Q$49-$H82),(Q$49-$H82)>=365),365,IF((Q$49-$H82)<=0,0,Q$49-$H82)) -> 0 | R82: =IF(OR(ISERROR(R$49-$H82),(R$49-$H82)>=365),365,IF((R$49-$H82)<=0,0,R$49-$H82)) -> 274 | S82: =IF(OR(ISERROR(S$49-$H82),(S$49-$H82)>=365),365,IF((S$49-$H82)<=0,0,S$49-$H82)) -> 365 | T82: =IF(OR(ISERROR(T$49-$H82),(T$49-$H82)>=365),365,IF((T$49-$H82)<=0,0,T$49-$H82)) -> 365 | U82: =IF(OR(ISERROR(U$49-$H82),(U$49-$H82)>=365),365,IF((U$49-$H82)<=0,0,U$49-$H82)) -> 365 | V82: =IF(OR(ISERROR(V$49-$H82),(V$49-$H82)>=365),365,IF((V$49-$H82)<=0,0,V$49-$H82)) -> 365 | W82: =IF(OR(ISERROR(W$49-$H82),(W$49-$H82)>=365),365,IF((W$49-$H82)<=0,0,W$49-$H82)) -> 365 | Y82: =IF(AND(O82=0,P82>0),1,IF(X82=0,0,X82+1)) -> 0 | Z82: =IF(AND(P82=0,Q82>0),1,IF(Y82=0,0,Y82+1)) -> 0 | AA82: =IF(AND(Q82=0,R82>0),1,IF(Z82=0,0,Z82+1)) -> 1 | AB82: =IF(AND(R82=0,S82>0),1,IF(AA82=0,0,AA82+1)) -> 2 | AC82: =IF(AND(S82=0,T82>0),1,IF(AB82=0,0,AB82+1)) -> 3 | AD82: =IF(AND(T82=0,U82>0),1,IF(AC82=0,0,AC82+1)) -> 4 | AE82: =IF(AND(U82=0,V82>0),1,IF(AD82=0,0,AD82+1)) -> 5 | AF82: =IF(AND(V82=0,W82>0),1,IF(AE82=0,0,AE82+1)) -> 6 | AH82: =IF(AND(P82<=0,Q82>0),$F82,IF(P82>0,$F82,0)) -> 0 | AI82: =IF(AND(Q82<=0,R82>0),$F82,IF(Q82>0,$F82,0)) -> 50 | AJ82: =IF(AND(R82<=0,S82>0),$F82,IF(R82>0,$F82,0)) -> 50 | AK82: =IF(AND(S82<=0,T82>0),$F82,IF(S82>0,$F82,0)) -> 50 | AL82: =IF(AND(T82<=0,U82>0),$F82,IF(T82>0,$F82,0)) -> 50 | AM82: =IF(AND(U82<=0,V82>0),$F82,IF(U82>0,$F82,0)) -> 50 | AN82: =IF(AND(V82<=0,W82>0),$F82,IF(V82>0,$F82,0)) -> 50 | AP82: 0.35 | AQ82: 0.35 | AR82: 0.35 | AS82: 0.35 | AT82: 0.35 | AU82: 0.35 | AV82: 0.35 | AX82: =$F82*8.766*AP82*(Q82/365) -> 0 | AY82: =$F82*8.766*AQ82*(R82/365) -> 115.15882 | AZ82: =$F82*8.766*AR82*(S82/365) -> 153.405 | BA82: =$F82*8.766*AS82*(T82/365) -> 153.405 | BB82: =$F82*8.766*AT82*(U82/365) -> 153.405 | BC82: =$F82*8.766*AU82*(V82/365) -> 153.405 | BD82: =$F82*8.766*AV82*(W82/365) -> 153.405 | BE82: 0.2 | BF82: =$BE82*$K82*(Q82/365)*($L82/(1-$M82)) -> 0 | BG82: =$BE82*$K82*(R82/365)*($L82/(1-$M82)) -> 78.071233 | BH82: =$BE82*$K82*(S82/365)*($L82/(1-$M82)) -> 104 | BI82: =$BE82*$K82*(T82/365)*($L82/(1-$M82)) -> 104 | BJ82: =$BE82*$K82*(U82/365)*($L82/(1-$M82)) -> 104 | BK82: =$BE82*$K82*(V82/365)*($L82/(1-$M82)) -> 104 | BL82: =$BE82*$K82*(W82/365)*($L82/(1-$M82)) -> 104 | BM82: 0.04 | BN82: =$BM82*$K82*(Q82/365) -> 0 | BO82: =($BM82*$K82*(R82/365)) -> 97.589041 | BP82: =$BM82*$K82*(S82/365) -> 130 | BQ82: =$BM82*$K82*(T82/365) -> 130 | BR82: =$BM82*$K82*(U82/365) -> 130 | BS82: =$BM82*$K82*(V82/365) -> 130 | BT82: =$BM82*$K82*(W82/365) -> 130 | CC82: 0 | CD82: 0 | CE82: =IF(SUM($BX82:$CB82)=0,0,BX82/SUM($BX82:$CB82)*(1-$O82)) -> 0 | CF82: =IF(SUM($BX82:$CB82)=0,0,BY82/SUM($BX82:$CB82)*(1-$O82)) -> 0 | CG82: =IF(SUM($BX82:$CB82)=0,0,BZ82/SUM($BX82:$CB82)*(1-$O82)) -> 0 | CH82: =IF(SUM($BX82:$CB82)=0,0,CA82/SUM($BX82:$CB82)*(1-$O82)) -> 0 | CI82: =IF(SUM($BX82:$CB82)=0,0,CB82/SUM($BX82:$CB82)*(1-$O82)) -> 0 | CJ82: =$O82+SUM(CC82:CI82) -> 0 | CL82: =IF($K82*CC82<=0,,$K82*CC82) -> 0 | CM82: =IF($K82*CD82<=0,,$K82*CD82) -> 0 | CN82: =IF($K82*CE82<=0,,$K82*CE82) -> 0 | CO82: =IF($K82*CF82<=0,,$K82*CF82) -> 0 | CP82: =IF($K82*CG82<=0,,$K82*CG82) -> 0 | CQ82: =IF($K82*CH82<=0,,$K82*CH82) -> 0 | CR82: =IF($K82*CI82<=0,,$K82*CI82) -> 0 | CT82: =$BE82*CL82 -> 0 | CU82: =$BE82*CM82 -> 0 | CV82: =$BE82*CN82 -> 0 | CW82: =$BE82*CO82 -> 0 | CX82: =$BE82*CP82 -> 0 | CY82: =$BE82*CQ82 -> 0 | CZ82: =$BE82*CR82 -> 0 | DB82: =CL82-CT82 -> 0 | DC82: =CM82-CU82 -> 0 | DD82: =CN82-CV82 -> 0 | DE82: =CO82-CW82 -> 0 | DF82: =CP82-CX82 -> 0 | DG82: =CQ82-CY82 -> 0 | DH82: =CR82-CZ82 -> 0 | DJ82: =IF(Z82<=26,IF(AND(P82=0,Q82>0),0,IF(Q82>0,($K82*(1-$BE82))/25,0)),0) -> 0 | DK82: =IF(AA82<=26,IF(AND(Q82=0,R82>0),0,IF(R82>0,($K82*(1-$BE82))/25,0)),0) -> 0 | DL82: =IF(AB82<=26,IF(AND(R82=0,S82>0),0,IF(S82>0,($K82*(1-$BE82))/25,0)),0) -> 104 | DM82: =IF(AC82<=26,IF(AND(S82=0,T82>0),0,IF(T82>0,($K82*(1-$BE82))/25,0)),0) -> 104 | DN82: =IF(AD82<=26,IF(AND(T82=0,U82>0),0,IF(U82>0,($K82*(1-$BE82))/25,0)),0) -> 104 | DO82: =IF(AE82<=26,IF(AND(U82=0,V82>0),0,IF(V82>0,($K82*(1-$BE82))/25,0)),0) -> 104 | DP82: =IF(AF82<=26,IF(AND(V82=0,W82>0),0,IF(W82>0,($K82*(1-$BE82))/25,0)),0) -> 104 | DR82: =+IF(Z82>0,$K82*(1-$BE82)-SUM($DJ82:DJ82),DB82) -> 0 | DS82: =+IF(AA82>0,$K82*(1-$BE82)-SUM($DJ82:DK82),DC82) -> 2600 | DT82: =+IF(AB82>0,$K82*(1-$BE82)-SUM($DJ82:DL82),DD82) -> 2496 | DU82: =+IF(AC82>0,$K82*(1-$BE82)-SUM($DJ82:DM82),DE82) -> 2392 | DV82: =+IF(AD82>0,$K82*(1-$BE82)-SUM($DJ82:DN82),DF82) -> 2288 | DW82: =+IF(AE82>0,$K82*(1-$BE82)-SUM($DJ82:DO82),DG82) -> 2184 | DX82: =+IF(AF82>0,$K82*(1-$BE82)-SUM($DJ82:DP82),DH82) -> 2080 | DZ82: =DR82*(DZ$51)*(Q82/365) -> 0 | EA82: =DS82*(EA$51)*(R82/365) -> 195.17808 | EB82: =DT82*(EB$51)*(S82/365) -> 249.6 | EC82: =DU82*(EC$51)*(T82/365) -> 239.2 | ED82: =DV82*(ED$51)*(U82/365) -> 228.8 | EE82: =DW82*(EE$51)*(V82/365) -> 218.4 | EF82: =DY82*(EF$51)*(W82/365) -> 0 | FM82: 0 | FN82: 0 | FO82: =IF(AA82<1,$K82*$O82,0) -> 0 | FV82: =IF($D82="BESS",IF(Z82<=$S$18,$S$13,$S$21),$N82) -> 2.9 | FW82: =IF($D82="BESS",IF(AA82<=$S$18,$S$13,$S$21),$N82) -> 2.9 | FX82: =IF($D82="BESS",IF(AB82<=$S$18,$S$13,$S$21),$N82) -> 2.9 | FY82: =IF($D82="BESS",IF(AC82<=$S$18,$S$13,$S$21),$N82) -> 2.9 | FZ82: =IF($D82="BESS",IF(AD82<=$S$18,$S$13,$S$21),$N82) -> 2.9 | GA82: =IF($D82="BESS",IF(AE82<=$S$18,$S$13,$S$21),$N82) -> 2.9 | GB82: =IF($D82="BESS",IF(AF82<=$S$18,$S$13,$S$21),$N82) -> 2.9
B83: =Key_New!D33 -> Gujarat | C83: =Key_New!B33 -> ACME Eco Clean Energy Pvt Ltd (Ph I-II) | D83: =Key_New!E33 -> Wind | E83: =Key_New!C33 -> Operational | F83: =Key_New!F33 -> 72 | G83: =IF(NOT(ISNUMBER($H83)),"",IF($H83<=DATE(2026,3,31),$H83,EDATE($H83,-IF($D83="BESS",$S$19,$S$26)))) -> 46053 | H83: =Key_New!O33 -> 46053 | I83: =IF(MONTH(H83)<=3,YEAR(H83),YEAR(H83)+1) -> 2026 | J83: 65 | K83: =J83*F83 -> 4680 | L83: 0.12 | M83: 0.25 | N83: =Key_New!J33 -> 3.01 | O83: =IF(OR(NOT(ISNUMBER($G83)),NOT(ISNUMBER($H83)),$H83<=DATE(2026,3,31)),0,MIN(1,MAX(0,(DATE(2026,3,31)-$G83)/($H83-$G83)))*$S$23) -> 0 | P83: =IF(OR(ISERROR(P$49-$H83),(P$49-$H83)>=365),365,IF((P$49-$H83)<=0,0,P$49-$H83)) -> 0 | Q83: =IF(OR(ISERROR(Q$49-$H83),(Q$49-$H83)>=365),365,IF((Q$49-$H83)<=0,0,Q$49-$H83)) -> 0 | R83: =IF(OR(ISERROR(R$49-$H83),(R$49-$H83)>=365),365,IF((R$49-$H83)<=0,0,R$49-$H83)) -> 59 | S83: =IF(OR(ISERROR(S$49-$H83),(S$49-$H83)>=365),365,IF((S$49-$H83)<=0,0,S$49-$H83)) -> 365 | T83: =IF(OR(ISERROR(T$49-$H83),(T$49-$H83)>=365),365,IF((T$49-$H83)<=0,0,T$49-$H83)) -> 365 | U83: =IF(OR(ISERROR(U$49-$H83),(U$49-$H83)>=365),365,IF((U$49-$H83)<=0,0,U$49-$H83)) -> 365 | V83: =IF(OR(ISERROR(V$49-$H83),(V$49-$H83)>=365),365,IF((V$49-$H83)<=0,0,V$49-$H83)) -> 365 | W83: =IF(OR(ISERROR(W$49-$H83),(W$49-$H83)>=365),365,IF((W$49-$H83)<=0,0,W$49-$H83)) -> 365 | Y83: =IF(AND(O83=0,P83>0),1,IF(X83=0,0,X83+1)) -> 0 | Z83: =IF(AND(P83=0,Q83>0),1,IF(Y83=0,0,Y83+1)) -> 0 | AA83: =IF(AND(Q83=0,R83>0),1,IF(Z83=0,0,Z83+1)) -> 1 | AB83: =IF(AND(R83=0,S83>0),1,IF(AA83=0,0,AA83+1)) -> 2 | AC83: =IF(AND(S83=0,T83>0),1,IF(AB83=0,0,AB83+1)) -> 3 | AD83: =IF(AND(T83=0,U83>0),1,IF(AC83=0,0,AC83+1)) -> 4 | AE83: =IF(AND(U83=0,V83>0),1,IF(AD83=0,0,AD83+1)) -> 5 | AF83: =IF(AND(V83=0,W83>0),1,IF(AE83=0,0,AE83+1)) -> 6 | AH83: =IF(AND(P83<=0,Q83>0),$F83,IF(P83>0,$F83,0)) -> 0 | AI83: =IF(AND(Q83<=0,R83>0),$F83,IF(Q83>0,$F83,0)) -> 72 | AJ83: =IF(AND(R83<=0,S83>0),$F83,IF(R83>0,$F83,0)) -> 72 | AK83: =IF(AND(S83<=0,T83>0),$F83,IF(S83>0,$F83,0)) -> 72 | AL83: =IF(AND(T83<=0,U83>0),$F83,IF(T83>0,$F83,0)) -> 72 | AM83: =IF(AND(U83<=0,V83>0),$F83,IF(U83>0,$F83,0)) -> 72 | AN83: =IF(AND(V83<=0,W83>0),$F83,IF(V83>0,$F83,0)) -> 72 | AP83: 0.35 | AQ83: 0.35 | AR83: 0.35 | AS83: 0.35 | AT83: 0.35 | AU83: 0.35 | AV83: 0.35 | AX83: =$F83*8.766*AP83*(Q83/365) -> 0 | AY83: =$F83*8.766*AQ83*(R83/365) -> 35.707641 | AZ83: =$F83*8.766*AR83*(S83/365) -> 220.9032 | BA83: =$F83*8.766*AS83*(T83/365) -> 220.9032 | BB83: =$F83*8.766*AT83*(U83/365) -> 220.9032 | BC83: =$F83*8.766*AU83*(V83/365) -> 220.9032 | BD83: =$F83*8.766*AV83*(W83/365) -> 220.9032 | BE83: 0.2 | BF83: =$BE83*$K83*(Q83/365)*($L83/(1-$M83)) -> 0 | BG83: =$BE83*$K83*(R83/365)*($L83/(1-$M83)) -> 24.207781 | BH83: =$BE83*$K83*(S83/365)*($L83/(1-$M83)) -> 149.76 | BI83: =$BE83*$K83*(T83/365)*($L83/(1-$M83)) -> 149.76 | BJ83: =$BE83*$K83*(U83/365)*($L83/(1-$M83)) -> 149.76 | BK83: =$BE83*$K83*(V83/365)*($L83/(1-$M83)) -> 149.76 | BL83: =$BE83*$K83*(W83/365)*($L83/(1-$M83)) -> 149.76 | BM83: 0.04 | BN83: =$BM83*$K83*(Q83/365) -> 0 | BO83: =($BM83*$K83*(R83/365)) -> 30.259726 | BP83: =$BM83*$K83*(S83/365) -> 187.2 | BQ83: =$BM83*$K83*(T83/365) -> 187.2 | BR83: =$BM83*$K83*(U83/365) -> 187.2 | BS83: =$BM83*$K83*(V83/365) -> 187.2 | BT83: =$BM83*$K83*(W83/365) -> 187.2 | CC83: 0 | CD83: 0 | CE83: =IF(SUM($BX83:$CB83)=0,0,BX83/SUM($BX83:$CB83)*(1-$O83)) -> 0 | CF83: =IF(SUM($BX83:$CB83)=0,0,BY83/SUM($BX83:$CB83)*(1-$O83)) -> 0 | CG83: =IF(SUM($BX83:$CB83)=0,0,BZ83/SUM($BX83:$CB83)*(1-$O83)) -> 0 | CH83: =IF(SUM($BX83:$CB83)=0,0,CA83/SUM($BX83:$CB83)*(1-$O83)) -> 0 | CI83: =IF(SUM($BX83:$CB83)=0,0,CB83/SUM($BX83:$CB83)*(1-$O83)) -> 0 | CJ83: =$O83+SUM(CC83:CI83) -> 0 | CL83: =IF($K83*CC83<=0,,$K83*CC83) -> 0 | CM83: =IF($K83*CD83<=0,,$K83*CD83) -> 0 | CN83: =IF($K83*CE83<=0,,$K83*CE83) -> 0 | CO83: =IF($K83*CF83<=0,,$K83*CF83) -> 0 | CP83: =IF($K83*CG83<=0,,$K83*CG83) -> 0 | CQ83: =IF($K83*CH83<=0,,$K83*CH83) -> 0 | CR83: =IF($K83*CI83<=0,,$K83*CI83) -> 0 | CT83: =$BE83*CL83 -> 0 | CU83: =$BE83*CM83 -> 0 | CV83: =$BE83*CN83 -> 0 | CW83: =$BE83*CO83 -> 0 | CX83: =$BE83*CP83 -> 0 | CY83: =$BE83*CQ83 -> 0 | CZ83: =$BE83*CR83 -> 0 | DB83: =CL83-CT83 -> 0 | DC83: =CM83-CU83 -> 0 | DD83: =CN83-CV83 -> 0 | DE83: =CO83-CW83 -> 0 | DF83: =CP83-CX83 -> 0 | DG83: =CQ83-CY83 -> 0 | DH83: =CR83-CZ83 -> 0 | DJ83: =IF(Z83<=26,IF(AND(P83=0,Q83>0),0,IF(Q83>0,($K83*(1-$BE83))/25,0)),0) -> 0 | DK83: =IF(AA83<=26,IF(AND(Q83=0,R83>0),0,IF(R83>0,($K83*(1-$BE83))/25,0)),0) -> 0 | DL83: =IF(AB83<=26,IF(AND(R83=0,S83>0),0,IF(S83>0,($K83*(1-$BE83))/25,0)),0) -> 149.76 | DM83: =IF(AC83<=26,IF(AND(S83=0,T83>0),0,IF(T83>0,($K83*(1-$BE83))/25,0)),0) -> 149.76 | DN83: =IF(AD83<=26,IF(AND(T83=0,U83>0),0,IF(U83>0,($K83*(1-$BE83))/25,0)),0) -> 149.76 | DO83: =IF(AE83<=26,IF(AND(U83=0,V83>0),0,IF(V83>0,($K83*(1-$BE83))/25,0)),0) -> 149.76 | DP83: =IF(AF83<=26,IF(AND(V83=0,W83>0),0,IF(W83>0,($K83*(1-$BE83))/25,0)),0) -> 149.76 | DR83: =+IF(Z83>0,$K83*(1-$BE83)-SUM($DJ83:DJ83),DB83) -> 0 | DS83: =+IF(AA83>0,$K83*(1-$BE83)-SUM($DJ83:DK83),DC83) -> 3744 | DT83: =+IF(AB83>0,$K83*(1-$BE83)-SUM($DJ83:DL83),DD83) -> 3594.24 | DU83: =+IF(AC83>0,$K83*(1-$BE83)-SUM($DJ83:DM83),DE83) -> 3444.48 | DV83: =+IF(AD83>0,$K83*(1-$BE83)-SUM($DJ83:DN83),DF83) -> 3294.72 | DW83: =+IF(AE83>0,$K83*(1-$BE83)-SUM($DJ83:DO83),DG83) -> 3144.96 | DX83: =+IF(AF83>0,$K83*(1-$BE83)-SUM($DJ83:DP83),DH83) -> 2995.2 | DZ83: =DR83*(DZ$51)*(Q83/365) -> 0 | EA83: =DS83*(EA$51)*(R83/365) -> 60.519452 | EB83: =DT83*(EB$51)*(S83/365) -> 359.424 | EC83: =DU83*(EC$51)*(T83/365) -> 344.448 | ED83: =DV83*(ED$51)*(U83/365) -> 329.472 | EE83: =DW83*(EE$51)*(V83/365) -> 314.496 | EF83: =DY83*(EF$51)*(W83/365) -> 0 | FM83: 0 | FN83: 0 | FO83: =IF(AA83<1,$K83*$O83,0) -> 0 | FV83: =IF($D83="BESS",IF(Z83<=$S$18,$S$13,$S$21),$N83) -> 3.01 | FW83: =IF($D83="BESS",IF(AA83<=$S$18,$S$13,$S$21),$N83) -> 3.01 | FX83: =IF($D83="BESS",IF(AB83<=$S$18,$S$13,$S$21),$N83) -> 3.01 | FY83: =IF($D83="BESS",IF(AC83<=$S$18,$S$13,$S$21),$N83) -> 3.01 | FZ83: =IF($D83="BESS",IF(AD83<=$S$18,$S$13,$S$21),$N83) -> 3.01 | GA83: =IF($D83="BESS",IF(AE83<=$S$18,$S$13,$S$21),$N83) -> 3.01 | GB83: =IF($D83="BESS",IF(AF83<=$S$18,$S$13,$S$21),$N83) -> 3.01
B84: =Key_New!D34 -> Gujarat | C84: =Key_New!B34 -> ACME Eco Clean Energy Pvt Ltd (Ph III) | D84: =Key_New!E34 -> Wind | E84: =Key_New!C34 -> Operational | F84: =Key_New!F34 -> 20 | G84: =IF(NOT(ISNUMBER($H84)),"",IF($H84<=DATE(2026,3,31),$H84,EDATE($H84,-IF($D84="BESS",$S$19,$S$26)))) -> 46112 | H84: =Key_New!O34 -> 46112 | I84: =IF(MONTH(H84)<=3,YEAR(H84),YEAR(H84)+1) -> 2026 | J84: 65 | K84: =J84*F84 -> 1300 | L84: 0.12 | M84: 0.25 | N84: =Key_New!J34 -> 3.01 | O84: =IF(OR(NOT(ISNUMBER($G84)),NOT(ISNUMBER($H84)),$H84<=DATE(2026,3,31)),0,MIN(1,MAX(0,(DATE(2026,3,31)-$G84)/($H84-$G84)))*$S$23) -> 0 | P84: =IF(OR(ISERROR(P$49-$H84),(P$49-$H84)>=365),365,IF((P$49-$H84)<=0,0,P$49-$H84)) -> 0 | Q84: =IF(OR(ISERROR(Q$49-$H84),(Q$49-$H84)>=365),365,IF((Q$49-$H84)<=0,0,Q$49-$H84)) -> 0 | R84: =IF(OR(ISERROR(R$49-$H84),(R$49-$H84)>=365),365,IF((R$49-$H84)<=0,0,R$49-$H84)) -> 0 | S84: =IF(OR(ISERROR(S$49-$H84),(S$49-$H84)>=365),365,IF((S$49-$H84)<=0,0,S$49-$H84)) -> 365 | T84: =IF(OR(ISERROR(T$49-$H84),(T$49-$H84)>=365),365,IF((T$49-$H84)<=0,0,T$49-$H84)) -> 365 | U84: =IF(OR(ISERROR(U$49-$H84),(U$49-$H84)>=365),365,IF((U$49-$H84)<=0,0,U$49-$H84)) -> 365 | V84: =IF(OR(ISERROR(V$49-$H84),(V$49-$H84)>=365),365,IF((V$49-$H84)<=0,0,V$49-$H84)) -> 365 | W84: =IF(OR(ISERROR(W$49-$H84),(W$49-$H84)>=365),365,IF((W$49-$H84)<=0,0,W$49-$H84)) -> 365 | Y84: =IF(AND(O84=0,P84>0),1,IF(X84=0,0,X84+1)) -> 0 | Z84: =IF(AND(P84=0,Q84>0),1,IF(Y84=0,0,Y84+1)) -> 0 | AA84: =IF(AND(Q84=0,R84>0),1,IF(Z84=0,0,Z84+1)) -> 0 | AB84: =IF(AND(R84=0,S84>0),1,IF(AA84=0,0,AA84+1)) -> 1 | AC84: =IF(AND(S84=0,T84>0),1,IF(AB84=0,0,AB84+1)) -> 2 | AD84: =IF(AND(T84=0,U84>0),1,IF(AC84=0,0,AC84+1)) -> 3 | AE84: =IF(AND(U84=0,V84>0),1,IF(AD84=0,0,AD84+1)) -> 4 | AF84: =IF(AND(V84=0,W84>0),1,IF(AE84=0,0,AE84+1)) -> 5 | AH84: =IF(AND(P84<=0,Q84>0),$F84,IF(P84>0,$F84,0)) -> 0 | AI84: =IF(AND(Q84<=0,R84>0),$F84,IF(Q84>0,$F84,0)) -> 0 | AJ84: =IF(AND(R84<=0,S84>0),$F84,IF(R84>0,$F84,0)) -> 20 | AK84: =IF(AND(S84<=0,T84>0),$F84,IF(S84>0,$F84,0)) -> 20 | AL84: =IF(AND(T84<=0,U84>0),$F84,IF(T84>0,$F84,0)) -> 20 | AM84: =IF(AND(U84<=0,V84>0),$F84,IF(U84>0,$F84,0)) -> 20 | AN84: =IF(AND(V84<=0,W84>0),$F84,IF(V84>0,$F84,0)) -> 20 | AP84: 0.35 | AQ84: 0.35 | AR84: 0.35 | AS84: 0.35 | AT84: 0.35 | AU84: 0.35 | AV84: 0.35 | AX84: =$F84*8.766*AP84*(Q84/365) -> 0 | AY84: =$F84*8.766*AQ84*(R84/365) -> 0 | AZ84: =$F84*8.766*AR84*(S84/365) -> 61.362 | BA84: =$F84*8.766*AS84*(T84/365) -> 61.362 | BB84: =$F84*8.766*AT84*(U84/365) -> 61.362 | BC84: =$F84*8.766*AU84*(V84/365) -> 61.362 | BD84: =$F84*8.766*AV84*(W84/365) -> 61.362 | BE84: 0.2 | BF84: =$BE84*$K84*(Q84/365)*($L84/(1-$M84)) -> 0 | BG84: =$BE84*$K84*(R84/365)*($L84/(1-$M84)) -> 0 | BH84: =$BE84*$K84*(S84/365)*($L84/(1-$M84)) -> 41.6 | BI84: =$BE84*$K84*(T84/365)*($L84/(1-$M84)) -> 41.6 | BJ84: =$BE84*$K84*(U84/365)*($L84/(1-$M84)) -> 41.6 | BK84: =$BE84*$K84*(V84/365)*($L84/(1-$M84)) -> 41.6 | BL84: =$BE84*$K84*(W84/365)*($L84/(1-$M84)) -> 41.6 | BM84: 0.04 | BN84: =$BM84*$K84*(Q84/365) -> 0 | BO84: =($BM84*$K84*(R84/365)) -> 0 | BP84: =$BM84*$K84*(S84/365) -> 52 | BQ84: =$BM84*$K84*(T84/365) -> 52 | BR84: =$BM84*$K84*(U84/365) -> 52 | BS84: =$BM84*$K84*(V84/365) -> 52 | BT84: =$BM84*$K84*(W84/365) -> 52 | CC84: 0 | CD84: 0 | CE84: =IF(SUM($BX84:$CB84)=0,0,BX84/SUM($BX84:$CB84)*(1-$O84)) -> 0 | CF84: =IF(SUM($BX84:$CB84)=0,0,BY84/SUM($BX84:$CB84)*(1-$O84)) -> 0 | CG84: =IF(SUM($BX84:$CB84)=0,0,BZ84/SUM($BX84:$CB84)*(1-$O84)) -> 0 | CH84: =IF(SUM($BX84:$CB84)=0,0,CA84/SUM($BX84:$CB84)*(1-$O84)) -> 0 | CI84: =IF(SUM($BX84:$CB84)=0,0,CB84/SUM($BX84:$CB84)*(1-$O84)) -> 0 | CJ84: =$O84+SUM(CC84:CI84) -> 0 | CL84: =IF($K84*CC84<=0,,$K84*CC84) -> 0 | CM84: =IF($K84*CD84<=0,,$K84*CD84) -> 0 | CN84: =IF($K84*CE84<=0,,$K84*CE84) -> 0 | CO84: =IF($K84*CF84<=0,,$K84*CF84) -> 0 | CP84: =IF($K84*CG84<=0,,$K84*CG84) -> 0 | CQ84: =IF($K84*CH84<=0,,$K84*CH84) -> 0 | CR84: =IF($K84*CI84<=0,,$K84*CI84) -> 0 | CT84: =$BE84*CL84 -> 0 | CU84: =$BE84*CM84 -> 0 | CV84: =$BE84*CN84 -> 0 | CW84: =$BE84*CO84 -> 0 | CX84: =$BE84*CP84 -> 0 | CY84: =$BE84*CQ84 -> 0 | CZ84: =$BE84*CR84 -> 0 | DB84: =CL84-CT84 -> 0 | DC84: =CM84-CU84 -> 0 | DD84: =CN84-CV84 -> 0 | DE84: =CO84-CW84 -> 0 | DF84: =CP84-CX84 -> 0 | DG84: =CQ84-CY84 -> 0 | DH84: =CR84-CZ84 -> 0 | DJ84: =IF(Z84<=26,IF(AND(P84=0,Q84>0),0,IF(Q84>0,($K84*(1-$BE84))/25,0)),0) -> 0 | DK84: =IF(AA84<=26,IF(AND(Q84=0,R84>0),0,IF(R84>0,($K84*(1-$BE84))/25,0)),0) -> 0 | DL84: =IF(AB84<=26,IF(AND(R84=0,S84>0),0,IF(S84>0,($K84*(1-$BE84))/25,0)),0) -> 0 | DM84: =IF(AC84<=26,IF(AND(S84=0,T84>0),0,IF(T84>0,($K84*(1-$BE84))/25,0)),0) -> 41.6 | DN84: =IF(AD84<=26,IF(AND(T84=0,U84>0),0,IF(U84>0,($K84*(1-$BE84))/25,0)),0) -> 41.6 | DO84: =IF(AE84<=26,IF(AND(U84=0,V84>0),0,IF(V84>0,($K84*(1-$BE84))/25,0)),0) -> 41.6 | DP84: =IF(AF84<=26,IF(AND(V84=0,W84>0),0,IF(W84>0,($K84*(1-$BE84))/25,0)),0) -> 41.6 | DR84: =+IF(Z84>0,$K84*(1-$BE84)-SUM($DJ84:DJ84),DB84) -> 0 | DS84: =+IF(AA84>0,$K84*(1-$BE84)-SUM($DJ84:DK84),DC84) -> 0 | DT84: =+IF(AB84>0,$K84*(1-$BE84)-SUM($DJ84:DL84),DD84) -> 1040 | DU84: =+IF(AC84>0,$K84*(1-$BE84)-SUM($DJ84:DM84),DE84) -> 998.4 | DV84: =+IF(AD84>0,$K84*(1-$BE84)-SUM($DJ84:DN84),DF84) -> 956.8 | DW84: =+IF(AE84>0,$K84*(1-$BE84)-SUM($DJ84:DO84),DG84) -> 915.2 | DX84: =+IF(AF84>0,$K84*(1-$BE84)-SUM($DJ84:DP84),DH84) -> 873.6 | DZ84: =DR84*(DZ$51)*(Q84/365) -> 0 | EA84: =DS84*(EA$51)*(R84/365) -> 0 | EB84: =DT84*(EB$51)*(S84/365) -> 104 | EC84: =DU84*(EC$51)*(T84/365) -> 99.84 | ED84: =DV84*(ED$51)*(U84/365) -> 95.68 | EE84: =DW84*(EE$51)*(V84/365) -> 91.52 | EF84: =DY84*(EF$51)*(W84/365) -> 0 | FM84: 0 | FN84: 0 | FO84: =IF(AA84<1,$K84*$O84,0) -> 0 | FV84: =IF($D84="BESS",IF(Z84<=$S$18,$S$13,$S$21),$N84) -> 3.01 | FW84: =IF($D84="BESS",IF(AA84<=$S$18,$S$13,$S$21),$N84) -> 3.01 | FX84: =IF($D84="BESS",IF(AB84<=$S$18,$S$13,$S$21),$N84) -> 3.01 | FY84: =IF($D84="BESS",IF(AC84<=$S$18,$S$13,$S$21),$N84) -> 3.01 | FZ84: =IF($D84="BESS",IF(AD84<=$S$18,$S$13,$S$21),$N84) -> 3.01 | GA84: =IF($D84="BESS",IF(AE84<=$S$18,$S$13,$S$21),$N84) -> 3.01 | GB84: =IF($D84="BESS",IF(AF84<=$S$18,$S$13,$S$21),$N84) -> 3.01
B85: =Key_New!D35 -> Gujarat | C85: =Key_New!B35 -> ACME Eco Clean Energy Pvt Ltd (Ph IV) | D85: =Key_New!E35 -> Wind | E85: =Key_New!C35 -> Operational | F85: =Key_New!F35 -> 8 | G85: =IF(NOT(ISNUMBER($H85)),"",IF($H85<=DATE(2026,3,31),$H85,EDATE($H85,-IF($D85="BESS",$S$19,$S$26)))) -> 45412 | H85: =Key_New!O35 -> 46142 | I85: =IF(MONTH(H85)<=3,YEAR(H85),YEAR(H85)+1) -> 2027 | J85: 65 | K85: =J85*F85 -> 520 | L85: 0.12 | M85: 0.25 | N85: =Key_New!J35 -> 3.01 | O85: =IF(OR(NOT(ISNUMBER($G85)),NOT(ISNUMBER($H85)),$H85<=DATE(2026,3,31)),0,MIN(1,MAX(0,(DATE(2026,3,31)-$G85)/($H85-$G85)))*$S$23) -> 0.3940137 | U85: =IF(OR(ISERROR(U$49-$H85),(U$49-$H85)>=365),365,IF((U$49-$H85)<=0,0,U$49-$H85)) -> 365 | V85: =IF(OR(ISERROR(V$49-$H85),(V$49-$H85)>=365),365,IF((V$49-$H85)<=0,0,V$49-$H85)) -> 365 | AP85: 0.35 | AQ85: 0.35 | AR85: 0.35 | AS85: 0.35 | AT85: 0.35 | AU85: 0.35 | AV85: 0.35 | CC85: 0 | CD85: 0 | CE85: =1-$O85 -> 0.6059863 | CF85: =IF(SUM($BX85:$CB85)=0,0,BY85/SUM($BX85:$CB85)*(1-$O85)) -> 0 | CG85: =IF(SUM($BX85:$CB85)=0,0,BZ85/SUM($BX85:$CB85)*(1-$O85)) -> 0 | CH85: =IF(SUM($BX85:$CB85)=0,0,CA85/SUM($BX85:$CB85)*(1-$O85)) -> 0 | CI85: =IF(SUM($BX85:$CB85)=0,0,CB85/SUM($BX85:$CB85)*(1-$O85)) -> 0 | CJ85: =$O85+SUM(CC85:CI85) -> 1 | CL85: =IF($K85*CC85<=0,,$K85*CC85) -> 0 | CM85: =IF($K85*CD85<=0,,$K85*CD85) -> 0 | CN85: =IF($K85*CE85<=0,,$K85*CE85) -> 315.11288 | CO85: =IF($K85*CF85<=0,,$K85*CF85) -> 0 | CP85: =IF($K85*CG85<=0,,$K85*CG85) -> 0 | CQ85: =IF($K85*CH85<=0,,$K85*CH85) -> 0 | CR85: =IF($K85*CI85<=0,,$K85*CI85) -> 0 | FM85: 0 | FN85: 0 | FO85: =IF(AA85<1,$K85*$O85,0) -> 204.88712 | FV85: =IF($D85="BESS",IF(Z85<=$S$18,$S$13,$S$21),$N85) -> 3.01 | FW85: =IF($D85="BESS",IF(AA85<=$S$18,$S$13,$S$21),$N85) -> 3.01 | FX85: =IF($D85="BESS",IF(AB85<=$S$18,$S$13,$S$21),$N85) -> 3.01 | FY85: =IF($D85="BESS",IF(AC85<=$S$18,$S$13,$S$21),$N85) -> 3.01 | FZ85: =IF($D85="BESS",IF(AD85<=$S$18,$S$13,$S$21),$N85) -> 3.01 | GA85: =IF($D85="BESS",IF(AE85<=$S$18,$S$13,$S$21),$N85) -> 3.01 | GB85: =IF($D85="BESS",IF(AF85<=$S$18,$S$13,$S$21),$N85) -> 3.01
B86: Under Construction | G86: =IF(NOT(ISNUMBER($H86)),"",IF($H86<=DATE(2026,3,31),$H86,EDATE($H86,-IF($D86="BESS",$S$19,$S$26)))) | O86: =IF(OR(NOT(ISNUMBER($G86)),NOT(ISNUMBER($H86)),$H86<=DATE(2026,3,31)),0,MIN(1,MAX(0,(DATE(2026,3,31)-$G86)/($H86-$G86)))*$S$23) -> 0 | AP86: 0 | AQ86: 0 | AR86: 0 | AS86: 0 | AT86: 0 | AU86: 0 | AV86: 0 | CC86: 0 | CD86: 0 | CE86: =IF(SUM($BX86:$CB86)=0,0,BX86/SUM($BX86:$CB86)*(1-$O86)) -> 0 | CF86: =IF(SUM($BX86:$CB86)=0,0,BY86/SUM($BX86:$CB86)*(1-$O86)) -> 0 | CG86: =IF(SUM($BX86:$CB86)=0,0,BZ86/SUM($BX86:$CB86)*(1-$O86)) -> 0 | CH86: =IF(SUM($BX86:$CB86)=0,0,CA86/SUM($BX86:$CB86)*(1-$O86)) -> 0 | CI86: =IF(SUM($BX86:$CB86)=0,0,CB86/SUM($BX86:$CB86)*(1-$O86)) -> 0 | CJ86: =$O86+SUM(CC86:CI86) -> 0 | CL86: =IF($K86*CC86<=0,,$K86*CC86) -> 0 | CM86: =IF($K86*CD86<=0,,$K86*CD86) -> 0 | CN86: =IF($K86*CE86<=0,,$K86*CE86) -> 0 | CO86: =IF($K86*CF86<=0,,$K86*CF86) -> 0 | CP86: =IF($K86*CG86<=0,,$K86*CG86) -> 0 | CQ86: =IF($K86*CH86<=0,,$K86*CH86) -> 0 | CR86: =IF($K86*CI86<=0,,$K86*CI86) -> 0 | FM86: 0 | FN86: 0 | FO86: =IF(AA86<1,$K86*$O86,0) -> 0 | FV86: =IF($D86="BESS",IF(Z86<=$S$18,$S$13,$S$21),$N86) -> 0 | FW86: =IF($D86="BESS",IF(AA86<=$S$18,$S$13,$S$21),$N86) -> 0 | FX86: =IF($D86="BESS",IF(AB86<=$S$18,$S$13,$S$21),$N86) -> 0 | FY86: =IF($D86="BESS",IF(AC86<=$S$18,$S$13,$S$21),$N86) -> 0 | FZ86: =IF($D86="BESS",IF(AD86<=$S$18,$S$13,$S$21),$N86) -> 0 | GA86: =IF($D86="BESS",IF(AE86<=$S$18,$S$13,$S$21),$N86) -> 0 | GB86: =IF($D86="BESS",IF(AF86<=$S$18,$S$13,$S$21),$N86) -> 0
