Workbook

Sheet P&L
Z1: <<Do not Delete this>>
A2: P&L Statement (Rs. crore) | B2: FY05 | C2: FY06 | D2: FY07 | E2: FY08 | F2: FY09 | G2: FY10 | H2: FY11 | I2: FY12 | J2: FY13 | K2: FY14 | L2: FY15 | M2: FY16 | N2: FY17 | O2: FY18 | P2: FY19 | Q2: FY20 | R2: FY21 | S2: FY22 | T2: FY23 | U2: FY24 | V2: FY25 | W2: FY26 | X2: FY27E | Y2: FY28E | Z2: FY29E | AA2: FY30E
A3: Net Sales | B3: 7.792 | C3: 10.3419 | D3: 27.3333 | E3: 46.099 | F3: 68.8106 | G3: 20.1678 | H3: 64.1328 | I3: 45.3417 | J3: 55.3772 | K3: 121.8294 | L3: 140.833 | M3: 77.6676 | N3: 124.3162 | O3: 222.2229 | P3: 193.8552 | Q3: 273.1538 | R3: 228.7898 | S3: 260.4711 | T3: 109.9514 | U3: 305.0648 | V3: 465.0381 | W3: 791.0474
A4: Growth, % | C4: =+C$3/B$3-1 -> 0.32724589 | D4: =+D$3/C$3-1 -> 1.642967 | E4: =+E$3/D$3-1 -> 0.68655084 | F4: =+F$3/E$3-1 -> 0.49267012 | G4: =+G$3/F$3-1 -> -0.70690853 | H4: =+H$3/G$3-1 -> 2.1799601 | I4: =+I$3/H$3-1 -> -0.29300296 | J4: =+J$3/I$3-1 -> 0.22133048 | ... W4: =+W$3/V$3-1 -> 0.70103783
A5: EXPENDITURE
A6: (Increase)/Decrease in Stock | B6: -0.052 | C6: 0.145 | D6: -0.0882 | E6: -0.0097 | F6: 0 | G6: 0 | H6: 0 | I6: 0 | J6: 0 | K6: 0 | L6: 0 | M6: 0 | N6: 0 | O6: 0 | P6: 0 | Q6: 0 | R6: 0 | S6: 0 | T6: 0 | U6: -0.2901 | V6: 0.1123 | W6: -0.1147
A7: Raw Material Consumed | B7: 0.0087 | C7: 0 | D7: 0 | E7: 0 | F7: 0 | G7: 0 | H7: 0 | I7: 0 | J7: 0 | K7: 0 | L7: 0 | M7: 0 | N7: 0 | O7: 0 | P7: 0 | Q7: 0 | R7: 0 | S7: 0 | T7: 0 | U7: 0 | V7: 0 | W7: 0
A8: Variable Cost | B8: =+B6+B7 -> -0.0433 | C8: =+C6+C7 -> 0.145 | D8: =+D6+D7 -> -0.0882 | E8: =+E6+E7 -> -0.0097 | F8: =+F6+F7 -> 0 | G8: =+G6+G7 -> 0 | H8: =+H6+H7 -> 0 | I8: =+I6+I7 -> 0 | ... W8: =+W6+W7 -> -0.1147
A9: Gross Profit | B9: =+B3-B8 -> 7.8353 | C9: =+C3-C8 -> 10.1969 | D9: =+D3-D8 -> 27.4215 | E9: =+E3-E8 -> 46.1087 | F9: =+F3-F8 -> 68.8106 | G9: =+G3-G8 -> 20.1678 | H9: =+H3-H8 -> 64.1328 | I9: =+I3-I8 -> 45.3417 | ... W9: =+W3-W8 -> 791.1621
A10: Gross Margin | B10: =+B9/B3 -> 1.005557 | C10: =+C9/C3 -> 0.98597937 | D10: =+D9/D3 -> 1.0032268 | E10: =+E9/E3 -> 1.0002104 | F10: =+F9/F3 -> 1 | G10: =+G9/G3 -> 1 | H10: =+H9/H3 -> 1 | I10: =+I9/I3 -> 1 | ... W10: =+W9/W3 -> 1.000145
A11: Power & Fuel Cost | B11: 0.0113 | C11: 0.0094 | D11: 0.0116 | E11: 0.0255 | F11: 0.0309 | G11: 0.3433 | H11: 1.646 | I11: 1.7599 | J11: 2.6158 | K11: 2.1969 | L11: 4.7593 | M11: 2.2245 | N11: 0.6942 | O11: 0.8584 | P11: 0.312 | Q11: 0.1863 | R11: 1.7866 | S11: 5.4573 | T11: 1.3327 | U11: 1.4511 | V11: 1.2851 | W11: 1.1548
A12: Employee Cost | B12: 0.2009 | C12: 0.2546 | D12: 0.3882 | E12: 1.7489 | F12: 2.8866 | G12: 3.6939 | H12: 10.2307 | I12: 10.6574 | J12: 12.5705 | K12: 15.6098 | L12: 22.9595 | M12: 17.461 | N12: 22.5332 | O12: 36.9253 | P12: 20.67 | Q12: 10.0333 | R12: 14.2757 | S12: 21.8715 | T12: 28.5933 | U12: 26.4386 | V12: 12.0414 | W12: 42.1453
A13: Other Manufacturing Expenses | B13: 6.1584 | C13: 7.8543 | D13: 17.3593 | E13: 25.665 | F13: 41.3242 | G13: 7.8215 | H13: 33.6653 | I13: 24.7249 | J13: 26.798 | K13: 82.259 | L13: 82.6211 | M13: 65.832 | N13: 16.0951 | O13: 75.6539 | P13: 110.2722 | Q13: 114.4034 | R13: 100.9672 | S13: 139.0727 | T13: 69.9947 | U13: 213.5349 | V13: 357.764 | W13: 607.6703
A14: General & Administration Expenses | B14: 0.4848 | C14: 0.6543 | D14: 1.1644 | E14: 3.2133 | F14: 11.5349 | G14: 5.5573 | H14: 12.4569 | I14: 12.7854 | J14: 15.4689 | K14: 13.868 | L14: 34.7563 | M14: 11.611 | N14: 58.8604 | O14: 66.5208 | P14: 27.9345 | Q14: 78.3647 | R14: 54.8935 | S14: 23.7932 | T14: 24.1306 | U14: 19.6858 | V14: 24.8796 | W14: 40.1986
A15: Selling & Distribution Expenses | B15: 0.0055 | C15: 0.0067 | D15: 0.0082 | E15: 0.0665 | F15: 0.0805 | G15: 0.0385 | H15: 0.0844 | I15: 0.1426 | J15: 0.6493 | K15: 8.9887 | L15: 0.6303 | M15: 0.079 | N15: 0.0363 | O15: 0.5893 | P15: 0.1322 | Q15: 0.043 | R15: 0.3676 | S15: 0.9364 | T15: 0.5568 | U15: 0.0502 | V15: 0.0706 | W15: 0
A16: Miscellaneous Expenses | B16: 0.0715 | C16: 0.05 | D16: 0.0245 | E16: 0.1717 | F16: 2.8141 | G16: 0.2217 | H16: 0.434 | I16: 1.3735 | J16: 0.6088 | K16: 1.3881 | L16: 0.6164 | M16: 5.5169 | N16: 44.3675 | O16: 0.985 | P16: 1.659 | Q16: 3.5754 | R16: 1.017 | S16: 3.0004 | T16: 4.1132 | U16: 2.3774 | V16: 2.7771 | W16: 4.6372
A17: Total Expenditure | B17: =SUM(B11:B16)+B8 -> 6.8891 | C17: =SUM(C11:C16)+C8 -> 8.9743 | D17: =SUM(D11:D16)+D8 -> 18.868 | E17: =SUM(E11:E16)+E8 -> 30.8812 | F17: =SUM(F11:F16)+F8 -> 58.6712 | G17: =SUM(G11:G16)+G8 -> 17.6762 | H17: =SUM(H11:H16)+H8 -> 58.5173 | I17: =SUM(I11:I16)+I8 -> 51.4437 | ... W17: =SUM(W11:W16)+W8 -> 695.6915
A19: EBITDA | B19: =B3-B17 -> 0.9029 | C19: =C3-C17 -> 1.3676 | D19: =D3-D17 -> 8.4653 | E19: =E3-E17 -> 15.2178 | F19: =F3-F17 -> 10.1394 | G19: =G3-G17 -> 2.4916 | H19: =H3-H17 -> 5.6155 | I19: =I3-I17 -> -6.102 | ... W19: =W3-W17 -> 95.3559
A20: Growth, % | C20: =IF(B19<=0,"n.m.",C19/B19-1) -> 0.51467494 | D20: =IF(C19<=0,"n.m.",D19/C19-1) -> 5.1898947 | E20: =IF(D19<=0,"n.m.",E19/D19-1) -> 0.79766813 | F20: =IF(E19<=0,"n.m.",F19/E19-1) -> -0.33371447 | G20: =IF(F19<=0,"n.m.",G19/F19-1) -> -0.75426554 | H20: =IF(G19<=0,"n.m.",H19/G19-1) -> 1.2537727 | I20: =IF(H19<=0,"n.m.",I19/H19-1) -> -2.0866352 | J20: =IF(I19<=0,"n.m.",J19/I19-1) -> n.m. | ... W20: =IF(V19<=0,"n.m.",W19/V19-1) -> 0.44242603
A21: Margin, % | B21: =+B19/B3 -> 0.11587526 | C21: =+C19/C3 -> 0.13223876 | D21: =+D19/D3 -> 0.30970648 | E21: =+E19/E3 -> 0.33011128 | F21: =+F19/F3 -> 0.1473523 | G21: =+G19/G3 -> 0.12354347 | H21: =+H19/H3 -> 0.087560499 | I21: =+I19/I3 -> -0.1345781 | ... W21: =+W19/W3 -> 0.12054385
A22: Other Income | B22: 0.1154 | C22: 0.2014 | D22: 0.2641 | E22: 1.8369 | F22: 2.4831 | G22: 0.8703 | H22: 3.6072 | I22: 4.4322 | J22: 6.3341 | K22: 3.4691 | L22: 6.5486 | M22: 28.5242 | N22: 3.8944 | O22: 3.524 | P22: 3.9772 | Q22: 3.4683 | R22: 5.4203 | S22: 2.8284 | T22: 4.0969 | U22: 6.22 | V22: 5.4144 | W22: 8.8908
A23: Depreciation | B23: 0.3666 | C23: 0.3404 | D23: 0.6558 | E23: 2.0428 | F23: 3.9044 | G23: 3.5659 | H23: 8.6267 | I23: 8.5149 | J23: 8.8169 | K23: 14.1454 | L23: 18.1089 | M23: 17.7781 | N23: 15.13 | O23: 17.0268 | P23: 19.4427 | Q23: 19.6594 | R23: 23.3298 | S23: 27.6881 | T23: 21.9704 | U23: 17.0187 | V23: 17.7066 | W23: 18.8635
A24: EBIT | B24: =B19+B22-B23 -> 0.6517 | C24: =C19+C22-C23 -> 1.2286 | D24: =D19+D22-D23 -> 8.0736 | E24: =E19+E22-E23 -> 15.0119 | F24: =F19+F22-F23 -> 8.7181 | G24: =G19+G22-G23 -> -0.204 | H24: =H19+H22-H23 -> 0.596 | I24: =I19+I22-I23 -> -10.1847 | ... W24: =W19+W22-W23 -> 85.3832
A25: Interest | B25: 0.1478 | C25: 0.227 | D25: 0.5023 | E25: 1.0213 | F25: 0.6507 | G25: 0.3162 | H25: 1.0053 | I25: 2.3447 | J25: 3.1862 | K25: 9.4699 | L25: 9.4525 | M25: 10.8918 | N25: 7.6827 | O25: 6.3407 | P25: 5.7206 | Q25: 2.852 | R25: 0.7134 | S25: 0.8092 | T25: 2.4636 | U25: 2.0613 | V25: 3.8255 | W25: 10.6512
A26: Share of Profit/(Loss) of JVs & Associates | B26: 0 | C26: 0 | D26: 0 | E26: 0 | F26: 0 | G26: 0 | H26: 0 | I26: 0 | J26: 0 | K26: 0 | L26: 0 | M26: 0 | N26: 0 | O26: 0 | P26: 0 | Q26: 0 | R26: 0 | S26: 0 | T26: 0.611 | U26: 1.5713 | V26: 6.1866 | W26: 3.5077
A27: Exceptional Income / (Expenses) | B27: 0 | C27: 0 | D27: -0.7947 | E27: -0.3402 | F27: 0 | G27: 0 | H27: -6.9808 | I27: -0.7394 | J27: -1.3842 | K27: -0.7823 | L27: -0.4492 | M27: 0 | N27: 19.1894 | O27: -10.3411 | P27: -2.5077 | Q27: -6.8655 | R27: -12.3446 | S27: 0 | T27: -6.0685 | U27: -1.851 | V27: 0 | W27: -9.4031
A28: PBT | B28: =+B24-B25+B26+B27 -> 0.5039 | C28: =+C24-C25+C26+C27 -> 1.0016 | D28: =+D24-D25+D26+D27 -> 6.7766 | E28: =+E24-E25+E26+E27 -> 13.6504 | F28: =+F24-F25+F26+F27 -> 8.0674 | G28: =+G24-G25+G26+G27 -> -0.5202 | H28: =+H24-H25+H26+H27 -> -7.3901 | I28: =+I24-I25+I26+I27 -> -13.2688 | ... W28: =+W24-W25+W26+W27 -> 68.8366
A29: Provision for Tax | B29: 0.1848 | C29: 0.3805 | D29: 2.4813 | E29: 4.0278 | F29: 2.8156 | G29: 0.3766 | H29: 0.1551 | I29: -4.2264 | J29: -0.0926 | K29: 0.0181 | L29: 0.039 | M29: 1.8531 | N29: 0.2052 | O29: 0.2017 | P29: 0.0808 | Q29: 11.4037 | R29: 1.9432 | S29: 1.8596 | T29: -0.1223 | U29: 3.1297 | V29: 14.0133 | W29: 16.9979
A30: Tax Rate % | B30: =IF(B28<=0,"n.m.",B29/B28) -> 0.36673943 | C30: =IF(C28<=0,"n.m.",C29/C28) -> 0.37989217 | D30: =IF(D28<=0,"n.m.",D29/D28) -> 0.36615707 | E30: =IF(E28<=0,"n.m.",E29/E28) -> 0.29506828 | F30: =IF(F28<=0,"n.m.",F29/F28) -> 0.34900959 | G30: =IF(G28<=0,"n.m.",G29/G28) -> n.m. | H30: =IF(H28<=0,"n.m.",H29/H28) -> n.m. | I30: =IF(I28<=0,"n.m.",I29/I28) -> n.m. | ... W30: =IF(W28<=0,"n.m.",W29/W28) -> 0.24693114
A31: PAT | B31: =+B28-B29 -> 0.3191 | C31: =+C28-C29 -> 0.6211 | D31: =+D28-D29 -> 4.2953 | E31: =+E28-E29 -> 9.6226 | F31: =+F28-F29 -> 5.2518 | G31: =+G28-G29 -> -0.8968 | H31: =+H28-H29 -> -7.5452 | I31: =+I28-I29 -> -9.0424 | ... W31: =+W28-W29 -> 51.8387
A32: Less: Minority Interest | B32: 0 | C32: 0 | D32: 0 | E32: 0 | F32: 0 | G32: 0 | H32: 0 | I32: 0 | J32: 0 | K32: 0 | L32: 0 | M32: 0 | N32: 0 | O32: 0 | P32: 0 | Q32: 0 | R32: 0 | S32: 0 | T32: -0.0852 | U32: 0.0802 | V32: 0.0405 | W32: 0.6816
A33: PAT attributable to owners | B33: =+B31-B32 -> 0.3191 | C33: =+C31-C32 -> 0.6211 | D33: =+D31-D32 -> 4.2953 | E33: =+E31-E32 -> 9.6226 | F33: =+F31-F32 -> 5.2518 | G33: =+G31-G32 -> -0.8968 | H33: =+H31-H32 -> -7.5452 | I33: =+I31-I32 -> -9.0424 | ... W33: =+W31-W32 -> 51.1571
A34: Growth, % | C34: =IF(B33<=0,"n.m.",C33/B33-1) -> 0.94641178 | D34: =IF(C33<=0,"n.m.",D33/C33-1) -> 5.9156336 | E34: =IF(D33<=0,"n.m.",E33/D33-1) -> 1.2402626 | F34: =IF(E33<=0,"n.m.",F33/E33-1) -> -0.45422235 | G34: =IF(F33<=0,"n.m.",G33/F33-1) -> -1.1707605 | H34: =IF(G33<=0,"n.m.",H33/G33-1) -> n.m. | I34: =IF(H33<=0,"n.m.",I33/H33-1) -> n.m. | J34: =IF(I33<=0,"n.m.",J33/I33-1) -> n.m. | ... W34: =IF(V33<=0,"n.m.",W33/V33-1) -> 0.21446665
A35: Margin, % | B35: =+B33/B3 -> 0.040952259 | C35: =+C33/C3 -> 0.060056663 | D35: =+D33/D3 -> 0.15714531 | E35: =+E33/E3 -> 0.20873772 | F35: =+F33/F3 -> 0.076322543 | G35: =+G33/G3 -> -0.044466923 | H35: =+H33/H3 -> -0.11764963 | I35: =+I33/I3 -> -0.1994279 | ... W35: =+W33/W3 -> 0.064670082
A36: No. of Shares (crore) | B36: =B43/10 -> 0.53571 | C36: =C43/10 -> 0.53571 | D36: =D43/10 -> 0.70071 | E36: =E43/10 -> 1.046 | F36: =F43/10 -> 1.12744 | G36: =G43/10 -> 1.53244 | H36: =H43/10 -> 1.53244 | I36: =I43/10 -> 1.53244 | ... W36: =W43/10 -> 4.49175
A37: EPS (Rs.) | B37: =+B33/B36 -> 0.5956581 | C37: =+C33/C36 -> 1.1593959 | D37: =+D33/D36 -> 6.1299254 | E37: =+E33/E36 -> 9.1994264 | F37: =+F33/F36 -> 4.6581636 | G37: =+G33/G36 -> -0.58521051 | H37: =+H33/H36 -> -4.9236512 | I37: =+I33/I36 -> -5.9006552 | ... W37: =+W33/W36 -> 11.389125
A38: Dividend (Rs. crore) | B38: =+B36*B39 -> 0 | C38: =+C36*C39 -> 0 | D38: =+D36*D39 -> 0 | E38: =+E36*E39 -> 0 | F38: =+F36*F39 -> 0 | G38: =+G36*G39 -> 0 | H38: =+H36*H39 -> 0 | I38: =+I36*I39 -> 0 | ... W38: =+W36*W39 -> 5.6146875
A39: DPS | B39: 0 | C39: 0 | D39: 0 | E39: 0 | F39: 0 | G39: 0 | H39: 0 | I39: 0 | J39: 0 | K39: 0 | L39: 0 | M39: 0 | N39: 0 | O39: 0 | P39: 0 | Q39: 0 | R39: 0 | S39: 0 | T39: 0 | U39: 0 | V39: 1 | W39: 1.25
A41: Balance Sheet (Rs. crore) | B41: =B$2 -> FY05 | C41: =C$2 -> FY06 | D41: =D$2 -> FY07 | E41: =E$2 -> FY08 | F41: =F$2 -> FY09 | G41: =G$2 -> FY10 | H41: =H$2 -> FY11 | I41: =I$2 -> FY12 | ... AA41: =AA$2 -> FY30E
A42: EQUITY AND LIABILITIES
A43: Share Capital | B43: 5.3571 | C43: 5.3571 | D43: 7.0071 | E43: 10.46 | F43: 11.2744 | G43: 15.3244 | H43: 15.3244 | I43: 15.3244 | J43: 15.3244 | K43: 22.3244 | L43: 22.3244 | M43: 22.3244 | N43: 26.0744 | O43: 38.0744 | P43: 38.0744 | Q43: 37.6937 | R43: 37.6937 | S43: 37.6937 | T43: 37.6937 | U43: 40.6529 | V43: 44.7035 | W43: 44.9175
A44: Share Warrants & Outstandings | B44: 0 | C44: 0 | D44: 0.3219 | E44: 5.5541 | F44: 2.28 | G44: 0 | H44: 0 | I44: 0 | J44: 0 | K44: 0 | L44: 0 | M44: 0 | N44: 48 | O44: 0.3798 | P44: 1.0127 | Q44: 0.51 | R44: 0.7923 | S44: 0 | T44: 0.0661 | U44: 12.5272 | V44: 40.966 | W44: 53.9924
A45: Total Reserves | B45: 1.4844 | C45: 2.1054 | D45: 7.9957 | E45: 50.7866 | F45: 64.3412 | G45: 85.0969 | H45: 76.1751 | I45: 66.9785 | J45: 56.918 | K45: 42.6831 | L45: 14.8677 | M45: -12.2576 | N45: 7.7175 | O45: 102.077 | P45: 112.9143 | Q45: 143.2492 | R45: 164.951 | S45: 204.069 | T45: 161.6927 | U45: 224.7 | V45: 313.0025 | W45: 395.2431
A46: Shareholder's Funds | B46: =SUM(B43:B45) -> 6.8415 | C46: =SUM(C43:C45) -> 7.4625 | D46: =SUM(D43:D45) -> 15.3247 | E46: =SUM(E43:E45) -> 66.8007 | F46: =SUM(F43:F45) -> 77.8956 | G46: =SUM(G43:G45) -> 100.4213 | H46: =SUM(H43:H45) -> 91.4995 | I46: =SUM(I43:I45) -> 82.3029 | ... W46: =SUM(W43:W45) -> 494.153
A47: Minority Interest | B47: 0 | C47: 0 | D47: 0 | E47: 0 | F47: 0 | G47: 0 | H47: 0 | I47: 0 | J47: 0 | K47: 0 | L47: 0 | M47: 0 | N47: 0 | O47: 0 | P47: 0 | Q47: 0 | R47: 0 | S47: 0 | T47: 0.0209 | U47: 0.1011 | V47: 0.1416 | W47: 0.8232
A49: Non-Current Liabilities
A50: Secured Loans | B50: 0.9048 | C50: 1.5553 | D50: 3.7518 | E50: 3.0908 | F50: 0.0146 | G50: 0.0066 | H50: 6.8 | I50: 2.6 | J50: 0.1883 | K50: 0.0779 | L50: 17.0546 | M50: 17.8738 | N50: 0 | O50: 5.3722 | P50: 0 | Q50: 0 | R50: 2.1795 | S50: 2.522 | T50: 2.5947 | U50: 0.9419 | V50: 6.336 | W50: 72.2426
A51: Unsecured Loans | B51: 0.172 | C51: 0.154 | D51: 0 | E51: 0 | F51: 0 | G51: 0 | H51: 0 | I51: 0 | J51: 0 | K51: 0 | L51: 12.5182 | M51: 0 | N51: 8.9154 | O51: 8.9436 | P51: 0 | Q51: 0 | R51: 0 | S51: 0 | T51: 0 | U51: 0 | V51: 0 | W51: 0
A52: Deferred Tax Liabilities / (Assets) | B52: 0.1905 | C52: 0.1905 | D52: 0.1298 | E52: 1.251 | F52: 3.3503 | G52: 4.1813 | H52: 4.3379 | I52: 0.102 | J52: 0.001 | K52: 0 | L52: 0 | M52: 0 | N52: 0 | O52: 0 | P52: 0 | Q52: 0 | R52: 0 | S52: 0.1692 | T52: 0 | U52: 2.415 | V52: 2.6427 | W52: -5.0725
A53: Other Long Term Liabilities | B53: 0 | C53: 0 | D53: 0 | E53: 0 | F53: 0 | G53: 0 | H53: 0 | I53: 0 | J53: 2.284 | K53: 35.9799 | L53: 19.8624 | M53: 0 | N53: 0 | O53: 0 | P53: 0.0398 | Q53: 2.8099 | R53: 0.5256 | S53: 1.167 | T53: 1.0429 | U53: 0.325 | V53: 0 | W53: 0
A54: Long Term Provisions | B54: 0 | C54: 0 | D54: 0 | E54: 0 | F54: 0 | G54: 0 | H54: 0.2793 | I54: 0.033 | J54: 0.0574 | K54: 0.1108 | L54: 0.0703 | M54: 0.077 | N54: 0 | O54: 0.0298 | P54: 0.0383 | Q54: 0.1062 | R54: 0.2105 | S54: 0.602 | T54: 0.3577 | U54: 0.9956 | V54: 5.7102 | W54: 12.3796
A55: Total Non-Current Liabilities | B55: =SUM(B50:B54) -> 1.2673 | C55: =SUM(C50:C54) -> 1.8998 | D55: =SUM(D50:D54) -> 3.8816 | E55: =SUM(E50:E54) -> 4.3418 | F55: =SUM(F50:F54) -> 3.3649 | G55: =SUM(G50:G54) -> 4.1879 | H55: =SUM(H50:H54) -> 11.4172 | I55: =SUM(I50:I54) -> 2.735 | ... W55: =SUM(W50:W54) -> 79.5497
A57: Current Liabilities
A58: Trade Payables | B58: 0.7951 | C58: 0.5676 | D58: 4.3099 | E58: 4.5082 | F58: 9.8333 | G58: 5.6369 | H58: 9.2015 | I58: 8.4769 | J58: 15.8215 | K58: 18.4727 | L58: 11.4495 | M58: 27.3305 | N58: 35.4283 | O58: 54.6194 | P58: 44.6631 | Q58: 63.2306 | R58: 92.2391 | S58: 71.388 | T58: 44.0688 | U58: 72.7812 | V58: 142.4448 | W58: 229.5765
A59: Other Current Liabilities | B59: 0.2441 | C59: 0.4713 | D59: 2.1644 | E59: 2.4794 | F59: 7.6436 | G59: 5.3659 | H59: 9.4448 | I59: 6.8282 | J59: 4.9884 | K59: 6.266 | L59: 29.2111 | M59: 71.6963 | N59: 16.608 | O59: 33.0182 | P59: 12.0741 | Q59: 48.6705 | R59: 36.566 | S59: 3.1467 | T59: 19.0039 | U59: 10.8998 | V59: 19.21 | W59: 35.5735
A60: Short Term Borrowings | B60: 0 | C60: 0 | D60: 0 | E60: 0 | F60: 0 | G60: 0 | H60: 0 | I60: 13.2349 | J60: 24.592 | K60: 46.4577 | L60: 22.5 | M60: 43.5447 | N60: 66.4389 | O60: 4.4934 | P60: 4.4 | Q60: 0 | R60: 0 | S60: 4.0117 | T60: 15.5824 | U60: 18.0192 | V60: 15.8095 | W60: 60.7017
A61: Short Term Provisions | B61: 0.4164 | C61: 1.1419 | D61: 3.0989 | E61: 3.1875 | F61: 0.108 | G61: 0.1608 | H61: 0.2539 | I61: 0.2797 | J61: 0.2496 | K61: 0.2423 | L61: 0.0021 | M61: 0.0152 | N61: 0.1292 | O61: 5.4876 | P61: 5.2365 | Q61: 11.4748 | R61: 12.8934 | S61: 13.4383 | T61: 14.595 | U61: 0.0913 | V61: 1.4899 | W61: 12.9618
A62: Total Current Liabilities | B62: =SUM(B58:B61) -> 1.4556 | C62: =SUM(C58:C61) -> 2.1808 | D62: =SUM(D58:D61) -> 9.5732 | E62: =SUM(E58:E61) -> 10.1751 | F62: =SUM(F58:F61) -> 17.5849 | G62: =SUM(G58:G61) -> 11.1636 | H62: =SUM(H58:H61) -> 18.9002 | I62: =SUM(I58:I61) -> 28.8197 | ... W62: =SUM(W58:W61) -> 338.8135
A64: TOTAL EQUITY AND LIABILITIES | B64: =B46+B47+B55+B62 -> 9.5644 | C64: =C46+C47+C55+C62 -> 11.5431 | D64: =D46+D47+D55+D62 -> 28.7795 | E64: =E46+E47+E55+E62 -> 81.3176 | F64: =F46+F47+F55+F62 -> 98.8454 | G64: =G46+G47+G55+G62 -> 115.7728 | H64: =H46+H47+H55+H62 -> 121.8169 | I64: =I46+I47+I55+I62 -> 113.8576 | ... W64: =W46+W47+W55+W62 -> 913.3394
A66: ASSETS
A67: Non-Current Assets
A68: Gross Block | B68: 6.7822 | C68: 6.9676 | D68: 8.5453 | E68: 24.8479 | F68: 31.5667 | G68: 49.9865 | H68: 60.398 | I68: 66.3341 | J68: 72.3399 | K68: 163.22 | L68: 164.7579 | M68: 173.0359 | N68: 94.8109 | O68: 127.9044 | P68: 133.5975 | Q68: 156.7121 | R68: 221.2483 | S68: 275.0995 | T68: 280.9525 | U68: 313.9248 | V68: 334.3936 | W68: 362.7596
A69: Less: Accumulated Depreciation | B69: 3.2318 | C69: 3.5722 | D69: 1.8056 | E69: 3.738 | F69: 7.5995 | G69: 10.2046 | H69: 18.7866 | I69: 27.2287 | J69: 33.949 | K69: 46.4561 | L69: 58.7459 | M69: 77.6295 | N69: 11.4099 | O69: 27.8073 | P69: 47.0855 | Q69: 66.5506 | R69: 89.3859 | S69: 163.1179 | T69: 185.2119 | U69: 202.1607 | V69: 219.0356 | W69: 248.2026
A70: Net Block | B70: =B68-B69 -> 3.5504 | C70: =C68-C69 -> 3.3954 | D70: =D68-D69 -> 6.7397 | E70: =E68-E69 -> 21.1099 | F70: =F68-F69 -> 23.9672 | G70: =G68-G69 -> 39.7819 | H70: =H68-H69 -> 41.6114 | I70: =I68-I69 -> 39.1054 | ... W70: =W68-W69 -> 114.557
A71: Capital Work in Progress | B71: 0 | C71: 0 | D71: 0 | E71: 0 | F71: 0 | G71: 0.8519 | H71: 4.1842 | I71: 0 | J71: 3.4685 | K71: 8.0464 | L71: 0 | M71: 0 | N71: 0 | O71: 0 | P71: 0 | Q71: 0 | R71: 0 | S71: 0 | T71: 0 | U71: 1.1572 | V71: 2.6268 | W71: 46.1305
A72: Intangible Assets under Development | B72: 0 | C72: 0 | D72: 0 | E72: 0 | F72: 0 | G72: 0 | H72: 0 | I72: 0.065 | J72: 0.1232 | K72: 0.1232 | L72: 0 | M72: 0 | N72: 0 | O72: 0 | P72: 0 | Q72: 0 | R72: 0 | S72: 0 | T72: 0 | U72: 0.2375 | V72: 0.2375 | W72: 0
A73: Assets in Transit | B73: 0 | C73: 0 | D73: 0 | E73: 0 | F73: 0 | G73: 0 | H73: 0 | I73: 0 | J73: 0 | K73: 0 | L73: 0 | M73: 0 | N73: 0 | O73: 0 | P73: 0 | Q73: 0 | R73: 0 | S73: 0 | T73: 0 | U73: 0 | V73: 0 | W73: 0
A74: Non-Current Investments | B74: 0.26 | C74: 0.1165 | D74: 0.0065 | E74: 34.3406 | F74: 23.8871 | G74: 22.5249 | H74: 0 | I74: 0 | J74: 0 | K74: 0 | L74: 0 | M74: 0 | N74: 0 | O74: 0 | P74: 0 | Q74: 0 | R74: 0 | S74: 6.1 | T74: 6.8452 | U74: 8.4165 | V74: 14.6031 | W74: 11.9357
A75: Long Term Loans & Advances | B75: 0 | C75: 0 | D75: 0 | E75: 0 | F75: 0 | G75: 0 | H75: 0.4999 | I75: 0.6472 | J75: 3.3602 | K75: 2.2867 | L75: 7.4361 | M75: 5.1436 | N75: 4.0465 | O75: 5.4903 | P75: 12.6825 | Q75: 16.009 | R75: 6.6329 | S75: 4.9575 | T75: 9.8925 | U75: 12.9697 | V75: 3.3769 | W75: 13.5488
A76: Other Non-Current Assets | B76: 0 | C76: 0 | D76: 0 | E76: 0 | F76: 0 | G76: 0 | H76: 0 | I76: 0 | J76: 0 | K76: 0 | L76: 4.8745 | M76: 5.559 | N76: 33.6853 | O76: 8.7592 | P76: 1.2244 | Q76: 11.6693 | R76: 5.2084 | S76: 4.9343 | T76: 6.9412 | U76: 27.3698 | V76: 6.7671 | W76: 12.0668
A77: Total Non-Current Assets | B77: =B70+SUM(B71:B76) -> 3.8104 | C77: =C70+SUM(C71:C76) -> 3.5119 | D77: =D70+SUM(D71:D76) -> 6.7462 | E77: =E70+SUM(E71:E76) -> 55.4505 | F77: =F70+SUM(F71:F76) -> 47.8543 | G77: =G70+SUM(G71:G76) -> 63.1587 | H77: =H70+SUM(H71:H76) -> 46.2955 | I77: =I70+SUM(I71:I76) -> 39.8176 | ... W77: =W70+SUM(W71:W76) -> 198.2388
A79: Current Assets
A80: Current Investments | B80: 0 | C80: 0 | D80: 0 | E80: 0 | F80: 11.2022 | G80: 17.1964 | H80: 4.0017 | I80: 10.7866 | J80: 5.9479 | K80: 0 | L80: 0 | M80: 0 | N80: 0 | O80: 0 | P80: 0 | Q80: 0 | R80: 0 | S80: 0 | T80: 13.1493 | U80: 3.4093 | V80: 18.3792 | W80: 0
A81: Inventories | B81: 0.15 | C81: 0.005 | D81: 0.0932 | E81: 0.1029 | F81: 0 | G81: 0 | H81: 2.3199 | I81: 3.4865 | J81: 5.9103 | K81: 4.2221 | L81: 3.8077 | M81: 5.6705 | N81: 1.5739 | O81: 1.8768 | P81: 0.6939 | Q81: 0.0161 | R81: 0 | S81: 0 | T81: 0 | U81: 0.2901 | V81: 0.1778 | W81: 0.2925
A82: Sundry Debtors | B82: 4.2893 | C82: 6.3066 | D82: 18.3543 | E82: 15.2262 | F82: 19.896 | G82: 9.8389 | H82: 25.3249 | I82: 18.5853 | J82: 15.2866 | K82: 10.9796 | L82: 18.8625 | M82: 42.91 | N82: 27.5121 | O82: 61.6137 | P82: 59.398 | Q82: 88.0607 | R82: 124.7184 | S82: 111.3331 | T82: 106.7256 | U82: 135.8781 | V82: 224.4159 | W82: 347.7344
A83: Cash and Bank | B83: 0.3988 | C83: 0.8861 | D83: 2.2083 | E83: 4.2125 | F83: 7.4471 | G83: 7.9855 | H83: 32.0268 | I83: 26.986 | J83: 18.2411 | K83: 9.3548 | L83: 2.997 | M83: 9.6584 | N83: 29.1432 | O83: 24.5741 | P83: 25.1937 | Q83: 81.9762 | R83: 23.8905 | S83: 50.2203 | T83: 26.9163 | U83: 38.9075 | V83: 77.6951 | W83: 146.8454
A84: Other Current Assets | B84: 0 | C84: 0 | D84: 0 | E84: 0 | F84: 0.8937 | G84: 3.0668 | H84: 4.7522 | I84: 7.9696 | J84: 20.2776 | K84: 5.1508 | L84: 1.9169 | M84: 4.891 | N84: 27.3634 | O84: 23.0986 | P84: 10.6905 | Q84: 5.1668 | R84: 3.7618 | S84: 7.768 | T84: 4.7873 | U84: 4.913 | V84: 4.7873 | W84: 9.7443
A85: Short Term Loans and Advances | B85: 0.8424 | C85: 0.809 | D85: 1.3774 | E85: 5.823 | F85: 11.5522 | G85: 14.5266 | H85: 7.0959 | I85: 6.2259 | J85: 9.4183 | K85: 15.6871 | L85: 3.9535 | M85: 1.3655 | N85: 2.5863 | O85: 26.9856 | P85: 22.0582 | Q85: 14.6853 | R85: 51.9767 | S85: 40.9128 | T85: 25.7208 | U85: 39.1374 | V85: 124.032 | W85: 210.484
A86: Total Current Assets | B86: =SUM(B80:B85) -> 5.6805 | C86: =SUM(C80:C85) -> 8.0067 | D86: =SUM(D80:D85) -> 22.0332 | E86: =SUM(E80:E85) -> 25.3646 | F86: =SUM(F80:F85) -> 50.9912 | G86: =SUM(G80:G85) -> 52.6142 | H86: =SUM(H80:H85) -> 75.5214 | I86: =SUM(I80:I85) -> 74.0399 | ... W86: =SUM(W80:W85) -> 715.1006
A87: Miscellaneous Expenses not Written Off | B87: 0.0735 | C87: 0.0245 | D87: 0 | E87: 0.5025 | F87: 0 | G87: 0 | H87: 0 | I87: 0 | J87: 0 | K87: 0 | L87: 0 | M87: 0 | N87: 0 | O87: 0 | P87: 0 | Q87: 0 | R87: 0 | S87: 0 | T87: 0 | U87: 0 | V87: 0 | W87: 0
A89: TOTAL ASSETS | B89: =B77+B86+B87 -> 9.5644 | C89: =C77+C86+C87 -> 11.5431 | D89: =D77+D86+D87 -> 28.7794 | E89: =E77+E86+E87 -> 81.3176 | F89: =F77+F86+F87 -> 98.8455 | G89: =G77+G86+G87 -> 115.7729 | H89: =H77+H86+H87 -> 121.8169 | I89: =I77+I86+I87 -> 113.8575 | ... W89: =W77+W86+W87 -> 913.3394
A90: Cash + current investments as % of current assets | B90: =(B80+B83)/B86 -> 0.070205088 | C90: =(C80+C83)/C86 -> 0.11066981 | D90: =(D80+D83)/D86 -> 0.10022602 | E90: =(E80+E83)/E86 -> 0.16607792 | F90: =(F80+F83)/F86 -> 0.36573566 | G90: =(G80+G83)/G86 -> 0.47861414 | H90: =(H80+H83)/H86 -> 0.47706345 | I90: =(I80+I83)/I86 -> 0.51016546 | ... W90: =(W80+W83)/W86 -> 0.20534929
A91: CHECK: | B91: =ROUND(B89-B64,1) -> 0 | C91: =ROUND(C89-C64,1) -> 0 | D91: =ROUND(D89-D64,1) -> 0 | E91: =ROUND(E89-E64,1) -> 0 | F91: =ROUND(F89-F64,1) -> 0 | G91: =ROUND(G89-G64,1) -> 0 | H91: =ROUND(H89-H64,1) -> 0 | I91: =ROUND(I89-I64,1) -> 0 | ... W91: =ROUND(W89-W64,1) -> 0
A93: Cash Flow Statement (Rs. crore) | B93: =B$2 -> FY05 | C93: =C$2 -> FY06 | D93: =D$2 -> FY07 | E93: =E$2 -> FY08 | F93: =F$2 -> FY09 | G93: =G$2 -> FY10 | H93: =H$2 -> FY11 | I93: =I$2 -> FY12 | ... AA93: =AA$2 -> FY30E
A94: Profit Before Tax (per CF as reported) | B94: 0.5037 | C94: 1.0015 | D94: 7.5713 | E94: 13.9905 | F94: 8.0675 | G94: -0.5201 | H94: -7.3899 | I94: -13.2688 | J94: -10.3874 | K94: -23.4028 | L94: -26.9718 | M94: -25.2025 | N94: -17.9994 | O94: 10.5056 | P94: 9.1815 | Q94: 40.6391 | R94: 24.5147 | S94: 40.6707 | T94: -44.5645 | U94: 28.6772 | V94: 56.1769 | W94: 68.8366
A96: Adjustments (non-cash / non-operating)
A97: Depreciation & Impairment | B97: 0 | C97: 0 | D97: 0 | E97: 0 | F97: 3.9044 | G97: 3.5659 | H97: 8.6267 | I97: 8.5149 | J97: 8.8169 | K97: 14.1454 | L97: 18.1089 | M97: 17.8995 | N97: 17.8399 | O97: 27.008 | P97: 19.4427 | Q97: 19.6594 | R97: 23.3298 | S97: 27.6881 | T97: 21.9704 | U97: 17.0187 | V97: 17.7066 | W97: 18.8635
A98: Interest Expenses | B98: 0 | C98: 0 | D98: 0 | E98: 0 | F98: 0.6507 | G98: 0.3162 | H98: 1.0053 | I98: 2.3447 | J98: 3.0848 | K98: 9.4699 | L98: 9.4525 | M98: 9.1352 | N98: 6.3519 | O98: 4.9078 | P98: 2.7173 | Q98: 2.4272 | R98: 0.3645 | S98: 0.438 | T98: 0.9362 | U98: 2.0473 | V98: 3.7687 | W98: 7.4251
A99: Profit/Loss on Sale of Fixed Assets | B99: 0 | C99: 0 | D99: 0 | E99: 0 | F99: -0.31 | G99: -0.0071 | H99: -0.0385 | I99: 0.0106 | J99: 0.2675 | K99: 0.5351 | L99: 0 | M99: 0 | N99: 2.0961 | O99: 0 | P99: -0.1362 | Q99: -0.2195 | R99: 0 | S99: -0.0106 | T99: 0 | U99: 0 | V99: 0 | W99: 0.0732
A100: Profit/Loss on Sale of Investments | B100: 0 | C100: 0 | D100: 0 | E100: 0 | F100: 0.022 | G100: -0.0034 | H100: 0 | I100: 0 | J100: 0 | K100: 0 | L100: 0 | M100: 0 | N100: 0 | O100: 0 | P100: 0 | Q100: 0 | R100: 0 | S100: 0 | T100: -0.1493 | U100: -0.4995 | V100: -1.2648 | W100: -1.0745
A101: Dividend Received | B101: 0 | C101: 0 | D101: 0 | E101: 0 | F101: -1.1783 | G101: -0.5043 | H101: -0.3623 | I101: -0.9173 | J101: -0.6751 | K101: -0.0871 | L101: 0 | M101: 0 | N101: 0 | O101: 0 | P101: 0 | Q101: 0 | R101: 0 | S101: 0 | T101: 0 | U101: 0 | V101: 0 | W101: 0
A102: Interest Income | B102: 0 | C102: 0 | D102: 0 | E102: 0 | F102: -0.8842 | G102: -0.2924 | H102: -1.1201 | I102: -2.8041 | J102: -2.1286 | K102: -0.8618 | L102: -0.4928 | M102: -0.5404 | N102: -1.2952 | O102: -2.834 | P102: -1.9516 | Q102: -2.1164 | R102: -4.761 | S102: -2.6339 | T102: -3.4891 | U102: -2.2279 | V102: -4.1496 | W102: -4.4949
A103: Diminution / Write-off of Investments | B103: 0 | C103: 0 | D103: 0 | E103: 0 | F103: 0 | G103: 0 | H103: 0 | I103: 0 | J103: 0 | K103: 0 | L103: 0 | M103: 0.01 | N103: 0 | O103: 0 | P103: 0 | Q103: 0 | R103: 0 | S103: 0 | T103: 0 | U103: 0 | V103: 0 | W103: 0
A104: Effect of Exchange Rate Change | B104: 0 | C104: 0 | D104: 0 | E104: 0 | F104: 0 | G104: -0.0353 | H104: 0.0107 | I104: -0.0153 | J104: 0.2344 | K104: -0.0507 | L104: 0.2353 | M104: -0.8269 | N104: 3.1961 | O104: -0.3937 | P104: -0.5418 | Q104: -0.5087 | R104: -0.2006 | S104: 0.0778 | T104: 0.022 | U104: -0.5743 | V104: 0.0043 | W104: 0
A105: Net Prior Year Adjustments | B105: 0 | C105: 0 | D105: 0 | E105: 0 | F105: 0 | G105: 0 | H105: 0 | I105: 0 | J105: 0 | K105: 0 | L105: 0 | M105: 0 | N105: 0 | O105: 0 | P105: 0 | Q105: 0 | R105: 0 | S105: 0 | T105: 0 | U105: 0 | V105: 0 | W105: 0
A106: Provisions & Write-offs | B106: 0 | C106: 0 | D106: 0 | E106: 0 | F106: 0 | G106: 0 | H106: 0 | I106: 0 | J106: -0.7394 | K106: 0 | L106: -2.364 | M106: 0.9341 | N106: 9.1694 | O106: -3.5472 | P106: 1.5835 | Q106: 11.1484 | R106: 11.0795 | S106: -0.7085 | T106: 0.5155 | U106: -1.2204 | V106: 0.0606 | W106: 0.8695
A107: Excess of Cost over Fair Value of Investments | B107: 0 | C107: 0 | D107: 0 | E107: 0 | F107: 0 | G107: 0 | H107: 0 | I107: 0 | J107: 0 | K107: 0 | L107: 0 | M107: 0 | N107: 0 | O107: 0 | P107: 0 | Q107: 0 | R107: 0 | S107: 0 | T107: 0 | U107: 0 | V107: 0 | W107: 0
A108: Bad Debts Written Off | B108: 0 | C108: 0 | D108: 0 | E108: 0 | F108: 0 | G108: 0 | H108: 0 | I108: 0 | J108: 0 | K108: 0 | L108: 0.2788 | M108: 2.7424 | N108: 0 | O108: 2.09 | P108: 0 | Q108: 0 | R108: 0 | S108: 0 | T108: 0 | U108: 0 | V108: 0 | W108: 0
... A111: Other Adjustments | B111: 0.5185336 | C111: 0.5634646 | D111: 1.0368551 | E111: 2.3765786 | F111: 0 | G111: 0 | H111: 0 | I111: 0 | J111: 0 | K111: 0 | L111: 0 | M111: 0 | N111: 0 | O111: 0.3774 | P111: 0 | Q111: 0 | R111: 0.2823 | S111: 0.0739 | T111: 5.4898 | U111: 0.4182 | V111: -5.3365 | W111: 5.6717
A112: Total Adjustments | B112: =SUM(B97:B111) -> 0.5185336 | C112: =SUM(C97:C111) -> 0.5634646 | D112: =SUM(D97:D111) -> 1.0368551 | E112: =SUM(E97:E111) -> 2.3765786 | F112: =SUM(F97:F111) -> 2.7071 | G112: =SUM(G97:G111) -> 3.0454 | H112: =SUM(H97:H111) -> 15.106 | I112: =SUM(I97:I111) -> 8.8173 | ... W112: =SUM(W97:W111) -> 28.8336
...

Sheet Segments
A1: Segment Data (Rs. cr) - Ind AS 108, consolidated | B1: FY21 | C1: FY22 | D1: FY23 | E1: FY24 | F1: FY25 | G1: FY26 | H1: FY27E | I1: FY28E | J1: FY29E | K1: FY30E
A3: Revenue
A4: Oil & Gas services revenue | B4: 221.91 | C4: 188.87 | D4: 63.22 | E4: 191.91 | F4: 192.44 | G4: 632.68
A5: Growth, % | C5: =+C4/B4-1 -> -0.14888919 | D5: =+D4/C4-1 -> -0.66527241 | E5: =+E4/D4-1 -> 2.03559 | F5: =+F4/E4-1 -> 0.0027617112 | G5: =+G4/F4-1 -> 2.2876741
A6: Mineral & other energy (coal CHP, power) revenue | B6: 6.88 | C6: 71.6 | D6: 46.73 | E6: 113.16 | F6: 272.59 | G6: 158.37
A7: Growth, % | C7: =IF(B6<=0,"n.m.",C6/B6-1) -> 9.4069767 | D7: =IF(C6<=0,"n.m.",D6/C6-1) -> -0.34734637 | E7: =IF(D6<=0,"n.m.",E6/D6-1) -> 1.4215707 | F7: =IF(E6<=0,"n.m.",F6/E6-1) -> 1.4088901 | G7: =IF(F6<=0,"n.m.",G6/F6-1) -> -0.41901757
A8: Total Segment Revenue | B8: =+B6+B4 -> 228.79 | C8: =+C6+C4 -> 260.47 | D8: =+D6+D4 -> 109.95 | E8: =+E6+E4 -> 305.07 | F8: =+F6+F4 -> 465.03 | G8: =+G6+G4 -> 791.05
A9: Oil & Gas share of revenue | B9: =+B4/B8 -> 0.96992876 | C9: =+C4/C8 -> 0.7251123 | D9: =+D4/D8 -> 0.57498863 | E9: =+E4/E8 -> 0.62906874 | F9: =+F4/F8 -> 0.41382276 | G9: =+G4/G8 -> 0.79979774
A10: Check vs P&L Net Sales | B10: =ROUND(B8-'P&L'!R3,1) -> 0 | C10: =ROUND(C8-'P&L'!S3,1) -> 0 | D10: =ROUND(D8-'P&L'!T3,1) -> 0 | E10: =ROUND(E8-'P&L'!U3,1) -> 0 | F10: =ROUND(F8-'P&L'!V3,1) -> 0 | G10: =ROUND(G8-'P&L'!W3,1) -> 0
A12: SEGMENT RESULT (EBITDA level: before D&A, finance cost, other income, unallocable)
A13: Oil & Gas result | B13: 77.79 | C13: 54.52 | D13: -0.3 | E13: 40.97 | F13: 33.05 | G13: 101.96
A14: Mineral & other energy result | B14: -3.8 | C14: 32.96 | D14: 6.73 | E14: 18.63 | F14: 58.87 | G14: 31.6
A15: Total segment result | B15: =SUM(B13:B14) -> 73.99 | C15: =SUM(C13:C14) -> 87.48 | D15: =SUM(D13:D14) -> 6.43 | E15: =SUM(E13:E14) -> 59.6 | F15: =SUM(F13:F14) -> 91.92 | G15: =SUM(G13:G14) -> 133.56
A16: Less: Depreciation & amortisation | B16: 23.33 | C16: 27.69 | D16: 21.97 | E16: 17.02 | F16: 17.71 | G16: 18.86
A17: Add: Other income | B17: 5.42 | C17: 2.83 | D17: 4.1 | E17: 6.22 | F17: 5.41 | G17: 8.89
A18: Less: Finance costs | B18: 0.71 | C18: 0.81 | D18: 2.46 | E18: 2.06 | F18: 3.83 | G18: 10.65
A19: Less: Other unallocable expenses (corporate staff, admin) | B19: 18.5 | C19: 21.14 | D19: 25.2 | E19: 17.79 | F19: 25.81 | G19: 38.2
A20: Profit before JV share, exceptional items and tax | B20: =+B15-B16+B17-B18-B19 -> 36.87 | C20: =+C15-C16+C17-C18-C19 -> 40.67 | D20: =+D15-D16+D17-D18-D19 -> -39.1 | E20: =+E15-E16+E17-E18-E19 -> 28.95 | F20: =+F15-F16+F17-F18-F19 -> 49.98 | G20: =+G15-G16+G17-G18-G19 -> 74.74
A22: SEGMENT MARGINS (Result/Revenue)
A23: Oil & Gas margin % | B23: =IF(B4=0,"n.m.",B13/B4) -> 0.35054752 | C23: =IF(C4=0,"n.m.",C13/C4) -> 0.28866416 | D23: =IF(D4=0,"n.m.",D13/D4) -> -0.0047453338 | E23: =IF(E4=0,"n.m.",E13/E4) -> 0.21348549 | F23: =IF(F4=0,"n.m.",F13/F4) -> 0.17174184 | G23: =IF(G4=0,"n.m.",G13/G4) -> 0.16115572
A24: Mineral & other energy margin % | B24: =IF(B6=0,"n.m.",B14/B6) -> -0.55232558 | C24: =IF(C6=0,"n.m.",C14/C6) -> 0.4603352 | D24: =IF(D6=0,"n.m.",D14/D6) -> 0.14401883 | E24: =IF(E6=0,"n.m.",E14/E6) -> 0.16463415 | F24: =IF(F6=0,"n.m.",F14/F6) -> 0.21596537 | G24: =IF(G6=0,"n.m.",G14/G6) -> 0.19953274
A25: Blended segment margin % | B25: =+B15/B8 -> 0.323397 | C25: =+C15/C8 -> 0.33585442 | D25: =+D15/D8 -> 0.058481128 | E25: =+E15/E8 -> 0.195365 | F25: =+F15/F8 -> 0.19766467 | G25: =+G15/G8 -> 0.16883889
A27: Segment capital employed
A28: Not disclosed: the CODM does not review assets and liabilities by segment (AR FY26 Note 45 VII; same wording FY22-FY25).
A30: Geography and concentration (Rs. cr)
A31: Revenue outside India | F31: 0 | G31: 299.37
A32: Revenue from top customer | F32: 112.7 | G32: 142.96
A33: Revenue from top three customers | F33: 246.6 | G33: 264.36
A34: Customers >10% of revenue (number) | F34: 4 | G34: 3
A36: Sources: AR FY22 Note (segment), AR FY24 Note (segment, FY23 comparatives), AR FY26 Note 45 (FY25 & FY26). FY21 from AR FY22 comparatives. All converted from Rs. lakh. Segment definitions: (i) Oil & Gas = services to oil & gas customers (seismic, O&M, drilling services, E&P-related, Kuiper international O&M from FY26); (ii) Mineral & other energy = coal handling plants and other energy EPC/O&M (CIL subsidiaries, SCCL, power).
A37: FY27E-FY30E columns are for Stage 3 (forecast by order book x execution), not filled in Stage 1.

Sheet Valuations
B2: CMP | C2: 455 | D2: BSE close 16-Oct-2026 (ACE price sheet). Replace with Bloomberg CMP and date at Stage 3.
B3: No of Shares (crore) | C3: ='P&L'!W36 -> 4.49175 | D3: FY26 year-end; +0.37cr shares issued on warrant conversion in May-2026 not yet included.
B4: Market Cap (Rs. crore) | C4: =C2*C3 -> 2043.7462
B6: Asian Energy Services - Valuation Matrix
D7: FY26 | E7: FY27E | F7: FY28E | G7: FY29E | H7: FY30E
B8: EV/EBITDA methodology
B9: Consolidated EBITDA | C9: Rs. crore | D9: ='P&L'!W19 -> 95.3559 | E9: ='P&L'!X19 -> 0 | F9: ='P&L'!Y19 -> 0 | G9: ='P&L'!Z19 -> 0 | H9: ='P&L'!AA19 -> 0
B10: Net Debt: -ve implies Net Cash | D10: ='P&L'!W200 -> 11.2727 | E10: ='P&L'!X200 -> 0 | F10: ='P&L'!Y200 -> 0 | G10: ='P&L'!Z200 -> 0 | H10: ='P&L'!AA200 -> 0
B11: =CONCATENATE("-@CMP of Rs.",ROUND($C$2,0),"/share") -> -@CMP of Rs.455/share | C11: implied EV/EBITDA | D11: =IF(D9<=0,"",($C$4+D10)/D9) -> 21.551041 | E11: =IF(E9<=0,"",($C$4+E10)/E9) | F11: =IF(F9<=0,"",($C$4+F10)/F9) | G11: =IF(G9<=0,"",($C$4+G10)/G9) | H11: =IF(H9<=0,"",($C$4+H10)/H9)
A12: 8 | B12: =CONCATENATE("-Target Price @",ROUND(A12,0),"x EV/EBITDA") -> -Target Price @8x EV/EBITDA | C12: Rs./ share | E12: =IF(E$9<=0,"",((E$9*$A12)-(E$10))/$C$3) | F12: =IF(F$9<=0,"",((F$9*$A12)-(F$10))/$C$3) | G12: =IF(G$9<=0,"",((G$9*$A12)-(G$10))/$C$3) | H12: =IF(H$9<=0,"",((H$9*$A12)-(H$10))/$C$3)
A13: 10 | B13: =CONCATENATE("-Target Price @",ROUND(A13,0),"x EV/EBITDA") -> -Target Price @10x EV/EBITDA | C13: Rs./ share | E13: =IF(E$9<=0,"",((E$9*$A13)-(E$10))/$C$3) | F13: =IF(F$9<=0,"",((F$9*$A13)-(F$10))/$C$3) | G13: =IF(G$9<=0,"",((G$9*$A13)-(G$10))/$C$3) | H13: =IF(H$9<=0,"",((H$9*$A13)-(H$10))/$C$3)
A14: 12 | B14: =CONCATENATE("-Target Price @",ROUND(A14,0),"x EV/EBITDA") -> -Target Price @12x EV/EBITDA | C14: Rs./ share | E14: =IF(E$9<=0,"",((E$9*$A14)-(E$10))/$C$3) | F14: =IF(F$9<=0,"",((F$9*$A14)-(F$10))/$C$3) | G14: =IF(G$9<=0,"",((G$9*$A14)-(G$10))/$C$3) | H14: =IF(H$9<=0,"",((H$9*$A14)-(H$10))/$C$3)
B15: Upside / (downside) at 12x | E15: =IF(E14="","",E14/$C$2-1) | F15: =IF(F14="","",F14/$C$2-1) | G15: =IF(G14="","",G14/$C$2-1) | H15: =IF(H14="","",H14/$C$2-1)
B17: Trailing context (FY26A, at CMP)
B18: P/E on FY26 EPS | C18: =$C$2/'P&L'!W37 -> 39.950393
B19: P/B on FY26 book value | C19: =$C$4/'P&L'!W46 -> 4.1358572
B20: EV/Sales on FY26 | C20: =($C$4+D10)/'P&L'!W3 -> 2.5978455
B22: Stage 3 will add: peer table, EV-to-equity bridge (net debt at FY26 year-end, minorities, probable contingent liabilities), bull/base/bear with different operating assumptions, reverse check of CMP. Multiples in column A are placeholders, not a view.

Sheet Notes
A1: BASIS
A2: Entity / basis | B2: Asian Energy Services Ltd (NSE: ASIANENE, BSE: 530355). Consolidated basis for FY09-FY26 from the ACE Equity consolidated dump (received 18-Oct-2026). FY05-FY08 are STANDALONE ACE data (consolidated series not available) and are shaded orange; they are not comparable with FY09+.
A3: Why consolidated | B3: Standalone is misleading for this company: FY26 consolidated revenue Rs.791cr vs standalone Rs.492cr (Kuiper, DMCC and other subsidiaries); FY15 consolidated Rs.141cr vs standalone Rs.1.4cr (Kurdistan contracts sat in the DMCC subsidiary). See reconciliation below.
A4: Units / style | B4: Rs. crore. Blue = hardcoded from source; black = formula; orange fill = standalone-basis column. Cell comments on row labels explain mapping choices.
A6: DISCONTINUITIES (never spliced over)
A7: FY08 / FY09 / FY10 periods | B7: Financial-year change: FY08 is a 15-month period to 30-Jun-2008 (standalone); FY09 is 12 months to 30-Jun-2009; FY10 is 9 months to 31-Mar-2010 (ACE "No of months" row). Growth rates across FY07-FY11 are therefore not like-for-like.
A8: FY16 -> FY17 GAAP change | B8: Indian GAAP up to FY16; Ind AS from FY17 (FY17 AR presents FY16 restated under Ind AS). ACE carries the originally reported basis for each year.
A9: FY17 promoter change | B9: Oilmax Energy Pvt Ltd (Kapil Garg) acquired control in FY17 via preferential issue (Rs.88.6cr equity raised in FY17, Rs.48cr in FY18). Business re-based from this point; large ESOP charges in FY17-FY18 and FY21 (Rs.43cr, Rs.29cr, Rs.30cr per AR cash-flow notes) depress reported PAT in those years.
A10: FY23 reclassification | B10: FY24 AR restated FY23 expense lines: employee benefits Rs.28.68cr (own-year AR Rs.28.59cr) and other expenses Rs.18.82cr (Rs.18.91cr). Totals unchanged. ACE carries the FY23 AR version.
A11: FY19 cash-flow restatement | B11: FY19 AR: operating cash flow Rs.34.8cr, closing cash Rs.2.97cr. FY20 AR comparatives: Rs.26.9cr and Rs.0.97cr (bank overdraft netted / reclassification). ACE uses the FY19 AR figures.
A12: FY21 cash-flow restatement | B12: FY21 AR: operating cash flow Rs.-17.5cr, closing cash Rs.12.1cr. FY22 AR comparatives: Rs.-6.8cr and Rs.22.7cr. Check which version ACE carries before relying on FY21 cash conversion.
A13: FY26 Kuiper consolidation | B13: Kuiper Holdings / Kuiper Group (international O&M, acquired Apr-2025 for Rs.122.8cr net cash paid; Rs.72.1cr cash acquired) consolidated from acquisition date. Adds Rs.299cr of revenue outside India in FY26 (AR FY26 Note 45 III). FY26 vs FY25 growth is therefore mostly inorganic.
A14: Post-FY26 share count | B14: May-2026: 36.6 lakh shares issued on warrant conversion (Rs.92cr). Diluted count for valuation = 4.49cr + 0.37cr = 4.86cr. Not yet in the model.
A15: Oilmax merger (pending) | B15: Scheme of merger by absorption of Oilmax Energy Pvt Ltd (promoter entity, E&P assets) into AESL: NCLT final order 29-Sep-2026, certified copy received 15-Oct-2026. Will change share count, segment mix (adds E&P) and related-party profile from FY27. Not in historicals.
A17: STANDALONE vs CONSOLIDATED (Rs. crore)
A18: Year | B18: Standalone revenue | C18: Consolidated revenue | D18: Standalone PAT | E18: Consolidated PAT | F18: Standalone net worth | G18: Consolidated net worth
A19: FY26 | B19: 491.8 | C19: 791 | D19: 44.8 | E19: 51.8 | F19: 447.6 | G19: 494.2
A20: FY25 | B20: 464.1 | C20: 465 | D20: 41 | E20: 42.2 | F20: 396.7 | G20: 398.7
A21: FY24 | B21: 305.1 | C21: 305.1 | D21: 28.7 | E21: 25.5 | F21: 276.5 | G21: 277.9
A22: FY23 | B22: 109.9 | C22: 110 | D22: -29.3 | E22: -44.4 | F22: 193.6 | G22: 199.5
A23: FY22 | B23: 254.1 | C23: 260.5 | D23: 62.8 | E23: 38.8 | F23: 222 | G23: 241.8
A24: FY21 | B24: 140.7 | C24: 228.8 | D24: 21.6 | E24: 22.6 | F24: 160.8 | G24: 203.4
A25: FY20 | B25: 64.5 | C25: 273.2 | D25: 4.7 | E25: 29.2 | F25: 138.9 | G25: 181.5
A26: FY19 | B26: 156.8 | C26: 193.9 | D26: 1.6 | E26: 9.1 | F26: 136.8 | G26: 152
A27: FY18 | B27: 95.7 | C27: 222.2 | D27: -20.7 | E27: 10.3 | F27: 134.5 | G27: 140.5
A28: FY17 | B28: 43.4 | C28: 124.3 | D28: 0.8 | E28: -18.2 | F28: 106.8 | G28: 81.8
A29: FY16 | B29: 9.4 | C29: 77.7 | D29: -29.4 | E29: -27.1 | F29: 17.4 | G29: 10.1
A30: FY15 | B30: 1.4 | C30: 140.8 | D30: -16.8 | E30: -27 | F30: 46.8 | G30: 37.2
... A36: FY09 | B36: 68.8 | C36: 68.8 | D36: 5.3 | E36: 5.3 | F36: 75.1 | G36: 77.9
A39: SOURCES
A40: ACE consolidated dump | B40: Sheets: P&L (schedules), Balance Sheet (schedules), Cash Flow, Ratios, Valuation ratios. FY09-FY26. Tag [S] secondary, verified against [A] audited ARs for FY16-FY26 on revenue, PBT, PAT, total assets, OCF, closing cash (all tie).
A41: ACE standalone dump | B41: Used only for FY05-FY08 columns and the reconciliation table above. Also source of DPS and the share-price row (BSE daily closes to 16-Oct-2026).
A42: Annual reports | B42: AR FY16-FY26 (company website) for segment note (Ind AS 108), restatement checks, acquisition and ESOP details. AR FY15 text is font-garbled in the PDF and was not used.
A43: Document repository | B43: Full filing set (annual reports, results, decks, transcripts, orders, merger documents) in the two zips delivered 18-Oct-2026; see their README for coverage.
A45: LAYOUT CHANGES vs SAMPLE
A46: Rows added | B46: P&L: Share of Profit/(Loss) of JVs; Less: Minority Interest; PAT attributable to owners. Cash flow: Acquisition of Subsidiaries; Cash acquired on acquisition / FX. Working capital: Debtor + Unbilled Days. Key ratios: current-maturities memo, ROCE ex-cash, asset and gross-block turns, capex/depreciation. All other rows, formulas and formats follow the sample.
A47: Raw material row | B47: ACE reports no raw-material cost for a services company, so Variable Cost = stock change only and Gross Margin is near 100%. The economically meaningful variable cost is Other Manufacturing Expenses (project-related costs). Read EBITDA margin, not gross margin.
